Workbook
Name \\\\: #REF!
Name \\\\: #REF!
Name \\\\: #REF!
Name \0: #REF!
Name \0: #REF!
Name \0: #REF!
Name \0: #REF!
Name \0: #REF!
Name \a: #REF!
Name \a: #REF!
Name \a: #REF!
Name \a: #REF!
Name \a: #REF!
Name \b: #REF!
Name \b: #REF!
Name \b: #REF!
Name \b: #REF!
Name \b: #REF!
Name \bbb: #REF!
Name \bbb: #REF!
Name \bbb: #REF!
Name \bbb: #REF!
Name \bbb: #REF!
Name \C: #REF!
Name \C: #REF!
Name \C: #REF!
Name \C: #REF!
Name \C: #REF!
Name \C: #REF!
Name \d: #REF!
Name \d: #REF!
Name \d: #REF!
Name \d: #REF!
Name \d: #REF!
Name \e: #REF!
Name \e: #REF!
Name \e: #REF!
Name \f: #N/A
Name \G: #REF!
Name \G: #REF!
Name \G: #REF!
Name \i: #REF!
Name \i: #REF!
Name \i: #REF!
Name \i: #REF!
Name \i: #REF!
Name \J: #REF!
Name \J: #REF!
Name \J: #REF!
Name \K: #REF!
Name \K: #REF!
Name \K: #REF!
Name \l: #REF!
Name \l: #REF!
Name \l: #REF!
Name \m: #REF!
Name \m: #REF!
Name \m: #REF!
Name \m: #REF!
Name \m: #REF!

Sheet FY22-25 IFRS（合并）
B2: CONSOLIDATED STATEMENTS OF PROFIT OR LOSS AND OTHER COMPREHENSIVE INCOME(RMB '000) | E2: IFRS-2021审定数 | G2: IFRS-2022审定数 | I2: IFRS-2023审定数 | K2: IFRS-2024审定数 | M2: IFRS-20240630审定数 | O2: IFRS-250630审定数 | Q2: IFRS-251231
B3: Continuing operations
A4: 营业收入 | B4: Revenue | E4: -79100967 | G4: -2.2281308e+08 | I4: -5.3080586e+08 | K4: -6.5543777e+08 | M4: -2.9311173e+08 | O4: -3.2580849e+08 | Q4: -7.8881792e+08
A5: 营业成本 | B5: Cost of sales | E5: 57146960 | G5: 1.3701032e+08 | I5: 2.8764505e+08 | K5: 4.3035922e+08 | M5: 1.9238482e+08 | O5: 2.2289836e+08 | Q5: 5.1674726e+08
B6: Gross profit | E6: =E4+E5 -> -21954007 | G6: =G4+G5 -> -85802758 | I6: =I4+I5 -> -2.4316081e+08 | K6: =K4+K5 -> -2.2507854e+08 | M6: =M4+M5 -> -1.0072691e+08 | O6: =O4+O5 -> -1.0291013e+08 | Q6: =Q4+Q5 -> -2.7207066e+08
A7: 其他收益 | B7: Other income | E7: -54187.55 | G7: -17971825 | I7: -15975719 | K7: -10846056 | M7: -7396419.4 | O7: -1171485.1 | Q7: -2554126.1
A8: 其他净(损失)/收益 | B8: Other net (loss)/gain | E8: -12669457 | G8: 124678.46 | I8: -37881.56 | K8: 678379.24 | M8: 659901.6 | O8: -167407.18 | Q8: -716563.08
A9: 销售费用 | B9: Selling and marketing expenses | E9: 29718059 | G9: 38110116 | I9: 1.0986149e+08 | K9: 84743936 | M9: 38445226 | O9: 22879865 | Q9: 55235424
A10: 管理费用 | B10: Administrative expenses | E10: 58667135 | G10: 47511905 | I10: 48367874 | K10: 39037309 | M10: 21478502 | O10: 17205791 | Q10: 55632191
A11: 研发费用 | B11: Research and development expenses | E11: 54066977 | G11: 75433068 | I11: 1.295689e+08 | K11: 1.5012925e+08 | M11: 82098448 | O11: 66538960 | Q11: 1.6334213e+08
A12: 信用减值损失 | B12: Impairment loss on financial assets | E12: 1446834.2 | G12: 3552828.8 | I12: 11750182 | K12: 21169519 | M12: 10345025 | O12: 6114900 | Q12: 27595443
B13: Loss from operations | E13: =SUM(E6:E12) -> 1.0922135e+08 | G13: =SUM(G6:G12) -> 60958013 | I13: =SUM(I6:I12) -> 40374033 | K13: =SUM(K6:K12) -> 59833791 | M13: =SUM(M6:M12) -> 44903776 | O13: =SUM(O6:O12) -> 8490494.6 | Q13: =SUM(Q6:Q12) -> 26463835
A14: 财务收入 | B14: Finance income | E14: -14076544 | G14: -9458184.8 | I14: -4606419.3 | K14: -2239349.8 | M14: -623760.44 | O14: -464884.35 | Q14: -856870.83
A15: 财务成本 | B15: Finance costs | E15: 0 | G15: 759096.24 | I15: 435137.11 | K15: 239820.09 | M15: 158049.15 | O15: 99442.49 | Q15: 143669.04
A16: 投资收益 | B16: Share of profits less losses of an associate | E16: 0 | G16: 0 | I16: 1104040.8 | K16: 26695.484 | M16: 0 | O16: 164418.73 | Q16: 164418.73
A17: 向投资者发行金融工具的公允价值变动 | B17: Changes in the carrying amount of redeemable preferred shares | E17: 58659747 | G17: 58659747 | I17: 58659747 | K17: 53838398 | M17: 29329873 | O17: 0 | Q17: 0
A18: 公允价值变动损益 | B18: Fair Value Through Other Comprehensive Income | E18: 0 | G18: 0 | I18: 0 | K18: 0 | M18: 0 | O18: 0 | Q18: 0
B19: Loss before taxation from continuing operations | E19: =SUM(E13:E17) -> 1.5380456e+08 | G19: =SUM(G13:G17) -> 1.1091867e+08 | I19: =SUM(I13:I17) -> 95966539 | K19: =SUM(K13:K17) -> 1.1169935e+08 | M19: =SUM(M13:M17) -> 73767938 | O19: =SUM(O13:O17) -> 8289471.4 | Q19: =SUM(Q13:Q17) -> 25915052
A20: 所得税费用 | B20: Income tax | E20: 0 | G20: 134240.41 | I20: -59685.84 | K20: 0 | M20: 0 | O20: 0 | Q20: 0
B21: Profit/(loss) for the year from continuing operations | E21: =SUM(E19:E20) -> 1.5380456e+08 | G21: =SUM(G19:G20) -> 1.1105291e+08 | I21: =SUM(I19:I20) -> 95906853 | K21: =SUM(K19:K20) -> 1.1169935e+08 | M21: =SUM(M19:M20) -> 73767938 | O21: =SUM(O19:O20) -> 8289471.4 | Q21: =SUM(Q19:Q20) -> 25915052
B23: Other comprehensive income for the year/period (after tax)
B24: Exchange differences on translation of financial statements of overseas subsidiaries | Q24: 474532.31
B26: Other comprehensive income for the year/period | E26: =E24 -> 0 | G26: =G24 -> 0 | I26: =I24 -> 0 | K26: =K24 -> 0 | M26: =M24 -> 0 | O26: =O24 -> 0 | Q26: =Q24 -> 474532.31
B28: Total comprehensive income for the year/period attributable to equity shareholders of the Company | E28: =E26+E21 -> 1.5380456e+08 | G28: =G26+G21 -> 1.1105291e+08 | I28: =I26+I21 -> 95906853 | K28: =K26+K21 -> 1.1169935e+08 | M28: =M26+M21 -> 73767938 | O28: =O26+O21 -> 8289471.4 | Q28: =Q26+Q21 -> 26389585
B30: Check
B32: CONSOLIDATED STATEMENTS OF FINANCIAL POSITION(RMB '000) | E32: IFRS-2021审定数 | G32: IFRS-2022审定数 | I32: IFRS-2023审定数 | K32: IFRS-2024审定数 | M32: IFRS-20240630审定数 | O32: IFRS-250630审定数 | Q32: IFRS-251231
B33: Expressed in RMB
B34: Non-current assets
A35: 物业、厂房及设备 | B35: Property, plant and equipment | E35: 13062838 | G35: 13977867 | I35: 13965362 | K35: 9842079.2 | M35: 12862054 | O35: 7201488 | Q35: 4746012.2
A36: 使用权资产 | B36: Right-of-use assets | E36: 18557943 | G36: 13111789 | I36: 6703851.9 | K36: 3465689.7 | M36: 6123908.5 | O36: 6342883.4 | Q36: 4886520.2
A37: 无形资产 | B37: Intangible assets | E37: 2013506.7 | G37: 1266086.5 | I37: 713394.6 | K37: 493005.35 | M37: 544443.18 | O37: 455394.83 | Q37: 417784.31
B38: Contract assets - LT | E38: 0 | G38: 428119.63 | I38: 1358136.9 | K38: 7137320.7 | M38: 2243838.9 | O38: 5588050.3 | Q38: 5463100.5
A39: 长期股权投资 | B39: Interests in an associates | E39: 2000000 | G39: 0 | I39: 0 | K39: 173304.52 | M39: 0 | O39: 198885.79 | Q39: 0
B40: Interests in subsidiaries
A41: 预付款项、按金及其他应收款项 - 长期 | B41: Prepayments, deposits and other receivables - LT | E41: 0 | G41: 0 | I41: 0 | K41: 0 | M41: 0 | O41: 0 | Q41: 0
A42: 长期应收款 | B42: Long-term receivables | E42: 0 | G42: 0 | I42: 0 | K42: 0 | M42: 0 | O42: 0 | Q42: 0
E43: =SUM(E35:E42) -> 35634288 | G43: =SUM(G35:G42) -> 28783861 | I43: =SUM(I35:I42) -> 22740745 | K43: =SUM(K35:K42) -> 21111399 | M43: =SUM(M35:M42) -> 21774245 | O43: =SUM(O35:O42) -> 19786702 | Q43: =SUM(Q35:Q42) -> 15513417
B44: Current assets
A45: 存货 | B45: Inventories | E45: 1483376.3 | G45: 297941.71 | I45: 14994415 | K45: 42367810 | M45: 694616.1 | O45: 70024651 | Q45: 79207862
A46: 应收账款 | B46: Trade receivables | E46: 28679317 | G46: 57107464 | I46: 1.4671723e+08 | K46: 2.3247504e+08 | M46: 2.613989e+08 | O46: 2.1485723e+08 | Q46: 2.8163701e+08
A47: 合同资产 | B47: Contract Assets - ST | E47: 0 | G47: 59015 | I47: 4016920.9 | K47: 674389.34 | M47: 0 | O47: 1598106.6 | Q47: 14792115
A48: 预付款项、按金及其他应收款项 - 短期 | B48: Prepayments, deposits and other receivables - ST | E48: 8033233.7 | G48: 59590690 | I48: 72327296 | K48: 40825050 | M48: 65444743 | O48: 34346833 | Q48: 81874373
A49: 以公允价值计量计入当期损益的金融资产 | B49: Financial assets measured at fair value through profit or loss | E49: 0 | G49: 0 | I49: 0 | K49: 0 | M49: 0 | O49: 0 | Q49: 0
B50: Financial assets measured at amortised cost | E50: 220000000 | G50: 110000000 | I50: 0 | K50: 0 | M50: 0 | O50: 0
A51: 货币资金 | B51: Cash and cash equivalents | E51: 2.0413428e+08 | G51: 2.0704444e+08 | I51: 2.5610653e+08 | K51: 1.7024983e+08 | M51: 1.8180223e+08 | O51: 3.048862e+08 | Q51: 2.1775561e+08
E52: =SUM(E45:E51) -> 4.6233021e+08 | G52: =SUM(G45:G51) -> 4.3409955e+08 | I52: =SUM(I45:I51) -> 4.9416239e+08 | K52: =SUM(K45:K51) -> 4.8659212e+08 | M52: =SUM(M45:M51) -> 5.0934049e+08 | O52: =SUM(O45:O51) -> 6.2571302e+08 | Q52: =SUM(Q45:Q51) -> 6.7526697e+08
B53: Current liabilities
A54: 应付账款 | B54: Trade payables | E54: -20631401 | G54: -37424701 | I54: -96413489 | K54: -1.1568943e+08 | M54: -1.601127e+08 | O54: -87110722 | Q54: -1.0251899e+08
A55: 其他应付款 | B55: Other payables and accruals | E55: -24578851 | G55: -22449693 | I55: -15568154 | K55: -23527523 | M55: -9992948.8 | O55: -33618810 | Q55: -16340657
A56: 合同负债 | B56: Contract liabilities | E56: -6339661.7 | G56: -6804807.3 | I56: -46497256 | K56: -50236540 | M56: -37654742 | O56: -20030907 | Q56: -75574267
A57: 租赁负债 - 短期 | B57: Lease liabilities - ST | E57: -6463610.5 | G57: -8249420.5 | I57: -5802185.5 | K57: -1220214.6 | M57: -3084536.6 | O57: -3021398.5 | Q57: -3107443.1
A58: 向投资者发行的金融负债 - 短期 | B58: Redeemable preferred shares - ST | E58: -7.9567896e+08 | G58: -8.5433871e+08 | I58: -9.1299846e+08 | K58: 0 | M58: -9.4232833e+08 | O58: 0 | Q58: 0
B59: Current taxation | E59: 0 | G59: 0 | I59: 0 | K59: 0 | M59: 0 | O59: 0 | Q59: 0
A60: 递延收益 - 流动 | B60: Deferred income - current | E60: 0 | G60: 0 | I60: 0 | K60: 0 | M60: 0 | O60: 0 | Q60: 0
E61: =SUM(E54:E60) -> -8.5369249e+08 | G61: =SUM(G54:G60) -> -9.2926733e+08 | I61: =SUM(I54:I60) -> -1.0772795e+09 | K61: =SUM(K54:K60) -> -1.9067371e+08 | M61: =SUM(M54:M60) -> -1.1531733e+09 | O61: =SUM(O54:O60) -> -1.4378184e+08 | Q61: =SUM(Q54:Q60) -> -1.9754136e+08
B63: Net current assets | E63: =E52+E61 -> -3.9136228e+08 | G63: =G52+G61 -> -4.9516779e+08 | I63: =I52+I61 -> -5.8311715e+08 | K63: =K52+K61 -> 2.9591841e+08 | M63: =M52+M61 -> -6.4383277e+08 | O63: =O52+O61 -> 4.8193118e+08 | Q63: =Q52+Q61 -> 4.7772562e+08
B64: Total assets less current liabilities | E64: -3.5572799e+08 | G64: -4.6638392e+08 | I64: -5.603764e+08 | K64: 3.1702981e+08 | M64: -6.2205853e+08 | O64: 5.0171788e+08 | Q64: 4.9338918e+08
B66: Non-current liabilities
A67: 租赁负债 - 长期 | B67: Lease liabilities - LT | E67: -12177717 | G67: -5173898.9 | I67: -306350.54 | K67: -1271463.6 | M67: -1845033.2 | O67: -3058547.8 | Q67: -1961255.2
A68: 长期应付款 | B68: Long-term payables | E68: -7.4505806e-09 | G68: -1.8626451e-09 | I68: -3.632158e-08 | K68: -1.4901161e-08 | M68: 0 | O68: 0 | Q68: 0
A69: 递延收益 | B69: Deferred income | E69: 0 | G69: -1228572.8 | I69: -175510.4 | K69: 0 | M69: 0 | O69: 0 | Q69: 0
A70: 递延所得税负债 | B70: Deferred tax liabilities | E70: 0 | G70: 0 | I70: 0 | K70: 0 | M70: 0 | O70: 0
A71: 向投资者发行的金融负债 - 长期 | B71: Redeemable preferred shares - LT | E71: 0 | G71: 0 | I71: 0 | K71: 0 | M71: 0 | O71: 0
B72: NET LIABILITIES | E72: =E64-E67-E68-E69-E71 -> -3.4355028e+08 | G72: =G64-G67-G68-G69-G71 -> -4.5998145e+08 | I72: =I64-I67-I68-I69-I71 -> -5.5989454e+08 | K72: =K64-K67-K68-K69-K71 -> 3.1830127e+08 | M72: =M64-M67-M68-M69-M71 -> -6.2021349e+08 | O72: =O64-O67-O68-O69-O71 -> 5.0477643e+08 | Q72: =Q64-Q67-Q68-Q69-Q71 -> 4.9535044e+08
B74: CAPITAL AND RESERVES
A75: 实收资本 | B75: Share capital | E75: -15787627 | G75: -15787627 | I75: -15787627 | K75: -15787627 | M75: -15787627 | O75: -17084745 | Q75: -17084745
A76: 未分配利润 | B76: Reserves | E76: 3.8369334e+08 | G76: 4.8857402e+08 | I76: 5.7664589e+08 | K76: -2.9997072e+08 | M76: 6.3969119e+08 | O76: -4.8157459e+08 | Q76: -4.7419303e+08
B78: TOTAL DEFICIT ATTRIBUTABLE TO EQUITY SHAREHOLDERS OF THE COMPANY | E78: =SUM(E75:E77) -> 3.6790571e+08 | G78: =SUM(G75:G77) -> 4.727864e+08 | I78: =SUM(I75:I77) -> 5.6085826e+08 | K78: =SUM(K75:K77) -> -3.1575834e+08 | M78: =SUM(M75:M77) -> 6.2390356e+08 | O78: =SUM(O75:O77) -> -4.9865934e+08 | Q78: =SUM(Q75:Q77) -> -4.9127778e+08
B80: BS check | E80: =ROUND(E43+E52+E61+SUM(E67:E71)+E78,2) -> 0 | G80: =ROUND(G43+G52+G61+SUM(G67:G71)+G78,2) -> 0 | I80: =ROUND(I43+I52+I61+SUM(I67:I71)+I78,2) -> 0 | K80: =ROUND(K43+K52+K61+SUM(K67:K71)+K78,2) -> 0 | M80: =ROUND(M43+M52+M61+SUM(M67:M71)+M78,2) -> 0 | O80: =ROUND(O43+O52+O61+SUM(O67:O71)+O78,2) -> 0 | Q80: =ROUND(Q43+Q52+Q61+SUM(Q67:Q71)+Q78,2) -> 0
B81: RE Check | E81: 0 | G81: 0 | I81: 0 | K81: 0 | M81: 0 | O81: 0 | Q81: 0

Sheet PL>>

Sheet 收入拆分
B1: Revenue | C1: 营业收入 | D1: 2022 | E1: 2023 | F1: 2024 | G1: 2025
B2: GJ digital human intelligent platform | C2: 硅基数字人智能交互（ICT+数字人智能产品） | D2: =(-收入成本拆分!D6-收入成本拆分!D7)/1000 -> 139864.03 | E2: =(-收入成本拆分!F6-收入成本拆分!F7)/1000 -> 460050.82 | F2: =(-收入成本拆分!H6-收入成本拆分!H7)/1000 -> 612656 | G2: =(-收入成本拆分!J6-收入成本拆分!J7)/1000 -> 722872.01
B3: GJ intelligent voice | C3: 硅基智能语音 | D3: =-收入成本拆分!D8/1000 -> 68752.075 | E3: =-收入成本拆分!F8/1000 -> 25312.277 | F3: =-收入成本拆分!H8/1000 -> 16788.507 | G3: =-收入成本拆分!J8/1000 -> 3974.9551
B4: GJ video production, livestreaming | C4: 硅基数字人视频、直播 | D4: =-收入成本拆分!D9/1000 -> 14196.979 | E4: =-收入成本拆分!F9/1000 -> 45442.759 | F4: =-收入成本拆分!H9/1000 -> 25993.256 | G4: =-收入成本拆分!J9/1000 -> 10583.474
B5: GJ Autopilot AIGC Agents | C5: 硅基全自动内容生产 | D5: 0 | E5: 0 | F5: 0 | G5: =-收入成本拆分!J10/1000 -> 51387.72
B6: Total revenue | C6: 收入合计 | D6: =D3+D4+D2+D5 -> 222813.08 | E6: =E3+E4+E2+E5 -> 530805.86 | F6: =F3+F4+F2+F5 -> 655437.77 | G6: =G3+G4+G2+G5 -> 788818.16
B8: Cost | C8: 营业成本 | D8: 2022 | E8: 2023 | F8: 2024 | G8: 2025
B9: GJ digital human intelligent platform | C9: 硅基数字人智能交互（ICT+数字人智能产品） | D9: =(收入成本拆分!D17+收入成本拆分!D18+收入成本拆分!D33)/1000 -> 83068.019 | E9: =(收入成本拆分!F17+收入成本拆分!F18+收入成本拆分!F33)/1000 -> 261270.72 | F9: =(收入成本拆分!H17+收入成本拆分!H18+收入成本拆分!H33)/1000 -> 411907.13 | G9: =(收入成本拆分!J17+收入成本拆分!J18+收入成本拆分!J33)/1000 -> 482503.68
B10: GJ intelligent voice | C10: 硅基智能语音 | D10: =收入成本拆分!D19/1000 -> 46230.954 | E10: =收入成本拆分!F19/1000 -> 17584.907 | F10: =收入成本拆分!H19/1000 -> 9888.2588 | G10: =收入成本拆分!J19/1000 -> 2951.9147
B11: GJ video production, livestreaming | C11: 硅基数字人视频、直播 | D11: =收入成本拆分!D20/1000 -> 7981.1702 | E11: =收入成本拆分!F20/1000 -> 8789.4208 | F11: =收入成本拆分!H20/1000 -> 8563.8367 | G11: =收入成本拆分!J20/1000 -> 8139.8702
B12: GJ Autopilot AIGC Agents | C12: 硅基全自动内容生产 | D12: 0 | E12: 0 | F12: 0 | G12: =收入成本拆分!J21/1000 -> 23151.796
B13: Total cost | C13: 成本合计 | D13: =SUM(D9:D12) -> 137280.14 | E13: =SUM(E9:E12) -> 287645.05 | F13: =SUM(F9:F12) -> 430359.22 | G13: =SUM(G9:G12) -> 516747.26
B15: Gross Margin | C15: 毛利率 | D15: 2022 | E15: 2023 | F15: 2024 | G15: 2025
B16: GJ digital human intelligent platform | C16: 硅基数字人智能交互（ICT+数字人智能产品） | D16: =(D2-D9)/D2 -> 0.40608017 | E16: =(E2-E9)/E2 -> 0.43208291 | F16: =(F2-F9)/F2 -> 0.32766981 | G16: =(G2-G9)/G2 -> 0.33251851
B17: GJ intelligent voice | C17: 硅基智能语音 | D17: =(D3-D10)/D3 -> 0.32757005 | E17: =(E3-E10)/E3 -> 0.3052815 | F17: =(F3-F10)/F3 -> 0.41101023 | G17: =(G3-G10)/G3 -> 0.25737157
B18: GJ video production, livestreaming | C18: 硅基数字人视频、直播 | D18: =(D4-D11)/D4 -> 0.43782616 | E18: =(E4-E11)/E4 -> 0.80658259 | F18: =(F4-F11)/F4 -> 0.67053621 | G18: =(G4-G11)/G4 -> 0.23088864
B19: GJ Autopilot AIGC Agents | C19: 硅基全自动内容生产 | G19: =(G5-G12)/G5 -> 0.54946831
B20: Gross margin% | C20: 毛利率 | D20: =(D6-D13)/D6 -> 0.38387754 | E20: =(E6-E13)/E6 -> 0.45809744 | F20: =(F6-F13)/F6 -> 0.34340185 | G20: =(G6-G13)/G6 -> 0.34490952
E22: 287645 | F22: 430359 | G22: 516747
E23: =E22-E13 -> -0.051423308 | F23: =F22-F13 -> -0.22178934 | G23: =G22-G13 -> -0.2645

Sheet 收入成本拆分
B3: 营业收入 | D3: 22年度 | F3: 23年度 | H3: 24年度 | J3: 25年度
D4: a | F4: b | H4: c | J4: d
B5: Customised AI workforce solutions | D5: =SUM(D6:D8) -> -2.086161e+08 | F5: =SUM(F6:F8) -> -4.853631e+08 | H5: =SUM(H6:H8) -> -6.2944451e+08 | J5: =SUM(J6:J10) -> -7.8881816e+08
B6: ICT services | D6: -37081816 | F6: -1.947907e+08 | H6: -4.2215234e+08 | J6: -3.2335846e+08
B7: AIGC services | D7: -1.0278221e+08 | F7: -2.6526012e+08 | H7: -1.9050367e+08 | J7: -3.9951355e+08
B8: AI voice services | D8: -68752074 | F8: -25312277 | H8: -16788507 | J8: -3974955.1
B9: Standardised and productized AI workforce solutions | D9: -14196979 | F9: -45442759 | H9: -25993256 | J9: -10583474
B10: GJ Autopilot AIGC Agents | J10: -51387720
B11: 合计 | D11: =SUM(D6:D9) -> -2.2281308e+08 | F11: =SUM(F6:F9) -> -5.3080586e+08 | H11: =SUM(H6:H9) -> -6.5543777e+08 | J11: =SUM(J6:J10) -> -7.8881816e+08
D12: =ROUND(D11-'[1]FY22-25630 IFRS（合并）'!G4,0) -> 0 | F12: =ROUND(F11-'[1]FY22-25630 IFRS（合并）'!I4,0) -> 0 | H12: =ROUND(H11-'[1]FY22-25630 IFRS（合并）'!K4,0) -> 0 | J12: =ROUND(J11-'[1]FY22-25 IFRS（合并）'!$AB$4,0) -> 0
B14: 营业成本
B16: Customised AI workforce solutions | D16: =D17+D18+D19 -> 1.2896516e+08 | F16: =F17+F18+F19 -> 2.7851244e+08 | H16: =H17+H18+H19 -> 4.2108509e+08 | J16: =J17+J18+J19 -> 4.8517689e+08
B17: ICT services | D17: =[1]PL2!E9 -> 27239174 | F17: =[1]PL2!I9 -> 1.3326885e+08 | H17: =[1]PL2!M9 -> 3.0115375e+08 | J17: 2.3036163e+08
B18: AIGC services | D18: =[1]PL2!E15 -> 55495031 | F18: =[1]PL2!I15 -> 1.2765868e+08 | H18: =[1]PL2!M15 -> 1.1004309e+08 | J18: =251772193.51-837866.44+1207721.07-278709.95 -> 2.5186334e+08
B19: AI voice services | D19: =[1]PL2!E31+[1]PL2!E35 -> 46230954 | F19: =[1]PL2!I31+[1]PL2!I35 -> 17584907 | H19: =[1]PL2!M31+[1]PL2!M35 -> 9888258.8 | J19: 2951914.7
B20: Standardised and productized AI workforce solutions | D20: =[1]PL2!E23 -> 7981170.2 | F20: =[1]PL2!I23 -> 8789420.8 | H20: =[1]PL2!M23 -> 8563836.7 | J20: 8139870.2
B21: GJ Autopilot AIGC Agents | D21: 0 | F21: 0 | J21: 23151796
B22: 合计 | D22: =SUM(D17:D21) -> 1.3694633e+08 | F22: =SUM(F17:F21) -> 2.8730186e+08 | H22: =SUM(H17:H21) -> 4.2964893e+08 | J22: =SUM(J17:J21) -> 5.1646855e+08
B24: 毛利 | D24: =-(-D11-D22)/D11 -> 0.38537572 | F24: =-(-F11-F22)/F11 -> 0.45874399 | H24: =-(-H11-H22)/H11 -> 0.34448555 | J24: =-(-J11-J22)/J11 -> 0.34526285
B26: Customised AI workforce solutions | D26: =-(-D5-D16)/D5 -> 0.38180631 | F26: =-(-F5-F16)/F5 -> 0.42617714 | H26: =-(-H5-H16)/H5 -> 0.3310211 | J26: =-(-J5-J16)/J5 -> 0.3849319
B27: ICT services | D27: =-(-D6-D17)/D6 -> 0.26543043 | F27: =-(-F6-F17)/F6 -> 0.31583568 | H27: =-(-H6-H17)/H6 -> 0.28662305 | J27: =-(-J6-J17)/J6 -> 0.28759669
B28: AIGC services | D28: =-(-D7-D18)/D7 -> 0.46007164 | F28: =-(-F7-F18)/F7 -> 0.51874151 | H28: =-(-H7-H18)/H7 -> 0.42235711 | J28: =-(-J7-J18)/J7 -> 0.36957498
B29: AI voice services | D29: =-(-D8-D19)/D8 -> 0.32757005 | F29: =-(-F8-F19)/F8 -> 0.3052815 | H29: =-(-H8-H19)/H8 -> 0.41101023 | J29: =-(-J8-J19)/J8 -> 0.25737157
B30: Standardised and productized AI workforce solutions | D30: =-(-D9-D20)/D9 -> 0.43782616 | F30: =-(-F9-F20)/F9 -> 0.80658259 | H30: =-(-H9-H20)/H9 -> 0.67053621 | J30: =-(-J9-J20)/J9 -> 0.23088864
B31: GJ Autopilot AIGC Agents | D31: n/a | F31: n/a | H31: n/a | J31: =-(-J10-J21)/J10 -> 0.54946831
B33: 税金及附加 | D33: 333814.56 | F33: 343189.27 | H33: 710292.53 | J33: 278709.95
D34: SPT | F34: ='[1]FY22-25 IFRS（合并）'!$J$5 -> 2.8764505e+08 | H34: ='[1]FY22-25 IFRS（合并）'!$L$5 -> 4.3035922e+08 | J34: ='[1]FY22-25 IFRS（合并）'!$AB$5 -> 5.1674726e+08
F35: =F22+F33 -> 2.8764505e+08 | H35: =H22+H33 -> 4.3035922e+08 | J35: =J22+J33 -> 5.1674726e+08
F36: =F35/1000 -> 287645.05 | G36: =G35/1000 -> 0 | H36: =H35/1000 -> 430359.22 | I36: =I35/1000 -> 0 | J36: =J35/1000 -> 516747.26

Sheet PL1
B3: 营业收入 | D3: 22年度 | F3: 23年度 | H3: 24年度 | J3: 25年度 | L3: 2024年1-6月 | N3: 2025年1-6月
D4: a | F4: b | H4: c | J4: d | L4: d1 | N4: d2
B5: Customised AI workforce solutions | D5: =SUM(D6:D8) -> -2.086161e+08 | F5: =SUM(F6:F8) -> -4.853631e+08 | H5: =SUM(H6:H8) -> -6.2944451e+08 | J5: =SUM(J6:J10) -> -7.8881816e+08 | L5: =SUM(L6:L8) -> -2.8004144e+08 | N5: =SUM(N6:N8) -> -3.1884501e+08
B6: ICT services | D6: -37081816 | F6: -1.947907e+08 | H6: -4.2215234e+08 | J6: -3.2335846e+08 | L6: -2.0269747e+08 | N6: -2.0980538e+08
B7: AIGC services | D7: -1.0278221e+08 | F7: -2.6526012e+08 | H7: -1.9050367e+08 | J7: -3.9951355e+08 | L7: -68796248 | N7: -1.070887e+08
B8: AI voice services | D8: -68752074 | F8: -25312277 | H8: -16788507 | J8: -3974955.1 | L8: -8547718 | N8: -1950936.2
B9: Standardised and productized AI workforce solutions | D9: -14196979 | F9: -45442759 | H9: -25993256 | J9: -10583474 | L9: -13070291 | N9: -6963475.6
B10: 全自动内容生产 | J10: -51387720
B11: 合计 | D11: =SUM(D6:D9) -> -2.2281308e+08 | F11: =SUM(F6:F9) -> -5.3080586e+08 | H11: =SUM(H6:H9) -> -6.5543777e+08 | J11: =SUM(J6:J10) -> -7.8881816e+08 | L11: =SUM(L6:L9) -> -2.9311173e+08 | N11: =SUM(N6:N9) -> -3.2580849e+08
D12: =ROUND(D11-'FY22-25 IFRS（合并）'!G4,0) -> 0 | F12: =ROUND(F11-'FY22-25 IFRS（合并）'!I4,0) -> 0 | H12: =ROUND(H11-'FY22-25 IFRS（合并）'!K4,0) -> 0 | J12: =ROUND(J11-'FY22-25 IFRS（合并）'!Q4,0) -> -236 | L12: =ROUND(L11-'FY22-25 IFRS（合并）'!M4,0) -> 0 | N12: =ROUND(N11-'FY22-25 IFRS（合并）'!O4,0) -> 0
B15: 收入地区 | D15: 22年度 | F15: 23年度 | H15: 24年度 | J15: 25年度 | L15: 2024年1-6月 | N15: 2025年1-6月
B17: 境内 | D17: -2.2281308e+08 | F17: -5.3080586e+08 | H17: -6.5543777e+08 | J17: =J11 -> -7.8881816e+08 | L17: -2.9311173e+08 | N17: -3.2580849e+08
B18: 境外 | D18: 0 | F18: 0 | H18: 0 | J18: 0 | L18: 0 | N18: 0
B20: 合计 | D20: =SUM(D17:D18) -> -2.2281308e+08 | F20: =SUM(F17:F18) -> -5.3080586e+08 | H20: =SUM(H17:H18) -> -6.5543777e+08 | J20: =SUM(J17:J18) -> -7.8881816e+08 | L20: =SUM(L17:L18) -> -2.9311173e+08 | N20: =SUM(N17:N18) -> -3.2580849e+08
D21: =ROUND(D20-'FY22-25 IFRS（合并）'!G4,0) -> 0 | F21: =ROUND(F20-'FY22-25 IFRS（合并）'!I4,0) -> 0 | H21: =ROUND(H20-'FY22-25 IFRS（合并）'!K4,0) -> 0 | J21: =ROUND(J20-'[1]FY22-25 IFRS（合并）'!$AB$4,0) -> 0 | L21: =ROUND(L20-'FY22-25 IFRS（合并）'!M4,0) -> 0 | N21: =ROUND(N20-#REF!,0) -> #REF!
B24: 收入来源 | D24: 22年度 | F24: 23年度 | H24: 24年度 | J24: 25年度 | L24: 2024年1-6月 | N24: 2025年1-6月
B26: 独立第三方
B27: 控股股东及其联系人
B28: 其他关联方
B30: 合计 | D30: =SUM(D25:D28) -> 0 | F30: =SUM(F25:F28) -> 0 | H30: =SUM(H25:H28) -> 0 | J30: =SUM(J25:J28) -> 0 | L30: =SUM(L25:L28) -> 0 | N30: =SUM(N25:N28) -> 0
B33: 客户类型 | D33: 22年度 | F33: 23年度 | H33: 24年度 | J33: 25年度 | L33: 2024年1-6月 | N33: 2025年1-6月
B35: 国企
B36: 非国企
B38: 合计 | D38: =SUM(D34:D36) -> 0 | F38: =SUM(F34:F36) -> 0 | H38: =SUM(H34:H36) -> 0 | J38: =SUM(J34:J36) -> 0 | L38: =SUM(L34:L36) -> 0 | N38: =SUM(N34:N36) -> 0
B40: 收入地区 | D40: 22年度 | F40: 23年度 | H40: 24年度 | J40: 25年度 | L40: 2024年1-6月 | N40: 2025年1-6月
B42: 华东
B43: 华南
B44: xxx
B46: 合计 | D46: =SUM(D41:D43) -> 0 | F46: =SUM(F41:F43) -> 0 | H46: =SUM(H41:H43) -> 0 | J46: =SUM(J41:J43) -> 0 | L46: =SUM(L41:L43) -> 0 | N46: =SUM(N41:N43) -> 0

Sheet 附 收入by客商
D1: =SUM(D3:D2218)+'FY22-25 IFRS（合并）'!G4 -> 0.64094365 | E1: =SUM(E3:E2218)+'FY22-25 IFRS（合并）'!I4 -> 0.13584453 | F1: =SUM(F3:F2218)+'FY22-25 IFRS（合并）'!K4 -> -9.2952838 | G1: =SUM(G3:G2218)+'FY22-25 IFRS（合并）'!Q4 -> 235.85321
B2: 客户名称 | C2: 合并客户名称 | D2: 2022年 | E2: 2023年 | F2: 2024年 | G2: 2025年 | H2: 2025年H1
B3: 中移建设有限公司江苏分公司 | C3: 中国移动通信有限公司 | D3: 0 | E3: 18232458 | F3: 79186060 | G3: 72540462 | H3: 58710255
B4: 中移建设有限公司南京分公司 | C4: 中国移动通信有限公司 | D4: 0 | E4: 406784.14 | F4: 48031472 | G4: 37809940 | H4: 28842016
B5: 嘉环科技股份有限公司 | C5: 嘉环科技股份有限公司 | G5: 27322508 | H5: 27322508
B6: 中移建设有限公司无锡分公司 | C6: 中国移动通信有限公司 | D6: 1960377.4 | E6: 59068021 | F6: 32463211 | G6: 40190109 | H6: 27954531
B7: 广州和联通信科技有限公司 | C7: 广州和联通信科技有限公司 | G7: 16664604 | H7: 16664604
B8: 中移铁通有限公司连云港分公司 | C8: 中国移动通信有限公司 | D8: 0 | E8: 26635473 | F8: 36644440 | G8: 16522641 | H8: 16522642
B9: 富康尼科技（泰州）有限公司 | C9: 富康尼科技（泰州）有限公司 | F9: 5167482.8 | G9: 27011581 | H9: 15819077
B10: 江苏磬石软件科技有限公司 | C10: 江苏磬石软件科技有限公司 | F10: 23170359 | G10: 20471733 | H10: 13995775
B11: 中移铁通有限公司徐州分公司 | C11: 中国移动通信有限公司 | F11: 12724993 | G11: 13738295 | H11: 13738295
B12: 中移建设有限公司苏州分公司 | C12: 中国移动通信有限公司 | F12: 56415094 | G12: 38468396 | H12: 11311321
B13: 中移铁通有限公司盐城分公司 | C13: 中国移动通信有限公司 | D13: 22377659 | E13: 18458625 | F13: 3960472.3 | G13: 12613212 | H13: 10830708
B14: 中移建设有限公司南通分公司 | C14: 中国移动通信有限公司 | F14: 53326065 | G14: 14218185 | H14: 9521188.7
B15: 中国移动通信集团江苏有限公司徐州分公司 | C15: 中国移动通信有限公司 | F15: 9797169.8 | G15: 7948113.2 | H15: 7948113.2
B16: 中移建设有限公司徐州分公司 | C16: 中国移动通信有限公司 | G16: 6213490.6 | H16: 6213490.6
B17: 中国移动通信集团江苏有限公司无锡分公司 | C17: 中国移动通信有限公司 | G17: 7941914.2 | H17: 6138735.8
B18: 联想（北京）信息技术有限公司 | C18: 联想（北京）有限公司 | F18: 11325225 | G18: 9254625 | H18: 6029100
B19: 中移铁通有限公司无锡分公司 | C19: 中国移动通信有限公司 | D19: 389905.66 | E19: 24214283 | F19: 8306886.8 | G19: 12487929 | H19: 4440094.3
B20: 无锡银通软件科技有限公司 | C20: 无锡银通软件科技有限公司 | E20: 2523584.9 | F20: 3136792.5 | G20: 4273584.9 | H20: 4273584.9
B21: 江苏赞奇科技股份有限公司 | C21: 江苏赞奇科技股份有限公司 | F21: 3883018.9 | G21: 3584905.7 | H21: 3584905.7
B22: 联想（北京）有限公司 | C22: 联想（北京）有限公司 | E22: 2174000 | F22: 7327070 | G22: 9439500 | H22: 9439500
B23: 杭州聚昂科技有限公司 | C23: 杭州聚昂科技有限公司 | G23: 2830188.7 | H23: 2830188.7
B24: 中国移动通信集团江苏有限公司常州分公司 | C24: 中国移动通信有限公司 | D24: 0 | E24: 8154785.5 | F24: 34187830 | G24: 2735849 | H24: 2735849.1
B25: 中国移动通信集团江苏有限公司南京分公司 | C25: 中国移动通信有限公司 | G25: 2735849 | H25: 2735849.1
B26: 中移铁通有限公司南通分公司 | C26: 中国移动通信有限公司 | D26: 0 | E26: 1966199.8 | F26: 0 | G26: 2990579.3 | H26: 2990579.2
B27: 南京信非技术有限公司 | C27: 南京信非技术有限公司 | F27: 10601368 | G27: 19418653 | H27: 1976382.4
B28: 江苏蓝色云湾数字科技有限公司 | C28: 江苏蓝色云湾数字科技有限公司 | G28: 1698490.6 | H28: 1698490.6
B29: 南通领讯信息技术有限公司 | C29: 南通领讯信息技术有限公司 | G29: 1132075.5 | H29: 1132075.5
B30: 其他零售 | C30: 个人 | D30: 2050029.9 | E30: 6153032.2 | F30: 2117004.4 | G30: 1251501 | H30: 944851.15
B31: 中信银行股份有限公司 | C31: 中信银行股份有限公司 | D31: 1335849.1 | E31: 13547.14 | F31: 1417754.7 | G31: 1256150.9 | H31: 858452.83
B32: 苏州吉天信息技术有限公司 | C32: 苏州吉天信息技术有限公司 | G32: 665070.75 | H32: 665070.75
B33: 溧阳市栗里文旅投资发展有限公司 | C33: 溧阳市栗里文旅投资发展有限公司 | G33: 542915.34 | H33: 555094.33
B34: 南京银行股份有限公司 | C34: 南京银行股份有限公司 | D34: 2828573.2 | E34: 1955526.8 | F34: 491528.29 | G34: 678301.89 | H34: 542452.84
B35: 厦门市美亚柏科信息安全研究所有限公司 | C35: 厦门市美亚柏科信息安全研究所有限公司 | F35: 130575.22 | G35: 444646.02 | H35: 444646.02
B36: 中国中金财富证券有限公司 | C36: 中国中金财富证券有限公司 | E36: 56132.08 | F36: 43396.22 | G36: 820905 | H36: 410452.5
B37: 北京粉笔上岸科技有限公司 | C37: 北京粉笔上岸科技有限公司 | F37: 16981.13 | G37: 405660.37 | H37: 405660.37
B38: 华为云计算技术有限公司 | C38: 华为技术有限公司 | D38: 2338206.1 | E38: 4391701.3 | F38: 4477077 | G38: 560872.8 | H38: 270432.23
B39: 陕西星辰智创科技有限公司 | C39: 陕西星辰智创科技有限公司 | F39: 9433.96 | G39: 266666.96 | H39: 227987.72
B40: 武汉木子柒广告有限公司 | C40: 武汉木子柒广告有限公司 | E40: 77017.03 | F40: 30260.38 | G40: 193701.89 | H40: 193701.89
B41: 中银保险有限公司 | C41: 中银保险有限公司 | G41: 229622.64 | H41: 176415.09
B42: 绵阳市涪城区城厢街道办事处 | C42: 绵阳市涪城区城厢街道办事处 | F42: 32830.19 | G42: 169436.47 | H42: 169436.47
B43: 兴业银行股份有限公司 | C43: 兴业银行股份有限公司 | G43: 156276.22 | H43: 156276.22
B44: 北京点富科技有限公司 | C44: 北京点富科技有限公司 | F44: 6566.04 | G44: 247547.16 | H44: 153207.54
B45: 北京水滴科技集团有限公司 | C45: 北京水滴科技集团有限公司 | F45: 62943.4 | G45: 142627.36 | H45: 142627.36
B46: 青岛圣纳尔健康管理有限公司 | C46: 青岛圣纳尔健康管理有限公司 | G46: 452830.19 | H46: 135849.06
B47: 北京青鸟职业教育科技发展有限公司 | C47: 北京青鸟职业教育科技发展有限公司 | G47: 123735.85 | H47: 123735.85
B48: 深圳中汇智达信息科技有限公司 | C48: 深圳中汇智达信息科技有限公司 | E48: 54193.4 | F48: 14194.34 | G48: 120291.51 | H48: 120291.51
B49: 浙江基普特数字智能科技有限公司 | C49: 浙江基普特数字智能科技有限公司 | E49: 663566.7 | F49: 215877.36 | G49: 142397.16 | H49: 116621.69
B50: 成都冥想时代科技有限公司 | C50: 成都冥想时代科技有限公司 | G50: 115403.78 | H50: 115403.78
B51: 杭州超享网络科技有限公司 | C51: 杭州超享网络科技有限公司 | F51: 100132.08 | G51: 233110.36 | H51: 101714.14
B52: 无锡汇跑体育有限公司南京分公司 | C52: 无锡汇跑体育有限公司 | G52: 98377.35 | H52: 98377.35
B53: 格远数智赋能（北京）科技有限公司 | C53: 格远数智赋能（北京）科技有限公司 | G53: 92801.89 | H53: 91858.49
B54: 北京大学武汉人工智能研究院 | C54: 北京大学武汉人工智能研究院 | F54: 241509.44 | G54: 166037.74 | H54: 90566.04
B55: 平安银行股份有限公司深圳分行 | C55: 平安银行股份有限公司 | G55: 237298.12 | H55: 89858.49
B56: 中国移动通信集团四川有限公司绵阳分公司 | C56: 中国移动通信有限公司 | G56: 111737.73 | H56: 82633.96
B57: 南京市硅基生态科技有限公司 | C57: 南京市硅基生态科技有限公司 | E57: 107490.08 | F57: 685410.37 | G57: 129138.68 | H57: 80209.44
B58: 江苏省广播电视集团有限公司 | C58: 江苏省广播电视集团有限公司 | E58: 82075.47 | F58: 112264.15 | G58: 79245.28 | H58: 79245.28
B59: 贵州硅亚智能科技有限公司 | C59: 贵州硅亚智能科技有限公司 | E59: 42942.92 | F59: 16006.62 | G59: 268940.85 | H59: 78044.9
B60: 江苏号百科技有限公司 | C60: 江苏号百科技有限公司 | E60: 138515.62 | G60: 75471.7 | H60: 75471.7
B61: 逸飞迅智能科技（杭州）有限公司 | C61: 逸飞迅智能科技（杭州）有限公司 | E61: 388915.1 | F61: 369206.6 | G61: 78036.8 | H61: 72630.19
B62: 南京生物医药谷建设发展有限公司 | C62: 南京生物医药谷建设发展有限公司 | G62: 71831.69 | H62: 71831.69
B63: 温州医科大学 | C63: 温州医科大学 | G63: 67811.32 | H63: 67811.32
B64: 成都灵猫智研科技有限公司 | C64: 成都灵猫智研科技有限公司 | G64: 66132.07 | H64: 66132.07
B65: 河北视抖文化传媒有限公司 | C65: 河北视抖文化传媒有限公司 | E65: 26405.66 | F65: 2198.11 | G65: 65735.85 | H65: 65735.85
B66: 杭州易有料科技有限公司 | C66: 杭州易有料科技有限公司 | E66: 7547.17 | G66: 64150.94 | H66: 64150.94
B67: 拜占庭人工智能科技（杭州）有限公司 | C67: 拜占庭人工智能科技（杭州）有限公司 | G67: 68415.08 | H67: 60094.33
B68: 深圳市华云中盛科技股份有限公司 | C68: 深圳市华云中盛科技股份有限公司 | D68: 0 | F68: 3730477.1 | G68: 0 | H68: 0
B69: 山西云会计财税科技有限公司 | C69: 山西云会计财税科技有限公司 | F69: 943.4 | G69: 56603.77 | H69: 56603.77
B70: 黄文铿 | C70: 个人 | G70: 0 | H70: 56603.77
B71: 厦门独众科技有限公司 | C71: 厦门独众科技有限公司 | G71: 56603.77 | H71: 56603.77
B72: 上海泰育盛企业咨询有限公司 | C72: 上海泰育盛企业咨询有限公司 | G72: 56603.77 | H72: 56603.77
B73: 泉州市紫曼电子商务有限公司 | C73: 泉州市智启时代科技有限公司 | E73: 91660.38 | F73: 171524.54 | G73: 56377.35 | H73: 51928.3
B74: 秋米网络技术（北京）有限公司 | C74: 秋米网络技术（北京）有限公司 | G74: 51886.79 | H74: 51886.79
B75: 北京美迪亚电子信息有限公司 | C75: 北京美迪亚电子信息有限公司 | E75: 101886.79 | G75: 71320.76 | H75: 50943.4
B76: 超级语言(北京)科技有限公司 | C76: 超级语言(北京)科技有限公司 | G76: 47169.81 | H76: 47169.81
B77: 南京良晨管理咨询有限公司 | C77: 南京良晨管理咨询有限公司 | G77: 50943.39 | H77: 47169.81
B78: 深圳市明源云客电子商务有限公司 | C78: 深圳市明源云客电子商务有限公司 | G78: 47169.81 | H78: 47169.81
B79: 河南餐赞网络科技有限公司 | C79: 河南餐赞网络科技有限公司 | G79: 47169.8 | H79: 47169.8
B80: 上海鼎捷数智软件有限公司 | C80: 上海鼎捷数智软件有限公司 | G80: 47132.08 | H80: 47132.08
B81: 南京擎天科技有限公司 | C81: 南京擎天科技有限公司 | G81: 46226.42 | H81: 46226.42
B82: 硅语（昆山）智能科技有限公司 | C82: 硅语（昆山）智能科技有限公司 | F82: 16849.05 | G82: 43781.89 | H82: 43781.89
B83: 广东阿康健康科技集团有限公司 | C83: 广东阿康健康科技集团有限公司 | E83: 106967.92 | F83: 124861.8 | G83: 71727.82 | H83: 43680.18
B84: 四川飞图文化发展有限公司 | C84: 四川飞图文化发展有限公司 | D84: 129153.45 | F84: 56167.46 | G84: 47659.44 | H84: 43032.08
B85: 硅亚智能科技（武汉）有限公司 | C85: 硅亚智能科技（武汉）有限公司 | G85: 50943.39 | H85: 41509.43
B86: 重庆硅基生命科技有限公司 | C86: 重庆硅基生命科技有限公司 | E86: 122641.5 | F86: 68031.12 | G86: 56581.84 | H86: 41076.18
B87: 泰康在线财产保险股份有限公司 | C87: 泰康在线财产保险股份有限公司 | E87: 29716.98 | F87: 189150.94 | G87: 63679.25 | H87: 40330.19
B88: 北京学而思教育科技有限公司 | C88: 北京学而思教育科技有限公司 | D88: 84905.66 | E88: 84905.65 | F88: 47641.48 | G88: 114622.61 | H88: 38207.52
B89: 北京天圣云科技有限公司 | C89: 北京天圣云科技有限公司 | E89: 73113.2 | F89: 153089.63 | G89: 9264.16 | H89: 38132.08
B90: 平安健康互联网股份有限公司上海分公司 | C90: 平安健康互联网股份有限公司 | G90: 37735.85 | H90: 37735.85
B91: 新疆硅语智能科技有限公司 | C91: 新疆硅语智能科技有限公司 | E91: 65451.88 | F91: 189157.55 | G91: 62719.247 | H91: 33766.42
B92: 树根互联股份有限公司 | C92: 树根互联股份有限公司 | G92: 33426.41 | H92: 33426.41
B93: 南京梅花餐饮管理有限公司 | C93: 南京梅花餐饮管理有限公司 | G93: 33415.93 | H93: 33415.93
B94: 杭州全食物日记科技有限公司 | C94: 杭州全食物日记科技有限公司 | E94: 61805.66 | F94: 23433 | G94: 38892.46 | H94: 33260.38
B95: 吉林市润石软件技术有限责任公司 | C95: 吉林市润石软件技术有限责任公司 | G95: 69028.3 | H95: 26764.16
B96: 上海云掌智能科技有限公司 | C96: 上海云掌智能科技有限公司 | G96: 30322.25 | H96: 30322.25
B97: 上海世味百膳科技发展有限公司 | C97: 上海世味百膳科技发展有限公司 | G97: 30150.94 | H97: 30150.94
B98: 张筱筠 | C98: 个人 | G98: 30037.73 | H98: 30037.73
B99: 平安健康互联网股份有限公司 | C99: 平安健康互联网股份有限公司 | F99: 55649.05 | G99: 28301.89 | H99: 28301.89
B100: 江苏嘉图网络科技股份有限公司 | C100: 江苏嘉图网络科技股份有限公司 | G100: 28283.02 | H100: 28283.02
...

Sheet contract liability
B1: Contract liability
B2: The Group | C2: As at 31 December | M2: End | O2: The Company | P2: As at 31 December
C3: 2022 | E3: 2023 | G3: 2024 | P3: 2022 | R3: 2023 | T3: 2024
C4: RMB’000 | E4: RMB’000 | G4: RMB’000 | P4: RMB’000 | R4: RMB’000 | T4: RMB’000
B6: Balance at the beginning of the year | C6: 0 | E6: 3139 | G6: 41127 | O6: Balance at the beginning of the year | P6: 0 | R6: 3139 | T6: 36207
B7: Decrease in contract liabilities as a result of recognizing revenue during the year that was included in the contract liabilities at the beginning of the year | C7: -7138 | E7: -43704 | G7: -108809 | O7: Decrease in contract liabilities as a result of recognizing revenue during the year that was included in the contract liabilities at the beginning of the year | P7: -1729 | R7: -43704 | T7: -108809
B8: Increase in contract liabilities as a result of receiving advance payments during the year | C8: 10465 | E8: 81692 | G8: 117435 | O8: Increase in contract liabilities as a result of receiving advance payments during the year | P8: -3398 | R8: 76772 | T8: 114439
B10: Balance at the end of the year | C10: =ROUND(SUM(C6:C9)/1.06,0) -> 3139 | E10: 41127 | G10: =SUM(G6:G9) -> 49753 | O10: Balance at the end of the year | P10: =SUM(P6:P9) -> -5127 | R10: =SUM(R6:R9) -> 36207 | T10: =SUM(T6:T9) -> 41837
O11: End
B16: Contract liability
B17: The Group | C17: As at 31 December | K17: As at 30 June | M17: End | O17: The Company | P17: As at 31 December | V17: As at 30 June
C18: 2022 | E18: 2023 | G18: 2024 | I18: 2025 | K18: 2025 | O18: 南京硅基 | P18: 2022 | R18: 2023 | T18: 2024 | V18: 2025
C19: RMB’000 | E19: RMB’000 | G19: RMB’000 | I19: RMB’000 | K19: RMB’000 | P19: RMB’000 | R19: RMB’000 | T19: RMB’000 | V19: RMB’000
A21: A | B21: Balance at the beginning of the year | C21: 6339661.7 | E21: 6804807.3 | G21: 46497256 | I21: 50236540 | K21: 50236540 | O21: Balance at the beginning of the year | P21: 1961479 | R21: 6804807.3 | T21: 41577312 | V21: 42298948
A22: B | B22: Decrease in contract liabilities as a result of recognizing revenue during the year that was included in the contract liabilities at the beginning of the year | C22: -6339661.7 | E22: -3243364.9 | G22: -33496871 | I22: -34671804 | K22: -33748518 | O22: Decrease in contract liabilities as a result of recognizing revenue during the year that was included in the contract liabilities at the beginning of the year | P22: -1961479 | R22: -3243364.9 | T22: -30860203 | V22: -32288646
A23: C | B23: Increase in contract liabilities as a result of receiving advance payments during the year | C23: 25192450 | E23: 1.3510211e+08 | G23: 1.5239679e+08 | I23: 1.4774352e+08 | K23: 44080148 | O23: Increase in contract liabilities as a result of receiving advance payments during the year | P23: 27497312 | R23: 1.2410581e+08 | T23: 1.3104298e+08 | V23: 39500708
A24: D | B24: Decrease in contract liabilities as a result of recognising revenue during the same year | C24: -18387643 | E24: -92166298 | G24: -1.1516063e+08 | I24: -87733993 | K24: -40537263 | P24: -20692505 | R24: -86089937 | T24: -99461143 | V24: -38044521
I25: 0
A26: E | B26: Balance at the end of the year | C26: 6804807.3 | E26: 46497256 | G26: 50236540 | I26: 75574267 | K26: 20030907 | O26: Balance at the end of the year | P26: 6804807.3 | R26: 41577312 | T26: 42298948 | V26: 11466489
O27: End
A30: A | B30: 运营商一体化改造 | C30: 0 | E30: 2829686.3 | G30: 20468113 | I30: 2830487.5 | K30: 2830487.5 | N30: A | O30: 运营商一体化改造 | P30: 0 | R30: 2829686.3 | T30: 20468113 | V30: 2830487.5 | Y30: by 收入板块movement
A31: A | B31: SaaS | C31: 6339661.7 | E31: 3975121 | G31: 26029143 | I31: 19917016 | K31: 19917016 | N31: A | O31: SaaS | P31: 1961479 | R31: 3975121 | T31: 21109200 | V31: 11979424
A32: A | B32: 数字人智能服务产品 | C32: 0 | E32: 0 | G32: 0 | I32: 27489036 | K32: 27489036 | N32: A | O32: 数字人智能服务产品 | P32: 0 | R32: 0 | T32: 0 | V32: 27489036 | Y32: SaaS | Z32: 2022 | AB32: 2023 | AD32: 2024 | AF32: 20250630
A33: A | B33: 全自动内容生产
Y34: 期初余额 | Z34: 6339661.7 | AB34: 3975121 | AD34: 26029143 | AF34: 19917016
A35: B | B35: 运营商一体化改造 | C35: 0 | E35: -2829686.3 | G35: -20468113 | I35: -2830487.5 | K35: -2830487.5 | N35: B | O35: 运营商一体化改造 | P35: 0 | R35: -2829686.3 | T35: -20468113 | V35: -2830487.5 | Y35: 往年预收本年确认收入 | Z35: -6339661.7 | AB35: -413678.59 | AD35: -13028759 | AF35: -3428994
A36: B | B36: SaaS | C36: -6339661.7 | E36: -413678.59 | G36: -13028759 | I36: -4352280.6 | K36: -3428994 | N36: B | O36: SaaS | P36: -1961479 | R36: -413678.59 | T36: -10392090 | V36: -1969122.4 | Y36: 本年新增 | Z36: 14910830 | AB36: 70223347 | AD36: 28265927 | AF36: 6477348.7
A37: B | B37: 数字人智能服务产品 | C37: 0 | E37: 0 | G37: 0 | I37: -27489036 | K37: -27489036 | N37: B | O37: 数字人智能服务产品 | P37: 0 | R37: 0 | T37: 0 | V37: -27489036 | Y37: 当年预收当年确认收入 | Z37: -10935709 | AB37: -47755646 | AD37: -21349295 | AF37: -3952290.1
A38: B | B38: 全自动内容生产
Y39: 期末余额 | Z39: 3975121 | AB39: 26029143 | AD39: 19917016 | AF39: 19013081
A40: C | B40: 运营商一体化改造 | C40: 10281620 | E40: 64878765 | G40: 96641824 | I40: 63100330 | K40: 37602799 | N40: C | O40: 运营商一体化改造 | P40: 10281620 | R40: 64878765 | T40: 96641824 | V40: 37602799 | Y40: 当年收入金额 | Z40: 17275370 | AB40: 48169325 | AD40: 34378054 | AF40: 7381284.1
A41: C | B41: SaaS | C41: 14910830 | E41: 70223347 | G41: 28265927 | I41: 8373593.3 | K41: 6477348.7 | N41: C | O41: SaaS | P41: 17215692 | R41: 59227043 | T41: 6912121 | V41: 1897908.4 | Z41: =Z40+Z37+Z35 -> 0.0039998991 | AB41: =AB40+AB37+AB35 -> -0.0017998034 | AD41: =AD40+AD37+AD35 -> -0.091599897 | AF41: =AF40+AF37+AF35 -> -0.0034000003
A42: C | B42: 数字人智能服务产品 | C42: 0 | E42: 0 | G42: 27489036 | I42: 65000000 | K42: 0 | N42: C | O42: 数字人智能服务产品 | P42: 0 | R42: 0 | T42: 27489036 | V42: 0
A43: C | B43: 全自动内容生产 | I43: 11269600
Y44: ICT | Z44: 2022 | AB44: 2023 | AD44: 2024 | AF44: 20250630
A45: D | B45: 运营商一体化改造 | C45: -7451934 | E45: -44410652 | G45: -93811337 | I45: -55613282 | K45: -36584973 | N45: D | O45: 运营商一体化改造 | P45: -7451934 | R45: -44410652 | T45: -93811337 | V45: -36584973 | Y45: 期初余额 | Z45: 0 | AB45: 2829686.3 | AD45: 20468113 | AF45: 2830487.5
A46: D | B46: SaaS | C46: -10935709 | E46: -47755646 | G46: -21349295 | I46: -6866202 | K46: -3952290.1 | N46: D | O46: SaaS | P46: -13240571 | R46: -41679285 | T46: -5649806.1 | V46: -1459547.4 | Y46: 往年预收本年确认收入 | Z46: 0 | AB46: -2829686.3 | AD46: -20468113 | AF46: -2830487.5
A47: D | B47: 数字人智能服务产品 | C47: 0 | E47: 0 | G47: 0 | I47: -18131701 | N47: D | O47: 数字人智能服务产品 | P47: 0 | R47: 0 | T47: 0 | Y47: 本年新增 | Z47: 10281620 | AB47: 64878765 | AD47: 96641824 | AF47: 37602799
A48: D | B48: 全自动内容生产 | I48: -7122807.5
Y49: 当年预收当年确认收入 | Z49: -7451934 | AB49: -44410652 | AD49: -93811337 | AF49: -36584973
A50: E | B50: 运营商一体化改造 | C50: 2829686.3 | E50: 20468113 | G50: 2830487.5 | I50: 7487048.5 | K50: 1017826.1 | N50: E | O50: 运营商一体化改造 | P50: 2829686.3 | R50: 20468113 | T50: 2830487.5 | V50: 1017826.1 | Y50: 期末余额 | Z50: 2829686.3 | AB50: 20468113 | AD50: 2830487.5 | AF50: 1017826.1
A51: E | B51: SaaS | C51: 3975121 | E51: 26029143 | G51: 19917016 | I51: 17072127 | K51: 19013081 | N51: E | O51: SaaS | P51: 3975121 | R51: 21109200 | T51: 11979424 | V51: 10448663 | Y51: 当年收入金额 | Z51: 37081816 | AB51: 1.947907e+08 | AD51: 4.2215234e+08 | AF51: 2.0980538e+08
A52: E | B52: 数字人智能服务产品 | C52: 0 | E52: 0 | G52: 27489036 | I52: 46868299 | K52: 0 | N52: E | O52: 数字人智能服务产品 | P52: 0 | R52: 0 | T52: 27489036 | V52: 0 | Z52: 29629882 | AB52: 1.4755037e+08 | AD52: 3.0787289e+08 | AF52: 1.7038992e+08
A53: E | B53: 全自动内容生产 | I53: 4146792.5
C55: 6804807.3 | E55: 46497256 | G55: 50236540 | I55: 75574267 | K55: 20030907 | P55: 6804807.3 | R55: 41577312 | T55: 42298948 | V55: 11466489 | Y55: DUIX | Z55: 2022 | AB55: 2023 | AD55: 2024 | AF55: 20250630
C56: -6831182.2 | E56: -46497256 | G56: -50236540 | I56: =-I55 -> -75574267 | K56: -20030907 | P56: -6831182.2 | R56: -41577312 | T56: -42298948 | V56: -11466489 | Y56: 期初余额 | Z56: 0 | AB56: 0 | AD56: 0 | AF56: 27489036
Y57: 往年预收本年确认收入 | Z57: 0 | AB57: 0 | AD57: 0 | AF57: -27489036
Y58: 本年新增 | Z58: 0 | AB58: 0 | AD58: 27489036 | AF58: 0
Y59: 当年预收当年确认收入 | Z59: 0 | AB59: 0 | AD59: 0 | AF59: 0
B60: NB1 | Y60: 期末余额 | Z60: 0 | AB60: 0 | AD60: 27489036 | AF60: 0
B61: 1、2023年12月31日，合同负债较2022年末增加人民币3,967万元，主要是因为2023年运营商一体化改造业务与数字人SaaS业务均大幅增长，因此公司2023年末合同负债余额较高。 2、2024年12月31日，合同负债较2023年末增加人民币374万元，变动幅度较小，主要系1）上期ICT项目于本年完成验收导致合同负债减少1,764万元；2）此外，2024年集团与嘉环科技股份有限公司签订了一份数字人智能服务产品业务合同，定制化部署大模型平台，根据合同预付2,980万元。 3、2025年6月30日合同负债较2024年末减少3,030万元，主要系嘉环科技的数字人智能服务产品项目已于2025年验收。 | Y61: 当年收入金额 | Z61: 1.0278221e+08 | AB61: 2.6526012e+08 | AD61: 1.840648e+08 | AF61: 1.070887e+08

Sheet PL2
C6: 2022 | E6: 2022 | G6: 2023 | I6: 2023 | K6: 2024 | M6: 2024 | O6: 2025 | Q6: 2025 | S6: 202406 | U6: 202406 | W6: 202506 | Y6: 202506
B7: 对应收入类型 | C7: 账面金额 | D7: 调整金额 | E7: 审定金额 | F7: 占比 | G7: 账面金额 | H7: 调整金额 | I7: 审定金额 | J7: 占比 | K7: 账面金额 | L7: 调整金额 | M7: 审定金额 | N7: 占比 | O7: 账面金额 | P7: 调整金额 | Q7: 审定金额 | R7: 占比 | S7: 账面金额 | T7: 调整金额 | U7: 审定金额 | V7: 占比 | W7: 账面金额 | X7: 调整金额 | Y7: 审定金额 | Z7: 占比
A9: ICT services | B9: 运营商一体化改造 | C9: 74497340 | D9: -47258167 | E9: =SUM(E10:E13) -> 27239174 | G9: 1.4411145e+08 | H9: -10842596 | I9: =SUM(I10:I13) -> 1.3326885e+08 | K9: 2.6579023e+08 | L9: 35363513 | M9: =SUM(M10:M13) -> 3.0115375e+08 | O9: =SUM(O10:O13) -> 2.3036163e+08 | P9: =SUM(P10:P13) -> 0 | Q9: =SUM(Q10:Q13) -> 2.3036163e+08 | S9: 95318080 | T9: 48498110 | U9: =SUM(U10:U13) -> 1.4381619e+08 | W9: 1.5361374e+08 | X9: -2272615.1 | Y9: =SUM(Y10:Y13) -> 1.5134113e+08
B10: 运营商项目实施费用 | C10: 74497340 | D10: -47258167 | E10: 27239174 | F10: 1 | G10: 1.4411145e+08 | H10: -10835596 | I10: 1.3327585e+08 | J10: 1.0000525 | K10: 2.6546735e+08 | L10: 35479202 | M10: 3.0094656e+08 | N10: 1.0000525 | O10: 2.2824551e+08 | Q10: 2.2824551e+08 | R10: 0.99931201 | S10: 95247306 | T10: 48600322 | U10: 1.4384763e+08 | V10: 1.0002186 | W10: 1.5361374e+08 | X10: -1177097.8 | Y10: 1.5243665e+08 | Z10: 1.0072387
B11: 人工成本 | C11: 0 | D11: 0 | E11: 0 | G11: 0 | H11: -7000 | I11: -7000 | K11: 0 | L11: 0 | M11: 0 | O11: 0 | Q11: 0 | R11: 0 | S11: 0 | T11: 0 | U11: 0 | V11: 0 | W11: 0 | X11: 0 | Y11: 0
B12: 硬件采购 | C12: 0 | D12: 0 | E12: 0 | G12: 0 | H12: 0 | I12: 0 | K12: 322879.15 | L12: 0 | M12: 322879.15 | O12: 2116130 | Q12: 2116130 | R12: 0.0010721406 | S12: 70774.36 | T12: -102212.37 | U12: -31438.01 | V12: -0.00021859855 | W12: 0 | X12: -1095517.2 | Y12: -1095517.2
B13: 其他 | C13: 0 | D13: 0 | E13: 0 | G13: 0 | H13: 0 | I13: 0 | K13: 0 | L13: -115688.6 | M13: -115688.6 | O13: 0 | P13: 0 | Q13: 0 | R13: -0.00038415129 | S13: 0 | T13: 0 | U13: 0 | V13: 0 | W13: 0 | X13: 0 | Y13: 0
A15: AIGC services | B15: 数字人智能服务产品 | C15: 1.1077918e+08 | D15: -55284146 | E15: =SUM(E16:E20) -> 55495031 | G15: 1.811597e+08 | H15: -53501019 | I15: =SUM(I16:I20) -> 1.2765868e+08 | K15: 1.1539481e+08 | L15: -5351726.5 | M15: =SUM(M16:M20) -> 1.1004309e+08 | O15: =SUM(O16:O20) -> 2.5093433e+08 | P15: =SUM(P16:P20) -> 0 | Q15: =SUM(Q16:Q20) -> 2.5093433e+08 | S15: 56968190 | T15: -16498488 | U15: =SUM(U16:U20) -> 40469702 | W15: 65660287 | X15: 266655.09 | Y15: =SUM(Y16:Y20) -> 65926942
B16: 项目实施费用 | C16: 15790734 | D16: -2695000 | E16: 13095734 | F16: 0.2359803 | G16: 12737277 | H16: 1745061.9 | I16: 14482339 | J16: 0.11337891 | K16: 32369471 | L16: -3204207.7 | M16: 29165263 | N16: 0.11337891 | O16: 23583614 | Q16: 23583614 | R16: 0.43923503 | S16: 5267185.6 | T16: -196415.1 | U16: 5070770.5 | V16: 0.12529795 | W16: 16467307 | X16: 595504.65 | Y16: 17062812 | Z16: 0.25881394
B17: 云服务费用 | C17: 93706524 | D17: -53319937 | E17: 40386587 | F17: 0.7277514 | G17: 1.6068935e+08 | H17: -55170788 | I17: 1.0551856e+08 | J17: 0.82608058 | K17: 75655807 | L17: -2086863.6 | M17: 73568944 | N17: 0.82608058 | O17: 46225834 | Q17: 46225834 | R17: 0.21912348 | S17: 47350711 | T17: -17132997 | U17: 30217714 | V17: 0.74667498 | W17: 30366003 | X17: 0 | Y17: 30366003 | Z17: 0.46060081
B18: 硬件采购 | C18: 1269919.3 | D18: 730790.95 | E18: 2000710.2 | F18: 0.036052061 | G18: 7733079.9 | H18: -75292.57 | I18: 7657787.3 | J18: 0.060540508 | K18: 7369536.1 | L18: -28407.06 | M18: 7341129.1 | N18: 0.060540508 | O18: 41762086 | Q18: 41762086 | R18: 0.17317123 | S18: 4214557.2 | T18: 0.010707965 | U18: 4214557.2 | V18: 0.10414105 | W18: 18826977 | X18: -328849.56 | Y18: 18498128 | Z18: 0.28058526
B19: 其他 | C19: 12000 | D19: 0 | E19: 12000 | F19: 0.00021623558 | G19: 0 | H19: 0 | I19: 0 | J19: 0 | K19: 0 | L19: -32248.08 | M19: -32248.08 | N19: 0 | Q19: 0 | R19: 0 | S19: 0 | T19: 966660.12 | U19: 966660.12 | V19: 0.02388602 | W19: 0 | X19: 0 | Y19: 0 | Z19: 0
B20: 软硬件产品 | O20: 1.3936279e+08 | Q20: 1.3936279e+08 | R20: 0.16847026
A22: AI application layer products | B22: 数字人产品SaaS | C22: 7981170.2 | D22: 0 | E22: =SUM(E24:E28) -> 7981170.2 | G22: 48404515 | H22: -39615094 | I22: =SUM(I24:I28) -> 8789420.8 | K22: 8563836.7 | L22: 0 | M22: =SUM(M24:M28) -> 8563836.7 | O22: =SUM(O24:O29) -> 8139870.2 | P22: =SUM(P24:P29) -> 0 | Q22: =SUM(Q24:Q28) -> 8139870.2 | S22: 4380318.5 | T22: -97222.284 | U22: =SUM(U24:U28) -> 4283096.3 | W22: 4582074.3 | X22: 78726.05 | Y22: =SUM(Y24:Y28) -> 4660800.3
B23: 数字人产品一体机 | C23: 0 | D23: 0 | E23: 0 | G23: 0 | H23: 0 | I23: 0 | K23: 0 | L23: 0 | M23: 0 | O23: 0 | P23: 0 | Q23: 0 | S23: 0 | T23: 0 | U23: 0 | W23: 0 | X23: 0 | Y23: 0
B24: 人工成本 | C24: 4503114.1 | D24: 0 | E24: 4503114.1 | F24: 0.56421728 | G24: 3798654.8 | H24: 0 | I24: 3798654.8 | J24: 0.43218488 | K24: 0 | L24: 0 | M24: 0 | N24: 0.43218488 | O24: 0 | P24: 0 | Q24: 0 | R24: 0 | S24: 0 | T24: 0 | U24: 0 | V24: 0 | W24: 0 | X24: 0 | Y24: 0 | Z24: 0
B25: 云服务费用 | C25: 2840146.7 | D25: 0 | E25: 2840146.7 | F25: 0.35585592 | G25: 44463742 | H25: -39615094 | I25: 4848647.5 | J25: 0.55164585 | K25: 8563836.7 | L25: 0 | M25: 8563836.7 | N25: 0.55164585 | O25: 8139870.2 | P25: 0 | Q25: 8139870.2 | R25: 1 | S25: 4380318.5 | T25: -97222.284 | U25: 4283096.3 | V25: 1 | W25: 4582074.3 | X25: 78726.05 | Y25: 4660800.3 | Z25: 1
B26: 其他 | C26: 637909.4 | D26: 0 | E26: 637909.4 | F26: 0.079926801 | G26: 142118.58 | H26: 0 | I26: 142118.58 | J26: 0.016169277 | K26: 0 | L26: 0 | M26: 0 | N26: 0.016169277 | O26: 0 | P26: 0 | Q26: 0 | R26: 0 | S26: 0 | T26: 0 | U26: 0 | V26: 0 | W26: 0 | X26: 0 | Y26: 0 | Z26: 0
B27: 项目实施费用 | C27: 0 | D27: 0 | E27: 0 | F27: 0 | G27: 0 | H27: 0 | I27: 0 | J27: 0 | K27: 0 | L27: 0 | M27: 0 | N27: 0 | O27: 0 | P27: 0 | Q27: 0 | R27: 0 | S27: 0 | T27: 0 | U27: 0 | V27: 0 | W27: 0 | X27: 0 | Y27: 0 | Z27: 0
B28: 硬件采购 | O28: 0 | P28: 0 | W28: 0 | X28: 0 | Y28: 0 | Z28: 0
A30: AI voice services | B30: 智能协呼机器人SaaS | C30: 6241119.7 | D30: -64555.34 | E30: =SUM(E31:E32) -> 6176564.3 | G30: 1962686.3 | H30: 1273805.1 | I30: =SUM(I31:I32) -> 3236491.3 | K30: 5556.89 | L30: 0 | M30: =SUM(M31:M32) -> 5556.89 | O30: 0 | P30: 0 | Q30: =SUM(Q31:Q32) -> 0 | S30: 5556.89 | T30: 0 | U30: =SUM(U31:U32) -> 5556.89 | W30: 0 | X30: 0 | Y30: =SUM(Y31:Y32) -> 0
B31: 项目实施费用 | C31: 0 | D31: 0 | E31: 0 | F31: 0 | G31: 80875.47 | H31: 0 | I31: 80875.47 | J31: 0.024988626 | K31: 0 | L31: 0 | M31: 0 | N31: 0.024988626 | R31: 0 | S31: 0 | T31: 0 | U31: 0 | V31: 0 | W31: 0 | X31: 0 | Y31: 0 | Z31: N/A
A32: 线路费用 | B32: 其他 | C32: 6241119.7 | D32: -64555.34 | E32: 6176564.3 | F32: 1 | G32: 1881810.8 | H32: 1273805.1 | I32: 3155615.9 | J32: 0.97501137 | K32: 5556.89 | L32: 0 | M32: 5556.89 | N32: 0.97501137 | R32: 0 | S32: 5556.89 | T32: 0 | U32: 5556.89 | V32: 1 | W32: 0 | X32: 0 | Y32: 0 | Z32: N/A
A34: AI voice services | B34: 智能外呼服务 | C34: 46542283 | D34: -6487893.3 | E34: =SUM(E35:E39) -> 40054390 | G34: 14504003 | H34: -155587.66 | I34: =SUM(I35:I39) -> 14348416 | K34: 7286027.2 | L34: 2596674.7 | M34: =SUM(M35:M39) -> 9882701.9 | O34: =SUM(O35:O39) -> 2951914.7 | P34: =SUM(P35:P39) -> 0 | Q34: =SUM(Q35:Q39) -> 2951914.7 | S34: 1018665.8 | T34: 2596674.7 | U34: =SUM(U35:U39) -> 3615340.5 | W34: 833973.55 | X34: 135285 | Y34: =SUM(Y35:Y39) -> 1087336.2
B35: 项目实施费用 | C35: 11471668 | D35: 0 | E35: 11471668 | F35: 0.28640226 | G35: 14386512 | H35: -155587.66 | I35: 14230925 | J35: 0.99181156 | K35: 4645006 | L35: 0 | M35: 4645006 | N35: 0.99181156 | O35: 2951914.7 | Q35: 2951914.7 | R35: 1.0418396 | S35: 454210.64 | T35: 0 | U35: 454210.64 | V35: 0.12563426 | W35: 951820.28 | X35: 135285 | Y35: 1087105.2 | Z35: 1.1215844
B36: 云服务费用 | C36: 24192453 | D36: -3891218.6 | E36: 20301234 | F36: 0.50684167 | G36: 0 | H36: 0 | I36: 0 | J36: 0 | K36: 2076566 | L36: 0 | M36: 2076566 | N36: 0 | O36: 0 | Q36: 0 | R36: 0 | S36: 0 | T36: 0 | U36: 0 | V36: 0 | W36: 0 | X36: 0 | Y36: 0 | Z36: 0
B37: 硬件采购 | C37: 2697602.2 | D37: -2596674.7 | E37: 100927.44 | F37: 0.0025197598 | G37: 117491.15 | H37: 0 | I37: 117491.15 | J37: 0.0081884406 | K37: 52991.15 | L37: 2596674.7 | M37: 2649665.9 | N37: 0.0081884406 | O37: 0 | Q37: 0 | R37: 0 | S37: 52991.15 | T37: 2596674.7 | U37: 2649665.9 | V37: 0.73289525 | W37: 0 | X37: 0 | Y37: 0 | Z37: 0
B38: 人工成本 | C38: 5334744.8 | D38: 0 | E38: 5334744.8 | F38: 0.13318752 | G38: 0 | H38: 0 | I38: 0 | J38: 0 | K38: 505375.05 | L38: 0 | M38: 505375.05 | N38: 0 | O38: 0 | Q38: 0 | R38: 0 | S38: 505375.05 | T38: 0 | U38: 505375.05 | V38: 0.13978629 | W38: 0 | X38: 0 | Y38: 0 | Z38: 0
B39: 其他 | C39: 2845815.8 | D39: 0 | E39: 2845815.8 | F39: 0.071048786 | G39: 0 | H39: 0 | I39: 0 | J39: 0 | K39: 6088.93 | L39: 0 | M39: 6088.93 | N39: 0 | R39: -0.041839625 | S39: 6088.93 | T39: 0 | U39: 6088.93 | V39: 0.0016841927 | W39: -117846.73 | X39: 0 | Y39: 230.94 | Z39: -0.032596302
B40: 全自动内容生产 | E40: =SUM(E41:E43) -> 0 | I40: =SUM(I41:I43) -> 0 | M40: =SUM(M41:M43) -> 0 | O40: 23151796 | Q40: =SUM(Q41:Q43) -> 23151796 | U40: =SUM(U41:U43) -> 0 | Y40: =SUM(Y41:Y43) -> 0
B41: 项目实施费用 | O41: 4358367.6 | Q41: 4358367.6
B42: 云服务费用 | O42: 18717886 | Q42: 18717886
B43: 其他 | O43: 75542.68 | Q43: 75542.68
B45: 税金及附加 | C45: 6625204.4 | D45: -6625204.4 | G45: 35900825 | H45: -35900825 | K45: 40165321 | L45: -40165321 | M45: 0 | O45: 44572019 | P45: -44572019 | Q45: 0 | S45: 11180775 | T45: -11180775 | U45: 0 | W45: 20054459 | X45: -20054459 | Y45: 0
C46: 2.5266629e+08 | D46: -1.1571997e+08 | E46: =E9+E15+E22+E30+E34+E40+E45 -> 1.3694633e+08 | G46: 4.2604318e+08 | H46: -1.3874132e+08 | I46: =I9+I15+I22+I30+I34+I40 -> 2.8730186e+08 | K46: 4.3720579e+08 | L46: -7556860.1 | M46: =M9+M15+M22+M30+M34+M40 -> 4.2964893e+08 | O46: =O45+O40+O34+O22+O15+O9 -> 5.6011156e+08 | P46: =P45+P40+P34+P22+P15+P9 -> -44572019 | Q46: =Q9+Q15+Q22+Q30+Q34+Q40 -> 5.1553954e+08 | S46: 1.6887159e+08 | T46: 23318298 | U46: =U9+U15+U22+U30+U34+U40 -> 1.9218989e+08 | W46: 2.4474454e+08 | X46: -21846408 | Y46: =Y9+Y15+Y22+Y30+Y34+Y40 -> 2.2301621e+08
E47: =E46-'FY22-25 IFRS（合并）'!G5 -> -63994.13 | I47: =I46-'FY22-25 IFRS（合并）'!I5 -> -343189.27 | M47: =M46-'FY22-25 IFRS（合并）'!K5 -> -710292.53 | Q47: =Q46-'FY22-25 IFRS（合并）'!Q5 -> -1207721.1 | U47: =U46-'FY22-25 IFRS（合并）'!M5 -> -194936.36 | Y47: =Y46-'FY22-25 IFRS（合并）'!O5 -> 117846.73
U49: 请KP确认
E50: 2023 | M50: 2024 | U50: 2025
B51: Project fulfillment costs | E51: RMB’000 | F51: % | M51: RMB’000 | N51: % | U51: RMB’000 | V51: %
B52: Cost of cloud services | E52: 162070 | F52: =E52/$E$57 -> 0.56343757 | M52: 334621 | N52: =M52/$M$57 -> 0.77753922 | U52: =262118+135523 -> 397641 | V52: =U52/$U$57 -> 0.7695072
B53: Cost of hardware and software | E53: 110367 | F53: =E53/$E$57 -> 0.3836917 | M53: 84209 | N53: =M53/$M$57 -> 0.19567152 | U53: 73150.467 | V53: =U53/$U$57 -> 0.14155937
B54: Staff costs | E54: 7775 | F54: =E54/$E$57 -> 0.027029846 | M54: 10314 | N54: =M54/$M$57 -> 0.023966038 | U54: =181124.87922-135523 -> 45601.879 | V54: =U54/$U$57 -> 0.088247878 | Y54: 定制化软件开发移到项目实施，和以前年度同口径
B55: Others | E55: 3792 | F55: =E55/$E$57 -> 0.013182916 | M55: 505 | N55: =M55/$M$57 -> 0.0011734389 | U55: 0 | V55: =U55/$U$57 -> 0
B56: Total | E56: 3641 | F56: =E56/$E$57 -> 0.012657964 | M56: 710 | N56: =M56/$M$57 -> 0.0016497854 | U56: 354.25264 | V56: =U56/$U$57 -> 0.00068554289
E57: =SUM(E52:E56) -> 287645 | F57: =E57/$E$57 -> 1 | M57: =SUM(M52:M56) -> 430359 | N57: =M57/$M$57 -> 1 | U57: =SUM(U52:U56) -> 516747.6 | V57: =U57/$U$57 -> 1
U58: =U57-收入拆分!G13 -> 0.33402 | V58: =U58/$U$57 -> 6.4638907e-07

Sheet PL3
B3: 营业收入 | D3: 22年度 | F3: 23年度 | H3: 24年度 | J3: 25年度 | L3: 2024年1-6月 | N3: 2025年1-6月
D4: a | F4: b | H4: c | J4: c | L4: d1 | N4: d2
B5: Customised AI workforce solutions | D5: =SUM(D6:D8) -> -2.086161e+08 | F5: =SUM(F6:F8) -> -4.853631e+08 | H5: =SUM(H6:H8) -> -6.2944451e+08 | J5: =SUM(J6:J8) -> -7.2703378e+08 | L5: =SUM(L6:L8) -> -2.8004144e+08 | N5: =SUM(N6:N8) -> -3.1884501e+08
B6: ICT services | D6: -37081816 | F6: -1.947907e+08 | H6: -4.2215234e+08 | J6: -3.2335846e+08 | L6: -2.0269747e+08 | N6: -2.0980538e+08
B7: AIGC services | D7: -1.0278221e+08 | F7: -2.6526012e+08 | H7: -1.9050367e+08 | J7: -3.9981265e+08 | L7: -68796248 | N7: -1.070887e+08
B8: AI voice services | D8: -68752074 | F8: -25312277 | H8: -16788507 | J8: -3862674.1 | L8: -8547718 | N8: -1950936.2
B9: Standardized and productized AI workforce solutions | D9: -14196979 | F9: -45442759 | H9: -25993256 | J9: -10396657 | L9: -13070291 | N9: -6963475.6
B10: 全自动内容生产 | J10: -51387720
B11: 合计 | D11: =SUM(D6:D9) -> -2.2281308e+08 | F11: =SUM(F6:F9) -> -5.3080586e+08 | H11: =SUM(H6:H9) -> -6.5543777e+08 | J11: =SUM(J6:J10) -> -7.8881816e+08 | L11: =SUM(L6:L9) -> -2.9311173e+08 | N11: =SUM(N6:N9) -> -3.2580849e+08
D12: 0 | F12: 0 | H12: 0 | J12: 0 | L12: 0 | N12: 0
B13: 营业成本
B14: Customised AI workforce solutions | D14: =SUM(D15:D17) -> 1.2896516e+08 | F14: =SUM(F15:F17) -> 2.7851244e+08 | H14: =SUM(H15:H17) -> 4.2057972e+08 | J14: =SUM(J15:J17) -> 4.8424788e+08 | L14: =SUM(L15:L17) -> 1.8740141e+08 | N14: =SUM(N15:N17) -> 2.1823733e+08
B15: ICT services | D15: 27239174 | F15: 1.3326885e+08 | H15: 3.0115375e+08 | J15: 2.3399155e+08 | L15: 1.439184e+08 | N15: 1.5134113e+08
B16: AIGC services | D16: 55495031 | F16: 1.2765868e+08 | H16: 1.1255568e+08 | J16: 2.474397e+08 | L16: 40367489 | N16: 65926942
B17: AI voice services | D17: 46230954 | F17: 17584907 | H17: 6870293.4 | J17: 2816629.7 | L17: 3115522.3 | N17: 969258.55
B18: Standardized and productized AI workforce solutions | D18: 7981170.2 | F18: 8789420.8 | H18: 9069211.8 | J18: 8139870.2 | L18: 4788471.3 | N18: 4660800.3
B19: 全自动内容生产 | J19: 23151796
B20: 小计 | D20: 1.3694633e+08 | F20: 2.8730186e+08 | H20: 4.2964893e+08 | J20: =SUM(J15:J19) -> 5.1553954e+08 | L20: 1.9218989e+08 | N20: 2.2289813e+08
B22: 税金及附加 | D22: 63994.13 | F22: 343189.27 | H22: 710292.49 | L22: 194936.36 | N22: 230.93
B24: 合计 | D24: 1.3701032e+08 | F24: 2.8764505e+08 | H24: 4.3035922e+08 | L24: 1.9238482e+08 | N24: 2.2289836e+08
D25: 0 | F25: 0 | H25: 0 | J25: 0 | L25: 0 | N25: 0
B28: 毛利率 | D28: 22年度 | F28: 23年度 | H28: 24年度 | J28: 25年度 | L28: 2024年1-6月 | N28: 2025年1-6月
B29: - Customized AI workforce solutions | D29: 0.38180631 | F29: 0.43363898 | H29: 0.36649337 | J29: =1-J14/(-J5) -> 0.33394034 | L29: 0.36708304 | N29: 0.37759621
B30: - Standardized and productized AI workforce solutions | D30: =(D9+D18)/D9 -> 0.43782616 | F30: =(F9+F18)/F9 -> 0.80658259 | H30: =(H9+H18)/H9 -> 0.65109367 | J30: =(J9+J18)/J9 -> 0.2170685 | L30: =(L9+L18)/L9 -> 0.63363698 | N30: =(N9+N18)/N9 -> 0.33067902
B31: 全自动内容生产 | J31: =(J10+J19)/J10 -> 0.54946831

Sheet PL4
C2: 其他收益 - 政府补助
C4: 按性质分类 | D4: 2022年 | F4: 2023年 | H4: 2024年 | J4: 202406 | L4: 202506
C5: 稳岗补贴 | D5: -20623.94 | F5: -29086 | H5: -9807 | J5: 0 | L5: 0
C6: 政府补助 | D6: -16604524 | F6: -12430572 | H6: -10000122 | J6: -6562001.4 | L6: -1057609.8
C7: 装修补贴 | D7: -965307.2 | F7: -1053062.4 | H7: -175510.4 | J7: -175510.4 | L7: 0
C8: 合计 | D8: =SUM(D5:D7) -> -17590455 | F8: =SUM(F5:F7) -> -13512720 | H8: =SUM(H5:H7) -> -10185440 | J8: =SUM(J5:J7) -> -6737511.8 | L8: =SUM(L5:L7) -> -1057609.8
C10: 其他收益的政府补助主要包括稳岗补贴、政府补助以及装修补贴。主要以政府补助为主，具体如下： （1）2022年集团的政府补助主要是南京硅基获得的中国（南京）软件谷管理委员会研发费用补贴人民币330万元、房租补贴人民币463万元和南京市雨花台区发展和改革委员会2022年省级现代服务业发展专项资金160万元以及绵阳硅基对绵阳汇鑫发展集团有限公司的销售收入442万元，实际为政府补助。其中，研发费用补贴为政府鼓励企业加大研发投入，对研发投入比达到10%的国家高新技术企业及科技创业家企业，补贴研发费用；房租补贴为软件谷对于入驻公司的房租补贴；发展专项资金主要系政府对集成电路设计企业首轮流片补贴等项目给予支持。 （2）2023年收到的政府补贴主要是硅基昆山获得的昆山经济技术开发区补助款人民币500万元、南京硅基获得的中国（南京）软件谷管理委员会房租补贴人民币243万元和中国（南京）软件谷管理委员会费用产发（2023年度27号文兑现）补助人民币144万元、绵阳硅基获得的绵阳政府招商引资项目的补贴资金人民币200万元。 （3）2024年收到的政府补助主要是昆山经济技术开发区管理委员会对昆山公司完成工商注册的落地奖励300万元和南京硅基获得的南京市雨花台区发展和改革委员会市级工业和信息化专项资金300万元。 （4）2025年上半年收到的政府补助主要系硅基昆山收到昆山市市级机关事务管理中心省文化专项资金补助人民币100万元。
C12: 请补充政府补助清单明细（金额大于PBC）
C14: 其他收益 - 增值税
C16: 按性质分类 | D16: 2022年 | F16: 2023年 | H16: 2024年 | J16: 202406 | L16: 202506
C17: 即征即退增值税 | D17: 0 | F17: -267878.21 | H17: -75791.33 | J17: -72472 | L17: -35249.49
C18: 增值税加计抵减 | D18: -270010.42 | F18: -1814340 | H18: -448406.66 | J18: -448406.66 | L18: 0
C19: 合计 | D19: =SUM(D17:D18) -> -270010.42 | F19: =SUM(F17:F18) -> -2082218.2 | H19: =SUM(H17:H18) -> -524197.99 | J19: =SUM(J17:J18) -> -520878.66 | L19: =SUM(L17:L18) -> -35249.49
C26: 其他收益 - 其他
C28: 按性质分类 | D28: 2022年 | F28: 2023年 | H28: 2024年 | J28: 202406 | L28: 202506
C29: 个税返还 | D29: -111360.2 | F29: -130780.51 | H29: -136418.51 | J29: -138028.92 | L29: -78625.8
C30: 合计 | D30: =SUM(D29:D29) -> -111360.2 | F30: =SUM(F29:F29) -> -130780.51 | H30: =SUM(H29:H29) -> -136418.51 | J30: =SUM(J29:J29) -> -138028.92 | L30: =SUM(L29:L29) -> -78625.8

Sheet PL5
B3: 其他净(收益)/损失 | D3: 22年度 | F3: 23年度 | H3: 24年度 | J3: 2024年1-6月 | L3: 2025年1-6月
D4: a | F4: b | H4: c | J4: d1 | L4: d2
B6: 诉讼费 | D6: 117800 | F6: 0 | H6: 320492.54 | J6: 320492.54
B7: 押金 | D7: 0 | F7: 250 | H7: 551320.44 | J7: 455060.58 | L7: 0
B8: 固定资产处置收益 | D8: 0 | F8: -65069.34 | H8: -17159.68 | J8: -17159.68 | L8: 0
B9: 其他 | D9: 6878.46 | F9: 26937.78 | H9: -176274.06 | J9: -98491.85 | L9: -167407.18
B11: 合计 | D11: =SUM(D6:D9) -> 124678.46 | F11: =SUM(F6:F9) -> -37881.56 | H11: =SUM(H6:H9) -> 678379.24 | J11: =SUM(J6:J9) -> 659901.59 | L11: =SUM(L6:L9) -> -167407.18
D12: =D11-'FY22-25 IFRS（合并）'!G8 -> 0 | F12: =F11-'FY22-25 IFRS（合并）'!I8 -> -4.6566129e-10 | H12: =H11-'FY22-25 IFRS（合并）'!K8 -> 0 | J12: =J11-'FY22-25 IFRS（合并）'!M8 -> -0.01 | L12: =L11-'FY22-25 IFRS（合并）'!O8 -> 0
B15: 请补充

Sheet 三费>>>
A1: Blue: Hard code vale
A2: Black: Calculation
A3: Green: Linked from another tab
A4: Red: Linked from the same tab
B7: Selling and Marketing Expenses
D8: Year ended December 31 | H8: Six months ended June 30 | O8: Year ended December 31 | R8: Six months ended June 30
D9: 2022 | E9: 2023 | F9: 2024 | G9: 2025 | H9: 2024 | I9: 2025 | O9: 2022 | P9: 2023 | Q9: 2024 | R9: 2024 | S9: 2025
B10: Employee benefit expenses | D10: 23303.949 | E10: 30540.088 | F10: 30891.563 | G10: 19613 | H10: 16260.771 | I10: 9812.3171 | L10: 研发/销售人员招聘 | M10: Employee benefit expenses | O10: =SUM(O11:O13) -> 97326.876 | P10: =SUM(P11:P13) -> 100459.09 | Q10: =SUM(Q11:Q13) -> 86633.257 | R10: =SUM(R11:R13) -> 45076.535 | S10: =SUM(S11:S13) -> 30409.624
C11: ESOP | D11: =[1]ESOP!K25/1000 -> 401.50492 | E11: =[1]ESOP!L25/1000 -> 917.10076 | F11: =[1]ESOP!N25/1000 -> 11298.321 | G11: 11279.704 | H11: =[1]ESOP!M25/1000 -> 5648.0603 | I11: =[1]ESOP!O25/2/1000 -> 5639.8522 | N11: ESOP | O11: =D11+D25+D41 -> 6172.2267 | P11: =E11+E25+E41 -> 7834.985 | Q11: =F11+F25+F41 -> 21479.107 | R11: =H11+H25+H41 -> 10722.643 | S11: =I11+I25+I41 -> 10718.557
C12: Employee benefit expenses | D12: =D10-D11 -> 22902.444 | E12: =E10-E11 -> 29622.987 | F12: =F10-F11 -> 19593.242 | G12: =G10-G11 -> 8333.2957 | H12: =H10-H11 -> 10612.71 | I12: =I10-I11 -> 4172.4649 | N12: Employee benefit expenses | O12: =D12+D26+D42 -> 91154.649 | P12: =E12+E26+E42 -> 92624.103 | Q12: =F12+F26+F42 -> 65154.15 | R12: =H12+H26+H42 -> 34353.892 | S12: =I12+I26+I42 -> 19691.067
B13: Marketing service expenses | D13: 8156.7859 | E13: 14132.193 | F13: 28201.959 | G13: 21325 | H13: 17862.172 | I13: 6659.8749 | N13: Listing Expenses | O13: =D27 -> 0 | P13: =E27 -> 0 | Q13: =F27 -> 0 | R13: =H27 -> 0 | S13: =I27 -> 0
B14: Advertising and promotion expenses | D14: 1043.2823 | E14: 61066.882 | F14: 17783.624 | G14: 10940 | H14: 225.53772 | I14: 3256.9344 | L14: 宣传推广 | M14: Marketing service expenses | O14: =D13 -> 8156.7859 | P14: =E13 -> 14132.193 | Q14: =F13 -> 28201.959 | R14: =H13 -> 17862.172 | S14: =I13 -> 6659.8749
B15: Office, utilities and travelling expenses | D15: 4113.4577 | E15: 3346.1403 | F15: 3238.0681 | G15: 2398 | H15: 1817.6485 | I15: 1082.0211 | M15: Advertising and promotion expenses | O15: =D14 -> 1043.2823 | P15: =E14 -> 61066.882 | Q15: =F14 -> 17783.624 | R15: =H14 -> 225.53772 | S15: =I14 -> 3256.9344
B16: Others | D16: 1894.1463 | E16: 1177.6911 | F16: 2454.2896 | G16: 2140 | H16: 1190.7804 | I16: 982.99067 | M16: Office, utilities and travelling expenses | O16: =D15+D32 -> 10471.615 | P16: =E15+E32 -> 11324.085 | Q16: =F15+F32 -> 8857.6512 | R16: =H15+H32 -> 4624.6168 | S16: =I15+I32 -> 2912.5373
D17: =SUM(D10,D13:D16) -> 38511.621 | E17: =SUM(E10,E13:E16) -> 110262.99 | F17: =SUM(F10,F13:F16) -> 82569.503 | G17: =SUM(G10,G13:G16) -> 56416 | H17: =SUM(H10,H13:H16) -> 37356.909 | I17: =SUM(I10,I13:I16) -> 21794.138 | M17: Professional service fees | O17: =D29 -> 5143.5 | P17: =E29 -> 5375.3938 | Q17: =F29 -> 6098.4992 | R17: =H29 -> 3508.0697 | S17: =I29 -> 4452.1599
C18: 主表check | E18: -0.0064251239 | F18: -0.49660094 | G18: 0 | K18: 委外研发 | L18: 算力采购及租赁 | M18: Technical service fees | O18: =D43 -> 11783 | P18: =E43 -> 74395 | Q18: =F43 -> 108237 | R18: =H43 -> 61176 | S18: =I43 -> 52398
M19: Material expenses | O19: =D45 -> 8434 | P19: =E45 -> 0 | Q19: =F45 -> 0 | R19: =H45 -> 0 | S19: =I45 -> 0
M20: Depreciation and amortization | O20: =D28+D44 -> 13399.461 | P20: =E28+E44 -> 14800.712 | Q20: =F28+F44 -> 12825.954 | R20: =H28+H44 -> 6480.1077 | S20: =I28+I44 -> 3814.9621
B21: Administrative and Other Operating Expenses | M21: Others | O21: =D16+D33+D46 -> 5296.5014 | P21: =E16+E33+E46 -> 6245.0096 | Q21: =F16+F33+F46 -> 5272.3001 | R21: =H16+H33+H46 -> 3068.6882 | S21: =I16+I33+I46 -> 2720.5638
D22: Year ended December 31 | H22: Six months ended June 30 | O22: =SUM(O10,O14:O21) -> 161055.02 | P22: =SUM(P10,P14:P21) -> 287798.36 | Q22: =SUM(Q10,Q14:Q21) -> 273910.24 | R22: =SUM(R10,R14:R21) -> 142021.73 | S22: =SUM(S10,S14:S21) -> 106624.66
D23: 2022 | E23: 2023 | F23: 2024 | G23: 2025 | H23: 2024 | I23: 2025
B24: Employee benefit expenses | D24: 24817.927 | E24: 24063 | F24: 23097.695 | G24: 22287 | H24: 12222.764 | I24: 10490.307 | J24: 10490 | N24: 左右check | O24: =O22-D17-D34-D47 -> 0 | P24: =P22-E17-E34-E47 -> 0 | Q24: =Q22-F17-F34-F47 -> 0 | R24: =R22-H17-H34-H47 -> 0 | S24: =S22-I17-I34-I47 -> 0
C25: ESOP | D25: =[1]ESOP!K24/1000 -> 5630.5233 | E25: =[1]ESOP!L24/1000 -> 5820.3662 | F25: =[1]ESOP!N24/1000 -> 8507.4349 | G25: 8487 | H25: =[1]ESOP!M24/1000 -> 4238.2914 | I25: =[1]ESOP!O24/2/1000 -> 4243.6898
C26: Employee benefit expenses | D26: =D24-D25 -> 19187.404 | E26: =E24-E25 -> 18242.634 | F26: =F24-F25 -> 14590.26 | G26: =G24-G25 -> 13800 | H26: =H24-H25 -> 7984.4729 | I26: =I24-I25 -> 6246.6173 | N26: 原版本三费加总check | O26: =O22+#REF!+#REF!+#REF! -> #REF! | P26: =P22+#REF!+#REF!+#REF! -> #REF! | Q26: =Q22+#REF!+#REF!+#REF! -> #REF! | R26: =R22+#REF!+#REF!+#REF! -> #REF! | S26: =S22+#REF!+#REF!+#REF! -> #REF!
B28: Depreciation and amortization | D28: 8401.4612 | E28: 7635.7121 | F28: 4608.9542 | G28: 3204 | H28: 3215.1077 | I28: 1032.9621
B29: Professional service fees | D29: 5143.5 | E29: 5375.3938 | F29: 6098.4992 | G29: 23110 | H29: 3508.0697 | I29: 4452.1599 | O29: =O20-SUM(#REF!) -> #REF! | P29: =P20-SUM(#REF!) -> #REF! | Q29: =Q20-SUM(#REF!) -> #REF! | R29: =R20-SUM(#REF!) -> #REF! | S29: =S20-SUM(#REF!) -> #REF!
C30: Listing Expenses | F30: =#REF! -> #REF! | G30: 18328 | H30: =#REF! -> #REF! | I30: =#REF! -> #REF!
C31: Remaing Professional service fees | D31: =D29-D30 -> 5143.5 | E31: =E29-E30 -> 5375.3938 | F31: =F29-F30 -> #REF! | G31: =G29-G30 -> 4782 | H31: =H29-H30 -> #REF! | I31: =I29-I30 -> #REF!
B32: Office, utilities, traveling and entertainment expenses | D32: 6358.157 | E32: 7977.9443 | F32: 5619.5831 | G32: 5344 | H32: 2806.9683 | I32: 1830.5161
B33: Others | D33: 2389.3551 | E33: 2914.3184 | F33: 1787.0105 | G33: 1707 | H33: 813.90784 | I33: 485.5731
D34: =SUM(D24,D28:D29,D32:D33) -> 47110.4 | E34: =SUM(E24,E28:E29,E32:E33) -> 47966.369 | F34: =SUM(F24,F28:F29,F32:F33) -> 41211.742 | G34: =SUM(G24,G28:G29,G32:G33) -> 55652 | H34: =SUM(H24,H28:H29,H32:H33) -> 22566.818 | I34: =SUM(I24,I28:I29,I32:I33) -> 18291.518 | O34: 8401
C35: 主表check | E35: -0.63088 | F35: 0.74157 | G35: 0 | O35: 4998
D36: =D28+D44 -> 13399.461 | E36: =E28+E44 -> 14800.712 | F36: =F28+F44 -> 12825.954
B37: Research and Development Expenses
D38: Year ended December 31 | H38: Six months ended June 30
D39: 2022 | E39: 2023 | F39: 2024 | G39: 2025 | H39: 2024 | I39: 2025
B40: Employee benefit expenses | D40: 49205 | E40: 45856 | F40: 32644 | G40: 19281 | H40: 16593 | I40: 10107 | J40: =G40/$G$47 -> 0.1180479
C41: ESOP | D41: =[1]ESOP!K26/1000 -> 140.19848 | E41: =[1]ESOP!L26/1000 -> 1097.5181 | F41: =[1]ESOP!N26/1000 -> 1673.3519 | G41: 1670 | H41: =[1]ESOP!M26/1000 -> 836.29182 | I41: =[1]ESOP!O26/2/1000 -> 835.01486 | J41: =G41/$G$47 -> 0.010224573
C42: Employee benefit expenses | D42: =D40-D41 -> 49064.802 | E42: =E40-E41 -> 44758.482 | F42: =F40-F41 -> 30970.648 | G42: =G40-G41 -> 17611 | H42: =H40-H41 -> 15756.708 | I42: =I40-I41 -> 9271.9851 | J42: =G42/$G$47 -> 0.10782333
B43: Technical service fees | D43: 11783 | E43: 74395 | F43: 108237 | G43: 138556 | H43: 61176 | I43: 52398 | J43: =G43/$G$47 -> 0.84830897
B44: Depreciation and amortization | D44: 4998 | E44: 7165 | F44: 8217 | G44: 4092 | H44: 3265 | I44: 2782 | J44: =G44/$G$47 -> 0.025053266
B45: Material expenses | D45: 8434 | E45: 0 | F45: 0 | G45: 0 | H45: 0 | I45: 0 | J45: =G45/$G$47 -> 0
B46: Others | D46: 1013 | E46: 2153 | F46: 1031 | G46: 1403 | H46: 1064 | I46: 1252 | J46: =G46/$G$47 -> 0.008589866
D47: =SUM(D40,D43:D46) -> 75433 | E47: =SUM(E40,E43:E46) -> 129569 | F47: =SUM(F40,F43:F46) -> 150129 | G47: =SUM(G40,G43:G46) -> 163332 | H47: =SUM(H40,H43:H46) -> 82098 | I47: =SUM(I40,I43:I46) -> 66539 | J47: =G47/$G$47 -> 1
C48: 主表check | E48: 0 | F48: 0 | G48: 0
B49: ESOP CHECK | D49: =D41+D25+D11-[1]ESOP!K28/1000 -> 0 | E49: =E41+E25+E11-[1]ESOP!L28/1000 -> 0 | F49: =F41+F25+F11-[1]ESOP!N28/1000 -> -4.3655746e-11 | H49: =H41+H25+H11-[1]ESOP!M28/1000 -> 0 | I49: =I41+I25+I11-[1]ESOP!O28/1000/2 -> 1.6370905e-11
B50: TOTAL CHECK | D50: =D47+D34+D17+#REF!+#REF!+#REF! -> #REF! | E50: =E47+E34+E17+#REF!+#REF!+#REF! -> #REF! | F50: =F47+F34+F17+#REF!+#REF!+#REF! -> #REF! | H50: =H47+H34+H17+#REF!+#REF!+#REF! -> #REF! | I50: =I47+I34+I17+#REF!+#REF!+#REF! -> #REF!

Sheet PL6
C5: 销售费用 | D5: 2022.1-12 | F5: 2023.1-12 | H5: 2024.1-12 | J5: 2025.1-12 | L5: 2024.1-6 | N5: 2025.1-6
D7: a | F7: b | H7: c | J7: d | L7: d | N7: e
C8: 员工福利开支 | D8: 22902444 | F8: 29622987 | H8: 19593242 | J8: 8333118.8 | L8: 10612710 | N8: 4879471.9
C9: 渠道費用 | D9: 6683624.7 | F9: 12406844 | H9: 25867472 | J9: 10446067 | L9: 16299441 | N9: 11801574
C10: 推广及广告开支 | D10: 1043282.3 | F10: 61066882 | H10: 14566643 | J10: 10939820 | L10: 225537.72 | N10: 3256934.4
C11: 服务费及其他咨询费用 | D11: 1473161.2 | F11: 1555077.4 | H11: 2334487.1 | J11: 10878828 | L11: 1562730.8 | N11: 4718917.8
C12: 营销及差旅开支 | D12: 4113457.6 | F12: 3346140.3 | H12: 3238068.1 | J12: 2397880.4 | L12: 1817648.5 | N12: 1082021.1
C13: 股份支付开支 | D13: 0 | F13: 5016443 | H13: 5340900.4 | J13: 11279704 | L13: 2670194.9 | N13: 2664852.5
C14: 其他 | D14: 1894146.3 | F14: 2903039.9 | H14: 4788776.8 | J14: 2140554 | L14: 2753511.2 | N14: 1904490.2
C16: 合计 | D16: 38110116 | F16: 1.0986149e+08 | H16: 84743936 | J16: 56415972 | L16: 38445226 | N16: 22879865
C17: Check: | D17: =ROUND(D16-'FY22-25 IFRS（合并）'!G9,0) -> 0 | F17: =ROUND(F16-'FY22-25 IFRS（合并）'!I9,0) -> 0 | H17: =ROUND(H16-'FY22-25 IFRS（合并）'!K9,0) -> 0 | J17: =J16-'[1]FY22-25 IFRS（合并）'!$AB$9 -> 0 | L17: =ROUND(L16-'FY22-25 IFRS（合并）'!M9,0) -> 0 | N17: =ROUND(N16-'FY22-25 IFRS（合并）'!O9,0) -> 0
C53: 请补充按招股书口径分类的数字

Sheet PL8
F5: 2022年 | H5: 2023年 | J5: 2024年 | L5: 2025年 | N5: 2024年1-6月 | P5: 2025年1-6月
F6: PRC审定数 | H6: PRC审定数 | J6: PRC审定数 | L6: PRC审定数 | N6: PRC审定数 | P6: PRC审定数
C8: 职工薪酬 | F8: 49205157 | H8: 45855549 | J8: 32643748 | L8: 19281285 | N8: 16592855 | P8: 10106788
C9: -工资 | F9: 44029377 | H9: 38048425 | J9: 27357678 | L9: 17680439 | N9: 15107505 | P9: 9322187.9
C10: -奖金 | F10: 111725 | H10: 3499269.4 | J10: 867233.75 | L10: 22000 | P10: 0
C11: -社保 | F11: 3560368.4 | H11: 2954022.9 | J11: 3940144.1 | L11: 1115001.5 | N11: 1140505.4 | P11: 537330.28
C12: -公积金 | F12: 1503686.5 | H12: 1353831.1 | J12: 478691.7 | L12: 463844.24 | N12: 344845 | P12: 247270
C13: 技术服务费 | F13: 20219135 | H13: 74396938 | J13: 1.0996728e+08 | L13: 1.3855578e+08 | N13: 61177347 | P13: 52398290
C14: 研发设备折旧 | F14: 481872.89 | H14: 2823599.5 | J14: 2276078.1 | L14: 4091593 | N14: 1006542.8 | P14: 1475541.4
C15: 无形资产摊销 | F15: 419740.9 | H15: 244793.81 | J15: 115688.6 | L15: 0 | N15: 209823 | P15: 0
C16: 研发知识产权费 | F16: 514662.5 | H16: 959089.03 | J16: 1012929 | L16: 698864.28 | N16: 209830.42 | P16: 417471.04
C17: 研发公共交通费 | F17: 111764.24 | H17: 95874.4 | J17: 17990.6 | L17: 0 | N17: 17990.6 | P17: 0
C18: 软件开发费 | F18: 1728.91 | H18: 0 | J18: 0 | L18: 0 | N18: 0 | P18: 0
C19: 研发材料 | F19: 7566.99 | H19: 0 | J19: 0 | L19: 0 | N19: 0 | P19: 0
C20: 房租 | F20: 4095534.5 | H20: 4095534.5 | J20: 4095534.5 | L20: 704926.34 | N20: 2047767.2 | P20: 1305853.9
C21: 股票成本 | F21: 140198.48 | H21: 1097518.1 | J21: 0 | L21: 0 | N21: 836291.82 | P21: 835014.86
C22: 其他 | F22: 0 | H22: 0 | J22: 0 | L22: 0 | N22: 0 | P22: 0
... C24: 合计 | F24: 75433068 | H24: 1.295689e+08 | J24: 1.5012925e+08 | L24: 1.6333245e+08 | N24: 82098448 | P24: 66538960
C25: check | F25: =F24-'FY22-25 IFRS（合并）'!G11 -> -0.0032132268 | H25: =H24-'FY22-25 IFRS（合并）'!I11 -> 0 | J25: =J24-'FY22-25 IFRS（合并）'!K11 -> -0.00053980947 | L25: =L24-'[1]FY22-25 IFRS（合并）'!$AB$11 -> 0 | N25: =N24-'FY22-25 IFRS（合并）'!M11 -> -0.0013011694 | P25: =P24-'FY22-25 IFRS（合并）'!O11 -> 0
C56: 请补充按招股书口径分类的数字

Sheet PL9&BS4
C4: 合同资产 | E4: 44926 | G4: 45291 | I4: 45657 | K4: 46022 | M4: 45838
E5: a | G5: b | I5: c | K5: c | M5: d
C6: 原值 | E6: 507784.39 | G6: 5602907.9 | I6: 8141850.4 | K6: 21220336 | M6: 7488285.7
C7: 坏账准备 | E7: -20649.762 | G7: -227850.08 | I7: -330140.4 | K7: -849497.65 | M7: -302128.8
C9: 小计 | E9: =SUM(E6:E7) -> 487134.63 | G9: =SUM(G6:G7) -> 5375057.8 | I9: =SUM(I6:I7) -> 7811710 | K9: =SUM(K6:K8) -> 20370838 | M9: =SUM(M6:M7) -> 7186156.9
E10: =E9-'FY22-25 IFRS（合并）'!G38-'FY22-25 IFRS（合并）'!G47 -> -0.0022035593 | G10: =G9-'FY22-25 IFRS（合并）'!I38-'FY22-25 IFRS（合并）'!I47 -> -0.00089157 | I10: =I9-'FY22-25 IFRS（合并）'!K38-'FY22-25 IFRS（合并）'!K47 -> 0.0049911498 | K10: =K9-'FY22-25 IFRS（合并）'!Q38-'FY22-25 IFRS（合并）'!Q47 -> 115622.33 | M10: =M9-'FY22-25 IFRS（合并）'!O38-'FY22-25 IFRS（合并）'!O47 -> 0.0049647014
C13: 请更新合同资产金额

Sheet PL7
C4: 管理费用 | E4: 2022.1-12 | G4: 2023.1-12 | I4: 2024.1-12 | K4: 2025.1-12 | M4: 2024.1-6 | O4: 2025.1-6
E6: a | G6: b | I6: c | K6: d | M6: d | O6: e
C7: 员工福利开支 | E7: 19187404 | G7: 18242634 | I7: 14590260 | K7: 13799376 | M7: 7984472.9 | O7: 6246617.3
C8: 折旧与摊销 | E8: 8401461.2 | G8: 7635712.1 | I8: 4608954.2 | K8: 3203936.4 | M8: 3215107.7 | O8: 1032962.1
C9: 专业服务及其他咨询费 | E9: 5143500 | G9: 5375393.8 | I9: 6098499.2 | K9: 23109978 | M9: 3508069.7 | O9: 4452159.9
C10: 办公费 | E10: 5108258.5 | G10: 6273689.1 | I10: 4447102.3 | K10: 4335878 | M10: 2408344.5 | O10: 1521563.4
C11: 差旅及招待费 | E11: 1249898.5 | G11: 1704255.2 | I11: 1172480.8 | K11: 1008617.6 | M11: 398623.77 | O11: 308952.7
C12: 股份支付开支 | E12: 6032028.2 | G12: 6221871.1 | I12: 6333002.8 | K12: 8487379.5 | M12: 3149975.3 | O12: 3157962.5
C13: 其他 | E13: 2389355.1 | G13: 2914318.4 | I13: 1787010.5 | K13: 1706829 | M13: 813907.84 | O13: 485573.1
C15: 合计 | E15: 47511905 | G15: 48367874 | I15: 39037309 | K15: =SUM(K7:K13) -> 55651994 | M15: 21478502 | O15: 17205791
C16: Check： | E16: =ROUND(E15-'FY22-25 IFRS（合并）'!G10,0) -> 0 | G16: =ROUND(G15-'FY22-25 IFRS（合并）'!I10,0) -> 0 | I16: =ROUND(I15-'FY22-25 IFRS（合并）'!K10,0) -> 0 | K16: =ROUND(K15-'[1]FY22-25 IFRS（合并）'!$AB$10,0) -> 0 | M16: =ROUND(M15-'FY22-25 IFRS（合并）'!M10,0) -> 0 | O16: =ROUND(O15-'FY22-25 IFRS（合并）'!O10,0) -> 0
C52: 请补充按招股书口径分类的数字

Sheet PL10
C4: 财务收入 | E4: 2022年度 | G4: 2023年度 | I4: 2024年度 | K4: 2025年度 | M4: 2024年1-6月 | O4: 2025年1-6月
E5: a | G5: b | I5: c | K5: d | M5: d1 | O5: d2
C6: 利息收入 | E6: -9458184.8 | G6: -4606419.3 | I6: -2239349.8 | K6: -856870.88 | M6: -623760.44 | O6: -464884.35
C8: 合计 | E8: -9458184.8 | G8: -4606419.3 | I8: -2239349.8 | K8: -856870.88 | M8: -623760.44 | O8: -464884.35
C9: Check： | E9: =ROUND(E8-'FY22-25 IFRS（合并）'!G14,0) -> 0 | G9: =ROUND(G8-'FY22-25 IFRS（合并）'!I14,0) -> 0 | I9: =ROUND(I8-'FY22-25 IFRS（合并）'!K14,0) -> 0 | K9: =ROUND('[1]FY22-25 IFRS（合并）'!$AB$14-K8,0) -> 0 | M9: =ROUND(M8-'FY22-25 IFRS（合并）'!M14,0) -> 0 | O9: =ROUND(O8-'FY22-25 IFRS（合并）'!O14,0) -> 0
C11: 财务成本 | E11: 2022年度 | G11: 2023年度 | I11: 2024年度 | K11: 2025年度 | M11: 2024年1-6月 | O11: 2025年1-6月
E12: a | G12: b | I12: c | K12: d | M12: d1 | O12: d2
C13: 租赁利息 | E13: 759096.24 | G13: 435137.11 | I13: 239820.09 | K13: 143669.04 | M13: 158049.15 | O13: 99442.49
C14: 其他 | E14: 0 | G14: 0 | I14: 0 | K14: 0 | M14: 0 | O14: 0
C16: 合计 | E16: 759096.24 | G16: 435137.11 | I16: 239820.09 | K16: 143669.04 | M16: 158049.15 | O16: 99442.49
C17: Check： | E17: =ROUND(E16-'FY22-25 IFRS（合并）'!G15,0) -> 0 | G17: =ROUND(G16-'FY22-25 IFRS（合并）'!I15,0) -> 0 | I17: =ROUND(I16-'FY22-25 IFRS（合并）'!K15,0) -> 0 | K17: =K16-'FY22-25 IFRS（合并）'!Q15 -> 0 | M17: =ROUND(M16-'FY22-25 IFRS（合并）'!M15,0) -> 0 | O17: =ROUND(O16-'FY22-25 IFRS（合并）'!O15,0) -> 0

Sheet PL11
A3: 2 | B3: 长期股权投资Movement | F3: 211231余额 | G3: 本年注资Cash out | H3: 本年退资Cash in | I3: 本年确认损益 | J3: 221231余额 | L3: 221231余额 | M3: 本年注资Cash out | N3: 本年退资Cash in | O3: 本年确认损益 | P3: 231231余额 | R3: 231231余额 | S3: 本年注资Cash out | T3: 本年退资Cash in | U3: 本年确认损益 | V3: 241231余额 | X3: 231231余额 | Y3: 本年注资Cash out | Z3: 本年退资Cash in | AA3: 本年确认损益 | AB3: 240630余额 | AD3: 241231余额 | AE3: 本年注资Cash out | AF3: 本年退资Cash in | AG3: 本年确认损益 | AH3: 250630余额
B4: 母公司对子公司投资：
B5: 南京硅信智能科技有限公司 | F5: 2000000 | G5: 0 | H5: 0 | I5: 0 | J5: 2000000 | L5: 2000000 | M5: 0 | N5: 0 | O5: 0 | P5: 2000000 | R5: 2000000 | S5: 0 | T5: 0 | U5: 0 | V5: 2000000 | X5: 2000000 | Y5: 0 | Z5: 0 | AA5: 0 | AB5: 2000000 | AD5: 2000000 | AE5: 0 | AF5: 0 | AG5: 0 | AH5: 2000000
B6: 硅基（昆山）智能科技有限公司 | F6: 0 | G6: 0 | H6: 0 | I6: 0 | J6: 0 | L6: 0 | M6: 12000000 | N6: 0 | O6: 0 | P6: 12000000 | R6: 12000000 | S6: 88000000 | T6: 0 | U6: 0 | V6: 100000000 | X6: 12000000 | Y6: 88000000 | Z6: 0 | AA6: 0 | AB6: 100000000 | AD6: 100000000 | AE6: 0 | AF6: 0 | AG6: 0 | AH6: 100000000
B7: 嘉兴硅基智能科技有限公司 | X7: 0 | Y7: 200000000 | AB7: 200000000 | AD7: 0 | AE7: 200000000 | AH7: 200000000
F8: 2000000 | G8: 0 | H8: 0 | I8: 0 | J8: 2000000 | L8: 2000000 | M8: 12000000 | N8: 0 | O8: 0 | P8: 14000000 | R8: 14000000 | S8: 88000000 | T8: 0 | U8: 0 | V8: 102000000 | X8: 14000000 | Y8: 288000000 | Z8: 0 | AA8: 0 | AB8: 302000000 | AD8: 102000000 | AE8: 200000000 | AF8: 0 | AG8: 0 | AH8: 302000000
B9: JV：
B10: 浙江硅梦 - 杭州硅羽智能科技有限公司 | F10: 0 | G10: 0 | H10: 0 | I10: 0 | J10: 0 | L10: 0 | M10: 500000 | N10: -395959.18 | O10: -104040.82 | P10: 0 | R10: 0 | S10: 0 | T10: 0 | U10: 0 | V10: 0 | X10: 0 | Y10: 0 | Z10: 0 | AA10: 0 | AB10: 0 | AD10: 0 | AE10: 0 | AF10: 0 | AG10: 0 | AH10: 0
B11: 南京硅基 - 杭州谦语智能科技有限公司 | F11: 0 | G11: 0 | H11: 0 | I11: 0 | J11: 0 | L11: 0 | M11: 1000000 | N11: 0 | O11: -1000000 | P11: 0 | R11: 0 | S11: 0 | T11: 0 | U11: 0 | V11: 0 | X11: 0 | Y11: 0 | Z11: 0 | AA11: 0 | AB11: 0 | AD11: 0 | AE11: 0 | AF11: 0 | AG11: 0 | AH11: 0
B12: 硅基昆山 - 硅语（昆山）智能科技有限公司 | F12: 0 | G12: 0 | H12: 0 | I12: 0 | J12: 0 | L12: 0 | M12: 0 | N12: 0 | O12: 0 | P12: 0 | R12: 0 | S12: 200000 | T12: 0 | U12: -26695.484 | V12: 173304.52 | X12: 0 | Y12: 0 | Z12: 0 | AA12: 0 | AB12: 0 | AD12: 173304.52 | AE12: 190000 | AF12: 0 | AG12: -164418.73 | AH12: 198885.79
F13: 0 | G13: 0 | H13: 0 | I13: 0 | J13: 0 | L13: 0 | M13: 1500000 | N13: -395959.18 | O13: -1104040.8 | P13: 0 | R13: 0 | S13: 200000 | T13: 0 | U13: -26695.484 | V13: 173304.52 | X13: 0 | Y13: 0 | Z13: 0 | AA13: 0 | AB13: 0 | AD13: 173304.52 | AE13: 190000 | AF13: 0 | AG13: -164418.73 | AH13: 198885.79
B15: 合并层面合计 | F15: 0 | G15: 0 | H15: 0 | I15: 0 | J15: 0 | L15: 0 | M15: 1500000 | N15: -395959.18 | O15: -1104040.8 | P15: 0 | R15: 0 | S15: 200000 | T15: 0 | U15: -26695.484 | V15: 173304.52 | X15: 0 | Y15: 0 | Z15: 0 | AA15: 0 | AB15: 0 | AD15: 173304.52 | AE15: 190000 | AF15: 0 | AG15: -164418.73 | AH15: 198885.79
B16: 母公司层面合计 | F16: 2000000 | G16: 0 | H16: 0 | I16: 0 | J16: 2000000 | L16: 2000000 | M16: 13000000 | N16: 0 | O16: -1000000 | P16: 14000000 | R16: 14000000 | S16: 88000000 | T16: 0 | U16: 0 | V16: 102000000 | X16: 14000000 | Y16: 288000000 | Z16: 0 | AA16: 0 | AB16: 302000000 | AD16: 102000000 | AE16: 200000000 | AF16: 0 | AG16: 0 | AH16: 302000000

Sheet PL12回购权会计处理
B1: =[1]Lead!B1 -> 南京硅基智能科技集团股份有限公司 | H1: 索引号：
B2: =[1]Lead!B2 -> 截至2024年12月31日
B3: 以人民币表示
B4: 借 / (贷)
B5: 历史沿革及历轮融资情况
A8: 1 | B8: 回购事件
B9: C轮融资的股东协议（R1-9-2.）规定了回购事件，列示如下：
B10: 9.2 回购事件 9.2.1 就B轮投资者、B+轮投资者和C轮投资者而言，本第9条所述的“回购事件”包括： (1) 创始股东或集团公司在任何重大方面违反了本协议、C轮股权转让及增资协议（仅就C轮投资者而言）或B+轮增资协议（仅就B+轮投资者而言）或B轮增资及股权转让协议（仅就B轮投资者而言）规定的任何陈述、保证、承诺或其他义务，且该等违反就其单一事件而言或与其他事件综合考虑而言对集团公司将产生重大不利变更（定义见B+轮增资协议或B轮增资及股权转让协议，视情况而定），或对C轮投资者或B轮投资者或B+轮投资者造成重大不利影响（视情况而定）； (2) 2024年12月31日之前公司仍未能完成合格的首次公开发行； (3) 创始股东违反了其与集团公司签署的竞业禁止协议或在本协议项下做出的竞业禁止承诺； (4) 创始股东主动终止与集团公司的劳动合同或因严重违反法律法规、公司规章制度被集团公司解职； (5) 集团公司出现严重违反法律、法规的规定，影响集团公司正常经营，或导致集团公司被吊销营业执照、被主管机关责令停业或进入破产程序； (6) 创始股东持有的限制性股权的注册资本金额低于本协议签署日创始股东持有的注册资本金额（不包括非限制股权对应的注册资本）的50%（即人民币2,123,998.85元）； (7) 有其他股东要求公司和/或管理层股东根据本第9条、公司章程或《公司法》回购其持有的公司股权。 对于腾讯而言，其回购事件还包括如下事件：集团公司或创始股东违反本协议第14条（限制性交易）或第15条（业务合作）的规定。 为免疑义，对上述第（4）项和第（6）项回购事件而言，B轮投资者、B+轮投资者和C轮投资者分别有权就其自身的回购权予以豁免；在C轮投资者和/或B轮投资者和/或B+轮投资者予以豁免的情况下，则该事件不触发予以豁免的投资者所享有的回购权。如果腾讯因集团公司或创始股东违反本协议第14条（限制性交易）或第15条（业务合作）的规定行使其回购权，C轮投资者（腾讯除外）和B+轮投资者不得依据上述第（7）项要求公司回购其持有的公司股权。 9.2.2 各投资者确认，对于除Pre-A轮投资者以外的在先投资者而言，其回购事件包括第9.2.1（2）项，第9.2.1（6）项且未能征得该等在先投资者的豁免，创始股东违反了第12条（竞业禁止承诺），创始股东主动 终止与集团公司的劳动合同或因严重违反法律法规、公司规章制度被集团公司解职，集团公司出现严重违反法律、法规的规定影响集团公司正常经营、或导致集团公司被吊销营业执照、被主管机关责令停业或进入破产程序，以及创始股东或集团公司在任何重大方面违反了相应轮次投资协议及/或本协议规定的任何陈述、保证、承诺或其他义务并且对该轮次投资者造成重大不利影响或对集团公司造成重大不利变更；在不影响腾讯根据第9.2.1条享有的回购权的前提下，对于Pre-A轮投资者而言，其回购事件适用第9.2.1（2）项，第9.2.1（6）项且未能征得该Pre-A轮投资者的豁免，以及创始股东违反了本协议第12条（竞业禁止承诺）。 9.3 约定价格 9.3.1 就C轮投资者持有的C轮股权而言，本协议第9条所述的约定价格为以下价格较高者： (1) 按照以下公式计算出的金额： A × P × (1+8%×N) + D；其中： A为C轮投资者的回购股权所代表的注册资本额； P为C轮投资者适用的C轮股权的每股原价格（受限于第5.2条之调整）； N为自C轮投资者针对其所持有C轮股权支付投资款（定义见C轮股权转让及增资协议）之日直至约定价格完全支付之日的天数除以365所得的数字； D为C轮投资者应获得的公司已宣布但尚未支付的股息红利； 或者 (2) 回购时C轮投资者所持有的C轮股权所对应的公司经审计的净资产值（该净资产值应依据由投资者认可的会计师事务所出具的审计合并财务报告确定）。 9.3.2 就B+轮投资者持有的B+轮股权而言，本协议第9条所述的约定价格为以下价格较高者： (1) 按照以下公式计算出的金额： A × P × (1+8%×N) + D；其中： A为B+轮投资者的回购股权所代表的注册资本额； P为B+轮投资者适用的B+轮股权的每股原价格（受限于第5.2条之调整）； N为自B+轮投资者针对其所持有股权支付投资款（定义见B+轮增资协议）之日直至约定价格完全支付之日的天数除以365所得的数字； D为B+轮投资者应获得的公司已宣布但尚未支付的股息红利； 或者 (2) 回购时B+轮投资者所持有的B+轮股权所对应的公司经审计的净资产值（该净资产值应依据由投资者认可的会计师事务所出具的审计合并财务报告确定）。 9.3.3 就B轮投资者持有的B轮股权而言，本第9条所述的约定价格是指按照以下公式计算出的金额： A × P × (1+12%×N)；其中： A为B轮投资者的回购股权所代表的注册资本额； P为B轮投资者适用的B轮股权的每股原价格（受限于第5.2条之调整）； N为自B轮投资者针对其所持有的B轮股权支付投资款或首期转让对价（定义见B轮增资及股权转让协议）之日直至约定价格完全支付之日的天数除以365所得的数字。 9.3.4 就在先投资者（合称“前轮次回购权人”）持有的A++轮股权、A+轮股权、A轮股权或Pre-A轮股权而言，本第9条所述的约定价格是指按照以下公式计算出的金额： A × P × (1+8%×N)；其中： A为前轮次回购权人的回购股权所代表的注册资本额； P为前轮次回购权人适用的相应轮次股权的每股原价格（受限于第5.2条之调整）； N为自前轮次回购权人就相应轮次股权投资款的支付日直至约定价格完全支付之日的天数除以365所得的数字。
A98: 2 | B98: 特殊权利解除
B99: 2024年12月31日签订的股东协议之补充协议的条款约定： 2.1 各方分别且不连带地同意，以下C轮股东协议约定自公司股改基准日前一日起自动终止： 1) C 轮股东协议第9 条中关于公司承担回购义务（包含公司支付回购价款、约定价格和相应利息的义务、实质构成公司回购义务的相关约定）约定。为免疑义，C 轮股东协议第9 条项下除公司承担回购义务部分之外的其他各方之间 的约定的终止应当适用本协议第2.2条和第2.3条；
A105: 3 | B105: 会计处理
B106: 确认金融负债
B108: 2023年12月31日
B109: 借： | C109: 银行存款 | D109: ='[1]M4.3.1 回购权价值计算'!S106 -> 675894
B110: 借： | C110: RE | D110: ='[1]M4.3.1 回购权价值计算'!S107 -> 400333.09
B111: 借： | C111: PL | D111: ='[1]M4.3.1 回购权价值计算'!S108 -> 310083.15
B112: 贷： | C112: redemption liability | D112: ='[1]M4.3.1 回购权价值计算'!S109 -> -1386310.2
B114: 2024年11月30日
B115: 借： | C115: 银行存款 | D115: ='[1]M4.3.1 回购权价值计算'!M151 -> 675894
B116: 借： | C116: RE | D116: ='[1]M4.3.1 回购权价值计算'!M152 -> 710416.23
B117: 借： | C117: PL | D117: ='[1]M4.3.1 回购权价值计算'!M153 -> 407229.77
B118: 贷： | C118: redemption liability | D118: ='[1]M4.3.1 回购权价值计算'!M154 -> -1793540
B120: 2024年11月30日
B121: 借： | C121: 银行存款 | D121: ='[1]M4.3.1 回购权价值计算'!M151 -> 675894
B122: 借： | C122: RE | D122: ='[1]M4.3.1 回购权价值计算'!M152 -> 710416.23
B123: 借： | C123: PL | D123: ='[1]M4.3.1 回购权价值计算'!M153 -> 407229.77
B124: 贷： | C124: redemption liability | D124: ='[1]M4.3.1 回购权价值计算'!M154 -> -1793540
B126: 终止金融负债
B128: 2024年11月30日
B129: 借： | C129: Capital reserve | D129: ='[1]M4.3.1 回购权价值计算'!M162 -> -1793540
B130: 贷： | C130: redemption liability | D130: ='[1]M4.3.1 回购权价值计算'!M163 -> 1793540

Sheet PL12.1回购权价值计算
B1: 南京硅基智能科技集团股份有限公司
B2: 截至2024年12月31日 | L2: =[1]Lead!F2 -> 索引号：
B3: 以人民币表示 | L3: =[1]Lead!F3 -> 编制人： | M3: =[1]Lead!G3 -> TS
B4: 借 / (贷) | L4: =[1]Lead!F4 -> 编制日期： | M4: =[1]Lead!G4 -> 45919
B5: 历次增资细节测试
B7: 对于历次增资，项目组对公司收款情况执行了细节测试 | I7: 简单测算回购
I8: 44155 | J8: 44196 | K8: 44561 | L8: 44926 | M8: 45291 | N8: 45626
B9: 轮次 | C9: 股东 | D9: 出资额 | E9: 水单号 | F9: 水单金额 | G9: 付款时间 | H9: 付款单位
B10: 设立 | C10: 乐慧玲 | D10: 81200 | E10: 17R4005495787 | F10: 31200 | G10: 42972 | H10: 乐慧玲
E11: 17R6005533100 | F11: 50000 | G11: 42972 | H11: 乐慧玲
B12: 设立 | C12: 宋伟 | D12: 18800 | E12: 17R5005566758 | F12: 18800 | G12: 42972 | H12: 宋伟
B13: 设立 | C13: 好望角 | D13: 12315.27 | E13: 18R6007405520 | F13: 12315.27 | G13: 43385 | H13: 杭州好望角越航投资合伙企业（有限合伙）
B14: 设立 | C14: 和君资本 | D14: 7044.33 | E14: 18R5007724608 | F14: 7044.33 | G14: 43396 | H14: 苏州和益投资合伙企业（有限合伙）
B15: 设立 | C15: 张大勇 | D15: 3793.1 | E15: 18R0007369273 | F15: 3793.1 | G15: 43392 | H15: 张大勇
B16: PreA | C16: 司马华鹏 | D16: 2500000 | E16: 17R0007657191 | F16: 1000000 | G16: 43054 | H16: 司马华鹏 | I16: =$F16*(1+8%*DATEDIF($G16,$I$8,"d")/365) -> 1241315.1 | J16: =$F16*(1+8%*DATEDIF($G16,$J$8,"d")/365) -> 1250301.4 | K16: =$F16*(1+8%*DATEDIF($G16,$K$8,"d")/365) -> 1330301.4 | L16: =$F16*(1+8%*DATEDIF($G16,$L$8,"d")/365) -> 1410301.4 | M16: =$F16*(1+8%*DATEDIF($G16,$M$8,"d")/365) -> 1490301.4 | N16: =$F16*(1+8%*DATEDIF($G16,$N$8,"d")/365) -> 1563726 | O16: =K16-F16 -> 330301.37
E17: 17R8007847688 | F17: 1500000 | G17: 43062 | H17: 司马华鹏 | I17: =$F17*(1+8%*DATEDIF($G17,$I$8,"d")/365) -> 1859342.5 | J17: =$F17*(1+8%*DATEDIF($G17,$J$8,"d")/365) -> 1872821.9 | K17: =$F17*(1+8%*DATEDIF($G17,$K$8,"d")/365) -> 1992821.9 | L17: =$F17*(1+8%*DATEDIF($G17,$L$8,"d")/365) -> 2112821.9 | M17: =$F17*(1+8%*DATEDIF($G17,$M$8,"d")/365) -> 2232821.9 | N17: =$F17*(1+8%*DATEDIF($G17,$N$8,"d")/365) -> 2342958.9 | O17: =K17-F17 -> 492821.92
B18: PreA | C18: 澎湃资本 | D18: 7500000 | E18: 17R5008081592 | F18: 7500000 | G18: 43067 | H18: 宁波澎湃磐石股权投资合伙企业（有限合伙） | I18: =$F18*(1+8%*DATEDIF($G18,$I$8,"d")/365) -> 9288493.2 | J18: =$F18*(1+8%*DATEDIF($G18,$J$8,"d")/365) -> 9355890.4 | K18: =$F18*(1+8%*DATEDIF($G18,$K$8,"d")/365) -> 9955890.4 | L18: =$F18*(1+8%*DATEDIF($G18,$L$8,"d")/365) -> 10555890 | M18: =$F18*(1+8%*DATEDIF($G18,$M$8,"d")/365) -> 11155890 | N18: =$F18*(1+8%*DATEDIF($G18,$N$8,"d")/365) -> 11706575 | O18: =K18-F18 -> 2455890.4
B19: PreA | C19: 陆剑锋 | D19: 5000000 | E19: 17R6007004060 | F19: 5000000 | G19: 43031 | H19: 陆剑锋 | I19: =$F19*(1+8%*DATEDIF($G19,$I$8,"d")/365) -> 6231780.8 | J19: =$F19*(1+8%*DATEDIF($G19,$J$8,"d")/365) -> 6276712.3 | K19: =$F19*(1+8%*DATEDIF($G19,$K$8,"d")/365) -> 6676712.3 | L19: =$F19*(1+8%*DATEDIF($G19,$L$8,"d")/365) -> 7076712.3 | M19: =$F19*(1+8%*DATEDIF($G19,$M$8,"d")/365) -> 7476712.3 | N19: =$F19*(1+8%*DATEDIF($G19,$N$8,"d")/365) -> 7843835.6 | O19: =K19-F19 -> 1676712.3
B20: PreA | C20: 中财奇虎 | D20: 7500000 | E20: 18R7000434297 | F20: 7500000 | G20: 43118 | H20: 共青城中财奇虎金控二期互联网产业投资中心（有限合伙） | I20: =$F20*(1+8%*DATEDIF($G20,$I$8,"d")/365) -> 9204657.5 | J20: =$F20*(1+8%*DATEDIF($G20,$J$8,"d")/365) -> 9272054.8 | K20: =$F20*(1+8%*DATEDIF($G20,$K$8,"d")/365) -> 9872054.8 | L20: =$F20*(1+8%*DATEDIF($G20,$L$8,"d")/365) -> 10472055 | M20: =$F20*(1+8%*DATEDIF($G20,$M$8,"d")/365) -> 11072055 | N20: =$F20*(1+8%*DATEDIF($G20,$N$8,"d")/365) -> 11622740 | O20: =K20-F20 -> 2372054.8
B21: A轮 | C21: 招银永吉 | D21: 18000000 | E21: 18R0004183570 | F21: 18000000 | G21: 43270 | H21: 招银国际资本管理（深圳）有限公司 - 深圳市招银永吉成长股权投 | I21: =$F21*(1+8%*DATEDIF($G21,$I$8,"d")/365) -> 21491507 | J21: =$F21*(1+8%*DATEDIF($G21,$J$8,"d")/365) -> 21653260 | K21: =$F21*(1+8%*DATEDIF($G21,$K$8,"d")/365) -> 23093260 | L21: =$F21*(1+8%*DATEDIF($G21,$L$8,"d")/365) -> 24533260 | M21: =$F21*(1+8%*DATEDIF($G21,$M$8,"d")/365) -> 25973260 | N21: =$F21*(1+8%*DATEDIF($G21,$N$8,"d")/365) -> 27294904 | O21: =K21-F21 -> 5093260.3
B22: A轮 | C22: 招银共赢 | D22: 2000000 | E22: 18R1004229066 | F22: 2000000 | G22: 43273 | H22: 深圳市招银共赢股权投资合伙企业（有限合伙） | I22: =$F22*(1+8%*DATEDIF($G22,$I$8,"d")/365) -> 2386630.1 | J22: =$F22*(1+8%*DATEDIF($G22,$J$8,"d")/365) -> 2404602.7 | K22: =$F22*(1+8%*DATEDIF($G22,$K$8,"d")/365) -> 2564602.7 | L22: =$F22*(1+8%*DATEDIF($G22,$L$8,"d")/365) -> 2724602.7 | M22: =$F22*(1+8%*DATEDIF($G22,$M$8,"d")/365) -> 2884602.7 | N22: =$F22*(1+8%*DATEDIF($G22,$N$8,"d")/365) -> 3031452.1 | O22: =K22-F22 -> 564602.74
B23: A+轮 | C23: 司马华鹏 | D23: 2500000 | E23: 18R7004665215 | F23: 2500000 | G23: 43285 | H23: 司马华鹏 | I23: =$F23*(1+8%*DATEDIF($G23,$I$8,"d")/365) -> 2976712.3 | J23: =$F23*(1+8%*DATEDIF($G23,$J$8,"d")/365) -> 2999178.1 | K23: =$F23*(1+8%*DATEDIF($G23,$K$8,"d")/365) -> 3199178.1 | L23: =$F23*(1+8%*DATEDIF($G23,$L$8,"d")/365) -> 3399178.1 | M23: =$F23*(1+8%*DATEDIF($G23,$M$8,"d")/365) -> 3599178.1 | N23: =$F23*(1+8%*DATEDIF($G23,$N$8,"d")/365) -> 3782739.7 | O23: =K23-F23 -> 699178.08
B24: A+轮 | C24: 中财奇虎 | D24: 7500000 | E24: 18R7004605845 | F24: 7500000 | G24: 43283 | H24: 共青城中财奇虎金控二期互联网产业投资中心（有限合伙） | I24: =$F24*(1+8%*DATEDIF($G24,$I$8,"d")/365) -> 8933424.7 | J24: =$F24*(1+8%*DATEDIF($G24,$J$8,"d")/365) -> 9000821.9 | K24: =$F24*(1+8%*DATEDIF($G24,$K$8,"d")/365) -> 9600821.9 | L24: =$F24*(1+8%*DATEDIF($G24,$L$8,"d")/365) -> 10200822 | M24: =$F24*(1+8%*DATEDIF($G24,$M$8,"d")/365) -> 10800822 | N24: =$F24*(1+8%*DATEDIF($G24,$N$8,"d")/365) -> 11351507 | O24: =K24-F24 -> 2100821.9
B25: A+轮 | C25: 红杉资本 | D25: 7500000 | E25: 18R9004540373 | F25: 7500000 | G25: 43280 | H25: 宁波梅山保税港区红杉智盛股权投资合伙企业（有限合伙） | I25: =$F25*(1+8%*DATEDIF($G25,$I$8,"d")/365) -> 8938356.2 | J25: =$F25*(1+8%*DATEDIF($G25,$J$8,"d")/365) -> 9005753.4 | K25: =$F25*(1+8%*DATEDIF($G25,$K$8,"d")/365) -> 9605753.4 | L25: =$F25*(1+8%*DATEDIF($G25,$L$8,"d")/365) -> 10205753 | M25: =$F25*(1+8%*DATEDIF($G25,$M$8,"d")/365) -> 10805753 | N25: =$F25*(1+8%*DATEDIF($G25,$N$8,"d")/365) -> 11356438 | O25: =K25-F25 -> 2105753.4
B26: A++轮 | C26: 红杉资本 | D26: 12500000 | E26: 18R4005457786 | F26: 12500000 | G26: 43312 | H26: 宁波梅山保税港区红杉智盛股权投资合伙企业（有限合伙） | I26: =$F26*(1+8%*DATEDIF($G26,$I$8,"d")/365) -> 14809589 | J26: =$F26*(1+8%*DATEDIF($G26,$J$8,"d")/365) -> 14921918 | K26: =$F26*(1+8%*DATEDIF($G26,$K$8,"d")/365) -> 15921918 | L26: =$F26*(1+8%*DATEDIF($G26,$L$8,"d")/365) -> 16921918 | M26: =$F26*(1+8%*DATEDIF($G26,$M$8,"d")/365) -> 17921918 | N26: =$F26*(1+8%*DATEDIF($G26,$N$8,"d")/365) -> 18839726 | O26: =K26-F26 -> 3421917.8
B27: B轮 | C27: 腾讯 | D27: 114705882 | E27: 19R0000778742 | F27: 40000000 | G27: 43495 | H27: 林芝腾讯投资管理有限公司 | I27: =$F27*(1+12%*DATEDIF($G27,$I$8,"d")/365) -> 48679452 | J27: =$F27*(1+12%*DATEDIF($G27,$J$8,"d")/365) -> 49218630 | K27: =$F27*(1+12%*DATEDIF($G27,$K$8,"d")/365) -> 54018630 | L27: =$F27*(1+12%*DATEDIF($G27,$L$8,"d")/365) -> 58818630 | M27: =$F27*(1+12%*DATEDIF($G27,$M$8,"d")/365) -> 63618630 | N27: =$F27*(1+12%*DATEDIF($G27,$N$8,"d")/365) -> 68024110 | O27: =K27-F27 -> 14018630
E28: 19R0000762085 | F28: 40000000 | G28: 43495 | H28: 林芝腾讯投资管理有限公司 | I28: =$F28*(1+12%*DATEDIF($G28,$I$8,"d")/365) -> 48679452 | J28: =$F28*(1+12%*DATEDIF($G28,$J$8,"d")/365) -> 49218630 | K28: =$F28*(1+12%*DATEDIF($G28,$K$8,"d")/365) -> 54018630 | L28: =$F28*(1+12%*DATEDIF($G28,$L$8,"d")/365) -> 58818630 | M28: =$F28*(1+12%*DATEDIF($G28,$M$8,"d")/365) -> 63618630 | N28: =$F28*(1+12%*DATEDIF($G28,$N$8,"d")/365) -> 68024110 | O28: =K28-F28 -> 14018630
E29: 19R0000778748 | F29: 34705882 | G29: 43495 | H29: 林芝腾讯投资管理有限公司 | I29: =$F29*(1+12%*DATEDIF($G29,$I$8,"d")/365) -> 42236583 | J29: =$F29*(1+12%*DATEDIF($G29,$J$8,"d")/365) -> 42704399 | K29: =$F29*(1+12%*DATEDIF($G29,$K$8,"d")/365) -> 46869105 | L29: =$F29*(1+12%*DATEDIF($G29,$L$8,"d")/365) -> 51033811 | M29: =$F29*(1+12%*DATEDIF($G29,$M$8,"d")/365) -> 55198517 | N29: =$F29*(1+12%*DATEDIF($G29,$N$8,"d")/365) -> 59020918 | O29: =K29-F29 -> 12163223
B30: B+轮 | C30: 江苏招银 | D30: 73230000 | E30: 19R1005759893 | F30: 73230000 | G30: 43703 | H30: 江苏招银现代化产业股权投资基金一期（有限合伙） | I30: =$F30*(1+8%*DATEDIF($G30,$I$8,"d")/365) -> 80484786 | J30: =$F30*(1+8%*DATEDIF($G30,$J$8,"d")/365) -> 81142853 | K30: =$F30*(1+8%*DATEDIF($G30,$K$8,"d")/365) -> 87001253 | L30: =$F30*(1+8%*DATEDIF($G30,$L$8,"d")/365) -> 92859653 | M30: =$F30*(1+8%*DATEDIF($G30,$M$8,"d")/365) -> 98718053 | N30: =$F30*(1+8%*DATEDIF($G30,$N$8,"d")/365) -> 1.0409494e+08 | O30: =K30-F30 -> 13771253
B31: B+轮 | C31: 招银电信 | D31: 73230000 | E31: 19R9006022116 | F31: 73230000 | G31: 43703 | H31: 招银电信 - 深圳招银电信新趋势股权投资基金合伙企业（有限合伙） | I31: =$F31*(1+8%*DATEDIF($G31,$I$8,"d")/365) -> 80484786 | J31: =$F31*(1+8%*DATEDIF($G31,$J$8,"d")/365) -> 81142853 | K31: =$F31*(1+8%*DATEDIF($G31,$K$8,"d")/365) -> 87001253 | L31: =$F31*(1+8%*DATEDIF($G31,$L$8,"d")/365) -> 92859653 | M31: =$F31*(1+8%*DATEDIF($G31,$M$8,"d")/365) -> 98718053 | N31: =$F31*(1+8%*DATEDIF($G31,$N$8,"d")/365) -> 1.0409494e+08 | O31: =K31-F31 -> 13771253
B32: B+轮 | C32: 招银共赢 | D32: 3540000 | E32: 19R8006222723 | F32: 3540000 | G32: 43704 | H32: 深圳市招银共赢股权投资合伙企业（有限合伙） | I32: =$F32*(1+8%*DATEDIF($G32,$I$8,"d")/365) -> 3889926.6 | J32: =$F32*(1+8%*DATEDIF($G32,$J$8,"d")/365) -> 3921738.1 | K32: =$F32*(1+8%*DATEDIF($G32,$K$8,"d")/365) -> 4204938.1 | L32: =$F32*(1+8%*DATEDIF($G32,$L$8,"d")/365) -> 4488138.1 | M32: =$F32*(1+8%*DATEDIF($G32,$M$8,"d")/365) -> 4771338.1 | N32: =$F32*(1+8%*DATEDIF($G32,$N$8,"d")/365) -> 5031261.4 | O32: =K32-F32 -> 664938.08
B33: B+轮 | C33: 司马华鹏 | D33: 1500000 | E33: 19R3005823795 | F33: 1500000 | G33: 43703 | H33: 司马华鹏 | I33: =$F33*(1+8%*DATEDIF($G33,$I$8,"d")/365) -> 1648602.7 | J33: =$F33*(1+8%*DATEDIF($G33,$J$8,"d")/365) -> 1662082.2 | K33: =$F33*(1+8%*DATEDIF($G33,$K$8,"d")/365) -> 1782082.2 | L33: =$F33*(1+8%*DATEDIF($G33,$L$8,"d")/365) -> 1902082.2 | M33: =$F33*(1+8%*DATEDIF($G33,$M$8,"d")/365) -> 2022082.2 | N33: =$F33*(1+8%*DATEDIF($G33,$N$8,"d")/365) -> 2132219.2 | O33: =K33-F33 -> 282082.19
B34: C轮 | C34: 国新央企 | D34: 1.3955664e+08 | E34: 20R4009101962 | F34: 1.3955664e+08 | G34: 44158 | H34: 国新央企运营（广州）投资基金（有限合伙）托管专户 | I34: 1.3955664e+08 | J34: =$F34*(1+8%*DATEDIF($G34,$J$8,"d")/365) -> 1.4071897e+08 | K34: =$F34*(1+8%*DATEDIF($G34,$K$8,"d")/365) -> 1.5188351e+08 | L34: =$F34*(1+8%*DATEDIF($G34,$L$8,"d")/365) -> 1.6304804e+08 | M34: =$F34*(1+8%*DATEDIF($G34,$M$8,"d")/365) -> 1.7421257e+08 | N34: =$F34*(1+8%*DATEDIF($G34,$N$8,"d")/365) -> 1.8445947e+08 | O34: =K34-F34 -> 12326866
B35: C轮 | C35: 新业广州 | D35: 1314800.1 | E35: 20R0008316246 | F35: 1314800.1 | G35: 44158 | H35: 新业（广州）股权投资合伙企业（有限合伙） | I35: 1314800.1 | J35: =$F35*(1+8%*DATEDIF($G35,$J$8,"d")/365) -> 1325750.8 | K35: =$F35*(1+8%*DATEDIF($G35,$K$8,"d")/365) -> 1430934.8 | L35: =$F35*(1+8%*DATEDIF($G35,$L$8,"d")/365) -> 1536118.8 | M35: =$F35*(1+8%*DATEDIF($G35,$M$8,"d")/365) -> 1641302.8 | N35: =$F35*(1+8%*DATEDIF($G35,$N$8,"d")/365) -> 1737841.5 | O35: =K35-F35 -> 116134.67
B36: C轮 | C36: 浦信 | D36: 20000000 | E36: 20R6009052781 | F36: 20000000 | G36: 44155 | H36: 上海熠云投资管理合伙企业（有限合伙） | I36: 20000000 | J36: =$F36*(1+8%*DATEDIF($G36,$J$8,"d")/365) -> 20179726 | K36: =$F36*(1+8%*DATEDIF($G36,$K$8,"d")/365) -> 21779726 | L36: =$F36*(1+8%*DATEDIF($G36,$L$8,"d")/365) -> 23379726 | M36: =$F36*(1+8%*DATEDIF($G36,$M$8,"d")/365) -> 24979726 | N36: =$F36*(1+8%*DATEDIF($G36,$N$8,"d")/365) -> 26448219 | O36: =K36-F36 -> 1779726
B37: C轮 | C37: 腾讯 | D37: 54227991 | E37: 20R2008589763 | F37: 14227991 | G37: 44166 | H37: 林芝腾讯投资管理有限公司 | I37: 14227991 | J37: =$F37*(1+8%*DATEDIF($G37,$J$8,"d")/365) -> 14321545 | K37: =$F37*(1+8%*DATEDIF($G37,$K$8,"d")/365) -> 15459785 | L37: =$F37*(1+8%*DATEDIF($G37,$L$8,"d")/365) -> 16598024 | M37: =$F37*(1+8%*DATEDIF($G37,$M$8,"d")/365) -> 17736263 | N37: =$F37*(1+8%*DATEDIF($G37,$N$8,"d")/365) -> 18780949 | O37: =K37-F37 -> 1231793.2
E38: 20R2008589764 | F38: 40000000 | G38: 44166 | H38: 林芝腾讯投资管理有限公司 | I38: 40000000 | J38: =$F38*(1+8%*DATEDIF($G38,$J$8,"d")/365) -> 40263014 | K38: =$F38*(1+8%*DATEDIF($G38,$K$8,"d")/365) -> 43463014 | L38: =$F38*(1+8%*DATEDIF($G38,$L$8,"d")/365) -> 46663014 | M38: =$F38*(1+8%*DATEDIF($G38,$M$8,"d")/365) -> 49863014 | N38: =$F38*(1+8%*DATEDIF($G38,$N$8,"d")/365) -> 52800000 | O38: =K38-F38 -> 3463013.7
B39: C轮 | C39: 海松 | D39: 1.2208858e+08 | E39: 20R2008261896 | F39: 1.2208858e+08 | G39: 44155 | H39: 嘉兴海松佳年股权投资合伙企业（有限合伙） | I39: 1.2208858e+08 | J39: =$F39*(1+8%*DATEDIF($G39,$J$8,"d")/365) -> 1.2318571e+08 | K39: =$F39*(1+8%*DATEDIF($G39,$K$8,"d")/365) -> 1.3295279e+08 | L39: =$F39*(1+8%*DATEDIF($G39,$L$8,"d")/365) -> 1.4271988e+08 | M39: =$F39*(1+8%*DATEDIF($G39,$M$8,"d")/365) -> 1.5248697e+08 | N39: =$F39*(1+8%*DATEDIF($G39,$N$8,"d")/365) -> 1.6145128e+08 | O39: =K39-F39 -> 10864211
E40: 合计 | F40: =SUM(F10:F39) -> 6.7601705e+08 | I40: =SUM(I16:I39) -> 7.3065341e+08 | J40: =SUM(J16:J39) -> 7.3701922e+08 | K40: =SUM(K16:K39) -> 7.9567896e+08 | L40: =SUM(L16:L39) -> 8.5433871e+08 | M40: =SUM(M16:M39) -> 9.1299846e+08 | N40: =SUM(N16:N39) -> 9.6683686e+08
F41: =[1]Sheet1!H245-F40 -> 0 | K41: =K40-J40 -> 58659747 | L41: =L40-K40 -> 58659747 | M41: =M40-L40 -> 58659747 | N41: =N40-M40 -> 53838398
F43: =F40-[1]Sheet1!D245 -> 6.6022942e+08
I44: =J40-I45 -> 61125322
H45: 银行存款 | I45: =SUM(F16:F39) -> 6.7589389e+08
B48: 轮次 | C48: 2020年11月20日 '000 | E48: 2021年12月31日 '000 | G48: 2022年12月31日 '000 | I48: 2023年12月31日 '000 | K48: 2024年11月30日 '000
C49: P+I | D49: FV | E49: P+I | F49: FV | G49: P+I | H49: FV | I49: P+I | J49: FV | K49: P+I | L49: FV
B51: PreA | C51: =SUM(I16:I20)/1000 -> 27825.589 | D51: 81161 | E51: 29828 | F51: =(D51+H51)/2 -> 95386.351 | G51: 31628 | H51: 109611.7 | I51: 33428 | J51: 152393.2 | K51: 35080 | L51: 211870
B52: A轮 | C52: =SUM(I21:I22)/1000 -> 23878.137 | D52: 38626 | E52: 25658 | F52: =(D52+H52)/2 -> 45422.85 | G52: 27258 | H52: 52219.699 | I52: 28858 | J52: 72252.896 | K52: 30326 | L52: 99971
B53: A+轮 | C53: =SUM(I23:I25)/1000 -> 20848.493 | D53: 31244 | E53: 22406 | F53: =(D53+H53)/2 -> 36747.236 | G53: 23806 | H53: 42250.472 | I53: 25206 | J53: 58417.693 | K53: 26491 | L53: 80771
B54: A++轮 | C54: =I26/1000 -> 14809.589 | D54: 20925 | E54: 15922 | F54: =(D54+H54)/2 -> 24601.416 | G54: 16922 | H54: 28277.831 | I54: 17922 | J54: 38980.37 | K54: 18840 | L54: 53733
B55: B轮 | C55: =SUM(I27:I29)/1000 -> 139595.49 | D55: 173016 | E55: 154906 | F55: =(D55+H55)/2 -> 202979.85 | G55: 168671 | H55: 232943.7 | I55: 182436 | J55: 317271.38 | K55: 195069 | L55: 432123
B56: B+轮 | C56: =SUM(I30:I33)/1000 -> 166508.1 | D56: 149191 | E56: 179990 | F56: =(D56+H56)/2 -> 173212.66 | G56: 192110 | H56: 197234.33 | I56: 204230 | J56: 256249.23 | K56: 215353 | L56: 332920
B57: C轮 | C57: =SUM(I34:I39)/1000 -> 337188.01 | D57: 338503 | E57: 366970 | F57: =(D57+H57)/2 -> 376096.18 | G57: 393945 | H57: 413689.36 | I57: 420920 | J57: 490745.46 | K57: 445678 | L57: 582152
B59: 合计 | C59: =SUM(C51:C57) -> 730653.41 | D59: =SUM(D51:D57) -> 832666 | E59: =SUM(E51:E57) -> 795680 | F59: =SUM(F51:F57) -> 954446.54 | G59: =SUM(G51:G57) -> 854340 | H59: =SUM(H51:H57) -> 1076227.1 | I59: =SUM(I51:I57) -> 913000 | J59: =SUM(J51:J57) -> 1386310.2 | ... L59: =SUM(L51:L57) -> 1793540
A61: NB1 | B61: 截止2022年12月31日，2023年12月31日和2024年11月30日，每轮次持有的股权的P+I+D都小于FV，因此按照FV计量。
M79: 公司估值
L80: 2022年 | M80: 1572488
L81: 2023年 | M81: 2113917

Sheet PL12.2JA-V2
A1: 公司分录
A2: 借：银行存款 | B2: ='PL12.1回购权价值计算'!I45 -> 6.7589389e+08
A3: 贷：实收资本 | B3: -9010338.8
A4: 贷：资本公积 | B4: =-B2-B3 -> -6.6688356e+08
A7: 20年实际分录 | D7: 20年调整分录
A8: 借：银行存款 | B8: =B2 -> 6.7589389e+08 | D8: 借：实收资本 | E8: =-ROUND(B3,2) -> 9010338.8
A9: 借：可赎回优先股利息 | D9: 借：资本公积 | E9: =-ROUND(B4,2) -> 6.6688356e+08
A10: 借：公允价值变动收益 | B10: =-(B8+B12) -> 61125322 | D10: 借：可赎回优先股利息
A11: 借：期初未分配利润 | D11: 借：公允价值变动收益 | E11: =ROUND(B10,2) -> 61125322
A12: 贷：可赎回优先股 | B12: =-'PL12.1回购权价值计算'!J40 -> -7.3701922e+08 | D12: 借：期初未分配利润
D13: 贷：可赎回优先股 | E13: =ROUND(B12,2) -> -7.3701922e+08
A15: 21年实际分录 | D15: 21年调整分录
A16: 借：银行存款 | B16: =B2 -> 6.7589389e+08 | D16: 借：实收资本 | E16: =-ROUND(B3,2) -> 9010338.8
A17: 借：可赎回优先股利息 | D17: 借：资本公积 | E17: =-ROUND(B4,2) -> 6.6688356e+08
A18: 借：公允价值变动收益 | B18: ='PL12.1回购权价值计算'!K40-'PL12.1回购权价值计算'!J40 -> 58659747 | D18: 借：可赎回优先股利息 | E18: =B17 -> 0
A19: 借：期初未分配利润 | B19: =B10 -> 61125322 | D19: 借：公允价值变动收益 | E19: =ROUND(B18,2) -> 58659747
A20: 贷：可赎回优先股 | B20: =-'PL12.1回购权价值计算'!K40 -> -7.9567896e+08 | D20: 借：期初未分配利润 | E20: =ROUND(B19,2) -> 61125322
D21: 贷：可赎回优先股 | E21: =ROUND(B20,2) -> -7.9567896e+08
A23: 22年实际分录 | D23: 22年调整分录
A24: 借：银行存款 | B24: =B2 -> 6.7589389e+08 | D24: 借：实收资本 | E24: =-ROUND(B3,2) -> 9010338.8
A25: 借：可赎回优先股利息 | D25: 借：资本公积 | E25: =-ROUND(B4,2) -> 6.6688356e+08
A26: 借：公允价值变动收益 | B26: ='PL12.1回购权价值计算'!L40-'PL12.1回购权价值计算'!K40 -> 58659747 | D26: 借：可赎回优先股利息 | E26: =B25 -> 0
A27: 借：期初未分配利润 | B27: =B18+B19 -> 1.1978507e+08 | D27: 借：公允价值变动收益 | E27: =ROUND(B26,2) -> 58659747
A28: 贷：可赎回优先股 | B28: =-'PL12.1回购权价值计算'!L40 -> -8.5433871e+08 | D28: 借：期初未分配利润 | E28: =ROUND(B27,2) -> 1.1978507e+08
D29: 贷：可赎回优先股 | E29: =ROUND(B28,2) -> -8.5433871e+08
A31: 23年实际分录 | D31: 23年调整分录
A32: 借：银行存款 | B32: =B2 -> 6.7589389e+08 | D32: 借：实收资本 | E32: =-ROUND(B3,2) -> 9010338.8
A33: 借：可赎回优先股利息 | D33: 借：资本公积 | E33: =-ROUND(B4,2) -> 6.6688356e+08
A34: 借：公允价值变动收益 | B34: ='PL12.1回购权价值计算'!M40-'PL12.1回购权价值计算'!L40 -> 58659747 | D34: 借：可赎回优先股利息 | E34: =B33 -> 0
A35: 借：期初未分配利润 | B35: =B25+B26+B27 -> 1.7844482e+08 | D35: 借：公允价值变动收益 | E35: =ROUND(B34,2) -> 58659747
A36: 贷：可赎回优先股 | B36: =-'PL12.1回购权价值计算'!M40 -> -9.1299846e+08 | D36: 借：期初未分配利润 | E36: =ROUND(B35,2) -> 1.7844482e+08
D37: 贷：可赎回优先股 | E37: =ROUND(B36,2) -> -9.1299846e+08
A39: 24年1130协议前分录
A40: 借：银行存款 | B40: =B2 -> 6.7589389e+08
A41: 借：可赎回优先股利息
A42: 借：投资收益 | B42: ='PL12.1回购权价值计算'!N40-'PL12.1回购权价值计算'!M40 -> 53838398
A43: 借：期初未分配利润 | B43: =B33+B34+B35 -> 2.3710456e+08
A44: 贷：可赎回优先股 | B44: =-'PL12.1回购权价值计算'!N40 -> -9.6683686e+08
A46: 24年1130协议后分录
A47: 借：可赎回优先股 | B47: =-B44 -> 9.6683686e+08
A48: 贷：实收资本 | B48: =B3 -> -9010338.8
A49: 贷：资本公积 | B49: =-B47-B48 -> -9.5782652e+08
A51: 24年分录汇总 | D51: 24年调整分录
A52: 借：银行存款 | B52: =B40 -> 6.7589389e+08 | D52: 借：可赎回优先股利息 | E52: =B53 -> 0
A53: 借：可赎回优先股利息 | B53: =B41 -> 0 | D53: 借：投资收益 | E53: =ROUND(B54,2) -> 53838398
A54: 借：投资收益 | B54: =B42 -> 53838398 | D54: 借：期初未分配利润 | E54: =ROUND(B55,2) -> 2.3710456e+08
A55: 借：期初未分配利润 | B55: =B43 -> 2.3710456e+08 | D55: 贷：资本公积 | E55: =ROUND(B57-B4,2) -> -2.9094296e+08
A56: 贷：实收资本 | B56: =B48 -> -9010338.8
A57: 贷：资本公积 | B57: =B49 -> -9.5782652e+08

Sheet PL13
C5: Year ended 31 December | K5: Six months ended 30 June
C6: 2022 | E6: 2023 | G6: 2024 | I6: 2025 | K6: 2024 | M6: 2025
C7: RMB’000 | E7: RMB’000 | G7: RMB’000 | I7: RMB’000 | K7: RMB’000 | M7: RMB’000
K8: (Unaudited)
B10: Salaries, wages and other benefits | C10: =-ROUND(O36/1000,0) -> 102154 | E10: =-ROUND(V36/1000,0) -> 85606 | G10: =-ROUND(O53/1000,0) -> 62412 | I10: =-ROUND(O72/1000,0) -> 44448 | K10: =-ROUND(AB53/1000,0) -> 33613 | M10: =-ROUND(V53/1000,0) -> 21131
B11: Contribution to defined contribution retirement plan | C11: =-ROUND(O28*0.6/1000,0) -> 5306 | E11: =-ROUND(V28*0.6/1000,0) -> 3356 | G11: =-ROUND(O45*0.6/1000,0) -> 2113 | I11: =-ROUND(O64*0.6/1000,0) -> 1403 | K11: =-ROUND(AB45*0.6/1000,0) -> 1169 | M11: =-ROUND(V45*0.6/1000,0) -> 772
B12: Equity-settled share-based payment expenses (note 27) | C12: =ROUND('PL13-ESOP测算V2'!K58/1000,0) -> #REF! | E12: =ROUND('PL13-ESOP测算V2'!L58/1000,0) -> #REF! | G12: =ROUND('PL13-ESOP测算V2'!M58/1000,0) -> #REF! | I12: =ROUND('PL13-ESOP测算V2'!N58/1000,0) -> #REF! | K12: =ROUND('PL13-ESOP测算V2'!M58/1000/2,0) -> #REF! | M12: =ROUND('PL13-ESOP测算V2'!N58/1000/2,0) -> #REF!
C14: =SUM(C10:C13) -> #REF! | E14: =SUM(E10:E13) -> #REF! | G14: =SUM(G10:G13) -> #REF! | I14: =SUM(I10:I13) -> #REF! | K14: =SUM(K10:K13) -> #REF! | M14: =SUM(M10:M13) -> #REF!
B21: Note： | C21: 薪酬较上一版有调整
N23: 2022年 | U23: 2023年
N24: 2022年1月1日 | O24: 本期计提 | P24: 本期发放 | Q24: 2022年12月31日 | U24: 2023年1月1日 | V24: 本期计提 | W24: 本期发放 | X24: 2023年12月31日
N25: a | O25: b | P25: c | Q25: d=a+b+c | U25: a | V25: b | W25: c | X25: d=a+b+c
L26: 工资 | N26: -7034854.1 | O26: -85466244 | P26: 86038951 | Q26: -6462146.5 | S26: 工资 | U26: -6491677.3 | V26: -74158717 | W26: 74857459 | X26: -5792935.2
L27: 奖金 | N27: -8270352.1 | O27: -1617528 | P27: 7440829.2 | Q27: -2447050.9 | S27: 奖金 | U27: -2447050.9 | V27: -1598606.7 | W27: 1923617.7 | X27: -2122039.8
L28: 社保 | N28: 1520.92 | O28: -8844035.4 | P28: 7962411.9 | Q28: -880102.65 | S28: 社保 | U28: -876670.66 | V28: -5592979 | W28: 6069482.7 | X28: -400167
L29: 公积金 | N29: 1060 | O29: -3682982.8 | P29: 3670231 | Q29: -11691.75 | S29: 公积金 | U29: -11691.75 | V29: -2328429.8 | W29: 2218192.8 | X29: -121928.68
L30: 小计 | N30: =N27+N28+N29+N26 -> -15302625 | O30: =O27+O28+O29+O26 -> -99610790 | P30: =P27+P28+P29+P26 -> 1.0511242e+08 | Q30: =Q27+Q28+Q29+Q26 -> -9800991.8 | S30: 小计 | U30: =U27+U28+U29+U26 -> -9827090.6 | V30: =V27+V28+V29+V26 -> -83678732 | W30: =W27+W28+W29+W26 -> 85068752 | X30: =X27+X28+X29+X26 -> -8437070.7
L32: 辞退福利 | N32: -144767 | O32: -652250 | P32: 51200 | Q32: -745817 | S32: 辞退福利 | U32: -745817 | V32: 0 | W32: 200000 | X32: -545817
L33: 福利费 | N33: 0 | O33: -1890473.1 | P33: 1890473.1 | Q33: 0 | S33: 福利费 | U33: 0 | V33: -1927210.7 | W33: 1927210.7 | X33: 0
L34: 小计 | N34: =N32+N33 -> -144767 | O34: =O32+O33 -> -2542723.1 | P34: =P32+P33 -> 1941673.1 | Q34: =Q32+Q33 -> -745817 | S34: 小计 | U34: =U32+U33 -> -745817 | V34: =V32+V33 -> -1927210.7 | W34: =W32+W33 -> 2127210.7 | X34: =X32+X33 -> -545817
L36: 合计 | N36: =N30+N34 -> -15447392 | O36: =O30+O34 -> -1.0215351e+08 | P36: =P30+P34 -> 1.070541e+08 | Q36: =Q30+Q34 -> -10546809 | S36: 合计 | U36: =U30+U34 -> -10572908 | V36: =V30+V34 -> -85605943 | W36: =W30+W34 -> 87195963 | X36: =X30+X34 -> -8982887.7
N40: 2024年 | U40: 2025年6月30日 | AA40: 2024年6月30日
N41: 2024年1月1日 | O41: 本期计提 | P41: 本期发放 | Q41: 2024年12月31日 | U41: 2025年1月1日 | V41: 本期计提 | W41: 本期发放 | X41: 2025年6月30日 | AA41: 2024年1月1日 | AB41: 本期计提 | AC41: 本期发放 | AD41: 2024年6月30日
N42: a | O42: b | P42: c | Q42: d=a+b+c | U42: a | V42: b | W42: c | X42: d=a+b+c | AA42: a | AB42: b | AC42: c | AD42: d=a+b+c
L43: 工资 | N43: -5792935.2 | O43: -54532481 | P43: 56837670 | Q43: -3487746.3 | S43: 工资 | U43: -3487746.3 | V43: -19470335 | W43: 20231729 | X43: -2726352.3 | Z43: 工资 | AA43: -5792935.2 | AB43: -30347061 | AC43: 32059988 | AD43: -4080008.1
L44: 奖金 | N44: -2122039.8 | O44: -2024388.3 | P44: 1416682.4 | Q44: -2729745.7 | S44: 奖金 | U44: -2729745.7 | V44: 172090 | W44: 470040 | X44: -2087615.7 | Z44: 奖金 | AA44: -2122039.8 | AB44: -48610.39 | AC44: 596210 | AD44: -1574440.2
L45: 社保 | N45: -400167 | O45: -3521037.6 | P45: 3764615.8 | Q45: -156588.78 | S45: 社保 | U45: -156588.78 | V45: -1287048.6 | W45: 1288477.8 | X45: -155159.62 | Z45: 社保 | AA45: -400167 | AB45: -1947786 | AC45: 2020202.3 | AD45: -327750.75
L46: 公积金 | N46: -121928.68 | O46: -1442619 | P46: 1482468.7 | Q46: -82079 | S46: 公积金 | U46: -82079 | V46: -545215.66 | W46: 545259 | X46: -82035.66 | Z46: 公积金 | AA46: -121928.68 | AB46: -812017 | AC46: 873689.68 | AD46: -60256
L47: 小计 | N47: =N44+N45+N46+N43 -> -8437070.7 | O47: =O44+O45+O46+O43 -> -61520526 | P47: =P44+P45+P46+P43 -> 63501437 | Q47: =Q44+Q45+Q46+Q43 -> -6456159.8 | S47: 小计 | U47: =U44+U45+U46+U43 -> -6456159.8 | V47: =V44+V45+V46+V43 -> -21130509 | W47: =W44+W45+W46+W43 -> 22535506 | X47: =X44+X45+X46+X43 -> -5051163.3 | Z47: 小计 | AA47: -8437070.7 | AB47: -33155474 | AC47: 35550090 | AD47: -6042455.1
L49: 辞退福利 | N49: -545817 | O49: 0 | P49: 0 | Q49: -545817 | S49: 辞退福利 | U49: -545817 | V49: 0 | W49: 0 | X49: -545817 | Z49: 辞退福利 | AA49: -545817 | AB49: 0 | AC49: 0 | AD49: -545817
L50: 福利费 | N50: 0 | O50: -891458.67 | P50: 891458.67 | Q50: 0 | S50: 福利费 | U50: 0 | V50: 0 | W50: 0 | X50: 0 | Z50: 福利费 | AA50: 0 | AB50: -457479 | AC50: 457179 | AD50: -300
L51: 小计 | N51: =N49+N50 -> -545817 | O51: =O49+O50 -> -891458.67 | P51: =P49+P50 -> 891458.67 | Q51: =Q49+Q50 -> -545817 | S51: 小计 | U51: =U49+U50 -> -545817 | V51: =V49+V50 -> 0 | W51: =W49+W50 -> 0 | X51: =X49+X50 -> -545817 | Z51: 小计 | AA51: -545817 | AB51: -457479 | AC51: 457179 | AD51: -546117
L53: 合计 | N53: =N47+N51 -> -8982887.7 | O53: =O47+O51 -> -62411985 | P53: =P47+P51 -> 64392896 | Q53: =Q47+Q51 -> -7001976.8 | S53: 合计 | U53: =U47+U51 -> -7001976.8 | V53: =V47+V51 -> -21130509 | W53: =W47+W51 -> 22535506 | X53: =X47+X51 -> -5596980.3 | Z53: 合计 | AA53: -8982887.7 | AB53: -33612953 | AC53: 36007269 | AD53: -6588572.1
N59: 2025年
N60: 2025年1月1日 | O60: 本期计提 | P60: 本期发放 | Q60: 2025年12月31日
G61: 见PL13-ESOP测算V2 | N61: a | O61: b | P61: c | Q61: d=a+b+c
L62: 工资 | N62: -3487746.3 | O62: -37755588 | P62: 37212839 | Q62: -4030495.3
L63: 奖金 | N63: -2324489.5 | O63: -2507610.6 | P63: 4864695.2 | Q63: 32595.167
L64: 社保 | N64: -156588.78 | O64: -2338007.5 | P64: 2419891.8 | Q64: -74704.46
L65: 公积金 | N65: -82079 | O65: -942497 | P65: 970956 | Q65: -53620
L66: 小计 | N66: -6050903.6 | O66: -43543703 | P66: 45468382 | Q66: -4126224.6
L68: 辞退福利 | N68: -545817 | O68: -854665 | P68: 1400482 | Q68: 0
L69: 福利费 | N69: 0 | O69: -49300 | P69: 49300 | Q69: 0
L70: 小计 | N70: -545817 | O70: -903965 | P70: 1449782 | Q70: 0
L72: 合计 | N72: -6596720.6 | O72: -44447668 | P72: 46918164 | Q72: -4126224.6
P73: Check: | Q73: 0

Sheet PL13-ESOP测算V2
A1: 上市日期 | B1: 46203
A3: 1元对价/股购买
B4: 授予日 | C4: 解锁日期 | D4: 授予总数 | E4: 分摊授予数量 | F4: 公允价值 | G4: 股份支付总额 | H4: 2019年 | I4: 2020年 | J4: 2021年 | K4: 2022年 | L4: 2023年 | M4: 2024年 | N4: 2025年 | O4: 2026年 | P4: 2027年
A5: 满四年未上市，在授予日至上市日期间内均摊 | B5: 43703 | C5: 43830 | D5: =GETPIVOTDATA("调整后的期权数",[1]Lead!$A$11,"年(调整后的授予日)",2019) -> #REF! | E5: =$D$5/($C$12-$B$5)*(C5-B5) -> #REF! | F5: =[1]Lead!$E$22 -> 40.921925 | G5: =E5*F5 -> #REF! | H5: =G5 -> #REF! | Q5: =SUM(H5:P5)-G5 -> #REF!
C6: 44196 | E6: =$D$5/($C$12-$B$5)*(C6-C5) -> #REF! | F6: =[1]Lead!$E$22 -> 40.921925 | G6: =E6*F6 -> #REF! | I6: =G6 -> #REF! | Q6: =SUM(H6:P6)-G6 -> #REF!
C7: 44561 | E7: =$D$5/($C$12-$B$5)*(C7-C6) -> #REF! | F7: =[1]Lead!$E$22 -> 40.921925 | G7: =E7*F7 -> #REF! | J7: =G7 -> #REF! | Q7: =SUM(H7:P7)-G7 -> #REF!
C8: 44926 | E8: =$D$5/($C$12-$B$5)*(C8-C7) -> #REF! | F8: =[1]Lead!$E$22 -> 40.921925 | G8: =E8*F8 -> #REF! | K8: =G8 -> #REF! | Q8: =SUM(H8:P8)-G8 -> #REF!
C9: 45291 | E9: =$D$5/($C$12-$B$5)*(C9-C8) -> #REF! | F9: =[1]Lead!$E$22 -> 40.921925 | G9: =E9*F9 -> #REF! | L9: =G9 -> #REF! | Q9: =SUM(H9:P9)-G9 -> #REF!
C10: 45657 | E10: =$D$5/($C$12-$B$5)*(C10-C9) -> #REF! | F10: =[1]Lead!$E$22 -> 40.921925 | G10: =E10*F10 -> #REF! | M10: =G10 -> #REF! | Q10: =SUM(H10:P10)-G10 -> #REF!
C11: 46022 | E11: =$D$5/($C$12-$B$5)*(C11-C10) -> #REF! | F11: =[1]Lead!$E$22 -> 40.921925 | G11: =E11*F11 -> #REF! | N11: =G11 -> #REF! | Q11: =SUM(H11:P11)-G11 -> #REF!
C12: =B1 -> 46203 | E12: =$D$5/($C$12-$B$5)*(C12-C11) -> #REF! | F12: =[1]Lead!$E$22 -> 40.921925 | G12: =E12*F12 -> #REF! | O12: =G12 -> #REF! | Q12: =SUM(H12:P12)-G12 -> #REF!
B13: 44155 | C13: 44196 | D13: =GETPIVOTDATA("调整后的期权数",[1]Lead!$A$11,"年(调整后的授予日)",2020) -> #REF! | E13: =$D$13/($C$19-$B$13)*(C13-B13) -> #REF! | F13: =[1]Lead!$E$26 -> 57.914229 | G13: =E13*F13 -> #REF! | I13: =G13 -> #REF! | Q13: =SUM(H13:P13)-G13 -> #REF!
C14: 44561 | E14: =$D$13/($C$19-$B$13)*(C14-C13) -> #REF! | F14: =[1]Lead!$E$26 -> 57.914229 | G14: =E14*F14 -> #REF! | J14: =G14 -> #REF! | Q14: =SUM(H14:P14)-G14 -> #REF!
C15: 44926 | E15: =$D$13/($C$19-$B$13)*(C15-C14) -> #REF! | F15: =[1]Lead!$E$26 -> 57.914229 | G15: =E15*F15 -> #REF! | K15: =G15 -> #REF! | Q15: =SUM(H15:P15)-G15 -> #REF!
C16: 45291 | E16: =$D$13/($C$19-$B$13)*(C16-C15) -> #REF! | F16: =[1]Lead!$E$26 -> 57.914229 | G16: =E16*F16 -> #REF! | L16: =G16 -> #REF! | Q16: =SUM(H16:P16)-G16 -> #REF!
C17: 45657 | E17: =$D$13/($C$19-$B$13)*(C17-C16) -> #REF! | F17: =[1]Lead!$E$26 -> 57.914229 | G17: =E17*F17 -> #REF! | M17: =G17 -> #REF! | Q17: =SUM(H17:P17)-G17 -> #REF!
C18: 46022 | E18: =$D$13/($C$19-$B$13)*(C18-C17) -> #REF! | F18: =[1]Lead!$E$26 -> 57.914229 | G18: =E18*F18 -> #REF! | N18: =G18 -> #REF! | Q18: =SUM(H18:P18)-G18 -> #REF!
C19: =B1 -> 46203 | E19: =$D$13/($C$19-$B$13)*(C19-C18) -> #REF! | F19: =[1]Lead!$E$26 -> 57.914229 | G19: =E19*F19 -> #REF! | O19: =G19 -> #REF! | Q19: =SUM(H19:P19)-G19 -> #REF!
A20: 前三期在授予日至上市日期间内均摊，第四期在四年内均摊 | B20: 44926 | C20: 45291 | D20: =GETPIVOTDATA("调整后的期权数",[1]Lead!$A$11,"年(调整后的授予日)",2022) -> #REF! | E20: =$D$20/4 -> #REF! | F20: =[1]Lead!$E$30 -> 78.356751 | G20: =E20*F20 -> #REF! | L20: =G20/($B$1-$B$20)*($C$20-$B$20) -> #REF! | M20: =G20/($B$1-$B$20)*($C$21-$C$20) -> #REF! | N20: =G20/($B$1-$B$20)*($C$22-$C$21) -> #REF! | O20: =G20/($B$1-$B$20)*($B$1-$C$22) -> #REF! | Q20: =SUM(H20:P20)-G20 -> #REF!
C21: 45657 | E21: =$D$20/4 -> #REF! | F21: =[1]Lead!$E$30 -> 78.356751 | G21: =E21*F21 -> #REF! | L21: =G21/($B$1-$B$20)*($C$20-$B$20) -> #REF! | M21: =G21/($B$1-$B$20)*($C$21-$C$20) -> #REF! | N21: =G21/($B$1-$B$20)*($C$22-$C$21) -> #REF! | O21: =G21/($B$1-$B$20)*($B$1-$C$22) -> #REF! | Q21: =SUM(H21:P21)-G21 -> #REF!
C22: 46022 | E22: =$D$20/4 -> #REF! | F22: =[1]Lead!$E$30 -> 78.356751 | G22: =E22*F22 -> #REF! | L22: =G22/($B$1-$B$20)*($C$20-$B$20) -> #REF! | M22: =G22/($B$1-$B$20)*($C$21-$C$20) -> #REF! | N22: =G22/($B$1-$B$20)*($C$22-$C$21) -> #REF! | O22: =G22/($B$1-$B$20)*($B$1-$C$22) -> #REF! | Q22: =SUM(H22:P22)-G22 -> #REF!
C23: 46387 | E23: =$D$20/4 -> #REF! | F23: =[1]Lead!$E$30 -> 78.356751 | G23: =E23*F23 -> #REF! | L23: =$G$23/4 -> #REF! | M23: =$G$23/4 -> #REF! | N23: =$G$23/4 -> #REF! | O23: =$G$23/4 -> #REF! | Q23: =SUM(H23:P23)-G23 -> #REF!
A24: 前两期在授予日至上市日期间内均摊，第三期在三年内摊销，第四期在四年内均摊 | B24: 45291 | C24: 45657 | D24: =GETPIVOTDATA("调整后的期权数",[1]Lead!$A$11,"年(调整后的授予日)",2023) -> #REF! | E24: =$D$24/4 -> #REF! | F24: =[1]Lead!$E$34 -> 109.50912 | G24: =E24*F24 -> #REF! | M24: =G24/($B$1-$B$24)*($C$24-$B$24) -> #REF! | N24: =G24/($B$1-$B$24)*($C$25-$C$24) -> #REF! | O24: =G24/($B$1-$B$24)*($B$1-$C$25) -> #REF! | Q24: =SUM(H24:P24)-G24 -> #REF!
C25: 46022 | E25: =$D$24/4 -> #REF! | F25: =[1]Lead!$E$34 -> 109.50912 | G25: =E25*F25 -> #REF! | M25: =G25/($B$1-$B$24)*($C$24-$B$24) -> #REF! | N25: =G25/($B$1-$B$24)*($C$25-$C$24) -> #REF! | O25: =G25/($B$1-$B$24)*($B$1-$C$25) -> #REF! | Q25: =SUM(H25:P25)-G25 -> #REF!
C26: 46387 | E26: =$D$24/4 -> #REF! | F26: =[1]Lead!$E$34 -> 109.50912 | G26: =E26*F26 -> #REF! | M26: =$G$26/3 -> #REF! | N26: =$G$26/3 -> #REF! | O26: =$G$26/3 -> #REF! | Q26: =SUM(H26:P26)-G26 -> #REF!
C27: 46752 | E27: =$D$24/4 -> #REF! | F27: =[1]Lead!$E$34 -> 109.50912 | G27: =E27*F27 -> #REF! | M27: =$G$27/4 -> #REF! | N27: =$G$27/4 -> #REF! | O27: =$G$27/4 -> #REF! | P27: =$G$27/4 -> #REF! | Q27: =SUM(H27:P27)-G27 -> #REF!
B29: 合计 | D29: =SUM(D5:D27) -> #REF! | G29: =SUM(G5:G27) -> #REF! | H29: =SUM(H5:H27) -> #REF! | I29: =SUM(I5:I27) -> #REF! | J29: =SUM(J5:J27) -> #REF! | K29: =SUM(K5:K27) -> #REF! | L29: =SUM(L5:L27) -> #REF! | M29: =SUM(M5:M27) -> #REF! | N29: =SUM(N5:N27) -> #REF! | ... P29: =SUM(P5:P27) -> #REF!
A32: 0元对价/股购买-销售代表华东
B33: 授予日 | C33: 解锁日期 | D33: 授予总数 | E33: 分摊授予数量 | F33: 公允价值 | G33: 股份支付总额 | H33: 2019年 | I33: 2020年 | J33: 2021年 | K33: 2022年 | L33: 2023年 | M33: 2024年 | N33: 2025年 | O33: 2026年 | P33: 2027年
A34: 前三期在授予日至上市日期间内均摊，第四期在四年内均摊 | B34: 44926 | C34: 45291 | D34: =[1]BKD!N255 -> 221027 | E34: =$D$34/4 -> 55256.75 | F34: =[1]Lead!$E$44 -> 79.287486 | G34: =E34*F34 -> 4381168.8 | L34: =G34/($B$1-$B$34)*($C$34-$B$34) -> 1252252.6 | M34: =G34/($B$1-$B$34)*($C$35-$C$34) -> 1255683.5 | N34: =G34/($B$1-$B$34)*($C$36-$C$35) -> 1252252.6 | O34: =G34/($B$1-$B$34)*($B$1-$C$36) -> 620980.07 | Q34: =SUM(H34:P34)-G34 -> 0
C35: 45657 | E35: =$D$34/4 -> 55256.75 | F35: =[1]Lead!$E$44 -> 79.287486 | G35: =E35*F35 -> 4381168.8 | L35: =G35/($B$1-$B$34)*($C$34-$B$34) -> 1252252.6 | M35: =G35/($B$1-$B$34)*($C$35-$C$34) -> 1255683.5 | N35: =G35/($B$1-$B$34)*($C$36-$C$35) -> 1252252.6 | O35: =G35/($B$1-$B$34)*($B$1-$C$36) -> 620980.07 | Q35: =SUM(H35:P35)-G35 -> 0
C36: 46022 | E36: =$D$34/4 -> 55256.75 | F36: =[1]Lead!$E$44 -> 79.287486 | G36: =E36*F36 -> 4381168.8 | L36: =G36/($B$1-$B$34)*($C$34-$B$34) -> 1252252.6 | M36: =G36/($B$1-$B$34)*($C$35-$C$34) -> 1255683.5 | N36: =G36/($B$1-$B$34)*($C$36-$C$35) -> 1252252.6 | O36: =G36/($B$1-$B$34)*($B$1-$C$36) -> 620980.07 | Q36: =SUM(H36:P36)-G36 -> 0
C37: 46387 | E37: =$D$34/4 -> 55256.75 | F37: =[1]Lead!$E$44 -> 79.287486 | G37: =E37*F37 -> 4381168.8 | L37: =$G$37/4 -> 1095292.2 | M37: =$G$37/4 -> 1095292.2 | N37: =$G$37/4 -> 1095292.2 | O37: =$G$37/4 -> 1095292.2 | Q37: =SUM(H37:P37)-G37 -> 0
B39: 合计 | D39: =SUM(D34:D37) -> 221027 | G39: =SUM(G34:G37) -> 17524675 | H39: =SUM(H34:H37) -> 0 | I39: =SUM(I34:I37) -> 0 | J39: =SUM(J34:J37) -> 0 | K39: =SUM(K34:K37) -> 0 | L39: =SUM(L34:L37) -> 4852050.1 | M39: =SUM(M34:M37) -> 4862342.6 | N39: =SUM(N34:N37) -> 4852050.1 | ... P39: =SUM(P34:P37) -> 0
A42: 0元对价/股购买-顾问朱靖雷
B43: 授予日 | C43: 摊销日期 | D43: 授予总数 | E43: 分摊授予数量 | F43: 公允价值 | G43: 股份支付总额 | H43: 2019年 | I43: 2020年 | J43: 2021年 | K43: 2022年 | L43: 2023年 | M43: 2024年 | N43: 2025年 | O43: 2026年 | P43: 2027年
A44: 以上市作为解锁条件，在授予日至上市日均摊 | B44: 45291 | C44: 45657 | D44: =[1]BKD!N254 -> 315753 | E44: =$D$44/($C$46-$B$44)*(C44-B44) -> 126716.66 | F44: =[1]Lead!$E$48 -> 110.4467 | G44: =E44*F44 -> 13995438 | M44: =G44 -> 13995438 | Q44: =SUM(H44:P44)-G44 -> 0
C45: 46022 | E45: =$D$44/($C$46-$B$44)*(C45-C44) -> 126370.44 | F45: =[1]Lead!$E$48 -> 110.4467 | G45: =E45*F45 -> 13957199 | N45: =G45 -> 13957199 | Q45: =SUM(H45:P45)-G45 -> 0
C46: 46203 | E46: =$D$44/($C$46-$B$44)*(C46-C45) -> 62665.891 | F46: =[1]Lead!$E$48 -> 110.4467 | G46: =E46*F46 -> 6921241 | O46: =G46 -> 6921241 | Q46: =SUM(H46:P46)-G46 -> 0
B48: 合计 | D48: =SUM(D44:D46) -> 315753 | G48: =SUM(G44:G46) -> 34873877 | H48: =SUM(H44:H46) -> 0 | I48: =SUM(I44:I46) -> 0 | J48: =SUM(J44:J46) -> 0 | K48: =SUM(K44:K46) -> 0 | L48: =SUM(L44:L46) -> 0 | M48: =SUM(M44:M46) -> 13995438 | N48: =SUM(N44:N46) -> 13957199 | ... P48: =SUM(P44:P46) -> 0
A52: by 费用属性统计
B53: 费用属性 | H53: 2019年 | I53: 2020年 | J53: 2021年 | K53: 2022年 | L53: 2023年 | M53: 2024年 | N53: 2025年 | O53: 2026年 | P53: 2027年
B54: 管理费用 | H54: =(H29+H39+H48)*[1]Lead!G13 -> #REF! | I54: =I6*[1]Lead!G13+I13*[1]Lead!G14 -> #REF! | J54: =J7*[1]Lead!G13+J14*[1]Lead!G14 -> #REF! | K54: =K8*[1]Lead!G13+'PL13-ESOP测算V2'!K15*[1]Lead!G14 -> #REF! | L54: =L9*[1]Lead!G13+'PL13-ESOP测算V2'!L16*[1]Lead!G14+SUM('PL13-ESOP测算V2'!L20:L23)*[1]Lead!G15 -> #REF! | M54: =M10*[1]Lead!G13+'PL13-ESOP测算V2'!M17*[1]Lead!G14+SUM('PL13-ESOP测算V2'!M20:M23)*[1]Lead!G15+SUM('PL13-ESOP测算V2'!M24:M27)*[1]Lead!G16+M48 -> #REF! | N54: =N11*[1]Lead!G13+'PL13-ESOP测算V2'!N18*[1]Lead!G14+SUM('PL13-ESOP测算V2'!N20:N23)*[1]Lead!G15+SUM('PL13-ESOP测算V2'!N24:N27)*[1]Lead!G16+N48 -> #REF! | O54: =O12*[1]Lead!G13+'PL13-ESOP测算V2'!O19*[1]Lead!G14+SUM('PL13-ESOP测算V2'!O20:O23)*[1]Lead!G15+SUM('PL13-ESOP测算V2'!O24:O27)*[1]Lead!G16+O48 -> #REF! | P54: =P23*[1]Lead!G15+'PL13-ESOP测算V2'!P27*[1]Lead!G16 -> #REF!
B55: 销售费用 | H55: =(H29+H39+H48)*[1]Lead!H13 -> #REF! | I55: =I6*[1]Lead!H13+I13*[1]Lead!H14 -> #REF! | J55: =J7*[1]Lead!H13+J14*[1]Lead!H14 -> #REF! | K55: =K8*[1]Lead!H13+'PL13-ESOP测算V2'!K15*[1]Lead!H14 -> #REF! | L55: =L9*[1]Lead!H13+'PL13-ESOP测算V2'!L16*[1]Lead!H14+SUM('PL13-ESOP测算V2'!L20:L23)*[1]Lead!H15+L39 -> #REF! | M55: =M10*[1]Lead!H13+'PL13-ESOP测算V2'!M17*[1]Lead!H14+SUM('PL13-ESOP测算V2'!M20:M23)*[1]Lead!H15+SUM('PL13-ESOP测算V2'!M24:M27)*[1]Lead!H16+M39 -> #REF! | N55: =N11*[1]Lead!H13+'PL13-ESOP测算V2'!N18*[1]Lead!H14+SUM('PL13-ESOP测算V2'!N20:N23)*[1]Lead!H15+SUM('PL13-ESOP测算V2'!N24:N27)*[1]Lead!H16+N39 -> #REF! | O55: =O12*[1]Lead!H13+'PL13-ESOP测算V2'!O19*[1]Lead!H14+SUM('PL13-ESOP测算V2'!O20:O23)*[1]Lead!H15+SUM('PL13-ESOP测算V2'!O24:O27)*[1]Lead!H16+O39 -> #REF! | P55: =P23*[1]Lead!H15+'PL13-ESOP测算V2'!P27*[1]Lead!H16+P39 -> #REF!
B56: 研发费用 | H56: =H29+H39+H48-H54-H55 -> #REF! | I56: =I29+I39+I48-I54-I55 -> #REF! | J56: =J29+J39+J48-J54-J55 -> #REF! | K56: =K29+K39+K48-K54-K55 -> #REF! | L56: =L29+L39+L48-L54-L55 -> #REF! | M56: =M29+M39+M48-M54-M55 -> #REF! | N56: =N29+N39+N48-N54-N55 -> #REF! | O56: =O29+O39+O48-O54-O55 -> #REF! | P56: =P29+P39+P48-P54-P55 -> #REF!
B58: 合计 | H58: =SUM(H54:H56) -> #REF! | I58: =SUM(I54:I56) -> #REF! | J58: =SUM(J54:J56) -> #REF! | K58: =SUM(K54:K56) -> #REF! | L58: =SUM(L54:L56) -> #REF! | M58: =SUM(M54:M56) -> #REF! | N58: =SUM(N54:N56) -> #REF! | O58: =SUM(O54:O56) -> #REF! | P58: =SUM(P54:P56) -> #REF!

Sheet ESOP
A1: 上市日期 | B1: 46203
A3: 1元对价/股购买 | H3: 43830 | I3: 44196 | J3: 44561 | K3: 44926 | L3: 45291 | M3: 45473 | N3: 45657 | O3: 46022 | P3: 46203
B4: 授予日 | C4: 解锁日期 | D4: 授予总数 | E4: 分摊授予数量 | F4: 公允价值 | G4: 股份支付总额 | H4: 2019年 | I4: 2020年 | J4: 2021年 | K4: 2022年 | L4: 2023年 | M4: 45473 | N4: 2024年 | O4: 2025年 | P4: 2026年 | Q4: 2027年 | S4: 2024年11月
A5: 满四年未上市，在授予日至上市日期间内均摊 | B5: 43703 | C5: 43830 | D5: 1039055 | E5: =$D$5/4 -> 259763.76 | F5: 40.686511 | G5: =E5*F5 -> 10568881 | H5: =$G$5/($B$1-$B$5)*(H3-B5) -> 536899.17 | I5: =$G$5/($B$1-$B$5)*(I3-H3) -> 1547284.2 | J5: =$G$5/($B$1-$B$5)*(J3-I3) -> 1543056.7 | K5: =$G$5/($B$1-$B$5)*(K3-J3) -> 1543056.7 | L5: =$G$5/($B$1-$B$5)*(L3-K3) -> 1543056.7 | M5: =$G$5/($B$1-$B$5)*(M3-L3) -> 769414.56 | N5: =$G$5/($B$1-$B$5)*(N3-L3) -> 1547284.2 | O5: =$G$5/($B$1-$B$5)*(O3-N3) -> 1543056.7 | P5: =$G$5/($B$1-$B$5)*(P3-O3) -> 765187.01 | R5: =SUM(H5:Q5)-G5-M5 -> 1.2805685e-09 | S5: 1412002.5 | T5: 1412002.5
C6: 44196 | E6: =$D$5/4 -> 259763.76 | F6: 40.686511 | G6: =E6*F6 -> 10568881 | H6: =$G$6/($B$1-$B$5)*(H3-B5) -> 536899.17 | I6: =$G$6/($B$1-$B$5)*(I3-H3) -> 1547284.2 | J6: =$G$6/($B$1-$B$5)*(J3-I3) -> 1543056.7 | K6: =$G$6/($B$1-$B$5)*(K3-J3) -> 1543056.7 | L6: =$G$6/($B$1-$B$5)*(L3-K3) -> 1543056.7 | M6: =$G$6/($B$1-$B$5)*(M3-L3) -> 769414.56 | N6: =$G$6/($B$1-$B$5)*(N3-L3) -> 1547284.2 | O6: =$G$6/($B$1-$B$5)*(O3-N3) -> 1543056.7 | P6: =$G$6/($B$1-$B$5)*(P3-O3) -> 765187.01 | R6: =SUM(H6:Q6)-G6-M6 -> 1.2805685e-09 | S6: 1412002.5 | T6: 1412002.5
C7: 44561 | E7: =$D$5/4 -> 259763.76 | F7: 40.686511 | G7: =E7*F7 -> 10568881 | H7: =$G$7/($B$1-$B$5)*(H3-B5) -> 536899.17 | I7: =$G$7/($B$1-$B$5)*(I3-H3) -> 1547284.2 | J7: =$G$7/($B$1-$B$5)*(J3-I3) -> 1543056.7 | K7: =$G$7/($B$1-$B$5)*(K3-J3) -> 1543056.7 | L7: =$G$7/($B$1-$B$5)*(L3-K3) -> 1543056.7 | M7: =$G$7/($B$1-$B$5)*(M3-L3) -> 769414.56 | N7: =$G$7/($B$1-$B$5)*(N3-L3) -> 1547284.2 | O7: =$G$7/($B$1-$B$5)*(O3-N3) -> 1543056.7 | P7: =$G$7/($B$1-$B$5)*(P3-O3) -> 765187.01 | R7: =SUM(H7:Q7)-G7-M7 -> 1.2805685e-09 | S7: 1412002.5 | T7: 1412002.5
C8: 44926 | E8: =$D$5/4 -> 259763.76 | F8: 40.686511 | G8: =E8*F8 -> 10568881 | H8: =$G$8/($B$1-$B$5)*(H3-B5) -> 536899.17 | I8: =$G$8/($B$1-$B$5)*(I3-H3) -> 1547284.2 | J8: =$G$8/($B$1-$B$5)*(J3-I3) -> 1543056.7 | K8: =$G$8/($B$1-$B$5)*(K3-J3) -> 1543056.7 | L8: =$G$8/($B$1-$B$5)*(L3-K3) -> 1543056.7 | M8: =$G$8/($B$1-$B$5)*(M3-L3) -> 769414.56 | N8: =$G$8/($B$1-$B$5)*(N3-L3) -> 1547284.2 | O8: =$G$8/($B$1-$B$5)*(O3-N3) -> 1543056.7 | P8: =$G$8/($B$1-$B$5)*(P3-O3) -> 765187.01 | R8: =SUM(H8:Q8)-G8-M8 -> 1.2805685e-09 | S8: 1412002.5 | T8: 1412002.5
A9: 前三期在授予日至上市日期间内均摊，第四期在四年内均摊 | B9: 44926 | C9: 45291 | D9: 76113.156 | E9: =$D$9/4 -> 19028.289 | F9: 78.903106 | G9: =E9*F9 -> 1501391.1 | L9: =G9/($B$1-$B$9)*($C$9-$B$9) -> 429136.85 | M9: =N9/2 -> 215156.28 | N9: =G9/($B$1-$B$9)*($C$10-$C$9) -> 430312.57 | O9: =G9/($B$1-$B$9)*($C$11-$C$10) -> 429136.85 | P9: =G9/($B$1-$B$9)*($B$1-$C$11) -> 212804.85 | R9: =SUM(H9:Q9)-G9-M9 -> 0 | S9: =N9/12*11 -> 394453.19
C10: 45657 | E10: =$D$9/4 -> 19028.289 | F10: 78.903106 | G10: =E10*F10 -> 1501391.1 | L10: =G10/($B$1-$B$9)*($C$9-$B$9) -> 429136.85 | M10: =N10/2 -> 215156.28 | N10: =G10/($B$1-$B$9)*($C$10-$C$9) -> 430312.57 | O10: =G10/($B$1-$B$9)*($C$11-$C$10) -> 429136.85 | P10: =G10/($B$1-$B$9)*($B$1-$C$11) -> 212804.85 | R10: =SUM(H10:Q10)-G10-M10 -> 0 | S10: =N10/12*11 -> 394453.19
C11: 46022 | E11: =$D$9/4 -> 19028.289 | F11: 78.903106 | G11: =E11*F11 -> 1501391.1 | L11: =G11/($B$1-$B$9)*($C$9-$B$9) -> 429136.85 | M11: =N11/2 -> 215156.28 | N11: =G11/($B$1-$B$9)*($C$10-$C$9) -> 430312.57 | O11: =G11/($B$1-$B$9)*($C$11-$C$10) -> 429136.85 | P11: =G11/($B$1-$B$9)*($B$1-$C$11) -> 212804.85 | R11: =SUM(H11:Q11)-G11-M11 -> 0 | S11: =N11/12*11 -> 394453.19
C12: 46387 | E12: =$D$9/4 -> 19028.289 | F12: 78.903106 | G12: =E12*F12 -> 1501391.1 | L12: =$G$12/4 -> 375347.78 | M12: =N12/2 -> 187673.89 | N12: =$G$12/4 -> 375347.78 | O12: =$G$12/4 -> 375347.78 | P12: =$G$12/4 -> 375347.78 | R12: =SUM(H12:Q12)-G12-M12 -> 0 | S12: =N12/12*11 -> 344068.8
A13: 前两期在授予日至上市日期间内均摊，第三期在三年内摊销，第四期在四年内均摊 | B13: 45291 | C13: 45657 | D13: 357323.43 | E13: =$D$13/4 -> 89330.857 | F13: 110.03754 | G13: =E13*F13 -> 9829747.4 | M13: =N13/2 -> 1972416.4 | N13: =G13/($B$1-$B$13)*($C$13-$B$13) -> 3944832.8 | O13: =G13/($B$1-$B$13)*($C$14-$C$13) -> 3934054.6 | P13: =G13/($B$1-$B$13)*($B$1-$C$14) -> 1950860 | R13: =SUM(H13:Q13)-G13-M13 -> 0 | S13: =N13/12*11 -> 3616096.8
C14: 46022 | E14: =$D$13/4 -> 89330.857 | F14: 110.03754 | G14: =E14*F14 -> 9829747.4 | M14: =N14/2 -> 1972416.4 | N14: =G14/($B$1-$B$13)*($C$13-$B$13) -> 3944832.8 | O14: =G14/($B$1-$B$13)*($C$14-$C$13) -> 3934054.6 | P14: =G14/($B$1-$B$13)*($B$1-$C$14) -> 1950860 | R14: =SUM(H14:Q14)-G14-M14 -> 0 | S14: =N14/12*11 -> 3616096.8
C15: 46387 | E15: =$D$13/4 -> 89330.857 | F15: 110.03754 | G15: =E15*F15 -> 9829747.4 | M15: =N15/2 -> 1638291.2 | N15: =$G$15/3 -> 3276582.5 | O15: =$G$15/3 -> 3276582.5 | P15: =$G$15/3 -> 3276582.5 | R15: =SUM(H15:Q15)-G15-M15 -> 0 | S15: =N15/12*11 -> 3003533.9
C16: 46752 | E16: =$D$13/4 -> 89330.857 | F16: 110.03754 | G16: =E16*F16 -> 9829747.4 | M16: =N16/2 -> 1228718.4 | N16: =$G$16/4 -> 2457436.9 | O16: =$G$16/4 -> 2457436.9 | P16: =$G$16/4 -> 2457436.9 | Q16: =$G$16/4 -> 2457436.9 | R16: =SUM(H16:Q16)-G16-M16 -> 0 | S16: =N16/12*11 -> 2252650.4
B18: 合计 | D18: =SUM(D5:D16) -> 1472491.6 | G18: =SUM(G5:G16) -> 87600079 | H18: =SUM(H5:H16) -> 2147596.7 | I18: =SUM(I5:I16) -> 6189136.9 | J18: =SUM(J5:J16) -> 6172226.7 | K18: =SUM(K5:K16) -> 6172226.7 | L18: =SUM(L5:L16) -> 7834985 | M18: =SUM(M5:M16) -> 10722643 | N18: =SUM(N5:N16) -> 21479107 | ... Q18: =SUM(Q5:Q16) -> 2457436.9 | R18: =SUM(H18:Q18)-G18-M18 -> 0 | S18: =SUM(H18:L18) -> 28516172 | T18: =SUM(S5:S16) -> 19663816
R19: =SUM(H19:Q19)-G19-M19 -> 0
S20: =S18+T18 -> 48179988
A22: by 费用属性统计
B23: 费用属性 | H23: 2019年 | I23: 2020年 | J23: 2021年 | K23: 2022年 | L23: 2023年 | M23: 45473 | N23: 2024年 | O23: 2025年 | P23: 2026年 | Q23: 2027年
B24: 管理费用 | H24: 1959113.6 | I24: 5645949.4 | J24: 5630523.3 | K24: 5630523.3 | L24: 5820366.2 | M24: 4238291.4 | N24: 8507434.9 | O24: 8487379.5 | P24: 4797177.8 | Q24: 481837.59
B25: 销售费用 | H25: 139701.71 | I25: 402604.93 | J25: 401504.92 | K25: 401504.92 | L25: 917100.76 | M25: 5648060.3 | N25: 11298321 | O25: 11279704 | P25: 7854316.4 | Q25: 1872166.1
B26: 研发费用 | H26: 48781.39 | I26: 140582.59 | J26: 140198.48 | K26: 140198.48 | L26: 1097518.1 | M26: 836291.82 | N26: 1673351.9 | O26: 1670029.7 | P26: 1058755.4 | Q26: 103433.17
B28: 合计 | H28: =SUM(H24:H26) -> 2147596.7 | I28: =SUM(I24:I26) -> 6189136.9 | J28: =SUM(J24:J26) -> 6172226.7 | K28: =SUM(K24:K26) -> 6172226.7 | L28: =SUM(L24:L26) -> 7834985 | M28: =SUM(M24:M26) -> 10722643 | N28: =SUM(N24:N26) -> 21479107 | O28: =SUM(O24:O26) -> 21437114 | ... Q28: =SUM(Q24:Q26) -> 2457436.9 | R28: =SUM(H28:Q28)-G28-M28 -> 87600079
H31: =SUM(H24:J24) -> 13235586 | O31: =O24/2 -> 4243689.8
H32: =SUM(H25:J25) -> 943811.56 | O32: =O25/2 -> 5639852.2
H33: =SUM(H26:J26) -> 329562.46 | O33: =O26/2 -> 835014.86

Sheet BS>>

Sheet BS1
C5: 物业、厂房及设备 | E5: 44926 | G5: 45291 | I5: 45657 | K5: 46022 | M5: 45838
E6: a | G6: b | I6: c | K6: c | M6: d
C7: 电子设备 | E7: 9291457.1 | G7: 11359271 | I7: 7593972.7 | K7: 3530540.9 | M7: 5432506.7
C8: 运输设备 | E8: 1580998 | G8: 1131209.9 | I8: 738563.36 | K8: 341764.1 | M8: 568734.44
C9: 办公设备及其他 | E9: 610974.18 | G9: 435207.28 | I9: 253681.82 | K9: 165751 | M9: 213498.61
C10: 租赁/(固定资产)改良支出 | E10: 2494437.3 | G10: 1039673.8 | I10: 1255861.4 | K10: 717635.1 | M10: 986748.24
C12: 合计 | E12: =SUM(E7:E10) -> 13977867 | G12: =SUM(G7:G10) -> 13965362 | I12: =SUM(I7:I10) -> 9842079.2 | K12: =SUM(K7:K10) -> 4755691.1 | M12: =SUM(M7:M10) -> 7201488
C13: Check： | E13: =ROUND(E12-'FY22-25 IFRS（合并）'!G35,0) -> 0 | G13: =ROUND(G12-'FY22-25 IFRS（合并）'!I35,0) -> 0 | I13: =ROUND(I12-'FY22-25 IFRS（合并）'!K35,0) -> 0 | K13: =K12-'FY22-25 IFRS（合并）'!Q35 -> 9678.91 | M13: =ROUND(M12-'FY22-25 IFRS（合并）'!O35,0) -> 0

Sheet BS1-Full List
A1: 年份 | B1: 编号 | C1: 主体 | D1: 资产 | E1: 资产类别 | F1: 采购日期 | G1: 固定资产成本 | H1: 使用月限 | I1: 净残值率 | J1: 月折旧额 | K1: 本年累计折旧 | L1: 净值
A2: 2022 | B2: mygj001 | C2: 绵阳硅基 | D2: 班台 | E2: 办公家具 | F2: 44439 | G2: 5275.82 | H2: 60 | I2: 0.05 | J2: 83.53 | K2: 1336.32 | L2: 3939.5
A3: 2022 | B3: mygj002 | C3: 绵阳硅基 | D3: 文件柜 | E3: 办公家具 | F3: 44439 | G3: 5275.82 | H3: 60 | I3: 0.05 | J3: 83.53 | K3: 1336.32 | L3: 3939.5
A4: 2022 | B4: mygj005 | C4: 绵阳硅基 | D4: 班台 | E4: 办公家具 | F4: 44439 | G4: 16515.61 | H4: 60 | I4: 0.05 | J4: 261.5 | K4: 4183.17 | L4: 12332.44
A5: 2022 | B5: mygj006 | C5: 绵阳硅基 | D5: 文件柜 | E5: 办公家具 | F5: 44439 | G5: 16309.17 | H5: 60 | I5: 0.05 | J5: 258.23 | K5: 4130.98 | L5: 12178.19
A6: 2022 | B6: mygj008 | C6: 绵阳硅基 | D6: 会议桌 | E6: 办公家具 | F6: 44433 | G6: 26035.03 | H6: 60 | I6: 0.05 | J6: 412.22 | K6: 6594.34 | L6: 19440.69
A7: 2022 | B7: mygj009 | C7: 绵阳硅基 | D7: 办公桌后面柜子 | E7: 办公家具 | F7: 44439 | G7: 43307.61 | H7: 60 | I7: 0.05 | J7: 685.7 | K7: 10969.35 | L7: 32338.26
A8: 2022 | B8: mygj010 | C8: 绵阳硅基 | D8: 接待沙发 | E8: 办公家具 | F8: 44433 | G8: 7799.04 | H8: 60 | I8: 0.05 | J8: 123.48 | K8: 1975.36 | L8: 5823.68
A9: 2022 | B9: mygj013 | C9: 绵阳硅基 | D9: 休闲沙发 | E9: 办公家具 | F9: 44439 | G9: 17433.15 | H9: 60 | I9: 0.05 | J9: 276.02 | K9: 4415.65 | L9: 13017.5
A10: 2022 | B10: mygj014 | C10: 绵阳硅基 | D10: ENBF08音响_x000D_ | E10: 电子设备 | F10: 44434 | G10: 6620.29 | H10: 36 | I10: 0.05 | J10: 174.7 | K10: 2795.36 | L10: 3824.93
A11: 2022 | B11: mygj018 | C11: 绵阳硅基 | D11: 大会议室商用投影机宝视来 | E11: 电子设备 | F11: 44434 | G11: 8224.3 | H11: 36 | I11: 0.05 | J11: 217.03 | K11: 3472.64 | L11: 4751.66
A12: 2022 | B12: mygj019 | C12: 绵阳硅基 | D12: 小会议室商用投影机宝视来 | E12: 电子设备 | F12: 44434 | G12: 8224.3 | H12: 36 | I12: 0.05 | J12: 217.03 | K12: 3472.64 | L12: 4751.66
A13: 2022 | B13: mygj020 | C13: 绵阳硅基 | D13: 路演厅商用投影机宝视来 | E13: 电子设备 | F13: 44434 | G13: 12336.44 | H13: 36 | I13: 0.05 | J13: 325.54 | K13: 5208.96 | L13: 7127.48
... A694: 2022 | B694: gj0455 | C694: 南京硅基 | D694: 鱼缸 | E694: 办公家具 | F694: 44620 | G694: 5000 | H694: 60 | I694: 0.05 | J694: 79.17 | K694: 848 | L694: 4152
A695: 2022 | B695: 合计数 | G695: =SUM(G2:G694) -> 26986666 | K695: =SUM(K2:K694) -> 15503237 | L695: =SUM(L2:L694) -> 11483429
B696: check | G696: =ROUND(G695-'[1]H1-console'!$J$13,0) -> 0 | K696: =ROUND(K695+'[1]H1-console'!$J$29,0) -> 0 | L696: =ROUND(L695-'[1]2022PRC审定'!$V$21,0) -> 0
A697: 2023 | B697: gy067 | C697: 南京硅语 | D697: 梅赛德斯-奔驰S 480 | E697: 运输设备 | F697: 44804 | G697: 1429969.9 | H697: 48 | I697: 0.05 | J697: 1150.03 | K697: 452785.76 | L697: =G697-K697 -> 977184.18
A698: 2023 | B698: gj0229 | C698: 南京硅基 | D698: 4台A100英伟达4卡深度学习服务器 | E698: 电子设备 | F698: 44340 | G698: 1238938 | H698: 36 | I698: 0.05 | J698: 537.03 | K698: 1039279.4 | L698: =G698-K698 -> 199658.55
A699: 2023 | B699: gj0190 | C699: 南京硅基 | D699: 服务器 | E699: 电子设备 | F699: 44135 | G699: 857345.13 | H699: 36 | I699: 0.05 | J699: 516.03 | K699: 814477.87 | L699: =G699-K699 -> 42867.26
A700: 2023 | B700: gj0239 | C700: 南京硅基 | D700: 2台A100英伟达4卡深度学习服务器 | E700: 电子设备 | F700: 44347 | G700: 619469.04 | H700: 36 | I700: 0.05 | J700: 544.03 | K700: 506798.57 | L700: =G700-K700 -> 112670.47
A701: 2023 | B701: gj0285 | C701: 南京硅基 | D701: 思腾合力 IW4211-4G GPU服务器 | E701: 电子设备 | F701: 44439 | G701: 604955.76 | H701: 36 | I701: 0.05 | J701: 590.03 | K701: 447013.84 | L701: =G701-K701 -> 157941.92
A702: 2023 | B702: gj0119 | C702: 南京硅基 | D702: 服务器加硬盘 | E702: 电子设备 | F702: 43799 | G702: 602035.4 | H702: 36 | I702: 0.05 | J702: 456.03 | K702: 571933.63 | L702: =G702-K702 -> 30101.77
A703: 2023 | B703: gj0148 | C703: 南京硅基 | D703: 华为服务器RH2488V5*5交换机*2光纤线10硬盘16块等 | E703: 电子设备 | F703: 43982 | G703: 601504.42 | H703: 36 | I703: 0.05 | J703: 15873.03 | K703: 573867.4 | L703: =G703-K703 -> 27637.02
A704: 2023 | B704: 0 | C704: 南京硅信 | D704: 别克牌多用途乘用车 | E704: 运输设备 | F704: 44195 | G704: 463994.65 | H704: 48 | I704: 0.05 | J704: 9183.23 | K704: 330596.28 | L704: =G704-K704 -> 133398.37
A705: 2023 | B705: gj0037 | C705: 南京硅基 | D705: 奔驰轿车 | E705: 运输设备 | F705: 43220 | G705: 412547.01 | H705: 48 | I705: 0.05 | J705: 8164.99 | K705: 391919.66 | L705: =G705-K705 -> 20627.35
A706: 2023 | B706: gj0062 | C706: 南京硅基 | D706: 无线网关 | E706: 电子设备 | F706: 43312 | G706: 400862.08 | H706: 36 | I706: 0.05 | J706: 386.03 | K706: 380818.98 | L706: =G706-K706 -> 20043.1
A707: 2023 | B707: gj0076 | C707: 南京硅基 | D707: 无线网关 | E707: 电子设备 | F707: 43343 | G707: 381034.48 | H707: 36 | I707: 0.05 | J707: 397.03 | K707: 361982.76 | L707: =G707-K707 -> 19051.72
A708: 2023 | B708: 033 | C708: 南京硅信 | D708: 计算机主机 | E708: 电子设备 | F708: 43769 | G708: 313982.3 | H708: 36 | I708: 0.05 | J708: 452.03 | K708: 298283.18 | L708: =G708-K708 -> 15699.12
A709: 2023 | B709: 004 | C709: 南京硅信 | D709: 主机计算机 | E709: 电子设备 | F709: 43404 | G709: 306206.9 | H709: 36 | I709: 0.05 | J709: 409.03 | K709: 290896.55 | L709: =G709-K709 -> 15310.35
A710: 2023 | B710: gy056 | C710: 南京硅语 | D710: 投影机及配套设备 | E710: 电子设备 | F710: 44378 | G710: 303595.64 | H710: 36 | I710: 0.05 | J710: 550.03 | K710: 232352.37 | L710: =G710-K710 -> 71243.27
A711: 2023 | B711: KUN0035 | C711: 昆山硅基 | D711: 机房改造设备 | E711: 电子设备 | F711: 45107 | G711: 282683.19 | H711: 36 | I711: 0.05 | J711: 1084.03 | K711: 44760.06 | L711: =G711-K711 -> 237923.13
A712: 2023 | B712: gj0121 | C712: 南京硅基 | D712: 3台华为服务器，1台交换机，2跟光纤 | E712: 电子设备 | F712: 43830 | G712: 280000 | H712: 36 | I712: 0.05 | J712: 459.03 | K712: 266000 | L712: =G712-K712 -> 14000
A713: 2023 | B713: gj0020 | C713: 南京硅基 | D713: 无线网关 | E713: 电子设备 | F713: 43159 | G713: 248717.95 | H713: 36 | I713: 0.05 | J713: 357.03 | K713: 236282.05 | L713: =G713-K713 -> 12435.9
A714: 2023 | B714: gj0142 | C714: 南京硅基 | D714: 服务器2488V5_x000D_ | E714: 电子设备 | F714: 43951 | G714: 215929.2 | H714: 36 | I714: 0.05 | J714: 477.03 | K714: 205132.74 | L714: =G714-K714 -> 10796.46
A715: 2023 | B715: gj0134 | C715: 南京硅基 | D715: 戴尔台式电脑_x000D_ | E715: 电子设备 | F715: 43921 | G715: 203230.09 | H715: 36 | I715: 0.05 | J715: 471.03 | K715: 193068.59 | L715: =G715-K715 -> 10161.5
A716: 2023 | B716: 002 | C716: 南京硅信 | D716: CPU服务器 | E716: 电子设备 | F716: 43434 | G716: 202581.9 | H716: 36 | I716: 0.05 | J716: 412.03 | K716: 192452.8 | L716: =G716-K716 -> 10129.1
A717: 2023 | B717: gj0209 | C717: 南京硅基 | D717: 显卡 | E717: 电子设备 | F717: 44227 | G717: 194158.41 | H717: 36 | I717: 0.05 | J717: 525.03 | K717: 179327.92 | L717: =G717-K717 -> 14830.49
A718: 2023 | B718: 006 | C718: 南京硅信 | D718: 融合网关 | E718: 电子设备 | F718: 43404 | G718: 181724.14 | H718: 36 | I718: 0.05 | J718: 411.03 | K718: 172637.93 | L718: =G718-K718 -> 9086.21
A719: 2023 | B719: gy003 | C719: 南京硅语 | D719: 177个员工桌、椅+2个超大会议室桌椅+5个小会议室桌椅+4个洽谈室桌椅+培训师讲台及椅子 | E719: 办公家具 | F719: 44377 | G719: 166371.68 | H719: 60 | I719: 0.05 | J719: 1069.03 | K719: =79009.8-25716.73 -> 53293.07 | L719: =G719-K719 -> 113078.61
A720: 2023 | B720: gj0091 | C720: 南京硅基 | D720: GPU主机服务器 | E720: 电子设备 | F720: 43373 | G720: 158617.24 | H720: 36 | I720: 0.05 | J720: 408.03 | K720: 150686.38 | L720: =G720-K720 -> 7930.86
A721: 2023 | B721: gj0752 | C721: 南京硅基 | D721: 服务器 | E721: 电子设备 | F721: 44926 | G721: 149380.54 | H721: 36 | I721: 0.05 | J721: 887.03 | K721: 47305.8 | L721: =G721-K721 -> 102074.74
A722: 2023 | B722: 005 | C722: 南京硅信 | D722: 网关 | E722: 电子设备 | F722: 43404 | G722: 147068.96 | H722: 36 | I722: 0.05 | J722: 410.03 | K722: 139715.51 | L722: =G722-K722 -> 7353.45
A723: 2023 | B723: 001 | C723: 南京硅信 | D723: 网关 | E723: 电子设备 | F723: 43312 | G723: 142758.64 | H723: 36 | I723: 0.05 | J723: 385.03 | K723: 135620.71 | L723: =G723-K723 -> 7137.93
A724: 2023 | B724: gj0138 | C724: 南京硅基 | D724: 服务器2488V5_x000D_ | E724: 电子设备 | F724: 43951 | G724: 133893.81 | H724: 36 | I724: 0.05 | J724: 475.03 | K724: 127199.12 | L724: =G724-K724 -> 6694.69
A725: 2023 | B725: gj0040 | C725: 南京硅基 | D725: 无线网关 | E725: 电子设备 | F725: 43251 | G725: 133620.7 | H725: 36 | I725: 0.05 | J725: 374.03 | K725: 126939.66 | L725: =G725-K725 -> 6681.04
A726: 2023 | B726: gj0044 | C726: 南京硅基 | D726: 无线网关 | E726: 电子设备 | F726: 43251 | G726: 133620.7 | H726: 36 | I726: 0.05 | J726: 375.03 | K726: 126939.66 | L726: =G726-K726 -> 6681.04
A727: 2023 | B727: gj0050 | C727: 南京硅基 | D727: 无线网关 | E727: 电子设备 | F727: 43281 | G727: 133620.7 | H727: 36 | I727: 0.05 | J727: 380.03 | K727: 126939.66 | L727: =G727-K727 -> 6681.04
A728: 2023 | B728: gj0055 | C728: 南京硅基 | D728: 无线网关 | E728: 电子设备 | F728: 43281 | G728: 133620.7 | H728: 36 | I728: 0.05 | J728: 384.03 | K728: 126939.66 | L728: =G728-K728 -> 6681.04
A729: 2023 | B729: gj0089 | C729: 南京硅基 | D729: ASR主机服务器 | E729: 电子设备 | F729: 43373 | G729: 130172.42 | H729: 36 | I729: 0.05 | J729: 407.03 | K729: 123663.8 | L729: =G729-K729 -> 6508.62
A730: 2023 | B730: gj0120 | C730: 南京硅基 | D730: 计算机 | E730: 电子设备 | F730: 43799 | G730: 126732.74 | H730: 36 | I730: 0.05 | J730: 457.03 | K730: 120396.1 | L730: =G730-K730 -> 6336.64
A731: 2023 | B731: gj0129 | C731: 南京硅基 | D731: 华通四楼办公家具 | E731: 办公家具 | F731: 43921 | G731: 126242.83 | H731: 60 | I731: 0.05 | J731: 672.03 | K731: 89946.79 | L731: =G731-K731 -> 36296.04
... A890: 2023 | B890: gj0197 | C890: 南京硅基 | D890: 智能客服交互设备、摄像头_x000D_ | E890: 电子设备 | F890: 44196 | G890: 48672.57 | H890: 36 | I890: 0.05 | J890: 520.03 | K890: 46238.94 | L890: =G890-K890 -> 2433.63
A891: 2023 | B891: mm001 | C891: 南京梦马 | D891: 云手机服务器 | E891: 电子设备 | F891: 44681 | G891: 48000 | H891: 36 | I891: 0.05 | J891: 1266.6667 | K891: 25334.04 | L891: =G891-K891 -> 22665.96
A892: 2023 | B892: gj0398 | C892: 南京硅基 | D892: 直播机 | E892: 电子设备 | F892: 44530 | G892: 47848.83 | H892: 36 | I892: 0.05 | J892: 629.03 | K892: 31142.08 | L892: =G892-K892 -> 16706.75
A893: 2023 | B893: gj0047 | C893: 南京硅基 | D893: GPU服务器 | E893: 电子设备 | F893: 43251 | G893: 46550.86 | H893: 36 | I893: 0.05 | J893: 378.03 | K893: 44223.32 | L893: =G893-K893 -> 2327.54
A894: 2023 | B894: mygj172 | C894: 绵阳硅基 | D894: 服务器 | E894: 电子设备 | F894: 44926 | G894: 46194.79 | H894: 36 | I894: 0.05 | J894: 892.03 | K894: 14628.96 | L894: =G894-K894 -> 31565.83
A895: 2023 | B895: mygj222 | C895: 绵阳硅基 | D895: 服务器 | E895: 电子设备 | F895: 44926 | G895: 46194.79 | H895: 36 | I895: 0.05 | J895: 942.03 | K895: 14628.96 | L895: =G895-K895 -> 31565.83
A896: 2023 | B896: mygj173 | C896: 绵阳硅基 | D896: 服务器 | E896: 电子设备 | F896: 44926 | G896: 46194.69 | H896: 36 | I896: 0.05 | J896: 893.03 | K896: 14628.96 | L896: =G896-K896 -> 31565.73
A897: 2023 | B897: mygj174 | C897: 绵阳硅基 | D897: 服务器 | E897: 电子设备 | F897: 44926 | G897: 46194.69 | H897: 36 | I897: 0.05 | J897: 894.03 | K897: 14628.96 | L897: =G897-K897 -> 31565.73
A898: 2023 | B898: mygj175 | C898: 绵阳硅基 | D898: 服务器 | E898: 电子设备 | F898: 44926 | G898: 46194.69 | H898: 36 | I898: 0.05 | J898: 895.03 | K898: 14628.96 | L898: =G898-K898 -> 31565.73
A899: 2023 | B899: mygj176 | C899: 绵阳硅基 | D899: 服务器 | E899: 电子设备 | F899: 44926 | G899: 46194.69 | H899: 36 | I899: 0.05 | J899: 896.03 | K899: 14628.96 | L899: =G899-K899 -> 31565.73
A900: 2023 | B900: mygj177 | C900: 绵阳硅基 | D900: 服务器 | E900: 电子设备 | F900: 44926 | G900: 46194.69 | H900: 36 | I900: 0.05 | J900: 897.03 | K900: 14628.96 | L900: =G900-K900 -> 31565.73
A901: 2023 | B901: mygj178 | C901: 绵阳硅基 | D901: 服务器 | E901: 电子设备 | F901: 44926 | G901: 46194.69 | H901: 36 | I901: 0.05 | J901: 898.03 | K901: 14628.96 | L901: =G901-K901 -> 31565.73
A902: 2023 | B902: mygj179 | C902: 绵阳硅基 | D902: 服务器 | E902: 电子设备 | F902: 44926 | G902: 46194.69 | H902: 36 | I902: 0.05 | J902: 899.03 | K902: 14628.96 | L902: =G902-K902 -> 31565.73
A903: 2023 | B903: mygj180 | C903: 绵阳硅基 | D903: 服务器 | E903: 电子设备 | F903: 44926 | G903: 46194.69 | H903: 36 | I903: 0.05 | J903: 900.03 | K903: 14628.96 | L903: =G903-K903 -> 31565.73
... A1330: 2023 | B1330: KUN0128 | C1330: 昆山硅基 | D1330: 配件 | E1330: 电子设备 | F1330: 45291 | G1330: 9557.52 | H1330: 36 | I1330: 0 | J1330: 1188.03 | K1330: 0 | L1330: =G1330-K1330 -> 9557.52
A1331: 2023 | B1331: gj0070 | C1331: 南京硅基 | D1331: 交换机 | E1331: 电子设备 | F1331: 43312 | G1331: 9500 | H1331: 36 | I1331: 0.05 | J1331: 396.03 | K1331: 9025 | L1331: =G1331-K1331 -> 475
A1332: 2023 | B1332: gj0738 | C1332: 南京硅基 | D1332: 1台苹果笔记本电脑 | E1332: 电子设备 | F1332: 44865 | G1332: 9469.03 | H1332: 36 | I1332: 0.05 | J1332: 841.03 | K1332: 3498.46 | L1332: =G1332-K1332 -> 5970.57
A1333: 2023 | B1333: gj0295 | C1333: 南京硅基 | D1333: 服务器工作站 | E1333: 电子设备 | F1333: 44439 | G1333: 9377.98 | H1333: 36 | I1333: 0.05 | J1333: 597.03 | K1333: 6912.91 | L1333: =G1333-K1333 -> 2465.07
A1334: 2023 | B1334: gj0651 | C1334: 南京硅基 | D1334: PC机器 | E1334: 电子设备 | F1334: 44773 | G1334: 9088.5 | H1334: 36 | I1334: 0.05 | J1334: 766.03 | K1334: 4077.45 | L1334: =G1334-K1334 -> 5011.05
A1335: 2023 | B1335: gy064 | C1335: 南京硅语 | D1335: 多媒体改造工程 | E1335: 电子设备 | F1335: 44496 | G1335: 9066.34 | H1335: 36 | I1335: 0.05 | J1335: 612.03 | K1335: 6220.76 | L1335: =G1335-K1335 -> 2845.58
A1336: 2023 | B1336: gy014 | C1336: 南京硅语 | D1336: 皮沙发及茶几 | E1336: 办公家具 | F1336: 44426 | G1336: 8944.59 | H1336: 60 | I1336: 0.05 | J1336: 1132.03 | K1336: 3964.52 | L1336: =G1336-K1336 -> 4980.07
A1337: 2023 | B1337: gy042 | C1337: 南京硅语 | D1337: 86寸小米电视 | E1337: 电子设备 | F1337: 44439 | G1337: 8868 | H1337: 36 | I1337: 0.05 | J1337: 599.03 | K1337: 6552.84 | L1337: =G1337-K1337 -> 2315.16
A1338: 2023 | B1338: gj0180 | C1338: 南京硅基 | D1338: 大屏 | E1338: 电子设备 | F1338: 44074 | G1338: 8849.56 | H1338: 36 | I1338: 0.05 | J1338: 507.03 | K1338: 8407.08 | L1338: =G1338-K1338 -> 442.48
A1339: 2023 | B1339: gj0482 | C1339: 南京硅基 | D1339: 直播机（组装） | E1339: 电子设备 | F1339: 44651 | G1339: 8849.56 | H1339: 36 | I1339: 0.05 | J1339: 674.03 | K1339: 4904.34 | L1339: =G1339-K1339 -> 3945.22
A1340: 2023 | B1340: gj0483 | C1340: 南京硅基 | D1340: 直播机（组装） | E1340: 电子设备 | F1340: 44651 | G1340: 8849.56 | H1340: 36 | I1340: 0.05 | J1340: 675.03 | K1340: 4904.34 | L1340: =G1340-K1340 -> 3945.22
A1341: 2023 | B1341: KUN0001 | C1341: 昆山硅基 | D1341: PC机器 | E1341: 电子设备 | F1341: 45107 | G1341: 8849.56 | H1341: 36 | I1341: 0.05 | J1341: 1070.03 | K1341: 1401.24 | L1341: =G1341-K1341 -> 7448.32
A1342: 2023 | B1342: KUN0033 | C1342: 昆山硅基 | D1342: 3090显卡 | E1342: 电子设备 | F1342: 45107 | G1342: 8849.56 | H1342: 36 | I1342: 0.05 | J1342: 1082.03 | K1342: 1401.24 | L1342: =G1342-K1342 -> 7448.32
A1343: 2023 | B1343: gj0578 | C1343: 南京硅基 | D1343: PC机 | E1343: 电子设备 | F1343: 44742 | G1343: 8848.67 | H1343: 36 | I1343: 0.05 | J1343: 713.03 | K1343: 4203.36 | L1343: =G1343-K1343 -> 4645.31
... A1547: 2023 | B1547: gj0455 | C1547: 南京硅基 | D1547: 鱼缸 | E1547: 办公家具 | F1547: 44620 | G1547: 5000 | H1547: 60 | I1547: 0.05 | J1547: 1185.03 | K1547: 1865.6 | L1547: =G1547-K1547 -> 3134.4
A1548: 2023 | B1548: 合计数 | G1548: =SUM(G697:G1547) -> 34157841 | K1548: =SUM(K697:K1547) -> 21232153 | L1548: =SUM(L697:L1547) -> 12925688
B1549: check | G1549: =ROUND(G1548-'[1]H1-console'!$J$16,0) -> 0 | K1549: =ROUND(K1548+'[1]H1-console'!$J$32,0) -> 0 | L1549: =ROUND(L1548-'[1]2023PRC审定'!$X$21,0) -> 0
A1550: 2024 | B1550: gj0002 | C1550: 南京硅基 | D1550: 苹果笔记本电脑 | E1550: 电子设备 | F1550: 43100 | G1550: 13075 | H1550: 36 | I1550: 0.05 | J1550: 345.03 | K1550: 12421.08 | L1550: =G1550-K1550 -> 653.92
A1551: 2024 | B1551: gj0007 | C1551: 南京硅基 | D1551: 无线网关 | E1551: 电子设备 | F1551: 43131 | G1551: 39743.59 | H1551: 36 | I1551: 0.050000013 | J1551: 1048.79 | K1551: 37756.44 | L1551: =G1551-K1551 -> 1987.15
A1552: 2024 | B1552: gj0008 | C1552: 南京硅基 | D1552: 无线网关 | E1552: 电子设备 | F1552: 43131 | G1552: 39743.59 | H1552: 36 | I1552: 0.050000013 | J1552: 1048.79 | K1552: 37756.44 | L1552: =G1552-K1552 -> 1987.15
A1553: 2024 | B1553: gj0009 | C1553: 南京硅基 | D1553: 无线网关 | E1553: 电子设备 | F1553: 43131 | G1553: 66239.31 | H1553: 36 | I1553: 0.050000068 | J1553: 1747.98 | K1553: 62927.28 | L1553: =G1553-K1553 -> 3312.03
A1554: 2024 | B1554: gj0010 | C1554: 南京硅基 | D1554: 苹果手机 | E1554: 电子设备 | F1554: 43131 | G1554: 20225.64 | H1554: 36 | I1554: 0.049999901 | J1554: 533.73 | K1554: 19214.28 | L1554: =G1554-K1554 -> 1011.36
A1555: 2024 | B1555: gj0011 | C1555: 南京硅基 | D1555: 苹果手机 | E1555: 电子设备 | F1555: 43131 | G1555: 9688 | H1555: 36 | I1555: 0.05 | J1555: 255.66 | K1555: 9203.76 | L1555: =G1555-K1555 -> 484.24
A1556: 2024 | B1556: gj0012 | C1556: 南京硅基 | D1556: 无线网关 | E1556: 电子设备 | F1556: 43131 | G1556: 39743.59 | H1556: 36 | I1556: 0.050000013 | J1556: 1048.79 | K1556: 37756.44 | L1556: =G1556-K1556 -> 1987.15
A1557: 2024 | B1557: gj0013 | C1557: 南京硅基 | D1557: 测试类移动设备 | E1557: 电子设备 | F1557: 43131 | G1557: 19376 | H1557: 36 | I1557: 0.05 | J1557: 511.31 | K1557: 18407.16 | L1557: =G1557-K1557 -> 968.84
A1558: 2024 | B1558: gj0014 | C1558: 南京硅基 | D1558: DELL笔记本电脑 | E1558: 电子设备 | F1558: 43131 | G1558: 5299 | H1558: 36 | I1558: 0.05 | J1558: 139.83 | K1558: 5033.88 | L1558: =G1558-K1558 -> 265.12
A1559: 2024 | B1559: gj0017 | C1559: 南京硅基 | D1559: 移动录音棚 | E1559: 电子设备 | F1559: 43131 | G1559: 7900 | H1559: 36 | I1559: 0.05 | J1559: 208.47 | K1559: 7504.92 | L1559: =G1559-K1559 -> 395.08
A1560: 2024 | B1560: gj0018 | C1560: 南京硅基 | D1560: 无线网关 | E1560: 电子设备 | F1560: 43159 | G1560: 79487.18 | H1560: 36 | I1560: 0.050000013 | J1560: 2097.58 | K1560: 75512.88 | L1560: =G1560-K1560 -> 3974.3
A1561: 2024 | B1561: gj0019 | C1561: 南京硅基 | D1561: 无线网关 | E1561: 电子设备 | F1561: 43159 | G1561: 79487.18 | H1561: 36 | I1561: 0.050000013 | J1561: 2097.58 | K1561: 75512.88 | L1561: =G1561-K1561 -> 3974.3
... A2458: 2024 | B2458: KUN0226 | C2458: 昆山硅基 | D2458: 65寸数字人一体机 | E2458: 电子设备 | F2458: 45553 | G2458: 7743.36 | H2458: 36 | I2458: 0.049998967 | J2458: 204.34 | K2458: 613.02 | L2458: =G2458-K2458 -> 7130.34
A2459: 2024 | B2459: gj0790 | C2459: 南京硅基 | D2459: PC机器 | E2459: 电子设备 | F2459: 45565 | G2459: 5711.16 | H2459: 9 | I2459: 0.049999939 | J2459: 602.84 | K2459: 1205.68 | L2459: =G2459-K2459 -> 4505.48
A2460: 2024 | B2460: gj0791 | C2460: 南京硅基 | D2460: PC机器 | E2460: 电子设备 | F2460: 45565 | G2460: 5711.16 | H2460: 9 | I2460: 0.049999939 | J2460: 602.84 | K2460: 1205.68 | L2460: =G2460-K2460 -> 4505.48
A2461: 2024 | B2461: gj0792 | C2461: 南京硅基 | D2461: PC机器 | E2461: 电子设备 | F2461: 45565 | G2461: 7453.91 | H2461: 9 | I2461: 0.049999939 | J2461: 786.8 | K2461: 1573.6 | L2461: =G2461-K2461 -> 5880.31
A2462: 2024 | B2462: gj0793 | C2462: 南京硅基 | D2462: PC机器 | E2462: 电子设备 | F2462: 45565 | G2462: 7453.91 | H2462: 9 | I2462: 0.049999939 | J2462: 786.8 | K2462: 1573.6 | L2462: =G2462-K2462 -> 5880.31
A2463: 2024 | B2463: mm001 | C2463: 南京梦马 | D2463: 云手机服务器 | E2463: 电子设备 | F2463: 44681 | G2463: 48000 | H2463: 36 | I2463: 0.05 | J2463: 1266.67 | K2463: 40533.44 | L2463: =G2463-K2463 -> 7466.56
...

Sheet BS1-新增&处置
A1: 固定资产新增List:
A2: 2022年南京硅基 | C2: 资产编号 | D2: 资产描述 | E2: 采购/在建工程转固日期 | F2: 固定资产成本
C3: gj0455 | D3: 鱼缸 | E3: 44620 | F3: 5000
A4: 办公家具 | F4: =SUM(F3:F3) -> 5000
C8: 资产编号 | D8: 资产描述 | E8: 采购/在建工程转固日期 | F8: 固定资产成本
C9: gj0424 | D9: PC机 | E9: 44592 | F9: 10247.79
C10: gj0425 | D10: PC机 | E10: 44592 | F10: 10247.79
C11: gj0426 | D11: PC机 | E11: 44592 | F11: 10247.79
C12: gj0427 | D12: PC机 | E12: 44592 | F12: 10247.79
C13: gj0428 | D13: PC机 | E13: 44592 | F13: 10247.79
C14: gj0429 | D14: 直播相机（含麦克风、实配线） | E14: 44592 | F14: 5631
C15: gj0430 | D15: 直播机（组装） | E15: 44592 | F15: 10889.01
C16: gj0445 | D16: 直播机（组装） | E16: 44592 | F16: 8068.04
C17: gj0451 | D17: 动捕设备 | E17: 44592 | F17: 106194.71
C18: gj0452 | D18: 动捕设备 | E18: 44592 | F18: 106194.69
C19: gj0456 | D19: 3080显卡 | E19: 44620 | F19: 8406.19
C20: gj0457 | D20: 直播机（组装） | E20: 44620 | F20: 10137.93
... C135: gj0446 | D135: 3080显卡 | E135: 44592 | F135: 9085.91
A136: 电子设备 | F136: =SUM(F9:F135) -> 2476189.4
A141: 2022年南京硅语 | C141: 资产编号 | D141: 资产描述 | E141: 采购/在建工程转固日期 | F141: 固定资产成本
C142: gy067 | D142: 梅赛德斯-奔驰S 480 | E142: 44804 | F142: 1429969.9
A143: 运输设备 | F143: =F142 -> 1429969.9
A147: 2022年绵阳硅基 | C147: 资产编号 | D147: 资产描述 | E147: 采购/在建工程转固日期 | F147: 固定资产成本
C148: mygj028 | D148: 直播机（组装） | E148: 44620 | F148: 22525.25
C149: mygj029 | D149: 直播机（组装） | E149: 44620 | F149: 22525.25
C150: mygj030 | D150: 直播机（组装） | E150: 44620 | F150: 22525.25
C151: mygj031 | D151: 直播机（组装） | E151: 44620 | F151: 22525.25
C152: mygj032 | D152: 直播机（组装） | E152: 44620 | F152: 22525.25
C153: mygj033 | D153: 直播机（组装） | E153: 44620 | F153: 22525.25
C154: mygj034 | D154: 直播机（组装） | E154: 44620 | F154: 22525.25
C155: mygj035 | D155: 直播机（组装） | E155: 44620 | F155: 22525.25
C156: mygj036 | D156: 直播机（组装） | E156: 44620 | F156: 22525.25
C157: mygj037 | D157: 直播机（组装） | E157: 44620 | F157: 22525.25
C158: mygj038 | D158: 直播机（组装） | E158: 44620 | F158: 32072.85
C159: mygj039 | D159: 直播机（组装） | E159: 44620 | F159: 22525.25
... C353: mygj271 | D353: 3090显卡 | E353: 44926 | F353: 10575.22
A354: 电子设备 | F354: =SUM(F148:F353)+0.05 -> 3071202
A358: 2022年芜湖硅语 | C358: 资产编号 | D358: 资产描述 | E358: 采购/在建工程转固日期 | F358: 固定资产成本
C359: whgy007 | D359: PC机 | E359: 44742 | F359: 19867.26
C360: whgy008 | D360: PC机 | E360: 44742 | F360: 19867.26
C361: whgy009 | D361: PC机 | E361: 44742 | F361: 25929.2
C362: whgy010 | D362: PC机 | E362: 44742 | F362: 25929.2
C363: whgy011 | D363: 声卡 | E363: 44742 | F363: 8761.05
C364: whgy012 | D364: 3080显卡 | E364: 44742 | F364: 6017.7
C365: whgy013 | D365: 3080显卡 | E365: 44742 | F365: 6017.7
C366: whgy014 | D366: 3090显卡 | E366: 44742 | F366: 14070.8
C367: whgy015 | D367: 3090显卡 | E367: 44742 | F367: 14070.8
A368: 电子设备 | F368: =SUM(F359:F367) -> 140530.97
A372: 2022年南京梦马 | C372: 资产编号 | D372: 资产描述 | E372: 采购/在建工程转固日期 | F372: 固定资产成本
C373: mm001 | D373: 云手机服务器 | E373: 44681 | F373: 48000
F374: =F373 -> 48000
A379: 2023年南京硅基 | C379: 资产编号 | D379: 资产描述 | E379: 采购/在建工程转固日期 | F379: 固定资产成本
C380: gj0757 | D380: PC机器（推流） | E380: 45046 | F380: 7699.12
C381: gj0758 | D381: PC机器（推流） | E381: 45046 | F381: 7699.12
C382: gj0759 | D382: PC机器（推流） | E382: 45046 | F382: 7699.12
C383: gj0760 | D383: PC机器（推流） | E383: 45046 | F383: 7699.12
C384: gj0761 | D384: PC机器（推流） | E384: 45046 | F384: 7699.12
C385: gj0762 | D385: PC机器（推流） | E385: 45046 | F385: 7699.12
C386: gj0763 | D386: PC机器（推流） | E386: 45046 | F386: 7699.12
C387: gj0764 | D387: PC机器（推流） | E387: 45046 | F387: 7699.12
C388: gj0765 | D388: PC机器（推流） | E388: 45046 | F388: 7699.12
C389: gj0766 | D389: PC机器（推流） | E389: 45046 | F389: 7699.12
C390: gj0767 | D390: 华为大屏电视 | E390: 45046 | F390: 20353.98
C391: gj0768 | D391: 华为大屏电视 | E391: 45046 | F391: 20353.98
... C407: gj0786 | D407: “明基E582” 办公投影仪 | E407: 45162 | F407: 6649.18
A408: 电子设备 | F408: =SUM(F380:F407) -> 225109.38
A413: 2023年昆山硅基 | C413: 资产编号 | D413: 资产描述 | E413: 采购/在建工程转固日期 | F413: 固定资产成本
C414: KUN0001 | D414: PC机器 | E414: 45107 | F414: 8849.56
C415: KUN0002 | D415: 3090显卡 | E415: 45107 | F415: 7521.23
C416: KUN0003 | D416: PC机器 | E416: 45107 | F416: 7699.11
C417: KUN0004 | D417: PC机器 | E417: 45107 | F417: 7699.11
C418: KUN0005 | D418: PC机器 | E418: 45107 | F418: 7699.11
C419: KUN0006 | D419: PC机器 | E419: 45107 | F419: 7699.11
C420: KUN0007 | D420: PC机器 | E420: 45107 | F420: 7699.11
C421: KUN0008 | D421: PC机器 | E421: 45107 | F421: 7699.11
C422: KUN0009 | D422: PC机器 | E422: 45107 | F422: 7699.11
C423: KUN0010 | D423: PC机器 | E423: 45107 | F423: 7699.11
C424: KUN0011 | D424: PC机器 | E424: 45107 | F424: 7699.11
C425: KUN0012 | D425: PC机器 | E425: 45107 | F425: 7699.11
... C508: KUN0134 | D508: 65寸数字人立式电容一体机 | E508: 45291 | F508: 7876.1
A509: 电子设备 | F509: =SUM(F414:F508) -> 5599910.5
A513: 2023年绵阳硅基 | C513: 资产编号 | D513: 资产描述 | E513: 采购/在建工程转固日期 | F513: 固定资产成本
C514: mygj272 | D514: 3080显卡 | E514: 44985 | F514: 5663.72
C515: mygj273 | D515: 服务器 | E515: 44985 | F515: 42477.88
C516: mygj274 | D516: 服务器 | E516: 44985 | F516: 42477.88
C517: mygj275 | D517: 服务器 | E517: 44985 | F517: 42477.88
C518: mygj276 | D518: 服务器 | E518: 44985 | F518: 42477.88
C519: mygj277 | D519: 服务器 | E519: 44985 | F519: 42477.88
C520: mygj278 | D520: 服务器 | E520: 44985 | F520: 42477.88
C521: mygj279 | D521: 服务器 | E521: 44985 | F521: 42477.88
C522: mygj280 | D522: 服务器 | E522: 44985 | F522: 42477.88
C523: mygj281 | D523: 服务器 | E523: 44985 | F523: 42477.88
C524: mygj282 | D524: 服务器 | E524: 44985 | F524: 42477.88
C525: mygj283 | D525: 服务器 | E525: 44985 | F525: 42477.87
... C554: mygj312 | D554: 服务器（无显卡） | E554: 45046 | F554: 30973.45
A555: 电子设备 | F555: =SUM(F514:F554) -> 1474690.2
A561: 2024年昆山硅基 | C561: 资产编号 | D561: 资产描述 | E561: 采购/在建工程转固日期 | F561: 固定资产成本
C562: KUN0135 | D562: 1台65寸华为大屏 | E562: 45322 | F562: 18849.56
C563: KUN0136 | D563: 32寸安卓大屏 | E563: 45351 | F563: 5097.35
C564: KUN0137 | D564: 32寸安卓大屏 | E564: 45351 | F564: 5097.34
...

Sheet BS2
A1: 2022年 | B1: 南京硅基 | C1: 南京硅信 | D1: 芜湖硅语 | E1: 南京硅语 | F1: 浙江硅梦 | G1: 硅基昆山 | H1: 合计 | I1: check
A2: 一、原值
A3: 年初数 | B3: 20818967 | C3: 346731.51 | D3: 220825.64 | E3: 6598773.6 | F3: 0 | G3: 0 | H3: 27985297
A4: 本年新增额 | B4: 1899116.2 | C4: 0 | D4: 0 | E4: 0 | F4: 0 | G4: 0 | H4: 1899116.2
A5: 本年减少额 | B5: 0 | C5: 0 | D5: 0 | E5: 0 | F5: 0 | G5: 0 | H5: 0
A6: -租赁终止
A7: -租赁变更
A8: 年末数 | B8: 22718083 | C8: 346731.51 | D8: 220825.64 | E8: 6598773.6 | F8: 0 | G8: 0 | H8: 29884414
A9: 二、累计折旧
A10: 年初数 | B10: -7508479.9 | C10: -28894.3 | D10: -56987.28 | E10: -1832992.7 | F10: 0 | G10: 0 | H10: -9427354.2
A11: 本年计提额 | B11: -4886832.9 | C11: -173365.8 | D11: -85480.92 | E11: -2199591.2 | F11: 0 | G11: 0 | H11: -7345270.9
A12: 本年减少额 | B12: 0 | C12: 0 | D12: 0 | E12: 0 | F12: 0 | G12: 0 | H12: 0
A13: -租赁终止 | B13: 0 | C13: 0 | D13: 0 | E13: 0 | F13: 0 | G13: 0 | H13: 0
A14: -租赁变更 | B14: 0 | C14: 0 | D14: 0 | E14: 0 | F14: 0 | G14: 0 | H14: 0
A15: 年末数 | B15: -12395313 | C15: -202260.1 | D15: -142468.2 | E15: -4032583.9 | F15: 0 | G15: 0 | H15: -16772625
A16: 三、净额
A17: 年初数 | B17: 13310487 | C17: 317837.21 | D17: 163838.36 | E17: 4765780.9 | F17: 0 | G17: 0 | H17: 18557943
A18: 年末数 | B18: 10322770 | C18: 144471.41 | D18: 78357.44 | E18: 2566189.7 | F18: 0 | G18: 0 | H18: 13111789 | I18: =H18-'FY22-25 IFRS（合并）'!G36 -> 0.0012441725
A21: 2023年 | B21: 南京硅基 | C21: 南京硅信 | D21: 芜湖硅语 | E21: 南京硅语 | F21: 浙江硅梦 | G21: 硅基昆山 | H21: 合计
A22: 一、原值
A23: 年初数 | B23: 22718083 | C23: 346731.51 | D23: 220825.64 | E23: 6598773.6 | F23: 0 | G23: 0 | H23: 29884414
A24: 本年新增额 | B24: 0 | C24: 0 | D24: 0 | E24: 0 | F24: 1431655.6 | G24: 0 | H24: 1431655.6
A25: 本年减少额 | B25: -442908.17 | C25: -346731.51 | D25: -220825.64 | E25: 0 | F25: 0 | G25: 0 | H25: -1010465.3
A26: -租赁到期 | C26: -346731.51 | D26: -220825.64 | H26: -567557.15
A27: -租赁变更 | B27: -442908.17 | H27: -442908.17
A28: 年末数 | B28: 22275175 | C28: 0 | D28: 0 | E28: 6598773.6 | F28: 1431655.6 | G28: 0 | H28: 30305604
A29: 二、累计折旧
A30: 年初数 | B30: -12395313 | C30: -202260.1 | D30: -142468.2 | E30: -4032583.9 | F30: 0 | G30: 0 | H30: -16772625
A31: 本年计提额 | B31: -5256470.4 | C31: -144471.41 | D31: -78357.44 | E31: -2199591.2 | F31: -298261.59 | G31: 0 | H31: -7977152.1
A32: 本年减少额 | B32: 580467.97 | C32: 346731.51 | D32: 220825.64 | E32: 0 | F32: 0 | G32: 0 | H32: 1148025.1
A33: -租赁到期 | C33: 346731.51 | D33: 220825.64 | H33: 567557.15
A34: -租赁变更 | B34: 580467.97 | H34: 580467.97
A35: 年末数 | B35: -17071315 | C35: 0 | D35: 0 | E35: -6232175.2 | F35: -298261.59 | G35: 0 | H35: -23601752
A36: 三、净额
A37: 年初数 | B37: 10322770 | C37: 144471.41 | D37: 78357.44 | E37: 2566189.7 | F37: 0 | G37: 0 | H37: 13111789
A38: 年末数 | B38: 5203859.5 | C38: 0 | D38: 0 | E38: 366598.43 | F38: 1133394 | G38: 0 | H38: 6703851.9 | I38: =H38-'FY22-25 IFRS（合并）'!I36 -> 0.0021920083
A42: 2024年 | B42: 南京硅基 | C42: 南京硅信 | D42: 芜湖硅语 | E42: 南京硅语 | F42: 浙江硅梦 | G42: 硅基昆山 | H42: 合计
A43: 一、原值
A44: 年初数 | B44: 22275175 | C44: 0 | D44: 0 | E44: 6598773.6 | F44: 1431655.6 | G44: 0 | H44: 30305604
A45: 本年新增额 | B45: 0 | C45: 0 | D45: 0 | E45: 0 | F45: 0 | G45: 3662709.5 | H45: 3662709.5
A46: 本年减少额 | B46: -1456208.1 | C46: 0 | D46: 0 | E46: -6598773.6 | F46: -1431655.6 | G46: 0 | H46: -9486637.3
A47: -租赁到期 | B47: -1456208.1 | E47: -6598773.6 | H47: -8054981.7
A48: -提前退租 | F48: -1431655.6 | H48: -1431655.6
A49: -租赁变更 | H49: 0
A50: 年末数 | B50: 20818967 | C50: 0 | D50: 0 | E50: 0 | F50: 0 | G50: 3662709.5 | H50: 24481676
A51: 二、累计折旧
A52: 年初数 | B52: -17071315 | C52: 0 | D52: 0 | E52: -6232175.2 | F52: -298261.59 | G52: 0 | H52: -23601752
A53: 本年计提额 | B53: -4179976.1 | C53: 0 | D53: 0 | E53: -366598.43 | F53: -119304.64 | G53: -1220903.2 | H53: -5886782.4
A54: 本年减少额 | B54: 1456208.1 | C54: 0 | D54: 0 | E54: 6598773.6 | F54: 417566.22 | G54: 0 | H54: 8472547.9
A55: -租赁到期 | B55: 1456208.1 | C55: 0 | D55: 0 | E55: 6598773.6 | F55: 0 | G55: 0 | H55: 8054981.7
A56: -提前退租 | F56: 417566.22 | H56: 417566.22
A57: -租赁变更 | H57: 0
A58: 年末数 | B58: -19795083 | C58: 0 | D58: 0 | E58: 0 | F58: 0 | G58: -1220903.2 | H58: -21015986
A59: 三、净额
A60: 年初数 | B60: 5203859.5 | C60: 0 | D60: 0 | E60: 366598.43 | F60: 1133394 | G60: 0 | H60: 6703851.9
A61: 年末数 | B61: 1023883.3 | C61: 0 | D61: 0 | E61: 0 | F61: 0 | G61: 2441806.3 | H61: 3465689.7 | I61: =H61-'FY22-25 IFRS（合并）'!K36 -> -0.0033333343
A64: 2025.06 | B64: 南京硅基 | C64: 南京硅信 | D64: 芜湖硅语 | E64: 南京硅语 | F64: 浙江硅梦 | G64: 硅基昆山 | H64: 合计
A65: 一、原值
A66: 年初数 | B66: 20818967 | C66: 0 | D66: 0 | E66: 0 | F66: 0 | G66: 3662709.5 | H66: 24481676
A67: 本年新增额 | B67: 5075469.7 | C67: 0 | D67: 0 | E67: 0 | F67: 0 | G67: 0 | H67: 5075469.7
A68: 本年减少额 | B68: -20818967 | C68: 0 | D68: 0 | E68: 0 | F68: 0 | G68: 0 | H68: -20818967
A69: -租赁到期 | B69: -20818967 | H69: -20818967
A70: -提前退租
A71: -租赁变更
A72: 年末数 | B72: 5075469.7 | C72: 0 | D72: 0 | E72: 0 | F72: 0 | G72: 3662709.5 | H72: 8738179.2
A73: 二、累计折旧
A74: 年初数 | B74: -19795083 | C74: 0 | D74: 0 | E74: 0 | F74: 0 | G74: -1220903.2 | H74: -21015986
A75: 本年计提额 | B75: -1587824.4 | C75: 0 | D75: 0 | E75: 0 | F75: 0 | G75: -610451.59 | H75: -2198276
A76: 本年减少额 | B76: 20818967 | C76: 0 | D76: 0 | E76: 0 | F76: 0 | G76: 0 | H76: 20818967
A77: -租赁到期 | B77: 20818967 | H77: 20818967
A78: -提前退租
A79: -租赁变更
A80: 年末数 | B80: -563941.07 | C80: 0 | D80: 0 | E80: 0 | F80: 0 | G80: -1831354.8 | H80: -2395295.8
A81: 三、净额
A82: 年初数 | B82: 1023883.3 | C82: 0 | D82: 0 | E82: 0 | F82: 0 | G82: 2441806.3 | H82: 3465689.7
A83: 年末数 | B83: 4511528.6 | C83: 0 | D83: 0 | E83: 0 | F83: 0 | G83: 1831354.8 | H83: 6342883.4 | I83: =H83-'FY22-25 IFRS（合并）'!O36 -> -0.0044444436
A87: 2025.12 | B87: 南京硅基 | C87: 南京硅信 | D87: 芜湖硅语 | E87: 南京硅语 | F87: 浙江硅梦 | G87: 硅基昆山 | H87: 合计
A88: 一、原值
A89: 年初数 | B89: 20818967 | C89: 0 | D89: 0 | E89: 0 | F89: 0 | G89: 3662709.5 | H89: 24481676
A90: 本年新增额 | B90: 5075469.7 | C90: 0 | D90: 0 | E90: 0 | F90: 0 | G90: 0 | H90: 5075469.7
A91: 本年减少额 | B91: -20818967 | C91: 0 | D91: 0 | E91: 0 | F91: 0 | G91: 0 | H91: -20818967
A92: -租赁到期 | B92: -20818967 | H92: -20818967
A93: -提前退租
A94: -租赁变更
A95: 年末数 | B95: 5075469.7 | C95: 0 | D95: 0 | E95: 0 | F95: 0 | G95: 3662709.5 | H95: 8738179.2
A96: 二、累计折旧
A97: 年初数 | B97: -19795083 | C97: 0 | D97: 0 | E97: 0 | F97: 0 | G97: -1220903.2 | H97: -21015986
A98: 本年计提额 | B98: -2433736 | C98: 0 | D98: 0 | E98: 0 | F98: 0 | G98: -1220903.2 | H98: -3654639.2
A99: 本年减少额 | B99: 20818967 | C99: 0 | D99: 0 | E99: 0 | F99: 0 | G99: 0 | H99: 20818967
A100: -租赁到期 | B100: 20818967 | H100: 20818967
A101: -提前退租
A102: -租赁变更
A103: 年末数 | B103: -1409852.7 | C103: 0 | D103: 0 | E103: 0 | F103: 0 | G103: -2441806.4 | H103: -3851659
A104: 三、净额
A105: 年初数 | B105: 1023883.3 | C105: 0 | D105: 0 | E105: 0 | F105: 0 | G105: 2441806.3 | H105: 3465689.7
A106: 年末数 | B106: 3665617 | C106: 0 | D106: 0 | E106: 0 | F106: 0 | G106: 1220903.2 | H106: 4886520.2 | I106: =H106-'FY22-25 IFRS（合并）'!Q36 -> -0.02
A118: 单位名称 | B118: 合同编号 | C118: 签订日期 | D118: 租赁标的 （合同载明） | E118: 用途 | F118: 起租日 | G118: 到期日 | H118: 资本化时点 | I118: 资本化的租赁期（月） | J118: 折旧期（月） | K118: 租期期（月） | L118: 支付频率 | M118: 租金币种 | N118: 年折现率 | O118: 折现率 | P118: 续租选择权
A120: 南京硅基 | B120: L01 南京硅基-南京万博 | C120: 43667 | D120: 万博科技园C号楼4层整层和5层整层 | E120: 办公 | F120: 43896 | G120: 45721 | H120: =IF(F120<DATE(2019,1,1),MAX(C120,DATE(2019,1,1)),MAX(C120,F120)) -> 43896 | I120: =DATEDIF(H120,G120,"m")+1 -> 60 | J120: =I120 -> 60 | K120: =DATEDIF(F120,G120,"m")+1 -> 60 | L120: 每半年 | M120: CNY | N120: 0.0465 | O120: =IF(L120="每月",N120/12,IF(L120="每两个月",N120/6,IF(L120="每三个月",N120/4,IF(L120="每半年",N120/2,N120)))) -> 0.02325 | P120: 享有优先续租权，期满前三个月书面通知，到期后6个月短期续租权。
A121: 南京硅基 | B121: L02 南京硅基-上海华新 | C121: 2022年1月25日 | D121: 上海市浦东新区银城路116/128号大华银行大厦8楼02室 | E121: 商业、办公 | F121: 44621 | G121: 45351 | H121: =IF(F121<DATE(2019,1,1),MAX(C121,DATE(2019,1,1)),MAX(C121,F121)) -> 44621 | I121: =DATEDIF(H121,G121,"m")+1 -> 24 | J121: =I121 -> 24 | K121: =DATEDIF(F121,G121,"m")+1 -> 24 | L121: 每月 | M121: CNY | N121: 0.046 | O121: =IF(L121="每月",N121/12,IF(L121="每两个月",N121/6,IF(L121="每三个月",N121/4,IF(L121="每半年",N121/2,N121)))) -> 0.0038333333 | P121: 无续租条款
A122: 南京硅基 | B122: L02-1 南京硅基-上海华新 | C122: 2023年2月15日 | D122: 上海市浦东新区银城路116/128号大华银行大厦8楼01室 | E122: 商业、办公 | F122: 44986 | G122: 45351 | H122: =IF(F122<DATE(2019,1,1),MAX(C122,DATE(2019,1,1)),MAX(C122,F122)) -> 44986 | I122: =DATEDIF(H122,G122,"m")+1 -> 12 | J122: =I122 -> 12 | K122: =DATEDIF(F122,G122,"m")+1 -> 12 | L122: 每月 | M122: CNY | N122: 0.043 | O122: =IF(L122="每月",N122/12,IF(L122="每两个月",N122/6,IF(L122="每三个月",N122/4,IF(L122="每半年",N122/2,N122)))) -> 0.0035833333 | P122: 无续租条款
...

Sheet BS3
R1: IA清单：
R2: 序号 | S2: 主体 | T2: 年份 | U2: 资产描述 | V2: 资产类别 | W2: 采购日期 | X2: 购置成本
R3: 1 | S3: 南京硅基 | T3: 2025 | U3: 灵云智能语音识别平台软件V1.0 | V3: 计算机软件 | W3: 43159 | X3: 299145.29
R4: 2 | S4: 南京硅基 | T4: 2025 | U4: 灵云智能语音识别平台软件V6.0 | V4: 计算机软件 | W4: 43281 | X4: 172413.8
C5: 无形资产 | E5: 2022年12月31日 | G5: 2023年12月31日 | I5: 2024年12月31日 | K5: 2025年12月31日 | M5: 2025年06月30日 | R5: 3 | S5: 南京硅基 | T5: 2025 | U5: 阿里云语音识别专有云软件V1.0 已摊销完896551.72 | V5: 计算机软件 | W5: 43434 | X5: 896551.72
R6: 4 | S6: 南京硅基 | T6: 2025 | U6: 阿里云语音识别专有云软件V1.0 已摊销完319933.15 | V6: 计算机软件 | W6: 43434 | X6: 319933.15
E7: a | G7: b | I7: c | K7: d | M7: d2 | R7: 5 | S7: 南京硅基 | T7: 2025 | U7: 昆石运营支持系统软件V2.1 | V7: 计算机软件 | W7: 43677 | X7: 80353.98
R8: 6 | S8: 南京硅基 | T8: 2025 | U8: 金蝶K3软件（财务供应链制造）2020/5/1 | V8: 计算机软件 | W8: 43982 | X8: 53189.66
C9: 软件 | E9: 643447.43 | G9: 568226.39 | I9: 0 | K9: 0 | M9: 0 | R9: 7 | S9: 南京硅基 | T9: 2025 | U9: 金蝶K3软件（财务供应链制造）2020/7/1 | V9: 计算机软件 | W9: 44043 | X9: 9433.96
C10: 外购专利 | E10: 622639.08 | G10: 145168.21 | I10: 493005.35 | K10: 417784.31 | M10: 455394.83 | R10: 8 | S10: 南京硅基 | T10: 2025 | U10: 阿里云语音识别专有软件V1.0 2020/8/1 | V10: 计算机软件 | W10: 44074 | X10: 0
R11: 9 | S11: 南京硅基 | T11: 2025 | U11: Jumpserver运维安全软件 | V11: 计算机软件 | W11: 44165 | X11: 36792.45
C12: 合计 | E12: =SUM(E9:E11) -> 1266086.5 | G12: =SUM(G9:G11) -> 713394.6 | I12: =SUM(I9:I11) -> 493005.35 | K12: =SUM(K9:K11) -> 417784.31 | M12: =SUM(M9:M11) -> 455394.83 | R12: 10 | S12: 南京硅基 | T12: 2025 | U12: Jumpserver运维安全软件 | V12: 计算机软件 | W12: 44165 | X12: 36792.45
C13: Check： | E13: =ROUND(E12-'FY22-25 IFRS（合并）'!G37,0) -> 0 | G13: =ROUND(G12-'FY22-25 IFRS（合并）'!I37,0) -> 0 | I13: =ROUND(I12-'FY22-25 IFRS（合并）'!K37,0) -> 0 | K13: =K12-'FY22-25 IFRS（合并）'!Q37 -> 0 | M13: =ROUND(M12-'FY22-25 IFRS（合并）'!O37,0) -> 0 | R13: 11 | S13: 南京硅基 | T13: 2025 | U13: MAYA、MarvelousDesigner以及Axure | V13: 计算机软件 | W13: 44347 | X13: 222987.14
R14: 12 | S14: 南京硅基 | T14: 2025 | U14: 阿里云语音识别专有云软件V1.0 2021/9/1 | V14: 计算机软件 | W14: 44469 | X14: 1258938.1
R15: 13 | S15: 南京硅语 | T15: 2025 | U15: 多媒体视频服务软件Hirender V3.0 | V15: 计算机软件 | W15: 44500 | X15: 74543.56
R16: 14 | S16: 南京硅语 | T16: 2025 | U16: 集控平台Hirender | V16: 计算机软件 | W16: 44500 | X16: 14521.48
R17: 15 | S17: 南京硅语 | T17: 2025 | U17: 手机与平版播控系统哲浩 | V17: 计算机软件 | W17: 44500 | X17: 19361.96
R18: 16 | S18: 南京硅基 | T18: 2025 | U18: 微软Visual Studio Pro | V18: 计算机软件 | W18: 44561 | X18: 43283.19
R19: 17 | S19: 南京硅基 | T19: 2025 | U19: 微软windowspro中文专业版 | V19: 计算机软件 | W19: 44561 | X19: 247504.43
R20: 18 | S20: 南京硅语 | T20: 2025 | U20: 华为AC控制器的无线AP设备管理授权软件 | V20: 计算机软件 | W20: 44561 | X20: 14508.67
R21: 19 | S21: 南京硅基 | T21: 2025 | U21: 2017107941508一种文本模式识别方法及系统 | V21: 外购专利 | W21: 44377 | X21: 40566.038
R22: 20 | S22: 南京硅基 | T22: 2025 | U22: 2018104081557一种分布式语音控制方法及系统 | V22: 外购专利 | W22: 44377 | X22: 32075.472
R23: 21 | S23: 南京硅基 | T23: 2025 | U23: 202010852699X一种用于语音指令捕捉的信号精确度调节系统及方法 | V23: 外购专利 | W23: 44377 | X23: 42079.208
R24: 22 | S24: 南京硅基 | T24: 2025 | U24: 2020111198045基于卷积循环神经网络的单通道人声与背景声分离方法 | V24: 外购专利 | W24: 44377 | X24: 42079.208
R25: 23 | S25: 南京硅基 | T25: 2025 | U25: 2020103305789一种基于语音识别控制的巡检机器人系统 | V25: 外购专利 | W25: 44377 | X25: 46039.604
... R148: 146 | S148: 宿迁硅基 | T148: 2022 | U148: 2021104565241一种情感分类方法及设备 | V148: 外购专利 | W148: 44561 | X148: 32178.22
R158: 序号 | S158: 主体 | T158: 年份 | U158: 资产描述 | V158: 资产类别 | W158: 采购日期 | X158: 购置成本
R159: 1 | S159: 南京硅基 | T159: 2018 | U159: 灵云智能语音识别平台软件V1.0 | V159: 计算机软件 | W159: 43159 | X159: 299145.29
R160: 2 | S160: 南京硅基 | T160: 2018 | U160: 灵云智能语音识别平台软件V6.0 | V160: 计算机软件 | W160: 43281 | X160: 172413.8
R161: 3 | S161: 南京硅基 | T161: 2018 | U161: 阿里云语音识别专有云软件V1.0 已摊销完896551.72 | V161: 计算机软件 | W161: 43434 | X161: 896551.72
R162: 4 | S162: 南京硅基 | T162: 2018 | U162: 阿里云语音识别专有云软件V1.0 已摊销完319933.15 | V162: 计算机软件 | W162: 43434 | X162: 319933.15
R163: 5 | S163: 南京硅基 | T163: 2019 | U163: 昆石运营支持系统软件V2.1 | V163: 计算机软件 | W163: 43677 | X163: 80353.98
R164: 6 | S164: 南京硅基 | T164: 2020 | U164: 金蝶K3软件（财务供应链制造）2020/5/1 | V164: 计算机软件 | W164: 43982 | X164: 53189.66
R165: 7 | S165: 南京硅基 | T165: 2020 | U165: 金蝶K3软件（财务供应链制造）2020/7/1 | V165: 计算机软件 | W165: 44043 | X165: 9433.96
R166: 8 | S166: 南京硅基 | T166: 2020 | U166: 销售易 | V166: 计算机软件 | W166: 44074 | X166: 193557.56
R167: 9 | S167: 南京硅基 | T167: 2020 | U167: Adobe软件2020/8/1 | V167: 计算机软件 | W167: 44074 | X167: 107969.03
R168: 10 | S168: 南京硅基 | T168: 2020 | U168: 阿里云语音识别专有软件V1.0 2020/8/1 | V168: 计算机软件 | W168: 44074 | X168: 0
R169: 11 | S169: 南京硅基 | T169: 2020 | U169: Jumpserver运维安全软件 | V169: 计算机软件 | W169: 44165 | X169: 36792.45
R170: 12 | S170: 南京硅基 | T170: 2020 | U170: Jumpserver运维安全软件 | V170: 计算机软件 | W170: 44165 | X170: 36792.45
... R201: 43 | S201: 宿迁硅基 | T201: 2021 | U201: 2021104565241一种情感分类方法及设备 | V201: 外购专利 | W201: 44561 | X201: 32178.22

Sheet BS4 合同资产明细
P1: =P2-'FY22-25 IFRS（合并）'!Q47 -> 492664.59 | Q1: =Q2-'FY22-25 IFRS（合并）'!Q38 -> 472455.39
G2: =SUBTOTAL(9,G4:G70) -> 507784.39 | H2: =SUBTOTAL(9,H4:H70) -> 59015 | I2: =SUBTOTAL(9,I4:I70) -> 5602907.9 | J2: =SUBTOTAL(9,J4:J70) -> 4016920.9 | K2: =SUBTOTAL(9,K4:K70) -> 8142850.4 | L2: =SUBTOTAL(9,L4:L70) -> 674389.34 | M2: =SUBTOTAL(9,M4:M70) -> 7488285.7 | N2: =SUBTOTAL(9,N4:N70) -> 1598106.6 | O2: =SUM(O71:O134) -> 21220336 | P2: =SUM(P71:P134) -> 15284780 | Q2: =SUM(Q71:Q134) -> 5935555.9
B3: 客户 | C3: 合同编号 | D3: 合同名称 | E3: 验收时间 | F3: 质保到期日 | G3: 22年质保金余额 | H3: 22年一年内到期 | I3: 23年质保金余额 | J3: 23年一年内到期 | K3: 24年质保金余额 | L3: 24年一年内到期 | M3: 25年06月质保金余额 | N3: 25年06月一年内到期 | O3: 25年12月质保金余额 | P3: 25年12月一年内到期的非流动资产 | Q3: 25年12月合同资产
B4: 中移建设有限公司宿迁分公司 | C4: ST-ZYSQ001 | D4: 城区智慧技防小区项目合同（沭阳县城区） | E4: 44834 | F4: 45734 | G4: 432769.39 | H4: 0
B5: 中国铁塔股份有限公司镇江分公司 | C5: ST-TTZJ000 | D5: 镇江奇美化工有限公司5G防爆云平台服务项目采购合同 | E5: 44834 | F5: 45554 | G5: 16000 | H5: 0
B6: 中移建设有限公司无锡分公司 | C6: ST-ZYWX003-1 | D6: 无锡斑目信息5G智能化改造项目采购合同 | E6: 44926 | F6: 45291 | G6: 56000 | H6: 56000
B7: 中移铁通有限公司无锡分公司 | C7: ST-TTWX004 | D7: 农商行门禁智能维保项目合同 | E7: 44926 | F7: 45291 | G7: 3015 | H7: 3015
B8: 中国移动通信集团江苏有限公司常州分公司 | C8: ST-ZYCZ002 | D8: 江苏今浪信息技术有限公司大数据广告投放系统项目采购合同 | E8: 45026 | F8: 45391 | I8: 136795 | J8: 136795
B9: 中移建设有限公司无锡分公司 | C9: ST-ZYWX009 | D9: 2022年梁溪区扬名街道老旧小区智能信息化系统改造三网改造部份ICT（DJ）项目合同 | E9: 44957 | F9: 45322 | I9: 472850 | J9: 472850
B10: 中移建设有限公司宿迁分公司 | C10: ST-ZYSQ001 | D10: 城区智慧技防小区项目合同（沭阳县城区） | E10: 44834 | F10: 45734 | I10: 432769.39 | J10: 0
B11: 中移铁通有限公司盐城分公司 | C11: ST-TTYC006 | D11: 2022-2025年安全监管应用智能化支撑服务项目采购分包合同 | E11: 45283 | F11: 46378 | I11: 559932.75 | J11: 0
B12: 中移建设有限公司无锡分公司 | C12: ST-ZYWX010 | D12: 2022年梁溪区山北街道老旧小区智能信息化系统改造三网改造部份ICT（DJ）项目合同 | E12: 44957 | F12: 45322 | I12: 430600 | J12: 430600
B13: 中移建设有限公司无锡分公司 | C13: ST-ZYWX011 | D13: 2022年梁溪区惠山街道老旧小区智能信息化系统改造三网改造部份ICT（DJ）项目合同 | E13: 44957 | F13: 45322 | I13: 368200 | J13: 368200
B14: 中移铁通有限公司盐城分公司 | C14: ST-TTYC010 | D14: 黑石云平台客户侧运营支撑服务项目分包合同 | E14: 45179 | F14: 45544 | I14: 243747.84 | J14: 243747.84
B15: 中国移动通信集团江苏有限公司盐城分公司 | C15: ST-ZYYC006 | D15: 移动云智能化安全办公相关服务项目采购合同 | E15: 45260 | F15: 46355 | I15: 290000 | J15: 0
B16: 中移信息系统集成有限公司 | C16: ST-ZYXT001-1 | D16: 江苏省某中学电子信息采购项目合同 | E16: 44957 | F16: 46052 | I16: 174745.88 | J16: 0
B17: 中移铁通有限公司盐城分公司 | C17: ST-TTYC009 | D17: 科宏行业云支撑服务项目分包合同 | E17: 45260 | F17: 45625 | I17: 243723.73 | J17: 243723.73
B18: 中移建设有限公司无锡分公司 | C18: ST-ZYWX004-1 | D18: 澄江街道天鹤社区城市更新老旧小区信息智能化系统改造项目合同 | E18: 45016 | F18: 46111 | I18: 96250 | J18: 0
B19: 中移铁通有限公司盐城分公司 | C19: ST-TTYC007 | D19: 鑫真源云平台客户侧运营支撑服务项目分包合同 | E19: 45169 | F19: 45534 | I19: 243747.84 | J19: 243747.84
... B30: 中移铁通有限公司连云港分公司 | C30: ST-TTLYG001 | D30: 赣榆区公安局居民小区智能感知项目（存储平台）采购合同 | E30: 45076 | F30: 45441 | I30: 618360.11 | J30: 618360.11
B31: 中国移动通信集团江苏有限公司常州分公司 | C31: ST-ZYCZ003 | D31: 实战平台项目采购合同 | E31: 45471 | F31: 46566 | K31: 3623910 | L31: 0
B32: 江苏移动信息系统集成有限公司 | C32: ST-YDJC003-1 | D32: “情指行”一体化实战平台项目 | E32: 45470 | F32: 46565 | K32: 1118284 | L32: 0
B33: 江苏移动信息系统集成有限公司 | C33: ST-YDJC002 | D33: 2023年全要素警务信息平台代码开发服务项目 | E33: 45471 | F33: 46566 | K33: 1080000 | L33: 0
B34: 中移建设有限公司宿迁分公司 | C34: ST-ZYSQ001 | D34: 城区智慧技防小区项目合同（沭阳县城区） | E34: 44834 | F34: 45734 | K34: 432769.39 | L34: 432769.39
B35: 中移铁通有限公司盐城分公司 | C35: ST-TTYC006 | D35: 2022-2025年安全监管应用智能化支撑服务项目采购分包合同 | E35: 45283 | F35: 46378 | K35: 559932.75 | L35: 0
B36: 中国移动通信集团江苏有限公司盐城分公司 | C36: ST-ZYYC006 | D36: 移动云智能化安全办公相关服务项目采购合同 | E36: 45260 | F36: 46355 | K36: 290000 | L36: 0
B37: 中移信息系统集成有限公司 | C37: ST-ZYXT001-1 | D37: 江苏省某中学电子信息采购项目合同 | E37: 44957 | F37: 46052 | K37: 174745.88 | L37: 0
B38: 中移建设有限公司无锡分公司 | C38: ST-ZYWX004-1 | D38: 澄江街道天鹤社区城市更新老旧小区信息智能化系统改造项目合同 | E38: 45016 | F38: 46111 | K38: 96250 | L38: 0
B39: 中移铁通有限公司镇江分公司 | C39: ST-TTZJ012 | D39: 镇江市丹徒区电子政务外网升级运营服务项目专线增值服务分包 | E39: 45380 | F39: 46460 | K39: 58707.6 | L39: 0
B40: 中移铁通有限公司镇江分公司 | C40: ST-TTZJ004 | D40: 镇江市医疗保障局定点药店音视频监管系统建设项目分包 | E40: 45066 | F40: 46161 | K40: 26314 | L40: 0
B41: 中移建设有限公司无锡分公司 | C41: ST-ZYWX031-1 | D41: 新吴区旺庄街道老小区信息化智能改造项目 | E41: 45471 | F41: 45836 | K41: 126548.1 | L41: 126548.1
B42: 中移建设有限公司江苏分公司 | C42: ST-ZYJS009 | D42: （扬州）2024年属地一体化人员支撑项目 | E42: 45443 | F42: 46173 | K42: 291900 | L42: 0
... B53: 中移铁通有限公司镇江分公司 | C53: ST-TTZJ014 | D53: 中国邮政集团有限公司镇江市分公司2023年网点改造LED屏采购及安装项目分包 | E53: 45384 | F53: 46824 | K53: 417.6 | L53: 0
B54: 中国移动通信集团江苏有限公司常州分公司 | C54: ST-ZYCZ003 | D54: 实战平台项目采购合同 | E54: 45471 | F54: 46566 | M54: 3623910 | N54: 0
B55: 江苏移动信息系统集成有限公司 | C55: ST-YDJC003-1 | D55: “情指行”一体化实战平台项目 | E55: 45470 | F55: 46565 | M55: 1118284 | N55: 0
B56: 江苏移动信息系统集成有限公司 | C56: ST-YDJC002 | D56: 2023年全要素警务信息平台代码开发服务项目 | E56: 45471 | F56: 46566 | M56: 1080000 | N56: 0
B57: 中移铁通有限公司盐城分公司 | C57: ST-TTYC006 | D57: 2022-2025年安全监管应用智能化支撑服务项目采购分包合同 | E57: 45283 | F57: 46378 | M57: 559932.75 | N57: 559932.75
B58: 中国移动通信集团江苏有限公司盐城分公司 | C58: ST-ZYYC006 | D58: 移动云智能化安全办公相关服务项目采购合同 | E58: 45260 | F58: 46355 | M58: 290000 | N58: 290000
B59: 中移信息系统集成有限公司 | C59: ST-ZYXT001-1 | D59: 江苏省某中学电子信息采购项目合同 | E59: 44957 | F59: 46052 | M59: 174745.88 | N59: 174745.88
B60: 中移建设有限公司无锡分公司 | C60: ST-ZYWX004-1 | D60: 澄江街道天鹤社区城市更新老旧小区信息智能化系统改造项目合同 | E60: 45016 | F60: 46111 | M60: 96250 | N60: 96250
B61: 中移铁通有限公司镇江分公司 | C61: ST-TTZJ012 | D61: 镇江市丹徒区电子政务外网升级运营服务项目专线增值服务分包 | E61: 45380 | F61: 46460 | M61: 58707.6 | N61: 0
B62: 中移铁通有限公司镇江分公司 | C62: ST-TTZJ004 | D62: 镇江市医疗保障局定点药店音视频监管系统建设项目分包 | E62: 45066 | F62: 46161 | M62: 26314 | N62: 26314
B63: 中移建设有限公司江苏分公司 | C63: ST-ZYJS009 | D63: （扬州）2024年属地一体化人员支撑项目 | E63: 45443 | F63: 46173 | M63: 291900 | N63: 291900
B64: 中移建设有限公司无锡分公司 | C64: ST-ZYWX030-1 | D64: 新安街道老街区信息化建设 ICT 项目 | E64: 45380 | F64: 46110 | M64: 60580.05 | N64: 60580.05
B65: 中移建设有限公司南通分公司 | C65: ST-JSNT004-1 | D65: 如东经济开发区管委会大楼室外监控系统改造项目 | E65: 45301 | F65: 46031 | M65: 35521.4 | N65: 35521.4
... B69: 中移铁通有限公司镇江分公司 | C69: ST-TTZJ014 | D69: 中国邮政集团有限公司镇江市分公司2023年网点改造LED屏采购及安装项目分包 | E69: 45384 | F69: 46824 | M69: 417.6 | N69: 0
B70: 溧阳市栗里文旅投资发展有限公司 | M70: 58840 | N70: 58840
A71: 南京硅基 | B71: 中国移动通信集团江苏有限公司常州分公司 | C71: ST-ZYCZ003 | D71: 实战平台项目采购合同 | E71: 45471 | F71: 46566 | O71: 3623910 | P71: 0 | Q71: =O71-P71 -> 3623910
A72: 南京硅基 | B72: 江苏移动信息系统集成有限公司 | C72: ST-YDJC003-1 | D72: “情指行”一体化实战平台项目 | E72: 45470 | F72: 46565 | O72: 1118284 | P72: 0 | Q72: =O72-P72 -> 1118284
A73: 南京硅基 | B73: 江苏移动信息系统集成有限公司 | C73: ST-YDJC002 | D73: 2023年全要素警务信息平台代码开发服务项目 | E73: 45471 | F73: 46566 | O73: 1080000 | P73: 0 | Q73: =O73-P73 -> 1080000
A74: 南京硅基 | B74: 中移铁通有限公司盐城分公司 | C74: ST-TTYC006 | D74: 2022-2025年安全监管应用智能化支撑服务项目采购分包合同 | E74: 45283 | F74: 46378 | O74: 14928.71 | P74: 14928.71 | Q74: =O74-P74 -> 0
A75: 南京硅基 | B75: 中国移动通信集团江苏有限公司盐城分公司 | C75: ST-ZYYC006 | D75: 移动云智能化安全办公相关服务项目采购合同 | E75: 45260 | F75: 46355 | O75: 290000 | P75: 290000 | Q75: =O75-P75 -> 0
A76: 南京硅基 | B76: 中移信息系统集成有限公司 | C76: ST-ZYXT001-1 | D76: 江苏省某中学电子信息采购项目合同 | E76: 44957 | F76: 46052 | O76: 174745.88 | P76: 174745.88 | Q76: =O76-P76 -> 0
A77: 南京硅基 | B77: 中移建设有限公司无锡分公司 | C77: ST-ZYWX004-1 | D77: 澄江街道天鹤社区城市更新老旧小区信息智能化系统改造项目合同 | E77: 45016 | F77: 46111 | O77: 96250 | P77: 96250 | Q77: =O77-P77 -> 0
A78: 南京硅基 | B78: 中移铁通有限公司镇江分公司 | C78: ST-TTZJ012 | D78: 镇江市丹徒区电子政务外网升级运营服务项目专线增值服务分包 | E78: 45380 | F78: 46460 | O78: 58707.6 | P78: 0 | Q78: =O78-P78 -> 58707.6
A79: 南京硅基 | B79: 中移铁通有限公司镇江分公司 | C79: ST-TTZJ004 | D79: 镇江市医疗保障局定点药店音视频监管系统建设项目分包 | E79: 45066 | F79: 46161 | O79: 26314 | P79: 26314 | Q79: =O79-P79 -> 0
A80: 南京硅基 | B80: 中移建设有限公司江苏分公司 | C80: ST-ZYJS009 | D80: （扬州）2024年属地一体化人员支撑项目 | E80: 45443 | F80: 46173 | O80: 291900 | P80: 291900 | Q80: =O80-P80 -> 0
A81: 南京硅基 | B81: 中移建设有限公司无锡分公司 | C81: ST-ZYWX030-1 | D81: 新安街道老街区信息化建设 ICT 项目 | E81: 45380 | F81: 46110 | O81: 60580.05 | P81: 60580.05 | Q81: =O81-P81 -> 0
A82: 南京硅基 | B82: 中移铁通有限公司南通分公司 | C82: ST-JSNT035 | D82: DICT合作实施协议-启东职校北侧地块信息化项目 | E82: 45715 | F82: 46810 | O82: 48161.4 | P82: 0 | Q82: =O82-P82 -> 48161.4
... A85: 南京硅基 | B85: 中移铁通有限公司镇江分公司 | C85: ST-TTZJ014 | D85: 中国邮政集团有限公司镇江市分公司2023年网点改造LED屏采购及安装项目分包 | E85: 45384 | F85: 46824 | O85: 417.6 | P85: 0 | Q85: =O85-P85 -> 417.6
A86: 南京硅基 | B86: 溧阳市栗里文旅投资发展有限公司 | O86: 58840 | P86: 58840 | Q86: =O86-P86 -> 0
A87: 南京硅基 | B87: 南京万博软件科技有限公司 | O87: 100000 | P87: 100000 | Q87: =O87-P87 -> 0
A88: 嘉兴硅基 | B88: 成都卡普数据服务有限责任公司 | D88: 能源行业智能化开发项目 | E88: 46022 | F88: =E88+60 -> 46082 | O88: 422000 | P88: 422000 | Q88: =O88-P88 -> 0
A89: 嘉兴硅基 | B89: 成都卡普数据服务有限责任公司 | D89: 新能源行业智能化管理建设项目 | E89: 46017 | F89: =E89+60 -> 46077 | O89: 620000 | P89: 620000 | Q89: =O89-P89 -> 0
A90: 嘉兴硅基 | B90: 成都万维图新信息技术有限公司 | D90: 园区智能化全域建设项目 | E90: 46022 | F90: =E90+60 -> 46082 | O90: 520000 | P90: 520000 | Q90: =O90-P90 -> 0
A91: 嘉兴硅基 | B91: 成都万维图新信息技术有限公司 | D91: 交通行业智能化运维分析系统技术开发服务项目 | E91: 46022 | F91: =E91+60 -> 46082 | O91: 380000 | P91: 380000 | Q91: =O91-P91 -> 0
A92: 嘉兴硅基 | B92: 航天广通科技（深圳）有限公司 | D92: 智慧交通设备只能诊断技术开发服务项目 | E92: 46022 | F92: =E92+60 -> 46082 | O92: 320000 | P92: 320000 | Q92: =O92-P92 -> 0
A93: 嘉兴硅基 | B93: 南京晶赛电气科技有限公司 | D93: 智能数据分析与数字员工系统技术开发服务项目 | E93: 46022 | F93: =E93+60 -> 46082 | O93: 500000 | P93: 500000 | Q93: =O93-P93 -> 0
A94: 嘉兴硅基 | B94: 南京迅集科技有限公司 | D94: 基于数字人智能交互平台的电力大数据治理平台实施 | E94: 46022 | F94: =E94+60 -> 46082 | O94: 322000 | P94: 322000 | Q94: =O94-P94 -> 0
A95: 嘉兴硅基 | B95: 南京迅集科技有限公司 | D95: 基于数字人智能交互平台的远程巡检系统实施 | E95: 46022 | F95: =E95+60 -> 46082 | O95: 312800 | P95: 312800 | Q95: =O95-P95 -> 0
A96: 嘉兴硅基 | B96: 南京迅集科技有限公司 | D96: 数智化电力大数据安全管控平台实施 | E96: 46022 | F96: =E96+60 -> 46082 | O96: 317000 | P96: 317000 | Q96: =O96-P96 -> 0
A97: 嘉兴硅基 | B97: 南京迅集科技有限公司 | D97: 数智化企业级电力人工智能+AR知识图谱平台实施项目 | E97: 46022 | F97: =E97+60 -> 46082 | O97: 322000 | P97: 322000 | Q97: =O97-P97 -> 0
A98: 嘉兴硅基 | B98: 南京迅集科技有限公司 | D98: 基于数字人智能交互平台的电力数智化运维平台实施 | E98: 46022 | F98: =E98+60 -> 46082 | O98: 211000 | P98: 211000 | Q98: =O98-P98 -> 0
A99: 嘉兴硅基 | B99: 南京迅集科技有限公司 | D99: 基于数字人智能交互平台的变电站智能操作防误系统实施项目 | E99: 46022 | F99: =E99+60 -> 46082 | O99: 309400 | P99: 309400 | Q99: =O99-P99 -> 0
... A103: 嘉兴硅基 | B103: 北京加菲智能科技有限公司 | D103: 智能化低端型安全接入网关客户端信创改造 | E103: 46022 | F103: =E103+60 -> 46082 | O103: 326000 | P103: 326000 | Q103: =O103-P103 -> 0
A104: 嘉兴硅基 | B104: 北京加菲智能科技有限公司 | D104: 信息安全网络隔离装置智能化管理功能实现服务 | E104: 46022 | F104: =E104+60 -> 46082 | O104: 352000 | P104: =O104 -> 352000 | Q104: =O104-P104 -> 0
A105: 嘉兴硅基 | B105: 北京加菲智能科技有限公司 | D105: 智能化主数据、稽核风控运维支撑技术服务 | E105: 46022 | F105: =E105+60 -> 46082 | O105: 276500 | P105: 276500 | Q105: =O105-P105 -> 0
A106: 嘉兴硅基 | B106: 北京加菲智能科技有限公司 | D106: 智慧数字业务风险预警监控系统应用实施项目 | E106: 46022 | F106: =E106+60 -> 46082 | O106: 281000 | P106: 281000 | Q106: =O106-P106 -> 0
A107: 嘉兴硅基 | B107: 高勘（广州）技术有限公司 | D107: 智能数据脱敏与交互决策平台 | E107: 46022 | F107: =E107+60 -> 46082 | O107: 282000 | P107: 282000 | Q107: =O107-P107 -> 0
A108: 嘉兴硅基 | B108: 高勘（广州）技术有限公司 | D108: 智能脚本处理与软件分发平台 | E108: 46022 | F108: =E108+60 -> 46082 | O108: 273500 | P108: 273500 | Q108: =O108-P108 -> 0
A109: 嘉兴硅基 | B109: 高勘（广州）技术有限公司 | D109: 智能证书密钥全生命周期管理平台 | E109: 46022 | F109: =E109+60 -> 46082 | O109: 243500 | P109: 243500 | Q109: =O109-P109 -> 0
A110: 嘉兴硅基 | B110: 高勘（广州）技术有限公司 | D110: 智能设备身份与信任分级交互系统 | E110: 46022 | F110: =E110+60 -> 46082 | O110: 231000 | P110: 231000 | Q110: =O110-P110 -> 0
A111: 嘉兴硅基 | B111: 北京天易数智科技有限公司 | D111: 资产数字化业务融合优化项目 | E111: 46022 | F111: =E111+60 -> 46082 | O111: 196590 | P111: 196590 | Q111: =O111-P111 -> 0
A112: 嘉兴硅基 | B112: 北京天易数智科技有限公司 | D112: 数据底座跨专业数据整理与关系梳理 | E112: 46022 | F112: =E112+60 -> 46082 | O112: 161600 | P112: 161600 | Q112: =O112-P112 -> 0
A113: 嘉兴硅基 | B113: 安徽天易数聚科技有限公司 | D113: 智慧电网运维管理 | E113: 46022 | F113: =E113+60 -> 46082 | O113: 121275 | P113: 121275 | Q113: =O113-P113 -> 0
A114: 嘉兴硅基 | B114: 安徽天易数聚科技有限公司 | D114: 智慧数字风险内控模型构建与智能化动态合规检测系统 | E114: 46022 | F114: =E114+60 -> 46082 | O114: 147000 | P114: 147000 | Q114: =O114-P114 -> 0
A115: 嘉兴硅基 | B115: 安徽天易数聚科技有限公司 | D115: 智能化数据传输与 AI 行为预警平台 | E115: 46022 | F115: =E115+60 -> 46082 | O115: 102340 | P115: 102340 | Q115: =O115-P115 -> 0
A116: 嘉兴硅基 | B116: 安徽天易数聚科技有限公司 | D116: 智慧数字隐私计算协同安全分析平台 | E116: 46022 | F116: =E116+60 -> 46082 | O116: 128576 | P116: 128576 | Q116: =O116-P116 -> 0
... A133: 嘉兴硅基 | B133: 中电数科科技有限公司 | D133: ZDSK-JXGJ25121271 | E133: 46022 | F133: =E133+60 -> 46082 | O133: 1900000 | P133: 1900000 | Q133: =O133-P133 -> 0
A134: 南京硅基 | B134: 上海浦东发展银行股份有限公司 | O134: 200000 | P134: 200000 | Q134: =O134-P134 -> 0

Sheet BS7
C3: 应收账款 | E3: 44926 | G3: 45291 | I3: 45657 | K3: 46022 | M3: 45838
E4: a | G4: b | I4: c | K4: c | M4: d
C5: Customised AI workforce solutions | E5: =SUM(E6:E8) -> 61688114 | G5: =SUM(G6:G8) -> 1.5894111e+08 | I5: =SUM(I6:I8) -> 2.6968078e+08 | K5: =SUM(K6:K8) -> 3.3065378e+08 | M5: =SUM(M6:M8) -> 2.5800388e+08
C6: ICT services | E6: 30826896 | G6: 94605802 | I6: 2.0979223e+08 | K6: 2.164368e+08 | M6: 2.1774845e+08
C7: AIGC services | E7: 25701500 | G7: 61676971 | I7: 58194498 | K7: 1.131688e+08 | M7: 39710208
C8: AI voice services | E8: 5159718.1 | G8: 2658342.2 | I8: 1694050.1 | K8: 1048171.1 | M8: 545223.12
C9: Standardised and productized AI workforce solutions | E9: 398363.32 | G9: 4298113.2 | I9: 382487.43 | K9: 2486403 | M9: 585478
C10: 全自动内容生产 | K10: 13146517
C11: 小计 | E11: =SUM(E6:E9) -> 62086478 | G11: =SUM(G6:G9) -> 1.6323923e+08 | I11: =SUM(I6:I9) -> 2.7006327e+08 | K11: =SUM(K6:K10) -> 3.462867e+08 | M11: =SUM(M6:M9) -> 2.5858936e+08
C13: 应收账款坏账准备 | E13: =SUM(E14:E15) -> -4979013.2 | G13: =SUM(G14:G15) -> -16521995 | I13: =SUM(I14:I15) -> -37588224 | K13: =SUM(K14:K15) -> -64532444 | M13: =SUM(M14:M15) -> -43732135
C14: - ICT services | E14: -1253618.8 | G14: -6898630.1 | I14: -30412714 | K14: -56472644 | M14: -37111023
C15: - others | E15: -3725394.4 | G15: -9623364.6 | I15: -7175509.2 | K15: -8059799.5 | M15: -6621112.6
C17: 合计 | E17: =E11+E13 -> 57107464 | G17: =G11+G13 -> 1.4671723e+08 | I17: =I11+I13 -> 2.3247504e+08 | K17: =K11+K13 -> 2.8175425e+08 | M17: =M11+M13 -> 2.1485723e+08
E18: =E17-'FY22-25 IFRS（合并）'!G46 -> 0.002688691 | G18: =G17-'FY22-25 IFRS（合并）'!I46 -> -0.0022366345 | I18: =I17-'FY22-25 IFRS（合并）'!K46 -> 0.0028155744 | K18: =K17-'FY22-25 IFRS（合并）'!Q46 -> 117242.89 | M18: =M17-'FY22-25 IFRS（合并）'!O46 -> 0.0023004115
C22: 应收账款账龄情况 | E22: 44926 | G22: 45291 | I22: 45657 | K22: 46022 | M22: 45838
C23: 小于6个月（含6个月） | E23: 59309515 | G23: =122128200.72-0.01 -> 1.221282e+08 | I23: =148345545.67+0.08 -> 1.4834555e+08 | M23: 1.487204e+08
C24: 6至12个月（含12个月） | E24: 567080.04 | G24: 26603385 | I24: 65337347 | M24: 38418745
C25: 12至18个月（含18个月） | E25: 2209882.6 | G25: 14466124 | I25: 26926436 | M25: 38961153
C26: 18至24个月（含24个月） | E26: 0 | G26: 10009 | I26: 21177313 | M26: 13973916
C27: 24个月以上 | E27: 0 | G27: 31509 | I27: 8276622.9 | M27: 18515147
C28: 合计 | E28: =SUM(E23:E27) -> 62086478 | G28: =SUM(G23:G27) -> 1.6323923e+08 | I28: =SUM(I23:I27) -> 2.7006327e+08 | K28: =SUM(K23:K27) -> 0 | M28: =SUM(M23:M27) -> 2.5858936e+08
E29: =ROUND(E28-E11,2) -> 0 | G29: =ROUND(G28-G11,2) -> 0 | I29: =ROUND(I28-I11,2) -> 0 | K29: =ROUND(K28-K11,2) -> -3.462867e+08 | M29: =ROUND(M28-M11,2) -> 0
C32: 请更新和acc对应的账龄和ECL
C63: 请协助提供

Sheet 附 应收账款by客商
H1: =SUM(H3:H130)-'BS7'!K11 -> 0
B2: 客户名称 | C2: 合并客户名称 | D2: 2022年 | E2: 2023年 | F2: 2024年 | G2: 2025年H1 | H2: 2025年
B3: 北京融创数金科技有限公司 | C3: 北京融创数金科技有限公司 | D3: 18500000 | E3: 0 | F3: 0 | G3: 0 | H3: 0
B4: 中移铁通有限公司盐城分公司 | C4: 中国移动通信有限公司 | D4: 14233089 | E4: 12337735 | F4: 12289133 | G4: 14634848 | H4: 3851751 | O4: 请协助提供
B5: 武汉长天银通应用软件有限公司 | C5: 武汉长天银通应用软件有限公司 | D5: 6400000 | E5: 5550000 | F5: 3540000 | G5: 3540000 | H5: 3540000
B6: 中移建设有限公司宿迁分公司 | C6: 中国移动通信有限公司 | D6: 5626002.1 | E6: 1298308.2 | F6: 2583655.1 | G6: 1900682.6 | H6: 2838562.2
B7: 中移铁通有限公司镇江分公司 | C7: 中国移动通信有限公司 | D7: 2964257.5 | E7: 6012798.7 | F7: 5956440.2 | G7: 2175388.1 | H7: 1817704.3
B8: 中移建设有限公司无锡分公司 | C8: 中国移动通信有限公司 | D8: 2757000 | E8: 22948059 | F8: 29806526 | G8: 20017630 | H8: 29225507
B9: 北京腾云天下科技有限公司 | C9: 北京腾云天下科技有限公司 | D9: 2036895.4 | E9: 0 | F9: 0 | G9: 0 | H9: 0
B10: 招商银行股份有限公司 | C10: 招商银行股份有限公司 | D10: 1336334 | E10: 2302220 | F10: 312000 | G10: 312000 | H10: 312000
B11: 中信银行股份有限公司 | C11: 中信银行股份有限公司 | D11: 708000 | E11: 0 | F11: 0 | G11: 0 | H11: 421560
B12: 中国工商银行股份有限公司安徽省分行 | C12: 中国工商银行股份有限公司 | D12: 591000 | E12: 0 | F12: 0 | G12: 0 | H12: 0
B13: 中移铁通有限公司无锡分公司 | C13: 中国移动通信有限公司 | D13: 410285 | E13: 13047957 | F13: 7923005.3 | G13: 5388291.8 | H13: 13179588
B14: 无锡广播电视集团 | C14: 无锡广播电视集团 | D14: 400000 | E14: 100000 | F14: 100000 | G14: 100000 | H14: 0
B15: 深圳市华云中盛科技股份有限公司 | C15: 深圳市华云中盛科技股份有限公司 | D15: 0 | E15: 0 | F15: 415626.94 | G15: 26978 | H15: 26978
B16: 华为云计算技术有限公司 | C16: 华为技术有限公司 | D16: 218163.32 | E16: 253861.82 | F16: 0 | G16: 0 | H16: 0
... B34: 锦创科技股份有限公司 | C34: 锦创科技股份有限公司 | D34: 8800 | E34: 0 | F34: 0 | G34: 0 | H34: 0
B35: 招商银行股份有限公司南京分行 | C35: 招商银行股份有限公司 | D35: 4000 | E35: 4000 | F35: 4000 | G35: 4000 | H35: 4000 | J35: 请核对期后回款数据与M104
B36: 南京士逞网络科技有限公司 | C36: 南京士逞网络科技有限公司 | D36: 200 | E36: 0 | F36: 0 | G36: 0 | H36: 0 | M36: 左侧明细数据与M104不一致，请核对
B37: 杭州闪应科技有限公司 | C37: 杭州闪应科技有限公司 | D37: 0.08 | E37: 0 | F37: 0 | G37: 0 | H37: 0 | K37: 92799375 | L37: 2.0895465e+08 | M37: 2.1854688e+08
B38: 厦门深言据意科技有限公司 | C38: 厦门深言据意科技有限公司 | E38: 20928000 | F38: 0 | G38: 0 | H38: 0 | J38: 中国移动通信有限公司 | K38: 45291 | L38: 45657 | M38: 46022
B39: 上海慕图信息科技有限公司 | C39: 上海慕图信息科技有限公司 | E39: 18883334 | F39: 0 | G39: 0 | H39: 0 | J39: 期初余额 | K39: ='AR analysis'!D9 -> 25991 | L39: =K42 -> 92799 | M39: =L42 -> 208955
B40: 中国移动通信集团江苏有限公司苏州分公司 | C40: 中国移动通信有限公司 | E40: 11775970 | F40: 1766395.5 | G40: 1766395.5 | H40: 784000 | J40: 本期新增 | K40: ='Top 5 customers'!E23*1.06 -> 206799.64 | L40: ='Top 5 customers'!E37*1.06 -> 447481.12 | M40: =325548*1.06 -> 345080.88
B41: 中移铁通有限公司连云港分公司 | C41: 中国移动通信有限公司 | E41: 9936092.7 | F41: 17603166 | G41: 10227585 | H41: 4952635.7 | J41: 本期收款 | K41: =K39+K40-K42 -> 139991.64 | L41: =L39+L40-L42 -> 331325.12 | M41: =M39+M40-M42 -> 337614.88
B42: 南京云创大数据科技股份有限公司 | C42: 南京云创大数据科技股份有限公司 | E42: 7226000 | F42: 0 | G42: 0 | H42: 0 | J42: 期末余额 | K42: ='AR analysis'!D22 -> 92799 | L42: ='AR analysis'!D35 -> 208955 | M42: 216421
B43: 江西嶝晓数字科技有限公司 | C43: 江西嶝晓数字科技有限公司 | E43: 6696222 | F43: 0 | G43: 0 | H43: 0 | J43: 期后回款251231 | K43: 81217 | L43: 129856
B44: 中移建设有限公司江苏分公司 | C44: 中国移动通信有限公司 | E44: 5616914.2 | F44: 25968551 | G44: 46395673 | H44: 53056282 | K44: =K43/K42 -> 0.87519262 | L44: =L43/L42 -> 0.62145438
B45: 中国移动通信集团江苏有限公司盐城分公司 | C45: 中国移动通信有限公司 | E45: 4481080 | F45: 7595392.4 | G45: 4000655.4 | H45: 3614496.1 | J45: 期后回款260228 | K45: 388 | L45: 10275 | M45: 13879
B46: 联想（北京）有限公司 | C46: 联想（北京）有限公司 | E46: 2304440 | F46: 6825202 | G46: 0 | H46: 0 | K46: =(K43+K45)/K42 -> 0.8793737 | L46: =(L43+L45)/L42 -> 0.67062765 | M46: =(M43+M45)/M42 -> 0.064129636
B47: 中移铁通有限公司南通分公司 | C47: 中国移动通信有限公司 | E47: 2084171.8 | F47: 0 | G47: 361900 | H47: 361900
B48: 中国移动通信集团江苏有限公司泰州分公司 | C48: 中国移动通信有限公司 | E48: 1201403 | F48: 1012670 | G48: 1012670 | H48: 1012670
B49: 北京巨量引擎信息技术有限公司 | C49: 北京巨量引擎信息技术有限公司 | E49: 1170618 | F49: 0 | G49: 0 | H49: 0 | J49: 验收年度 | K49: 求和项:2022年回款 | L49: 求和项:2023年回款 | M49: 求和项:2024年回款 | N49: 求和项:2025年回款 | O49: 求和项:2026年1-2月回款
B50: 中移信息系统集成有限公司 | C50: 中国移动通信有限公司 | E50: 1036300.5 | F50: 1036300.5 | G50: 738023.38 | H50: 1003773.7 | J50: 2022 | K50: 16755382 | L50: 17802607 | M50: 5718209.4 | N50: 942087.6 | O50: 344068.88
B51: 上海鑫众通信技术有限公司 | C51: 上海鑫众通信技术有限公司 | E51: 933539 | F51: 0 | G51: 0 | H51: 0 | J51: 2023 | K51: 2999467.5 | L51: 1.18899e+08 | M51: 39944663 | N51: 34612103 | O51: 44490.68
B52: 无锡银通软件科技有限公司 | C52: 无锡银通软件科技有限公司 | E52: 900000 | F52: 600000 | G52: 3700000 | H52: 120000 | J52: 2024 | K52: 0 | L52: 21955478 | M52: 2.7063308e+08 | N52: 94301805 | O52: 9886333.6
B53: 中移建设有限公司南京分公司 | C53: 中国移动通信有限公司 | E53: 431191.19 | F53: 22857238 | G53: 30678777 | H53: 40565264 | J53: 2025 | K53: 0 | L53: 0 | M53: 2150814 | N53: 2.0639217e+08 | O53: 3603728.9
B54: 中国移动通信集团江苏有限公司常州分公司 | C54: 中国移动通信有限公司 | E54: 378200 | F54: 12705605 | G54: 15189360 | H54: 14666670 | J54: 2026 | K54: 0 | L54: 0 | M54: 0 | N54: 6474971.2 | O54: 17128004
B55: 中移（上海）信息通信科技有限公司 | C55: 中国移动通信有限公司 | E55: 213193.4 | F55: 213193.4 | G55: 213193.4 | H55: 213193.4 | J55: 未验收 | K55: 0 | L55: 0 | M55: 0 | N55: 2085326.7 | O55: 12060.3
B56: 中国工商银行股份有限公司贵州省分行 | C56: 中国工商银行股份有限公司 | E56: 160000 | F56: 0 | G56: 0 | H56: 0 | J56: 总计 | K56: 19754850 | L56: 1.5865709e+08 | M56: 3.1844677e+08 | N56: 3.4480846e+08 | O56: 31018686
B57: 杭州海川信息技术有限公司 | C57: 杭州海川信息技术有限公司 | E57: 123000 | F57: 123000 | G57: 123000 | H57: 123000
B58: 南京智苑机电设备有限公司 | C58: 南京智苑机电设备有限公司 | E58: 114000 | F58: 14250 | G58: 14250 | H58: 14250 | P58: As at 31 December 2022 | Q58: Balance
B59: 上海蔲樱信息科技有限公司 | C59: 上海蔲樱信息科技有限公司 | E59: 105000 | F59: 0 | G59: 0 | H59: 0 | P59: 前十大应收客户 | Q59: RMB'000 | R59: %
B60: 江西新原电子商务有限公司 | C60: 江西新原电子商务有限公司 | E60: 84997 | F60: 0 | G60: 0 | H60: 0 | P60: 中国移动通信有限公司 | Q60: =ROUND(N63/1000,0) -> 218547 | R60: =Q60/($N$62/1000) -> 0.63111579
B61: 湖北泰跃卫星技术发展股份有限公司 | C61: 湖北泰跃卫星技术发展股份有限公司 | E61: 66000 | F61: 0 | G61: 0 | H61: 0 | J61: 合并客户名称 | K61: 求和项:2025年 | M61: 合并客户名称 | N61: 求和项:2025年 | P61: 南京迅集科技有限公司 | Q61: =ROUND(N64/1000,0) -> 18600 | R61: =Q61/($N$62/1000) -> 0.053712719
B62: 交通银行股份有限公司江苏省分行 | C62: 交通银行股份有限公司 | E62: 38250 | F62: 0 | G62: 0 | H62: 0 | J62: 安徽天易数聚科技有限公司 | K62: 6226290 | M62: 总计 | N62: 3.462867e+08 | P62: 中电数科科技有限公司 | Q62: =ROUND(N65/1000,0) -> 15100 | R62: =Q62/($N$62/1000) -> 0.043605487
B63: 中国工商银行股份有限公司泸州分行 | C63: 中国工商银行股份有限公司 | E63: 13091.02 | F63: 0 | G63: 0 | H63: 0 | J63: 安庆市云升信息科技有限公司 | K63: 0 | M63: 中国移动通信有限公司 | N63: 2.1854688e+08 | P63: 高勘（广州）技术有限公司 | Q63: =ROUND(N66/1000,0) -> 9270 | R63: =Q63/($N$62/1000) -> 0.026769726
B64: 联通数字科技有限公司陕西分公司 | C64: 联通数字科技有限公司 | E64: 9449.9 | F64: 34487.43 | G64: 34487.43 | H64: 34487.43 | J64: 北京百瑞德展览展示中心 | K64: 25000 | M64: 南京迅集科技有限公司 | N64: 18600300 | P64: 国汽智端（成都）科技有限公司 | Q64: =ROUND(N67/1000,0) -> 8169 | R64: =Q64/($N$62/1000) -> 0.02359028
B65: 中国工商银行股份有限公司内江分行 | C65: 中国工商银行股份有限公司 | E65: 8632.35 | F65: 0 | G65: 0 | H65: 0 | J65: 北京加菲智能科技有限公司 | K65: 7100000 | M65: 中电数科科技有限公司 | N65: 15100000 | P65: 吉创文化传播（上海）有限公司 | Q65: =ROUND(N68/1000,0) -> 7287 | R65: =Q65/($N$62/1000) -> 0.021043257
B66: 陕西交通职业技术学院 | C66: 陕西交通职业技术学院 | E66: 8000 | F66: 0 | G66: 0 | H66: 0 | J66: 北京巨量引擎信息技术有限公司 | K66: 0 | M66: 高勘（广州）技术有限公司 | N66: 9270000 | P66: 北京加菲智能科技有限公司 | Q66: =ROUND(N69/1000,0) -> 7100 | R66: =Q66/($N$62/1000) -> 0.020503242
B67: 中国工商银行股份有限公司绵阳分行 | C67: 中国工商银行股份有限公司 | E67: 6992 | F67: 0 | G67: 0 | H67: 0 | J67: 北京融创数金科技有限公司 | K67: 0 | M67: 国汽智端（成都）科技有限公司 | N67: 8169000 | P67: 安徽天易数聚科技有限公司 | Q67: =ROUND(N70/1000,0) -> 6226 | R67: =Q67/($N$62/1000) -> 0.017979322
B68: 中国工商银行股份有限公司南充分行 | C68: 中国工商银行股份有限公司 | E68: 5546.46 | F68: 0 | G68: 0 | H68: 0 | J68: 北京腾云天下科技有限公司 | K68: 0 | M68: 吉创文化传播（上海）有限公司 | N68: 7286836.9 | P68: 南京形翼科技有限公司 | Q68: =ROUND(N71/1000,0) -> 5697 | R68: =Q68/($N$62/1000) -> 0.016451686
B69: 苏州银行股份有限公司 | C69: 苏州银行股份有限公司 | E69: 4950 | F69: 4950 | G69: 0 | H69: 0 | J69: 北京天易数智科技有限公司 | K69: 3223710 | M69: 北京加菲智能科技有限公司 | N69: 7100000 | P69: 成都万维图新信息技术有限公司 | Q69: =ROUND(N72/1000,0) -> 5100 | R69: =Q69/($N$62/1000) -> 0.014727681
B70: 中国工商银行股份有限公司德阳分行 | C70: 中国工商银行股份有限公司 | E70: 3495 | F70: 0 | G70: 0 | H70: 0 | J70: 成都卡普数据服务有限责任公司 | K70: 4578000 | M70: 安徽天易数聚科技有限公司 | N70: 6226290 | P70: 合计 | Q70: =SUM(Q60:Q69) -> 301096 | R70: =Q70/($N$62/1000) -> 0.86949919
B71: 江西福百弘信息科技有限公司 | C71: 江西福百弘信息科技有限公司 | E71: 1729 | F71: 0 | G71: 0 | H71: 0 | J71: 成都万维图新信息技术有限公司 | K71: 5100000 | M71: 南京形翼科技有限公司 | N71: 5697000
B72: 中国工商银行股份有限公司甘孜直属支行 | C72: 中国工商银行股份有限公司 | E72: 290.12 | F72: 290.12 | G72: 290.12 | H72: 290.12 | J72: 东部机场集团有限公司 | K72: 4950 | M72: 成都万维图新信息技术有限公司 | N72: 5100000
B73: 诺优信息技术（上海）有限公司 | C73: 诺优信息技术（上海）有限公司 | F73: 29939242 | G73: 0 | H73: 0 | J73: 富康尼科技（泰州）有限公司 | K73: 4466800 | M73: 上海马师傅品牌管理有限公司 | N73: 4648680
B74: 中移建设有限公司南通分公司 | C74: 中国移动通信有限公司 | F74: 28495157 | G74: 20029140 | H74: 14036326 | J74: 高勘（广州）技术有限公司 | K74: 9270000 | M74: 成都卡普数据服务有限责任公司 | N74: 4578000
B75: 江苏移动信息系统集成有限公司 | C75: 中国移动通信有限公司 | F75: 13227988 | G75: 9987988 | H75: 9987988 | J75: 广州灏成计算机科技有限公司 | K75: 10000 | M75: 南京晶赛电气科技有限公司 | N75: 4500000
B76: 江苏数智网联信息技术有限公司 | C76: 江苏数智网联信息技术有限公司 | F76: 10400000 | G76: 10400000 | H76: 0 | J76: 广州和联通信科技有限公司 | K76: 883224 | M76: 富康尼科技（泰州）有限公司 | N76: 4466800
B77: 中移建设有限公司苏州分公司 | C77: 中国移动通信有限公司 | F77: 8006263.3 | G77: 14167594 | H77: 3226908.9 | J77: 广州市玄武无线科技股份有限公司 | K77: 0 | M77: 武汉长天银通应用软件有限公司 | N77: 3540000
B78: 中移铁通有限公司徐州分公司 | C78: 中国移动通信有限公司 | F78: 5415126.1 | G78: 3628999.1 | H78: 1070974.5 | J78: 国汽智端（成都）科技有限公司 | K78: 8169000 | M78: 南京信非技术有限公司 | N78: 3509232
B79: 富康尼科技（泰州）有限公司 | C79: 富康尼科技（泰州）有限公司 | F79: 2610000 | G79: 8264846.5 | H79: 4466800 | J79: 杭州海川信息技术有限公司 | K79: 123000 | M79: 深圳市广通软件有限公司 | N79: 3505000
B80: 中国移动通信集团江苏有限公司连云港分公司 | C80: 中国移动通信有限公司 | F80: 2571572 | G80: 127172 | H80: 127172 | J80: 杭州闪应科技有限公司 | K80: 0 | M80: 北京天易数智科技有限公司 | N80: 3223710
B81: 珠海市东信时代信息技术有限公司 | C81: 珠海市东信时代信息技术有限公司 | F81: 1776623.1 | G81: 0 | H81: 0 | J81: 航天广通科技（深圳）有限公司 | K81: 2880000 | M81: 航天广通科技（深圳）有限公司 | N81: 2880000
B82: 联想（北京）信息技术有限公司 | C82: 联想（北京）有限公司 | F82: 1616155.5 | G82: 3575830.5 | H82: 0 | J82: 湖北泰跃卫星技术发展股份有限公司 | K82: 0 | M82: 众安在线财产保险股份有限公司 | N82: 2504084.6
B83: 中国移动通信集团江苏有限公司徐州分公司 | C83: 中国移动通信有限公司 | F83: 960662.72 | G83: 4404054.2 | H83: 1803697.7 | J83: 华为技术有限公司 | K83: 0 | M83: 江苏磬石软件科技有限公司 | N83: 2007324
B84: 中国工商银行股份有限公司江苏省分行 | C84: 中国工商银行股份有限公司 | F84: 748000 | G84: 0 | H84: 0 | J84: 吉创文化传播（上海）有限公司 | K84: 7286836.9 | M84: 上海浦东发展银行股份有限公司 | N84: 1980000
... B95: 中国铁塔股份有限公司镇江分公司 | C95: 中国铁塔股份有限公司 | F95: 16000 | G95: 0 | H95: 16000 | J95: 昆山慧创信息科技有限公司 | K95: 0 | M95: 联通数字科技有限公司 | N95: 34487.43
B96: 江苏磬石软件科技有限公司 | C96: 江苏磬石软件科技有限公司 | G96: 7451935 | H96: 2007324 | J96: 溧阳市栗里文旅投资发展有限公司 | K96: 0 | M96: 深圳市华云中盛科技股份有限公司 | N96: 26978
B97: 中移建设有限公司徐州分公司 | C97: 中国移动通信有限公司 | G97: 6379321.6 | H97: 6379321.6 | J97: 联通数字科技有限公司 | K97: 34487.43 | M97: 北京百瑞德展览展示中心 | N97: 25000
B98: 中国移动通信集团江苏有限公司南京分公司 | C98: 中国移动通信有限公司 | G98: 2747000 | H98: 2692000 | J98: 联想（北京）有限公司 | K98: 0 | M98: 中国铁塔股份有限公司 | N98: 16000
B99: 广州和联通信科技有限公司 | C99: 广州和联通信科技有限公司 | G99: 883224 | H99: 883224 | J99: 咪咕新空文化科技（厦门） | K99: 1209000 | M99: 南京智苑机电设备有限公司 | N99: 14250
B100: 江苏赞奇科技股份有限公司 | C100: 江苏赞奇科技股份有限公司 | G100: 700000 | H100: 0 | J100: 绵阳锐达科技有限公司 | K100: 0 | M100: 南京市雨花台区市场监督管理局 | N100: 11333
B101: 溧阳市栗里文旅投资发展有限公司 | C101: 溧阳市栗里文旅投资发展有限公司 | G101: 411880 | H101: 0 | J101: 绵阳市涪城区城郊街道城郊社区居民委员会 | K101: 0 | M101: 广州灏成计算机科技有限公司 | N101: 10000
B102: 中国移动通信集团江苏有限公司无锡分公司 | C102: 中国移动通信有限公司 | G102: 375408 | H102: 1988567.1 | J102: 绵阳市涪城区城厢街道办事处 | K102: 130500 | M102: 东部机场集团有限公司 | N102: 4950
B103: 绵阳市涪城区城厢街道办事处 | C103: 绵阳市涪城区城厢街道办事处 | G103: 130500 | H103: 130500 | J103: 默沙东（中国）投资有限公司 | K103: 0 | M103: 深圳迅策科技股份有限公司 | N103: 2000
B104: 江苏号百科技有限公司 | C104: 江苏号百科技有限公司 | G104: 80000 | H104: 0 | J104: 南京晶赛电气科技有限公司 | K104: 4500000 | M104: 中国工商银行股份有限公司 | N104: 290.12
B105: 中移铁通有限公司南通分公司 | C105: 中国移动通信有限公司 | G105: 48161.4 | H105: 0 | J105: 南京士逞网络科技有限公司 | K105: 0 | M105: 安庆市云升信息科技有限公司 | N105: 0
B106: 盐亭县公安局 | C106: 盐亭县公安局 | G106: 29800 | H106: 0 | J106: 南京市雨花台区市场监督管理局 | K106: 11333 | M106: 北京巨量引擎信息技术有限公司 | N106: 0
B107: 其他 | C107: 其他 | D107: 4836262.8 | E107: 2019619.7 | F107: 821583.89 | G107: 0 | H107: 0 | J107: 南京信非技术有限公司 | K107: 3509232 | M107: 北京融创数金科技有限公司 | N107: 0
B108: 其他客商 | C108: 其他 | G108: 424473.97 | H108: 0 | J108: 南京形翼科技有限公司 | K108: 5697000 | M108: 北京腾云天下科技有限公司 | N108: 0
B109: 中国移动通信集团四川有限公司绵阳分公司 | C109: 中国移动通信有限公司 | H109: 925 | J109: 南京迅集科技有限公司 | K109: 18600300 | M109: 广州市玄武无线科技股份有限公司 | N109: 0
B110: 东部机场集团有限公司 | C110: 东部机场集团有限公司 | H110: 4950 | J110: 南京银行股份有限公司 | K110: 0 | M110: 杭州闪应科技有限公司 | N110: 0
B111: 吉创文化传播（上海）有限公司 | C111: 吉创文化传播（上海）有限公司 | H111: 7286836.9 | J111: 南京云创大数据科技股份有限公司 | K111: 0 | M111: 湖北泰跃卫星技术发展股份有限公司 | N111: 0
B112: 上海马师傅品牌管理有限公司 | C112: 上海马师傅品牌管理有限公司 | H112: 4648680 | J112: 南京云设智能科技有限公司 | K112: 0 | M112: 华为技术有限公司 | N112: 0
B113: 深圳迅策科技股份有限公司 | C113: 深圳迅策科技股份有限公司 | H113: 2000 | J113: 南京智苑机电设备有限公司 | K113: 14250 | M113: 江苏号百科技有限公司 | N113: 0
B114: 成都万维图新信息技术有限公司 | C114: 成都万维图新信息技术有限公司 | H114: 5100000 | J114: 诺优信息技术（上海）有限公司 | K114: 0 | M114: 江苏数智网联信息技术有限公司 | N114: 0
B115: 成都卡普数据服务有限责任公司 | C115: 成都卡普数据服务有限责任公司 | H115: 4578000 | J115: 普强信息技术（北京）有限公司 | K115: 0 | M115: 江苏索派科技产业集团有限公司 | N115: 0
B116: 深圳市广通软件有限公司 | C116: 深圳市广通软件有限公司 | H116: 3505000 | J116: 其他 | K116: 0 | M116: 江苏赞奇科技股份有限公司 | N116: 0
B117: 北京加菲智能科技有限公司 | C117: 北京加菲智能科技有限公司 | H117: 7100000 | J117: 厦门深言据意科技有限公司 | K117: 0 | M117: 江西嶝晓数字科技有限公司 | N117: 0
B118: 南京迅集科技有限公司 | C118: 南京迅集科技有限公司 | H118: 18600300 | J118: 陕西交通职业技术学院 | K118: 0 | M118: 江西福百弘信息科技有限公司 | N118: 0
B119: 安徽天易数聚科技有限公司 | C119: 安徽天易数聚科技有限公司 | H119: 6226290 | J119: 上海畅途融资租赁有限公司 | K119: 0 | M119: 江西新原电子商务有限公司 | N119: 0
B120: 南京形翼科技有限公司 | C120: 南京形翼科技有限公司 | H120: 5697000 | J120: 上海电信百事应信息有限公司 | K120: 174600 | M120: 交通银行股份有限公司 | N120: 0
... B130: 咪咕新空文化科技（厦门） | C130: 咪咕新空文化科技（厦门） | H130: 1209000 | J130: 苏州创捷传媒展览股份有限公司 | K130: 0 | M130: 南京云创大数据科技股份有限公司 | N130: 0
H131: =SUMIF(N:N,B131,P:P) -> 0 | J131: 苏州银行股份有限公司 | K131: 0 | M131: 南京云设智能科技有限公司 | N131: 0
H132: =SUMIF(N:N,B132,P:P) -> 0 | J132: 添可电器有限公司 | K132: 0 | M132: 诺优信息技术（上海）有限公司 | N132: 0
H133: =SUMIF(N:N,B133,P:P) -> 0 | J133: 无锡广播电视集团 | K133: 0 | M133: 普强信息技术（北京）有限公司 | N133: 0
H134: =SUMIF(N:N,B134,P:P) -> 0 | J134: 无锡银通软件科技有限公司 | K134: 120000 | M134: 其他 | N134: 0
H135: =SUMIF(N:N,B135,P:P) -> 0 | J135: 武汉长天银通应用软件有限公司 | K135: 3540000 | M135: 厦门深言据意科技有限公司 | N135: 0
J136: 盐亭县公安局 | K136: 0 | M136: 陕西交通职业技术学院 | N136: 0
...

Sheet Top 5 customers
B1: Nanjing Silicon Intelligence Technology Group Co., Ltd.
B2: For three years ended 31 December 2024 and six months ended 30 June 2025
B3: Analysis of top five customers
B5: For the year ended 31 December 2022
B7: No. | C7: Customer | D7: Location of business/Jurisdiction | E7: Transaction amount | F7: % of total revenue | G7: Types of services | H7: Length of relationship | I7: Business/Authority scope | J7: Credit term | K7: Payment method
E8: RMB'000
B9: 1 | C9: China Mobile Communications Group Co., Ltd. | D9: Beijing | E9: 36931 | F9: =E9/$E$17 -> 0.16574886 | G9: AI workforce solutions | H9: Since 2022 | I9: a telecom operator | J9: Due upon the date of billing up to 90 days | K9: wire transfer
B10: 2 | C10: Beijing Hongyi Technology Co., Ltd. | D10: Beijing | E10: 34595 | F10: =E10/$E$17 -> 0.15526473 | G10: AI workforce solutions | H10: Since 2022 | I10: a technology promotion and application service provider | J10: Due upon the date of billing up to 30 days | K10: wire transfer
B11: 3 | C11: Shenzhen Kaifuyuan Technology Co., Ltd. | D11: Guangdong Province | E11: 19027 | F11: =E11/$E$17 -> 0.085394479 | G11: AI workforce solutions | H11: Since 2022 | I11: a commercial service provider | J11: Prepayment | K11: wire transfer
B12: 4 | C12: Shanghai Yixu Network Technology Co., Ltd. | D12: Shanghai | E12: 17747 | F12: =E12/$E$17 -> 0.079649751 | G12: AI workforce solutions | H12: Since 2022 | I12: an Internet and related service provider | J12: Due upon the date of billing within 10 days | K12: wire transfer
B13: 5 | C13: Beijing Sunac Digital Technology Co., Ltd. | D13: Beijing | E13: 17453 | F13: =E13/$E$17 -> 0.078330259 | G13: AI workforce solutions | H13: Since 2022 | I13: a technology promotion and application service provider | J13: Due upon the date of billing within 15 days | K13: wire transfer
C15: Total revenue from top 5 customers | E15: =SUM(E9:E13) -> 125753 | F15: =E15/E17 -> 0.56438807
C17: Total revenue | E17: 222813 | F17: 1
B19: For the year ended 31 December 2023
B21: No. | C21: Customer | D21: Location of business/Jurisdiction | E21: Transaction amount | F21: % of total revenue | G21: Types of services | H21: Length of relationship | I21: Business/Authority scope | J21: Credit term | K21: Payment method
E22: RMB'000
B23: 1 | C23: China Mobile Communications Group Co., Ltd. | D23: Beijing | E23: 195094 | F23: =E23/$E$31 -> 0.36754294 | G23: AI workforce solutions | H23: Since 2022 | I23: a telecom operator | J23: Due upon the date of billing up to 90 days | K23: wire transfer
B24: 2 | C24: Xiamen Shenyan Juyi Technology Co., Ltd. | D24: Fujian Province | E24: 56642 | F24: =E24/$E$31 -> 0.10670942 | G24: AI workforce solutions | H24: Since 2023 | I24: a software and information technology service provider | J24: Due upon the date of billing up to 40 days | K24: wire transfer
B25: 3 | C25: Zhuhai Dongxin Times Information Technology Co., Ltd. | D25: Guangdong Province | E25: 21537 | F25: =E25/$E$31 -> 0.040574146 | G25: AI workforce solutions | H25: Since 2023 | I25: a software and information technology service provider | J25: Due upon the date of billing within 20 days | K25: wire transfer
B26: 4 | C26: Shanghai Mutu Information Technology Co., Ltd. | D26: Shanghai | E26: 17814 | F26: =E26/$E$31 -> 0.033560284 | G26: AI workforce solutions | H26: Since 2023 | I26: a technology promotion and application service provider | J26: Due upon the date of billing up to 25 days | K26: wire transfer
B27: 5 | C27: Guizhou Chuangdong Information Technology Co., Ltd. | D27: Guizhou Province | E27: 15236 | F27: =E27/$E$31 -> 0.028703519 | G27: AI workforce solutions | H27: Since 2023 | I27: a technology promotion and application service provider | J27: Prepayment | K27: wire transfer
C29: Total revenue from top 5 customers | E29: =SUM(E23:E27) -> 306323 | F29: =E29/E31 -> 0.57709031
C31: Total revenue | E31: 530806 | F31: 1
B33: For the year ended 31 December 2024
B35: No. | C35: Customer | D35: Location of business/Jurisdiction | E35: Transaction amount | F35: % of total revenue | G35: Types of services | H35: Length of relationship | I35: Business/Authority scope | J35: Credit term | K35: Payment method
E36: RMB'000
B37: 1 | C37: China Mobile Communications Group Co., Ltd. | D37: Beijing | E37: 422152 | F37: =E37/$E$45 -> 0.64407618 | G37: AI workforce solutions | H37: Since 2022 | I37: a telecom operator | J37: Due upon the date of billing up to 90 days | K37: wire transfer
B38: 2 | C38: Knowyou Technologies Co., Ltd. | D38: Shanghai | E38: 28245 | F38: =E38/$E$45 -> 0.043093321 | G38: AI workforce solutions | H38: Since 2024 | I38: a technology promotion and application service provider | J38: Due upon the date of billing within 30 days | K38: wire transfer
B39: 3 | C39: Beijing Duoke Yilian Technology Co., Ltd. | D39: Beijing | E39: 24772 | F39: =E39/$E$45 -> 0.037794574 | G39: AI workforce solutions | H39: Since 2022 | I39: a technology promotion and application service provider | J39: Due upon the date of billing within 30 days | K39: wire transfer
B40: 4 | C40: Jiangsu Qingshi Software Technology Co., Ltd. | D40: Jiangsu Province | E40: 23170 | F40: =E40/$E$45 -> 0.035350407 | G40: AI workforce solutions | H40: Since 2024 | I40: a software and information technology service provider | J40: N/A | K40: wire transfer
B41: 5 | C41: Lenovo (Beijing) Co., Ltd. | D41: Beijing | E41: 18652 | F41: =E41/$E$45 -> 0.028457306 | G41: AI workforce solutions | H41: Since 2023 | I41: a technology enterprise manufacturing computers, communications and other electronic equipment | J41: Due upon the date of billing within 60 days | K41: wire transfer
C43: Total revenue from top 5 customers | E43: =SUM(E37:E41) -> 516991 | F43: =E43/E45 -> 0.78877178
C45: Total revenue | E45: 655438 | F45: 1
B47: For the six months ended 30 June 2025
B49: No. | C49: Customer | D49: Location of business/Jurisdiction | E49: Transaction amount | F49: % of total revenue | G49: Types of services | H49: Length of relationship | I49: Business/Authority scope | J49: Credit term | K49: Payment method
E50: RMB'000
B51: 1 | C51: China Mobile Communications Group Co., Ltd. | D51: Beijing | E51: 209888 | F51: =E51/$E$59 -> 0.64420763 | G51: AI workforce solutions | H51: Since 2022 | I51: a telecom operator | J51: Due upon the date of billing up to 90 days | K51: wire transfer
B52: 2 | C52: Bestlink Technologies Co., Ltd. | D52: Jiangsu Province | E52: 27323 | F52: =E52/$E$59 -> 0.083862275 | G52: AI workforce solutions | H52: Since 2024 | I52: a software and information technology service provider | J52: Due upon the date of billing within 15 days | K52: wire transfer or bank acceptance bill
B53: 3 | C53: Guangzhou Helian Communication Technology Co., Ltd. | D53: Guangdong Province | E53: 16665 | F53: =E53/$E$59 -> 0.051149757 | G53: AI workforce solutions | H53: Since 2025 | I53: a high-tech enterprise | J53: Due upon the date of billing within 30 days | K53: wire transfer
B54: 4 | C54: Fukangni Technology (Taizhou) Co., Ltd. | D54: Jiangsu Province | E54: 15819 | F54: =E54/$E$59 -> 0.048553136 | G54: AI workforce solutions | H54: Since 2024 | I54: a software and information technology service provider | J54: Due upon the date of billing within 5 days | K54: wire transfer
B55: 5 | C55: Lenovo (Beijing) Co., Ltd. | D55: Beijing | E55: 15469 | F55: =E55/$E$59 -> 0.047478883 | G55: AI workforce solutions | H55: Since 2023 | I55: a technology enterprise manufacturing computers, communications and other electronic equipment | J55: Due upon the date of billing within 60 days | K55: wire transfer
C57: Total revenue from top 5 customers | E57: =SUM(E51:E55) -> 285164 | F57: =E57/E59 -> 0.87525168
C59: Total revenue | E59: 325808 | F59: 1

Sheet AR analysis
B1: Nanjing Silicon Intelligence Technology Group Co., Ltd.
B2: For three years ended 31 December 2024 and six months ended 30 June 2025
B3: Analysis of aging and subsequent settlement of trade receivables
B5: As at 31 December 2022
B7: No. | C7: Customers of top 5 trade receivables | D7: Balance | E7: % of total trade receivables | F7: Within 1 year | G7: 1-2 years | H7: Over 2 years | I7: Subsequent Settlement Up to 30 September 2025 | K7: Credit Term
D8: RMB'000 | F8: RMB'000 | G8: RMB'000 | H8: RMB'000 | I8: RMB'000
B9: 1 | C9: China Mobile Communications Group Co., Ltd. | D9: 25991 | E9: =D9/$D$16 -> 0.418629 | F9: 25991 | G9: 0 | H9: 0 | I9: 22453 | J9: =I9/D9 -> 0.86387596 | K9: Due upon the date of billing up to 90 days
B10: 2 | C10: Beijing Sunac Digital Technology Co., Ltd. | D10: 18500 | E10: =D10/$D$16 -> 0.29797378 | F10: 18500 | G10: 0 | H10: 0 | I10: 18500 | J10: =I10/D10 -> 1 | K10: Due upon the date of billing within 15 days
B11: 3 | C11: Wuhan Pansky Application Software Co., Ltd. | D11: 6400 | E11: =D11/$D$16 -> 0.10308282 | F11: 6400 | G11: 0 | H11: 0 | I11: 2860 | J11: =I11/D11 -> 0.446875 | K11: Due upon the date of billing within 5 days
B12: 4 | C12: Beijing Tendcloud Tianxia Technology Co., Ltd. | D12: 2037 | E12: =D12/$D$16 -> 0.032809329 | F12: 2037 | G12: 0 | H12: 0 | I12: 2037 | J12: =I12/D12 -> 1 | K12: Due upon the date of billing within 5 days
