Workbook
Name \0: #REF!
Name \a: #REF!
Name \b: #REF!
Name \bbb: #REF!
Name \C: #REF!
Name \d: #REF!
Name \f: #N/A
Name \i: #REF!
Name \m: #REF!
Name \p: #REF!
Name \Q: #REF!
Name \R: #REF!
Name \s: #N/A
Name \z: #REF!
Name _: #REF!
Name _.30: #REF!
Name _.dbf: #REF!
Name _.xls: #REF!
Name _?: #REF!
Name _??????: #REF!
Name ____________txt1: #REF!
Name ____________txt2: #REF!
Name ____________txt3: #REF!
Name ____________txt4: #REF!
Name _______DAT1: #REF!
Name _______DAT10: #REF!
Name _______DAT11: #REF!
Name _______DAT12: #REF!
Name _______DAT13: #REF!
Name _______DAT14: #REF!
Name _______DAT15: #REF!
Name _______DAT2: #REF!
Name _______DAT3: #REF!
Name _______DAT4: #REF!
Name _______DAT5: #REF!
Name _______DAT6: #REF!
Name _______DAT7: #REF!
Name _______DAT8: #REF!
Name _______DAT9: #REF!
Name ______DAT1: #REF!
Name ______DAT10: #REF!
Name ______DAT11: #REF!
Name ______DAT12: #REF!
Name ______DAT13: #REF!
Name ______DAT14: #REF!
Name ______DAT15: #REF!
Name ______DAT2: #REF!
Name ______DAT3: #REF!
Name ______DAT4: #REF!
Name ______DAT5: #REF!
Name ______DAT6: #REF!
Name ______DAT7: #REF!
Name ______DAT8: #REF!
Name ______DAT9: #REF!
Name ______PA7: #REF!
Name ______PA8: #REF!
Name ______PD1: #REF!
Name ______PE12: #REF!
Name ______PE13: #REF!
Name ______PE6: #REF!

Sheet Cover
B9: Project GJ Financial Projections
B12: =TODAY() -> 46162
B14: PRELIMINARY AND CONFIDENTIAL DRAFT
D24: Color Code:
D25: Blue: Hard code value
D26: Black: Calculation
D27: Green: Linked from another tab
D28: Red: Linked from the same tab

Sheet Control
B2: Master Control
A4: x | B4: General Assumptions
C6: Beginning period | F6: date | H6: 45838
C8: Hours per day | F8: hours | H8: 24
C9: Monthes per year | F9: month | H9: 12
C10: Days per year | F10: day | H10: 365
C12: Sensitivity Analysis | F12: % | H12: 0 | I12: << Revenue Growth
C13: Sensitivity Analysis for GJ autopilot AIGC agents | F13: % | H13: 0 | I13: << Revenue Growth
A15: x | B15: IPO Assumptions
C17: IPO Case | H17: 1 | I17: 1=IPO; 0=no IPO
C18: Banking Facilities Case | H18: 0 | I18: 1=Optimistic; 0=Pessimistic
C19: IPO Date | H19: 6/30/2026
C20: Number of shares outstanding | H20: 17084745
C21: Offer % | H21: =H22/(H20+H22) -> 0.25 | I21: %
C22: Shares offered | H22: 5694915
C23: Norminal price | H23: 1 | I23: RMB
C25: Listing Expense | G25: 1HK$= | H25: =1/'listing expense'!F5 -> 0.87408 | I25: RMB
C26: Listing Expense (HK$ thousand) | H26: ='listing expense'!P51/1000 -> 117942.2
C27: Net proceeds to Company (HK$ thousand) | H27: ='listing expense'!P54/1000 -> 1320621.4
C28: Total Net Proceeds (HK$ thousand) | H28: ='listing expense'!P56/1000 -> 1279073.7
C29: Net proceeds to Company (RMB thousand) | H29: =H27*H25 -> 1154328.8
C30: Total Net Proceeds (RMB thousand) | H30: =H28*$H$25 -> 1118012.8
C32: IPO Use of Proceeds
E33: R&D | H33: =UOP!K10 -> 559006.38 | I33: RMB Thousand
E34: Computing Power Procurement & Leasing | H34: =UOP!K11 -> 156521.79 | I34: RMB Thousand
E35: R&D Talent Recruitment | H35: =UOP!K13 -> 111801.28 | I35: RMB Thousand
E36: Outsourced R&D | H36: =UOP!K14 -> 55900.638 | I36: RMB Thousand
E37: Business Expansion | H37: =UOP!K18 -> 279503.19 | I37: RMB Thousand
E38: Marketing & Brand Promotion | H38: =UOP!K19 -> 223602.55 | I38: RMB Thousand
E39: Sales Talent Recruitment | H39: =UOP!K20 -> 55900.638 | I39: RMB Thousand
E40: Strategic Partnerships & Acquisitions | H40: =UOP!K24 -> 167701.91 | I40: RMB Thousand
E41: Working Capitacl Supplement | H41: =UOP!K26 -> 111801.28 | I41: RMB Thousand
E42: Check
E44: Overall Check
E45: UOP
E46: IS
E47: WC
E48: BS
E49: Consolidated Financials
E50: Consolidated Financials
E51: P&L
E52: Other Calculations

Sheet PFM Outupt>>>

Sheet IS simplified_0319
A1: Blue: Hard code vale | AU1: x
A2: Black: Calculation | AU2: x
A3: Green: Linked from another tab | AU3: x
A4: Red: Linked from the same tab | AU4: x
AU5: x
W6: Annual Forecast | AU6: x
K7: 2022 | L7: 2023 | M7: 2024 | N7: 2025 | O7: Apr 2026 | P7: Dec 2026 | Q7: 2026 | R7: =Q7+1 -> 2027 | W7: 45839 | X7: =EDATE(W7,1) -> 45870 | Y7: =EDATE(X7,1) -> 45901 | Z7: =EDATE(Y7,1) -> 45931 | AA7: =EDATE(Z7,1) -> 45962 | AB7: =EDATE(AA7,1) -> 45992 | AC7: =EDATE(AB7,1) -> 46023 | AD7: =EDATE(AC7,1) -> 46054 | AE7: =EDATE(AD7,1) -> 46082 | ... AT7: =EDATE(AS7,1) -> 46539 | AU7: x
K8: 12 mths | L8: 12 mths | M8: 12 mths | N8: 12 mths | O8: 4 mths | P8: 8 mths | Q8: 12 mths | R8: 6 mths | AU8: x
K9: Actual | L9: Actual | M9: Actual | N9: Actual | Q9: Forecast | R9: Forecast | W9: RMB’000 | X9: RMB’000 | Y9: RMB’000 | Z9: RMB’000 | AA9: RMB’000 | AB9: RMB’000 | AC9: RMB’000 | AD9: RMB’000 | AE9: RMB’000 | AF9: RMB’000 | AG9: RMB’000 | AH9: RMB’000 | AI9: RMB’000 | AJ9: RMB’000 | AK9: RMB’000 | AL9: RMB’000 | AM9: RMB’000 | AN9: RMB’000 | AO9: RMB’000 | AP9: RMB’000 | AQ9: RMB’000 | AR9: RMB’000 | AS9: RMB’000 | AT9: RMB’000 | AU9: x
A10: 3 | C10: Profit Forecast for the year ending December 31, 2026 | AU10: x
C11: (In RMB thousands) | AU11: x
C12: Revenue | K12: ='Consolidated Financials'!J10 -> 222813.08 | L12: ='Consolidated Financials'!K10 -> 530805.86 | M12: ='Consolidated Financials'!L10 -> 655437.77 | N12: ='Consolidated Financials'!M10 -> 788818.16 | O12: =SUM('Consolidated Financials'!U10:X10) -> 215686.73 | P12: =Q12-O12 -> 875633.25 | Q12: ='Consolidated Financials'!N10 -> 1091320 | R12: ='Consolidated Financials'!O10 -> 619476.7 | AU12: x
C13: Cost of sales | K13: ='Consolidated Financials'!J18 -> -137010 | L13: ='Consolidated Financials'!K18 -> -287645.05 | M13: ='Consolidated Financials'!L18 -> -430359.22 | N13: ='Consolidated Financials'!M18 -> -516747.26 | O13: =SUM('Consolidated Financials'!U18:X18) -> -139083.98 | P13: =Q13-O13 -> -563276.09 | Q13: ='Consolidated Financials'!N18 -> -702360.08 | R13: ='Consolidated Financials'!O18 -> -397437.85 | AU13: x
AU14: x
C15: Gross profit | K15: =SUM(K12,K13) -> 85803.08 | L15: =SUM(L12,L13) -> 243160.81 | M15: =SUM(M12,M13) -> 225078.54 | N15: =SUM(N12,N13) -> 272070.9 | O15: =SUM('Consolidated Financials'!U20:X20) -> 76602.748 | P15: =Q15-O15 -> 312357.16 | Q15: =SUM(Q12,Q13) -> 388959.9 | R15: =SUM(R12,R13) -> 222038.85 | AU15: x
AU16: x
C17: Other income | K17: ='Consolidated Financials'!J23 -> 17972 | L17: ='Consolidated Financials'!K23 -> 15976 | M17: ='Consolidated Financials'!L23 -> 10846 | N17: ='Consolidated Financials'!M23 -> 2554 | O17: =SUM('Consolidated Financials'!U23:X23) -> 155.88479 | P17: =Q17-O17 -> -29.4766 | Q17: ='Consolidated Financials'!N23 -> 126.40819 | R17: ='Consolidated Financials'!O23 -> 0 | AU17: x
C18: Other net (loss)/gain | K18: ='Consolidated Financials'!J24 -> -125 | L18: ='Consolidated Financials'!K24 -> 38 | M18: ='Consolidated Financials'!L24 -> -678 | N18: ='Consolidated Financials'!M24 -> 717 | O18: =SUM('Consolidated Financials'!U24:X24) -> -486.34861 | P18: =Q18-O18 -> 0 | Q18: ='Consolidated Financials'!N24 -> -486.34861 | R18: ='Consolidated Financials'!O24 -> 0 | AU18: x
C19: Selling and marketing expenses | K19: ='Consolidated Financials'!J25 -> -38511.621 | L19: ='Consolidated Financials'!K25 -> -110263 | M19: ='Consolidated Financials'!L25 -> -82570 | N19: ='Consolidated Financials'!M25 -> -55235 | O19: =SUM('Consolidated Financials'!U25:X25) -> -14827.4 | P19: =Q19-O19 -> -65776.125 | Q19: ='Consolidated Financials'!N25 -> -80603.525 | R19: ='Consolidated Financials'!O25 -> -51440.423 | AU19: x
C20: Administrative and other operating expenses | K20: ='Consolidated Financials'!J26 -> -47110.4 | L20: ='Consolidated Financials'!K26 -> -47966 | M20: ='Consolidated Financials'!L26 -> -41211 | N20: ='Consolidated Financials'!M26 -> -55634 | O20: =SUM('Consolidated Financials'!U26:X26) -> -14384 | P20: =Q20-O20 -> -47636.78 | Q20: ='Consolidated Financials'!N26 -> -62020.78 | R20: ='Consolidated Financials'!O26 -> -23058.414 | AU20: x
C21: Research and development expenses | K21: ='Consolidated Financials'!J27 -> -75433 | L21: ='Consolidated Financials'!K27 -> -129569 | M21: ='Consolidated Financials'!L27 -> -150129 | N21: ='Consolidated Financials'!M27 -> -163342 | O21: =SUM('Consolidated Financials'!U27:X27) -> -68939.855 | P21: =Q21-O21 -> -161136.38 | Q21: ='Consolidated Financials'!N27 -> -230076.24 | R21: ='Consolidated Financials'!O27 -> -152790.74 | AU21: x
C22: Impairment loss on trade and other receivables and contract assets | K22: ='Consolidated Financials'!J28 -> -3553 | L22: ='Consolidated Financials'!K28 -> -11750 | M22: -21170 | N22: ='Consolidated Financials'!M28 -> -27595 | O22: =SUM('Consolidated Financials'!U28:X28) -> -3427.7737 | P22: =Q22-O22 -> -23437.047 | Q22: ='Consolidated Financials'!N28 -> -26864.821 | R22: ='Consolidated Financials'!O28 -> -10970.471 | AU22: x
C23: Profit/(Loss) from operations | K23: =SUM(K17:K22,K15) -> -60957.941 | L23: =SUM(L17:L22,L15) -> -40373.194 | M23: =SUM(M17:M22,M15) -> -59833.456 | N23: =SUM(N17:N22,N15) -> -26464.105 | O23: =SUM(O17:O22,O15) -> -25306.744 | P23: =SUM(P17:P22,P15) -> 14341.346 | Q23: =SUM(Q17:Q22,Q15) -> -10965.398 | R23: =SUM(R17:R22,R15) -> -16221.205 | AU23: x
AU24: x
C25: Finance income | K25: ='Consolidated Financials'!J32 -> 9458 | L25: ='Consolidated Financials'!K32 -> 4606 | M25: ='Consolidated Financials'!L32 -> 2239 | N25: ='Consolidated Financials'!M32 -> 857 | O25: =SUM('Consolidated Financials'!U32:X32) -> 151.26373 | P25: =Q25-O25 -> 2568.5738 | Q25: ='Consolidated Financials'!N32 -> 2719.8375 | R25: ='Consolidated Financials'!O32 -> 1959.1037 | AU25: x
C26: Finance costs | K26: ='Consolidated Financials'!J33 -> -759 | L26: ='Consolidated Financials'!K33 -> -435 | M26: ='Consolidated Financials'!L33 -> -240 | N26: ='Consolidated Financials'!M33 -> -144 | O26: =SUM('Consolidated Financials'!U33:X33) -> -632.07287 | P26: =Q26-O26 -> 432.59772 | Q26: ='Consolidated Financials'!N33 -> -199.47515 | R26: ='Consolidated Financials'!O33 -> -193.09421 | AU26: x
C27: Share of loss of associates | K27: ='Consolidated Financials'!J34 -> 0 | L27: ='Consolidated Financials'!K34 -> -1104 | M27: ='Consolidated Financials'!L34 -> -27 | N27: ='Consolidated Financials'!M34 -> -164 | O27: =SUM('Consolidated Financials'!U34:X34) -> 0 | P27: =Q27-O27 -> 0 | Q27: ='Consolidated Financials'!N34 -> 0 | R27: ='Consolidated Financials'!O34 -> 0 | AU27: x
C28: Accretion of redeemable capital contributions | K28: ='Consolidated Financials'!J35 -> -58660 | L28: ='Consolidated Financials'!K35 -> -58660 | M28: ='Consolidated Financials'!L35 -> -53838 | N28: ='Consolidated Financials'!M35 -> 0 | O28: =SUM('Consolidated Financials'!U35:X35) -> 0 | P28: =Q28-O28 -> 0 | Q28: ='Consolidated Financials'!N35 -> 0 | R28: ='Consolidated Financials'!O35 -> 0 | AU28: x
C29: Profit/(Loss) before taxation | K29: =SUM(K25:K28,K23) -> -110918.94 | L29: =SUM(L25:L28,L23) -> -95966.194 | M29: =SUM(M25:M28,M23) -> -111699.46 | N29: =SUM(N25:N28,N23) -> -25915.105 | O29: =SUM(O25:O28,O23) -> -25787.553 | P29: =SUM(P25:P28,P23) -> 17342.518 | Q29: =SUM(Q25:Q28,Q23) -> -8445.0357 | R29: =SUM(R25:R28,R23) -> -14455.196 | AU29: x
AU30: x
C31: Income tax | K31: ='Consolidated Financials'!J39 -> -134 | L31: ='Consolidated Financials'!K39 -> 60 | M31: ='Consolidated Financials'!L39 -> 0 | N31: ='Consolidated Financials'!M39 -> 0 | O31: =SUM('Consolidated Financials'!U39:X39) -> 0 | P31: =Q31-O31 -> 0 | Q31: ='Consolidated Financials'!N39 -> 0 | R31: ='Consolidated Financials'!O39 -> 0 | AU31: x
AU32: x
C33: Profit/(Loss) for the year/period | K33: =K29+K31 -> -111052.94 | L33: =L29+L31 -> -95906.194 | M33: =M29+M31 -> -111699.46 | N33: =N29+N31 -> -25915.105 | O33: =O29+O31 -> -25787.553 | P33: =P29+P31 -> 17342.518 | Q33: =Q29+Q31 -> -8445.0357 | R33: =R29+R31 -> -14455.196 | AU33: x
C34: Attributable to: | AU34: x
AU35: x
C36: Equity shareholders of the Company | K36: =K33 -> -111052.94 | L36: =L33 -> -95906.194 | M36: =M33 -> -111699.46 | N36: =N33 -> -25915.105 | O36: =SUM('Consolidated Financials'!U45:X45) -> -25787.553 | P36: =Q36-O36 -> 17342.518 | Q36: =Q33 -> -8445.0357 | R36: =R33 -> -14455.196 | AU36: x
AU37: x
C38: Other comprehensive income for the year | AU38: x
AU39: x
C40: Exchange differences on translation of financial statements of a foreign subsidiary, net of nil tax | K40: ='Consolidated Financials'!J51 -> 0 | L40: ='Consolidated Financials'!K51 -> 0 | M40: ='Consolidated Financials'!L51 -> 0 | N40: ='Consolidated Financials'!M51 -> -475 | O40: =SUM('Consolidated Financials'!U51:X51) -> 73.03884 | P40: =Q40-O40 -> 0 | Q40: ='Consolidated Financials'!N51 -> 73.03884 | R40: ='Consolidated Financials'!O51 -> 0 | AU40: x
AU41: x
C42: Attributable to: | AU42: x
C43: Equity shareholders of the Company | K43: =K36+K40 -> -111052.94 | L43: =L36+L40 -> -95906.194 | M43: =M36+M40 -> -111699.46 | N43: =N36+N40 -> -26390.105 | O43: =O36+O40 -> -25714.515 | P43: =P36+P40 -> 17342.518 | Q43: =Q36+Q40 -> -8371.9969 | R43: =R36+R40 -> -14455.196 | AU43: x
AU44: x
C45: Total comprehensive income for the year | K45: =K36+K40 -> -111052.94 | L45: =L36+L40 -> -95906.194 | M45: =M36+M40 -> -111699.46 | N45: =N36+N40 -> -26390.105 | O45: =O36+O40 -> -25714.515 | P45: =P36+P40 -> 17342.518 | Q45: =Q36+Q40 -> -8371.9969 | R45: =R36+R40 -> -14455.196 | AU45: x
AU46: x
C47: ADD: | AU47: x
C48: Listing expenses | K48: ='Consolidated Financials'!J60 -> 0 | L48: ='Consolidated Financials'!K60 -> 0 | M48: ='Consolidated Financials'!L60 -> 1140 | N48: ='Consolidated Financials'!M60 -> 18328 | O48: =SUM('Consolidated Financials'!U60:X60) -> 1752 | P48: =Q48-O48 -> 15095.896 | Q48: ='Consolidated Financials'!N60 -> 16847.896 | R48: ='Consolidated Financials'!O60 -> 0 | AU48: x
C49: Equity-settled share-based payment expneses | K49: ='Consolidated Financials'!J61 -> 6172 | L49: ='Consolidated Financials'!K61 -> 7835 | M49: ='Consolidated Financials'!L61 -> 21479 | N49: ='Consolidated Financials'!M61 -> 21437 | O49: =SUM('Consolidated Financials'!U61:X61) -> 4570.0832 | P49: =Q49-O49 -> 9140.1664 | Q49: ='Consolidated Financials'!N61 -> 13710.25 | R49: ='Consolidated Financials'!O61 -> 1228.7184 | AU49: x
C50: Accretion of redemption liabilities | K50: ='Consolidated Financials'!J62 -> 58660 | L50: ='Consolidated Financials'!K62 -> 58660 | M50: ='Consolidated Financials'!L62 -> 53838 | N50: ='Consolidated Financials'!M62 -> 0 | O50: =SUM('Consolidated Financials'!U62:X62) -> 0 | P50: =Q50-O50 -> 0 | Q50: ='Consolidated Financials'!N62 -> 0 | R50: ='Consolidated Financials'!O62 -> 0 | AU50: x
C51: Adjusted net (loss)/profit (non-IFRS measure) | K51: =K45+SUM(K48:K50) -> -46220.941 | L51: =L45+SUM(L48:L50) -> -29411.194 | M51: =M33+SUM(M48:M50) -> -35242.456 | N51: =N33+SUM(N48:N50) -> 13849.895 | O51: =O33+SUM(O48:O50) -> -19465.47 | P51: =P33+SUM(P48:P50) -> 41578.58 | Q51: =Q33+SUM(Q48:Q50) -> 22113.11 | R51: =R33+SUM(R48:R50) -> -13226.477 | AU51: x
AU52: x
AU53: x
A54: 3.1 | C54: Revenue | AU54: x
B55: 收入（人民币千元） | C55: Revenue (In RMB thousands) | AU55: x
AU56: x
C57: Revenue from ICT services | AU57: x
C58: Revenue from AIGC services | AU58: x
C59: Revenue from AI voice services | AU59: x
C60: Revenue from AI application layer products | AU60: x
C61: Revenue from[] | AU61: x
C62: Total Revenue | AU62: x
AU63: x
AU64: x
A65: 3.2 | C65: Cost of Sales and Gross Profit Margin | AU65: x
B66: 销售成本（人民币千元） | C66: Cost of Sales (RMB in thousands) | AU66: x
AU67: x
C68: Cost for ICT services | AU68: x
C69: Cost for AIGC services | AU69: x
C70: Cost for AI voice services | AU70: x
C71: Cost for AI application layer products | AU71: x
C72: Cost for[] | AU72: x
AU73: x
C74: Gross Margin (%) | AU74: x
AU75: x
C76: ICT services | AU76: x
C77: AIGC services | AU77: x
C78: AI voice services | AU78: x
C79: AI application layer products | AU79: x
C80: [] | AU80: x
C81: overall | AU81: x
AU82: x
A83: 3.3 | C83: Operating Expenses | AU83: x
C84: Operating Expenses (In RMB thousands) | AU84: x
AU85: x
A86: y | C86: Selling and distribution expenses | M86: =M99 -> 82569.503 | N86: 55235 | O86: =O99 -> 14827.4 | P86: =P99 -> 65776.125 | Q86: =Q99 -> 80603.525 | R86: =R99 -> 51440.423 | AU86: x
C87: Administrative expenses | M87: 41211 | N87: =N109 -> 55634 | O87: =O109 -> 14384 | P87: =P109 -> 47636.78 | Q87: =Q109 -> 62020.78 | R87: =R109 -> 23058.414 | AU87: x
C88: Research and development expenses | M88: =M119 -> 150129 | N88: =N119 -> 163342 | O88: =O119 -> 68939.855 | P88: =P119 -> 161136.38 | Q88: =Q119 -> 230076.24 | R88: =R119 -> 152790.74 | AU88: x
C89: Total | M89: =SUM(M86:M88) -> 273909.5 | N89: =SUM(N86:N88) -> 274211 | O89: =SUM(O86:O88) -> 98151.255 | P89: =SUM(P86:P88) -> 274549.29 | Q89: =SUM(Q86:Q88) -> 372700.54 | R89: =SUM(R86:R88) -> 227289.58 | AU89: x
AU90: x
AU91: x
AU92: x
C93: Selling and distribution expenses | AU93: x
D94: Employee benefit expenses | M94: ='IS-Other Calculations'!L60 -> 30891.563 | N94: ='IS-Other Calculations'!M60 -> 18449 | O94: =SUM('IS-Other Calculations'!W60:Z60) -> 6587 | P94: =Q94-O94 -> 13992.543 | Q94: ='IS-Other Calculations'!N60 -> 20579.543 | R94: ='IS-Other Calculations'!O60 -> 7130.85 | AU94: x
D95: Marketing service expenses | M95: ='IS-Other Calculations'!L68 -> 28201.959 | N95: ='IS-Other Calculations'!M68 -> 21325 | O95: =SUM('IS-Other Calculations'!W68:Z68) -> 3274 | P95: =Q95-O95 -> 26268.997 | Q95: ='IS-Other Calculations'!N68 -> 29542.997 | R95: ='IS-Other Calculations'!O68 -> 15005.228 | AU95: x
D96: Advertising and promotion expenses | M96: ='IS-Other Calculations'!L72+'IS-Other Calculations'!L74 -> 17783.624 | N96: ='IS-Other Calculations'!M72+'IS-Other Calculations'!M74 -> 10940 | O96: =SUM('IS-Other Calculations'!W71:Z71) -> 4324 | P96: =Q96-O96 -> 19936.46 | Q96: ='IS-Other Calculations'!N72+'IS-Other Calculations'!N74 -> 24260.46 | R96: ='IS-Other Calculations'!O72+'IS-Other Calculations'!O74 -> 25773.328 | AU96: x
D97: Office, utilities and travelling expenses | M97: ='IS-Other Calculations'!L76 -> 3238.0681 | N97: ='IS-Other Calculations'!M76 -> 2398 | O97: =SUM('IS-Other Calculations'!W76:Z76) -> 487.31 | P97: =Q97-O97 -> 2786.6499 | Q97: ='IS-Other Calculations'!N76 -> 3273.9599 | R97: ='IS-Other Calculations'!O76 -> 1858.4301 | AU97: x
D98: Others | M98: ='IS-Other Calculations'!L79 -> 2454.2896 | N98: 2123 | O98: =SUM('IS-Other Calculations'!W79:Z79) -> 155.09 | P98: =Q98-O98 -> 2791.4739 | Q98: ='IS-Other Calculations'!N79 -> 2946.5639 | R98: ='IS-Other Calculations'!O79 -> 1672.5871 | AU98: x
C99: Total | M99: =SUM(M94:M98) -> 82569.503 | N99: =SUM(N94:N98) -> 55235 | O99: =SUM(O94:O98) -> 14827.4 | P99: =SUM(P94:P98) -> 65776.125 | Q99: =SUM(Q94:Q98) -> 80603.525 | R99: =SUM(R94:R98) -> 51440.423 | AU99: x
H100: checker | M100: =M99+'IS-Other Calculations'!L81 -> 0 | Q100: =Q99+'IS-Other Calculations'!N81 -> 0 | R100: =R99+'IS-Other Calculations'!O81 -> 0 | AU100: x
...

Sheet Cash Burn&CCC
A1: Blue: Hard code vale
A2: Black: Calculation
A3: Green: Linked from another tab
A4: Red: Linked from the same tab
C6: Cash burn rate
C7: RMB'000
C8: Cash burn rate | D8: 1.16
C10: Cash balance as of 31 Dec 2025 | D10: ='Consolidated Financials'!M135 -> 217756
C11: Average monthly net cash used in operating activities | D11: =$D$8*D31 -> -11830.786
C12: Average monthly capital expenditures | D12: =$D$8*D32 -> -13.05
C13: Average other scheduled cash payment | D13: =$D$8*D33 -> -241.5207
C14: Average Interest payment | D14: =$D$8*D34 -> -13.92
C15: Net IPO proceeds | D15: =Control!H30 -> 1118012.8
C18: Average cash outflow in 2023 | D18: =SUM(D19:D22) -> -5375.167 | F18: =D18/$D$48 -> 1.1325841
C19: Average monthly net cash used in operating activities | D19: ='Consolidated Financials'!K101/12 -> -4234.0003
C20: Average monthly purchase of property, plant and equipment | D20: ='Consolidated Financials'!K105/12 -> -620.91667
C21: Average monthly capital element of lease rental paid | D21: ='Consolidated Financials'!K120/12 -> -484
C22: Average monthly interest element of lease rental paid | D22: ='Consolidated Financials'!K121/12 -> -36.25
C24: Average cash outflow in 2024 | D24: =SUM(D25:D28) -> -7446.3333 | F24: =D24/$D$48 -> 1.5689929
C25: Average monthly net cash used in operating activities | D25: ='Consolidated Financials'!L101/12 -> -6851.3333
C26: Average monthly purchase of property, plant and equipment | D26: ='Consolidated Financials'!L105/12 -> -266.75
C27: Average monthly capital element of lease rental paid | D27: ='Consolidated Financials'!L120/12 -> -308.25
C28: Average monthly interest element of lease rental paid | D28: ='Consolidated Financials'!L121/12 -> -20
C30: Average cash outflow in 2025 | D30: =SUM(D31:D34) -> -10430.411 | F30: =D30/$D$48 -> 2.1977582
C31: Average monthly net cash used in operating activities | D31: ='Consolidated Financials'!M101/12 -> -10198.953
C32: Average monthly purchase of property, plant and equipment | D32: ='Consolidated Financials'!M105/12 -> -11.25
C33: Average monthly capital element of lease rental paid | D33: ='Consolidated Financials'!M120/12 -> -208.2075
C34: Average monthly interest element of lease rental paid | D34: ='Consolidated Financials'!M121/12 -> -12
C36: Average cash outflow from 1 Mar 2026 to 30 June 2027 | D36: =SUM(D37:D40) -> -7029.4081
C37: Average monthly net Cash used in operating activities (Litsting expense included) | D37: =SUM('Consolidated Financials'!W101:AL101)/16 -> -5390.0159
C38: Average monthly purchase of property, plant and equipment | D38: =SUM('Consolidated Financials'!W105:AL105)/16 -> -1238.8187
C39: Average monthly capital element of lease rental paid | D39: =SUM('Consolidated Financials'!W120:AL120)/16 -> -397.42548
C40: Average monthly interest element of lease rental paid | D40: =SUM('Consolidated Financials'!W121:AL121)/16 -> -3.1479703
C42: Average cash outflow from 1 Mar 2026 to 31 Dec 2026 | D42: =SUM(D43:D46) -> -3573.0606
C43: Average monthly net Cash used in operating activities (Litsting expense included) | D43: =SUM('Consolidated Financials'!W101:AF101)/10 -> -2520.7368
C44: Average monthly purchase of property, plant and equipment | D44: =SUM('Consolidated Financials'!W105:AF105)/10 -> -797.5947
C45: Average monthly capital element of lease rental paid | D45: =SUM('Consolidated Financials'!W120:AF120)/10 -> -269.00177
C46: Average monthly interest element of lease rental paid | D46: =SUM('Consolidated Financials'!W121:AF121)/10 -> 14.272668
C48: Average cash outflow from 1 Jan 2026 to 31 Dec 2026 | D48: =SUM(D49:D52) -> -4745.9319 | F48: =$D$48/D48 -> 1
C49: Average monthly net Cash used in operating activities (Litsting expense included) | D49: =SUM('Consolidated Financials'!U101:AF101)/12 -> -3748.811
C50: Average monthly purchase of property, plant and equipment | D50: =SUM('Consolidated Financials'!U105:AF105)/12 -> -664.66225
C51: Average monthly capital element of lease rental paid | D51: =SUM('Consolidated Financials'!U120:AF120)/12 -> -315.83566
C52: Average monthly interest element of lease rental paid | D52: =SUM('Consolidated Financials'!U121:AF121)/12 -> -16.622929
C54: Financial viability w/ IPO net proceeds | D54: =(D10+D15)/-SUM(D11:D14) -> 110.40071 | F54: =D54/12 -> 9.2000594 | G54: =IF(F54>1,"years","year") -> years
C55: Financial viability w/ 10% IPO net proceeds | D55: =(D10+D15/10)/-SUM(D11:D14) -> 27.237767 | F55: =D55/12 -> 2.2698139 | G55: =IF(F55>1,"years","year") -> years
C56: Financial viability w/o IPO net proceeds | D56: =(D10)/-SUM(D11:D14) -> 17.99744 | F56: =D56/12 -> 1.4997866 | G56: =IF(F56>1,"years","year") -> years
C61: Cash Conersion Cycle
D63: 2023 | E63: =D63+1 -> 2024 | F63: =E63+1 -> 2025 | G63: 2026E
C64: Revenue | D64: ='Consolidated Financials'!K10 -> 530805.86 | E64: ='Consolidated Financials'!L10 -> 655437.77 | F64: ='Consolidated Financials'!M10 -> 788818.16 | G64: ='Consolidated Financials'!N10 -> 1091320
C65: Cost of sales | D65: =-'Consolidated Financials'!K18 -> 287645.05 | E65: =-'Consolidated Financials'!L18 -> 430359.22 | F65: =-'Consolidated Financials'!M18 -> 516747.26 | G65: =-'Consolidated Financials'!N18 -> 702360.08
C66: Inventories | D66: ='Consolidated Financials'!K147 -> 14994 | E66: ='Consolidated Financials'!L147 -> 42368 | F66: ='Consolidated Financials'!M147 -> 79208 | G66: ='Consolidated Financials'!N147 -> 82431.031
C67: Trade receivables | D67: ='Consolidated Financials'!K148 -> 146717 | E67: ='Consolidated Financials'!L148 -> 232475 | F67: ='Consolidated Financials'!M148 -> 281637 | G67: ='Consolidated Financials'!N148 -> 383500.28
C68: Trade payables | D68: ='Consolidated Financials'!K159 -> 96413 | E68: ='Consolidated Financials'!L159 -> 115689 | F68: ='Consolidated Financials'!M159 -> 102487 | G68: ='Consolidated Financials'!N159 -> 193851.22
C69: Contract liabilities | D69: ='Consolidated Financials'!K161 -> 46497 | E69: ='Consolidated Financials'!L161 -> 50237 | F69: ='Consolidated Financials'!M161 -> 75574 | G69: ='Consolidated Financials'!N161 -> 81530.924
C72: Turnover | D72: 2023 | E72: =D72+1 -> 2024 | F72: =E72+1 -> 2025 | G72: 2026E
C73: Inventories | E73: =AVERAGE(D66:E66)/E65*365 -> 24.325179 | F73: =AVERAGE(E66:F66)/F65*365 -> 42.937083 | G73: =AVERAGE(F66:G66)/G65*365 -> 42
C74: Trade receivables | E74: =AVERAGE(D67:E67)/E64*365 -> 105.58217 | F74: =AVERAGE(E67:F67)/F64*365 -> 118.94432 | G74: =AVERAGE(F67:G67)/G64*365 -> 111.23003
C75: Trade payables | E75: =AVERAGE(D68:E68)/E65*365 -> 89.944895 | F75: =AVERAGE(E68:F68)/F65*365 -> 77.053374 | G75: =AVERAGE(F68:G68)/G65*365 -> 77
C76: Contract liabilities | E76: =AVERAGE(D69:E69)/E64*365 -> 26.934601 | F76: =AVERAGE(E69:F69)/F64*365 -> 29.107478 | G76: =AVERAGE(F69:G69)/G64*365 -> 26.272449
C77: Cash conversion cycle (without CL) | E77: =E73+E74-E75 -> 39.962451 | F77: =F73+F74-F75 -> 84.82803 | G77: =G73+G74-G75 -> 76.23003
C78: Cash conversion cycle (with CL) | E78: =E77-E76 -> 13.02785 | F78: =F77-F76 -> 55.720551 | G78: =G77-G76 -> 49.957581

Sheet Working Capital Output_0319
A1: Blue: Hard code vale
A2: Black: Calculation
A3: Green: Linked from another tab
A4: Red: Linked from the same tab
E7: 2022 | F7: =E7+1 -> 2023 | G7: =F7+1 -> 2024 | H7: =G7+1 -> 2025 | I7: =H7+1 -> 2026 | J7: 2027 H1 | O7: 46023 | P7: =EDATE(O7,1) -> 46054 | Q7: =EDATE(P7,1) -> 46082 | R7: =EDATE(Q7,1) -> 46113 | S7: =EDATE(R7,1) -> 46143 | T7: =EDATE(S7,1) -> 46174 | U7: =EDATE(T7,1) -> 46204 | V7: =EDATE(U7,1) -> 46235 | W7: =EDATE(V7,1) -> 46266 | ... Z7: =EDATE(Y7,1) -> 46357 | AA7: 2026 | AB7: =EDATE(Z7,1) -> 46388 | AC7: =EDATE(AB7,1) -> 46419 | AD7: =EDATE(AC7,1) -> 46447 | AE7: =EDATE(AD7,1) -> 46478 | AF7: =EDATE(AE7,1) -> 46508 | AG7: =EDATE(AF7,1) -> 46539 | AH7: 2027 H1
E8: Actual | F8: Actual | G8: Actual | H8: Actual | I8: Forecast | J8: Forecast | O8: Estimate | P8: Estimate | Q8: Estimate | R8: Estimate | S8: Forecast | T8: Forecast | U8: Forecast | V8: Forecast | W8: Forecast | X8: Forecast | Y8: Forecast | Z8: Forecast | AA8: Forecast | AB8: Forecast | AC8: Forecast | AD8: Forecast | AE8: Forecast | AF8: Forecast | AG8: Forecast | AH8: Forecast
E9: Actual | F9: Actual | G9: Actual
C10: Working Capital Forecast for the year ending December 31, 2026
C11: (In RMB thousands)
C12: Operating activities
C13: Profit (Loss) before taxation | E13: ='Consolidated Financials'!J67 -> -110918.94 | F13: ='Consolidated Financials'!K67 -> -95967 | G13: ='Consolidated Financials'!L67 -> -111699 | H13: ='Consolidated Financials'!M67 -> -25915 | I13: ='Consolidated Financials'!N67 -> -8445.0357 | J13: ='Consolidated Financials'!O67 -> -14455.196 | O13: ='Consolidated Financials'!U67 -> 9724.9118 | P13: ='Consolidated Financials'!V67 -> -15019.423 | Q13: ='Consolidated Financials'!W67 -> -10763.644 | R13: ='Consolidated Financials'!X67 -> -9729.3977 | S13: ='Consolidated Financials'!Y67 -> -3128.8664 | T13: ='Consolidated Financials'!Z67 -> -7962.4015 | U13: ='Consolidated Financials'!AA67 -> 4257.32 | V13: ='Consolidated Financials'!AB67 -> 4464.8044 | ... Z13: ='Consolidated Financials'!AF67 -> 5023.8129 | AA13: =SUM(O13:Z13) -> -8445.0357 | AB13: ='Consolidated Financials'!AG67 -> -3333.9765 | AC13: ='Consolidated Financials'!AH67 -> -2224.4783 | AD13: ='Consolidated Financials'!AI67 -> -3201.6609 | AE13: ='Consolidated Financials'!AJ67 -> -2229.719 | AF13: ='Consolidated Financials'!AK67 -> -2232.3394 | AG13: ='Consolidated Financials'!AL67 -> -1233.0216 | AH13: =SUM(AB13:AG13) -> -14455.196
C14: Adjustments for:
C15: Depreciation of property, plant and equipment | E15: ='Consolidated Financials'!J70 -> 6257 | F15: ='Consolidated Financials'!K70 -> 7446 | G15: ='Consolidated Financials'!L70 -> 7276 | H15: ='Consolidated Financials'!M70 -> 5231 | I15: ='Consolidated Financials'!N70 -> 2964.4784 | J15: ='Consolidated Financials'!O70 -> 3290.6838 | O15: ='Consolidated Financials'!U70 -> 301.5731 | P15: ='Consolidated Financials'!V70 -> 323.922 | Q15: ='Consolidated Financials'!W70 -> 301.3447 | R15: ='Consolidated Financials'!X70 -> 300.6981 | S15: ='Consolidated Financials'!Y70 -> 152.5795 | T15: ='Consolidated Financials'!Z70 -> 152.5795 | U15: ='Consolidated Financials'!AA70 -> 152.5795 | V15: ='Consolidated Financials'!AB70 -> 186.9998 | ... Z15: ='Consolidated Financials'!AF70 -> 324.681 | AA15: =SUM(O15:Z15) -> 2964.4784 | AB15: ='Consolidated Financials'!AG70 -> 419.37117 | AC15: ='Consolidated Financials'!AH70 -> 471.00162 | AD15: ='Consolidated Financials'!AI70 -> 522.63207 | AE15: ='Consolidated Financials'!AJ70 -> 574.26252 | AF15: ='Consolidated Financials'!AK70 -> 625.89297 | AG15: ='Consolidated Financials'!AL70 -> 677.52342 | AH15: =SUM(AB15:AG15) -> 3290.6838
C16: Depreciation of right-of-use assets | E16: ='Consolidated Financials'!J71 -> 7345 | F16: ='Consolidated Financials'!K71 -> 7398 | G16: ='Consolidated Financials'!L71 -> 5887 | H16: ='Consolidated Financials'!M71 -> 3654 | I16: ='Consolidated Financials'!N71 -> 3917.495 | J16: ='Consolidated Financials'!O71 -> 3738.8893 | O16: ='Consolidated Financials'!U71 -> 243.7 | P16: ='Consolidated Financials'!V71 -> 242.72691 | Q16: ='Consolidated Financials'!W71 -> 1158.4019 | R16: ='Consolidated Financials'!X71 -> 140.98527 | S16: ='Consolidated Financials'!Y71 -> 266.46012 | T16: ='Consolidated Financials'!Z71 -> 266.46012 | U16: ='Consolidated Financials'!AA71 -> 266.46012 | V16: ='Consolidated Financials'!AB71 -> 266.46012 | ... Z16: ='Consolidated Financials'!AF71 -> 266.46012 | AA16: =SUM(O16:Z16) -> 3917.495 | AB16: ='Consolidated Financials'!AG71 -> 623.14821 | AC16: ='Consolidated Financials'!AH71 -> 623.14821 | AD16: ='Consolidated Financials'!AI71 -> 623.14821 | AE16: ='Consolidated Financials'!AJ71 -> 623.14821 | AF16: ='Consolidated Financials'!AK71 -> 623.14821 | AG16: ='Consolidated Financials'!AL71 -> 623.14821 | AH16: =SUM(AB16:AG16) -> 3738.8893
C17: Amortisation of intangible assets | E17: ='Consolidated Financials'!J72 -> 747 | F17: ='Consolidated Financials'!K72 -> 553 | G17: ='Consolidated Financials'!L72 -> 220 | H17: ='Consolidated Financials'!M72 -> 74.56 | I17: ='Consolidated Financials'!N72 -> 74.56 | J17: ='Consolidated Financials'!O72 -> 37.28 | O17: ='Consolidated Financials'!U72 -> 6.4999 | P17: ='Consolidated Financials'!V72 -> 6.27 | Q17: ='Consolidated Financials'!W72 -> 6.251 | R17: ='Consolidated Financials'!X72 -> 6.268 | S17: ='Consolidated Financials'!Y72 -> 6.1588875 | T17: ='Consolidated Financials'!Z72 -> 6.1588875 | U17: ='Consolidated Financials'!AA72 -> 6.1588875 | V17: ='Consolidated Financials'!AB72 -> 6.1588875 | ... Z17: ='Consolidated Financials'!AF72 -> 6.1588875 | AA17: =SUM(O17:Z17) -> 74.56 | AB17: ='Consolidated Financials'!AG72 -> 6.2133333 | AC17: ='Consolidated Financials'!AH72 -> 6.2133333 | AD17: ='Consolidated Financials'!AI72 -> 6.2133333 | AE17: ='Consolidated Financials'!AJ72 -> 6.2133333 | AF17: ='Consolidated Financials'!AK72 -> 6.2133333 | AG17: ='Consolidated Financials'!AL72 -> 6.2133333 | AH17: =SUM(AB17:AG17) -> 37.28
C18: Impairment loss on trade and other receivables and contract assets | E18: ='Consolidated Financials'!J73 -> 3553 | F18: ='Consolidated Financials'!K73 -> 11749.996 | G18: ='Consolidated Financials'!L73 -> 21170 | H18: ='Consolidated Financials'!M73 -> 27595 | I18: ='Consolidated Financials'!N73 -> 26864.821 | J18: ='Consolidated Financials'!O73 -> 10970.471 | O18: ='Consolidated Financials'!U73 -> 4813.1893 | P18: ='Consolidated Financials'!V73 -> -1121.2699 | Q18: ='Consolidated Financials'!W73 -> 2171.1621 | R18: ='Consolidated Financials'!X73 -> -2435.3079 | S18: ='Consolidated Financials'!Y73 -> 1035.5685 | T18: ='Consolidated Financials'!Z73 -> 2962.919 | U18: ='Consolidated Financials'!AA73 -> 3205.7096 | V18: ='Consolidated Financials'!AB73 -> 3103.7754 | ... Z18: ='Consolidated Financials'!AF73 -> 3433.7995 | AA18: =SUM(O18:Z18) -> 26864.821 | AB18: ='Consolidated Financials'!AG73 -> 2026.5909 | AC18: ='Consolidated Financials'!AH73 -> 1713.9302 | AD18: ='Consolidated Financials'!AI73 -> 1987.9184 | AE18: ='Consolidated Financials'!AJ73 -> 1713.9302 | AF18: ='Consolidated Financials'!AK73 -> 1713.9302 | AG18: ='Consolidated Financials'!AL73 -> 1814.1713 | AH18: =SUM(AB18:AG18) -> 10970.471
C19: Government grants | E19: ='Consolidated Financials'!J77 -> -4629 | F19: ='Consolidated Financials'!K77 -> -2430 | G19: ='Consolidated Financials'!L77 -> -2552 | H19: ='Consolidated Financials'!M77 -> 0 | I19: ='Consolidated Financials'!N77 -> 0 | J19: ='Consolidated Financials'!O77 -> 0 | O19: ='Consolidated Financials'!U77 -> 0 | P19: ='Consolidated Financials'!V77 -> 0 | Q19: ='Consolidated Financials'!W77 -> 0 | R19: ='Consolidated Financials'!X77 -> 0 | S19: ='Consolidated Financials'!Y77 -> 0 | T19: ='Consolidated Financials'!Z77 -> 0 | U19: ='Consolidated Financials'!AA77 -> 0 | V19: ='Consolidated Financials'!AB77 -> 0 | ... Z19: ='Consolidated Financials'!AF77 -> 0 | AA19: =SUM(O19:Z19) -> 0 | AB19: ='Consolidated Financials'!AG77 -> 0 | AC19: ='Consolidated Financials'!AH77 -> 0 | AD19: ='Consolidated Financials'!AI77 -> 0 | AE19: ='Consolidated Financials'!AJ77 -> 0 | AF19: ='Consolidated Financials'!AK77 -> 0 | AG19: ='Consolidated Financials'!AL77 -> 0 | AH19: =SUM(AB19:AG19) -> 0
C20: Finance income | E20: ='Consolidated Financials'!J78 -> -9458 | F20: ='Consolidated Financials'!K78 -> -4606 | G20: ='Consolidated Financials'!L78 -> -2239 | H20: ='Consolidated Financials'!M78 -> -857 | I20: ='Consolidated Financials'!N78 -> -2719.8375 | J20: ='Consolidated Financials'!O78 -> -1959.1037 | O20: ='Consolidated Financials'!U78 -> -0.000913536 | P20: ='Consolidated Financials'!V78 -> -0.17778724 | Q20: ='Consolidated Financials'!W78 -> -150.58093 | R20: ='Consolidated Financials'!X78 -> -0.50410647 | S20: ='Consolidated Financials'!Y78 -> -81.092033 | T20: ='Consolidated Financials'!Z78 -> -360.59522 | U20: ='Consolidated Financials'!AA78 -> -358.84833 | V20: ='Consolidated Financials'!AB78 -> -357.10143 | ... Z20: ='Consolidated Financials'!AF78 -> -350.11385 | AA20: =SUM(O20:Z20) -> -2719.8375 | AB20: ='Consolidated Financials'!AG78 -> -333.06814 | AC20: ='Consolidated Financials'!AH78 -> -330.4478 | AD20: ='Consolidated Financials'!AI78 -> -327.82746 | AE20: ='Consolidated Financials'!AJ78 -> -325.20712 | AF20: ='Consolidated Financials'!AK78 -> -322.58677 | AG20: ='Consolidated Financials'!AL78 -> -319.96643 | AH20: =SUM(AB20:AG20) -> -1959.1037
C21: Finance costs | E21: ='Consolidated Financials'!J79 -> 759 | F21: ='Consolidated Financials'!K79 -> 435 | G21: ='Consolidated Financials'!L79 -> 240 | H21: ='Consolidated Financials'!M79 -> 144 | I21: ='Consolidated Financials'!N79 -> 199.47515 | J21: ='Consolidated Financials'!O79 -> 193.09421 | O21: ='Consolidated Financials'!U79 -> 133.213 | P21: ='Consolidated Financials'!V79 -> 208.98883 | Q21: ='Consolidated Financials'!W79 -> 167.66132 | R21: ='Consolidated Financials'!X79 -> 122.20971 | S21: ='Consolidated Financials'!Y79 -> -19.114378 | T21: ='Consolidated Financials'!Z79 -> -54.689142 | U21: ='Consolidated Financials'!AA79 -> -59.170536 | V21: ='Consolidated Financials'!AB79 -> -57.28905 | ... Z21: ='Consolidated Financials'!AF79 -> -63.380586 | AA21: =SUM(O21:Z21) -> 199.47515 | AB21: ='Consolidated Financials'!AG79 -> 35.67057 | AC21: ='Consolidated Financials'!AH79 -> 30.167346 | AD21: ='Consolidated Financials'!AI79 -> 34.989884 | AE21: ='Consolidated Financials'!AJ79 -> 30.167346 | AF21: ='Consolidated Financials'!AK79 -> 30.167346 | AG21: ='Consolidated Financials'!AL79 -> 31.931715 | AH21: =SUM(AB21:AG21) -> 193.09421
C22: Accretion of redemption liabilities | E22: ='Consolidated Financials'!J80 -> 58660 | F22: ='Consolidated Financials'!K80 -> 58660 | G22: ='Consolidated Financials'!L80 -> 53838 | H22: ='Consolidated Financials'!M80 -> 0 | I22: ='Consolidated Financials'!N80 -> 0 | J22: ='Consolidated Financials'!O80 -> 0 | O22: ='Consolidated Financials'!U80 -> 0 | P22: ='Consolidated Financials'!V80 -> 0 | Q22: ='Consolidated Financials'!W80 -> 0 | R22: ='Consolidated Financials'!X80 -> 0 | S22: ='Consolidated Financials'!Y80 -> 0 | T22: ='Consolidated Financials'!Z80 -> 0 | U22: ='Consolidated Financials'!AA80 -> 0 | V22: ='Consolidated Financials'!AB80 -> 0 | ... Z22: ='Consolidated Financials'!AF80 -> 0 | AA22: =SUM(O22:Z22) -> 0 | AB22: ='Consolidated Financials'!AG80 -> 0 | AC22: ='Consolidated Financials'!AH80 -> 0 | AD22: ='Consolidated Financials'!AI80 -> 0 | AE22: ='Consolidated Financials'!AJ80 -> 0 | AF22: ='Consolidated Financials'!AK80 -> 0 | AG22: ='Consolidated Financials'!AL80 -> 0 | AH22: =SUM(AB22:AG22) -> 0
C23: Equity-settled share-based payment expenses | E23: ='Consolidated Financials'!J81 -> 6172 | F23: ='Consolidated Financials'!K81 -> 7835 | G23: ='Consolidated Financials'!L81 -> 21479 | H23: ='Consolidated Financials'!M81 -> 21437 | I23: ='Consolidated Financials'!N81 -> 13710.25 | J23: ='Consolidated Financials'!O81 -> 1228.7184 | O23: ='Consolidated Financials'!U81 -> 1142.5208 | P23: ='Consolidated Financials'!V81 -> 1142.5208 | Q23: ='Consolidated Financials'!W81 -> 1142.5208 | R23: ='Consolidated Financials'!X81 -> 1142.5208 | S23: ='Consolidated Financials'!Y81 -> 1142.5208 | T23: ='Consolidated Financials'!Z81 -> 1142.5208 | U23: ='Consolidated Financials'!AA81 -> 1142.5208 | V23: ='Consolidated Financials'!AB81 -> 1142.5208 | ... Z23: ='Consolidated Financials'!AF81 -> 1142.5208 | AA23: =SUM(O23:Z23) -> 13710.25 | AB23: ='Consolidated Financials'!AG81 -> 204.7864 | AC23: ='Consolidated Financials'!AH81 -> 204.7864 | AD23: ='Consolidated Financials'!AI81 -> 204.7864 | AE23: ='Consolidated Financials'!AJ81 -> 204.7864 | AF23: ='Consolidated Financials'!AK81 -> 204.7864 | AG23: ='Consolidated Financials'!AL81 -> 204.7864 | AH23: =SUM(AB23:AG23) -> 1228.7184
C24: Net gain on disposal of property, plant and equipment | E24: ='Consolidated Financials'!J82 -> 0 | F24: ='Consolidated Financials'!K82 -> -48 | G24: ='Consolidated Financials'!L82 -> -15 | H24: ='Consolidated Financials'!M82 -> 0 | I24: ='Consolidated Financials'!N82 -> 0 | J24: ='Consolidated Financials'!O82 -> 0 | O24: ='Consolidated Financials'!U82 -> 0 | P24: ='Consolidated Financials'!V82 -> 0 | Q24: ='Consolidated Financials'!W82 -> 0 | R24: ='Consolidated Financials'!X82 -> 0 | S24: ='Consolidated Financials'!Y82 -> 0 | T24: ='Consolidated Financials'!Z82 -> 0 | U24: ='Consolidated Financials'!AA82 -> 0 | V24: ='Consolidated Financials'!AB82 -> 0 | ... Z24: ='Consolidated Financials'!AF82 -> 0 | AA24: =SUM(O24:Z24) -> 0 | AB24: ='Consolidated Financials'!AG82 -> 0 | AC24: ='Consolidated Financials'!AH82 -> 0 | AD24: ='Consolidated Financials'!AI82 -> 0 | AE24: ='Consolidated Financials'!AJ82 -> 0 | AF24: ='Consolidated Financials'!AK82 -> 0 | AG24: ='Consolidated Financials'!AL82 -> 0 | AH24: =SUM(AB24:AG24) -> 0
C25: Share of loss of associates | E25: ='Consolidated Financials'!J83 -> 0 | F25: ='Consolidated Financials'!K83 -> 1104 | G25: ='Consolidated Financials'!L83 -> 27 | H25: ='Consolidated Financials'!M83 -> 164 | I25: ='Consolidated Financials'!N83 -> 0 | J25: ='Consolidated Financials'!O83 -> 0 | O25: ='Consolidated Financials'!U83 -> 0 | P25: ='Consolidated Financials'!V83 -> 0 | Q25: ='Consolidated Financials'!W83 -> 0 | R25: ='Consolidated Financials'!X83 -> 0 | S25: ='Consolidated Financials'!Y83 -> 0 | T25: ='Consolidated Financials'!Z83 -> 0 | U25: ='Consolidated Financials'!AA83 -> 0 | V25: ='Consolidated Financials'!AB83 -> 0 | ... Z25: ='Consolidated Financials'!AF83 -> 0 | AA25: =SUM(O25:Z25) -> 0 | AB25: ='Consolidated Financials'!AG83 -> 0 | AC25: ='Consolidated Financials'!AH83 -> 0 | AD25: ='Consolidated Financials'!AI83 -> 0 | AE25: ='Consolidated Financials'!AJ83 -> 0 | AF25: ='Consolidated Financials'!AK83 -> 0 | AG25: ='Consolidated Financials'!AL83 -> 0 | AH25: =SUM(AB25:AG25) -> 0
C26: Net foreign exchange loss/(gain) | E26: ='Consolidated Financials'!J84 -> 0 | F26: ='Consolidated Financials'!K84 -> 0 | G26: ='Consolidated Financials'!L84 -> 0 | H26: ='Consolidated Financials'!M84 -> 0 | I26: ='Consolidated Financials'!N84 -> 0 | J26: ='Consolidated Financials'!O84 -> 0 | O26: ='Consolidated Financials'!U84 -> 0 | P26: ='Consolidated Financials'!V84 -> 0 | Q26: ='Consolidated Financials'!W84 -> 0 | R26: ='Consolidated Financials'!X84 -> 0 | S26: ='Consolidated Financials'!Y84 -> 0 | T26: ='Consolidated Financials'!Z84 -> 0 | U26: ='Consolidated Financials'!AA84 -> 0 | V26: ='Consolidated Financials'!AB84 -> 0 | ... Z26: ='Consolidated Financials'!AF84 -> 0 | AA26: =SUM(O26:Z26) -> 0 | AB26: ='Consolidated Financials'!AG84 -> 0 | AC26: ='Consolidated Financials'!AH84 -> 0 | AD26: ='Consolidated Financials'!AI84 -> 0 | AE26: ='Consolidated Financials'!AJ84 -> 0 | AF26: ='Consolidated Financials'!AK84 -> 0 | AG26: ='Consolidated Financials'!AL84 -> 0 | AH26: =SUM(AB26:AG26) -> 0
C27: Net gain on disposal of an associate | E27: ='Consolidated Financials'!J85 -> 0 | F27: ='Consolidated Financials'!K85 -> 0 | G27: ='Consolidated Financials'!L85 -> 0 | H27: ='Consolidated Financials'!M85 -> -801 | I27: ='Consolidated Financials'!N85 -> 0 | J27: ='Consolidated Financials'!O85 -> 0 | O27: ='Consolidated Financials'!U85 -> 0 | P27: ='Consolidated Financials'!V85 -> 0 | Q27: ='Consolidated Financials'!W85 -> 0 | R27: ='Consolidated Financials'!X85 -> 0 | S27: ='Consolidated Financials'!Y85 -> 0 | T27: ='Consolidated Financials'!Z85 -> 0 | U27: ='Consolidated Financials'!AA85 -> 0 | V27: ='Consolidated Financials'!AB85 -> 0 | ... Z27: ='Consolidated Financials'!AF85 -> 0 | AA27: =SUM(O27:Z27) -> 0 | AB27: ='Consolidated Financials'!AG85 -> 0 | AC27: ='Consolidated Financials'!AH85 -> 0 | AD27: ='Consolidated Financials'!AI85 -> 0 | AE27: ='Consolidated Financials'!AJ85 -> 0 | AF27: ='Consolidated Financials'!AK85 -> 0 | AG27: ='Consolidated Financials'!AL85 -> 0 | AH27: =SUM(AB27:AG27) -> 0
C29: Changes in working capital:
C30: Decrease/(increase) in inventories | E30: ='Consolidated Financials'!J88 -> 1185 | F30: ='Consolidated Financials'!K88 -> -14696 | G30: ='Consolidated Financials'!L88 -> -27374 | H30: ='Consolidated Financials'!M88 -> -36840 | I30: ='Consolidated Financials'!N88 -> -3223.0313 | J30: ='Consolidated Financials'!O88 -> -18068.237 | O30: ='Consolidated Financials'!U88 -> 25913.608 | P30: ='Consolidated Financials'!V88 -> 9571.5609 | Q30: ='Consolidated Financials'!W88 -> 792.67309 | R30: ='Consolidated Financials'!X88 -> -27789.275 | S30: ='Consolidated Financials'!Y88 -> -517.47824 | T30: ='Consolidated Financials'!Z88 -> -1480.584 | U30: ='Consolidated Financials'!AA88 -> -1601.9075 | V30: ='Consolidated Financials'!AB88 -> -1550.9705 | ... Z30: ='Consolidated Financials'!AF88 -> -1715.885 | AA30: =SUM(O30:Z30) -> -3223.0313 | AB30: ='Consolidated Financials'!AG88 -> -3337.7713 | AC30: ='Consolidated Financials'!AH88 -> -2822.8229 | AD30: ='Consolidated Financials'!AI88 -> -3274.0781 | AE30: ='Consolidated Financials'!AJ88 -> -2822.8229 | AF30: ='Consolidated Financials'!AK88 -> -2822.8229 | AG30: ='Consolidated Financials'!AL88 -> -2987.9188 | AH30: =SUM(AB30:AG30) -> -18068.237
C31: (Increase)/decrease in trade receivables | E31: ='Consolidated Financials'!J89 -> -31960 | F31: ='Consolidated Financials'!K89 -> -101153 | G31: ='Consolidated Financials'!L89 -> -106824 | H31: ='Consolidated Financials'!M89 -> -76224 | I31: ='Consolidated Financials'!N89 -> -126665.46 | J31: ='Consolidated Financials'!O89 -> 15839.282 | O31: ='Consolidated Financials'!U89 -> -20685.835 | P31: ='Consolidated Financials'!V89 -> 6926.905 | Q31: ='Consolidated Financials'!W89 -> 31415.93 | R31: ='Consolidated Financials'!X89 -> 37629 | S31: ='Consolidated Financials'!Y89 -> -8039.5456 | T31: ='Consolidated Financials'!Z89 -> -23002.363 | U31: ='Consolidated Financials'!AA89 -> -24887.246 | V31: ='Consolidated Financials'!AB89 -> -24095.889 | ... Z31: ='Consolidated Financials'!AF89 -> -26658.001 | AA31: =SUM(O31:Z31) -> -126665.46 | AB31: ='Consolidated Financials'!AG89 -> 2926.0132 | AC31: ='Consolidated Financials'!AH89 -> 2474.5905 | AD31: ='Consolidated Financials'!AI89 -> 2870.1774 | AE31: ='Consolidated Financials'!AJ89 -> 2474.5905 | AF31: ='Consolidated Financials'!AK89 -> 2474.5905 | AG31: ='Consolidated Financials'!AL89 -> 2619.3196 | AH31: =SUM(AB31:AG31) -> 15839.282
C32: (Increase) /decrease in contract assets | E32: ='Consolidated Financials'!J90 -> -508 | F32: ='Consolidated Financials'!K90 -> -5095 | G32: ='Consolidated Financials'!L90 -> -2540 | H32: ='Consolidated Financials'!M90 -> -12977 | I32: ='Consolidated Financials'!N90 -> -21826.4 | J32: ='Consolidated Financials'!O90 -> -12389.534 | O32: ='Consolidated Financials'!U90 -> -500 | P32: ='Consolidated Financials'!V90 -> -28.73 | Q32: ='Consolidated Financials'!W90 -> -972.79931 | R32: ='Consolidated Financials'!X90 -> 10691.815 | S32: ='Consolidated Financials'!Y90 -> -1370.4757 | T32: ='Consolidated Financials'!Z90 -> -3921.1393 | U32: ='Consolidated Financials'!AA90 -> -4242.4493 | V32: ='Consolidated Financials'!AB90 -> -4107.5492 | ... Z32: ='Consolidated Financials'!AF90 -> -4544.3044 | AA32: =SUM(O32:Z32) -> -21826.4 | AB32: ='Consolidated Financials'!AG90 -> -2288.7364 | AC32: ='Consolidated Financials'!AH90 -> -1935.6321 | AD32: ='Consolidated Financials'!AI90 -> -2245.0615 | AE32: ='Consolidated Financials'!AJ90 -> -1935.6321 | AF32: ='Consolidated Financials'!AK90 -> -1935.6321 | AG32: ='Consolidated Financials'!AL90 -> -2048.8397 | AH32: =SUM(AB32:AG32) -> -12389.534
C33: (Increase)/decrease in prepayments, deposits and other receivables | E33: ='Consolidated Financials'!J91 -> -51558 | F33: ='Consolidated Financials'!K91 -> -12736 | G33: ='Consolidated Financials'!L91 -> 31502 | H33: ='Consolidated Financials'!M91 -> -33467 | I33: ='Consolidated Financials'!N91 -> -22414.879 | J33: ='Consolidated Financials'!O91 -> 22179.336 | O33: ='Consolidated Financials'!U91 -> -15507.151 | P33: ='Consolidated Financials'!V91 -> 29805.871 | Q33: ='Consolidated Financials'!W91 -> -21957.924 | R33: ='Consolidated Financials'!X91 -> 4090.3563 | S33: ='Consolidated Financials'!Y91 -> -422.08052 | T33: ='Consolidated Financials'!Z91 -> -1207.6366 | U33: ='Consolidated Financials'!AA91 -> -3263.1163 | V33: ='Consolidated Financials'!AB91 -> -3058.5261 | ... Z33: ='Consolidated Financials'!AF91 -> -2540.8643 | AA33: =SUM(O33:Z33) -> -22414.879 | AB33: ='Consolidated Financials'!AG91 -> 3631.6018 | AC33: ='Consolidated Financials'!AH91 -> 3014.0362 | AD33: ='Consolidated Financials'!AI91 -> 4014.0967 | AE33: ='Consolidated Financials'!AJ91 -> 3503.1667 | AF33: ='Consolidated Financials'!AK91 -> 3747.732 | AG33: ='Consolidated Financials'!AL91 -> 4268.7022 | AH33: =SUM(AB33:AG33) -> 22179.336
C34: (Increase)/decrease in restricted bank deposits | E34: ='Consolidated Financials'!J92 -> -3 | F34: ='Consolidated Financials'!K92 -> 3 | G34: ='Consolidated Financials'!L92 -> -1412 | H34: ='Consolidated Financials'!M92 -> 1412 | I34: ='Consolidated Financials'!N92 -> 0 | J34: ='Consolidated Financials'!O92 -> 0 | O34: ='Consolidated Financials'!U92 -> 0 | P34: ='Consolidated Financials'!V92 -> 0 | Q34: ='Consolidated Financials'!W92 -> 0 | R34: ='Consolidated Financials'!X92 -> 0 | S34: ='Consolidated Financials'!Y92 -> 0 | T34: ='Consolidated Financials'!Z92 -> 0 | U34: ='Consolidated Financials'!AA92 -> 0 | V34: ='Consolidated Financials'!AB92 -> 0 | ... Z34: ='Consolidated Financials'!AF92 -> 0 | AA34: =SUM(O34:Z34) -> 0 | AB34: ='Consolidated Financials'!AG92 -> 0 | AC34: ='Consolidated Financials'!AH92 -> 0 | AD34: ='Consolidated Financials'!AI92 -> 0 | AE34: ='Consolidated Financials'!AJ92 -> 0 | AF34: ='Consolidated Financials'!AK92 -> 0 | AG34: ='Consolidated Financials'!AL92 -> 0 | AH34: =SUM(AB34:AG34) -> 0
C35: Increase/(decrease) in trade payables | E35: ='Consolidated Financials'!J93 -> 16794 | F35: ='Consolidated Financials'!K93 -> 58921 | G35: ='Consolidated Financials'!L93 -> 19276 | H35: ='Consolidated Financials'!M93 -> -13202 | I35: ='Consolidated Financials'!N93 -> 91364.224 | J35: ='Consolidated Financials'!O93 -> -52330.232 | O35: ='Consolidated Financials'!U93 -> 595.781 | P35: ='Consolidated Financials'!V93 -> -2637.7343 | Q35: ='Consolidated Financials'!W93 -> -15204.942 | R35: ='Consolidated Financials'!X93 -> -22322.788 | S35: ='Consolidated Financials'!Y93 -> 5785.3292 | T35: ='Consolidated Financials'!Z93 -> 16552.707 | U35: ='Consolidated Financials'!AA93 -> 17909.086 | V35: ='Consolidated Financials'!AB93 -> 17339.618 | ... Z35: ='Consolidated Financials'!AF93 -> 19183.337 | AA35: =SUM(O35:Z35) -> 91364.224 | AB35: ='Consolidated Financials'!AG93 -> -9667.0389 | AC35: ='Consolidated Financials'!AH93 -> -8175.6166 | AD35: ='Consolidated Financials'!AI93 -> -9482.5671 | AE35: ='Consolidated Financials'!AJ93 -> -8175.6166 | AF35: ='Consolidated Financials'!AK93 -> -8175.6166 | AG35: ='Consolidated Financials'!AL93 -> -8653.7764 | AH35: =SUM(AB35:AG35) -> -52330.232
C36: Increase/ (decrease) in other payables and accruals | E36: ='Consolidated Financials'!J94 -> -2129 | F36: ='Consolidated Financials'!K94 -> -6881 | G36: ='Consolidated Financials'!L94 -> 7960 | H36: ='Consolidated Financials'!M94 -> -7153 | I36: ='Consolidated Financials'!N94 -> -4742.9266 | J36: ='Consolidated Financials'!O94 -> -3139.8139 | O36: ='Consolidated Financials'!U94 -> -4996.3609 | P36: ='Consolidated Financials'!V94 -> -207.01058 | Q36: ='Consolidated Financials'!W94 -> -1284.6804 | R36: ='Consolidated Financials'!X94 -> 109.20179 | S36: ='Consolidated Financials'!Y94 -> 72.283464 | T36: ='Consolidated Financials'!Z94 -> 206.81398 | U36: ='Consolidated Financials'!AA94 -> 223.76095 | V36: ='Consolidated Financials'!AB94 -> 216.64586 | ... Z36: ='Consolidated Financials'!AF94 -> 239.68179 | AA36: =SUM(O36:Z36) -> -4742.9266 | AB36: ='Consolidated Financials'!AG94 -> -580.02233 | AC36: ='Consolidated Financials'!AH94 -> -490.537 | AD36: ='Consolidated Financials'!AI94 -> -568.95403 | AE36: ='Consolidated Financials'!AJ94 -> -490.537 | AF36: ='Consolidated Financials'!AK94 -> -490.537 | AG36: ='Consolidated Financials'!AL94 -> -519.22659 | AH36: =SUM(AB36:AG36) -> -3139.8139
C37: Increase/(decrease) in deferred income | E37: ='Consolidated Financials'!J95 -> 1229 | F37: ='Consolidated Financials'!K95 -> -1053 | G37: ='Consolidated Financials'!L95 -> -176 | H37: ='Consolidated Financials'!M95 -> 0 | I37: ='Consolidated Financials'!N95 -> 0 | J37: ='Consolidated Financials'!O95 -> 0 | O37: ='Consolidated Financials'!U95 -> 0 | P37: ='Consolidated Financials'!V95 -> 0 | Q37: ='Consolidated Financials'!W95 -> 0 | R37: ='Consolidated Financials'!X95 -> 0 | S37: ='Consolidated Financials'!Y95 -> 0 | T37: ='Consolidated Financials'!Z95 -> 0 | U37: ='Consolidated Financials'!AA95 -> 0 | V37: ='Consolidated Financials'!AB95 -> 0 | ... Z37: ='Consolidated Financials'!AF95 -> 0 | AA37: =SUM(O37:Z37) -> 0 | AB37: ='Consolidated Financials'!AG95 -> 0 | AC37: ='Consolidated Financials'!AH95 -> 0 | AD37: ='Consolidated Financials'!AI95 -> 0 | AE37: ='Consolidated Financials'!AJ95 -> 0 | AF37: ='Consolidated Financials'!AK95 -> 0 | AG37: ='Consolidated Financials'!AL95 -> 0 | AH37: =SUM(AB37:AG37) -> 0
C38: Increase/ (decrease) in contract liabilities | E38: ='Consolidated Financials'!J96 -> 465 | F38: ='Consolidated Financials'!K96 -> 39692 | G38: ='Consolidated Financials'!L96 -> 3740 | H38: ='Consolidated Financials'!M96 -> 25337 | I38: ='Consolidated Financials'!N96 -> 5956.5391 | J38: ='Consolidated Financials'!O96 -> -16168.525 | O38: ='Consolidated Financials'!U96 -> -3317.614 | P38: ='Consolidated Financials'!V96 -> -46860.82 | Q38: ='Consolidated Financials'!W96 -> 1746.9936 | R38: ='Consolidated Financials'!X96 -> -807.21352 | S38: ='Consolidated Financials'!Y96 -> 2170.7076 | T38: ='Consolidated Financials'!Z96 -> 6982.5058 | U38: ='Consolidated Financials'!AA96 -> 7588.6536 | V38: ='Consolidated Financials'!AB96 -> 7334.1661 | ... Z38: ='Consolidated Financials'!AF96 -> 8158.0997 | AA38: =SUM(O38:Z38) -> 5956.5391 | AB38: ='Consolidated Financials'!AG96 -> -2986.8348 | AC38: ='Consolidated Financials'!AH96 -> -2526.0285 | AD38: ='Consolidated Financials'!AI96 -> -2929.8383 | AE38: ='Consolidated Financials'!AJ96 -> -2526.0285 | AF38: ='Consolidated Financials'!AK96 -> -2526.0285 | AG38: ='Consolidated Financials'!AL96 -> -2673.766 | AH38: =SUM(AB38:AG38) -> -16168.525
C40: Cash generated from / (used in) operating activities | E40: =SUM(E13,E15:E27,E30:E38) -> -107997.94 | F40: =SUM(F13,F15:F27,F30:F38) -> -50868.004 | G40: =SUM(G13,G15:G27,G30:G38) -> -82216 | H40: =SUM(H13,H15:H27,H30:H38) -> -122387.44 | I40: =SUM(I13,I15:I27,I30:I38) -> -44985.732 | J40: =SUM(J13,J15:J27,J30:J38) -> -61032.887 | O40: =SUM(O13,O15:O27,O30:O38) -> -2131.9647 | P40: =SUM(P13,P15:P27,P30:P38) -> -17646.4 | Q40: =SUM(Q13,Q15:Q27,Q30:Q38) -> -11431.633 | R40: =SUM(R13,R15:R27,R30:R38) -> -8851.4319 | S40: =SUM(S13,S15:S27,S30:S38) -> -2947.0447 | T40: =SUM(T13,T15:T27,T30:T38) -> -9716.7435 | U40: =SUM(U13,U15:U27,U30:U38) -> 339.51116 | V40: =SUM(V13,V15:V27,V30:V38) -> 833.82412 | ... Z40: =SUM(Z13,Z15:Z27,Z30:Z38) -> 1906.0023 | AA40: =SUM(O40:Z40) -> -44985.732 | AB40: =SUM(AB13,AB15:AB27,AB30:AB38) -> -12654.053 | AC40: =SUM(AC13,AC15:AC27,AC30:AC38) -> -9967.6895 | AD40: =SUM(AD13,AD15:AD27,AD30:AD38) -> -11766.025 | AE40: =SUM(AE13,AE15:AE27,AE30:AE38) -> -9375.298 | AF40: =SUM(AF13,AF15:AF27,AF30:AF38) -> -9079.1023 | AG40: =SUM(AG13,AG15:AG27,AG30:AG38) -> -8190.7194 | AH40: =SUM(AB40:AG40) -> -61032.887
C41: Tax (paid)/refunded | E41: ='Consolidated Financials'!J99 -> -134 | F41: ='Consolidated Financials'!K99 -> 60 | G41: ='Consolidated Financials'!L99 -> 0 | H41: ='Consolidated Financials'!M99 -> 0 | I41: ='Consolidated Financials'!N99 -> 0 | J41: ='Consolidated Financials'!O99 -> 0 | O41: ='Consolidated Financials'!U99 -> 0 | P41: ='Consolidated Financials'!V99 -> 0 | Q41: ='Consolidated Financials'!W99 -> 0 | R41: ='Consolidated Financials'!X99 -> 0 | S41: ='Consolidated Financials'!Y99 -> 0 | T41: ='Consolidated Financials'!Z99 -> 0 | U41: ='Consolidated Financials'!AA99 -> 0 | V41: ='Consolidated Financials'!AB99 -> 0 | ... Z41: ='Consolidated Financials'!AF99 -> 0 | AA41: =SUM(O41:Z41) -> 0 | AB41: ='Consolidated Financials'!AG99 -> 0 | AC41: ='Consolidated Financials'!AH99 -> 0 | AD41: ='Consolidated Financials'!AI99 -> 0 | AE41: ='Consolidated Financials'!AJ99 -> 0 | AF41: ='Consolidated Financials'!AK99 -> 0 | AG41: ='Consolidated Financials'!AL99 -> 0 | AH41: =SUM(AB41:AG41) -> 0
C43: Net cash generated from / (used in) operating activities | E43: =SUM(E40,E41) -> -108131.94 | F43: =SUM(F40,F41) -> -50808.004 | G43: =SUM(G40,G41) -> -82216 | H43: =SUM(H40,H41) -> -122387.44 | I43: =SUM(I40,I41) -> -44985.732 | J43: =SUM(J40,J41) -> -61032.887 | O43: =SUM(O40,O41) -> -2131.9647 | P43: =SUM(P40,P41) -> -17646.4 | Q43: =SUM(Q40,Q41) -> -11431.633 | R43: =SUM(R40,R41) -> -8851.4319 | S43: =SUM(S40,S41) -> -2947.0447 | T43: =SUM(T40,T41) -> -9716.7435 | U43: =SUM(U40,U41) -> 339.51116 | V43: =SUM(V40,V41) -> 833.82412 | ... Z43: =SUM(Z40,Z41) -> 1906.0023 | AA43: =SUM(O43:Z43) -> -44985.732 | AB43: =SUM(AB40,AB41) -> -12654.053 | AC43: =SUM(AC40,AC41) -> -9967.6895 | AD43: =SUM(AD40,AD41) -> -11766.025 | AE43: =SUM(AE40,AE41) -> -9375.298 | AF43: =SUM(AF40,AF41) -> -9079.1023 | AG43: =SUM(AG40,AG41) -> -8190.7194 | AH43: =SUM(AB43:AG43) -> -61032.887
C45: Investing activities
C47: Payment for the acquisition of property, plant and equipment | E47: ='Consolidated Financials'!J105 -> -7172 | F47: ='Consolidated Financials'!K105 -> -7451 | G47: ='Consolidated Financials'!L105 -> -3201 | H47: ='Consolidated Financials'!M105 -> -135 | I47: ='Consolidated Financials'!N105 -> -7975.947 | J47: ='Consolidated Financials'!O105 -> -11845.152 | O47: ='Consolidated Financials'!U105 -> 0 | P47: ='Consolidated Financials'!V105 -> 0 | Q47: ='Consolidated Financials'!W105 -> 0 | R47: ='Consolidated Financials'!X105 -> 0 | S47: ='Consolidated Financials'!Y105 -> -6.6214811 | T47: ='Consolidated Financials'!Z105 -> -18.945065 | U47: ='Consolidated Financials'!AA105 -> -1324.8457 | V47: ='Consolidated Financials'!AB105 -> -1324.1939 | ... Z47: ='Consolidated Financials'!AF105 -> -1326.3041 | AA47: =SUM(O47:Z47) -> -7975.947 | AB47: ='Consolidated Financials'!AG105 -> -1976.1073 | AC47: ='Consolidated Financials'!AH105 -> -1973.0857 | AD47: ='Consolidated Financials'!AI105 -> -1975.7336 | AE47: ='Consolidated Financials'!AJ105 -> -1973.0857 | AF47: ='Consolidated Financials'!AK105 -> -1973.0857 | AG47: ='Consolidated Financials'!AL105 -> -1974.0545 | AH47: =SUM(AB47:AG47) -> -11845.152
C48: Proceeds from disposal of property, plant and equipment | E48: ='Consolidated Financials'!J106 -> 0 | F48: ='Consolidated Financials'!K106 -> 66 | G48: ='Consolidated Financials'!L106 -> 48 | H48: ='Consolidated Financials'!M106 -> 0 | I48: ='Consolidated Financials'!N106 -> 0 | J48: ='Consolidated Financials'!O106 -> 0 | O48: ='Consolidated Financials'!U106 -> 0 | P48: ='Consolidated Financials'!V106 -> 0 | Q48: ='Consolidated Financials'!W106 -> 0 | R48: ='Consolidated Financials'!X106 -> 0 | S48: ='Consolidated Financials'!Y106 -> 0 | T48: ='Consolidated Financials'!Z106 -> 0 | U48: ='Consolidated Financials'!AA106 -> 0 | V48: ='Consolidated Financials'!AB106 -> 0 | ... Z48: ='Consolidated Financials'!AF106 -> 0 | AA48: =SUM(O48:Z48) -> 0 | AB48: ='Consolidated Financials'!AG106 -> 0 | AC48: ='Consolidated Financials'!AH106 -> 0 | AD48: ='Consolidated Financials'!AI106 -> 0 | AE48: ='Consolidated Financials'!AJ106 -> 0 | AF48: ='Consolidated Financials'!AK106 -> 0 | AG48: ='Consolidated Financials'!AL106 -> 0 | AH48: =SUM(AB48:AG48) -> 0
C49: Payment for capital contribution to associates | E49: ='Consolidated Financials'!J107 -> 0 | F49: ='Consolidated Financials'!K107 -> -1500 | G49: ='Consolidated Financials'!L107 -> -200 | H49: ='Consolidated Financials'!M107 -> -190 | I49: ='Consolidated Financials'!N107 -> 0 | J49: ='Consolidated Financials'!O107 -> 0 | O49: ='Consolidated Financials'!U107 -> 0 | P49: ='Consolidated Financials'!V107 -> 0 | Q49: ='Consolidated Financials'!W107 -> 0 | R49: ='Consolidated Financials'!X107 -> 0 | S49: ='Consolidated Financials'!Y107 -> 0 | T49: ='Consolidated Financials'!Z107 -> 0 | U49: ='Consolidated Financials'!AA107 -> 0 | V49: ='Consolidated Financials'!AB107 -> 0 | ... Z49: ='Consolidated Financials'!AF107 -> 0 | AA49: =SUM(O49:Z49) -> 0 | AB49: ='Consolidated Financials'!AG107 -> 0 | AC49: ='Consolidated Financials'!AH107 -> 0 | AD49: ='Consolidated Financials'!AI107 -> 0 | AE49: ='Consolidated Financials'!AJ107 -> 0 | AF49: ='Consolidated Financials'!AK107 -> 0 | AG49: ='Consolidated Financials'!AL107 -> 0 | AH49: =SUM(AB49:AG49) -> 0
C50: Proceeds from deregistration of associates | E50: ='Consolidated Financials'!J108 -> 0 | F50: ='Consolidated Financials'!K108 -> 396 | G50: ='Consolidated Financials'!L108 -> 0 | H50: ='Consolidated Financials'!M108 -> 0 | I50: ='Consolidated Financials'!N108 -> 0 | J50: ='Consolidated Financials'!O108 -> 0 | O50: ='Consolidated Financials'!U108 -> 0 | P50: ='Consolidated Financials'!V108 -> 0 | Q50: ='Consolidated Financials'!W108 -> 0 | R50: ='Consolidated Financials'!X108 -> 0 | S50: ='Consolidated Financials'!Y108 -> 0 | T50: ='Consolidated Financials'!Z108 -> 0 | U50: ='Consolidated Financials'!AA108 -> 0 | V50: ='Consolidated Financials'!AB108 -> 0 | ... Z50: ='Consolidated Financials'!AF108 -> 0 | AA50: =SUM(O50:Z50) -> 0 | AB50: ='Consolidated Financials'!AG108 -> 0 | AC50: ='Consolidated Financials'!AH108 -> 0 | AD50: ='Consolidated Financials'!AI108 -> 0 | AE50: ='Consolidated Financials'!AJ108 -> 0 | AF50: ='Consolidated Financials'!AK108 -> 0 | AG50: ='Consolidated Financials'!AL108 -> 0 | AH50: =SUM(AB50:AG50) -> 0
C51: Proceeds from disposal of other investments in equity securities | E51: ='Consolidated Financials'!J109 -> 2000 | F51: ='Consolidated Financials'!K109 -> 0 | G51: ='Consolidated Financials'!L109 -> 0 | H51: ='Consolidated Financials'!M109 -> 0 | I51: ='Consolidated Financials'!N109 -> 0 | J51: ='Consolidated Financials'!O109 -> 0 | O51: ='Consolidated Financials'!U109 -> 0 | P51: ='Consolidated Financials'!V109 -> 0 | Q51: ='Consolidated Financials'!W109 -> 0 | R51: ='Consolidated Financials'!X109 -> 0 | S51: ='Consolidated Financials'!Y109 -> 0 | T51: ='Consolidated Financials'!Z109 -> 0 | U51: ='Consolidated Financials'!AA109 -> 0 | V51: ='Consolidated Financials'!AB109 -> 0 | ... Z51: ='Consolidated Financials'!AF109 -> 0 | AA51: =SUM(O51:Z51) -> 0 | AB51: ='Consolidated Financials'!AG109 -> 0 | AC51: ='Consolidated Financials'!AH109 -> 0 | AD51: ='Consolidated Financials'!AI109 -> 0 | AE51: ='Consolidated Financials'!AJ109 -> 0 | AF51: ='Consolidated Financials'!AK109 -> 0 | AG51: ='Consolidated Financials'!AL109 -> 0 | AH51: =SUM(AB51:AG51) -> 0
C52: Proceeds from certificate of deposits | E52: ='Consolidated Financials'!J110 -> 110000 | F52: ='Consolidated Financials'!K110 -> 110000 | G52: ='Consolidated Financials'!L110 -> 0 | H52: ='Consolidated Financials'!M110 -> 0 | I52: ='Consolidated Financials'!N110 -> 0 | J52: ='Consolidated Financials'!O110 -> 0 | O52: ='Consolidated Financials'!U110 -> 0 | P52: ='Consolidated Financials'!V110 -> 0 | Q52: ='Consolidated Financials'!W110 -> 0 | R52: ='Consolidated Financials'!X110 -> 0 | S52: ='Consolidated Financials'!Y110 -> 0 | T52: ='Consolidated Financials'!Z110 -> 0 | U52: ='Consolidated Financials'!AA110 -> 0 | V52: ='Consolidated Financials'!AB110 -> 0 | ... Z52: ='Consolidated Financials'!AF110 -> 0 | AA52: =SUM(O52:Z52) -> 0 | AB52: ='Consolidated Financials'!AG110 -> 0 | AC52: ='Consolidated Financials'!AH110 -> 0 | AD52: ='Consolidated Financials'!AI110 -> 0 | AE52: ='Consolidated Financials'!AJ110 -> 0 | AF52: ='Consolidated Financials'!AK110 -> 0 | AG52: ='Consolidated Financials'!AL110 -> 0 | AH52: =SUM(AB52:AG52) -> 0
C53: Interest income received | E53: ='Consolidated Financials'!J111 -> 9458 | F53: ='Consolidated Financials'!K111 -> 4606 | G53: ='Consolidated Financials'!L111 -> 2239 | H53: ='Consolidated Financials'!M111 -> 857 | I53: ='Consolidated Financials'!N111 -> 2719.8375 | J53: ='Consolidated Financials'!O111 -> 1959.1037 | O53: ='Consolidated Financials'!U111 -> 0.000913536 | P53: ='Consolidated Financials'!V111 -> 0.17778724 | Q53: ='Consolidated Financials'!W111 -> 150.58093 | R53: ='Consolidated Financials'!X111 -> 0.50410647 | S53: ='Consolidated Financials'!Y111 -> 81.092033 | T53: ='Consolidated Financials'!Z111 -> 360.59522 | U53: ='Consolidated Financials'!AA111 -> 358.84833 | V53: ='Consolidated Financials'!AB111 -> 357.10143 | ... Z53: ='Consolidated Financials'!AF111 -> 350.11385 | AA53: =SUM(O53:Z53) -> 2719.8375 | AB53: ='Consolidated Financials'!AG111 -> 333.06814 | AC53: ='Consolidated Financials'!AH111 -> 330.4478 | AD53: ='Consolidated Financials'!AI111 -> 327.82746 | AE53: ='Consolidated Financials'!AJ111 -> 325.20712 | AF53: ='Consolidated Financials'!AK111 -> 322.58677 | AG53: ='Consolidated Financials'!AL111 -> 319.96643 | AH53: =SUM(AB53:AG53) -> 1959.1037
C55: Net cash generated from / (used in) investing activities | E55: =SUM(E47:E53) -> 114286 | F55: =SUM(F47:F53) -> 106117 | G55: =SUM(G47:G53) -> -1114 | H55: =SUM(H47:H53) -> 532 | I55: =SUM(I47:I53) -> -5256.1095 | J55: =SUM(J47:J53) -> -9886.0488 | O55: =SUM(O47:O53) -> 0.000913536 | P55: =SUM(P47:P53) -> 0.17778724 | Q55: =SUM(Q47:Q53) -> 150.58093 | R55: =SUM(R47:R53) -> 0.50410647 | S55: =SUM(S47:S53) -> 74.470552 | T55: =SUM(T47:T53) -> 341.65016 | U55: =SUM(U47:U53) -> -965.99737 | V55: =SUM(V47:V53) -> -967.09249 | ... Z55: =SUM(Z47:Z53) -> -976.19026 | AA55: =SUM(O55:Z55) -> -5256.1095 | AB55: =SUM(AB47:AB53) -> -1643.0391 | AC55: =SUM(AC47:AC53) -> -1642.6379 | AD55: =SUM(AD47:AD53) -> -1647.9061 | AE55: =SUM(AE47:AE53) -> -1647.8786 | AF55: =SUM(AF47:AF53) -> -1650.499 | AG55: =SUM(AG47:AG53) -> -1654.088 | AH55: =SUM(AB55:AG55) -> -9886.0488
C57: Financing activities
C59: New borrowings | E59: ='Consolidated Financials'!J117 -> 0 | F59: ='Consolidated Financials'!K117 -> 0 | G59: ='Consolidated Financials'!L117 -> 0 | H59: ='Consolidated Financials'!M117 -> 0 | I59: ='Consolidated Financials'!N117 -> 0 | J59: ='Consolidated Financials'!O117 -> 0 | O59: ='Consolidated Financials'!U117 -> 0 | P59: ='Consolidated Financials'!V117 -> 0 | Q59: ='Consolidated Financials'!W117 -> 0 | R59: ='Consolidated Financials'!X117 -> 0 | S59: ='Consolidated Financials'!Y117 -> 0 | T59: ='Consolidated Financials'!Z117 -> 0 | U59: ='Consolidated Financials'!AA117 -> 0 | V59: ='Consolidated Financials'!AB117 -> 0 | ... Z59: ='Consolidated Financials'!AF117 -> 0 | AA59: =SUM(O59:Z59) -> 0 | AB59: ='Consolidated Financials'!AG117 -> 0 | AC59: ='Consolidated Financials'!AH117 -> 0 | AD59: ='Consolidated Financials'!AI117 -> 0 | AE59: ='Consolidated Financials'!AJ117 -> 0 | AF59: ='Consolidated Financials'!AK117 -> 0 | AG59: ='Consolidated Financials'!AL117 -> 0 | AH59: =SUM(AB59:AG59) -> 0
C60: Repayments of borrowings | E60: ='Consolidated Financials'!J118 -> 0 | F60: ='Consolidated Financials'!K118 -> 0 | G60: ='Consolidated Financials'!L118 -> 0 | H60: ='Consolidated Financials'!M118 -> 0 | I60: ='Consolidated Financials'!N118 -> 0 | J60: ='Consolidated Financials'!O118 -> 0 | O60: ='Consolidated Financials'!U118 -> 0 | P60: ='Consolidated Financials'!V118 -> 0 | Q60: ='Consolidated Financials'!W118 -> 0 | R60: ='Consolidated Financials'!X118 -> 0 | S60: ='Consolidated Financials'!Y118 -> 0 | T60: ='Consolidated Financials'!Z118 -> 0 | U60: ='Consolidated Financials'!AA118 -> 0 | V60: ='Consolidated Financials'!AB118 -> 0 | ... Z60: ='Consolidated Financials'!AF118 -> 0 | AA60: =SUM(O60:Z60) -> 0 | AB60: ='Consolidated Financials'!AG118 -> 0 | AC60: ='Consolidated Financials'!AH118 -> 0 | AD60: ='Consolidated Financials'!AI118 -> 0 | AE60: ='Consolidated Financials'!AJ118 -> 0 | AF60: ='Consolidated Financials'!AK118 -> 0 | AG60: ='Consolidated Financials'!AL118 -> 0 | AH60: =SUM(AB60:AG60) -> 0
C61: Interest paid | E61: ='Consolidated Financials'!J119 -> 0 | F61: ='Consolidated Financials'!K119 -> 0 | G61: ='Consolidated Financials'!L119 -> 0 | H61: ='Consolidated Financials'!M119 -> 0 | I61: ='Consolidated Financials'!N119 -> 0 | J61: ='Consolidated Financials'!O119 -> 0 | O61: ='Consolidated Financials'!U119 -> 0 | P61: ='Consolidated Financials'!V119 -> 0 | Q61: ='Consolidated Financials'!W119 -> 0 | R61: ='Consolidated Financials'!X119 -> 0 | S61: ='Consolidated Financials'!Y119 -> 0 | T61: ='Consolidated Financials'!Z119 -> 0 | U61: ='Consolidated Financials'!AA119 -> 0 | V61: ='Consolidated Financials'!AB119 -> 0 | ... Z61: ='Consolidated Financials'!AF119 -> 0 | AA61: =SUM(O61:Z61) -> 0 | AB61: ='Consolidated Financials'!AG119 -> 0 | AC61: ='Consolidated Financials'!AH119 -> 0 | AD61: ='Consolidated Financials'!AI119 -> 0 | AE61: ='Consolidated Financials'!AJ119 -> 0 | AF61: ='Consolidated Financials'!AK119 -> 0 | AG61: ='Consolidated Financials'!AL119 -> 0 | AH61: =SUM(AB61:AG61) -> 0
C62: Capital element of lease rental paid | E62: ='Consolidated Financials'!J120 -> -2488 | F62: ='Consolidated Financials'!K120 -> -5808 | G62: ='Consolidated Financials'!L120 -> -3699 | H62: ='Consolidated Financials'!M120 -> -2498.49 | I62: ='Consolidated Financials'!N120 -> -3790.0279 | J62: ='Consolidated Financials'!O120 -> -3668.7899 | O62: ='Consolidated Financials'!U120 -> -628.203 | P62: ='Consolidated Financials'!V120 -> -471.80717 | Q62: ='Consolidated Financials'!W120 -> 12.017323 | R62: ='Consolidated Financials'!X120 -> 9.8717131 | S62: ='Consolidated Financials'!Y120 -> -119.8259 | T62: ='Consolidated Financials'!Z120 -> -342.84012 | U62: ='Consolidated Financials'!AA120 -> -370.93348 | V62: ='Consolidated Financials'!AB120 -> -359.13865 | ... Z62: ='Consolidated Financials'!AF120 -> -397.32581 | AA62: =SUM(O62:Z62) -> -3790.0279 | AB62: ='Consolidated Financials'!AG120 -> -677.74083 | AC62: ='Consolidated Financials'!AH120 -> -573.17957 | AD62: ='Consolidated Financials'!AI120 -> -664.8078 | AE62: ='Consolidated Financials'!AJ120 -> -573.17957 | AF62: ='Consolidated Financials'!AK120 -> -573.17957 | AG62: ='Consolidated Financials'!AL120 -> -606.70259 | AH62: =SUM(AB62:AG62) -> -3668.7899
C63: Interest element of lease rental paid | E63: ='Consolidated Financials'!J121 -> -759 | F63: ='Consolidated Financials'!K121 -> -435 | G63: ='Consolidated Financials'!L121 -> -240 | H63: ='Consolidated Financials'!M121 -> -144 | I63: ='Consolidated Financials'!N121 -> -199.47515 | J63: ='Consolidated Financials'!O121 -> -193.09421 | O63: ='Consolidated Financials'!U121 -> -133.213 | P63: ='Consolidated Financials'!V121 -> -208.98883 | Q63: ='Consolidated Financials'!W121 -> -167.66132 | R63: ='Consolidated Financials'!X121 -> -122.20971 | S63: ='Consolidated Financials'!Y121 -> 19.114378 | T63: ='Consolidated Financials'!Z121 -> 54.689142 | U63: ='Consolidated Financials'!AA121 -> 59.170536 | V63: ='Consolidated Financials'!AB121 -> 57.28905 | ... Z63: ='Consolidated Financials'!AF121 -> 63.380586 | AA63: =SUM(O63:Z63) -> -199.47515 | AB63: ='Consolidated Financials'!AG121 -> -35.67057 | AC63: ='Consolidated Financials'!AH121 -> -30.167346 | AD63: ='Consolidated Financials'!AI121 -> -34.989884 | AE63: ='Consolidated Financials'!AJ121 -> -30.167346 | AF63: ='Consolidated Financials'!AK121 -> -30.167346 | AG63: ='Consolidated Financials'!AL121 -> -31.931715 | AH63: =SUM(AB63:AG63) -> -193.09421
C64: Capital contribution from investors | E64: ='Consolidated Financials'!J122 -> 0 | F64: ='Consolidated Financials'!K122 -> 0 | G64: ='Consolidated Financials'!L122 -> 0 | H64: ='Consolidated Financials'!M122 -> 180472 | I64: ='Consolidated Financials'!N122 -> 0 | J64: ='Consolidated Financials'!O122 -> 0 | O64: ='Consolidated Financials'!U122 -> 0 | P64: ='Consolidated Financials'!V122 -> 0 | Q64: ='Consolidated Financials'!W122 -> 0 | R64: ='Consolidated Financials'!X122 -> 0 | S64: ='Consolidated Financials'!Y122 -> 0 | T64: ='Consolidated Financials'!Z122 -> 0 | U64: ='Consolidated Financials'!AA122 -> 0 | V64: ='Consolidated Financials'!AB122 -> 0 | ... Z64: ='Consolidated Financials'!AF122 -> 0 | AA64: =SUM(O64:Z64) -> 0 | AB64: ='Consolidated Financials'!AG122 -> 0 | AC64: ='Consolidated Financials'!AH122 -> 0 | AD64: ='Consolidated Financials'!AI122 -> 0 | AE64: ='Consolidated Financials'!AJ122 -> 0 | AF64: ='Consolidated Financials'!AK122 -> 0 | AG64: ='Consolidated Financials'!AL122 -> 0 | AH64: =SUM(AB64:AG64) -> 0
C65: Net Proceeds from issue of ordinary shares | E65: ='Consolidated Financials'!J123 -> 0 | F65: ='Consolidated Financials'!K123 -> 0 | G65: ='Consolidated Financials'!L123 -> 0 | H65: ='Consolidated Financials'!M123 -> 0 | I65: ='Consolidated Financials'!N123 -> 1154328.8 | J65: ='Consolidated Financials'!O123 -> 0 | O65: ='Consolidated Financials'!U123 -> 0 | P65: ='Consolidated Financials'!V123 -> 0 | Q65: ='Consolidated Financials'!W123 -> 0 | R65: ='Consolidated Financials'!X123 -> 0 | S65: ='Consolidated Financials'!Y123 -> 0 | T65: ='Consolidated Financials'!Z123 -> 1154328.8 | U65: ='Consolidated Financials'!AA123 -> 0 | V65: ='Consolidated Financials'!AB123 -> 0 | ... Z65: ='Consolidated Financials'!AF123 -> 0 | AA65: =SUM(O65:Z65) -> 1154328.8 | AB65: ='Consolidated Financials'!AG123 -> 0 | AC65: ='Consolidated Financials'!AH123 -> 0 | AD65: ='Consolidated Financials'!AI123 -> 0 | AE65: ='Consolidated Financials'!AJ123 -> 0 | AF65: ='Consolidated Financials'!AK123 -> 0 | AG65: ='Consolidated Financials'!AL123 -> 0 | AH65: =SUM(AB65:AG65) -> 0
C66: Payment of listing expenses to be capitalised | E66: ='Consolidated Financials'!J124 -> 0 | F66: ='Consolidated Financials'!K124 -> 0 | G66: ='Consolidated Financials'!L124 -> 0 | H66: ='Consolidated Financials'!M124 -> -6582 | I66: ='Consolidated Financials'!N124 -> 0 | J66: ='Consolidated Financials'!O124 -> 0 | O66: ='Consolidated Financials'!U124 -> 0 | P66: ='Consolidated Financials'!V124 -> 0 | Q66: ='Consolidated Financials'!W124 -> 0 | R66: ='Consolidated Financials'!X124 -> 0 | S66: ='Consolidated Financials'!Y124 -> 0 | T66: ='Consolidated Financials'!Z124 -> 0 | U66: ='Consolidated Financials'!AA124 -> 0 | V66: ='Consolidated Financials'!AB124 -> 0 | ... Z66: ='Consolidated Financials'!AF124 -> 0 | AA66: =SUM(O66:Z66) -> 0 | AB66: ='Consolidated Financials'!AG124 -> 0 | AC66: ='Consolidated Financials'!AH124 -> 0 | AD66: ='Consolidated Financials'!AI124 -> 0 | AE66: ='Consolidated Financials'!AJ124 -> 0 | AF66: ='Consolidated Financials'!AK124 -> 0 | AG66: ='Consolidated Financials'!AL124 -> 0 | AH66: =SUM(AB66:AG66) -> 0
C68: Net cash (used in)/generated from financing activities | E68: =SUM(E59:E66) -> -3247 | F68: =SUM(F59:F66) -> -6243 | G68: =SUM(G59:G66) -> -3939 | H68: =SUM(H59:H66) -> 171247.51 | I68: =SUM(I59:I66) -> 1150339.3 | J68: =SUM(J59:J66) -> -3861.8841 | O68: =SUM(O59:O66) -> -761.416 | P68: =SUM(P59:P66) -> -680.796 | Q68: =SUM(Q59:Q66) -> -155.644 | R68: =SUM(R59:R66) -> -112.338 | S68: =SUM(S59:S66) -> -100.71152 | T68: =SUM(T59:T66) -> 1154040.6 | U68: =SUM(U59:U66) -> -311.76294 | V68: =SUM(V59:V66) -> -301.8496 | ... Z68: =SUM(Z59:Z66) -> -333.94523 | AA68: =SUM(O68:Z68) -> 1150339.3 | AB68: =SUM(AB59:AB66) -> -713.4114 | AC68: =SUM(AC59:AC66) -> -603.34691 | AD68: =SUM(AD59:AD66) -> -699.79768 | AE68: =SUM(AE59:AE66) -> -603.34691 | AF68: =SUM(AF59:AF66) -> -603.34691 | AG68: =SUM(AG59:AG66) -> -638.63431 | AH68: =SUM(AB68:AG68) -> -3861.8841
C70: Net increase/(decrease) in cash and cash equivalents | E70: =E43+E55+E68 -> 2907.0588 | F70: =F43+F55+F68 -> 49065.996 | G70: -87269 | H70: 49393 | I70: =I43+I55+I68 -> 1100097.4 | J70: =J43+J55+J68 -> -74780.82 | O70: =O43+O55+O68 -> -2893.3798 | P70: =P43+P55+P68 -> -18327.018 | Q70: =Q43+Q55+Q68 -> -11436.696 | R70: =R43+R55+R68 -> -8963.2658 | S70: =S43+S55+S68 -> -2973.2857 | T70: =T43+T55+T68 -> 1144665.5 | U70: =U43+U55+U68 -> -938.24915 | V70: =V43+V55+V68 -> -435.11797 | ... Z70: =Z43+Z55+Z68 -> 595.86682 | AA70: =SUM(O70:Z70) -> 1100097.4 | AB70: =AB43+AB55+AB68 -> -15010.503 | AC70: =AC43+AC55+AC68 -> -12213.674 | AD70: =AD43+AD55+AD68 -> -14113.729 | AE70: =AE43+AE55+AE68 -> -11626.524 | AF70: =AF43+AF55+AF68 -> -11332.948 | AG70: =AG43+AG55+AG68 -> -10483.442 | AH70: =SUM(AB70:AG70) -> -74780.82
C72: Cash and cash equivalents at the beginning of the year/period | E72: ='Consolidated Financials'!J131 -> 204134 | F72: =E76 -> 207041.06 | G72: =F76 -> 256107 | H72: 168838 | I72: =H76 -> 217756 | J72: =I76 -> 1317926.5 | O72: =H76 -> 217756 | P72: =O76 -> 214908.92 | Q72: =P76 -> 196594.47 | R72: =Q76 -> 185151.91 | S72: =R76 -> 176208.68 | T72: =S76 -> 173235.39 | U72: =T76 -> 1317900.9 | V72: =U76 -> 1316962.7 | W72: =V76 -> 1316527.6 | ... Z72: =Y76 -> 1317330.6 | AA72: =H76 -> 217756 | AB72: =Z76 -> 1317926.5 | AC72: =AB76 -> 1302916 | AD72: =AC76 -> 1290702.3 | AE72: =AD76 -> 1276588.6 | AF72: =AE76 -> 1264962 | AG72: =AF76 -> 1253629.1 | AH72: =AA76 -> 1317926.5
C74: Effect of foreign exchange rate changes | E74: ='Consolidated Financials'!J133 -> 0 | F74: ='Consolidated Financials'!K133 -> 0 | G74: ='Consolidated Financials'!L133 -> 0 | H74: ='Consolidated Financials'!M133 -> -475 | I74: ='Consolidated Financials'!N133 -> 73.03884 | J74: ='Consolidated Financials'!O133 -> 0 | O74: ='Consolidated Financials'!U133 -> 46.3 | P74: ='Consolidated Financials'!V133 -> 12.56884 | Q74: ='Consolidated Financials'!W133 -> -5.87 | R74: ='Consolidated Financials'!X133 -> 20.04 | S74: ='Consolidated Financials'!Y133 -> 0 | T74: ='Consolidated Financials'!Z133 -> 0 | U74: ='Consolidated Financials'!AA133 -> 0 | V74: ='Consolidated Financials'!AB133 -> 0 | ... Z74: ='Consolidated Financials'!AF133 -> 0 | AA74: =SUM(O74:Z74) -> 73.03884 | AB74: ='Consolidated Financials'!AG133 -> 0 | AC74: ='Consolidated Financials'!AH133 -> 0 | AD74: ='Consolidated Financials'!AI133 -> 0 | AE74: ='Consolidated Financials'!AJ133 -> 0 | AF74: ='Consolidated Financials'!AK133 -> 0 | AG74: ='Consolidated Financials'!AL133 -> 0 | AH74: =SUM(AB74:AG74) -> 0
C76: Cash and cash equivalents at the end of the year/period | E76: =E70+E72+E74 -> 207041.06 | F76: 256107 | G76: 168838 | H76: =H70+H72+H74 -> 217756 | I76: =I70+I72+I74 -> 1317926.5 | J76: =J70+J72+J74 -> 1243145.7 | O76: =O70+O72+O74 -> 214908.92 | P76: =P70+P72+P74 -> 196594.47 | Q76: =Q70+Q72+Q74 -> 185151.91 | R76: =R70+R72+R74 -> 176208.68 | S76: =S70+S72+S74 -> 173235.39 | T76: =T70+T72+T74 -> 1317900.9 | U76: =U70+U72+U74 -> 1316962.7 | V76: =V70+V72+V74 -> 1316527.6 | ... AH76: =AH70+AH72+AH74 -> 1243145.7
D81: check | E81: =E43-'Consolidated Financials'!J101 -> 0 | F81: =F43-'Consolidated Financials'!K101 -> 0 | G81: =G43-'Consolidated Financials'!L101 -> 0 | I81: =I43-'Consolidated Financials'!N101 -> 0 | J81: =J43-'Consolidated Financials'!O101 -> 0 | O81: =O43-'Consolidated Financials'!U101 -> 0 | P81: =P43-'Consolidated Financials'!V101 -> 0 | Q81: =Q43-'Consolidated Financials'!W101 -> 0 | R81: =R43-'Consolidated Financials'!X101 -> 0 | S81: =S43-'Consolidated Financials'!Y101 -> 0 | T81: =T43-'Consolidated Financials'!Z101 -> 0 | U81: =U43-'Consolidated Financials'!AA101 -> 0 | V81: =V43-'Consolidated Financials'!AB101 -> 0 | ... Z81: =Z43-'Consolidated Financials'!AF101 -> 0 | AB81: =AB43-'Consolidated Financials'!AG101 -> 0 | AC81: =AC43-'Consolidated Financials'!AH101 -> 0 | AD81: =AD43-'Consolidated Financials'!AI101 -> 0 | AE81: =AE43-'Consolidated Financials'!AJ101 -> 0 | AF81: =AF43-'Consolidated Financials'!AK101 -> 0 | AG81: =AG43-'Consolidated Financials'!AL101 -> 0
D82: check | E82: =E55-'Consolidated Financials'!J113 -> 0 | F82: =F55-'Consolidated Financials'!K113 -> 0 | G82: =G55-'Consolidated Financials'!L113 -> 0 | H82: =H55-'Consolidated Financials'!M113 -> 0 | I82: =I55-'Consolidated Financials'!N113 -> 0 | J82: =J55-'Consolidated Financials'!O113 -> 0 | O82: =O55-'Consolidated Financials'!U113 -> 0 | P82: =P55-'Consolidated Financials'!V113 -> 0 | Q82: =Q55-'Consolidated Financials'!W113 -> 0 | R82: =R55-'Consolidated Financials'!X113 -> 0 | S82: =S55-'Consolidated Financials'!Y113 -> 0 | T82: =T55-'Consolidated Financials'!Z113 -> 0 | U82: =U55-'Consolidated Financials'!AA113 -> 0 | V82: =V55-'Consolidated Financials'!AB113 -> 0 | ... Z82: =Z55-'Consolidated Financials'!AF113 -> 0 | AB82: =AB55-'Consolidated Financials'!AG113 -> 0 | AC82: =AC55-'Consolidated Financials'!AH113 -> 0 | AD82: =AD55-'Consolidated Financials'!AI113 -> 0 | AE82: =AE55-'Consolidated Financials'!AJ113 -> 0 | AF82: =AF55-'Consolidated Financials'!AK113 -> 0 | AG82: =AG55-'Consolidated Financials'!AL113 -> 0
D83: check | E83: =E68-'Consolidated Financials'!J126 -> 0 | F83: =F68-'Consolidated Financials'!K126 -> 0 | G83: =G68-'Consolidated Financials'!L126 -> 0 | H83: =H68-'Consolidated Financials'!M126 -> 0 | I83: =I68-'Consolidated Financials'!N126 -> 0 | J83: =J68-'Consolidated Financials'!O126 -> 0 | O83: =O68-'Consolidated Financials'!U126 -> 0 | P83: =P68-'Consolidated Financials'!V126 -> 0 | Q83: =Q68-'Consolidated Financials'!W126 -> 0 | R83: =R68-'Consolidated Financials'!X126 -> 0 | S83: =S68-'Consolidated Financials'!Y126 -> 0 | T83: =T68-'Consolidated Financials'!Z126 -> 0 | U83: =U68-'Consolidated Financials'!AA126 -> 0 | V83: =V68-'Consolidated Financials'!AB126 -> 0 | ... Z83: =Z68-'Consolidated Financials'!AF126 -> 0 | AB83: =AB68-'Consolidated Financials'!AG126 -> 0 | AC83: =AC68-'Consolidated Financials'!AH126 -> 0 | AD83: =AD68-'Consolidated Financials'!AI126 -> 0 | AE83: =AE68-'Consolidated Financials'!AJ126 -> 0 | AF83: =AF68-'Consolidated Financials'!AK126 -> 0 | AG83: =AG68-'Consolidated Financials'!AL126 -> 0
D84: check | E84: =E76-'Consolidated Financials'!J135 -> 0 | F84: =F76-'Consolidated Financials'!K135 -> -0.3060406 | G84: =G76-'Consolidated Financials'!L135 -> -0.3060406 | H84: =H76-'Consolidated Financials'!M135 -> 0 | I84: =I76-'Consolidated Financials'!N135 -> 0 | J84: =J76-'Consolidated Financials'!O135 -> 0 | O84: =O76-'Consolidated Financials'!U135 -> 0 | P84: =P76-'Consolidated Financials'!V135 -> 0 | Q84: =Q76-'Consolidated Financials'!W135 -> 0 | R84: =R76-'Consolidated Financials'!X135 -> 0 | S84: =S76-'Consolidated Financials'!Y135 -> 0 | T84: =T76-'Consolidated Financials'!Z135 -> 0 | U84: =U76-'Consolidated Financials'!AA135 -> 0 | V84: =V76-'Consolidated Financials'!AB135 -> 0 | ... X84: =X76-'Consolidated Financials'!AD135 -> 0

Sheet Sensitivity analysis
G3: 测算前，整体Growth Rate 必须为0
C4: 只改变整体的Growth rate | G4: 整体Growth rate为0，只改变新业务Growth rate
D5: 2026 | H5: 2026
C6: Revenue | D6: ='Consolidated Financials'!N10 -> 1091320 | G6: Revenue | H6: ='Consolidated Financials'!N10 -> 1091320
C7: Gross profit | D7: ='Consolidated Financials'!N20 -> 388959.9 | G7: Gross profit | H7: ='Consolidated Financials'!N20 -> 388959.9
C8: Net profit | D8: ='Consolidated Financials'!N41 -> -8445.0357 | G8: Net profit | H8: ='Consolidated Financials'!N41 -> -8445.0357
C9: Adjusted net profit | D9: ='Consolidated Financials'!N63 -> 22113.11 | G9: Adjusted net profit | H9: ='Consolidated Financials'!N63 -> 22113.11
C10: Cash and cash equivalent | D10: ='Consolidated Financials'!N135 -> 1317926.5 | G10: Cash and cash equivalent | H10: ='Consolidated Financials'!N135 -> 1317926.5
B13: hardcode | F13: hardcode
C14: Scenario 1 (20% decrease in revenue*) | G14: Scenario 1 (40% decrease in revenue*)
C15: Revenue | D15: 916193.33 | G15: Revenue | H15: 994967.78
C16: Gross profit | D16: 326488.47 | G16: Gross profit | H16: 345601.41
C17: Net profit | D17: -28053.132 | G17: Net profit | H17: -33376.403
C18: Adjusted net profit | D18: 2505.0136 | G18: Adjusted net profit | H18: -2818.2576
C19: Cash and cash equivalent | D19: 1377470.1 | G19: Cash and cash equivalent | H19: 1323115.3
C21: Scenario 2 (10% decrease in revenue*) | G21: Scenario 2 (30% decrease in revenue*)
C22: Revenue | D22: 1003756.7 | G22: Revenue | H22: 1019055.8
C23: Gross profit | D23: 357724.19 | G23: Gross profit | H23: 356441.04
C24: Net profit | D24: -18249.084 | G24: Net profit | H24: -28557.299
C25: Adjusted net profit | D25: 12309.062 | G25: Adjusted net profit | H25: 2000.8469
C26: Cash and cash equivalent | D26: 1347698.3 | G26: Cash and cash equivalent | H26: 1314343.3
C28: Scenario 3 (base case) | G28: Scenario 3 (20% decrease in revenue*)
C29: Revenue | D29: 1091320 | G29: Revenue | H29: 1043143.9
C30: Gross profit | D30: 388959.9 | G30: Gross profit | H30: 367280.66
C31: Net profit | D31: -8445.0357 | G31: Net profit | H31: -23738.194
C32: Adjusted net profit | D32: 22113.11 | G32: Adjusted net profit | H32: 6819.9513
C33: Cash and cash equivalent | D33: 1317926.5 | G33: Cash and cash equivalent | H33: 1305571.3
C35: Scenario 4 (10% increase in revenue*) | G35: Scenario 4 (10% decrease in revenue*)
C36: Revenue | D36: 1178883.3 | G36: Revenue | H36: 1067231.9
C37: Gross profit | D37: 420195.62 | G37: Gross profit | H37: 378120.28
C38: Net profit | D38: 483.37924 | G38: Net profit | H38: -18919.09
C39: Adjusted net profit | D39: 31041.525 | G39: Adjusted net profit | H39: 11639.056
C40: Cash and cash equivalent | D40: 1287279 | G40: Cash and cash equivalent | H40: 1296799.3
C42: Scenario 5 (20% increase in revenue*) | G42: Scenario 5 (base case)
C43: Revenue | D43: 1266446.6 | G43: Revenue | H43: 1091320 | K43: =H43-D29 -> 0
C44: Gross profit | D44: 451431.34 | G44: Gross profit | H44: 388959.9 | K44: =H44-D30 -> 0
C45: Net profit | D45: 9411.7942 | G45: Net profit | H45: -8445.0357 | K45: =H45-D31 -> 0
C46: Adjusted net profit | D46: 39969.94 | G46: Adjusted net profit | H46: 22113.11 | K46: =H46-D32 -> 0
C47: Cash and cash equivalent | D47: 1256631.6 | G47: Cash and cash equivalent | H47: 1317926.5 | K47: =H47-D33 -> 0

Sheet listing expense
A1: Nanjing Silicon Intelligence Technology Group Co., Ltd. (the "Company") | D1: A1版本（LPD 2025.10.24） | F1: LPD 2026.5.13
A2: E16. Listing expenses | C2: 汇率 | E2: 汇率 | I2: Domestic Shares | L2: 17084745 | P2: =P4/('Consolidated Financials'!N10*1000) -> 4.4757032
C3: 港币 | D3: 1 | E3: 港币 | F3: 1 | I3: Global Offering (25%) | L3: 5694900 | M3: =L3/(L3+L2) -> 0.24999951 | T3: Market Cap
C4: 美元兌港币 | D4: 7.7716 | E4: 美元兌港币 | F4: 7.8289 | G4: =6.9025*F5 -> 7.8968744 | I4: Over-allotment Option (15%) | L4: 854220 | N4: =N5/$F$5 -> 4.4055592e+09 | P4: =P5/$F$5 -> 4.8844243e+09 | R4: =R5/$F$5 -> 5.3632895e+09 | T4: =T10*$L$7/$F$5 -> 4.5707645e+09 | V4: =V10*$L$7/$F$5 -> 5.0675867e+09 | X4: =X10*$L$7/$F$5 -> 5.5644089e+09
C5: 人民币兌港币 | D5: =1/0.91266 -> 1.0956983 | E5: 人民币兌港币 | F5: =1/0.87408 -> 1.14406 | I5: Global Offering with OAO | L5: =SUM(L3:L4) -> 6549120 | N5: =N10*$L$6 -> 5.0402243e+09 | P5: =P10*$L$6 -> 5.5880747e+09 | R5: =R10*$L$6 -> 6.1359252e+09
F6: <to update as per LPD> | I6: Total without OAO | L6: =L2+L3 -> 22779645 | Z6: Global Offering WITHOUT Over-allotment Option exercised | AL6: Global Offering WITH Over-allotment Option exercised | AY6: Global Offering WITHOUT Over-allotment Option exercised | BE6: Global Offering WITH Over-allotment Option exercised | BK6: 管理帐人民币倒推
F7: 2026.5.13 | I7: Total with OAO | L7: =L2+L5 -> 23633865 | N7: Global Offering WITHOUT Over-allotment Option exercised | T7: Global Offering WITH Over-allotment Option exercised | BO7: 25% Equity;75% Expense | BW7: 25% Equity;75% Expense
D8: =7.0928*1.0957 -> 7.771581 | N8: Offer Price | T8: Offer Price | AC8: Low | AF8: Mid | AI8: High | AO8: Low | AR8: Mid | AU8: High | AY8: TRP | BB8: Post-TRP | BE8: TRP | BH8: Post-TRP | BK8: HKD | BS8: RMB
I9: Exchange rate | L9: Contract amount in HKD | N9: Low | P9: Mid | R9: High | T9: Low | V9: Mid | X9: High | AC9: =N10 -> 221.26 | AF9: =AVERAGE(AC9,AI9) -> 245.31 | AI9: =R10 -> 269.36 | AO9: 1.64 | AR9: 1.8 | AU9: 1.96 | AY9: Mid point | BB9: Mid point | BE9: Mid point | BH9: Mid point | BK9: 2024 | BN9: 2025 | BQ9: Remaining | BS9: 2024 | BV9: 2025 | BY9: Remaining | CF9: LPD
A10: No. | C10: Name of professional parties | D10: Particulars | E10: Oct | F10: Nov | G10: Contract currency | H10: Contract amount | I10: Currency / HKD | J10: Oct | K10: Nov | L10: HK$ | N10: 221.26 | P10: 245.31 | R10: 269.36 | T10: =N10 -> 221.26 | V10: =P10 -> 245.31 | X10: =R10 -> 269.36 | Z10: Equity | AA10: Expenses | AC10: Equity | AD10: Expenses | AF10: Equity | AG10: Expenses | AI10: Equity | AJ10: Expenses | AL10: Equity | AM10: Expenses | AO10: Equity | AP10: Expenses | AR10: Equity | AS10: Expenses | AU10: Equity | AV10: Expenses | AY10: Equity | AZ10: Expenses | BB10: Equity | BC10: Expenses | BE10: Equity | BF10: Expenses | BH10: Equity | BI10: Expenses | BK10: Total (HK$) | BL10: Equity (HK$) | BM10: Expenses (HK$) | BN10: Total (HK$) | BO10: Equity (HK$) | BP10: Expenses (HK$) | BQ10: Equity (HK$) | BR10: Expenses (HK$) | BS10: Total (RMB) | BT10: Equity (RMB) | BU10: Expenses (RMB) | BV10: Total (RMB) | BW10: Equity (RMB) | BX10: Expenses (RMB) | BY10: Equity (RMB) | BZ10: Expenses (RMB) | CC10: 已支付金额 | CD10: Contract currency | CE10: Remaining (Contract currency) | CF10: Remaining (HKD) | CG10: Remaining (RMB)
A11: 1 | B11: 招银国际融资有限公司 | C11: CMB International Capital Limited | D11: Joint Sponsor and Underwriters | F11: 600000 | G11: USD | H11: 1500000 | I11: =IF(G11="HKD",$F$3,IF(G11="USD",$F$4,IF(G11="RMB",$F$5,""))) -> 7.8289 | J11: =I11*E11 -> 0 | K11: =I11*F11 -> 4697340 | L11: =I11*H11 -> 11743350 | N11: =L11 -> 11743350 | P11: =L11 -> 11743350 | R11: =L11 -> 11743350 | T11: =L11 -> 11743350 | V11: =L11 -> 11743350 | X11: =L11 -> 11743350 | Z11: 0.25 | AA11: =1-Z11 -> 0.75 | AC11: =Z11*N11 -> 2935837.5 | AD11: =AA11*N11 -> 8807512.5 | AF11: =Z11*P11 -> 2935837.5 | AG11: =AA11*P11 -> 8807512.5 | AI11: =Z11*R11 -> 2935837.5 | AJ11: =AA11*R11 -> 8807512.5 | AL11: =Z11 -> 0.25 | AM11: =1-AL11 -> 0.75 | AO11: =AL11*T11 -> 2935837.5 | AP11: =AM11*T11 -> 8807512.5 | AR11: =AL11*V11 -> 2935837.5 | AS11: =AM11*V11 -> 8807512.5 | AU11: =AL11*X11 -> 2935837.5 | AV11: =AM11*X11 -> 8807512.5 | AY11: 0 | AZ11: 0 | BB11: =AF11-AY11 -> 2935837.5 | BC11: =AG11-AZ11 -> 8807512.5 | BE11: 0 | BF11: 0 | BH11: =AR11-BE11 -> 2935837.5 | BI11: =AS11-BF11 -> 8807512.5 | BL11: 100% Expense | BN11: =IF(BV11>0,IF(G11="HKD",H11,BV11*$F$5),0) -> 10333178 | BO11: =IF(BW11>0,IF(G11="HKD",AF11,BW11*$F$5),0) -> 2583294.5 | BP11: =IF(BX11>0,IF(G11="HKD",AG11,BX11*$F$5),0) -> 7749883.6 | BT11: 100% Expense | BV11: 9032024.4 | BW11: 2258006.1 | BX11: 6774018.3 | CC11: 1000000 | CD11: =G11 -> USD | CE11: =H11-CC11 -> 500000 | CF11: =CE11*I11 -> 3914450 | CG11: =CF11/$F$5 -> 3421542.5
A12: 2 | B12: 星展亚洲融资有限公司 | C12: DBS Asia Capital Limited | D12: Joint Sponsor and Underwriters | F12: 100000 | G12: USD | H12: 300000 | I12: =IF(G12="HKD",$F$3,IF(G12="USD",$F$4,IF(G12="RMB",$F$5,""))) -> 7.8289 | J12: =I12*E12 -> 0 | K12: =I12*F12 -> 782890 | L12: =I12*H12 -> 2348670 | N12: =L12 -> 2348670 | P12: =L12 -> 2348670 | R12: =L12 -> 2348670 | T12: =L12 -> 2348670 | V12: =L12 -> 2348670 | X12: =L12 -> 2348670 | Z12: 0.25 | AA12: =1-Z12 -> 0.75 | AC12: =Z12*N12 -> 587167.5 | AD12: =AA12*N12 -> 1761502.5 | AF12: =Z12*P12 -> 587167.5 | AG12: =AA12*P12 -> 1761502.5 | AI12: =Z12*R12 -> 587167.5 | AJ12: =AA12*R12 -> 1761502.5 | AL12: =Z12 -> 0.25 | AM12: =1-AL12 -> 0.75 | AO12: =AL12*T12 -> 587167.5 | AP12: =AM12*T12 -> 1761502.5 | AR12: =AL12*V12 -> 587167.5 | AS12: =AM12*V12 -> 1761502.5 | AU12: =AL12*X12 -> 587167.5 | AV12: =AM12*X12 -> 1761502.5 | AY12: 0 | AZ12: 0 | BB12: =AF12-AY12 -> 587167.5 | BC12: =AG12-AZ12 -> 1761502.5 | BE12: 0 | BF12: 0 | BH12: =AR12-BE12 -> 587167.5 | BI12: =AS12-BF12 -> 1761502.5 | BN12: =IF(BV12>0,IF(G12="HKD",H12,BV12*$F$5),0) -> 905777.75 | BO12: =IF(BW12>0,IF(G12="HKD",AF12,BW12*$F$5),0) -> 226444.44 | BP12: =IF(BX12>0,IF(G12="HKD",AG12,BX12*$F$5),0) -> 679333.32 | BV12: 791722.22 | BW12: 197930.55 | BX12: 593791.67 | CC12: 100000 | CD12: =G12 -> USD | CE12: =H12-CC12 -> 200000 | CF12: =CE12*I12 -> 1565780 | CG12: =CF12/$F$5 -> 1368617
A13: 3 | B13: 天元律師事務所 | C13: Tian Yuan Law Firm LLP | D13: Legal Advisors to the Company As to Hong Kong laws | F13: 360000 | G13: USD | H13: 900000 | I13: =IF(G13="HKD",$F$3,IF(G13="USD",$F$4,IF(G13="RMB",$F$5,""))) -> 7.8289 | J13: =I13*E13 -> 0 | K13: =I13*F13 -> 2818404 | L13: =I13*H13 -> 7046010 | N13: =L13 -> 7046010 | P13: =L13 -> 7046010 | R13: =L13 -> 7046010 | T13: =L13 -> 7046010 | V13: =L13 -> 7046010 | X13: =L13 -> 7046010 | Z13: 0.25 | AA13: =1-Z13 -> 0.75 | AC13: =Z13*N13 -> 1761502.5 | AD13: =AA13*N13 -> 5284507.5 | AF13: =Z13*P13 -> 1761502.5 | AG13: =AA13*P13 -> 5284507.5 | AI13: =Z13*R13 -> 1761502.5 | AJ13: =AA13*R13 -> 5284507.5 | AL13: =Z13 -> 0.25 | AM13: =1-AL13 -> 0.75 | AO13: =AL13*T13 -> 1761502.5 | AP13: =AM13*T13 -> 5284507.5 | AR13: =AL13*V13 -> 1761502.5 | AS13: =AM13*V13 -> 5284507.5 | AU13: =AL13*X13 -> 1761502.5 | AV13: =AM13*X13 -> 5284507.5 | AY13: 0 | AZ13: 0 | BB13: =AF13-AY13 -> 1761502.5 | BC13: =AG13-AZ13 -> 5284507.5 | BE13: 0 | BF13: 0 | BH13: =AR13-BE13 -> 1761502.5 | BI13: =AS13-BF13 -> 5284507.5 | BN13: =IF(BV13>0,IF(G13="HKD",H13,BV13*$F$5),0) -> 4558622.1 | BO13: =IF(BW13>0,IF(G13="HKD",AF13,BW13*$F$5),0) -> 1139655.5 | BP13: =IF(BX13>0,IF(G13="HKD",AG13,BX13*$F$5),0) -> 3418966.6 | BV13: 3984600.4 | BW13: 996150.1 | BX13: 2988450.3 | CC13: 540000 | CD13: =G13 -> USD | CE13: =H13-CC13 -> 360000 | CF13: =CE13*I13 -> 2818404 | CG13: =CF13/$F$5 -> 2463510.6
A14: 4 | B14: 上海澄明则正律师事务所 | C14: CM Law Firm | D14: Legal Advisors to the Company As to PRC laws | F14: 480000 | G14: RMB | H14: 1200000 | I14: =IF(G14="HKD",$F$3,IF(G14="USD",$F$4,IF(G14="RMB",$F$5,""))) -> 1.14406 | J14: =I14*E14 -> 0 | K14: =I14*F14 -> 549148.82 | L14: =I14*H14 -> 1372872 | N14: =L14 -> 1372872 | P14: =L14 -> 1372872 | R14: =L14 -> 1372872 | T14: =L14 -> 1372872 | V14: =L14 -> 1372872 | X14: =L14 -> 1372872 | Z14: 0.25 | AA14: =1-Z14 -> 0.75 | AC14: =Z14*N14 -> 343218.01 | AD14: =AA14*N14 -> 1029654 | AF14: =Z14*P14 -> 343218.01 | AG14: =AA14*P14 -> 1029654 | AI14: =Z14*R14 -> 343218.01 | AJ14: =AA14*R14 -> 1029654 | AL14: =Z14 -> 0.25 | AM14: =1-AL14 -> 0.75 | AO14: =AL14*T14 -> 343218.01 | AP14: =AM14*T14 -> 1029654 | AR14: =AL14*V14 -> 343218.01 | AS14: =AM14*V14 -> 1029654 | AU14: =AL14*X14 -> 343218.01 | AV14: =AM14*X14 -> 1029654 | AY14: 0 | AZ14: 0 | BB14: =AF14-AY14 -> 343218.01 | BC14: =AG14-AZ14 -> 1029654 | BE14: 0 | BF14: 0 | BH14: =AR14-BE14 -> 343218.01 | BI14: =AS14-BF14 -> 1029654 | BN14: =IF(BV14>0,IF(G14="HKD",H14,BV14*$F$5),0) -> 299352.47 | BO14: =IF(BW14>0,IF(G14="HKD",AF14,BW14*$F$5),0) -> 74838.118 | BP14: =IF(BX14>0,IF(G14="HKD",AG14,BX14*$F$5),0) -> 224514.36 | BV14: 261658.01 | BW14: 65414.503 | BX14: 196243.51 | CC14: 480000 | CD14: =G14 -> RMB | CE14: =H14-CC14 -> 720000 | CF14: =CE14*I14 -> 823723.23 | CG14: =CF14/$F$5 -> 720000
A15: 5 | B15: 君合律师事务所 | C15: Jun He Law Offices | D15: Legal Advisors to the Joint Sponsors and Underwriters As to Hong Kong laws | F15: 280000 | G15: USD | H15: 700000 | I15: =IF(G15="HKD",$F$3,IF(G15="USD",$F$4,IF(G15="RMB",$F$5,""))) -> 7.8289 | J15: =I15*E15 -> 0 | K15: =I15*F15 -> 2192092 | L15: =I15*H15 -> 5480230 | N15: =L15 -> 5480230 | P15: =L15 -> 5480230 | R15: =L15 -> 5480230 | T15: =L15 -> 5480230 | V15: =L15 -> 5480230 | X15: =L15 -> 5480230 | Z15: 0.25 | AA15: =1-Z15 -> 0.75 | AC15: =Z15*N15 -> 1370057.5 | AD15: =AA15*N15 -> 4110172.5 | AF15: =Z15*P15 -> 1370057.5 | AG15: =AA15*P15 -> 4110172.5 | AI15: =Z15*R15 -> 1370057.5 | AJ15: =AA15*R15 -> 4110172.5 | AL15: =Z15 -> 0.25 | AM15: =1-AL15 -> 0.75 | AO15: =AL15*T15 -> 1370057.5 | AP15: =AM15*T15 -> 4110172.5 | AR15: =AL15*V15 -> 1370057.5 | AS15: =AM15*V15 -> 4110172.5 | AU15: =AL15*X15 -> 1370057.5 | AV15: =AM15*X15 -> 4110172.5 | AY15: 0 | AZ15: 0 | BB15: =AF15-AY15 -> 1370057.5 | BC15: =AG15-AZ15 -> 4110172.5 | BE15: 0 | BF15: 0 | BH15: =AR15-BE15 -> 1370057.5 | BI15: =AS15-BF15 -> 4110172.5 | BN15: =IF(BV15>0,IF(G15="HKD",H15,BV15*$F$5),0) -> 2674070.2 | BO15: =IF(BW15>0,IF(G15="HKD",AF15,BW15*$F$5),0) -> 668517.55 | BP15: =IF(BX15>0,IF(G15="HKD",AG15,BX15*$F$5),0) -> 2005552.6 | BV15: 2337351.3 | BW15: 584337.82 | BX15: 1753013.5 | CC15: 280000 | CD15: =G15 -> USD | CE15: =H15-CC15 -> 420000 | CF15: =CE15*I15 -> 3288138 | CG15: =CF15/$F$5 -> 2874095.7
A16: 6 | B16: 北京市君合律师事务所 | C16: JunHe LLP | D16: Legal Advisors to the Joint Sponsors and Underwriters As to PRC laws | F16: 240000 | G16: RMB | H16: 1200000 | I16: =IF(G16="HKD",$F$3,IF(G16="USD",$F$4,IF(G16="RMB",$F$5,""))) -> 1.14406 | J16: =I16*E16 -> 0 | K16: =I16*F16 -> 274574.41 | L16: =I16*H16 -> 1372872 | N16: =L16 -> 1372872 | P16: =L16 -> 1372872 | R16: =L16 -> 1372872 | T16: =L16 -> 1372872 | V16: =L16 -> 1372872 | X16: =L16 -> 1372872 | Z16: 0.25 | AA16: =1-Z16 -> 0.75 | AC16: =Z16*N16 -> 343218.01 | AD16: =AA16*N16 -> 1029654 | AF16: =Z16*P16 -> 343218.01 | AG16: =AA16*P16 -> 1029654 | AI16: =Z16*R16 -> 343218.01 | AJ16: =AA16*R16 -> 1029654 | AL16: =Z16 -> 0.25 | AM16: =1-AL16 -> 0.75 | AO16: =AL16*T16 -> 343218.01 | AP16: =AM16*T16 -> 1029654 | AR16: =AL16*V16 -> 343218.01 | AS16: =AM16*V16 -> 1029654 | AU16: =AL16*X16 -> 343218.01 | AV16: =AM16*X16 -> 1029654 | AY16: 0 | AZ16: 0 | BB16: =AF16-AY16 -> 343218.01 | BC16: =AG16-AZ16 -> 1029654 | BE16: 0 | BF16: 0 | BH16: =AR16-BE16 -> 343218.01 | BI16: =AS16-BF16 -> 1029654 | BN16: =IF(BV16>0,IF(G16="HKD",H16,BV16*$F$5),0) -> 609726.73 | BO16: =IF(BW16>0,IF(G16="HKD",AF16,BW16*$F$5),0) -> 152431.68 | BP16: =IF(BX16>0,IF(G16="HKD",AG16,BX16*$F$5),0) -> 457295.05 | BV16: 532949.94 | BW16: 133237.48 | BX16: 399712.45 | CC16: 480000 | CD16: =G16 -> RMB | CE16: =H16-CC16 -> 720000 | CF16: =CE16*I16 -> 823723.23 | CG16: =CF16/$F$5 -> 720000
A17: 7 | B17: 毕马威华振会计师事务所(特殊普通合伙)南京分所 | C17: KPMG | D17: Auditor and Reporting Accountants | F17: 300000 | G17: RMB | H17: 5500000 | I17: =IF(G17="HKD",$F$3,IF(G17="USD",$F$4,IF(G17="RMB",$F$5,""))) -> 1.14406 | J17: =I17*E17 -> 0 | K17: =I17*F17 -> 343218.01 | L17: =I17*H17 -> 6292330.2 | N17: =L17 -> 6292330.2 | P17: =L17 -> 6292330.2 | R17: =L17 -> 6292330.2 | T17: =L17 -> 6292330.2 | V17: =L17 -> 6292330.2 | X17: =L17 -> 6292330.2 | Z17: 0.25 | AA17: =1-Z17 -> 0.75 | AC17: =Z17*N17 -> 1573082.6 | AD17: =AA17*N17 -> 4719247.7 | AF17: =Z17*P17 -> 1573082.6 | AG17: =AA17*P17 -> 4719247.7 | AI17: =Z17*R17 -> 1573082.6 | AJ17: =AA17*R17 -> 4719247.7 | AL17: =Z17 -> 0.25 | AM17: =1-AL17 -> 0.75 | AO17: =AL17*T17 -> 1573082.6 | AP17: =AM17*T17 -> 4719247.7 | AR17: =AL17*V17 -> 1573082.6 | AS17: =AM17*V17 -> 4719247.7 | AU17: =AL17*X17 -> 1573082.6 | AV17: =AM17*X17 -> 4719247.7 | AY17: 0 | AZ17: 0 | BB17: =AF17-AY17 -> 1573082.6 | BC17: =AG17-AZ17 -> 4719247.7 | BE17: 0 | BF17: 0 | BH17: =AR17-BE17 -> 1573082.6 | BI17: =AS17-BF17 -> 4719247.7 | BK17: =BS17*$F$5 -> 1304228.4 | BN17: =IF(BV17>0,IF(G17="HKD",H17,BV17*$F$5),0) -> 5302310.8 | BO17: =IF(BW17>0,IF(G17="HKD",AF17,BW17*$F$5),0) -> 1405035.9 | BP17: =IF(BX17>0,IF(G17="HKD",AG17,BX17*$F$5),0) -> 3897274.9 | BS17: 1140000 | BU17: 1140000 | BV17: 4634643.8 | BW17: 1228113.8 | BX17: 3406530 | CC17: 4600000 | CD17: =G17 -> RMB | CE17: =H17-CC17 -> 900000 | CF17: =CE17*I17 -> 1029654 | CG17: =CF17/$F$5 -> 900000
A18: 8 | B18: 毕马威企业咨询（中国）有限公司北京分公司 | C18: KPMG | D18: Internal control consultant | F18: 350000 | G18: RMB | H18: 350000 | I18: =IF(G18="HKD",$F$3,IF(G18="USD",$F$4,IF(G18="RMB",$F$5,""))) -> 1.14406 | J18: =I18*E18 -> 0 | K18: =I18*F18 -> 400421.01 | L18: =I18*H18 -> 400421.01 | N18: =L18 -> 400421.01 | P18: =L18 -> 400421.01 | R18: =L18 -> 400421.01 | T18: =L18 -> 400421.01 | V18: =L18 -> 400421.01 | X18: =L18 -> 400421.01 | Z18: 0.25 | AA18: =1-Z18 -> 0.75 | AC18: =Z18*N18 -> 100105.25 | AD18: =AA18*N18 -> 300315.76 | AF18: =Z18*P18 -> 100105.25 | AG18: =AA18*P18 -> 300315.76 | AI18: =Z18*R18 -> 100105.25 | AJ18: =AA18*R18 -> 300315.76 | AL18: =Z18 -> 0.25 | AM18: =1-AL18 -> 0.75 | AO18: =AL18*T18 -> 100105.25 | AP18: =AM18*T18 -> 300315.76 | AR18: =AL18*V18 -> 100105.25 | AS18: =AM18*V18 -> 300315.76 | AU18: =AL18*X18 -> 100105.25 | AV18: =AM18*X18 -> 300315.76 | AY18: 0 | AZ18: 0 | BB18: =AF18-AY18 -> 100105.25 | BC18: =AG18-AZ18 -> 300315.76 | BE18: 0 | BF18: 0 | BH18: =AR18-BE18 -> 100105.25 | BI18: =AS18-BF18 -> 300315.76 | BN18: =IF(BV18>0,IF(G18="HKD",H18,BV18*$F$5),0) -> 403324.07 | BO18: =IF(BW18>0,IF(G18="HKD",AF18,BW18*$F$5),0) -> 100831.02 | BP18: =IF(BX18>0,IF(G18="HKD",AG18,BX18*$F$5),0) -> 302493.05 | BV18: 352537.5 | BW18: 88134.375 | BX18: 264403.12 | CC18: 350000 | CD18: =G18 -> RMB | CE18: =H18-CC18 -> 0 | CF18: =CE18*I18 -> 0 | CG18: =CF18/$F$5 -> 0
A19: 9 | B19: 毕马威华振会计师事务所（特殊普通合伙） | C19: KPMG | D19: IT Audit | F19: 600000 | G19: RMB | H19: 600000 | I19: =IF(G19="HKD",$F$3,IF(G19="USD",$F$4,IF(G19="RMB",$F$5,""))) -> 1.14406 | J19: =I19*E19 -> 0 | K19: =I19*F19 -> 686436.02 | L19: =I19*H19 -> 686436.02 | N19: =L19 -> 686436.02 | P19: =L19 -> 686436.02 | R19: =L19 -> 686436.02 | T19: =L19 -> 686436.02 | V19: =L19 -> 686436.02 | X19: =L19 -> 686436.02 | Z19: 0.25 | AA19: =1-Z19 -> 0.75 | AC19: =Z19*N19 -> 171609.01 | AD19: =AA19*N19 -> 514827.02 | AF19: =Z19*P19 -> 171609.01 | AG19: =AA19*P19 -> 514827.02 | AI19: =Z19*R19 -> 171609.01 | AJ19: =AA19*R19 -> 514827.02 | AL19: =Z19 -> 0.25 | AM19: =1-AL19 -> 0.75 | AO19: =AL19*T19 -> 171609.01 | AP19: =AM19*T19 -> 514827.02 | AR19: =AL19*V19 -> 171609.01 | AS19: =AM19*V19 -> 514827.02 | AU19: =AL19*X19 -> 171609.01 | AV19: =AM19*X19 -> 514827.02 | AY19: 0 | AZ19: 0 | BB19: =AF19-AY19 -> 171609.01 | BC19: =AG19-AZ19 -> 514827.02 | BE19: 0 | BF19: 0 | BH19: =AR19-BE19 -> 171609.01 | BI19: =AS19-BF19 -> 514827.02 | BN19: =IF(BV19>0,IF(G19="HKD",H19,BV19*$F$5),0) -> 424547.88 | BO19: =IF(BW19>0,IF(G19="HKD",AF19,BW19*$F$5),0) -> 106136.97 | BP19: =IF(BX19>0,IF(G19="HKD",AG19,BX19*$F$5),0) -> 318410.91 | BV19: 371088.81 | BW19: 92772.202 | BX19: 278316.61 | CC19: 360000 | CD19: =G19 -> RMB | CE19: =H19-CC19 -> 240000 | CF19: =CE19*I19 -> 274574.41 | CG19: =CF19/$F$5 -> 240000
A20: 10 | B20: 灼识企业管理咨询(上海)有限公司 | C20: China Insights Industry Consultancy Limited | D20: Industry consultant | E20: 200000 | F20: 300000 | G20: RMB | H20: 500000 | I20: =IF(G20="HKD",$F$3,IF(G20="USD",$F$4,IF(G20="RMB",$F$5,""))) -> 1.14406 | J20: =I20*E20 -> 228812.01 | K20: =I20*F20 -> 343218.01 | L20: =I20*H20 -> 572030.02 | N20: =L20 -> 572030.02 | P20: =L20 -> 572030.02 | R20: =L20 -> 572030.02 | T20: =L20 -> 572030.02 | V20: =L20 -> 572030.02 | X20: =L20 -> 572030.02 | Z20: 0.25 | AA20: =1-Z20 -> 0.75 | AC20: =Z20*N20 -> 143007.51 | AD20: =AA20*N20 -> 429022.52 | AF20: =Z20*P20 -> 143007.51 | AG20: =AA20*P20 -> 429022.52 | AI20: =Z20*R20 -> 143007.51 | AJ20: =AA20*R20 -> 429022.52 | AL20: =Z20 -> 0.25 | AM20: =1-AL20 -> 0.75 | AO20: =AL20*T20 -> 143007.51 | AP20: =AM20*T20 -> 429022.52 | AR20: =AL20*V20 -> 143007.51 | AS20: =AM20*V20 -> 429022.52 | AU20: =AL20*X20 -> 143007.51 | AV20: =AM20*X20 -> 429022.52 | AY20: 0 | AZ20: 0 | BB20: =AF20-AY20 -> 143007.51 | BC20: =AG20-AZ20 -> 429022.52 | BE20: 0 | BF20: 0 | BH20: =AR20-BE20 -> 143007.51 | BI20: =AS20-BF20 -> 429022.52 | BN20: =IF(BV20>0,IF(G20="HKD",H20,BV20*$F$5),0) -> 486454.33 | BO20: =IF(BW20>0,IF(G20="HKD",AF20,BW20*$F$5),0) -> 121613.58 | BP20: =IF(BX20>0,IF(G20="HKD",AG20,BX20*$F$5),0) -> 364840.75 | BV20: 425200 | BW20: 106300 | BX20: 318900 | CC20: 400000 | CD20: =G20 -> RMB | CE20: =H20-CC20 -> 100000 | CF20: =CE20*I20 -> 114406 | CG20: =CF20/$F$5 -> 100000
A21: 11 | B21: 奥盈财经印刷有限公司 | C21: Orange Financial Printing | D21: Financial printer | E21: 763623 | F21: 545445 | G21: HKD | H21: =2181780+60000 -> 2241780 | I21: =IF(G21="HKD",$F$3,IF(G21="USD",$F$4,IF(G21="RMB",$F$5,""))) -> 1 | J21: =I21*E21 -> 763623 | K21: =I21*F21 -> 545445 | L21: =I21*H21 -> 2241780 | N21: =L21 -> 2241780 | P21: =L21 -> 2241780 | R21: =L21 -> 2241780 | T21: =L21 -> 2241780 | V21: =L21 -> 2241780 | X21: =L21 -> 2241780 | Z21: 0.25 | AA21: =1-Z21 -> 0.75 | AC21: =Z21*N21 -> 560445 | AD21: =AA21*N21 -> 1681335 | AF21: =Z21*P21 -> 560445 | AG21: =AA21*P21 -> 1681335 | AI21: =Z21*R21 -> 560445 | AJ21: =AA21*R21 -> 1681335 | AL21: =Z21 -> 0.25 | AM21: =1-AL21 -> 0.75 | AO21: =AL21*T21 -> 560445 | AP21: =AM21*T21 -> 1681335 | AR21: =AL21*V21 -> 560445 | AS21: =AM21*V21 -> 1681335 | AU21: =AL21*X21 -> 560445 | AV21: =AM21*X21 -> 1681335 | AY21: 0 | AZ21: 0 | BB21: =AF21-AY21 -> 560445 | BC21: =AG21-AZ21 -> 1681335 | BE21: 0 | BF21: 0 | BH21: =AR21-BE21 -> 560445 | BI21: =AS21-BF21 -> 1681335 | BN21: =1309068+77931.97/$F$5 -> 1377186.8 | BO21: =BN21*0.25 -> 344296.69 | BP21: =BN21*0.75 -> 1032890.1 | BV21: 1311333.3 | BW21: 327833.32 | BX21: 983499.97 | CC21: 1309068 | CD21: =G21 -> HKD | CE21: =H21-CC21 -> 932712 | CF21: =CE21*I21 -> 932712 | CG21: =CF21/$F$5 -> 815264.9
A22: 12 | B22: 上海澄明则正律师事务所 | C22: CM Law Firm | D22: Legal Advisors to the Company As to PRC laws in respect of data compliance | F22: 180000 | G22: RMB | H22: 300000 | I22: =IF(G22="HKD",$F$3,IF(G22="USD",$F$4,IF(G22="RMB",$F$5,""))) -> 1.14406 | J22: =I22*E22 -> 0 | K22: =I22*F22 -> 205930.81 | L22: =I22*H22 -> 343218.01 | N22: =L22 -> 343218.01 | P22: =L22 -> 343218.01 | R22: =L22 -> 343218.01 | T22: =L22 -> 343218.01 | V22: =L22 -> 343218.01 | X22: =L22 -> 343218.01 | Z22: 0.25 | AA22: =1-Z22 -> 0.75 | AC22: =Z22*N22 -> 85804.503 | AD22: =AA22*N22 -> 257413.51 | AF22: =Z22*P22 -> 85804.503 | AG22: =AA22*P22 -> 257413.51 | AI22: =Z22*R22 -> 85804.503 | AJ22: =AA22*R22 -> 257413.51 | AL22: =Z22 -> 0.25 | AM22: =1-AL22 -> 0.75 | AO22: =AL22*T22 -> 85804.503 | AP22: =AM22*T22 -> 257413.51 | AR22: =AL22*V22 -> 85804.503 | AS22: =AM22*V22 -> 257413.51 | AU22: =AL22*X22 -> 85804.503 | AV22: =AM22*X22 -> 257413.51 | AY22: 0 | AZ22: 0 | BB22: =AF22-AY22 -> 85804.503 | BC22: =AG22-AZ22 -> 257413.51 | BE22: 0 | BF22: 0 | BH22: =AR22-BE22 -> 85804.503 | BI22: =AS22-BF22 -> 257413.51 | BN22: =IF(BV22>0,IF(G22="HKD",H22,BV22*$F$5),0) -> 324928.4 | BO22: =IF(BW22>0,IF(G22="HKD",AF22,BW22*$F$5),0) -> 81232.101 | BP22: =IF(BX22>0,IF(G22="HKD",AG22,BX22*$F$5),0) -> 243696.3 | BV22: 284013.42 | BW22: 71003.355 | BX22: 213010.07 | CC22: 240000 | CD22: =G22 -> RMB | CE22: =H22-CC22 -> 60000 | CF22: =CE22*I22 -> 68643.602 | CG22: =CF22/$F$5 -> 60000
A23: 13 | B23: 北京采安律师事务所 | C23: Arthur CHIU | D23: Legal Advisors to the Company As to International Sanctions | F23: 288000 | G23: RMB | H23: =360000+70000 -> 430000 | I23: =IF(G23="HKD",$F$3,IF(G23="USD",$F$4,IF(G23="RMB",$F$5,""))) -> 1.14406 | J23: =I23*E23 -> 0 | K23: =I23*F23 -> 329489.29 | L23: =I23*H23 -> 491945.82 | N23: =L23 -> 491945.82 | P23: =L23 -> 491945.82 | R23: =L23 -> 491945.82 | T23: =L23 -> 491945.82 | V23: =L23 -> 491945.82 | X23: =L23 -> 491945.82 | Z23: 0.25 | AA23: =1-Z23 -> 0.75 | AC23: =Z23*N23 -> 122986.45 | AD23: =AA23*N23 -> 368959.36 | AF23: =Z23*P23 -> 122986.45 | AG23: =AA23*P23 -> 368959.36 | AI23: =Z23*R23 -> 122986.45 | AJ23: =AA23*R23 -> 368959.36 | AL23: =Z23 -> 0.25 | AM23: =1-AL23 -> 0.75 | AO23: =AL23*T23 -> 122986.45 | AP23: =AM23*T23 -> 368959.36 | AR23: =AL23*V23 -> 122986.45 | AS23: =AM23*V23 -> 368959.36 | AU23: =AL23*X23 -> 122986.45 | AV23: =AM23*X23 -> 368959.36 | AY23: 0 | AZ23: 0 | BB23: =AF23-AY23 -> 122986.45 | BC23: =AG23-AZ23 -> 368959.36 | BE23: 0 | BF23: 0 | BH23: =AR23-BE23 -> 122986.45 | BI23: =AS23-BF23 -> 368959.36 | BN23: =IF(BV23>0,IF(G23="HKD",H23,BV23*$F$5),0) -> 310838.96 | BO23: =IF(BW23>0,IF(G23="HKD",AF23,BW23*$F$5),0) -> 77709.741 | BP23: =IF(BX23>0,IF(G23="HKD",AG23,BX23*$F$5),0) -> 233129.22 | BV23: 271698.12 | BW23: 67924.53 | BX23: 203773.59 | CC23: 288000 | CD23: =G23 -> RMB | CE23: =H23-CC23 -> 142000 | CF23: =CE23*I23 -> 162456.53 | CG23: =CF23/$F$5 -> 142000
A24: 14 | B24: 汇华商业资讯有限公司 | C24: Central Business Information Limited | D24: Background search | E24: 65500 | F24: 17837 | G24: USD | H24: =83337+9000 -> 92337 | I24: =IF(G24="HKD",$F$3,IF(G24="USD",$F$4,IF(G24="RMB",$F$5,""))) -> 7.8289 | J24: =I24*E24 -> 512792.95 | K24: =I24*F24 -> 139644.09 | L24: =H24*I24 -> 722897.14 | N24: =L24 -> 722897.14 | P24: =L24 -> 722897.14 | R24: =L24 -> 722897.14 | T24: =L24 -> 722897.14 | V24: =L24 -> 722897.14 | X24: =L24 -> 722897.14 | Z24: 0.25 | AA24: =1-Z24 -> 0.75 | AC24: =Z24*N24 -> 180724.28 | AD24: =AA24*N24 -> 542172.85 | AF24: =Z24*P24 -> 180724.28 | AG24: =AA24*P24 -> 542172.85 | AI24: =Z24*R24 -> 180724.28 | AJ24: =AA24*R24 -> 542172.85 | AL24: =Z24 -> 0.25 | AM24: =1-AL24 -> 0.75 | AO24: =AL24*T24 -> 180724.28 | AP24: =AM24*T24 -> 542172.85 | AR24: =AL24*V24 -> 180724.28 | AS24: =AM24*V24 -> 542172.85 | AU24: =AL24*X24 -> 180724.28 | AV24: =AM24*X24 -> 542172.85 | AY24: 0 | AZ24: 0 | BB24: =AF24-AY24 -> 180724.28 | BC24: =AG24-AZ24 -> 542172.85 | BE24: 0 | BF24: 0 | BH24: =AR24-BE24 -> 180724.28 | BI24: =AS24-BF24 -> 542172.85 | BN24: =IF(BV24>0,IF(G24="HKD",H24,BV24*$F$5),0) -> 626101.73 | BO24: =IF(BW24>0,IF(G24="HKD",AF24,BW24*$F$5),0) -> 156525.43 | BP24: =IF(BX24>0,IF(G24="HKD",AG24,BX24*$F$5),0) -> 469576.3 | BV24: 547263 | BW24: 136815.75 | BX24: 410447.25 | CC24: 91051.83 | CD24: =G24 -> USD | CE24: =H24-CC24 -> 1285.17 | CF24: =CE24*I24 -> 10061.467 | CG24: =CF24/$F$5 -> 8794.5274
A25: 15 | B25: 惠悦公共关系顾问集团有限公司 | C25: Intelligent Joy | D25: PR company | F25: 26400 | G25: RMB | H25: 88000 | I25: =IF(G25="HKD",$F$3,IF(G25="USD",$F$4,IF(G25="RMB",$F$5,""))) -> 1.14406 | J25: =I25*E25 -> 0 | K25: =I25*F25 -> 30203.185 | L25: =H25*I25 -> 100677.28 | N25: =L25 -> 100677.28 | P25: =L25 -> 100677.28 | R25: =L25 -> 100677.28 | T25: =L25 -> 100677.28 | V25: =L25 -> 100677.28 | X25: =L25 -> 100677.28 | Z25: 0 | AA25: =1-Z25 -> 1 | AC25: =Z25*N25 -> 0 | AD25: =AA25*N25 -> 100677.28 | AF25: =Z25*P25 -> 0 | AG25: =AA25*P25 -> 100677.28 | AI25: =Z25*R25 -> 0 | AJ25: =AA25*R25 -> 100677.28 | AL25: =Z25 -> 0 | AM25: =1-AL25 -> 1 | AO25: =AL25*T25 -> 0 | AP25: =AM25*T25 -> 100677.28 | AR25: =AL25*V25 -> 0 | AS25: =AM25*V25 -> 100677.28 | AU25: =AL25*X25 -> 0 | AV25: =AM25*X25 -> 100677.28 | AY25: 0 | AZ25: 0 | BB25: =AF25-AY25 -> 0 | BC25: =AG25-AZ25 -> 100677.28 | BE25: 0 | BF25: 0 | BH25: =AR25-BE25 -> 0 | BI25: =AS25-BF25 -> 100677.28 | BN25: =IF(BV25>0,IF(G25="HKD",H25,BV25*$F$5),0) -> 29904.139 | BO25: =IF(BW25>0,IF(G25="HKD",AF25,BW25*$F$5),0) -> 7476.0348 | BP25: =IF(BX25>0,IF(G25="HKD",AG25,BX25*$F$5),0) -> 22428.104 | BV25: 26138.61 | BW25: 6534.6525 | BX25: 19603.958 | CC25: 26400 | CD25: =G25 -> RMB | CE25: =H25-CC25 -> 61600 | CF25: =CE25*I25 -> 70474.098 | CG25: =CF25/$F$5 -> 61600
A26: 16 | C26: TMF Hong Kong Limited | D26: Company Secretary | G26: HKD | H26: 12000 | I26: =IF(G26="HKD",$F$3,IF(G26="USD",$F$4,IF(G26="RMB",$F$5,""))) -> 1 | J26: =I26*E26 -> 0 | K26: =I26*F26 -> 0 | L26: =H26*I26 -> 12000 | N26: =L26 -> 12000 | P26: =L26 -> 12000 | R26: =L26 -> 12000 | T26: =L26 -> 12000 | V26: =L26 -> 12000 | X26: =L26 -> 12000 | Z26: 0 | AA26: =1-Z26 -> 1 | AC26: =Z26*N26 -> 0 | AD26: =AA26*N26 -> 12000 | AF26: =Z26*P26 -> 0 | AG26: =AA26*P26 -> 12000 | AI26: =Z26*R26 -> 0 | AJ26: =AA26*R26 -> 12000 | AL26: =Z26 -> 0 | AM26: =1-AL26 -> 1 | AO26: =AL26*T26 -> 0 | AP26: =AM26*T26 -> 12000 | AR26: =AL26*V26 -> 0 | AS26: =AM26*V26 -> 12000 | AU26: =AL26*X26 -> 0 | AV26: =AM26*X26 -> 12000 | AY26: 0 | AZ26: 0 | BB26: =AF26-AY26 -> 0 | BC26: =AG26-AZ26 -> 12000 | BE26: 0 | BF26: 0 | BH26: =AR26-BE26 -> 0 | BI26: =AS26-BF26 -> 12000 | BN26: =IF(BV26>0,IF(G26="HKD",H26,BV26*$F$5),0) -> 0 | BO26: =IF(BW26>0,IF(G26="HKD",AF26,BW26*$F$5),0) -> 0 | BP26: =IF(BX26>0,IF(G26="HKD",AG26,BX26*$F$5),0) -> 0 | CD26: =G26 -> HKD | CE26: =H26-CC26 -> 12000 | CF26: =CE26*I26 -> 12000 | CG26: =CF26/$F$5 -> 10488.96
A27: 17 | B27: 卓佳证券登记有限公司 | C27: Vistra | D27: Hong Kong Share Registrar | G27: HKD | H27: 80000 | I27: =IF(G27="HKD",$F$3,IF(G27="USD",$F$4,IF(G27="RMB",$F$5,""))) -> 1 | J27: =I27*E27 -> 0 | K27: =I27*F27 -> 0 | L27: =I27*H27 -> 80000 | N27: =L27 -> 80000 | P27: =L27 -> 80000 | R27: =L27 -> 80000 | T27: =L27 -> 80000 | V27: =L27 -> 80000 | X27: =L27 -> 80000 | Z27: 0 | AA27: =1-Z27 -> 1 | AC27: =Z27*N27 -> 0 | AD27: =AA27*N27 -> 80000 | AF27: =Z27*P27 -> 0 | AG27: =AA27*P27 -> 80000 | AI27: =Z27*R27 -> 0 | AJ27: =AA27*R27 -> 80000 | AL27: =Z27 -> 0 | AM27: =1-AL27 -> 1 | AO27: =AL27*T27 -> 0 | AP27: =AM27*T27 -> 80000 | AR27: =AL27*V27 -> 0 | AS27: =AM27*V27 -> 80000 | AU27: =AL27*X27 -> 0 | AV27: =AM27*X27 -> 80000 | AY27: 0 | AZ27: 0 | BB27: =AF27-AY27 -> 0 | BC27: =AG27-AZ27 -> 80000 | BE27: 0 | BF27: 0 | BH27: =AR27-BE27 -> 0 | BI27: =AS27-BF27 -> 80000 | BN27: =IF(BV27>0,IF(G27="HKD",H27,BV27*$F$5),0) -> 0 | BO27: =IF(BW27>0,IF(G27="HKD",AF27,BW27*$F$5),0) -> 0 | BP27: =IF(BX27>0,IF(G27="HKD",AG27,BX27*$F$5),0) -> 0 | CD27: =G27 -> HKD | CE27: =H27-CC27 -> 80000 | CF27: =CE27*I27 -> 80000 | CG27: =CF27/$F$5 -> 69926.4
A28: 18 | C28: Underwriters | D28: Underwriting Commission (3.5% of gross proceeds) | G28: HKD | H28: 0.035 | I28: =IF(G28="HKD",$F$3,IF(G28="USD",$F$4,IF(G28="RMB",$F$5,""))) -> 1 | J28: =I28*E28 -> 0 | K28: =I28*F28 -> 0 | L28: =P28 -> 48895557 | N28: =N10*$L$3*$H$28 -> 44101875 | P28: =P10*$L$3*$H$28 -> 48895557 | R28: =R10*$L$3*$H$28 -> 53689239 | T28: =$L$5*$H28*T$10 -> 50717040 | V28: =$L$5*$H28*V$10 -> 56229762 | X28: =$L$5*$H28*X$10 -> 61742484 | Z28: 1 | AA28: =1-Z28 -> 0 | AC28: =Z28*N28 -> 44101875 | AD28: =AA28*N28 -> 0 | AF28: =Z28*P28 -> 48895557 | AG28: =AA28*P28 -> 0 | AI28: =Z28*R28 -> 53689239 | AJ28: =AA28*R28 -> 0 | AL28: =Z28 -> 1 | AM28: =1-AL28 -> 0 | AO28: =AL28*T28 -> 50717040 | AP28: =AM28*T28 -> 0 | AR28: =AL28*V28 -> 56229762 | AS28: =AM28*V28 -> 0 | AU28: =AL28*X28 -> 61742484 | AV28: =AM28*X28 -> 0 | AY28: 0 | AZ28: 0 | BB28: =AF28-AY28 -> 48895557 | BC28: =AG28-AZ28 -> 0 | BE28: 0 | BF28: 0 | BH28: =AR28-BE28 -> 56229762 | BI28: =AS28-BF28 -> 0 | BN28: =IF(BV28>0,IF(G28="HKD",H28,BV28*$F$5),0) -> 0 | BO28: =IF(BW28>0,IF(G28="HKD",AF28,BW28*$F$5),0) -> 0 | BP28: =IF(BX28>0,IF(G28="HKD",AG28,BX28*$F$5),0) -> 0 | CD28: =G28 -> HKD | CE28: =H28-CC28 -> 0.035 | CF28: =CE28*I28 -> 0.035 | CG28: =CF28/$F$5 -> 0.0305928
A29: 19 | C29: Underwriters | D29: Incenive fee (1% of gross proceeds) | G29: HKD | H29: 0.01 | I29: =IF(G29="HKD",$F$3,IF(G29="USD",$F$4,IF(G29="RMB",$F$5,""))) -> 1 | J29: =I29*E29 -> 0 | K29: =I29*F29 -> 0 | L29: =P29 -> 13970159 | N29: =N10*$L$3*$H$29 -> 12600536 | P29: =P10*$L$3*$H$29 -> 13970159 | R29: =R10*$L$3*$H$29 -> 15339783 | T29: =$L$5*$H29*T$10 -> 14490583 | V29: =$L$5*$H29*V$10 -> 16065646 | X29: =$L$5*$H29*X$10 -> 17640710 | Z29: 1 | AA29: =1-Z29 -> 0 | AC29: =Z29*N29 -> 12600536 | AD29: =AA29*N29 -> 0 | AF29: =Z29*P29 -> 13970159 | AG29: =AA29*P29 -> 0 | AI29: =Z29*R29 -> 15339783 | AJ29: =AA29*R29 -> 0 | AL29: =Z29 -> 1 | AM29: =1-AL29 -> 0 | AO29: =AL29*T29 -> 14490583 | AP29: =AM29*T29 -> 0 | AR29: =AL29*V29 -> 16065646 | AS29: =AM29*V29 -> 0 | AU29: =AL29*X29 -> 17640710 | AV29: =AM29*X29 -> 0 | AY29: 0 | AZ29: 0 | BB29: =AF29-AY29 -> 13970159 | BC29: =AG29-AZ29 -> 0 | BE29: 0 | BF29: 0 | BH29: =AR29-BE29 -> 16065646 | BI29: =AS29-BF29 -> 0 | BN29: =IF(BV29>0,IF(G29="HKD",H29,BV29*$F$5),0) -> 0 | BO29: =IF(BW29>0,IF(G29="HKD",AF29,BW29*$F$5),0) -> 0 | BP29: =IF(BX29>0,IF(G29="HKD",AG29,BX29*$F$5),0) -> 0 | CD29: =G29 -> HKD | CE29: =H29-CC29 -> 0.01 | CF29: =CE29*I29 -> 0.01 | CG29: =CF29/$F$5 -> 0.0087408
A30: 20 | C30: The Stock Exchange of Hong Kong Limited | D30: Initial listing fee | G30: HKD | H30: 650000 | I30: =IF(G30="HKD",$F$3,IF(G30="USD",$F$4,IF(G30="RMB",$F$5,""))) -> 1 | J30: =I30*E30 -> 0 | K30: =I30*F30 -> 0 | L30: =H30 -> 650000 | N30: =L30 -> 650000 | P30: =L30 -> 650000 | R30: =L30 -> 650000 | T30: =L30 -> 650000 | V30: =L30 -> 650000 | X30: =L30 -> 650000 | Z30: 0 | AA30: =1-Z30 -> 1 | AC30: =Z30*N30 -> 0 | AD30: =AA30*N30 -> 650000 | AF30: =Z30*P30 -> 0 | AG30: =AA30*P30 -> 650000 | AI30: =Z30*R30 -> 0 | AJ30: =AA30*R30 -> 650000 | AL30: =Z30 -> 0 | AM30: =1-AL30 -> 1 | AO30: =AL30*T30 -> 0 | AP30: =AM30*T30 -> 650000 | AR30: =AL30*V30 -> 0 | AS30: =AM30*V30 -> 650000 | AU30: =AL30*X30 -> 0 | AV30: =AM30*X30 -> 650000 | AY30: 0 | AZ30: 0 | BB30: =AF30-AY30 -> 0 | BC30: =AG30-AZ30 -> 650000 | BE30: 0 | BF30: 0 | BH30: =AR30-BE30 -> 0 | BI30: =AS30-BF30 -> 650000 | BN30: =IF(BV30>0,IF(G30="HKD",H30,BV30*$F$5),0) -> 650000 | BO30: =IF(BW30>0,IF(G30="HKD",AF30,BW30*$F$5),0) -> 0 | BP30: =IF(BX30>0,IF(G30="HKD",AG30,BX30*$F$5),0) -> 650000 | BV30: 595140 | BW30: 148785 | BX30: 446355 | CC30: 650000 | CD30: =G30 -> HKD | CE30: =H30-CC30 -> 0 | CF30: =CE30*I30 -> 0 | CG30: =CF30/$F$5 -> 0
A31: 21 | C31: The Stock Exchange of Hong Kong Limited | D31: Stock Exchange trading fee (0.00565%) | G31: HKD | H31: 5.65e-05 | I31: =IF(G31="HKD",$F$3,IF(G31="USD",$F$4,IF(G31="RMB",$F$5,""))) -> 1 | J31: =I31*E31 -> 0 | K31: =I31*F31 -> 0 | L31: =P31 -> 78931.399 | N31: =$L$3*$H$31*N$10 -> 71193.027 | P31: =$L$3*$H$31*P$10 -> 78931.399 | R31: =$L$3*$H$31*R$10 -> 86669.772 | T31: =$L$5*$H31*T$10 -> 81871.793 | V31: =$L$5*$H31*V$10 -> 90770.901 | X31: =$L$5*$H31*X$10 -> 99670.009 | Z31: 0 | AA31: =1-Z31 -> 1 | AC31: =Z31*N31 -> 0 | AD31: =AA31*N31 -> 71193.027 | AF31: =Z31*P31 -> 0 | AG31: =AA31*P31 -> 78931.399 | AI31: =Z31*R31 -> 0 | AJ31: =AA31*R31 -> 86669.772 | AL31: =Z31 -> 0 | AM31: =1-AL31 -> 1 | AO31: =AL31*T31 -> 0 | AP31: =AM31*T31 -> 81871.793 | AR31: =AL31*V31 -> 0 | AS31: =AM31*V31 -> 90770.901 | AU31: =AL31*X31 -> 0 | AV31: =AM31*X31 -> 99670.009 | AY31: 0 | AZ31: 0 | BB31: =AF31-AY31 -> 0 | BC31: =AG31-AZ31 -> 78931.399 | BE31: 0 | BF31: 0 | BH31: =AR31-BE31 -> 0 | BI31: =AS31-BF31 -> 90770.901 | BN31: =IF(BV31>0,IF(G31="HKD",H31,BV31*$F$5),0) -> 0 | BO31: =IF(BW31>0,IF(G31="HKD",AF31,BW31*$F$5),0) -> 0 | BP31: =IF(BX31>0,IF(G31="HKD",AG31,BX31*$F$5),0) -> 0 | CD31: =G31 -> HKD | CE31: =H31-CC31 -> 5.65e-05 | CF31: =CE31*I31 -> 5.65e-05 | CG31: =CF31/$F$5 -> 4.938552e-05
A32: 22 | C32: The Stock Exchange of Hong Kong Limited | D32: SFC transaction levy (0.0027%) | G32: HKD | H32: 2.7e-05 | I32: =IF(G32="HKD",$F$3,IF(G32="USD",$F$4,IF(G32="RMB",$F$5,""))) -> 1 | J32: =I32*E32 -> 0 | K32: =I32*F32 -> 0 | L32: =P32 -> 37719.43 | N32: =$L$3*$H$32*N$10 -> 34021.446 | P32: =$L$3*$H$32*P$10 -> 37719.43 | R32: =$L$3*$H$32*R$10 -> 41417.413 | T32: =$L$5*$H32*T$10 -> 39124.574 | V32: =$L$5*$H32*V$10 -> 43377.245 | X32: =$L$5*$H32*X$10 -> 47629.916 | Z32: 0 | AA32: =1-Z32 -> 1 | AC32: =Z32*N32 -> 0 | AD32: =AA32*N32 -> 34021.446 | AF32: =Z32*P32 -> 0 | AG32: =AA32*P32 -> 37719.43 | AI32: =Z32*R32 -> 0 | AJ32: =AA32*R32 -> 41417.413 | AL32: =Z32 -> 0 | AM32: =1-AL32 -> 1 | AO32: =AL32*T32 -> 0 | AP32: =AM32*T32 -> 39124.574 | AR32: =AL32*V32 -> 0 | AS32: =AM32*V32 -> 43377.245 | AU32: =AL32*X32 -> 0 | AV32: =AM32*X32 -> 47629.916 | AY32: 0 | AZ32: 0 | BB32: =AF32-AY32 -> 0 | BC32: =AG32-AZ32 -> 37719.43 | BE32: 0 | BF32: 0 | BH32: =AR32-BE32 -> 0 | BI32: =AS32-BF32 -> 43377.245 | BN32: =IF(BV32>0,IF(G32="HKD",H32,BV32*$F$5),0) -> 0 | BO32: =IF(BW32>0,IF(G32="HKD",AF32,BW32*$F$5),0) -> 0 | BP32: =IF(BX32>0,IF(G32="HKD",AG32,BX32*$F$5),0) -> 0 | CD32: =G32 -> HKD | CE32: =H32-CC32 -> 2.7e-05 | CF32: =CE32*I32 -> 2.7e-05 | CG32: =CF32/$F$5 -> 2.360016e-05
A33: 23 | C33: The Stock Exchange of Hong Kong Limited | D33: AFRC transaction levy (0.00015%) | G33: HKD | H33: 1.5e-06 | I33: =IF(G33="HKD",$F$3,IF(G33="USD",$F$4,IF(G33="RMB",$F$5,""))) -> 1 | J33: =I33*E33 -> 0 | K33: =I33*F33 -> 0 | L33: =P33 -> 2095.5239 | N33: =$L$3*$H$33*N$10 -> 1890.0804 | P33: =$L$3*$H$33*P$10 -> 2095.5239 | R33: =$L$3*$H$33*R$10 -> 2300.9674 | T33: =$L$5*$H33*T$10 -> 2173.5874 | V33: =$L$5*$H33*V$10 -> 2409.8469 | X33: =$L$5*$H33*X$10 -> 2646.1064 | Z33: 0 | AA33: =1-Z33 -> 1 | AC33: =Z33*N33 -> 0 | AD33: =AA33*N33 -> 1890.0804 | AF33: =Z33*P33 -> 0 | AG33: =AA33*P33 -> 2095.5239 | AI33: =Z33*R33 -> 0 | AJ33: =AA33*R33 -> 2300.9674 | AL33: =Z33 -> 0 | AM33: =1-AL33 -> 1 | AO33: =AL33*T33 -> 0 | AP33: =AM33*T33 -> 2173.5874 | AR33: =AL33*V33 -> 0 | AS33: =AM33*V33 -> 2409.8469 | AU33: =AL33*X33 -> 0 | AV33: =AM33*X33 -> 2646.1064 | AY33: 0 | AZ33: 0 | BB33: =AF33-AY33 -> 0 | BC33: =AG33-AZ33 -> 2095.5239 | BE33: 0 | BF33: 0 | BH33: =AR33-BE33 -> 0 | BI33: =AS33-BF33 -> 2409.8469 | BN33: =IF(BV33>0,IF(G33="HKD",H33,BV33*$F$5),0) -> 0 | BO33: =IF(BW33>0,IF(G33="HKD",AF33,BW33*$F$5),0) -> 0 | BP33: =IF(BX33>0,IF(G33="HKD",AG33,BX33*$F$5),0) -> 0 | CD33: =G33 -> HKD | CE33: =H33-CC33 -> 1.5e-06 | CF33: =CE33*I33 -> 1.5e-06 | CG33: =CF33/$F$5 -> 1.31112e-06
A34: 24 | C34: Others | D34: Contingent and miscellaneous expenses | G34: HKD | H34: =ROUNDUP(SUM(X11:X33)*0.1,-6) -> 13000000 | I34: =IF(G34="HKD",$F$3,IF(G34="USD",$F$4,IF(G34="RMB",$F$5,""))) -> 1 | J34: =I34*E34 -> 0 | K34: =I34*F34 -> 0 | L34: =H34*I34 -> 13000000 | N34: =L34 -> 13000000 | P34: =L34 -> 13000000 | R34: =L34 -> 13000000 | T34: =L34 -> 13000000 | V34: =L34 -> 13000000 | X34: =L34 -> 13000000 | Z34: 0.25 | AA34: =1-Z34 -> 0.75 | AC34: =Z34*N34 -> 3250000 | AD34: =AA34*N34 -> 9750000 | AF34: =Z34*P34 -> 3250000 | AG34: =AA34*P34 -> 9750000 | AI34: =Z34*R34 -> 3250000 | AJ34: =AA34*R34 -> 9750000 | AL34: 0 | AM34: =1-AL34 -> 1 | AO34: =AL34*T34 -> 0 | AP34: =AM34*T34 -> 13000000 | AR34: =AL34*V34 -> 0 | AS34: =AM34*V34 -> 13000000 | AU34: =AL34*X34 -> 0 | AV34: =AM34*X34 -> 13000000 | AY34: 0 | AZ34: 0 | BB34: =AF34-AY34 -> 3250000 | BC34: =AG34-AZ34 -> 9750000 | BE34: 0 | BF34: 0 | BH34: =AR34-BE34 -> 0 | BI34: =AS34-BF34 -> 13000000 | BN34: =BV34*$F$5 -> 332640.85 | BO34: =IF(BW34>0,BW34*$F$5,0) -> 83160.211 | BP34: =IF(BX34>0,BX34*$F$5,0) -> 249480.63 | BV34: 290754.71 | BW34: 72688.677 | BX34: 218066.03 | CD34: =G34 -> HKD | CE34: =H34-CC34 -> 13000000 | CF34: =CE34*I34 -> 13000000 | CG34: =CF34/$F$5 -> 11363040
C36: Total | I36: HK$ | J36: =SUM(J11:J34) -> 1505228 | K36: =SUM(K11:K34) -> 14338455 | L36: HK$ | N36: =SUM(N11:N34) -> 1.1176726e+08 | P36: =SUM(P11:P34) -> 1.179422e+08 | R36: =SUM(R11:R34) -> 1.2411715e+08 | T36: =SUM(T11:T34) -> 1.2028853e+08 | V36: =SUM(V11:V34) -> 1.2738971e+08 | X36: =SUM(X11:X34) -> 1.3449088e+08 | AC36: =SUM(AC11:AC34) -> 70231176 | AD36: =SUM(AD11:AD34) -> 41536079 | AF36: =SUM(AF11:AF34) -> 76394482 | AG36: =SUM(AG11:AG34) -> 41547720 | AI36: =SUM(AI11:AI34) -> 82557787 | AJ36: =SUM(AJ11:AJ34) -> 41559362 | AO36: =SUM(AO11:AO34) -> 75486389 | AP36: =SUM(AP11:AP34) -> 44802144 | AR36: =SUM(AR11:AR34) -> 82574174 | AS36: =SUM(AS11:AS34) -> 44815532 | AU36: =SUM(AU11:AU34) -> 89661959 | AV36: =SUM(AV11:AV34) -> 44828920 | AX36: HKD | AY36: =SUM(AY11:AY34) -> 0 | AZ36: =SUM(AZ11:AZ34) -> 0 | BB36: =SUM(BB11:BB34) -> 76394482 | BC36: =SUM(BC11:BC34) -> 41547720 | BE36: =SUM(BE11:BE34) -> 0 | BF36: =SUM(BF11:BF34) -> 0 | BH36: =SUM(BH11:BH34) -> 82574174 | BI36: =SUM(BI11:BI34) -> 44815532 | BK36: =SUM(BK11:BK34) -> 1304228.4 | BL36: 0 | BM36: =BK36-BL36 -> 1304228.4 | BN36: =BV36*$F$5 -> 28498670 | BO36: =BW36*$F$5 -> 7530182.8 | BP36: =BX36*$F$5 -> 20968487 | BQ36: =AF36-BL36-BO36 -> 68864299 | BR36: =AG36-BM36-BP36 -> 19275005 | BS36: =SUM(BS11:BS34) -> 1140000 | BT36: 0 | BU36: =BS36-BT36 -> 1140000 | BV36: =SUM(BV11:BV34)-BU36 -> 24910117 | BW36: =BV36-BX36 -> 6581982.2 | BX36: =19468135.28-BU36 -> 18328135 | BY36: =AF36/$F$5-BW36 -> 60192907 | BZ36: =AG36/$F$5-BX36-BU36 -> 16847896 | CF36: =SUM(CF11:CF34) -> 28989201 | CG36: =SUM(CG11:CG34) -> 25338881
C38: Note 1: During the IPO process, the engaged professional parties may liaise other third parties on certain work, and OPE / OOP stands for the expenses that are incurred in such processes and supposed to be reimbursed by the Issuer. A buffer is also reserved in the listing expense estimate in case the Issuer commissions additional services beyond the current scope during the IPO process. | BQ38: =BQ36+BR36 -> 88139304 | BV38: =BV36+BU36 -> 26050117 | BX38: 18328 | BZ38: =BZ36+BY36 -> 77040803
I39: RMB | J39: =J36/$F$5 -> 1315689.7 | K39: =K36/$F$5 -> 12532956 | L39: RMB | N39: =N36/$F$5 -> 97693522 | P39: =P36/$F$5 -> 1.0309092e+08 | R39: =R36/$F$5 -> 1.0848832e+08 | T39: =T36/$F$5 -> 1.051418e+08 | V39: =V36/$F$5 -> 1.1134879e+08 | X39: =X36/$F$5 -> 1.1755579e+08 | AX39: RMB | AY39: =AY36/$F$5 -> 0 | AZ39: =AZ36/$F$5 -> 0 | BB39: =BB36/$F$5 -> 66774889 | BC39: =BC36/$F$5 -> 36316031 | BE39: =BE36/$F$5 -> 0 | BF39: =BF36/$F$5 -> 0 | BH39: =BH36/$F$5 -> 72176434 | BI39: =BI36/$F$5 -> 39172360
BW40: Expected to incur | BX40: TOTAL | BY40: RMB | BZ40: =BY36+BZ36 -> 77040803 | CA40: =BZ40/1000000 -> 77.040803
N41: Global Offering WITHOUT Over-allotment Option exercised | T41: Global Offering WITH Over-allotment Option exercised | BY41: HKD | BZ41: =BZ40*$F$5 -> 88139304 | CA41: =BZ41/1000000 -> 88.139304
N42: Low | P42: Mid | R42: High | T42: Low | V42: Mid | X42: High
N43: =$N$10 -> 221.26 | P43: =$P$10 -> 245.31 | R43: =$R$10 -> 269.36 | T43: =$N$10 -> 221.26 | V43: =$P$10 -> 245.31 | X43: =$R$10 -> 269.36 | BX43: EXPENSES | BY43: RMB | BZ43: =BZ36 -> 16847896 | CA43: =BZ43/1000000 -> 16.847896
BY44: HKD | BZ44: =BZ43*$F$5 -> 19275005 | CA44: =BZ44/1000000 -> 19.275005
D45: Gross fund raise to Company | N45: =N10*$L$3 -> 1260053574 | P45: =P10*$L$3 -> 1397015919 | R45: =R10*$L$3 -> 1533978264 | T45: =T10*L5 -> 1.4490583e+09 | V45: =V10*L5 -> 1.6065646e+09 | X45: =X10*L5 -> 1.764071e+09
D46: Total gross fund raise | N46: =N45 -> 1260053574 | P46: =P45 -> 1397015919 | R46: =R45 -> 1533978264 | T46: =T45 -> 1.4490583e+09 | V46: =V45 -> 1.6065646e+09 | X46: =X45 -> 1.764071e+09 | BX46: EQUITY | BY46: RMB | BZ46: =BY36 -> 60192907 | CA46: =BZ46/1000000 -> 60.192907
R47: =R46-N46 -> 273924690 | BY47: HKD | BZ47: =BZ46*$F$5 -> 68864299 | CA47: =BZ47/1000000 -> 68.864299
D49: Listing expenses to be bornes by Company (Equity) | N49: =AC36 -> 70231176 | P49: =AF36 -> 76394482 | R49: =AI36 -> 82557787 | T49: =AO36 -> 75486389 | V49: =AR36 -> 82574174 | X49: =AU36 -> 89661959
D50: Listing expenses to be bornes by Company (Expenses) | N50: =AD36 -> 41536079 | P50: =AG36 -> 41547720 | R50: =AJ36 -> 41559362 | T50: =AP36 -> 44802144 | V50: =AS36 -> 44815532 | X50: =AV36 -> 44828920
D51: Total listing expenses | N51: =SUM(N49:N50) -> 1.1176726e+08 | P51: =SUM(P49:P50) -> 1.179422e+08 | R51: =SUM(R49:R50) -> 1.2411715e+08 | T51: =SUM(T49:T50) -> 1.2028853e+08 | V51: =SUM(V49:V50) -> 1.2738971e+08 | X51: =SUM(X49:X50) -> 1.3449088e+08 | BW51: TRP | BX51: TOTAL | BY51: RMB | BZ51: =BV36+BS36 -> 26050117 | CA51: =BZ51/1000000 -> 26.050117
BY52: HKD | BZ52: =BZ51*$F$5 -> 29802898 | CA52: =BZ52/1000000 -> 29.802898
D54: Net proceeds to Company | N54: =N46-N50 -> 1.2185175e+09 | O54: =O46-O50 -> 0 | P54: =P46-P49 -> 1.3206214e+09 | Q54: =Q46-Q50 -> 0 | R54: =R46-R50 -> 1.4924189e+09 | T54: =T46-T50 -> 1.4042561e+09 | U54: =U46-U50 -> 0 | V54: =V46-V50 -> 1.5617491e+09 | X54: =X46-X50 -> 1.719242e+09 | BX54: EXPENSES | BY54: RMB | BZ54: =BU36+BX36 -> 19468135 | CA54: =BZ54/1000000 -> 19.468135
BY55: HKD | BZ55: =BZ54*$F$5 -> 22272716 | CA55: =BZ55/1000000 -> 22.272716
D56: Total net proceeds | N56: =N46-N51 -> 1.1482863e+09 | P56: =P46-P51 -> 1.2790737e+09 | R56: =R46-R51 -> 1.4098611e+09 | T56: =T46-T51 -> 1.3287698e+09 | V56: =V46-V51 -> 1.4791749e+09 | X56: =X46-X51 -> 1.6295801e+09
BX57: EQUITY | BY57: RMB | BZ57: =BT36+BW36 -> 6581982.2 | CA57: =BZ57/1000000 -> 6.5819822
P58: =(P56-N56)/1000000 -> 130.7874 | R58: =(R56-P56)/1000000 -> 130.7874 | T58: =(T56-$N$56)/1000000 -> 180.48344 | V58: =(V56-$P$56)/1000000 -> 200.1012 | X58: =(X56-$R$56)/1000000 -> 219.71897 | BY58: HKD | BZ58: =BZ57*$F$5 -> 7530182.8 | CA58: =BZ58/1000000 -> 7.5301828
C60: A1-Hardcode | N60: Global Offering WITHOUT Over-allotment Option exercised | T60: Global Offering WITH Over-allotment Option exercised
N61: Low | P61: Mid | R61: High | T61: Low | V61: Mid | X61: High
N62: =$N$10 -> 221.26 | P62: =$P$10 -> 245.31 | R62: =$R$10 -> 269.36 | T62: =$N$10 -> 221.26 | V62: =$P$10 -> 245.31 | X62: =$R$10 -> 269.36
D64: Gross fund raise to Company | N64: 1260053574 | P64: 1397015919 | R64: 1533978264 | T64: 1.4490583e+09 | V64: 1.6065646e+09 | X64: 1.764071e+09
D65: Total gross fund raise | N65: =SUM(N64) -> 1260053574 | P65: =SUM(P64) -> 1397015919 | R65: =SUM(R64) -> 1533978264 | T65: =SUM(T64) -> 1.4490583e+09 | V65: =SUM(V64) -> 1.6065646e+09 | X65: =SUM(X64) -> 1.764071e+09
R66: =R65-N65 -> 273924690
D68: Listing expenses to be bornes by Company (Equity) | N68: 70007616 | P68: 76170922 | R68: 82334227 | T68: 75262829 | V68: 82350614 | X68: 89438399
D69: Listing expenses to be bornes by Company (Expenses) | N69: 40861142 | P69: 40872784 | R69: 40884426 | T69: 44127208 | V69: 44140596 | X69: 44153984
D70: Total listing expenses | N70: =SUM(N68:N69) -> 1.1086876e+08 | P70: =SUM(P68:P69) -> 1.1704371e+08 | R70: =SUM(R68:R69) -> 1.2321865e+08 | T70: =SUM(T68:T69) -> 1.1939004e+08 | V70: =SUM(V68:V69) -> 1.2649121e+08 | X70: =SUM(X68:X69) -> 1.3359238e+08
D73: Net proceeds to Company | N73: =N65-N69 -> 1.2191924e+09 | O73: =O65-O69 -> 0 | P73: =P65-P68 -> 1.320845e+09 | Q73: =Q65-Q69 -> 0 | R73: =R65-R69 -> 1.4930938e+09 | T73: =T65-T69 -> 1.4049311e+09 | U73: =U65-U69 -> 0 | V73: =V65-V69 -> 1.562424e+09 | X73: =X65-X69 -> 1.719917e+09
D75: Total net proceeds | N75: =N65-N70 -> 1.1491848e+09 | P75: =P65-P70 -> 1.2799722e+09 | R75: =R65-R70 -> 1.4107596e+09 | T75: =T65-T70 -> 1.3296683e+09 | V75: =V65-V70 -> 1.4800734e+09 | X75: =X65-X70 -> 1.6304786e+09
N79: Global Offering WITHOUT Over-allotment Option exercised | T79: Global Offering WITH Over-allotment Option exercised
N80: Low | P80: Mid | R80: High | T80: Low | V80: Mid | X80: High
N81: =$N$43 -> 221.26 | P81: =$P$43 -> 245.31 | R81: =$R$43 -> 269.36 | T81: =$N$43 -> 221.26 | V81: =$P$43 -> 245.31 | X81: =$R$43 -> 269.36
N82: in RMB | P82: in RMB | R82: in RMB | T82: in RMB | V82: in RMB | X82: in RMB
D83: Gross fund raise to Company | N83: =N45/$F$5 -> 1.1013876e+09 | P83: =P45/$F$5 -> 1.2211037e+09 | R83: =R45/$F$5 -> 1.3408197e+09 | T83: =T45/$F$5 -> 1.2665929e+09 | V83: =V45/$F$5 -> 1.404266e+09 | X83: =X45/$F$5 -> 1.5419391e+09
D84: Total gross fund raise | N84: =N46/$F$5 -> 1.1013876e+09 | P84: =P46/$F$5 -> 1.2211037e+09 | R84: =R46/$F$5 -> 1.3408197e+09 | T84: =T46/$F$5 -> 1.2665929e+09 | V84: =V46/$F$5 -> 1.404266e+09 | X84: =X46/$F$5 -> 1.5419391e+09
D87: Listing expenses to be bornes by Company (Equity) | N87: =N49/$F$5 -> 61387667 | P87: =P49/$F$5 -> 66774889 | R87: =R49/$F$5 -> 72162111 | T87: =T49/$F$5 -> 65981143 | V87: =V49/$F$5 -> 72176434 | X87: =X49/$F$5 -> 78371725
D88: Listing expenses to be bornes by Company (Expenses) | N88: =N50/$F$5 -> 36305856 | P88: =P50/$F$5 -> 36316031 | R88: =R50/$F$5 -> 36326207 | T88: =T50/$F$5 -> 39160658 | V88: =V50/$F$5 -> 39172360 | X88: =X50/$F$5 -> 39184062
D89: Total listing expenses | N89: =N51/$F$5 -> 97693522 | P89: =P51/$F$5 -> 1.0309092e+08 | R89: =R51/$F$5 -> 1.0848832e+08 | T89: =T51/$F$5 -> 1.051418e+08 | V89: =V51/$F$5 -> 1.1134879e+08 | X89: =X51/$F$5 -> 1.1755579e+08
D92: Net proceeds to Company | N92: =N54/$F$5 -> 1.0650818e+09 | P92: =P54/$F$5 -> 1.1543288e+09 | R92: =R54/$F$5 -> 1.3044935e+09 | T92: =T54/$F$5 -> 1.2274322e+09 | V92: =V54/$F$5 -> 1.3650936e+09 | X92: =X54/$F$5 -> 1.5027551e+09
D94: Total net proceeds | N94: =N56/$F$5 -> 1.0036941e+09 | P94: =P56/$F$5 -> 1.1180128e+09 | R94: =R56/$F$5 -> 1.2323314e+09 | T94: =T56/$F$5 -> 1.1614511e+09 | V94: =V56/$F$5 -> 1.2929172e+09 | X94: =X56/$F$5 -> 1.4243834e+09
C98: A1-Hardcode | N98: Global Offering WITHOUT Over-allotment Option exercised
N99: Low | P99: Mid | R99: High | T99: Low | V99: Mid | X99: High
N100: =$N$43 -> 221.26 | P100: =$P$43 -> 245.31 | R100: =$R$43 -> 269.36 | T100: =$N$43 -> 221.26 | V100: =$P$43 -> 245.31 | X100: =$R$43 -> 269.36
N101: in RMB | P101: in RMB | R101: in RMB | T101: in RMB | V101: in RMB | X101: in RMB
D102: Gross fund raise to Company | N102: 1.1500005e+09 | P102: 1.2750005e+09 | R102: 1.4000006e+09 | T102: =T64/$F$5 -> 1.2665929e+09 | V102: =V64/$F$5 -> 1.404266e+09 | X102: =X64/$F$5 -> 1.5419391e+09
D103: Total gross fund raise | N103: =SUM(N102) -> 1.1500005e+09 | P103: =SUM(P102) -> 1.2750005e+09 | R103: =SUM(R102) -> 1.4000006e+09 | T103: =T65/$F$5 -> 1.2665929e+09 | V103: =V65/$F$5 -> 1.404266e+09 | X103: =X65/$F$5 -> 1.5419391e+09
D106: Listing expenses to be bornes by Company (Equity) | N106: 63893151 | P106: 69518153 | R106: 75143156 | T106: =T68/$F$5 -> 65785733 | V106: =V68/$F$5 -> 71981024 | X106: =X68/$F$5 -> 78176316
D107: Listing expenses to be bornes by Company (Expenses) | N107: 37292330 | P107: 37302955 | R107: 37313580 | T107: =T69/$F$5 -> 38570710 | V107: =V69/$F$5 -> 38582412 | X107: =X69/$F$5 -> 38594114
D108: Total listing expenses | N108: =SUM(N106:N107) -> 1.0118548e+08 | P108: =SUM(P106:P107) -> 1.0682111e+08 | R108: =SUM(R106:R107) -> 1.1245674e+08 | T108: =T70/$F$5 -> 1.0435644e+08 | V108: =V70/$F$5 -> 1.1056344e+08 | X108: =X70/$F$5 -> 1.1677043e+08
D111: Net proceeds to Company | N111: 1.1127082e+09 | P111: 1.2054824e+09 | R111: 1.362687e+09 | T111: =T73/$F$5 -> 1.2280222e+09 | V111: =V73/$F$5 -> 1.3656836e+09 | X111: =X73/$F$5 -> 1.503345e+09
D113: Total net proceeds | N113: =N103-N108 -> 1.048815e+09 | P113: =P103-P108 -> 1.1681794e+09 | R113: =R103-R108 -> 1.2875439e+09 | T113: =T75/$F$5 -> 1.1622364e+09 | V113: =V75/$F$5 -> 1.2937026e+09 | X113: =X75/$F$5 -> 1.4251687e+09
G117: HKD | H117: RMB | I117: in RMB mil
D118: Underwriting | G118: =P28+P29 -> 62865716 | H118: =G118/$F$5 -> 54949665 | I118: =H118/1000000 -> 54.949665
D119: Sponsor | G119: =SUM(P11,P12) -> 14092020 | H119: =G119/$F$5 -> 12317553 | I119: =H119/1000000 -> 12.317553
D120: Professional parties | G120: =SUM(P13:P27) -> 27215720 | H120: =G120/$F$5 -> 23788716 | I120: =H120/1000000 -> 23.788716
D121: Others | G121: =SUM(P30:P34) -> 13768746 | H121: =G121/$F$5 -> 12034986 | I121: =H121/1000000 -> 12.034986
D122: Total | G122: =SUM(G118:G121) -> 1.179422e+08 | H122: =G122/$F$5 -> 1.0309092e+08 | I122: =H122/1000000 -> 103.09092
D124: Deducted from Equity | G124: =P49 -> 76394482 | H124: =P87 -> 66774889 | I124: =ROUND(I122,1)-ROUND(I125,1) -> 66.8
D125: Deducted from PnL | G125: =P50 -> 41547720 | H125: =P88 -> 36316031 | I125: =H125/1000000 -> 36.316031
G129: HKD | H129: in HKD mil | I129: RMB | J129: in RMB mil
D130: underwriting commissions, SFC transaction levy, Stock Exchange trading fees and AFRC transaction levy | G130: =P28+P29+P30+P31+P32+P33 -> 63634463 | H130: =G130/1000000 -> 63.634463 | I130: =G130/$F$5 -> 55621611 | J130: =I130/1000000 -> 55.621611
D131: non-underwriting related expenses | G131: =G122-G130 -> 54307740 | H131: =G131/1000000 -> 54.30774 | I131: =G131/$F$5 -> 47469309 | J131: =I131/1000000 -> 47.469309
D132: fees and expenses of legal advisors and accountants | G132: =P13+P14+P15+P16+P17 -> 21564314 | H132: =G132/1000000 -> 21.564314 | I132: =G132/$F$5 -> 18848936 | J132: =I132/1000000 -> 18.848936
D133: sponsors fee and other fees and expenses | G133: =G131-G132 -> 32743425 | H133: =G133/1000000 -> 32.743425 | I133: =G133/$F$5 -> 28620373 | J133: =I133/1000000 -> 28.620373
...

Sheet UOP
B1: Blue: Hard code vale | AD1: x
B2: Black: Calculation | AD2: x
B3: Green: Linked from another tab | AD3: x
B4: Red: Linked from the same tab | AD4: x
AD5: x
L6: Annual Forecast | AD6: x
C7: Total Net Proceeds (RMB thousand) | G7: =Control!H30 -> 1118012.8 | L7: 46204 | M7: =EDATE(L7,1) -> 46235 | N7: =EDATE(M7,1) -> 46266 | O7: =EDATE(N7,1) -> 46296 | P7: =EDATE(O7,1) -> 46327 | Q7: =EDATE(P7,1) -> 46357 | R7: =EDATE(Q7,1) -> 46388 | S7: =EDATE(R7,1) -> 46419 | T7: =EDATE(S7,1) -> 46447 | ... AC7: =EDATE(AB7,1) -> 46722 | AD7: x
C8: Total Net Proceeds (HKD thousand) | G8: =Control!H28 -> 1279073.7 | I8: Treatment | J8: HKD’000 | K8: RMB’000 | L8: RMB’000 | M8: RMB’000 | N8: RMB’000 | O8: RMB’000 | P8: RMB’000 | Q8: RMB’000 | R8: RMB’000 | S8: RMB’000 | T8: RMB’000 | U8: RMB’000 | V8: RMB’000 | W8: RMB’000 | X8: RMB’000 | Y8: RMB’000 | Z8: RMB’000 | AA8: RMB’000 | AB8: RMB’000 | AC8: RMB’000 | AD8: x
B9: x | C9: UOP Schedule | AD9: x
C10: R&D Developments | G10: 研发能力的提升 | H10: =H11+H13+H14+H12 -> 0.5 | J10: =J11+J13+J14+J12 -> 639536.86 | K10: =K11+K13+K14+K12 -> 559006.38 | L10: =L11+L13+L14+L12 -> 4658.3865 | M10: =M11+M13+M14+M12 -> 4658.3865 | N10: =N11+N13+N14+N12 -> 4658.3865 | O10: =O11+O13+O14+O12 -> 4658.3865 | P10: =P11+P13+P14+P12 -> 4658.3865 | Q10: =Q11+Q13+Q14+Q12 -> 4658.3865 | ... AC10: =AC11+AC13+AC14+AC12 -> 6987.5797 | AD10: x
D11: Computing Power Procurement & Leasing | G11: 算力采购及租赁 | H11: =35%/10*4 -> 0.14 | I11: BS - PP&E | J11: =H11*$G$8 -> 179070.32 | K11: =H11*$G$7 -> 156521.79 | L11: =$M$36/6 -> 1304.3482 | M11: =$M$36/6 -> 1304.3482 | N11: =$M$36/6 -> 1304.3482 | O11: =$M$36/6 -> 1304.3482 | P11: =$M$36/6 -> 1304.3482 | Q11: =$M$36/6 -> 1304.3482 | R11: =$N$36/12 -> 1956.5223 | S11: =$N$36/12 -> 1956.5223 | T11: =$N$36/12 -> 1956.5223 | U11: =$N$36/12 -> 1956.5223 | V11: =$N$36/12 -> 1956.5223 | W11: =$N$36/12 -> 1956.5223 | X11: =$N$36/12 -> 1956.5223 | Y11: =$N$36/12 -> 1956.5223 | ... AC11: =$N$36/12 -> 1956.5223 | AD11: x
G12: 算力租赁 | H12: =35%/10*6 -> 0.21 | I12: BS - Prepayment | J12: =H12*$G$8 -> 268605.48 | K12: =H12*$G$7 -> 234782.68 | L12: =$M$40/6 -> 1956.5223 | M12: =$M$40/6 -> 1956.5223 | N12: =$M$40/6 -> 1956.5223 | O12: =$M$40/6 -> 1956.5223 | P12: =$M$40/6 -> 1956.5223 | Q12: =$M$40/6 -> 1956.5223 | R12: =$N$40/12 -> 2934.7835 | S12: =$N$40/12 -> 2934.7835 | T12: =$N$40/12 -> 2934.7835 | U12: =$N$40/12 -> 2934.7835 | V12: =$N$40/12 -> 2934.7835 | W12: =$N$40/12 -> 2934.7835 | X12: =$N$40/12 -> 2934.7835 | Y12: =$N$40/12 -> 2934.7835 | ... AC12: =$N$40/12 -> 2934.7835 | AD12: x
D13: R&D Talent Recruitment | G13: 研发人员招聘 | H13: 0.1 | I13: PL - R&D | J13: =H13*$G$8 -> 127907.37 | K13: =H13*$G$7 -> 111801.28 | L13: =$M$44/6 -> 931.6773 | M13: =$M$44/6 -> 931.6773 | N13: =$M$44/6 -> 931.6773 | O13: =$M$44/6 -> 931.6773 | P13: =$M$44/6 -> 931.6773 | Q13: =$M$44/6 -> 931.6773 | R13: =$N$44/12 -> 1397.5159 | S13: =$N$44/12 -> 1397.5159 | T13: =$N$44/12 -> 1397.5159 | U13: =$N$44/12 -> 1397.5159 | V13: =$N$44/12 -> 1397.5159 | W13: =$N$44/12 -> 1397.5159 | X13: =$N$44/12 -> 1397.5159 | Y13: =$N$44/12 -> 1397.5159 | ... AC13: =$N$44/12 -> 1397.5159 | AD13: x
D14: Outsourced R&D | G14: 委外研发 | H14: 0.05 | I14: PL - R&D | J14: =H14*$G$8 -> 63953.686 | K14: =H14*$G$7 -> 55900.638 | L14: =$M$48/6 -> 465.83865 | M14: =$M$48/6 -> 465.83865 | N14: =$M$48/6 -> 465.83865 | O14: =$M$48/6 -> 465.83865 | P14: =$M$48/6 -> 465.83865 | Q14: =$M$48/6 -> 465.83865 | R14: =$N$48/12 -> 698.75797 | S14: =$N$48/12 -> 698.75797 | T14: =$N$48/12 -> 698.75797 | U14: =$N$48/12 -> 698.75797 | V14: =$N$48/12 -> 698.75797 | W14: =$N$48/12 -> 698.75797 | X14: =$N$48/12 -> 698.75797 | Y14: =$N$48/12 -> 698.75797 | ... AC14: =$N$48/12 -> 698.75797 | AD14: x
I15: BS部分 | L15: =L11+L12 -> 3260.8705 | M15: =M11+M12 -> 3260.8705 | N15: =N11+N12 -> 3260.8705 | O15: =O11+O12 -> 3260.8705 | P15: =P11+P12 -> 3260.8705 | Q15: =Q11+Q12 -> 3260.8705 | R15: =R11+R12 -> 4891.3058 | S15: =S11+S12 -> 4891.3058 | ... AC15: =AC11+AC12 -> 4891.3058 | AD15: x
I16: PL部分 | L16: =L13+L14 -> 1397.5159 | M16: =M13+M14 -> 1397.5159 | N16: =N13+N14 -> 1397.5159 | O16: =O13+O14 -> 1397.5159 | P16: =P13+P14 -> 1397.5159 | Q16: =Q13+Q14 -> 1397.5159 | R16: =R13+R14 -> 2096.2739 | S16: =S13+S14 -> 2096.2739 | ... AC16: =AC13+AC14 -> 2096.2739 | AD16: x
I17: PL部分check | L17: =IF(Control!$H$17=1,'IS-Other Calculations'!AC114+'IS-Other Calculations'!AC120=UOP!L16,"NA") -> TRUE | M17: =IF(Control!$H$17=1,'IS-Other Calculations'!AD114+'IS-Other Calculations'!AD120=UOP!M16,"NA") -> TRUE | N17: =IF(Control!$H$17=1,'IS-Other Calculations'!AE114+'IS-Other Calculations'!AE120=UOP!N16,"NA") -> TRUE | O17: =IF(Control!$H$17=1,'IS-Other Calculations'!AF114+'IS-Other Calculations'!AF120=UOP!O16,"NA") -> TRUE | P17: =IF(Control!$H$17=1,'IS-Other Calculations'!AG114+'IS-Other Calculations'!AG120=UOP!P16,"NA") -> TRUE | Q17: =IF(Control!$H$17=1,'IS-Other Calculations'!AH114+'IS-Other Calculations'!AH120=UOP!Q16,"NA") -> TRUE | R17: =IF(Control!$H$17=1,'IS-Other Calculations'!AI114+'IS-Other Calculations'!AI120=UOP!R16,"NA") -> TRUE | S17: =IF(Control!$H$17=1,'IS-Other Calculations'!AJ114+'IS-Other Calculations'!AJ120=UOP!S16,"NA") -> TRUE | ... AC17: =IF(Control!$H$17=1,'IS-Other Calculations'!AT114+'IS-Other Calculations'!AT120=UOP!AC16,"NA") -> TRUE | AD17: x
C18: Business Expansion | G18: 商机开拓 | H18: =H19+H20 -> 0.25 | J18: =J19+J20 -> 319768.43 | K18: =K19+K20 -> 279503.19 | L18: =L19+L20 -> 2329.1932 | M18: =M19+M20 -> 2329.1932 | N18: =N19+N20 -> 2329.1932 | O18: =O19+O20 -> 2329.1932 | P18: =P19+P20 -> 2329.1932 | Q18: =Q19+Q20 -> 2329.1932 | ... AC18: =AC19+AC20 -> 3493.7899 | AD18: x
D19: Marketing & Brand Promotion | G19: 宣传推广 | H19: 0.2 | I19: PL - Selling and marketing | J19: =H19*$G$8 -> 255814.74 | K19: =H19*$G$7 -> 223602.55 | L19: =$M$52/6 -> 1863.3546 | M19: =$M$52/6 -> 1863.3546 | N19: =$M$52/6 -> 1863.3546 | O19: =$M$52/6 -> 1863.3546 | P19: =$M$52/6 -> 1863.3546 | Q19: =$M$52/6 -> 1863.3546 | R19: =$N$52/12 -> 2795.0319 | S19: =$N$52/12 -> 2795.0319 | T19: =$N$52/12 -> 2795.0319 | U19: =$N$52/12 -> 2795.0319 | V19: =$N$52/12 -> 2795.0319 | W19: =$N$52/12 -> 2795.0319 | X19: =$N$52/12 -> 2795.0319 | Y19: =$N$52/12 -> 2795.0319 | ... AC19: =$N$52/12 -> 2795.0319 | AD19: x
D20: Sales Talent Recruitment | G20: 销售人员招聘 | H20: 0.05 | I20: PL - Selling and marketing | J20: =H20*$G$8 -> 63953.686 | K20: =H20*$G$7 -> 55900.638 | L20: =$M$56/6 -> 465.83865 | M20: =$M$56/6 -> 465.83865 | N20: =$M$56/6 -> 465.83865 | O20: =$M$56/6 -> 465.83865 | P20: =$M$56/6 -> 465.83865 | Q20: =$M$56/6 -> 465.83865 | R20: =$N$56/12 -> 698.75797 | S20: =$N$56/12 -> 698.75797 | T20: =$N$56/12 -> 698.75797 | U20: =$N$56/12 -> 698.75797 | V20: =$N$56/12 -> 698.75797 | W20: =$N$56/12 -> 698.75797 | X20: =$N$56/12 -> 698.75797 | Y20: =$N$56/12 -> 698.75797 | ... AC20: =$N$56/12 -> 698.75797 | AD20: x
I21: PL部分 | L21: =L19+L20 -> 2329.1932 | M21: =M19+M20 -> 2329.1932 | N21: =N19+N20 -> 2329.1932 | O21: =O19+O20 -> 2329.1932 | P21: =P19+P20 -> 2329.1932 | Q21: =Q19+Q20 -> 2329.1932 | R21: =R19+R20 -> 3493.7899 | S21: =S19+S20 -> 3493.7899 | ... AC21: =AC19+AC20 -> 3493.7899 | AD21: x
I22: PL部分check | L22: =IF(Control!$H$17=1,'IS-Other Calculations'!AC65+'IS-Other Calculations'!AC74=UOP!L21,"NA") -> TRUE | M22: =IF(Control!$H$17=1,'IS-Other Calculations'!AD65+'IS-Other Calculations'!AD74=UOP!M21,"NA") -> TRUE | N22: =IF(Control!$H$17=1,'IS-Other Calculations'!AE65+'IS-Other Calculations'!AE74=UOP!N21,"NA") -> TRUE | O22: =IF(Control!$H$17=1,'IS-Other Calculations'!AF65+'IS-Other Calculations'!AF74=UOP!O21,"NA") -> TRUE | P22: =IF(Control!$H$17=1,'IS-Other Calculations'!AG65+'IS-Other Calculations'!AG74=UOP!P21,"NA") -> TRUE | Q22: =IF(Control!$H$17=1,'IS-Other Calculations'!AH65+'IS-Other Calculations'!AH74=UOP!Q21,"NA") -> TRUE | R22: =IF(Control!$H$17=1,'IS-Other Calculations'!AI65+'IS-Other Calculations'!AI74=UOP!R21,"NA") -> TRUE | S22: =IF(Control!$H$17=1,'IS-Other Calculations'!AJ65+'IS-Other Calculations'!AJ74=UOP!S21,"NA") -> TRUE | ... AC22: =IF(Control!$H$17=1,'IS-Other Calculations'!AT65+'IS-Other Calculations'!AT74=UOP!AC21,"NA") -> TRUE | AD22: x
AD23: x
C24: Strategic Partnerships & Acquisitions | G24: 战略合作与收购 | H24: 0.15 | I24: BS - Cash | J24: =H24*$G$8 -> 191861.06 | K24: =H24*$G$7 -> 167701.91 | L24: 0 | M24: 0 | N24: 0 | O24: 0 | P24: 0 | Q24: 0 | R24: 0 | S24: 0 | T24: 0 | U24: 0 | V24: 0 | W24: 0 | X24: 0 | Y24: 0 | Z24: 0 | AA24: 0 | AB24: 0 | AC24: 0 | AD24: x
AD25: x
C26: Working Capitacl Supplement | G26: 补流 | H26: 0.1 | I26: BS - Cash | J26: =H26*$G$8 -> 127907.37 | K26: =H26*$G$7 -> 111801.28 | L26: 0 | M26: 0 | N26: 0 | O26: 0 | P26: 0 | Q26: 0 | R26: 0 | S26: 0 | T26: 0 | U26: 0 | V26: 0 | W26: 0 | X26: 0 | Y26: 0 | Z26: 0 | AA26: 0 | AB26: 0 | AC26: 0 | AD26: x
AD27: x
C28: Sum | G28: 总计 | H28: =H10+H18+H24+H26 -> 1 | J28: =H28*$G$8 -> 1279073.7 | K28: =K10+K18+K24+K26 -> 1118012.8 | L28: =L26+L24+L18+L10 -> 6987.5797 | M28: =M26+M24+M18+M10 -> 6987.5797 | N28: =N26+N24+N18+N10 -> 6987.5797 | O28: =O26+O24+O18+O10 -> 6987.5797 | P28: =P26+P24+P18+P10 -> 6987.5797 | Q28: =Q26+Q24+Q18+Q10 -> 6987.5797 | R28: =R26+R24+R18+R10 -> 10481.37 | S28: =S26+S24+S18+S10 -> 10481.37 | ... AC28: =AC26+AC24+AC18+AC10 -> 10481.37 | AD28: x
C29: Accumulated UOP outflows | G29: 募集资金累计使用 | L29: =SUM($L$28:L28) -> 6987.5797 | M29: =SUM($L$28:M28) -> 13975.159 | N29: =SUM($L$28:N28) -> 20962.739 | O29: =SUM($L$28:O28) -> 27950.319 | P29: =SUM($L$28:P28) -> 34937.899 | Q29: =SUM($L$28:Q28) -> 41925.478 | R29: =SUM($L$28:R28) -> 52406.848 | S29: =SUM($L$28:S28) -> 62888.217 | ... AC29: =SUM($L$28:AC28) -> 167701.91 | AD29: x
C30: Remianing UOP | G30: 募集资金剩余 | L30: =$G$7-L29 -> 1111025.2 | M30: =$G$7-M29 -> 1104037.6 | N30: =$G$7-N29 -> 1097050 | O30: =$G$7-O29 -> 1090062.4 | P30: =$G$7-P29 -> 1083074.9 | Q30: =$G$7-Q29 -> 1076087.3 | R30: =$G$7-R29 -> 1065605.9 | S30: =$G$7-S29 -> 1055124.5 | ... AC30: =$G$7-AC29 -> 950310.84 | AD30: x
AD31: x
AD32: x
AD33: x
E34: Computing Power Procurement & Leasing | H34: 算力采购及租赁 | K34: =K11 -> 156521.79 | L34: 分配比例 | M34: 0.05 | N34: 0.15 | O34: 0.2 | P34: 0.3 | Q34: 0.3 | AD34: x
M35: 2026H2E | N35: 2027E | O35: 2028E | P35: 2029E | Q35: 2030E | AD35: x
M36: =$K$34*M34 -> 7826.0893 | N36: =$K$34*N34 -> 23478.268 | O36: =$K$34*O34 -> 31304.357 | P36: =$K$34*P34 -> 46956.536 | Q36: =$K$34*Q34 -> 46956.536 | AD36: x
AD37: x
H38: 算力租赁 | K38: =K12 -> 234782.68 | L38: 分配比例 | M38: 0.05 | N38: 0.15 | O38: 0.2 | P38: 0.3 | Q38: 0.3 | AD38: x
M39: 2026H2E | N39: 2027E | O39: 2028E | P39: 2029E | Q39: 2030E | AD39: x
M40: =$K$38*M38 -> 11739.134 | N40: =$K$38*N38 -> 35217.402 | O40: =$K$38*O38 -> 46956.536 | P40: =$K$38*P38 -> 70434.804 | Q40: =$K$38*Q38 -> 70434.804 | AD40: x
E42: R&D Talent Recruitment | H42: 研发人员招聘 | K42: =K13 -> 111801.28 | L42: 分配比例 | M42: 0.05 | N42: 0.15 | O42: 0.2 | P42: 0.3 | Q42: 0.3 | AD42: x
M43: 2026H2E | N43: 2027E | O43: 2028E | P43: 2029E | Q43: 2030E | AD43: x
M44: =$K$42*M42 -> 5590.0638 | N44: =$K$42*N42 -> 16770.191 | O44: =$K$42*O42 -> 22360.255 | P44: =$K$42*P42 -> 33540.383 | Q44: =$K$42*Q42 -> 33540.383 | AD44: x
AD45: x
E46: Outsourced R&D | H46: 委外研发 | K46: =K14 -> 55900.638 | L46: 分配比例 | M46: 0.05 | N46: 0.15 | O46: 0.2 | P46: 0.3 | Q46: 0.3 | AD46: x
M47: 2026H2E | N47: 2027E | O47: 2028E | P47: 2029E | Q47: 2030E | AD47: x
M48: =$K$46*M46 -> 2795.0319 | N48: =$K$46*N46 -> 8385.0957 | O48: =$K$46*O46 -> 11180.128 | P48: =$K$46*P46 -> 16770.191 | Q48: =$K$46*Q46 -> 16770.191 | AD48: x
AD49: x
E50: Marketing & Brand Promotion | H50: 宣传推广 | K50: =K19 -> 223602.55 | L50: 分配比例 | M50: 0.05 | N50: 0.15 | O50: 0.2 | P50: 0.3 | Q50: 0.3 | AD50: x
M51: 2026H2E | N51: 2027E | O51: 2028E | P51: 2029E | Q51: 2030E | AD51: x
M52: =$K$50*M50 -> 11180.128 | N52: =$K$50*N50 -> 33540.383 | O52: =$K$50*O50 -> 44720.51 | P52: =$K$50*P50 -> 67080.765 | Q52: =$K$50*Q50 -> 67080.765 | AD52: x
AD53: x
E54: Sales Talent Recruitment | H54: 销售人员招聘 | K54: =K20 -> 55900.638 | L54: 分配比例 | M54: 0.05 | N54: 0.15 | O54: 0.2 | P54: 0.3 | Q54: 0.3 | AD54: x
M55: 2026H2E | N55: 2027E | O55: 2028E | P55: 2029E | Q55: 2030E | AD55: x
M56: =$K$54*M54 -> 2795.0319 | N56: =$K$54*N54 -> 8385.0957 | O56: =$K$54*O54 -> 11180.128 | P56: =$K$54*P54 -> 16770.191 | Q56: =$K$54*Q54 -> 16770.191 | AD56: x
AD57: x
AD58: x
AD59: x
AD60: x
AD61: x

Sheet UOP_Depreciation
A1: Blue: Hard code vale
A2: Black: Calculation
A3: Green: Linked from another tab
A4: Red: Linked from the same tab
E7: 46204 | F7: =EDATE(E7,1) -> 46235 | G7: =EDATE(F7,1) -> 46266 | H7: =EDATE(G7,1) -> 46296 | I7: =EDATE(H7,1) -> 46327 | J7: =EDATE(I7,1) -> 46357 | K7: =EDATE(J7,1) -> 46388 | L7: =EDATE(K7,1) -> 46419 | M7: =EDATE(L7,1) -> 46447 | ... V7: =EDATE(U7,1) -> 46722
B8: Deprecation-Addition of electrionic equipment from UOP_BS_PP&E | AT8: x
W9: x
B10: Beginning Balance | E10: 0 | F10: =E13 -> 1304.3482 | G10: =F13 -> 2574.2761 | H10: =G13 -> 3809.7837 | I10: =H13 -> 5010.8711 | J10: =I13 -> 6177.5381 | K10: =J13 -> 7309.7848 | L10: =K13 -> 9059.7853 | M10: =L13 -> 10758.155 | ... V10: =U13 -> 23720.116 | W10: x
C11: (+) Additions | E11: =UOP!L11 -> 1304.3482 | F11: =UOP!M11 -> 1304.3482 | G11: =UOP!N11 -> 1304.3482 | H11: =UOP!O11 -> 1304.3482 | I11: =UOP!P11 -> 1304.3482 | J11: =UOP!Q11 -> 1304.3482 | K11: =UOP!R11 -> 1956.5223 | L11: =UOP!S11 -> 1956.5223 | ... V11: =UOP!AC11 -> 1956.5223 | W11: x
C12: (-) Depreciation charges | E12: =-E41 -> 0 | F12: =-F41 -> -34.4203 | G12: =-G41 -> -68.8406 | H12: =-H41 -> -103.2609 | I12: =-I41 -> -137.6812 | J12: =-J41 -> -172.1015 | K12: =-K41 -> -206.5218 | L12: =-L41 -> -258.15225 | ... V12: =-V41 -> -774.45675 | W12: x
B13: Ending Balance | E13: =E10+E11+E12 -> 1304.3482 | F13: =F10+F11+F12 -> 2574.2761 | G13: =G10+G11+G12 -> 3809.7837 | H13: =H10+H11+H12 -> 5010.8711 | I13: =I10+I11+I12 -> 6177.5381 | J13: =J10+J11+J12 -> 7309.7848 | K13: =K10+K11+K12 -> 9059.7853 | L13: =L10+L11+L12 -> 10758.155 | ... V13: =V10+V11+V12 -> 24902.181 | W13: x
W14: x
W15: x
C16: Useful Life | D16: 36 | E16: months | W16: x
C17: Residual rate | D17: 0.05 | W17: x
W18: x
W19: x
W20: x
B21: Depreciation | E21: 46204 | F21: =EDATE(E21,1) -> 46235 | G21: =EDATE(F21,1) -> 46266 | H21: =EDATE(G21,1) -> 46296 | I21: =EDATE(H21,1) -> 46327 | J21: =EDATE(I21,1) -> 46357 | K21: =EDATE(J21,1) -> 46388 | L21: =EDATE(K21,1) -> 46419 | M21: =EDATE(L21,1) -> 46447 | ... V21: =EDATE(U21,1) -> 46722 | W21: x
D22: 46204 | E22: =IF(AND(E$21>$D22,E$21<=EDATE($D22,$D$16)),($E$11*(1-$D$17)/$D$16),0) -> 0 | F22: =IF(AND(F$21>$D22,F$21<=EDATE($D22,$D$16)),($E$11*(1-$D$17)/$D$16),0) -> 34.4203 | G22: =IF(AND(G$21>$D22,G$21<=EDATE($D22,$D$16)),($E$11*(1-$D$17)/$D$16),0) -> 34.4203 | H22: =IF(AND(H$21>$D22,H$21<=EDATE($D22,$D$16)),($E$11*(1-$D$17)/$D$16),0) -> 34.4203 | I22: =IF(AND(I$21>$D22,I$21<=EDATE($D22,$D$16)),($E$11*(1-$D$17)/$D$16),0) -> 34.4203 | J22: =IF(AND(J$21>$D22,J$21<=EDATE($D22,$D$16)),($E$11*(1-$D$17)/$D$16),0) -> 34.4203 | K22: =IF(AND(K$21>$D22,K$21<=EDATE($D22,$D$16)),($E$11*(1-$D$17)/$D$16),0) -> 34.4203 | L22: =IF(AND(L$21>$D22,L$21<=EDATE($D22,$D$16)),($E$11*(1-$D$17)/$D$16),0) -> 34.4203 | ... V22: =IF(AND(V$21>$D22,V$21<=EDATE($D22,$D$16)),($E$11*(1-$D$17)/$D$16),0) -> 34.4203 | W22: x
D23: =EDATE(D22,1) -> 46235 | E23: =IF(AND(E$21>$D23,E$21<=EDATE($D23,$D$16)),($F$11*(1-$D$17)/$D$16),0) -> 0 | F23: =IF(AND(F$21>$D23,F$21<=EDATE($D23,$D$16)),($F$11*(1-$D$17)/$D$16),0) -> 0 | G23: =IF(AND(G$21>$D23,G$21<=EDATE($D23,$D$16)),($F$11*(1-$D$17)/$D$16),0) -> 34.4203 | H23: =IF(AND(H$21>$D23,H$21<=EDATE($D23,$D$16)),($F$11*(1-$D$17)/$D$16),0) -> 34.4203 | I23: =IF(AND(I$21>$D23,I$21<=EDATE($D23,$D$16)),($F$11*(1-$D$17)/$D$16),0) -> 34.4203 | J23: =IF(AND(J$21>$D23,J$21<=EDATE($D23,$D$16)),($F$11*(1-$D$17)/$D$16),0) -> 34.4203 | K23: =IF(AND(K$21>$D23,K$21<=EDATE($D23,$D$16)),($F$11*(1-$D$17)/$D$16),0) -> 34.4203 | L23: =IF(AND(L$21>$D23,L$21<=EDATE($D23,$D$16)),($F$11*(1-$D$17)/$D$16),0) -> 34.4203 | ... V23: =IF(AND(V$21>$D23,V$21<=EDATE($D23,$D$16)),($F$11*(1-$D$17)/$D$16),0) -> 34.4203 | W23: x
D24: =EDATE(D23,1) -> 46266 | E24: =IF(AND(E$21>$D24,E$21<=EDATE($D24,$D$16)),($G$11*(1-$D$17)/$D$16),0) -> 0 | F24: =IF(AND(F$21>$D24,F$21<=EDATE($D24,$D$16)),($G$11*(1-$D$17)/$D$16),0) -> 0 | G24: =IF(AND(G$21>$D24,G$21<=EDATE($D24,$D$16)),($G$11*(1-$D$17)/$D$16),0) -> 0 | H24: =IF(AND(H$21>$D24,H$21<=EDATE($D24,$D$16)),($G$11*(1-$D$17)/$D$16),0) -> 34.4203 | I24: =IF(AND(I$21>$D24,I$21<=EDATE($D24,$D$16)),($G$11*(1-$D$17)/$D$16),0) -> 34.4203 | J24: =IF(AND(J$21>$D24,J$21<=EDATE($D24,$D$16)),($G$11*(1-$D$17)/$D$16),0) -> 34.4203 | K24: =IF(AND(K$21>$D24,K$21<=EDATE($D24,$D$16)),($G$11*(1-$D$17)/$D$16),0) -> 34.4203 | L24: =IF(AND(L$21>$D24,L$21<=EDATE($D24,$D$16)),($G$11*(1-$D$17)/$D$16),0) -> 34.4203 | ... V24: =IF(AND(V$21>$D24,V$21<=EDATE($D24,$D$16)),($G$11*(1-$D$17)/$D$16),0) -> 34.4203 | W24: x
D25: =EDATE(D24,1) -> 46296 | E25: =IF(AND(E$21>$D25,E$21<=EDATE($D25,$D$16)),($H$11*(1-$D$17)/$D$16),0) -> 0 | F25: =IF(AND(F$21>$D25,F$21<=EDATE($D25,$D$16)),($H$11*(1-$D$17)/$D$16),0) -> 0 | G25: =IF(AND(G$21>$D25,G$21<=EDATE($D25,$D$16)),($H$11*(1-$D$17)/$D$16),0) -> 0 | H25: =IF(AND(H$21>$D25,H$21<=EDATE($D25,$D$16)),($H$11*(1-$D$17)/$D$16),0) -> 0 | I25: =IF(AND(I$21>$D25,I$21<=EDATE($D25,$D$16)),($H$11*(1-$D$17)/$D$16),0) -> 34.4203 | J25: =IF(AND(J$21>$D25,J$21<=EDATE($D25,$D$16)),($H$11*(1-$D$17)/$D$16),0) -> 34.4203 | K25: =IF(AND(K$21>$D25,K$21<=EDATE($D25,$D$16)),($H$11*(1-$D$17)/$D$16),0) -> 34.4203 | L25: =IF(AND(L$21>$D25,L$21<=EDATE($D25,$D$16)),($H$11*(1-$D$17)/$D$16),0) -> 34.4203 | ... V25: =IF(AND(V$21>$D25,V$21<=EDATE($D25,$D$16)),($H$11*(1-$D$17)/$D$16),0) -> 34.4203 | W25: x
D26: =EDATE(D25,1) -> 46327 | E26: =IF(AND(E$21>$D26,E$21<=EDATE($D26,$D$16)),($I$11*(1-$D$17)/$D$16),0) -> 0 | F26: =IF(AND(F$21>$D26,F$21<=EDATE($D26,$D$16)),($I$11*(1-$D$17)/$D$16),0) -> 0 | G26: =IF(AND(G$21>$D26,G$21<=EDATE($D26,$D$16)),($I$11*(1-$D$17)/$D$16),0) -> 0 | H26: =IF(AND(H$21>$D26,H$21<=EDATE($D26,$D$16)),($I$11*(1-$D$17)/$D$16),0) -> 0 | I26: =IF(AND(I$21>$D26,I$21<=EDATE($D26,$D$16)),($I$11*(1-$D$17)/$D$16),0) -> 0 | J26: =IF(AND(J$21>$D26,J$21<=EDATE($D26,$D$16)),($I$11*(1-$D$17)/$D$16),0) -> 34.4203 | K26: =IF(AND(K$21>$D26,K$21<=EDATE($D26,$D$16)),($I$11*(1-$D$17)/$D$16),0) -> 34.4203 | L26: =IF(AND(L$21>$D26,L$21<=EDATE($D26,$D$16)),($I$11*(1-$D$17)/$D$16),0) -> 34.4203 | ... V26: =IF(AND(V$21>$D26,V$21<=EDATE($D26,$D$16)),($I$11*(1-$D$17)/$D$16),0) -> 34.4203 | W26: x
D27: =EDATE(D26,1) -> 46357 | E27: =IF(AND(E$21>$D27,E$21<=EDATE($D27,$D$16)),($J$11*(1-$D$17)/$D$16),0) -> 0 | F27: =IF(AND(F$21>$D27,F$21<=EDATE($D27,$D$16)),($J$11*(1-$D$17)/$D$16),0) -> 0 | G27: =IF(AND(G$21>$D27,G$21<=EDATE($D27,$D$16)),($J$11*(1-$D$17)/$D$16),0) -> 0 | H27: =IF(AND(H$21>$D27,H$21<=EDATE($D27,$D$16)),($J$11*(1-$D$17)/$D$16),0) -> 0 | I27: =IF(AND(I$21>$D27,I$21<=EDATE($D27,$D$16)),($J$11*(1-$D$17)/$D$16),0) -> 0 | J27: =IF(AND(J$21>$D27,J$21<=EDATE($D27,$D$16)),($J$11*(1-$D$17)/$D$16),0) -> 0 | K27: =IF(AND(K$21>$D27,K$21<=EDATE($D27,$D$16)),($J$11*(1-$D$17)/$D$16),0) -> 34.4203 | L27: =IF(AND(L$21>$D27,L$21<=EDATE($D27,$D$16)),($J$11*(1-$D$17)/$D$16),0) -> 34.4203 | ... V27: =IF(AND(V$21>$D27,V$21<=EDATE($D27,$D$16)),($J$11*(1-$D$17)/$D$16),0) -> 34.4203 | W27: x
D28: =EDATE(D27,1) -> 46388 | E28: =IF(AND(E$21>$D28,E$21<=EDATE($D28,$D$16)),($K$11*(1-$D$17)/$D$16),0) -> 0 | F28: =IF(AND(F$21>$D28,F$21<=EDATE($D28,$D$16)),($K$11*(1-$D$17)/$D$16),0) -> 0 | G28: =IF(AND(G$21>$D28,G$21<=EDATE($D28,$D$16)),($K$11*(1-$D$17)/$D$16),0) -> 0 | H28: =IF(AND(H$21>$D28,H$21<=EDATE($D28,$D$16)),($K$11*(1-$D$17)/$D$16),0) -> 0 | I28: =IF(AND(I$21>$D28,I$21<=EDATE($D28,$D$16)),($K$11*(1-$D$17)/$D$16),0) -> 0 | J28: =IF(AND(J$21>$D28,J$21<=EDATE($D28,$D$16)),($K$11*(1-$D$17)/$D$16),0) -> 0 | K28: =IF(AND(K$21>$D28,K$21<=EDATE($D28,$D$16)),($K$11*(1-$D$17)/$D$16),0) -> 0 | L28: =IF(AND(L$21>$D28,L$21<=EDATE($D28,$D$16)),($K$11*(1-$D$17)/$D$16),0) -> 51.63045 | ... V28: =IF(AND(V$21>$D28,V$21<=EDATE($D28,$D$16)),($K$11*(1-$D$17)/$D$16),0) -> 51.63045 | W28: x
D29: =EDATE(D28,1) -> 46419 | E29: =IF(AND(E$21>$D29,E$21<=EDATE($D29,$D$16)),($L$11*(1-$D$17)/$D$16),0) -> 0 | F29: =IF(AND(F$21>$D29,F$21<=EDATE($D29,$D$16)),($L$11*(1-$D$17)/$D$16),0) -> 0 | G29: =IF(AND(G$21>$D29,G$21<=EDATE($D29,$D$16)),($L$11*(1-$D$17)/$D$16),0) -> 0 | H29: =IF(AND(H$21>$D29,H$21<=EDATE($D29,$D$16)),($L$11*(1-$D$17)/$D$16),0) -> 0 | I29: =IF(AND(I$21>$D29,I$21<=EDATE($D29,$D$16)),($L$11*(1-$D$17)/$D$16),0) -> 0 | J29: =IF(AND(J$21>$D29,J$21<=EDATE($D29,$D$16)),($L$11*(1-$D$17)/$D$16),0) -> 0 | K29: =IF(AND(K$21>$D29,K$21<=EDATE($D29,$D$16)),($L$11*(1-$D$17)/$D$16),0) -> 0 | L29: =IF(AND(L$21>$D29,L$21<=EDATE($D29,$D$16)),($L$11*(1-$D$17)/$D$16),0) -> 0 | ... V29: =IF(AND(V$21>$D29,V$21<=EDATE($D29,$D$16)),($L$11*(1-$D$17)/$D$16),0) -> 51.63045 | W29: x
D30: =EDATE(D29,1) -> 46447 | E30: =IF(AND(E$21>$D30,E$21<=EDATE($D30,$D$16)),($M$11*(1-$D$17)/$D$16),0) -> 0 | F30: =IF(AND(F$21>$D30,F$21<=EDATE($D30,$D$16)),($M$11*(1-$D$17)/$D$16),0) -> 0 | G30: =IF(AND(G$21>$D30,G$21<=EDATE($D30,$D$16)),($M$11*(1-$D$17)/$D$16),0) -> 0 | H30: =IF(AND(H$21>$D30,H$21<=EDATE($D30,$D$16)),($M$11*(1-$D$17)/$D$16),0) -> 0 | I30: =IF(AND(I$21>$D30,I$21<=EDATE($D30,$D$16)),($M$11*(1-$D$17)/$D$16),0) -> 0 | J30: =IF(AND(J$21>$D30,J$21<=EDATE($D30,$D$16)),($M$11*(1-$D$17)/$D$16),0) -> 0 | K30: =IF(AND(K$21>$D30,K$21<=EDATE($D30,$D$16)),($M$11*(1-$D$17)/$D$16),0) -> 0 | L30: =IF(AND(L$21>$D30,L$21<=EDATE($D30,$D$16)),($M$11*(1-$D$17)/$D$16),0) -> 0 | ... V30: =IF(AND(V$21>$D30,V$21<=EDATE($D30,$D$16)),($M$11*(1-$D$17)/$D$16),0) -> 51.63045 | W30: x
D31: =EDATE(D30,1) -> 46478 | E31: =IF(AND(E$21>$D31,E$21<=EDATE($D31,$D$16)),($N$11*(1-$D$17)/$D$16),0) -> 0 | F31: =IF(AND(F$21>$D31,F$21<=EDATE($D31,$D$16)),($N$11*(1-$D$17)/$D$16),0) -> 0 | G31: =IF(AND(G$21>$D31,G$21<=EDATE($D31,$D$16)),($N$11*(1-$D$17)/$D$16),0) -> 0 | H31: =IF(AND(H$21>$D31,H$21<=EDATE($D31,$D$16)),($N$11*(1-$D$17)/$D$16),0) -> 0 | I31: =IF(AND(I$21>$D31,I$21<=EDATE($D31,$D$16)),($N$11*(1-$D$17)/$D$16),0) -> 0 | J31: =IF(AND(J$21>$D31,J$21<=EDATE($D31,$D$16)),($N$11*(1-$D$17)/$D$16),0) -> 0 | K31: =IF(AND(K$21>$D31,K$21<=EDATE($D31,$D$16)),($N$11*(1-$D$17)/$D$16),0) -> 0 | L31: =IF(AND(L$21>$D31,L$21<=EDATE($D31,$D$16)),($N$11*(1-$D$17)/$D$16),0) -> 0 | ... V31: =IF(AND(V$21>$D31,V$21<=EDATE($D31,$D$16)),($N$11*(1-$D$17)/$D$16),0) -> 51.63045 | W31: x
D32: =EDATE(D31,1) -> 46508 | E32: =IF(AND(E$21>$D32,E$21<=EDATE($D32,$D$16)),($O$11*(1-$D$17)/$D$16),0) -> 0 | F32: =IF(AND(F$21>$D32,F$21<=EDATE($D32,$D$16)),($O$11*(1-$D$17)/$D$16),0) -> 0 | G32: =IF(AND(G$21>$D32,G$21<=EDATE($D32,$D$16)),($O$11*(1-$D$17)/$D$16),0) -> 0 | H32: =IF(AND(H$21>$D32,H$21<=EDATE($D32,$D$16)),($O$11*(1-$D$17)/$D$16),0) -> 0 | I32: =IF(AND(I$21>$D32,I$21<=EDATE($D32,$D$16)),($O$11*(1-$D$17)/$D$16),0) -> 0 | J32: =IF(AND(J$21>$D32,J$21<=EDATE($D32,$D$16)),($O$11*(1-$D$17)/$D$16),0) -> 0 | K32: =IF(AND(K$21>$D32,K$21<=EDATE($D32,$D$16)),($O$11*(1-$D$17)/$D$16),0) -> 0 | L32: =IF(AND(L$21>$D32,L$21<=EDATE($D32,$D$16)),($O$11*(1-$D$17)/$D$16),0) -> 0 | ... V32: =IF(AND(V$21>$D32,V$21<=EDATE($D32,$D$16)),($O$11*(1-$D$17)/$D$16),0) -> 51.63045 | W32: x
D33: =EDATE(D32,1) -> 46539 | E33: =IF(AND(E$21>$D33,E$21<=EDATE($D33,$D$16)),($P$11*(1-$D$17)/$D$16),0) -> 0 | F33: =IF(AND(F$21>$D33,F$21<=EDATE($D33,$D$16)),($P$11*(1-$D$17)/$D$16),0) -> 0 | G33: =IF(AND(G$21>$D33,G$21<=EDATE($D33,$D$16)),($P$11*(1-$D$17)/$D$16),0) -> 0 | H33: =IF(AND(H$21>$D33,H$21<=EDATE($D33,$D$16)),($P$11*(1-$D$17)/$D$16),0) -> 0 | I33: =IF(AND(I$21>$D33,I$21<=EDATE($D33,$D$16)),($P$11*(1-$D$17)/$D$16),0) -> 0 | J33: =IF(AND(J$21>$D33,J$21<=EDATE($D33,$D$16)),($P$11*(1-$D$17)/$D$16),0) -> 0 | K33: =IF(AND(K$21>$D33,K$21<=EDATE($D33,$D$16)),($P$11*(1-$D$17)/$D$16),0) -> 0 | L33: =IF(AND(L$21>$D33,L$21<=EDATE($D33,$D$16)),($P$11*(1-$D$17)/$D$16),0) -> 0 | ... V33: =IF(AND(V$21>$D33,V$21<=EDATE($D33,$D$16)),($P$11*(1-$D$17)/$D$16),0) -> 51.63045 | W33: x
D34: =EDATE(D33,1) -> 46569 | E34: =IF(AND(E$21>$D34,E$21<=EDATE($D34,$D$16)),($Q$11*(1-$D$17)/$D$16),0) -> 0 | F34: =IF(AND(F$21>$D34,F$21<=EDATE($D34,$D$16)),($Q$11*(1-$D$17)/$D$16),0) -> 0 | G34: =IF(AND(G$21>$D34,G$21<=EDATE($D34,$D$16)),($Q$11*(1-$D$17)/$D$16),0) -> 0 | H34: =IF(AND(H$21>$D34,H$21<=EDATE($D34,$D$16)),($Q$11*(1-$D$17)/$D$16),0) -> 0 | I34: =IF(AND(I$21>$D34,I$21<=EDATE($D34,$D$16)),($Q$11*(1-$D$17)/$D$16),0) -> 0 | J34: =IF(AND(J$21>$D34,J$21<=EDATE($D34,$D$16)),($Q$11*(1-$D$17)/$D$16),0) -> 0 | K34: =IF(AND(K$21>$D34,K$21<=EDATE($D34,$D$16)),($Q$11*(1-$D$17)/$D$16),0) -> 0 | L34: =IF(AND(L$21>$D34,L$21<=EDATE($D34,$D$16)),($Q$11*(1-$D$17)/$D$16),0) -> 0 | ... V34: =IF(AND(V$21>$D34,V$21<=EDATE($D34,$D$16)),($Q$11*(1-$D$17)/$D$16),0) -> 51.63045 | W34: x
D35: =EDATE(D34,1) -> 46600 | E35: =IF(AND(E$21>$D35,E$21<=EDATE($D35,$D$16)),($R$11*(1-$D$17)/$D$16),0) -> 0 | F35: =IF(AND(F$21>$D35,F$21<=EDATE($D35,$D$16)),($R$11*(1-$D$17)/$D$16),0) -> 0 | G35: =IF(AND(G$21>$D35,G$21<=EDATE($D35,$D$16)),($R$11*(1-$D$17)/$D$16),0) -> 0 | H35: =IF(AND(H$21>$D35,H$21<=EDATE($D35,$D$16)),($R$11*(1-$D$17)/$D$16),0) -> 0 | I35: =IF(AND(I$21>$D35,I$21<=EDATE($D35,$D$16)),($R$11*(1-$D$17)/$D$16),0) -> 0 | J35: =IF(AND(J$21>$D35,J$21<=EDATE($D35,$D$16)),($R$11*(1-$D$17)/$D$16),0) -> 0 | K35: =IF(AND(K$21>$D35,K$21<=EDATE($D35,$D$16)),($R$11*(1-$D$17)/$D$16),0) -> 0 | L35: =IF(AND(L$21>$D35,L$21<=EDATE($D35,$D$16)),($R$11*(1-$D$17)/$D$16),0) -> 0 | ... V35: =IF(AND(V$21>$D35,V$21<=EDATE($D35,$D$16)),($R$11*(1-$D$17)/$D$16),0) -> 51.63045 | W35: x
D36: =EDATE(D35,1) -> 46631 | E36: =IF(AND(E$21>$D36,E$21<=EDATE($D36,$D$16)),($S$11*(1-$D$17)/$D$16),0) -> 0 | F36: =IF(AND(F$21>$D36,F$21<=EDATE($D36,$D$16)),($S$11*(1-$D$17)/$D$16),0) -> 0 | G36: =IF(AND(G$21>$D36,G$21<=EDATE($D36,$D$16)),($S$11*(1-$D$17)/$D$16),0) -> 0 | H36: =IF(AND(H$21>$D36,H$21<=EDATE($D36,$D$16)),($S$11*(1-$D$17)/$D$16),0) -> 0 | I36: =IF(AND(I$21>$D36,I$21<=EDATE($D36,$D$16)),($S$11*(1-$D$17)/$D$16),0) -> 0 | J36: =IF(AND(J$21>$D36,J$21<=EDATE($D36,$D$16)),($S$11*(1-$D$17)/$D$16),0) -> 0 | K36: =IF(AND(K$21>$D36,K$21<=EDATE($D36,$D$16)),($S$11*(1-$D$17)/$D$16),0) -> 0 | L36: =IF(AND(L$21>$D36,L$21<=EDATE($D36,$D$16)),($S$11*(1-$D$17)/$D$16),0) -> 0 | ... V36: =IF(AND(V$21>$D36,V$21<=EDATE($D36,$D$16)),($S$11*(1-$D$17)/$D$16),0) -> 51.63045 | W36: x
D37: =EDATE(D36,1) -> 46661 | E37: =IF(AND(E$21>$D37,E$21<=EDATE($D37,$D$16)),($T$11*(1-$D$17)/$D$16),0) -> 0 | F37: =IF(AND(F$21>$D37,F$21<=EDATE($D37,$D$16)),($T$11*(1-$D$17)/$D$16),0) -> 0 | G37: =IF(AND(G$21>$D37,G$21<=EDATE($D37,$D$16)),($T$11*(1-$D$17)/$D$16),0) -> 0 | H37: =IF(AND(H$21>$D37,H$21<=EDATE($D37,$D$16)),($T$11*(1-$D$17)/$D$16),0) -> 0 | I37: =IF(AND(I$21>$D37,I$21<=EDATE($D37,$D$16)),($T$11*(1-$D$17)/$D$16),0) -> 0 | J37: =IF(AND(J$21>$D37,J$21<=EDATE($D37,$D$16)),($T$11*(1-$D$17)/$D$16),0) -> 0 | K37: =IF(AND(K$21>$D37,K$21<=EDATE($D37,$D$16)),($T$11*(1-$D$17)/$D$16),0) -> 0 | L37: =IF(AND(L$21>$D37,L$21<=EDATE($D37,$D$16)),($T$11*(1-$D$17)/$D$16),0) -> 0 | ... V37: =IF(AND(V$21>$D37,V$21<=EDATE($D37,$D$16)),($T$11*(1-$D$17)/$D$16),0) -> 51.63045 | W37: x
D38: =EDATE(D37,1) -> 46692 | E38: =IF(AND(E$21>$D38,E$21<=EDATE($D38,$D$16)),($U$11*(1-$D$17)/$D$16),0) -> 0 | F38: =IF(AND(F$21>$D38,F$21<=EDATE($D38,$D$16)),($U$11*(1-$D$17)/$D$16),0) -> 0 | G38: =IF(AND(G$21>$D38,G$21<=EDATE($D38,$D$16)),($U$11*(1-$D$17)/$D$16),0) -> 0 | H38: =IF(AND(H$21>$D38,H$21<=EDATE($D38,$D$16)),($U$11*(1-$D$17)/$D$16),0) -> 0 | I38: =IF(AND(I$21>$D38,I$21<=EDATE($D38,$D$16)),($U$11*(1-$D$17)/$D$16),0) -> 0 | J38: =IF(AND(J$21>$D38,J$21<=EDATE($D38,$D$16)),($U$11*(1-$D$17)/$D$16),0) -> 0 | K38: =IF(AND(K$21>$D38,K$21<=EDATE($D38,$D$16)),($U$11*(1-$D$17)/$D$16),0) -> 0 | L38: =IF(AND(L$21>$D38,L$21<=EDATE($D38,$D$16)),($U$11*(1-$D$17)/$D$16),0) -> 0 | ... V38: =IF(AND(V$21>$D38,V$21<=EDATE($D38,$D$16)),($U$11*(1-$D$17)/$D$16),0) -> 51.63045 | W38: x
D39: =EDATE(D38,1) -> 46722 | E39: =IF(AND(E$21>$D39,E$21<=EDATE($D39,$D$16)),($V$11*(1-$D$17)/$D$16),0) -> 0 | F39: =IF(AND(F$21>$D39,F$21<=EDATE($D39,$D$16)),($V$11*(1-$D$17)/$D$16),0) -> 0 | G39: =IF(AND(G$21>$D39,G$21<=EDATE($D39,$D$16)),($V$11*(1-$D$17)/$D$16),0) -> 0 | H39: =IF(AND(H$21>$D39,H$21<=EDATE($D39,$D$16)),($V$11*(1-$D$17)/$D$16),0) -> 0 | I39: =IF(AND(I$21>$D39,I$21<=EDATE($D39,$D$16)),($V$11*(1-$D$17)/$D$16),0) -> 0 | J39: =IF(AND(J$21>$D39,J$21<=EDATE($D39,$D$16)),($V$11*(1-$D$17)/$D$16),0) -> 0 | K39: =IF(AND(K$21>$D39,K$21<=EDATE($D39,$D$16)),($V$11*(1-$D$17)/$D$16),0) -> 0 | L39: =IF(AND(L$21>$D39,L$21<=EDATE($D39,$D$16)),($V$11*(1-$D$17)/$D$16),0) -> 0 | ... V39: =IF(AND(V$21>$D39,V$21<=EDATE($D39,$D$16)),($V$11*(1-$D$17)/$D$16),0) -> 0 | W39: x
W40: x
D41: Total | E41: =SUM(E22:E39) -> 0 | F41: =SUM(F22:F39) -> 34.4203 | G41: =SUM(G22:G39) -> 68.8406 | H41: =SUM(H22:H39) -> 103.2609 | I41: =SUM(I22:I39) -> 137.6812 | J41: =SUM(J22:J39) -> 172.1015 | K41: =SUM(K22:K39) -> 206.5218 | L41: =SUM(L22:L39) -> 258.15225 | ... V41: =SUM(V22:V39) -> 774.45675 | W41: x
W42: x
W43: x
B44: Allowance-Addition of electrionic equipment from UOP_BS_Prepayment | AT44: x
W45: x
B46: Beginning Balance | E46: 0 | F46: =E49 -> 1956.5223 | G46: =F49 -> 3750.0011 | H46: =G49 -> 5380.4364 | I46: =H49 -> 6847.8281 | J46: =I49 -> 8152.1763 | K46: =J49 -> 9293.481 | L46: =K49 -> 11250.003 | M46: =L49 -> 12961.96 | ... V46: =U49 -> 18994.571 | W46: x
C47: (+) Additions | E47: =UOP!L12 -> 1956.5223 | F47: =UOP!M12 -> 1956.5223 | G47: =UOP!N12 -> 1956.5223 | H47: =UOP!O12 -> 1956.5223 | I47: =UOP!P12 -> 1956.5223 | J47: =UOP!Q12 -> 1956.5223 | K47: =UOP!R12 -> 2934.7835 | L47: =UOP!S12 -> 2934.7835 | ... V47: =UOP!AC12 -> 2934.7835 | W47: x
C48: (-) Depreciation charges | E48: =-E77 -> 0 | F48: =-F77 -> -163.04353 | G48: =-G77 -> -326.08705 | H48: =-H77 -> -489.13058 | I48: =-I77 -> -652.17411 | J48: =-J77 -> -815.21763 | K48: =-K77 -> -978.26116 | L48: =-L77 -> -1222.8264 | ... V48: =-V77 -> -2853.2617 | W48: x
B49: Ending Balance | E49: =E46+E47+E48 -> 1956.5223 | F49: =F46+F47+F48 -> 3750.0011 | G49: =G46+G47+G48 -> 5380.4364 | H49: =H46+H47+H48 -> 6847.8281 | I49: =I46+I47+I48 -> 8152.1763 | J49: =J46+J47+J48 -> 9293.481 | K49: =K46+K47+K48 -> 11250.003 | L49: =L46+L47+L48 -> 12961.96 | ... V49: =V46+V47+V48 -> 19076.093 | W49: x
W50: x
W51: x
C52: Useful Life | D52: 12 | E52: months | W52: x
C53: Residual rate | D53: 0 | W53: x
W54: x
W55: x
W56: x
B57: Depreciation | E57: 46204 | F57: =EDATE(E57,1) -> 46235 | G57: =EDATE(F57,1) -> 46266 | H57: =EDATE(G57,1) -> 46296 | I57: =EDATE(H57,1) -> 46327 | J57: =EDATE(I57,1) -> 46357 | K57: =EDATE(J57,1) -> 46388 | L57: =EDATE(K57,1) -> 46419 | M57: =EDATE(L57,1) -> 46447 | ... V57: =EDATE(U57,1) -> 46722 | W57: x
D58: 46204 | E58: =IF(AND(E$57>$D58,E$57<=EDATE($D58,$D$52)),($E$47*(1-$D$53)/$D$52),0) -> 0 | F58: =IF(AND(F$57>$D58,F$57<=EDATE($D58,$D$52)),($E$47*(1-$D$53)/$D$52),0) -> 163.04353 | G58: =IF(AND(G$57>$D58,G$57<=EDATE($D58,$D$52)),($E$47*(1-$D$53)/$D$52),0) -> 163.04353 | H58: =IF(AND(H$57>$D58,H$57<=EDATE($D58,$D$52)),($E$47*(1-$D$53)/$D$52),0) -> 163.04353 | I58: =IF(AND(I$57>$D58,I$57<=EDATE($D58,$D$52)),($E$47*(1-$D$53)/$D$52),0) -> 163.04353 | J58: =IF(AND(J$57>$D58,J$57<=EDATE($D58,$D$52)),($E$47*(1-$D$53)/$D$52),0) -> 163.04353 | K58: =IF(AND(K$57>$D58,K$57<=EDATE($D58,$D$52)),($E$47*(1-$D$53)/$D$52),0) -> 163.04353 | L58: =IF(AND(L$57>$D58,L$57<=EDATE($D58,$D$52)),($E$47*(1-$D$53)/$D$52),0) -> 163.04353 | ... V58: =IF(AND(V$57>$D58,V$57<=EDATE($D58,$D$52)),($E$47*(1-$D$53)/$D$52),0) -> 0 | W58: x
D59: =EDATE(D58,1) -> 46235 | E59: =IF(AND(E$57>$D59,E$57<=EDATE($D59,$D$52)),($F$47*(1-$D$53)/$D$52),0) -> 0 | F59: =IF(AND(F$57>$D59,F$57<=EDATE($D59,$D$52)),($F$47*(1-$D$53)/$D$52),0) -> 0 | G59: =IF(AND(G$57>$D59,G$57<=EDATE($D59,$D$52)),($F$47*(1-$D$53)/$D$52),0) -> 163.04353 | H59: =IF(AND(H$57>$D59,H$57<=EDATE($D59,$D$52)),($F$47*(1-$D$53)/$D$52),0) -> 163.04353 | I59: =IF(AND(I$57>$D59,I$57<=EDATE($D59,$D$52)),($F$47*(1-$D$53)/$D$52),0) -> 163.04353 | J59: =IF(AND(J$57>$D59,J$57<=EDATE($D59,$D$52)),($F$47*(1-$D$53)/$D$52),0) -> 163.04353 | K59: =IF(AND(K$57>$D59,K$57<=EDATE($D59,$D$52)),($F$47*(1-$D$53)/$D$52),0) -> 163.04353 | L59: =IF(AND(L$57>$D59,L$57<=EDATE($D59,$D$52)),($F$47*(1-$D$53)/$D$52),0) -> 163.04353 | ... V59: =IF(AND(V$57>$D59,V$57<=EDATE($D59,$D$52)),($F$47*(1-$D$53)/$D$52),0) -> 0 | W59: x
D60: =EDATE(D59,1) -> 46266 | E60: =IF(AND(E$57>$D60,E$57<=EDATE($D60,$D$52)),($G$47*(1-$D$53)/$D$52),0) -> 0 | F60: =IF(AND(F$57>$D60,F$57<=EDATE($D60,$D$52)),($G$47*(1-$D$53)/$D$52),0) -> 0 | G60: =IF(AND(G$57>$D60,G$57<=EDATE($D60,$D$52)),($G$47*(1-$D$53)/$D$52),0) -> 0 | H60: =IF(AND(H$57>$D60,H$57<=EDATE($D60,$D$52)),($G$47*(1-$D$53)/$D$52),0) -> 163.04353 | I60: =IF(AND(I$57>$D60,I$57<=EDATE($D60,$D$52)),($G$47*(1-$D$53)/$D$52),0) -> 163.04353 | J60: =IF(AND(J$57>$D60,J$57<=EDATE($D60,$D$52)),($G$47*(1-$D$53)/$D$52),0) -> 163.04353 | K60: =IF(AND(K$57>$D60,K$57<=EDATE($D60,$D$52)),($G$47*(1-$D$53)/$D$52),0) -> 163.04353 | L60: =IF(AND(L$57>$D60,L$57<=EDATE($D60,$D$52)),($G$47*(1-$D$53)/$D$52),0) -> 163.04353 | ... V60: =IF(AND(V$57>$D60,V$57<=EDATE($D60,$D$52)),($G$47*(1-$D$53)/$D$52),0) -> 0 | W60: x
D61: =EDATE(D60,1) -> 46296 | E61: =IF(AND(E$57>$D61,E$57<=EDATE($D61,$D$52)),($H$47*(1-$D$53)/$D$52),0) -> 0 | F61: =IF(AND(F$57>$D61,F$57<=EDATE($D61,$D$52)),($H$47*(1-$D$53)/$D$52),0) -> 0 | G61: =IF(AND(G$57>$D61,G$57<=EDATE($D61,$D$52)),($H$47*(1-$D$53)/$D$52),0) -> 0 | H61: =IF(AND(H$57>$D61,H$57<=EDATE($D61,$D$52)),($H$47*(1-$D$53)/$D$52),0) -> 0 | I61: =IF(AND(I$57>$D61,I$57<=EDATE($D61,$D$52)),($H$47*(1-$D$53)/$D$52),0) -> 163.04353 | J61: =IF(AND(J$57>$D61,J$57<=EDATE($D61,$D$52)),($H$47*(1-$D$53)/$D$52),0) -> 163.04353 | K61: =IF(AND(K$57>$D61,K$57<=EDATE($D61,$D$52)),($H$47*(1-$D$53)/$D$52),0) -> 163.04353 | L61: =IF(AND(L$57>$D61,L$57<=EDATE($D61,$D$52)),($H$47*(1-$D$53)/$D$52),0) -> 163.04353 | ... V61: =IF(AND(V$57>$D61,V$57<=EDATE($D61,$D$52)),($H$47*(1-$D$53)/$D$52),0) -> 0 | W61: x
D62: =EDATE(D61,1) -> 46327 | E62: =IF(AND(E$57>$D62,E$57<=EDATE($D62,$D$52)),($I$47*(1-$D$53)/$D$52),0) -> 0 | F62: =IF(AND(F$57>$D62,F$57<=EDATE($D62,$D$52)),($I$47*(1-$D$53)/$D$52),0) -> 0 | G62: =IF(AND(G$57>$D62,G$57<=EDATE($D62,$D$52)),($I$47*(1-$D$53)/$D$52),0) -> 0 | H62: =IF(AND(H$57>$D62,H$57<=EDATE($D62,$D$52)),($I$47*(1-$D$53)/$D$52),0) -> 0 | I62: =IF(AND(I$57>$D62,I$57<=EDATE($D62,$D$52)),($I$47*(1-$D$53)/$D$52),0) -> 0 | J62: =IF(AND(J$57>$D62,J$57<=EDATE($D62,$D$52)),($I$47*(1-$D$53)/$D$52),0) -> 163.04353 | K62: =IF(AND(K$57>$D62,K$57<=EDATE($D62,$D$52)),($I$47*(1-$D$53)/$D$52),0) -> 163.04353 | L62: =IF(AND(L$57>$D62,L$57<=EDATE($D62,$D$52)),($I$47*(1-$D$53)/$D$52),0) -> 163.04353 | ... V62: =IF(AND(V$57>$D62,V$57<=EDATE($D62,$D$52)),($I$47*(1-$D$53)/$D$52),0) -> 0 | W62: x
D63: =EDATE(D62,1) -> 46357 | E63: =IF(AND(E$57>$D63,E$57<=EDATE($D63,$D$52)),($J$47*(1-$D$53)/$D$52),0) -> 0 | F63: =IF(AND(F$57>$D63,F$57<=EDATE($D63,$D$52)),($J$47*(1-$D$53)/$D$52),0) -> 0 | G63: =IF(AND(G$57>$D63,G$57<=EDATE($D63,$D$52)),($J$47*(1-$D$53)/$D$52),0) -> 0 | H63: =IF(AND(H$57>$D63,H$57<=EDATE($D63,$D$52)),($J$47*(1-$D$53)/$D$52),0) -> 0 | I63: =IF(AND(I$57>$D63,I$57<=EDATE($D63,$D$52)),($J$47*(1-$D$53)/$D$52),0) -> 0 | J63: =IF(AND(J$57>$D63,J$57<=EDATE($D63,$D$52)),($J$47*(1-$D$53)/$D$52),0) -> 0 | K63: =IF(AND(K$57>$D63,K$57<=EDATE($D63,$D$52)),($J$47*(1-$D$53)/$D$52),0) -> 163.04353 | L63: =IF(AND(L$57>$D63,L$57<=EDATE($D63,$D$52)),($J$47*(1-$D$53)/$D$52),0) -> 163.04353 | ... V63: =IF(AND(V$57>$D63,V$57<=EDATE($D63,$D$52)),($J$47*(1-$D$53)/$D$52),0) -> 163.04353 | W63: x
D64: =EDATE(D63,1) -> 46388 | E64: =IF(AND(E$57>$D64,E$57<=EDATE($D64,$D$52)),($K$47*(1-$D$53)/$D$52),0) -> 0 | F64: =IF(AND(F$57>$D64,F$57<=EDATE($D64,$D$52)),($K$47*(1-$D$53)/$D$52),0) -> 0 | G64: =IF(AND(G$57>$D64,G$57<=EDATE($D64,$D$52)),($K$47*(1-$D$53)/$D$52),0) -> 0 | H64: =IF(AND(H$57>$D64,H$57<=EDATE($D64,$D$52)),($K$47*(1-$D$53)/$D$52),0) -> 0 | I64: =IF(AND(I$57>$D64,I$57<=EDATE($D64,$D$52)),($K$47*(1-$D$53)/$D$52),0) -> 0 | J64: =IF(AND(J$57>$D64,J$57<=EDATE($D64,$D$52)),($K$47*(1-$D$53)/$D$52),0) -> 0 | K64: =IF(AND(K$57>$D64,K$57<=EDATE($D64,$D$52)),($K$47*(1-$D$53)/$D$52),0) -> 0 | L64: =IF(AND(L$57>$D64,L$57<=EDATE($D64,$D$52)),($K$47*(1-$D$53)/$D$52),0) -> 244.56529 | ... V64: =IF(AND(V$57>$D64,V$57<=EDATE($D64,$D$52)),($K$47*(1-$D$53)/$D$52),0) -> 244.56529 | W64: x
D65: =EDATE(D64,1) -> 46419 | E65: =IF(AND(E$57>$D65,E$57<=EDATE($D65,$D$52)),($L$47*(1-$D$53)/$D$52),0) -> 0 | F65: =IF(AND(F$57>$D65,F$57<=EDATE($D65,$D$52)),($L$47*(1-$D$53)/$D$52),0) -> 0 | G65: =IF(AND(G$57>$D65,G$57<=EDATE($D65,$D$52)),($L$47*(1-$D$53)/$D$52),0) -> 0 | H65: =IF(AND(H$57>$D65,H$57<=EDATE($D65,$D$52)),($L$47*(1-$D$53)/$D$52),0) -> 0 | I65: =IF(AND(I$57>$D65,I$57<=EDATE($D65,$D$52)),($L$47*(1-$D$53)/$D$52),0) -> 0 | J65: =IF(AND(J$57>$D65,J$57<=EDATE($D65,$D$52)),($L$47*(1-$D$53)/$D$52),0) -> 0 | K65: =IF(AND(K$57>$D65,K$57<=EDATE($D65,$D$52)),($L$47*(1-$D$53)/$D$52),0) -> 0 | L65: =IF(AND(L$57>$D65,L$57<=EDATE($D65,$D$52)),($L$47*(1-$D$53)/$D$52),0) -> 0 | ... V65: =IF(AND(V$57>$D65,V$57<=EDATE($D65,$D$52)),($L$47*(1-$D$53)/$D$52),0) -> 244.56529 | W65: x
D66: =EDATE(D65,1) -> 46447 | E66: =IF(AND(E$57>$D66,E$57<=EDATE($D66,$D$52)),($M$47*(1-$D$53)/$D$52),0) -> 0 | F66: =IF(AND(F$57>$D66,F$57<=EDATE($D66,$D$52)),($M$47*(1-$D$53)/$D$52),0) -> 0 | G66: =IF(AND(G$57>$D66,G$57<=EDATE($D66,$D$52)),($M$47*(1-$D$53)/$D$52),0) -> 0 | H66: =IF(AND(H$57>$D66,H$57<=EDATE($D66,$D$52)),($M$47*(1-$D$53)/$D$52),0) -> 0 | I66: =IF(AND(I$57>$D66,I$57<=EDATE($D66,$D$52)),($M$47*(1-$D$53)/$D$52),0) -> 0 | J66: =IF(AND(J$57>$D66,J$57<=EDATE($D66,$D$52)),($M$47*(1-$D$53)/$D$52),0) -> 0 | K66: =IF(AND(K$57>$D66,K$57<=EDATE($D66,$D$52)),($M$47*(1-$D$53)/$D$52),0) -> 0 | L66: =IF(AND(L$57>$D66,L$57<=EDATE($D66,$D$52)),($M$47*(1-$D$53)/$D$52),0) -> 0 | ... V66: =IF(AND(V$57>$D66,V$57<=EDATE($D66,$D$52)),($M$47*(1-$D$53)/$D$52),0) -> 244.56529 | W66: x
D67: =EDATE(D66,1) -> 46478 | E67: =IF(AND(E$57>$D67,E$57<=EDATE($D67,$D$52)),($N$47*(1-$D$53)/$D$52),0) -> 0 | F67: =IF(AND(F$57>$D67,F$57<=EDATE($D67,$D$52)),($N$47*(1-$D$53)/$D$52),0) -> 0 | G67: =IF(AND(G$57>$D67,G$57<=EDATE($D67,$D$52)),($N$47*(1-$D$53)/$D$52),0) -> 0 | H67: =IF(AND(H$57>$D67,H$57<=EDATE($D67,$D$52)),($N$47*(1-$D$53)/$D$52),0) -> 0 | I67: =IF(AND(I$57>$D67,I$57<=EDATE($D67,$D$52)),($N$47*(1-$D$53)/$D$52),0) -> 0 | J67: =IF(AND(J$57>$D67,J$57<=EDATE($D67,$D$52)),($N$47*(1-$D$53)/$D$52),0) -> 0 | K67: =IF(AND(K$57>$D67,K$57<=EDATE($D67,$D$52)),($N$47*(1-$D$53)/$D$52),0) -> 0 | L67: =IF(AND(L$57>$D67,L$57<=EDATE($D67,$D$52)),($N$47*(1-$D$53)/$D$52),0) -> 0 | ... V67: =IF(AND(V$57>$D67,V$57<=EDATE($D67,$D$52)),($N$47*(1-$D$53)/$D$52),0) -> 244.56529 | W67: x
D68: =EDATE(D67,1) -> 46508 | E68: =IF(AND(E$57>$D68,E$57<=EDATE($D68,$D$52)),($O$47*(1-$D$53)/$D$52),0) -> 0 | F68: =IF(AND(F$57>$D68,F$57<=EDATE($D68,$D$52)),($O$47*(1-$D$53)/$D$52),0) -> 0 | G68: =IF(AND(G$57>$D68,G$57<=EDATE($D68,$D$52)),($O$47*(1-$D$53)/$D$52),0) -> 0 | H68: =IF(AND(H$57>$D68,H$57<=EDATE($D68,$D$52)),($O$47*(1-$D$53)/$D$52),0) -> 0 | I68: =IF(AND(I$57>$D68,I$57<=EDATE($D68,$D$52)),($O$47*(1-$D$53)/$D$52),0) -> 0 | J68: =IF(AND(J$57>$D68,J$57<=EDATE($D68,$D$52)),($O$47*(1-$D$53)/$D$52),0) -> 0 | K68: =IF(AND(K$57>$D68,K$57<=EDATE($D68,$D$52)),($O$47*(1-$D$53)/$D$52),0) -> 0 | L68: =IF(AND(L$57>$D68,L$57<=EDATE($D68,$D$52)),($O$47*(1-$D$53)/$D$52),0) -> 0 | ... V68: =IF(AND(V$57>$D68,V$57<=EDATE($D68,$D$52)),($O$47*(1-$D$53)/$D$52),0) -> 244.56529 | W68: x
D69: =EDATE(D68,1) -> 46539 | E69: =IF(AND(E$57>$D69,E$57<=EDATE($D69,$D$52)),($P$47*(1-$D$53)/$D$52),0) -> 0 | F69: =IF(AND(F$57>$D69,F$57<=EDATE($D69,$D$52)),($P$47*(1-$D$53)/$D$52),0) -> 0 | G69: =IF(AND(G$57>$D69,G$57<=EDATE($D69,$D$52)),($P$47*(1-$D$53)/$D$52),0) -> 0 | H69: =IF(AND(H$57>$D69,H$57<=EDATE($D69,$D$52)),($P$47*(1-$D$53)/$D$52),0) -> 0 | I69: =IF(AND(I$57>$D69,I$57<=EDATE($D69,$D$52)),($P$47*(1-$D$53)/$D$52),0) -> 0 | J69: =IF(AND(J$57>$D69,J$57<=EDATE($D69,$D$52)),($P$47*(1-$D$53)/$D$52),0) -> 0 | K69: =IF(AND(K$57>$D69,K$57<=EDATE($D69,$D$52)),($P$47*(1-$D$53)/$D$52),0) -> 0 | L69: =IF(AND(L$57>$D69,L$57<=EDATE($D69,$D$52)),($P$47*(1-$D$53)/$D$52),0) -> 0 | ... V69: =IF(AND(V$57>$D69,V$57<=EDATE($D69,$D$52)),($P$47*(1-$D$53)/$D$52),0) -> 244.56529 | W69: x
D70: =EDATE(D69,1) -> 46569 | E70: =IF(AND(E$57>$D70,E$57<=EDATE($D70,$D$52)),($Q$47*(1-$D$53)/$D$52),0) -> 0 | F70: =IF(AND(F$57>$D70,F$57<=EDATE($D70,$D$52)),($Q$47*(1-$D$53)/$D$52),0) -> 0 | G70: =IF(AND(G$57>$D70,G$57<=EDATE($D70,$D$52)),($Q$47*(1-$D$53)/$D$52),0) -> 0 | H70: =IF(AND(H$57>$D70,H$57<=EDATE($D70,$D$52)),($Q$47*(1-$D$53)/$D$52),0) -> 0 | I70: =IF(AND(I$57>$D70,I$57<=EDATE($D70,$D$52)),($Q$47*(1-$D$53)/$D$52),0) -> 0 | J70: =IF(AND(J$57>$D70,J$57<=EDATE($D70,$D$52)),($Q$47*(1-$D$53)/$D$52),0) -> 0 | K70: =IF(AND(K$57>$D70,K$57<=EDATE($D70,$D$52)),($Q$47*(1-$D$53)/$D$52),0) -> 0 | L70: =IF(AND(L$57>$D70,L$57<=EDATE($D70,$D$52)),($Q$47*(1-$D$53)/$D$52),0) -> 0 | ... V70: =IF(AND(V$57>$D70,V$57<=EDATE($D70,$D$52)),($Q$47*(1-$D$53)/$D$52),0) -> 244.56529 | W70: x
D71: =EDATE(D70,1) -> 46600 | E71: =IF(AND(E$57>$D71,E$57<=EDATE($D71,$D$52)),($R$47*(1-$D$53)/$D$52),0) -> 0 | F71: =IF(AND(F$57>$D71,F$57<=EDATE($D71,$D$52)),($R$47*(1-$D$53)/$D$52),0) -> 0 | G71: =IF(AND(G$57>$D71,G$57<=EDATE($D71,$D$52)),($R$47*(1-$D$53)/$D$52),0) -> 0 | H71: =IF(AND(H$57>$D71,H$57<=EDATE($D71,$D$52)),($R$47*(1-$D$53)/$D$52),0) -> 0 | I71: =IF(AND(I$57>$D71,I$57<=EDATE($D71,$D$52)),($R$47*(1-$D$53)/$D$52),0) -> 0 | J71: =IF(AND(J$57>$D71,J$57<=EDATE($D71,$D$52)),($R$47*(1-$D$53)/$D$52),0) -> 0 | K71: =IF(AND(K$57>$D71,K$57<=EDATE($D71,$D$52)),($R$47*(1-$D$53)/$D$52),0) -> 0 | L71: =IF(AND(L$57>$D71,L$57<=EDATE($D71,$D$52)),($R$47*(1-$D$53)/$D$52),0) -> 0 | ... V71: =IF(AND(V$57>$D71,V$57<=EDATE($D71,$D$52)),($R$47*(1-$D$53)/$D$52),0) -> 244.56529 | W71: x
D72: =EDATE(D71,1) -> 46631 | E72: =IF(AND(E$57>$D72,E$57<=EDATE($D72,$D$52)),($S$47*(1-$D$53)/$D$52),0) -> 0 | F72: =IF(AND(F$57>$D72,F$57<=EDATE($D72,$D$52)),($S$47*(1-$D$53)/$D$52),0) -> 0 | G72: =IF(AND(G$57>$D72,G$57<=EDATE($D72,$D$52)),($S$47*(1-$D$53)/$D$52),0) -> 0 | H72: =IF(AND(H$57>$D72,H$57<=EDATE($D72,$D$52)),($S$47*(1-$D$53)/$D$52),0) -> 0 | I72: =IF(AND(I$57>$D72,I$57<=EDATE($D72,$D$52)),($S$47*(1-$D$53)/$D$52),0) -> 0 | J72: =IF(AND(J$57>$D72,J$57<=EDATE($D72,$D$52)),($S$47*(1-$D$53)/$D$52),0) -> 0 | K72: =IF(AND(K$57>$D72,K$57<=EDATE($D72,$D$52)),($S$47*(1-$D$53)/$D$52),0) -> 0 | L72: =IF(AND(L$57>$D72,L$57<=EDATE($D72,$D$52)),($S$47*(1-$D$53)/$D$52),0) -> 0 | ... V72: =IF(AND(V$57>$D72,V$57<=EDATE($D72,$D$52)),($S$47*(1-$D$53)/$D$52),0) -> 244.56529 | W72: x
D73: =EDATE(D72,1) -> 46661 | E73: =IF(AND(E$57>$D73,E$57<=EDATE($D73,$D$52)),($T$47*(1-$D$53)/$D$52),0) -> 0 | F73: =IF(AND(F$57>$D73,F$57<=EDATE($D73,$D$52)),($T$47*(1-$D$53)/$D$52),0) -> 0 | G73: =IF(AND(G$57>$D73,G$57<=EDATE($D73,$D$52)),($T$47*(1-$D$53)/$D$52),0) -> 0 | H73: =IF(AND(H$57>$D73,H$57<=EDATE($D73,$D$52)),($T$47*(1-$D$53)/$D$52),0) -> 0 | I73: =IF(AND(I$57>$D73,I$57<=EDATE($D73,$D$52)),($T$47*(1-$D$53)/$D$52),0) -> 0 | J73: =IF(AND(J$57>$D73,J$57<=EDATE($D73,$D$52)),($T$47*(1-$D$53)/$D$52),0) -> 0 | K73: =IF(AND(K$57>$D73,K$57<=EDATE($D73,$D$52)),($T$47*(1-$D$53)/$D$52),0) -> 0 | L73: =IF(AND(L$57>$D73,L$57<=EDATE($D73,$D$52)),($T$47*(1-$D$53)/$D$52),0) -> 0 | ... V73: =IF(AND(V$57>$D73,V$57<=EDATE($D73,$D$52)),($T$47*(1-$D$53)/$D$52),0) -> 244.56529 | W73: x
D74: =EDATE(D73,1) -> 46692 | E74: =IF(AND(E$57>$D74,E$57<=EDATE($D74,$D$52)),($U$47*(1-$D$53)/$D$52),0) -> 0 | F74: =IF(AND(F$57>$D74,F$57<=EDATE($D74,$D$52)),($U$47*(1-$D$53)/$D$52),0) -> 0 | G74: =IF(AND(G$57>$D74,G$57<=EDATE($D74,$D$52)),($U$47*(1-$D$53)/$D$52),0) -> 0 | H74: =IF(AND(H$57>$D74,H$57<=EDATE($D74,$D$52)),($U$47*(1-$D$53)/$D$52),0) -> 0 | I74: =IF(AND(I$57>$D74,I$57<=EDATE($D74,$D$52)),($U$47*(1-$D$53)/$D$52),0) -> 0 | J74: =IF(AND(J$57>$D74,J$57<=EDATE($D74,$D$52)),($U$47*(1-$D$53)/$D$52),0) -> 0 | K74: =IF(AND(K$57>$D74,K$57<=EDATE($D74,$D$52)),($U$47*(1-$D$53)/$D$52),0) -> 0 | L74: =IF(AND(L$57>$D74,L$57<=EDATE($D74,$D$52)),($U$47*(1-$D$53)/$D$52),0) -> 0 | ... V74: =IF(AND(V$57>$D74,V$57<=EDATE($D74,$D$52)),($U$47*(1-$D$53)/$D$52),0) -> 244.56529 | W74: x
D75: =EDATE(D74,1) -> 46722 | E75: =IF(AND(E$57>$D75,E$57<=EDATE($D75,$D$52)),($V$47*(1-$D$53)/$D$52),0) -> 0 | F75: =IF(AND(F$57>$D75,F$57<=EDATE($D75,$D$52)),($V$47*(1-$D$53)/$D$52),0) -> 0 | G75: =IF(AND(G$57>$D75,G$57<=EDATE($D75,$D$52)),($V$47*(1-$D$53)/$D$52),0) -> 0 | H75: =IF(AND(H$57>$D75,H$57<=EDATE($D75,$D$52)),($V$47*(1-$D$53)/$D$52),0) -> 0 | I75: =IF(AND(I$57>$D75,I$57<=EDATE($D75,$D$52)),($V$47*(1-$D$53)/$D$52),0) -> 0 | J75: =IF(AND(J$57>$D75,J$57<=EDATE($D75,$D$52)),($V$47*(1-$D$53)/$D$52),0) -> 0 | K75: =IF(AND(K$57>$D75,K$57<=EDATE($D75,$D$52)),($V$47*(1-$D$53)/$D$52),0) -> 0 | L75: =IF(AND(L$57>$D75,L$57<=EDATE($D75,$D$52)),($V$47*(1-$D$53)/$D$52),0) -> 0 | ... V75: =IF(AND(V$57>$D75,V$57<=EDATE($D75,$D$52)),($V$47*(1-$D$53)/$D$52),0) -> 0 | W75: x
W76: x
D77: Total | E77: =SUM(E58:E75) -> 0 | F77: =SUM(F58:F75) -> 163.04353 | G77: =SUM(G58:G75) -> 326.08705 | H77: =SUM(H58:H75) -> 489.13058 | I77: =SUM(I58:I75) -> 652.17411 | J77: =SUM(J58:J75) -> 815.21763 | K77: =SUM(K58:K75) -> 978.26116 | L77: =SUM(L58:L75) -> 1222.8264 | ... V77: =SUM(V58:V75) -> 2853.2617 | W77: x
W78: x
W79: x

Sheet Consolidated Financials
A1: Blue: Hard code vale | AS1: x
A2: Black: Calculation | AS2: x
A3: Green: Linked from another tab | AS3: x
A4: Red: Linked from the same tab | AS4: x
Q5: - | AS5: x
J6: Historical | N6: Annual Forecast | U6: Management Account | Y6: Monthly Forecast | AS6: x
J7: 2022 | K7: =J7+1 -> 2023 | L7: =K7+1 -> 2024 | M7: =L7+1 -> 2025 | N7: =M7+1 -> 2026 | O7: 2027H1E | P7: =N7+1 -> 2027 | U7: 46023 | V7: =EDATE(U7,1) -> 46054 | W7: =EDATE(V7,1) -> 46082 | X7: =EDATE(W7,1) -> 46113 | Y7: =EDATE(X7,1) -> 46143 | Z7: =EDATE(Y7,1) -> 46174 | AA7: =EDATE(Z7,1) -> 46204 | AB7: =EDATE(AA7,1) -> 46235 | AC7: =EDATE(AB7,1) -> 46266 | ... AR7: =EDATE(AQ7,1) -> 46722 | AS7: x
J8: RMB’000 | K8: RMB’000 | L8: RMB’000 | M8: RMB’000 | N8: RMB’000 | O8: RMB’000 | P8: RMB’000 | U8: RMB’000 | V8: RMB’000 | W8: RMB’000 | X8: RMB’000 | Y8: RMB’000 | Z8: RMB’000 | AA8: RMB’000 | AB8: RMB’000 | AC8: RMB’000 | AD8: RMB’000 | AE8: RMB’000 | AF8: RMB’000 | AG8: RMB’000 | AH8: RMB’000 | AI8: RMB’000 | AJ8: RMB’000 | AK8: RMB’000 | AL8: RMB’000 | AM8: RMB’000 | AN8: RMB’000 | AO8: RMB’000 | AP8: RMB’000 | AQ8: RMB’000 | AR8: RMB’000 | AS8: x | AT8: 2023 vs 2024 | AU8: 2024vs2025 | AV8: 2025vs2026
A9: 已核对0331审计报告 | B9: Income Statement | AS9: x
B10: Revenue | J10: =COGS_Breakdown_1231!D37 -> 222813.08 | K10: =COGS_Breakdown_1231!E37 -> 530805.86 | L10: =COGS_Breakdown_1231!F37 -> 655437.77 | M10: =COGS_Breakdown_1231!G37 -> 788818.16 | N10: ='IS-Other Calculations'!N27 -> 1091320 | O10: ='IS-Other Calculations'!O27 -> 619476.7 | P10: ='IS-Other Calculations'!P27 -> 1500522.8 | Q10: x | U10: ='IS-Other Calculations'!W27 -> 95427.667 | V10: ='IS-Other Calculations'!X27 -> 60517.064 | W10: ='IS-Other Calculations'!Y27 -> 42711 | X10: ='IS-Other Calculations'!Z27 -> 17031 | Y10: ='IS-Other Calculations'!AA27 -> 38689.952 | Z10: ='IS-Other Calculations'!AB27 -> 110697.84 | AA10: ='IS-Other Calculations'!AC27 -> 119768.75 | AB10: ='IS-Other Calculations'!AD27 -> 115960.38 | ... AR10: ='IS-Other Calculations'!AT27 -> 143757.48 | AS10: x
C11: GJ AI Real-time Video Agent | J11: =COGS_Breakdown_1231!D33 -> 139864.03 | K11: =COGS_Breakdown_1231!E33 -> 460050.82 | L11: =COGS_Breakdown_1231!F33 -> 612656 | M11: =COGS_Breakdown_1231!G33 -> 722872.01 | N11: =N12+N13 -> 827685.12 | O11: =O12+O13 -> 491467.31 | P11: =P12+P13 -> 938843.62 | Q11: x | U11: =U12+U13 -> 90177.731 | V11: =V12+V13 -> 59827 | W11: =W12+W13 -> 34333 | X11: =X12+X13 -> 15986 | Y11: =Y12+Y13 -> 38004.949 | Z11: =Z12+Z13 -> 65648.676 | AA11: =AA12+AA13 -> 88370.961 | AB11: =AB12+AB13 -> 84562.591 | ... AL11: =AL12+AL13 -> 76390.105 | AS11: x
D12: ICT services | J12: =COGS_Breakdown_1231!D6/-1000 -> 37081.816 | K12: =COGS_Breakdown_1231!E6/-1000 -> 194790.7 | L12: =COGS_Breakdown_1231!F6/-1000 -> 422152.34 | M12: =COGS_Breakdown_1231!G6/-1000 -> 323358.46 | N12: ='IS-Other Calculations'!N13 -> 246685.92 | O12: ='IS-Other Calculations'!O13 -> 141626.68 | P12: ='IS-Other Calculations'!P13 -> 250126.68 | Q12: x | U12: ='IS-Other Calculations'!W13 -> 31850.376 | V12: ='IS-Other Calculations'!X13 -> 2738 | W12: ='IS-Other Calculations'!Y13 -> 16983 | X12: ='IS-Other Calculations'!Z13 -> 4546 | Y12: ='IS-Other Calculations'!AA13 -> 22151.007 | Z12: ='IS-Other Calculations'!AB13 -> 18140.596 | AA12: ='IS-Other Calculations'!AC13 -> 26725.287 | AB12: ='IS-Other Calculations'!AD13 -> 21106.147 | ... AR12: ='IS-Other Calculations'!AT13 -> 18083.333 | AS12: x
D13: AIGC services | J13: =COGS_Breakdown_1231!D7/-1000 -> 102782.21 | K13: =COGS_Breakdown_1231!E7/-1000 -> 265260.12 | L13: =COGS_Breakdown_1231!F7/-1000 -> 190503.67 | M13: =COGS_Breakdown_1231!G7/-1000 -> 399513.55 | N13: ='IS-Other Calculations'!N16 -> 580999.21 | O13: ='IS-Other Calculations'!O16 -> 349840.63 | P13: ='IS-Other Calculations'!P16 -> 688716.94 | Q13: x | U13: ='IS-Other Calculations'!W16 -> 58327.355 | V13: ='IS-Other Calculations'!X16 -> 57089 | W13: ='IS-Other Calculations'!Y16 -> 17350 | X13: ='IS-Other Calculations'!Z16 -> 11440 | Y13: ='IS-Other Calculations'!AA16 -> 15853.942 | Z13: ='IS-Other Calculations'!AB16 -> 47508.08 | AA13: ='IS-Other Calculations'!AC16 -> 61645.674 | AB13: ='IS-Other Calculations'!AD16 -> 63456.444 | ... AR13: ='IS-Other Calculations'!AT16 -> 53395.856 | AS13: x
C14: GJ AI Real-time Voice Agent | J14: =COGS_Breakdown_1231!D34 -> 68752.075 | K14: =COGS_Breakdown_1231!E34 -> 25312.277 | L14: =COGS_Breakdown_1231!F34 -> 16788.507 | M14: =COGS_Breakdown_1231!G34 -> 3974.9551 | N14: ='IS-Other Calculations'!N19 -> 3986.3274 | O14: ='IS-Other Calculations'!O19 -> 0 | P14: ='IS-Other Calculations'!P19 -> 0 | Q14: x | U14: ='IS-Other Calculations'!W19 -> 77 | V14: ='IS-Other Calculations'!X19 -> 319 | W14: ='IS-Other Calculations'!Y19 -> 1425 | X14: ='IS-Other Calculations'!Z19 -> 254 | Y14: ='IS-Other Calculations'!AA19 -> 0 | Z14: ='IS-Other Calculations'!AB19 -> 1911.3274 | AA14: ='IS-Other Calculations'!AC19 -> 0 | AB14: ='IS-Other Calculations'!AD19 -> 0 | ... AR14: ='IS-Other Calculations'!AT19 -> 0 | AS14: x
C15: GJ AI Video Generation Agent and GJ AI Live Streaming Agent | J15: =COGS_Breakdown_1231!D35 -> 14196.979 | K15: =COGS_Breakdown_1231!E35 -> 45442.759 | L15: =COGS_Breakdown_1231!F35 -> 25993.256 | M15: =COGS_Breakdown_1231!G35 -> 10583.474 | N15: ='IS-Other Calculations'!N22 -> 6791.025 | O15: ='IS-Other Calculations'!O22 -> 4110.0188 | P15: ='IS-Other Calculations'!P22 -> 8220.0375 | Q15: x | U15: ='IS-Other Calculations'!W22 -> 672 | V15: ='IS-Other Calculations'!X22 -> 50 | W15: ='IS-Other Calculations'!Y22 -> 257 | X15: ='IS-Other Calculations'!Z22 -> 332 | Y15: ='IS-Other Calculations'!AA22 -> 685.00313 | Z15: ='IS-Other Calculations'!AB22 -> 685.00313 | AA15: ='IS-Other Calculations'!AC22 -> 685.00313 | AB15: ='IS-Other Calculations'!AD22 -> 685.00313 | ... AR15: ='IS-Other Calculations'!AT22 -> 685.00313 | AS15: x
C16: GJ Autopilot AIGC Agent | J16: =COGS_Breakdown_1231!D36 -> 0 | K16: =COGS_Breakdown_1231!E36 -> 0 | L16: =COGS_Breakdown_1231!F36 -> 0 | M16: =COGS_Breakdown_1231!G36 -> 51387.72 | N16: ='IS-Other Calculations'!N25 -> 252857.5 | O16: ='IS-Other Calculations'!O25 -> 123899.37 | P16: ='IS-Other Calculations'!P25 -> 553459.12 | Q16: x | U16: ='IS-Other Calculations'!W25 -> 4500 | V16: ='IS-Other Calculations'!X25 -> 322 | W16: ='IS-Other Calculations'!Y25 -> 6696 | X16: ='IS-Other Calculations'!Z25 -> 459 | Y16: ='IS-Other Calculations'!AA25 -> 0 | Z16: ='IS-Other Calculations'!AB25 -> 42452.83 | AA16: ='IS-Other Calculations'!AC25 -> 30712.788 | AB16: ='IS-Other Calculations'!AD25 -> 30712.788 | ... AR16: ='IS-Other Calculations'!AT25 -> 71593.291 | AS16: x
C18: Cost of sales | J18: =-COGS_Breakdown_1231!D48 -> -137010 | K18: =-COGS_Breakdown_1231!E48 -> -287645.05 | L18: =-COGS_Breakdown_1231!F48 -> -430359.22 | M18: =-COGS_Breakdown_1231!G48 -> -516747.26 | N18: ='IS-Other Calculations'!N56 -> -702360.08 | O18: ='IS-Other Calculations'!O56 -> -397437.85 | P18: ='IS-Other Calculations'!P56 -> -916065.34 | Q18: x | U18: ='IS-Other Calculations'!W56 -> -58238.334 | V18: ='IS-Other Calculations'!X56 -> -42034.649 | W18: ='IS-Other Calculations'!Y56 -> -27982 | X18: ='IS-Other Calculations'!Z56 -> -10829 | Y18: ='IS-Other Calculations'!AA56 -> -27244.81 | Z18: ='IS-Other Calculations'!AB56 -> -69673.074 | AA18: ='IS-Other Calculations'!AC56 -> -77286.436 | AB18: ='IS-Other Calculations'!AD56 -> -74305.274 | ... AR18: ='IS-Other Calculations'!AT56 -> -84433.621 | AS18: x
Q19: x | AS19: x
B20: Gross profit | J20: =J10+J18 -> 85803.08 | K20: =K10+K18 -> 243160.81 | L20: =L10+L18 -> 225078.54 | M20: =M10+M18 -> 272070.9 | N20: =N10+N18 -> 388959.9 | O20: =O10+O18 -> 222038.85 | Q20: x | U20: =U10+U18 -> 37189.333 | V20: =V10+V18 -> 18482.415 | W20: =W10+W18 -> 14729 | X20: =X10+X18 -> 6202 | Y20: =Y10+Y18 -> 11445.142 | Z20: =Z10+Z18 -> 41024.762 | AA20: =AA10+AA18 -> 42482.316 | AB20: =AB10+AB18 -> 41655.109 | ... AR20: =AR10+AR18 -> 59323.863 | AS20: x
B21: Gross margin % | J21: =J20/J10 -> 0.38508996 | K21: =K20/K10 -> 0.45809744 | L21: =L20/L10 -> 0.34340185 | M21: =M20/M10 -> 0.34490952 | N21: =N20/N10 -> 0.35641234 | O21: =O20/O10 -> 0.3584297 | Q21: x | AS21: x
Q22: x | AS22: x
B23: Other income | J23: ='IS-Other Calculations'!J135 -> 17972 | K23: 15976 | L23: 10846 | M23: 2554 | N23: ='IS-Other Calculations'!N135 -> 126.40819 | O23: ='IS-Other Calculations'!O135 -> 0 | Q23: x | U23: ='IS-Other Calculations'!W135 -> 0 | V23: ='IS-Other Calculations'!X135 -> 0.74479 | W23: ='IS-Other Calculations'!Y135 -> 155.14 | X23: ='IS-Other Calculations'!Z135 -> 0 | Y23: ='IS-Other Calculations'!AA135 -> -3.684575 | Z23: ='IS-Other Calculations'!AB135 -> -3.684575 | AA23: ='IS-Other Calculations'!AC135 -> -3.684575 | AB23: ='IS-Other Calculations'!AD135 -> -3.684575 | ... AR23: ='IS-Other Calculations'!AT135 -> 0 | AS23: x
B24: Other net (loss)/gain | J24: ='IS-Other Calculations'!J143 -> -125 | K24: 38 | L24: -678 | M24: 717 | N24: ='IS-Other Calculations'!N143 -> -486.34861 | O24: ='IS-Other Calculations'!O143 -> 0 | Q24: x | U24: ='IS-Other Calculations'!W143 -> -112.07482 | V24: ='IS-Other Calculations'!X143 -> -168.73186 | W24: ='IS-Other Calculations'!Y143 -> -205.54192 | X24: ='IS-Other Calculations'!Z143 -> -3.149e-06 | Y24: ='IS-Other Calculations'!AA143 -> 0 | Z24: ='IS-Other Calculations'!AB143 -> 0 | AA24: ='IS-Other Calculations'!AC143 -> 0 | AB24: ='IS-Other Calculations'!AD143 -> 0 | ... AR24: ='IS-Other Calculations'!AT143 -> 0 | AS24: x
B25: Selling and marketing expenses | J25: ='IS-Other Calculations'!J81 -> -38511.621 | K25: -110263 | L25: -82570 | M25: -55235 | N25: ='IS-Other Calculations'!N81 -> -80603.525 | O25: ='IS-Other Calculations'!O81 -> -51440.423 | Q25: x | U25: ='IS-Other Calculations'!W81 -> -3708.09 | V25: ='IS-Other Calculations'!X81 -> -6055.31 | W25: ='IS-Other Calculations'!Y81 -> -2607 | X25: ='IS-Other Calculations'!Z81 -> -2457 | Y25: ='IS-Other Calculations'!AA81 -> -3286.2894 | Z25: ='IS-Other Calculations'!AB81 -> -6886.6837 | AA25: ='IS-Other Calculations'!AC81 -> -9203.5841 | AB25: ='IS-Other Calculations'!AD81 -> -9013.1656 | ... AR25: ='IS-Other Calculations'!AT81 -> -8529.0662 | AS25: x
B26: Administrative and other operating expenses | J26: ='IS-Other Calculations'!J104 -> -47110.4 | K26: -47966 | L26: -41211 | M26: -55634 | N26: ='IS-Other Calculations'!N104 -> -62020.78 | O26: ='IS-Other Calculations'!O104 -> -23058.414 | Q26: x | U26: ='IS-Other Calculations'!W104 -> -3552 | V26: ='IS-Other Calculations'!X104 -> -2958 | W26: ='IS-Other Calculations'!Y104 -> -4978 | X26: ='IS-Other Calculations'!Z104 -> -2896 | Y26: ='IS-Other Calculations'!AA104 -> -2829.2369 | Z26: ='IS-Other Calculations'!AB104 -> -19185.271 | AA26: ='IS-Other Calculations'!AC104 -> -4248.116 | AB26: ='IS-Other Calculations'!AD104 -> -4181.4695 | ... AR26: ='IS-Other Calculations'!AT104 -> -4957.6498 | AS26: x
B27: Research and development expenses | J27: ='IS-Other Calculations'!J130 -> -75433 | K27: -129569 | L27: -150129 | M27: -163342 | N27: ='IS-Other Calculations'!N130 -> -230076.24 | O27: ='IS-Other Calculations'!O130 -> -152790.74 | Q27: x | U27: ='IS-Other Calculations'!W130 -> -15145.855 | V27: ='IS-Other Calculations'!X130 -> -25233 | W27: ='IS-Other Calculations'!Y130 -> -15669 | X27: ='IS-Other Calculations'!Z130 -> -12892 | Y27: ='IS-Other Calculations'!AA130 -> -7519.4354 | Z27: ='IS-Other Calculations'!AB130 -> -20363.89 | AA27: ='IS-Other Calculations'!AC130 -> -21981.921 | AB27: ='IS-Other Calculations'!AD130 -> -21302.6 | ... AR27: ='IS-Other Calculations'!AT130 -> -26258.577 | AS27: x
B28: Impairment loss on trade and other receivables and contract assets | J28: ='IS-Other Calculations'!J149 -> -3553 | K28: -11750 | L28: -21169 | M28: -27595 | N28: ='IS-Other Calculations'!N149 -> -26864.821 | O28: ='IS-Other Calculations'!O149 -> -10970.471 | Q28: x | U28: ='IS-Other Calculations'!W149 -> -4813.1893 | V28: ='IS-Other Calculations'!X149 -> 1121.2699 | W28: ='IS-Other Calculations'!Y149 -> -2171.1621 | X28: ='IS-Other Calculations'!Z149 -> 2435.3079 | Y28: ='IS-Other Calculations'!AA149 -> -1035.5685 | Z28: ='IS-Other Calculations'!AB149 -> -2962.919 | AA28: ='IS-Other Calculations'!AC149 -> -3205.7096 | AB28: ='IS-Other Calculations'!AD149 -> -3103.7754 | ... AR28: ='IS-Other Calculations'!AT149 -> -2545.838 | AS28: x
Q29: x | AS29: x
B30: Gain/(loss) from operations | J30: =SUM(J20,J23:J28) -> -60957.941 | K30: =SUM(K20,K23:K28) -> -40373.194 | L30: =SUM(L20,L23:L28) -> -59832.456 | M30: -26464 | N30: =SUM(N20,N23:N28) -> -10965.398 | O30: =SUM(O20,O23:O28) -> -16221.205 | Q30: x | U30: =SUM(U20,U23:U28) -> 9858.1239 | V30: =SUM(V20,V23:V28) -> -14810.612 | W30: =SUM(W20,W23:W28) -> -10746.564 | X30: =SUM(X20,X23:X28) -> -9607.6921 | Y30: =SUM(Y20,Y23:Y28) -> -3229.0728 | Z30: =SUM(Z20,Z23:Z28) -> -8377.6859 | AA30: =SUM(AA20,AA23:AA28) -> 3839.3011 | AB30: =SUM(AB20,AB23:AB28) -> 4050.4139 | ... AR30: =SUM(AR20,AR23:AR28) -> 17032.731 | AS30: x
Q31: x | AS31: x
B32: Finance income | J32: ='IS-Other Calculations'!J157 -> 9458 | K32: 4606 | L32: 2239 | M32: 857 | N32: ='IS-Other Calculations'!N157 -> 2719.8375 | O32: ='IS-Other Calculations'!O157 -> 1959.1037 | Q32: x | U32: ='IS-Other Calculations'!W157 -> 0.000913536 | V32: ='IS-Other Calculations'!X157 -> 0.17778724 | W32: ='IS-Other Calculations'!Y157 -> 150.58093 | X32: ='IS-Other Calculations'!Z157 -> 0.50410647 | Y32: ='IS-Other Calculations'!AA157 -> 81.092033 | Z32: ='IS-Other Calculations'!AB157 -> 360.59522 | AA32: ='IS-Other Calculations'!AC157 -> 358.84833 | AB32: ='IS-Other Calculations'!AD157 -> 357.10143 | ... AR32: ='IS-Other Calculations'!AT157 -> 343.84066 | AS32: x
B33: Finance costs | J33: ='IS-Other Calculations'!J162 -> -759 | K33: -435 | L33: -240 | M33: -144 | N33: ='IS-Other Calculations'!N162 -> -199.47515 | O33: ='IS-Other Calculations'!O162 -> -193.09421 | Q33: x | U33: ='IS-Other Calculations'!W162 -> -133.213 | V33: ='IS-Other Calculations'!X162 -> -208.98883 | W33: ='IS-Other Calculations'!Y162 -> -167.66132 | X33: ='IS-Other Calculations'!Z162 -> -122.20971 | Y33: ='IS-Other Calculations'!AA162 -> 19.114378 | Z33: ='IS-Other Calculations'!AB162 -> 54.689142 | AA33: ='IS-Other Calculations'!AC162 -> 59.170536 | AB33: ='IS-Other Calculations'!AD162 -> 57.28905 | ... AR33: ='IS-Other Calculations'!AT162 -> #REF! | AS33: x
B34: Share of loss of associates | J34: ='IS-Other Calculations'!J167 -> 0 | K34: -1104 | L34: -27 | M34: -164 | N34: ='IS-Other Calculations'!N167 -> 0 | O34: ='IS-Other Calculations'!O167 -> 0 | Q34: x | U34: ='IS-Other Calculations'!W167 -> 0 | V34: ='IS-Other Calculations'!X167 -> 0 | W34: ='IS-Other Calculations'!Y167 -> 0 | X34: ='IS-Other Calculations'!Z167 -> 0 | Y34: ='IS-Other Calculations'!AA167 -> 0 | Z34: ='IS-Other Calculations'!AB167 -> 0 | AA34: ='IS-Other Calculations'!AC167 -> 0 | AB34: ='IS-Other Calculations'!AD167 -> 0 | ... AR34: ='IS-Other Calculations'!AT167 -> 0 | AS34: x
B35: Accretion of redeemable capital contributions | J35: ='IS-Other Calculations'!J170 -> -58660 | K35: -58660 | L35: -53838 | M35: 0 | N35: ='IS-Other Calculations'!N170 -> 0 | O35: ='IS-Other Calculations'!O170 -> 0 | Q35: x | U35: ='IS-Other Calculations'!W170 -> 0 | V35: ='IS-Other Calculations'!X170 -> 0 | W35: ='IS-Other Calculations'!Y170 -> 0 | X35: ='IS-Other Calculations'!Z170 -> 0 | Y35: ='IS-Other Calculations'!AA170 -> 0 | Z35: ='IS-Other Calculations'!AB170 -> 0 | AA35: ='IS-Other Calculations'!AC170 -> 0 | AB35: ='IS-Other Calculations'!AD170 -> 0 | ... AR35: ='IS-Other Calculations'!AT170 -> 0 | AS35: x
Q36: x | AS36: x
B37: Gain/(loss) before taxation | J37: =SUM(J30,J32:J35) -> -110918.94 | K37: -95967 | L37: -111699 | M37: -25915 | N37: =SUM(N30,N32:N35) -> -8445.0357 | O37: =SUM(O30,O32:O35) -> -14455.196 | Q37: x | U37: =SUM(U30,U32:U35) -> 9724.9118 | V37: =SUM(V30,V32:V35) -> -15019.423 | W37: =SUM(W30,W32:W35) -> -10763.644 | X37: =SUM(X30,X32:X35) -> -9729.3977 | Y37: =SUM(Y30,Y32:Y35) -> -3128.8664 | Z37: =SUM(Z30,Z32:Z35) -> -7962.4015 | AA37: =SUM(AA30,AA32:AA35) -> 4257.32 | AB37: =SUM(AB30,AB32:AB35) -> 4464.8044 | ... AR37: =SUM(AR30,AR32:AR35) -> #REF! | AS37: x
Q38: x | AS38: x
B39: Income tax | J39: ='IS-Other Calculations'!J183 -> -134 | K39: 60 | L39: 0 | M39: 0 | N39: ='IS-Other Calculations'!N183 -> 0 | O39: ='IS-Other Calculations'!O183 -> 0 | Q39: x | U39: ='IS-Other Calculations'!W183 -> 0 | V39: ='IS-Other Calculations'!X183 -> 0 | W39: ='IS-Other Calculations'!Y183 -> 0 | X39: ='IS-Other Calculations'!Z183 -> 0 | Y39: ='IS-Other Calculations'!AA183 -> 0 | Z39: ='IS-Other Calculations'!AB183 -> 0 | AA39: ='IS-Other Calculations'!AC183 -> 0 | AB39: ='IS-Other Calculations'!AD183 -> 0 | ... AR39: ='IS-Other Calculations'!AT183 -> 0 | AS39: x
Q40: x | AS40: x
B41: Loss for the year/period | J41: =J37+J39 -> -111052.94 | K41: =K37+K39 -> -95907 | L41: =L37+L39 -> -111699 | M41: =M37+M39 -> -25915 | N41: =N37+N39 -> -8445.0357 | O41: =O37+O39 -> -14455.196 | Q41: x | U41: =U37+U39 -> 9724.9118 | V41: =V37+V39 -> -15019.423 | W41: =W37+W39 -> -10763.644 | X41: =X37+X39 -> -9729.3977 | Y41: =Y37+Y39 -> -3128.8664 | Z41: =Z37+Z39 -> -7962.4015 | AA41: =AA37+AA39 -> 4257.32 | AB41: =AB37+AB39 -> 4464.8044 | ... AR41: =AR37+AR39 -> #REF! | AS41: x
Q42: x | AS42: x
B43: Attributable to: | Q43: x | AS43: x
Q44: x | AS44: x
C45: Equity shareholders of the Company | K45: =K41 -> -95907 | L45: =L41 -> -111699 | M45: =M41 -> -25915 | N45: =N41 -> -8445.0357 | O45: =O41 -> -14455.196 | Q45: x | U45: =U41 -> 9724.9118 | V45: =V41 -> -15019.423 | W45: =W41 -> -10763.644 | X45: =X41 -> -9729.3977 | Y45: =Y41 -> -3128.8664 | Z45: =Z41 -> -7962.4015 | AA45: =AA41 -> 4257.32 | AB45: =AB41 -> 4464.8044 | ... AL45: =AL41 -> -1233.0216 | AS45: x
Q46: x | AS46: x
B47: Other comprehensive income for the year | Q47: x | AS47: x
Q48: x | AS48: x
B49: Items that may be reclassified subsequently to profit or loss: | Q49: x | AS49: x
Q50: x | AS50: x
B51: Exchange differences on translation of financial statements of a foreign subsidiary, net of nil tax | J51: 0 | K51: 0 | L51: 0 | M51: -475 | N51: =SUM(U51:AF51) -> 73.03884 | O51: =SUM(AG51:AL51) -> 0 | Q51: x | U51: ='IS-Other Calculations'!W187 -> 46.3 | V51: ='IS-Other Calculations'!X187 -> 12.56884 | W51: ='IS-Other Calculations'!Y187 -> -5.87 | X51: ='IS-Other Calculations'!Z187 -> 20.04 | Y51: ='IS-Other Calculations'!AA187 -> 0 | Z51: ='IS-Other Calculations'!AB187 -> 0 | AA51: ='IS-Other Calculations'!AC187 -> 0 | AB51: ='IS-Other Calculations'!AD187 -> 0 | ... AL51: ='IS-Other Calculations'!AN187 -> 0 | AS51: x
Q52: x | AS52: x
B53: Total comprehensive income for the year | K53: =K45+K51 -> -95907 | L53: =L45+L51 -> -111699 | M53: =M45+M51 -> -26390 | N53: =N45+N51 -> -8371.9969 | O53: =O45+O51 -> -14455.196 | Q53: x | U53: =U45+U51 -> 9771.2118 | V53: =V45+V51 -> -15006.854 | W53: =W45+W51 -> -10769.514 | X53: =X45+X51 -> -9709.3577 | Y53: =Y45+Y51 -> -3128.8664 | Z53: =Z45+Z51 -> -7962.4015 | AA53: =AA45+AA51 -> 4257.32 | AB53: =AB45+AB51 -> 4464.8044 | ... AL53: =AL45+AL51 -> -1233.0216 | AS53: x
Q54: x | AS54: x
B55: Attributable to: | Q55: x | AS55: x
Q56: x | AS56: x
C57: Equity shareholders of the Company | J57: =J41+J51 -> -111052.94 | K57: =K53 -> -95907 | L57: =L53 -> -111699 | M57: =M53 -> -26390 | N57: =N53 -> -8371.9969 | O57: =O53 -> -14455.196 | Q57: x | U57: =U41+U51 -> 9771.2118 | V57: =V41+V51 -> -15006.854 | W57: =W41+W51 -> -10769.514 | X57: =X41+X51 -> -9709.3577 | Y57: =Y41 -> -3128.8664 | Z57: =Z41 -> -7962.4015 | AA57: =AA41 -> 4257.32 | AB57: =AB41 -> 4464.8044 | AC57: =AC41 -> 6142.3944 | AD57: =AD41 -> 4296.884 | AE57: =AE41 -> 4248.57 | AF57: =AF41 -> 5023.8129 | ... AR57: =AR41 -> #REF! | AS57: x
Q58: x | AS58: x
B59: ADD: | Q59: x | AS59: x
B60: Listing expenses | J60: 0 | K60: 0 | L60: 1140 | M60: 18328 | N60: ='IS-Other Calculations'!N95 -> 16847.896 | O60: ='IS-Other Calculations'!O95 -> 0 | Q60: x | U60: ='IS-Other Calculations'!W95 -> 772 | V60: ='IS-Other Calculations'!X95 -> 242 | W60: ='IS-Other Calculations'!Y95 -> 604 | X60: ='IS-Other Calculations'!Z95 -> 134 | Y60: ='IS-Other Calculations'!AA95 -> 0 | Z60: ='IS-Other Calculations'!AB95 -> 15095.896 | AA60: ='IS-Other Calculations'!AC95 -> 0 | AB60: ='IS-Other Calculations'!AD95 -> 0 | ... AL60: ='IS-Other Calculations'!AN95 -> 0 | AM60: ='IS-Other Calculations'!#REF! -> #REF! | AN60: ='IS-Other Calculations'!#REF! -> #REF! | AO60: ='IS-Other Calculations'!#REF! -> #REF! | AP60: ='IS-Other Calculations'!#REF! -> #REF! | AQ60: ='IS-Other Calculations'!#REF! -> #REF! | AR60: ='IS-Other Calculations'!#REF! -> #REF! | AS60: x
