Workbook

Sheet Stats
B2: Project GJ | F2: 1 | G2: RMB | H2: = | I2: =1/0.87408 -> 1.14406 | J2: HKD
I3: =1/0.87408 -> 1.14406
B6: Domestic Unlisted Shares in issue 内资股 | C6: 17084745
L7: Without OAO | M7: With OAO
B8: Nominal value (RMB) 面值 | C8: 1 | K8: high-mid | L8: =H26-G26 -> 136962345 | M8: =L26-K26 -> 157506336
B9: Issued share capital (RMB, before listing) 注册股本(发行前) | C9: =C6*C8 -> 17084745 | K9: mid-low | L9: =G26-F26 -> 136962345 | M9: =K26-J26 -> 157506336
B10: Enlarged capital in IPO (before OAO) 股本增加比例 | C10: 0.25 | L10: With OAO - without OAO
B11: H Shares to be converted from Domestic Unlisted Shares 内资股转换至H股股数 | C11: =C6 -> 17084745 | D11: 全部全流通 | E11: 不向下取可被20整除原数 | G11: 发行结构（初） | K11: high | L11: =L26-H26 -> 2.300927e+08
B12: H Shares to be issued under Global Offering (before OAO) 根据全球发售发行的H股（假设超额配售股权未获行使） | C12: =FLOOR(C10*C9/(1-C10),20) -> 5694900 | D12: =C12/C13 -> 0.24999951 | E12: 5694915 | G12: HK offering | H12: =CEILING(ROUND(I12*C12,0),20) -> 569500 | I12: 0.1 | K12: mid | L12: =K26-G26 -> 2.0954871e+08
B13: Shares in total （Before OAO) 总计（假设超额配售股权未获行使） | C13: =C12+C9 -> 22779645 | D13: =SUM(C12+C9) -> 22779645 | G13: Global offering | H13: =FLOOR(ROUND(I13*C12,0),20) -> 5125400 | I13: 0.9 | K13: low | L13: =J26-F26 -> 1.8900472e+08
B14: Over-allotment Option 超额配售权或行使 | C14: =FLOOR(C12*D14,20) -> 854220 | D14: 0.15
B15: Global Offering with OAO 根据全球发售发行的H股（假设超额配售股权获行使） | C15: =C12+C14 -> 6549120
B16: Shares in total with OAO 总计（假设超额配售股权获行使） | C16: =C13+C14 -> 23633865
F18: Before OAO 超额配售股权行使前 | J18: After OAO 超额配售股权行使后
F19: Price per share 每股股价 | J19: Price per share 每股股价
C20: Shares in issue before Global Offering 全球公开发售发行前的内资股股数 | D20: =B12 -> H Shares to be issued under Global Offering (before OAO) 根据全球发售发行的H股（假设超额配售股权未获行使） | E20: Par value (RMB) 面值 | F20: Low-end 低位 | G20: Mid-point 中位 | H20: High-end 高位 | J20: Low-end 低位 | K20: Mid-point 中位 | L20: High-end 高位 | M20: High-end vs low end | N20: GL90-18 price range check
B21: H shares in issue as of the date of prospectus 于招股书日期的H股股数 | C21: =C9 -> 17084745 | D21: =C12 -> 5694900 | E21: =C8 -> 1 | F21: =ROUND(F28/$C$13,2) -> 193.4 | G21: =ROUND(G28/$C$13,2) -> 214.42 | H21: =ROUND(H28/$C$13,2) -> 235.44 | J21: =F21 -> 193.4 | K21: =G21 -> 214.42 | L21: =H21 -> 235.44 | M21: =(H28-F28)/F28 -> 0.2173913 | N21: 0.3 | O21: =M21<N21 -> TRUE
E23: Price (HKD) 股价（港币） | F23: 221.26 | G23: 245.31 | H23: 269.36 | J23: =F23 -> 221.26 | K23: =G23 -> 245.31 | L23: =H23 -> 269.36
E25: Market Cap (HKD) 市值（港币） | F25: =F23*$C$13 -> 5.0402243e+09 | G25: =G23*$C$13 -> 5.5880747e+09 | H25: =H23*$C$13 -> 6.1359252e+09 | J25: =J23*C16 -> 5.229229e+09 | K25: =K23*C16 -> 5.7976234e+09 | L25: =L23*C16 -> 6.3660179e+09
E26: Gross proceeds (HKD) 集资总额（港币） | F26: =F23*$C$12 -> 1260053574 | G26: =G23*$C$12 -> 1397015919 | H26: =H23*$C$12 -> 1533978264 | J26: =J23*C15 -> 1.4490583e+09 | K26: =K23*C15 -> 1.6065646e+09 | L26: =L23*C15 -> 1.764071e+09
E28: Market Cap (RMB) 市值（人民币） | F28: =F25/$I$2 -> 4.4055592e+09 | G28: =G25/$I$2 -> 4.8844243e+09 | H28: =H25/$I$2 -> 5.3632895e+09 | J28: =J21*$C$16 -> 4570789491 | K28: =K21*C16 -> 5.0675733e+09 | L28: =L21*C16 -> 5.5643572e+09
E29: Gross proceeds (RMB) 集资总额（人民币） | F29: =F26/$I$2 -> 1.1013876e+09 | G29: =G26/$I$2 -> 1.2211037e+09 | H29: =H26/$I$2 -> 1.3408197e+09 | J29: =J21*$C$15 -> 1266599808 | K29: =K21*$C$15 -> 1.4042623e+09 | L29: =L21*$C$15 -> 1.5419248e+09
C32: =C20 -> Shares in issue before Global Offering 全球公开发售发行前的内资股股数 | D32: After Global Offering (before OAO) 全球发售发行后 （假设超额配售股权未获行使） | E32: Shareholding % 股本百分比 | F32: After Global Offering (after OAO) 全球发售发行后 （假设超额配售股权获行使） | G32: Shareholding % 股本百分比
B33: Nanjing Sillicon Intelligence 硅基智能 | C33: =C6 -> 17084745 | D33: =C33 -> 17084745 | E33: =D33/$D$36 -> 0.75000049 | F33: =D33 -> 17084745 | G33: =F33/F36 -> 0.72289255
B34: Other H Shares Public Shareholders 其他H股公众股东 | C34: 0 | D34: =C12 -> 5694900 | E34: =D34/$D$36 -> 0.24999951 | F34: =C15 -> 6549120 | G34: =F34/F36 -> 0.27710745
B36: Total 总计 | C36: =SUM(C33:C34) -> 17084745 | D36: =SUM(D33:D34) -> 22779645 | E36: =SUM(E33:E34) -> 1 | F36: =SUM(F33:F34) -> 23633865 | G36: =SUM(G33:G34) -> 1
B38: Board Lot: 每手买卖单位 | C38: 20
B40: 每手交易价格 | C40: =C38*H23 -> 5387.2 | D40: HKD

Sheet 发行前后股权结构
A1: 序号 | B1: 股东姓名/名称 | C1: 发行前 | E1: 完成本次发行上市后（未行使超额配售权） | G1: 完成本次发行上市后（行使超额配售权）
C2: 股数（股） | D2: 股比 | E2: 股数（股） | F2: 股比 | G2: 股数（股） | H2: 股比
A3: 1 | B3: 司马华鹏 | C3: 4533683 | D3: =C3/$C$23 -> 0.26536439 | E3: =C3 -> 4533683 | F3: =E3/$E$23 -> 0.19902343 | G3: =C3 -> 4533683 | H3: =G3/$G$23 -> 0.19182994
A4: 2 | B4: 腾讯投资 | C4: 2834130 | D4: =C4/$C$23 -> 0.16588658 | E4: =C4 -> 2834130 | F4: =E4/$E$23 -> 0.12441502 | G4: =C4 -> 2834130 | H4: =G4/$G$23 -> 0.11991818
A5: 3 | B5: 员工持股实体 | C5: 1756039 | D5: =C5/$C$23 -> 0.10278403 | E5: =C5 -> 1756039 | F5: =E5/$E$23 -> 0.077088076 | G5: =C5 -> 1756039 | H5: =G5/$G$23 -> 0.074301812
A6: 4 | B6: 国新投资 | C6: 1150757 | D6: =C6/$C$23 -> 0.067355819 | E6: =C6 -> 1150757 | F6: =E6/$E$23 -> 0.050516898 | G6: =C6 -> 1150757 | H6: =G6/$G$23 -> 0.04869102
A7: 5 | B7: 嘉兴高投 | C7: 1084746 | D7: =C7/$C$23 -> 0.06349208 | E7: =C7 -> 1084746 | F7: =E7/$E$23 -> 0.047619092 | G7: =C7 -> 1084746 | H7: =G7/$G$23 -> 0.045897952
A8: 6 | B8: 嘉兴海松 | C8: 1006719 | D8: =C8/$C$23 -> 0.058925023 | E8: =C8 -> 1006719 | F8: =E8/$E$23 -> 0.044193797 | G8: =C8 -> 1006719 | H8: =G8/$G$23 -> 0.042596461
A9: 7 | B9: 招银现代 | C9: 744754 | D9: =C9/$C$23 -> 0.043591754 | E9: =C9 -> 744754 | F9: =E9/$E$23 -> 0.032693837 | G9: =C9 -> 744754 | H9: =G9/$G$23 -> 0.031512154
A10: 8 | B10: 招银电信 | C10: 744754 | D10: =C10/$C$23 -> 0.043591754 | E10: =C10 -> 744754 | F10: =E10/$E$23 -> 0.032693837 | G10: =C10 -> 744754 | H10: =G10/$G$23 -> 0.031512154
A11: 9 | B11: 杭州好望角 | C11: 593730 | D11: =C11/$C$23 -> 0.034752055 | E11: =C11 -> 593730 | F11: =E11/$E$23 -> 0.026064059 | G11: =C11 -> 593730 | H11: =G11/$G$23 -> 0.025122002
A12: 10 | B12: 中财奇虎 | C12: 572749 | D12: =C12/$C$23 -> 0.033524001 | E12: =C12 -> 572749 | F12: =E12/$E$23 -> 0.025143017 | G12: =C12 -> 572749 | H12: =G12/$G$23 -> 0.02423425
A13: 11 | B13: 红杉智盛 | C13: 508247 | D13: =C13/$C$23 -> 0.029748586 | E13: =C13 -> 508247 | F13: =E13/$E$23 -> 0.022311454 | G13: =C13 -> 508247 | H13: =G13/$G$23 -> 0.021505031
A14: 12 | B14: 招银永祥 | C14: 351539 | D14: =C14/$C$23 -> 0.020576192 | E14: =C14 -> 351539 | F14: =E14/$E$23 -> 0.015432154 | G14: =C14 -> 351539 | H14: =G14/$G$23 -> 0.014874376
... A21: 19 | B21: 新业广州 | C21: 10842 | D21: =C21/$C$23 -> 0.00063460122 | E21: =C21 -> 10842 | F21: =E21/$E$23 -> 0.00047595123 | G21: =C21 -> 10842 | H21: =G21/$G$23 -> 0.0004587485
A22: 20 | B22: 新增H股股东 | C22: 0 | D22: =C22/$C$23 -> 0 | E22: =Stats!C12 -> 5694900 | F22: =E22/$E$23 -> 0.24999951 | G22: =Stats!C15 -> 6549120 | H22: =G22/$G$23 -> 0.27710745
B23: 合计 | C23: =SUM(C3:C22) -> 17084745 | D23: =SUM(D3:D22) -> 1 | E23: =SUM(E3:E22) -> 22779645 | F23: =SUM(F3:F22) -> 1 | G23: =SUM(G3:G22) -> 23633865 | H23: =SUM(H3:H22) -> 1

Sheet Comps
A1: 截至20250930 | F1: 单位：亿元人民币
A2: 序号 | B2: 可比公司 | C2: PS（TTM） | D2: PB | F2: 硅基智能 | G2: 2024年度/20241231 | H2: 对应估值
A3: 1 | B3: 云知声 | C3: 34.3638 | D3: -12.8528 | F3: 营业收入 | G3: 6.56 | H3: =G3*C7 -> 107.40344
A4: 2 | B4: 出门问问 | C4: 2.4522 | D4: 3.3271 | F4: 净资产 | G4: 2.92 | H4: =G4*D7 -> 13.949521
A5: 3 | B5: 商汤 | C5: 23.2149 | D5: 4.4117
A6: 4 | B6: 第四范式 | C6: 5.459 | D6: 6.5929
B7: 均值 | C7: =AVERAGE(C3:C6) -> 16.372475 | D7: =AVERAGE(D4:D6) -> 4.7772333

Sheet UOP
A1: 序号 | B1: 投向 | C1: 比例 | D1: 对应金额（元人民币） | E1: 对应金额（元港币） | F1: 对应金额（元人民币） | G1: 对应金额（元港币） | H1: 对应金额（元人民币） | I1: 对应金额（元港币） | J1: 汇率 | K1: =Stats!I2 -> 1.14406
D2: 下限-44.39亿人民币 | F2: 中位数-49.21亿人民币 | H2: 上限-54.04亿
A3: 1 | B3: 研发能力的提升 | C3: 0.5 | D3: =C3*$D$12 -> 5.0184705e+08 | E3: =C3*$E$12 -> 5.7414316e+08 | F3: =$F$12*C3 -> 5.5900638e+08 | G3: =C3*$G$12 -> 6.3953686e+08 | H3: =C3*$H$12 -> 6.161657e+08 | I3: =C3*$I$12 -> 7.0493056e+08
A4: 1-1 | B4: 算力采购及租赁 | C4: 0.35 | D4: =C4*$D$12 -> 3.5129294e+08 | E4: =C4*$E$12 -> 4.0190021e+08 | F4: =$F$12*C4 -> 3.9130446e+08 | G4: =C4*$G$12 -> 4.476758e+08 | H4: =C4*$H$12 -> 4.3131599e+08 | I4: =C4*$I$12 -> 4.9345139e+08
A5: 1-2 | B5: 研发人员招聘 | C5: 0.1 | D5: =C5*$D$12 -> 1.0036941e+08 | E5: =C5*$E$12 -> 1.1482863e+08 | F5: =$F$12*C5 -> 1.1180128e+08 | G5: =C5*$G$12 -> 1.2790737e+08 | H5: =C5*$H$12 -> 1.2323314e+08 | I5: =C5*$I$12 -> 1.4098611e+08
A6: 1-3 | B6: 委外研发 | C6: 0.05 | D6: =C6*$D$12 -> 50184705 | E6: =C6*$E$12 -> 57414316 | F6: =$F$12*C6 -> 55900638 | G6: =C6*$G$12 -> 63953686 | H6: =C6*$H$12 -> 61616570 | I6: =C6*$I$12 -> 70493056
A7: 2 | B7: 商机开拓 | C7: 0.25 | D7: =C7*$D$12 -> 2.5092353e+08 | E7: =C7*$E$12 -> 2.8707158e+08 | F7: =$F$12*C7 -> 2.7950319e+08 | G7: =C7*$G$12 -> 3.1976843e+08 | H7: =C7*$H$12 -> 3.0808285e+08 | I7: =C7*$I$12 -> 3.5246528e+08
A8: 2-1 | B8: 宣传推广 | C8: 0.2 | D8: =C8*$D$12 -> 2.0073882e+08 | E8: =C8*$E$12 -> 2.2965726e+08 | F8: =$F$12*C8 -> 2.2360255e+08 | G8: =C8*$G$12 -> 2.5581474e+08 | H8: =C8*$H$12 -> 2.4646628e+08 | I8: =C8*$I$12 -> 2.8197222e+08
A9: 2-2 | B9: 销售人员招聘 | C9: 0.05 | D9: =C9*$D$12 -> 50184705 | E9: =C9*$E$12 -> 57414316 | F9: =$F$12*C9 -> 55900638 | G9: =C9*$G$12 -> 63953686 | H9: =C9*$H$12 -> 61616570 | I9: =C9*$I$12 -> 70493056
A10: 3 | B10: 战略合作与收购 | C10: 0.15 | D10: =C10*$D$12 -> 1.5055412e+08 | E10: =C10*$E$12 -> 1.7224295e+08 | F10: =$F$12*C10 -> 1.6770191e+08 | G10: =C10*$G$12 -> 1.9186106e+08 | H10: =C10*$H$12 -> 1.8484971e+08 | I10: =C10*$I$12 -> 2.1147917e+08
A11: 4 | B11: 补流 | C11: 0.1 | D11: =C11*$D$12 -> 1.0036941e+08 | E11: =C11*$E$12 -> 1.1482863e+08 | F11: =$F$12*C11 -> 1.1180128e+08 | G11: =C11*$G$12 -> 1.2790737e+08 | H11: =C11*$H$12 -> 1.2323314e+08 | I11: =C11*$I$12 -> 1.4098611e+08
B12: 合计 | C12: 1 | D12: =Stats!F29-D15/Stats!I2 -> 1.0036941e+09 | E12: =Stats!F26-D15 -> 1.1482863e+09 | F12: =Stats!G29-D16/Stats!I2 -> 1.1180128e+09 | G12: =Stats!G26-D16 -> 1.2790737e+09 | H12: =Stats!H29-D17/Stats!I2 -> 1.2323314e+09 | I12: =Stats!H26-D17 -> 1.4098611e+09
B15: listing expense | C15: low | D15: 1.1176726e+08
C16: mid | D16: 1.179422e+08
C17: high | D17: 1.2411715e+08
