Workbook

Sheet Sheet1
A1: Currency | B1: HKD | C1: USD | E1: CRNCY_ADJ_MKT_CAP | F1: Crncy Adj Mkt Cap | G1: Px Last | H1: Net Assets | I1: Net Assets | J1: Sales Rev Turn | K1: Sales Rev Turn | L1: Net Income | M1: Net Income | N1: Gross_Margin_Adjusted | O1: EBITDA_MARGIN_ADJUSTED | P1: Prof Margin | Q1: Sales_Growth | R1: Net Inc Growth | S1: TOT_DEBT_TO_TOT_EQY | T1: TOT_DEBT_TO_COM_EQY | U1: NET_DEBT_TO_SHRHLDR_EQTY | V1: TOT_DEBT_TO_TOT_ASSET | W1: RETURN_ON_ASSET | Z1: RETURN_COM_EQY | AD1: Pe Ratio | AJ1: BEST_EV_TO_BEST_EBITDA | AM1: Px To Book Ratio | AT1: EQY_DVD_YLD_IND | AU1: BEST_DIV_YLD | CZ1: CIE_DES
AC2: TTM PE = | AD2: IF(AB7<0,"N/A",$E7/AB7) | AF2: TTM PS = | AG2: $E7/AA7
A3: Company Name | B3: 公司名 | C3: Stock Code | E3: Operating Data | AD3: Valuation | AW3: Forecast CAGR | AZ3: Key financials (USD'b) | CW3: Volatility
D4: Listing date | E4: Market Capitalization (HKD 'm) | F4: Market Capitalization (USD 'm) | G4: Price (Traded Currency) | H4: Net Assets (HKD 'm) | I4: Net Assets (USD 'm) | J4: Revenue (HKD 'm) | K4: Revenue (USD 'm) | L4: Net Profit (HKD 'm) | M4: Net Profit (USD 'm) | N4: GP Margin (%) | O4: EBITDA Margin (%) | P4: NP Margin (%) | Q4: Revenue Growth (%) | R4: NP Growth (%) | S4: Debt to equity | T4: Debt to common equity | U4: Net debt To Shareholders Equity | V4: Total Debt to Total Assets | W4: ROA | X4: EV (HKD'm) | Y4: EV (USD'm) | Z4: ROE | AA4: TTM Sales Profit (HKD 'm) | AB4: TTM Net Profit (HKD 'm) | AC4: TTM EBITDA (HKD 'm) | AD4: PE Ratio (x) | AG4: PS Ratio (x) | AJ4: EV/EBITDA (x) | AM4: PB Ratio (x) | AQ4: ROE (%) | AT4: Dividend Yield (x) | AW4: Revenue | AX4: EBITDA | AY4: Net profit | AZ4: cash flow from operations (USD'b) | BF4: Free cash flow (USD'b) | BL4: Revenue | BR4: EBITDA | BX4: Net profit | CD4: Dividend | CH4: Dividend yield | CL4: 5D Avg ADTV (HKD'm) | CM4: 10D Avg ADTV (HKD'm) | CN4: 20D Avg ADTV (HKD'm) | CO4: 1M Avg ADTV (HKD'm) | CP4: 3M Avg ADTV (HKD'm) | CQ4: 6M Avg ADTV (HKD'm) | CR4: 1M Return | CS4: 3M Return | CT4: 6M Return | CU4: 1Y Return | CV4: YTD Return | CW4: 30-day volatility (%) | CX4: 90-day volatility (%) | CY4: 180-day volatility (%)
AD5: 2025A | AE5: 2026F | AF5: 2027F | AG5: 2025A | AH5: 2026F | AI5: 2027F | AJ5: TTM | AK5: 2026F | AL5: 2027F | AM5: TTM | AN5: 2026F | AO5: 2027F | AP5: 2027F | AQ5: TTM | AR5: 2026F | AS5: 2027F | AT5: TTM | AU5: 2026F | AV5: 2027F | AW5: 2026 vs 2024 | AZ5: CY2022A | BA5: CY2023A | BB5: CY2024A | BC5: CY2025F | BD5: CY2026F | BE5: CY2027F | BF5: CY2022A | BG5: CY2023A | BH5: CY2024A | BI5: CY2025F | BJ5: CY2026F | BK5: CY2027F | BL5: CY2022A | BM5: CY2023A | BN5: CY2024A | BO5: CY2025F | BP5: CY2026F | BQ5: CY2027F | BR5: CY2022A | BS5: CY2023A | BT5: CY2024A | BU5: CY2025F | BV5: CY2026F | BW5: CY2027F | BX5: CY2022A | BY5: CY2023A | BZ5: CY2024A | CA5: CY2025F | CB5: CY2026F | CC5: CY2027F | CD5: CY2024A | CE5: CY2025F | CF5: CY2026F | CG5: CY2027F | CH5: CY2024A | CI5: CY2025F | CJ5: CY2026F | CK5: CY2027F
A7: =_xll.BDP($C7,"security name") -> #NAME? | B7: =_xll.BDP($C7,"NAME_CHINESE_SIMPLIFIED") -> #NAME? | C7: pdsl in Equity | D7: =_xll.BDP($C7,"LISTING_DATE") -> #NAME? | E7: =_xll.BDP($C7,E$1,"EQY_FUND_CRNCY="&$B$1) -> #NAME? | F7: =_xll.BDP($C7,F$1,"EQY_FUND_CRNCY="&$C$1) -> #NAME? | G7: =_xll.BDP($C7,G$1) -> #NAME? | H7: =_xll.BDP($C7,H$1,"EQY_FUND_CRNCY="&$B$1) -> #NAME? | I7: =_xll.BDP($C7,I$1,"EQY_FUND_CRNCY="&$C$1) -> #NAME? | J7: =_xll.BDP($C7,J$1,"EQY_FUND_CRNCY="&$B$1) -> #NAME? | K7: =_xll.BDP($C7,K$1,"EQY_FUND_CRNCY="&$C$1) -> #NAME? | L7: =_xll.BDP($C7,L$1,"EQY_FUND_CRNCY="&$B$1) -> #NAME? | M7: =_xll.BDP($C7,M$1,"EQY_FUND_CRNCY="&$C$1) -> #NAME? | N7: =_xll.BDP($C7,N$1)/100 -> #NAME? | O7: =_xll.BDP($C7,O$1)/100 -> #NAME? | P7: =_xll.BDP($C7,P$1)/100 -> #NAME? | Q7: =_xll.BDP($C7,Q$1)/100 -> #NAME? | R7: =_xll.BDP($C7,R$1)/100 -> #NAME? | S7: =_xll.BDP($C7,S$1)/100 -> #NAME? | T7: =_xll.BDP($C7,T$1)/100 -> #NAME? | U7: =_xll.BDP($C7,U$1)/100 -> #NAME? | ... W7: =_xll.BDP($C7,W$1)/100 -> #NAME? | X7: {=_xll.BDP($C7,"CRNCY_ADJ_CURR_EV", "EQY_FUND_CRNCY=HKD")} -> #NAME? | Y7: {=_xll.BDP($C7,"CRNCY_ADJ_CURR_EV", "EQY_FUND_CRNCY=USD")} -> #NAME? | Z7: =_xll.BDP($C7,Z$1)/100 -> #NAME? | AA7: =_xll.BDP($C7,"TRAIL_12M_NET_SALES","EQY_FUND_CRNCY=HKD") -> #NAME? | AB7: =_xll.BDP($C7,"TRAIL_12M_NET_INC","EQY_FUND_CRNCY=HKD") -> #NAME? | AC7: =_xll.BDP($C7,"TRAIL_12M_EBITDA","EQY_FUND_CRNCY=HKD") -> #NAME? | AD7: {=_xll.BQL($C7, "PE_RATIO(FPT=BA, FPR=2025, FYE=C1231, AE=E)")} -> #NAME? | AE7: {=_xll.BQL($C7, "PE_RATIO(FPT=BA, FPR=2026, FYE=C1231, AE=E)")} -> #NAME? | AF7: {=_xll.BQL($C7, "PE_RATIO(FPT=BA, FPR=2027, FYE=C1231, AE=E)")} -> #NAME? | AG7: {=_xll.BQL($C7, "PX_TO_SALES_RATIO(FPT=BA, FPR=2025, FYE=C1231, AE=E)")} -> #NAME? | AH7: {=_xll.BQL($C7, "PX_TO_SALES_RATIO(FPT=BA, FPR=2026, FYE=C1231, AE=E)")} -> #NAME? | AI7: {=_xll.BQL($C7, "PX_TO_SALES_RATIO(FPT=BA, FPR=2027, FYE=C1231, AE=E)")} -> #NAME? | AJ7: =IF(AC7<0,"N/A",$X7/AC7) -> #NAME? | AK7: {=IF(_xll.BQL($C7, "CURR_ENTP_VAL(FPT=A,FPO=0)/EBITDA(FPT=BA, FPR=2026, FYE=C1231, AE=E)")<0,"N/A",_xll.BQL($C7, "CURR_ENTP_VAL(FPT=A,FPO=0)/EBITDA(FPT=BA, FPR=2026, FYE=C1231, AE=E)"))} -> #NAME? | AL7: {=IF(_xll.BQL($C7, "CURR_ENTP_VAL(FPT=A,FPO=0)/EBITDA(FPT=BA, FPR=2027, FYE=C1231, AE=E)")<0,"N/A",_xll.BQL($C7, "CURR_ENTP_VAL(FPT=A,FPO=0)/EBITDA(FPT=BA, FPR=2027, FYE=C1231, AE=E)"))} -> #NAME? | AM7: =_xll.BDP($C7,AM$1) -> #NAME? | AN7: {=_xll.BQL($C7, "PX_TO_BOOK_RATIO(FPT=BA, FPR=2026, FYE=C1231, AE=E)")} -> #NAME? | AO7: {=_xll.BQL($C7, "PX_TO_BOOK_RATIO(FPT=BA, FPR=2027, FYE=C1231, AE=E)")} -> #NAME? | AP7: =_xll.BDP($C7,"BEST Px bps ratio","BEST fperiod override","27Y") -> #NAME? | AQ7: =Z7 -> #NAME? | AR7: =_xll.BDP($C7,"BEST_ROE","BEST fperiod override","26Y")/100 -> #NAME? | AS7: =_xll.BDP($C7,"BEST_ROE","BEST fperiod override","27Y")/100 -> #NAME? | AT7: =_xll.BDP($C7,AT$1) -> #NAME? | AU7: =_xll.BDP($C7,$AU$1,"BEST fperiod override","26Y") -> #NAME? | AV7: =_xll.BDP($C7,$AU$1,"BEST fperiod override","27Y") -> #NAME? | AW7: =(BP7/BN7)^(1/2)-1 -> #NAME? | AX7: =(BV7/BT7)^(1/2)-1 -> #NAME? | AY7: =(CB7/BZ7)^(1/2)-1 -> #NAME? | AZ7: {=_xll.BQL($C7, "CF_CASH_FROM_OPER(FPT=BA, FPR=2022, FYE=C1231, AE=A)", "currency=USD")/1000000000} -> #NAME? | BA7: {=_xll.BQL($C7, "CF_CASH_FROM_OPER(FPT=BA, FPR=2023, FYE=C1231, AE=A)", "currency=USD")/1000000000} -> #NAME? | BB7: {=_xll.BQL($C7, "CF_CASH_FROM_OPER(FPT=BA, FPR=2024, FYE=C1231, AE=A)", "currency=USD")/1000000000} -> #NAME? | BC7: {=_xll.BQL($C7, "CF_CASH_FROM_OPER(FPT=BA, FPR=2025, FYE=C1231, AE=E)", "currency=USD")/1000000000} -> #NAME? | BD7: {=_xll.BQL($C7, "CF_CASH_FROM_OPER(FPT=BA, FPR=2026, FYE=C1231, AE=E)", "currency=USD")/1000000000} -> #NAME? | BE7: {=_xll.BQL($C7, "CF_CASH_FROM_OPER(FPT=BA, FPR=2027, FYE=C1231, AE=E)", "currency=USD")/1000000000} -> #NAME? | BF7: {=_xll.BQL($C7, "CF_FREE_CASH_FLOW(FPT=BA, FPR=2022, FYE=C1231, AE=A)", "currency=USD")/1000000000} -> #NAME? | BG7: {=_xll.BQL($C7, "CF_FREE_CASH_FLOW(FPT=BA, FPR=2023, FYE=C1231, AE=A)", "currency=USD")/1000000000} -> #NAME? | BH7: {=_xll.BQL($C7, "CF_FREE_CASH_FLOW(FPT=BA, FPR=2024, FYE=C1231, AE=A)", "currency=USD")/1000000000} -> #NAME? | BI7: {=_xll.BQL($C7, "CF_FREE_CASH_FLOW(FPT=BA, FPR=2025, FYE=C1231, AE=E)", "currency=USD")/1000000000} -> #NAME? | BJ7: {=_xll.BQL($C7, "CF_FREE_CASH_FLOW(FPT=BA, FPR=2026, FYE=C1231, AE=E)", "currency=USD")/1000000000} -> #NAME? | BK7: {=_xll.BQL($C7, "CF_FREE_CASH_FLOW(FPT=BA, FPR=2027, FYE=C1231, AE=E)", "currency=USD")/1000000000} -> #NAME? | BL7: {=_xll.BQL($C7, "SALES_REV_TURN(FPT=BA, FPR=2022, FYE=C1231, AE=A)", "currency=USD")/1000000000} -> #NAME? | BM7: {=_xll.BQL($C7, "SALES_REV_TURN(FPT=BA, FPR=2023, FYE=C1231, AE=A)", "currency=USD")/1000000000} -> #NAME? | BN7: {=_xll.BQL($C7, "SALES_REV_TURN(FPT=BA, FPR=2024, FYE=C1231, AE=A)", "currency=USD")/1000000000} -> #NAME? | BO7: {=_xll.BQL($C7, "SALES_REV_TURN(FPT=BA, FPR=2025, FYE=C1231, AE=E)", "currency=USD")/1000000000} -> #NAME? | BP7: {=_xll.BQL($C7, "SALES_REV_TURN(FPT=BA, FPR=2026, FYE=C1231, AE=E)", "currency=USD")/1000000000} -> #NAME? | BQ7: {=_xll.BQL($C7, "SALES_REV_TURN(FPT=BA, FPR=2027, FYE=C1231, AE=E)", "currency=USD")/1000000000} -> #NAME? | BR7: {=_xll.BQL($C7, "EBITDA(FPT=BA, FPR=2022, FYE=C1231, AE=A)", "currency=USD")/1000000000} -> #NAME? | BS7: {=_xll.BQL($C7, "EBITDA(FPT=BA, FPR=2023, FYE=C1231, AE=A)", "currency=USD")/1000000000} -> #NAME? | BT7: {=_xll.BQL($C7, "EBITDA(FPT=BA, FPR=2024, FYE=C1231, AE=A)", "currency=USD")/1000000000} -> #NAME? | BU7: {=_xll.BQL($C7, "EBITDA(FPT=BA, FPR=2025, FYE=C1231, AE=E)", "currency=USD")/1000000000} -> #NAME? | BV7: {=_xll.BQL($C7, "EBITDA(FPT=BA, FPR=2026, FYE=C1231, AE=E)", "currency=USD")/1000000000} -> #NAME? | BW7: {=_xll.BQL($C7, "EBITDA(FPT=BA, FPR=2027, FYE=C1231, AE=E)", "currency=USD")/1000000000} -> #NAME? | BX7: {=_xll.BQL($C7, "NET_INCOME(FPT=BA, FPR=2022, FYE=C1231, AE=A)", "currency=USD")/1000000000} -> #NAME? | BY7: {=_xll.BQL($C7, "NET_INCOME(FPT=BA, FPR=2023, FYE=C1231, AE=A)", "currency=USD")/1000000000} -> #NAME? | BZ7: {=_xll.BQL($C7, "NET_INCOME(FPT=BA, FPR=2024, FYE=C1231, AE=A)", "currency=USD")/1000000000} -> #NAME? | CA7: {=_xll.BQL($C7, "NET_INCOME(FPT=BA, FPR=2025, FYE=C1231, AE=E)", "currency=USD")/1000000000} -> #NAME? | CB7: {=_xll.BQL($C7, "NET_INCOME(FPT=BA, FPR=2026, FYE=C1231, AE=E)", "currency=USD")/1000000000} -> #NAME? | CC7: {=_xll.BQL($C7, "NET_INCOME(FPT=BA, FPR=2027, FYE=C1231, AE=E)", "currency=USD")/1000000000} -> #NAME? | CD7: {=-_xll.BQL($C7, "CF_DVD_PAID(FPT=BA, FPR=2024, FYE=C1231, AE=A)", "currency=USD")/1000000000} -> #NAME? | CE7: {=-_xll.BQL($C7, "CF_DVD_PAID(FPT=BA, FPR=2025, FYE=C1231, AE=E)", "currency=USD")/1000000000} -> #NAME? | CF7: {=-_xll.BQL($C7, "CF_DVD_PAID(FPT=BA, FPR=2026, FYE=C1231, AE=E)", "currency=USD")/1000000000} -> #NAME? | CG7: {=-_xll.BQL($C7, "CF_DVD_PAID(FPT=BA, FPR=2027, FYE=C1231, AE=E)", "currency=USD")/1000000000} -> #NAME? | CH7: =CD7/$F7 -> #NAME? | CI7: =CE7/$F7 -> #NAME? | CJ7: =CF7/$F7 -> #NAME? | CK7: =CG7/$F7 -> #NAME? | CL7: {=_xll.BDP($C7,"INTERVAL_AVG", "MARKET_DATA_OVERRIDE=turnover", "CALC_INTERVAL=5D","CRNCY=HKD")/1000000} -> #NAME? | CM7: {=_xll.BDP($C7,"INTERVAL_AVG", "MARKET_DATA_OVERRIDE=turnover", "CALC_INTERVAL=10D","CRNCY=HKD")/1000000} -> #NAME? | CN7: {=_xll.BDP($C7,"INTERVAL_AVG", "MARKET_DATA_OVERRIDE=turnover", "CALC_INTERVAL=20D","CRNCY=HKD")/1000000} -> #NAME? | CO7: {=_xll.BDP($C7,"INTERVAL_AVG", "MARKET_DATA_OVERRIDE=turnover", "CALC_INTERVAL=1m","CRNCY=HKD")/1000000} -> #NAME? | CP7: {=_xll.BDP($C7,"INTERVAL_AVG", "MARKET_DATA_OVERRIDE=turnover", "CALC_INTERVAL=3M","CRNCY=HKD")/1000000} -> #NAME? | CQ7: {=_xll.BDP($C7,"INTERVAL_AVG", "MARKET_DATA_OVERRIDE=turnover", "CALC_INTERVAL=6M","CRNCY=HKD")/1000000} -> #NAME? | CR7: =_xll.BDP($C7,"chg pct 1m")/100 -> #NAME? | CS7: =_xll.BDP($C7,"chg pct 3m")/100 -> #NAME? | CT7: =_xll.BDP($C7,"chg pct 6m")/100 -> #NAME? | CU7: =_xll.BDP($C7,"chg pct 1yr")/100 -> #NAME? | CV7: =_xll.BDP($C7,"chg pct ytd")/100 -> #NAME? | CW7: {=_xll.BQL($C7, "volatility(calc_interval=range(-1M, 0D))")} -> #NAME? | CX7: {=_xll.BQL($C7, "volatility(calc_interval=range(-3M, 0D))")} -> #NAME? | CY7: {=_xll.BQL($C7, "volatility(calc_interval=range(-6M, 0D))")} -> #NAME? | CZ7: =_xll.BDP($C7,CZ$1) -> #NAME?
A8: =_xll.BDP($C8,"security name") -> #NAME? | B8: =_xll.BDP($C8,"NAME_CHINESE_SIMPLIFIED") -> #NAME? | C8: wmt us Equity | D8: =_xll.BDP($C8,"LISTING_DATE") -> #NAME? | E8: =_xll.BDP($C8,E$1,"EQY_FUND_CRNCY="&$B$1) -> #NAME? | F8: =_xll.BDP($C8,F$1,"EQY_FUND_CRNCY="&$C$1) -> #NAME? | G8: =_xll.BDP($C8,G$1) -> #NAME? | H8: =_xll.BDP($C8,H$1,"EQY_FUND_CRNCY="&$B$1) -> #NAME? | I8: =_xll.BDP($C8,I$1,"EQY_FUND_CRNCY="&$C$1) -> #NAME? | J8: =_xll.BDP($C8,J$1,"EQY_FUND_CRNCY="&$B$1) -> #NAME? | K8: =_xll.BDP($C8,K$1,"EQY_FUND_CRNCY="&$C$1) -> #NAME? | L8: =_xll.BDP($C8,L$1,"EQY_FUND_CRNCY="&$B$1) -> #NAME? | M8: =_xll.BDP($C8,M$1,"EQY_FUND_CRNCY="&$C$1) -> #NAME? | N8: =_xll.BDP($C8,N$1)/100 -> #NAME? | O8: =_xll.BDP($C8,O$1)/100 -> #NAME? | P8: =_xll.BDP($C8,P$1)/100 -> #NAME? | Q8: =_xll.BDP($C8,Q$1)/100 -> #NAME? | R8: =_xll.BDP($C8,R$1)/100 -> #NAME? | S8: =_xll.BDP($C8,S$1)/100 -> #NAME? | T8: =_xll.BDP($C8,T$1)/100 -> #NAME? | U8: =_xll.BDP($C8,U$1)/100 -> #NAME? | ... W8: =_xll.BDP($C8,W$1)/100 -> #NAME? | X8: {=_xll.BDP($C8,"CRNCY_ADJ_CURR_EV", "EQY_FUND_CRNCY=HKD")} -> #NAME? | Y8: {=_xll.BDP($C8,"CRNCY_ADJ_CURR_EV", "EQY_FUND_CRNCY=USD")} -> #NAME? | Z8: =_xll.BDP($C8,Z$1)/100 -> #NAME? | AA8: =_xll.BDP($C8,"TRAIL_12M_NET_SALES","EQY_FUND_CRNCY=HKD") -> #NAME? | AB8: =_xll.BDP($C8,"TRAIL_12M_NET_INC","EQY_FUND_CRNCY=HKD") -> #NAME? | AC8: =_xll.BDP($C8,"TRAIL_12M_EBITDA","EQY_FUND_CRNCY=HKD") -> #NAME? | AD8: {=_xll.BQL($C8, "PE_RATIO(FPT=BA, FPR=2025, FYE=C1231, AE=E)")} -> #NAME? | AE8: {=_xll.BQL($C8, "PE_RATIO(FPT=BA, FPR=2026, FYE=C1231, AE=E)")} -> #NAME? | AF8: {=_xll.BQL($C8, "PE_RATIO(FPT=BA, FPR=2027, FYE=C1231, AE=E)")} -> #NAME? | AG8: {=_xll.BQL($C8, "PX_TO_SALES_RATIO(FPT=BA, FPR=2025, FYE=C1231, AE=E)")} -> #NAME? | AH8: {=_xll.BQL($C8, "PX_TO_SALES_RATIO(FPT=BA, FPR=2026, FYE=C1231, AE=E)")} -> #NAME? | AI8: {=_xll.BQL($C8, "PX_TO_SALES_RATIO(FPT=BA, FPR=2027, FYE=C1231, AE=E)")} -> #NAME? | AJ8: =IF(AC8<0,"N/A",$X8/AC8) -> #NAME? | AK8: {=IF(_xll.BQL($C8, "CURR_ENTP_VAL(FPT=A,FPO=0)/EBITDA(FPT=BA, FPR=2026, FYE=C1231, AE=E)")<0,"N/A",_xll.BQL($C8, "CURR_ENTP_VAL(FPT=A,FPO=0)/EBITDA(FPT=BA, FPR=2026, FYE=C1231, AE=E)"))} -> #NAME? | AL8: {=IF(_xll.BQL($C8, "CURR_ENTP_VAL(FPT=A,FPO=0)/EBITDA(FPT=BA, FPR=2027, FYE=C1231, AE=E)")<0,"N/A",_xll.BQL($C8, "CURR_ENTP_VAL(FPT=A,FPO=0)/EBITDA(FPT=BA, FPR=2027, FYE=C1231, AE=E)"))} -> #NAME? | AM8: =_xll.BDP($C8,AM$1) -> #NAME? | AN8: {=_xll.BQL($C8, "PX_TO_BOOK_RATIO(FPT=BA, FPR=2026, FYE=C1231, AE=E)")} -> #NAME? | AO8: {=_xll.BQL($C8, "PX_TO_BOOK_RATIO(FPT=BA, FPR=2027, FYE=C1231, AE=E)")} -> #NAME? | AP8: =_xll.BDP($C8,"BEST Px bps ratio","BEST fperiod override","27Y") -> #NAME? | AQ8: =Z8 -> #NAME? | AR8: =_xll.BDP($C8,"BEST_ROE","BEST fperiod override","26Y")/100 -> #NAME? | AS8: =_xll.BDP($C8,"BEST_ROE","BEST fperiod override","27Y")/100 -> #NAME? | AT8: =_xll.BDP($C8,AT$1) -> #NAME? | AU8: =_xll.BDP($C8,$AU$1,"BEST fperiod override","26Y") -> #NAME? | AV8: =_xll.BDP($C8,$AU$1,"BEST fperiod override","27Y") -> #NAME? | AW8: =(BP8/BN8)^(1/2)-1 -> #NAME? | AX8: =(BV8/BT8)^(1/2)-1 -> #NAME? | AY8: =(CB8/BZ8)^(1/2)-1 -> #NAME? | AZ8: {=_xll.BQL($C8, "CF_CASH_FROM_OPER(FPT=BA, FPR=2022, FYE=C1231, AE=A)", "currency=USD")/1000000000} -> #NAME? | BA8: {=_xll.BQL($C8, "CF_CASH_FROM_OPER(FPT=BA, FPR=2023, FYE=C1231, AE=A)", "currency=USD")/1000000000} -> #NAME? | BB8: {=_xll.BQL($C8, "CF_CASH_FROM_OPER(FPT=BA, FPR=2024, FYE=C1231, AE=A)", "currency=USD")/1000000000} -> #NAME? | BC8: {=_xll.BQL($C8, "CF_CASH_FROM_OPER(FPT=BA, FPR=2025, FYE=C1231, AE=E)", "currency=USD")/1000000000} -> #NAME? | BD8: {=_xll.BQL($C8, "CF_CASH_FROM_OPER(FPT=BA, FPR=2026, FYE=C1231, AE=E)", "currency=USD")/1000000000} -> #NAME? | BE8: {=_xll.BQL($C8, "CF_CASH_FROM_OPER(FPT=BA, FPR=2027, FYE=C1231, AE=E)", "currency=USD")/1000000000} -> #NAME? | BF8: {=_xll.BQL($C8, "CF_FREE_CASH_FLOW(FPT=BA, FPR=2022, FYE=C1231, AE=A)", "currency=USD")/1000000000} -> #NAME? | BG8: {=_xll.BQL($C8, "CF_FREE_CASH_FLOW(FPT=BA, FPR=2023, FYE=C1231, AE=A)", "currency=USD")/1000000000} -> #NAME? | BH8: {=_xll.BQL($C8, "CF_FREE_CASH_FLOW(FPT=BA, FPR=2024, FYE=C1231, AE=A)", "currency=USD")/1000000000} -> #NAME? | BI8: {=_xll.BQL($C8, "CF_FREE_CASH_FLOW(FPT=BA, FPR=2025, FYE=C1231, AE=E)", "currency=USD")/1000000000} -> #NAME? | BJ8: {=_xll.BQL($C8, "CF_FREE_CASH_FLOW(FPT=BA, FPR=2026, FYE=C1231, AE=E)", "currency=USD")/1000000000} -> #NAME? | BK8: {=_xll.BQL($C8, "CF_FREE_CASH_FLOW(FPT=BA, FPR=2027, FYE=C1231, AE=E)", "currency=USD")/1000000000} -> #NAME? | BL8: {=_xll.BQL($C8, "SALES_REV_TURN(FPT=BA, FPR=2022, FYE=C1231, AE=A)", "currency=USD")/1000000000} -> #NAME? | BM8: {=_xll.BQL($C8, "SALES_REV_TURN(FPT=BA, FPR=2023, FYE=C1231, AE=A)", "currency=USD")/1000000000} -> #NAME? | BN8: {=_xll.BQL($C8, "SALES_REV_TURN(FPT=BA, FPR=2024, FYE=C1231, AE=A)", "currency=USD")/1000000000} -> #NAME? | BO8: {=_xll.BQL($C8, "SALES_REV_TURN(FPT=BA, FPR=2025, FYE=C1231, AE=E)", "currency=USD")/1000000000} -> #NAME? | BP8: {=_xll.BQL($C8, "SALES_REV_TURN(FPT=BA, FPR=2026, FYE=C1231, AE=E)", "currency=USD")/1000000000} -> #NAME? | BQ8: {=_xll.BQL($C8, "SALES_REV_TURN(FPT=BA, FPR=2027, FYE=C1231, AE=E)", "currency=USD")/1000000000} -> #NAME? | BR8: {=_xll.BQL($C8, "EBITDA(FPT=BA, FPR=2022, FYE=C1231, AE=A)", "currency=USD")/1000000000} -> #NAME? | BS8: {=_xll.BQL($C8, "EBITDA(FPT=BA, FPR=2023, FYE=C1231, AE=A)", "currency=USD")/1000000000} -> #NAME? | BT8: {=_xll.BQL($C8, "EBITDA(FPT=BA, FPR=2024, FYE=C1231, AE=A)", "currency=USD")/1000000000} -> #NAME? | BU8: {=_xll.BQL($C8, "EBITDA(FPT=BA, FPR=2025, FYE=C1231, AE=E)", "currency=USD")/1000000000} -> #NAME? | BV8: {=_xll.BQL($C8, "EBITDA(FPT=BA, FPR=2026, FYE=C1231, AE=E)", "currency=USD")/1000000000} -> #NAME? | BW8: {=_xll.BQL($C8, "EBITDA(FPT=BA, FPR=2027, FYE=C1231, AE=E)", "currency=USD")/1000000000} -> #NAME? | BX8: {=_xll.BQL($C8, "NET_INCOME(FPT=BA, FPR=2022, FYE=C1231, AE=A)", "currency=USD")/1000000000} -> #NAME? | BY8: {=_xll.BQL($C8, "NET_INCOME(FPT=BA, FPR=2023, FYE=C1231, AE=A)", "currency=USD")/1000000000} -> #NAME? | BZ8: {=_xll.BQL($C8, "NET_INCOME(FPT=BA, FPR=2024, FYE=C1231, AE=A)", "currency=USD")/1000000000} -> #NAME? | CA8: {=_xll.BQL($C8, "NET_INCOME(FPT=BA, FPR=2025, FYE=C1231, AE=E)", "currency=USD")/1000000000} -> #NAME? | CB8: {=_xll.BQL($C8, "NET_INCOME(FPT=BA, FPR=2026, FYE=C1231, AE=E)", "currency=USD")/1000000000} -> #NAME? | CC8: {=_xll.BQL($C8, "NET_INCOME(FPT=BA, FPR=2027, FYE=C1231, AE=E)", "currency=USD")/1000000000} -> #NAME? | CD8: {=-_xll.BQL($C8, "CF_DVD_PAID(FPT=BA, FPR=2024, FYE=C1231, AE=A)", "currency=USD")/1000000000} -> #NAME? | CE8: {=-_xll.BQL($C8, "CF_DVD_PAID(FPT=BA, FPR=2025, FYE=C1231, AE=E)", "currency=USD")/1000000000} -> #NAME? | CF8: {=-_xll.BQL($C8, "CF_DVD_PAID(FPT=BA, FPR=2026, FYE=C1231, AE=E)", "currency=USD")/1000000000} -> #NAME? | CG8: {=-_xll.BQL($C8, "CF_DVD_PAID(FPT=BA, FPR=2027, FYE=C1231, AE=E)", "currency=USD")/1000000000} -> #NAME? | CH8: =CD8/$F8 -> #NAME? | CI8: =CE8/$F8 -> #NAME? | CJ8: =CF8/$F8 -> #NAME? | CK8: =CG8/$F8 -> #NAME? | CL8: {=_xll.BDP($C8,"INTERVAL_AVG", "MARKET_DATA_OVERRIDE=turnover", "CALC_INTERVAL=5D","CRNCY=HKD")/1000000} -> #NAME? | CM8: {=_xll.BDP($C8,"INTERVAL_AVG", "MARKET_DATA_OVERRIDE=turnover", "CALC_INTERVAL=10D","CRNCY=HKD")/1000000} -> #NAME? | CN8: {=_xll.BDP($C8,"INTERVAL_AVG", "MARKET_DATA_OVERRIDE=turnover", "CALC_INTERVAL=20D","CRNCY=HKD")/1000000} -> #NAME? | CO8: {=_xll.BDP($C8,"INTERVAL_AVG", "MARKET_DATA_OVERRIDE=turnover", "CALC_INTERVAL=1m","CRNCY=HKD")/1000000} -> #NAME? | CP8: {=_xll.BDP($C8,"INTERVAL_AVG", "MARKET_DATA_OVERRIDE=turnover", "CALC_INTERVAL=3M","CRNCY=HKD")/1000000} -> #NAME? | CQ8: {=_xll.BDP($C8,"INTERVAL_AVG", "MARKET_DATA_OVERRIDE=turnover", "CALC_INTERVAL=6M","CRNCY=HKD")/1000000} -> #NAME? | CR8: =_xll.BDP($C8,"chg pct 1m")/100 -> #NAME? | CS8: =_xll.BDP($C8,"chg pct 3m")/100 -> #NAME? | CT8: =_xll.BDP($C8,"chg pct 6m")/100 -> #NAME? | CU8: =_xll.BDP($C8,"chg pct 1yr")/100 -> #NAME? | CV8: =_xll.BDP($C8,"chg pct ytd")/100 -> #NAME? | CW8: {=_xll.BQL($C8, "volatility(calc_interval=range(-1M, 0D))")} -> #NAME? | CX8: {=_xll.BQL($C8, "volatility(calc_interval=range(-3M, 0D))")} -> #NAME? | CY8: {=_xll.BQL($C8, "volatility(calc_interval=range(-6M, 0D))")} -> #NAME? | CZ8: =_xll.BDP($C8,CZ$1) -> #NAME?
A9: =_xll.BDP($C9,"security name") -> #NAME? | B9: =_xll.BDP($C9,"NAME_CHINESE_SIMPLIFIED") -> #NAME? | C9: aeo us Equity | D9: =_xll.BDP($C9,"LISTING_DATE") -> #NAME? | E9: =_xll.BDP($C9,E$1,"EQY_FUND_CRNCY="&$B$1) -> #NAME? | F9: =_xll.BDP($C9,F$1,"EQY_FUND_CRNCY="&$C$1) -> #NAME? | G9: =_xll.BDP($C9,G$1) -> #NAME? | H9: =_xll.BDP($C9,H$1,"EQY_FUND_CRNCY="&$B$1) -> #NAME? | I9: =_xll.BDP($C9,I$1,"EQY_FUND_CRNCY="&$C$1) -> #NAME? | J9: =_xll.BDP($C9,J$1,"EQY_FUND_CRNCY="&$B$1) -> #NAME? | K9: =_xll.BDP($C9,K$1,"EQY_FUND_CRNCY="&$C$1) -> #NAME? | L9: =_xll.BDP($C9,L$1,"EQY_FUND_CRNCY="&$B$1) -> #NAME? | M9: =_xll.BDP($C9,M$1,"EQY_FUND_CRNCY="&$C$1) -> #NAME? | N9: =_xll.BDP($C9,N$1)/100 -> #NAME? | O9: =_xll.BDP($C9,O$1)/100 -> #NAME? | P9: =_xll.BDP($C9,P$1)/100 -> #NAME? | Q9: =_xll.BDP($C9,Q$1)/100 -> #NAME? | R9: =_xll.BDP($C9,R$1)/100 -> #NAME? | S9: =_xll.BDP($C9,S$1)/100 -> #NAME? | T9: =_xll.BDP($C9,T$1)/100 -> #NAME? | U9: =_xll.BDP($C9,U$1)/100 -> #NAME? | ... W9: =_xll.BDP($C9,W$1)/100 -> #NAME? | X9: {=_xll.BDP($C9,"CRNCY_ADJ_CURR_EV", "EQY_FUND_CRNCY=HKD")} -> #NAME? | Y9: {=_xll.BDP($C9,"CRNCY_ADJ_CURR_EV", "EQY_FUND_CRNCY=USD")} -> #NAME? | Z9: =_xll.BDP($C9,Z$1)/100 -> #NAME? | AA9: =_xll.BDP($C9,"TRAIL_12M_NET_SALES","EQY_FUND_CRNCY=HKD") -> #NAME? | AB9: =_xll.BDP($C9,"TRAIL_12M_NET_INC","EQY_FUND_CRNCY=HKD") -> #NAME? | AC9: =_xll.BDP($C9,"TRAIL_12M_EBITDA","EQY_FUND_CRNCY=HKD") -> #NAME? | AD9: {=_xll.BQL($C9, "PE_RATIO(FPT=BA, FPR=2025, FYE=C1231, AE=E)")} -> #NAME? | AE9: {=_xll.BQL($C9, "PE_RATIO(FPT=BA, FPR=2026, FYE=C1231, AE=E)")} -> #NAME? | AF9: {=_xll.BQL($C9, "PE_RATIO(FPT=BA, FPR=2027, FYE=C1231, AE=E)")} -> #NAME? | AG9: {=_xll.BQL($C9, "PX_TO_SALES_RATIO(FPT=BA, FPR=2025, FYE=C1231, AE=E)")} -> #NAME? | AH9: {=_xll.BQL($C9, "PX_TO_SALES_RATIO(FPT=BA, FPR=2026, FYE=C1231, AE=E)")} -> #NAME? | AI9: {=_xll.BQL($C9, "PX_TO_SALES_RATIO(FPT=BA, FPR=2027, FYE=C1231, AE=E)")} -> #NAME? | AJ9: =IF(AC9<0,"N/A",$X9/AC9) -> #NAME? | AK9: {=IF(_xll.BQL($C9, "CURR_ENTP_VAL(FPT=A,FPO=0)/EBITDA(FPT=BA, FPR=2026, FYE=C1231, AE=E)")<0,"N/A",_xll.BQL($C9, "CURR_ENTP_VAL(FPT=A,FPO=0)/EBITDA(FPT=BA, FPR=2026, FYE=C1231, AE=E)"))} -> #NAME? | AL9: {=IF(_xll.BQL($C9, "CURR_ENTP_VAL(FPT=A,FPO=0)/EBITDA(FPT=BA, FPR=2027, FYE=C1231, AE=E)")<0,"N/A",_xll.BQL($C9, "CURR_ENTP_VAL(FPT=A,FPO=0)/EBITDA(FPT=BA, FPR=2027, FYE=C1231, AE=E)"))} -> #NAME? | AM9: =_xll.BDP($C9,AM$1) -> #NAME? | AN9: {=_xll.BQL($C9, "PX_TO_BOOK_RATIO(FPT=BA, FPR=2026, FYE=C1231, AE=E)")} -> #NAME? | AO9: {=_xll.BQL($C9, "PX_TO_BOOK_RATIO(FPT=BA, FPR=2027, FYE=C1231, AE=E)")} -> #NAME? | AP9: =_xll.BDP($C9,"BEST Px bps ratio","BEST fperiod override","27Y") -> #NAME? | AQ9: =Z9 -> #NAME? | AR9: =_xll.BDP($C9,"BEST_ROE","BEST fperiod override","26Y")/100 -> #NAME? | AS9: =_xll.BDP($C9,"BEST_ROE","BEST fperiod override","27Y")/100 -> #NAME? | AT9: =_xll.BDP($C9,AT$1) -> #NAME? | AU9: =_xll.BDP($C9,$AU$1,"BEST fperiod override","26Y") -> #NAME? | AV9: =_xll.BDP($C9,$AU$1,"BEST fperiod override","27Y") -> #NAME? | AW9: =(BP9/BN9)^(1/2)-1 -> #NAME? | AX9: =(BV9/BT9)^(1/2)-1 -> #NAME? | AY9: =(CB9/BZ9)^(1/2)-1 -> #NAME? | AZ9: {=_xll.BQL($C9, "CF_CASH_FROM_OPER(FPT=BA, FPR=2022, FYE=C1231, AE=A)", "currency=USD")/1000000000} -> #NAME? | BA9: {=_xll.BQL($C9, "CF_CASH_FROM_OPER(FPT=BA, FPR=2023, FYE=C1231, AE=A)", "currency=USD")/1000000000} -> #NAME? | BB9: {=_xll.BQL($C9, "CF_CASH_FROM_OPER(FPT=BA, FPR=2024, FYE=C1231, AE=A)", "currency=USD")/1000000000} -> #NAME? | BC9: {=_xll.BQL($C9, "CF_CASH_FROM_OPER(FPT=BA, FPR=2025, FYE=C1231, AE=E)", "currency=USD")/1000000000} -> #NAME? | BD9: {=_xll.BQL($C9, "CF_CASH_FROM_OPER(FPT=BA, FPR=2026, FYE=C1231, AE=E)", "currency=USD")/1000000000} -> #NAME? | BE9: {=_xll.BQL($C9, "CF_CASH_FROM_OPER(FPT=BA, FPR=2027, FYE=C1231, AE=E)", "currency=USD")/1000000000} -> #NAME? | BF9: {=_xll.BQL($C9, "CF_FREE_CASH_FLOW(FPT=BA, FPR=2022, FYE=C1231, AE=A)", "currency=USD")/1000000000} -> #NAME? | BG9: {=_xll.BQL($C9, "CF_FREE_CASH_FLOW(FPT=BA, FPR=2023, FYE=C1231, AE=A)", "currency=USD")/1000000000} -> #NAME? | BH9: {=_xll.BQL($C9, "CF_FREE_CASH_FLOW(FPT=BA, FPR=2024, FYE=C1231, AE=A)", "currency=USD")/1000000000} -> #NAME? | BI9: {=_xll.BQL($C9, "CF_FREE_CASH_FLOW(FPT=BA, FPR=2025, FYE=C1231, AE=E)", "currency=USD")/1000000000} -> #NAME? | BJ9: {=_xll.BQL($C9, "CF_FREE_CASH_FLOW(FPT=BA, FPR=2026, FYE=C1231, AE=E)", "currency=USD")/1000000000} -> #NAME? | BK9: {=_xll.BQL($C9, "CF_FREE_CASH_FLOW(FPT=BA, FPR=2027, FYE=C1231, AE=E)", "currency=USD")/1000000000} -> #NAME? | BL9: {=_xll.BQL($C9, "SALES_REV_TURN(FPT=BA, FPR=2022, FYE=C1231, AE=A)", "currency=USD")/1000000000} -> #NAME? | BM9: {=_xll.BQL($C9, "SALES_REV_TURN(FPT=BA, FPR=2023, FYE=C1231, AE=A)", "currency=USD")/1000000000} -> #NAME? | BN9: {=_xll.BQL($C9, "SALES_REV_TURN(FPT=BA, FPR=2024, FYE=C1231, AE=A)", "currency=USD")/1000000000} -> #NAME? | BO9: {=_xll.BQL($C9, "SALES_REV_TURN(FPT=BA, FPR=2025, FYE=C1231, AE=E)", "currency=USD")/1000000000} -> #NAME? | BP9: {=_xll.BQL($C9, "SALES_REV_TURN(FPT=BA, FPR=2026, FYE=C1231, AE=E)", "currency=USD")/1000000000} -> #NAME? | BQ9: {=_xll.BQL($C9, "SALES_REV_TURN(FPT=BA, FPR=2027, FYE=C1231, AE=E)", "currency=USD")/1000000000} -> #NAME? | BR9: {=_xll.BQL($C9, "EBITDA(FPT=BA, FPR=2022, FYE=C1231, AE=A)", "currency=USD")/1000000000} -> #NAME? | BS9: {=_xll.BQL($C9, "EBITDA(FPT=BA, FPR=2023, FYE=C1231, AE=A)", "currency=USD")/1000000000} -> #NAME? | BT9: {=_xll.BQL($C9, "EBITDA(FPT=BA, FPR=2024, FYE=C1231, AE=A)", "currency=USD")/1000000000} -> #NAME? | BU9: {=_xll.BQL($C9, "EBITDA(FPT=BA, FPR=2025, FYE=C1231, AE=E)", "currency=USD")/1000000000} -> #NAME? | BV9: {=_xll.BQL($C9, "EBITDA(FPT=BA, FPR=2026, FYE=C1231, AE=E)", "currency=USD")/1000000000} -> #NAME? | BW9: {=_xll.BQL($C9, "EBITDA(FPT=BA, FPR=2027, FYE=C1231, AE=E)", "currency=USD")/1000000000} -> #NAME? | BX9: {=_xll.BQL($C9, "NET_INCOME(FPT=BA, FPR=2022, FYE=C1231, AE=A)", "currency=USD")/1000000000} -> #NAME? | BY9: {=_xll.BQL($C9, "NET_INCOME(FPT=BA, FPR=2023, FYE=C1231, AE=A)", "currency=USD")/1000000000} -> #NAME? | BZ9: {=_xll.BQL($C9, "NET_INCOME(FPT=BA, FPR=2024, FYE=C1231, AE=A)", "currency=USD")/1000000000} -> #NAME? | CA9: {=_xll.BQL($C9, "NET_INCOME(FPT=BA, FPR=2025, FYE=C1231, AE=E)", "currency=USD")/1000000000} -> #NAME? | CB9: {=_xll.BQL($C9, "NET_INCOME(FPT=BA, FPR=2026, FYE=C1231, AE=E)", "currency=USD")/1000000000} -> #NAME? | CC9: {=_xll.BQL($C9, "NET_INCOME(FPT=BA, FPR=2027, FYE=C1231, AE=E)", "currency=USD")/1000000000} -> #NAME? | CD9: {=-_xll.BQL($C9, "CF_DVD_PAID(FPT=BA, FPR=2024, FYE=C1231, AE=A)", "currency=USD")/1000000000} -> #NAME? | CE9: {=-_xll.BQL($C9, "CF_DVD_PAID(FPT=BA, FPR=2025, FYE=C1231, AE=E)", "currency=USD")/1000000000} -> #NAME? | CF9: {=-_xll.BQL($C9, "CF_DVD_PAID(FPT=BA, FPR=2026, FYE=C1231, AE=E)", "currency=USD")/1000000000} -> #NAME? | CG9: {=-_xll.BQL($C9, "CF_DVD_PAID(FPT=BA, FPR=2027, FYE=C1231, AE=E)", "currency=USD")/1000000000} -> #NAME? | CH9: =CD9/$F9 -> #NAME? | CI9: =CE9/$F9 -> #NAME? | CJ9: =CF9/$F9 -> #NAME? | CK9: =CG9/$F9 -> #NAME? | CL9: {=_xll.BDP($C9,"INTERVAL_AVG", "MARKET_DATA_OVERRIDE=turnover", "CALC_INTERVAL=5D","CRNCY=HKD")/1000000} -> #NAME? | CM9: {=_xll.BDP($C9,"INTERVAL_AVG", "MARKET_DATA_OVERRIDE=turnover", "CALC_INTERVAL=10D","CRNCY=HKD")/1000000} -> #NAME? | CN9: {=_xll.BDP($C9,"INTERVAL_AVG", "MARKET_DATA_OVERRIDE=turnover", "CALC_INTERVAL=20D","CRNCY=HKD")/1000000} -> #NAME? | CO9: {=_xll.BDP($C9,"INTERVAL_AVG", "MARKET_DATA_OVERRIDE=turnover", "CALC_INTERVAL=1m","CRNCY=HKD")/1000000} -> #NAME? | CP9: {=_xll.BDP($C9,"INTERVAL_AVG", "MARKET_DATA_OVERRIDE=turnover", "CALC_INTERVAL=3M","CRNCY=HKD")/1000000} -> #NAME? | CQ9: {=_xll.BDP($C9,"INTERVAL_AVG", "MARKET_DATA_OVERRIDE=turnover", "CALC_INTERVAL=6M","CRNCY=HKD")/1000000} -> #NAME? | CR9: =_xll.BDP($C9,"chg pct 1m")/100 -> #NAME? | CS9: =_xll.BDP($C9,"chg pct 3m")/100 -> #NAME? | CT9: =_xll.BDP($C9,"chg pct 6m")/100 -> #NAME? | CU9: =_xll.BDP($C9,"chg pct 1yr")/100 -> #NAME? | CV9: =_xll.BDP($C9,"chg pct ytd")/100 -> #NAME? | CW9: {=_xll.BQL($C9, "volatility(calc_interval=range(-1M, 0D))")} -> #NAME? | CX9: {=_xll.BQL($C9, "volatility(calc_interval=range(-3M, 0D))")} -> #NAME? | CY9: {=_xll.BQL($C9, "volatility(calc_interval=range(-6M, 0D))")} -> #NAME? | CZ9: =_xll.BDP($C9,CZ$1) -> #NAME?
A10: =_xll.BDP($C10,"security name") -> #NAME? | B10: =_xll.BDP($C10,"NAME_CHINESE_SIMPLIFIED") -> #NAME? | C10: cost us Equity | D10: =_xll.BDP($C10,"LISTING_DATE") -> #NAME? | E10: =_xll.BDP($C10,E$1,"EQY_FUND_CRNCY="&$B$1) -> #NAME? | F10: =_xll.BDP($C10,F$1,"EQY_FUND_CRNCY="&$C$1) -> #NAME? | G10: =_xll.BDP($C10,G$1) -> #NAME? | H10: =_xll.BDP($C10,H$1,"EQY_FUND_CRNCY="&$B$1) -> #NAME? | I10: =_xll.BDP($C10,I$1,"EQY_FUND_CRNCY="&$C$1) -> #NAME? | J10: =_xll.BDP($C10,J$1,"EQY_FUND_CRNCY="&$B$1) -> #NAME? | K10: =_xll.BDP($C10,K$1,"EQY_FUND_CRNCY="&$C$1) -> #NAME? | L10: =_xll.BDP($C10,L$1,"EQY_FUND_CRNCY="&$B$1) -> #NAME? | M10: =_xll.BDP($C10,M$1,"EQY_FUND_CRNCY="&$C$1) -> #NAME? | N10: =_xll.BDP($C10,N$1)/100 -> #NAME? | O10: =_xll.BDP($C10,O$1)/100 -> #NAME? | P10: =_xll.BDP($C10,P$1)/100 -> #NAME? | Q10: =_xll.BDP($C10,Q$1)/100 -> #NAME? | R10: =_xll.BDP($C10,R$1)/100 -> #NAME? | S10: =_xll.BDP($C10,S$1)/100 -> #NAME? | T10: =_xll.BDP($C10,T$1)/100 -> #NAME? | U10: =_xll.BDP($C10,U$1)/100 -> #NAME? | ... W10: =_xll.BDP($C10,W$1)/100 -> #NAME? | X10: {=_xll.BDP($C10,"CRNCY_ADJ_CURR_EV", "EQY_FUND_CRNCY=HKD")} -> #NAME? | Y10: {=_xll.BDP($C10,"CRNCY_ADJ_CURR_EV", "EQY_FUND_CRNCY=USD")} -> #NAME? | Z10: =_xll.BDP($C10,Z$1)/100 -> #NAME? | AA10: =_xll.BDP($C10,"TRAIL_12M_NET_SALES","EQY_FUND_CRNCY=HKD") -> #NAME? | AB10: =_xll.BDP($C10,"TRAIL_12M_NET_INC","EQY_FUND_CRNCY=HKD") -> #NAME? | AC10: =_xll.BDP($C10,"TRAIL_12M_EBITDA","EQY_FUND_CRNCY=HKD") -> #NAME? | AD10: {=_xll.BQL($C10, "PE_RATIO(FPT=BA, FPR=2025, FYE=C1231, AE=E)")} -> #NAME? | AE10: {=_xll.BQL($C10, "PE_RATIO(FPT=BA, FPR=2026, FYE=C1231, AE=E)")} -> #NAME? | AF10: {=_xll.BQL($C10, "PE_RATIO(FPT=BA, FPR=2027, FYE=C1231, AE=E)")} -> #NAME? | AG10: {=_xll.BQL($C10, "PX_TO_SALES_RATIO(FPT=BA, FPR=2025, FYE=C1231, AE=E)")} -> #NAME? | AH10: {=_xll.BQL($C10, "PX_TO_SALES_RATIO(FPT=BA, FPR=2026, FYE=C1231, AE=E)")} -> #NAME? | AI10: {=_xll.BQL($C10, "PX_TO_SALES_RATIO(FPT=BA, FPR=2027, FYE=C1231, AE=E)")} -> #NAME? | AJ10: =IF(AC10<0,"N/A",$X10/AC10) -> #NAME? | AK10: {=IF(_xll.BQL($C10, "CURR_ENTP_VAL(FPT=A,FPO=0)/EBITDA(FPT=BA, FPR=2026, FYE=C1231, AE=E)")<0,"N/A",_xll.BQL($C10, "CURR_ENTP_VAL(FPT=A,FPO=0)/EBITDA(FPT=BA, FPR=2026, FYE=C1231, AE=E)"))} -> #NAME? | AL10: {=IF(_xll.BQL($C10, "CURR_ENTP_VAL(FPT=A,FPO=0)/EBITDA(FPT=BA, FPR=2027, FYE=C1231, AE=E)")<0,"N/A",_xll.BQL($C10, "CURR_ENTP_VAL(FPT=A,FPO=0)/EBITDA(FPT=BA, FPR=2027, FYE=C1231, AE=E)"))} -> #NAME? | AM10: =_xll.BDP($C10,AM$1) -> #NAME? | AN10: {=_xll.BQL($C10, "PX_TO_BOOK_RATIO(FPT=BA, FPR=2026, FYE=C1231, AE=E)")} -> #NAME? | AO10: {=_xll.BQL($C10, "PX_TO_BOOK_RATIO(FPT=BA, FPR=2027, FYE=C1231, AE=E)")} -> #NAME? | AP10: =_xll.BDP($C10,"BEST Px bps ratio","BEST fperiod override","27Y") -> #NAME? | AQ10: =Z10 -> #NAME? | AR10: =_xll.BDP($C10,"BEST_ROE","BEST fperiod override","26Y")/100 -> #NAME? | AS10: =_xll.BDP($C10,"BEST_ROE","BEST fperiod override","27Y")/100 -> #NAME? | AT10: =_xll.BDP($C10,AT$1) -> #NAME? | AU10: =_xll.BDP($C10,$AU$1,"BEST fperiod override","26Y") -> #NAME? | AV10: =_xll.BDP($C10,$AU$1,"BEST fperiod override","27Y") -> #NAME? | AW10: =(BP10/BN10)^(1/2)-1 -> #NAME? | AX10: =(BV10/BT10)^(1/2)-1 -> #NAME? | AY10: =(CB10/BZ10)^(1/2)-1 -> #NAME? | AZ10: {=_xll.BQL($C10, "CF_CASH_FROM_OPER(FPT=BA, FPR=2022, FYE=C1231, AE=A)", "currency=USD")/1000000000} -> #NAME? | BA10: {=_xll.BQL($C10, "CF_CASH_FROM_OPER(FPT=BA, FPR=2023, FYE=C1231, AE=A)", "currency=USD")/1000000000} -> #NAME? | BB10: {=_xll.BQL($C10, "CF_CASH_FROM_OPER(FPT=BA, FPR=2024, FYE=C1231, AE=A)", "currency=USD")/1000000000} -> #NAME? | BC10: {=_xll.BQL($C10, "CF_CASH_FROM_OPER(FPT=BA, FPR=2025, FYE=C1231, AE=E)", "currency=USD")/1000000000} -> #NAME? | BD10: {=_xll.BQL($C10, "CF_CASH_FROM_OPER(FPT=BA, FPR=2026, FYE=C1231, AE=E)", "currency=USD")/1000000000} -> #NAME? | BE10: {=_xll.BQL($C10, "CF_CASH_FROM_OPER(FPT=BA, FPR=2027, FYE=C1231, AE=E)", "currency=USD")/1000000000} -> #NAME? | BF10: {=_xll.BQL($C10, "CF_FREE_CASH_FLOW(FPT=BA, FPR=2022, FYE=C1231, AE=A)", "currency=USD")/1000000000} -> #NAME? | BG10: {=_xll.BQL($C10, "CF_FREE_CASH_FLOW(FPT=BA, FPR=2023, FYE=C1231, AE=A)", "currency=USD")/1000000000} -> #NAME? | BH10: {=_xll.BQL($C10, "CF_FREE_CASH_FLOW(FPT=BA, FPR=2024, FYE=C1231, AE=A)", "currency=USD")/1000000000} -> #NAME? | BI10: {=_xll.BQL($C10, "CF_FREE_CASH_FLOW(FPT=BA, FPR=2025, FYE=C1231, AE=E)", "currency=USD")/1000000000} -> #NAME? | BJ10: {=_xll.BQL($C10, "CF_FREE_CASH_FLOW(FPT=BA, FPR=2026, FYE=C1231, AE=E)", "currency=USD")/1000000000} -> #NAME? | BK10: {=_xll.BQL($C10, "CF_FREE_CASH_FLOW(FPT=BA, FPR=2027, FYE=C1231, AE=E)", "currency=USD")/1000000000} -> #NAME? | BL10: {=_xll.BQL($C10, "SALES_REV_TURN(FPT=BA, FPR=2022, FYE=C1231, AE=A)", "currency=USD")/1000000000} -> #NAME? | BM10: {=_xll.BQL($C10, "SALES_REV_TURN(FPT=BA, FPR=2023, FYE=C1231, AE=A)", "currency=USD")/1000000000} -> #NAME? | BN10: {=_xll.BQL($C10, "SALES_REV_TURN(FPT=BA, FPR=2024, FYE=C1231, AE=A)", "currency=USD")/1000000000} -> #NAME? | BO10: {=_xll.BQL($C10, "SALES_REV_TURN(FPT=BA, FPR=2025, FYE=C1231, AE=E)", "currency=USD")/1000000000} -> #NAME? | BP10: {=_xll.BQL($C10, "SALES_REV_TURN(FPT=BA, FPR=2026, FYE=C1231, AE=E)", "currency=USD")/1000000000} -> #NAME? | BQ10: {=_xll.BQL($C10, "SALES_REV_TURN(FPT=BA, FPR=2027, FYE=C1231, AE=E)", "currency=USD")/1000000000} -> #NAME? | BR10: {=_xll.BQL($C10, "EBITDA(FPT=BA, FPR=2022, FYE=C1231, AE=A)", "currency=USD")/1000000000} -> #NAME? | BS10: {=_xll.BQL($C10, "EBITDA(FPT=BA, FPR=2023, FYE=C1231, AE=A)", "currency=USD")/1000000000} -> #NAME? | BT10: {=_xll.BQL($C10, "EBITDA(FPT=BA, FPR=2024, FYE=C1231, AE=A)", "currency=USD")/1000000000} -> #NAME? | BU10: {=_xll.BQL($C10, "EBITDA(FPT=BA, FPR=2025, FYE=C1231, AE=E)", "currency=USD")/1000000000} -> #NAME? | BV10: {=_xll.BQL($C10, "EBITDA(FPT=BA, FPR=2026, FYE=C1231, AE=E)", "currency=USD")/1000000000} -> #NAME? | BW10: {=_xll.BQL($C10, "EBITDA(FPT=BA, FPR=2027, FYE=C1231, AE=E)", "currency=USD")/1000000000} -> #NAME? | BX10: {=_xll.BQL($C10, "NET_INCOME(FPT=BA, FPR=2022, FYE=C1231, AE=A)", "currency=USD")/1000000000} -> #NAME? | BY10: {=_xll.BQL($C10, "NET_INCOME(FPT=BA, FPR=2023, FYE=C1231, AE=A)", "currency=USD")/1000000000} -> #NAME? | BZ10: {=_xll.BQL($C10, "NET_INCOME(FPT=BA, FPR=2024, FYE=C1231, AE=A)", "currency=USD")/1000000000} -> #NAME? | CA10: {=_xll.BQL($C10, "NET_INCOME(FPT=BA, FPR=2025, FYE=C1231, AE=E)", "currency=USD")/1000000000} -> #NAME? | CB10: {=_xll.BQL($C10, "NET_INCOME(FPT=BA, FPR=2026, FYE=C1231, AE=E)", "currency=USD")/1000000000} -> #NAME? | CC10: {=_xll.BQL($C10, "NET_INCOME(FPT=BA, FPR=2027, FYE=C1231, AE=E)", "currency=USD")/1000000000} -> #NAME? | CD10: {=-_xll.BQL($C10, "CF_DVD_PAID(FPT=BA, FPR=2024, FYE=C1231, AE=A)", "currency=USD")/1000000000} -> #NAME? | CE10: {=-_xll.BQL($C10, "CF_DVD_PAID(FPT=BA, FPR=2025, FYE=C1231, AE=E)", "currency=USD")/1000000000} -> #NAME? | CF10: {=-_xll.BQL($C10, "CF_DVD_PAID(FPT=BA, FPR=2026, FYE=C1231, AE=E)", "currency=USD")/1000000000} -> #NAME? | CG10: {=-_xll.BQL($C10, "CF_DVD_PAID(FPT=BA, FPR=2027, FYE=C1231, AE=E)", "currency=USD")/1000000000} -> #NAME? | CH10: =CD10/$F10 -> #NAME? | CI10: =CE10/$F10 -> #NAME? | CJ10: =CF10/$F10 -> #NAME? | CK10: =CG10/$F10 -> #NAME? | CL10: {=_xll.BDP($C10,"INTERVAL_AVG", "MARKET_DATA_OVERRIDE=turnover", "CALC_INTERVAL=5D","CRNCY=HKD")/1000000} -> #NAME? | CM10: {=_xll.BDP($C10,"INTERVAL_AVG", "MARKET_DATA_OVERRIDE=turnover", "CALC_INTERVAL=10D","CRNCY=HKD")/1000000} -> #NAME? | CN10: {=_xll.BDP($C10,"INTERVAL_AVG", "MARKET_DATA_OVERRIDE=turnover", "CALC_INTERVAL=20D","CRNCY=HKD")/1000000} -> #NAME? | CO10: {=_xll.BDP($C10,"INTERVAL_AVG", "MARKET_DATA_OVERRIDE=turnover", "CALC_INTERVAL=1m","CRNCY=HKD")/1000000} -> #NAME? | CP10: {=_xll.BDP($C10,"INTERVAL_AVG", "MARKET_DATA_OVERRIDE=turnover", "CALC_INTERVAL=3M","CRNCY=HKD")/1000000} -> #NAME? | CQ10: {=_xll.BDP($C10,"INTERVAL_AVG", "MARKET_DATA_OVERRIDE=turnover", "CALC_INTERVAL=6M","CRNCY=HKD")/1000000} -> #NAME? | CR10: =_xll.BDP($C10,"chg pct 1m")/100 -> #NAME? | CS10: =_xll.BDP($C10,"chg pct 3m")/100 -> #NAME? | CT10: =_xll.BDP($C10,"chg pct 6m")/100 -> #NAME? | CU10: =_xll.BDP($C10,"chg pct 1yr")/100 -> #NAME? | CV10: =_xll.BDP($C10,"chg pct ytd")/100 -> #NAME? | CW10: {=_xll.BQL($C10, "volatility(calc_interval=range(-1M, 0D))")} -> #NAME? | CX10: {=_xll.BQL($C10, "volatility(calc_interval=range(-3M, 0D))")} -> #NAME? | CY10: {=_xll.BQL($C10, "volatility(calc_interval=range(-6M, 0D))")} -> #NAME? | CZ10: =_xll.BDP($C10,CZ$1) -> #NAME?
A11: =_xll.BDP($C11,"security name") -> #NAME? | B11: =_xll.BDP($C11,"NAME_CHINESE_SIMPLIFIED") -> #NAME? | C11: abf ln EQUITY | D11: =_xll.BDP($C11,"LISTING_DATE") -> #NAME? | E11: =_xll.BDP($C11,E$1,"EQY_FUND_CRNCY="&$B$1) -> #NAME? | F11: =_xll.BDP($C11,F$1,"EQY_FUND_CRNCY="&$C$1) -> #NAME? | G11: =_xll.BDP($C11,G$1) -> #NAME? | H11: =_xll.BDP($C11,H$1,"EQY_FUND_CRNCY="&$B$1) -> #NAME? | I11: =_xll.BDP($C11,I$1,"EQY_FUND_CRNCY="&$C$1) -> #NAME? | J11: =_xll.BDP($C11,J$1,"EQY_FUND_CRNCY="&$B$1) -> #NAME? | K11: =_xll.BDP($C11,K$1,"EQY_FUND_CRNCY="&$C$1) -> #NAME? | L11: =_xll.BDP($C11,L$1,"EQY_FUND_CRNCY="&$B$1) -> #NAME? | M11: =_xll.BDP($C11,M$1,"EQY_FUND_CRNCY="&$C$1) -> #NAME? | N11: =_xll.BDP($C11,N$1)/100 -> #NAME? | O11: =_xll.BDP($C11,O$1)/100 -> #NAME? | P11: =_xll.BDP($C11,P$1)/100 -> #NAME? | Q11: =_xll.BDP($C11,Q$1)/100 -> #NAME? | R11: =_xll.BDP($C11,R$1)/100 -> #NAME? | S11: =_xll.BDP($C11,S$1)/100 -> #NAME? | T11: =_xll.BDP($C11,T$1)/100 -> #NAME? | U11: =_xll.BDP($C11,U$1)/100 -> #NAME? | ... W11: =_xll.BDP($C11,W$1)/100 -> #NAME? | X11: {=_xll.BDP($C11,"CRNCY_ADJ_CURR_EV", "EQY_FUND_CRNCY=HKD")} -> #NAME? | Y11: {=_xll.BDP($C11,"CRNCY_ADJ_CURR_EV", "EQY_FUND_CRNCY=USD")} -> #NAME? | Z11: =_xll.BDP($C11,Z$1)/100 -> #NAME? | AA11: =_xll.BDP($C11,"TRAIL_12M_NET_SALES","EQY_FUND_CRNCY=HKD") -> #NAME? | AB11: =_xll.BDP($C11,"TRAIL_12M_NET_INC","EQY_FUND_CRNCY=HKD") -> #NAME? | AC11: =_xll.BDP($C11,"TRAIL_12M_EBITDA","EQY_FUND_CRNCY=HKD") -> #NAME? | AD11: {=_xll.BQL($C11, "PE_RATIO(FPT=BA, FPR=2025, FYE=C1231, AE=E)")} -> #NAME? | AE11: {=_xll.BQL($C11, "PE_RATIO(FPT=BA, FPR=2026, FYE=C1231, AE=E)")} -> #NAME? | AF11: {=_xll.BQL($C11, "PE_RATIO(FPT=BA, FPR=2027, FYE=C1231, AE=E)")} -> #NAME? | AG11: {=_xll.BQL($C11, "PX_TO_SALES_RATIO(FPT=BA, FPR=2025, FYE=C1231, AE=E)")} -> #NAME? | AH11: {=_xll.BQL($C11, "PX_TO_SALES_RATIO(FPT=BA, FPR=2026, FYE=C1231, AE=E)")} -> #NAME? | AI11: {=_xll.BQL($C11, "PX_TO_SALES_RATIO(FPT=BA, FPR=2027, FYE=C1231, AE=E)")} -> #NAME? | AJ11: =IF(AC11<0,"N/A",$X11/AC11) -> #NAME? | AK11: {=IF(_xll.BQL($C11, "CURR_ENTP_VAL(FPT=A,FPO=0)/EBITDA(FPT=BA, FPR=2026, FYE=C1231, AE=E)")<0,"N/A",_xll.BQL($C11, "CURR_ENTP_VAL(FPT=A,FPO=0)/EBITDA(FPT=BA, FPR=2026, FYE=C1231, AE=E)"))} -> #NAME? | AL11: {=IF(_xll.BQL($C11, "CURR_ENTP_VAL(FPT=A,FPO=0)/EBITDA(FPT=BA, FPR=2027, FYE=C1231, AE=E)")<0,"N/A",_xll.BQL($C11, "CURR_ENTP_VAL(FPT=A,FPO=0)/EBITDA(FPT=BA, FPR=2027, FYE=C1231, AE=E)"))} -> #NAME? | AM11: =_xll.BDP($C11,AM$1) -> #NAME? | AN11: {=_xll.BQL($C11, "PX_TO_BOOK_RATIO(FPT=BA, FPR=2026, FYE=C1231, AE=E)")} -> #NAME? | AO11: {=_xll.BQL($C11, "PX_TO_BOOK_RATIO(FPT=BA, FPR=2027, FYE=C1231, AE=E)")} -> #NAME? | AP11: =_xll.BDP($C11,"BEST Px bps ratio","BEST fperiod override","27Y") -> #NAME? | AQ11: =Z11 -> #NAME? | AR11: =_xll.BDP($C11,"BEST_ROE","BEST fperiod override","26Y")/100 -> #NAME? | AS11: =_xll.BDP($C11,"BEST_ROE","BEST fperiod override","27Y")/100 -> #NAME? | AT11: =_xll.BDP($C11,AT$1) -> #NAME? | AU11: =_xll.BDP($C11,$AU$1,"BEST fperiod override","26Y") -> #NAME? | AV11: =_xll.BDP($C11,$AU$1,"BEST fperiod override","27Y") -> #NAME? | AW11: =(BP11/BN11)^(1/2)-1 -> #NAME? | AX11: =(BV11/BT11)^(1/2)-1 -> #NAME? | AY11: =(CB11/BZ11)^(1/2)-1 -> #NAME? | AZ11: {=_xll.BQL($C11, "CF_CASH_FROM_OPER(FPT=BA, FPR=2022, FYE=C1231, AE=A)", "currency=USD")/1000000000} -> #NAME? | BA11: {=_xll.BQL($C11, "CF_CASH_FROM_OPER(FPT=BA, FPR=2023, FYE=C1231, AE=A)", "currency=USD")/1000000000} -> #NAME? | BB11: {=_xll.BQL($C11, "CF_CASH_FROM_OPER(FPT=BA, FPR=2024, FYE=C1231, AE=A)", "currency=USD")/1000000000} -> #NAME? | BC11: {=_xll.BQL($C11, "CF_CASH_FROM_OPER(FPT=BA, FPR=2025, FYE=C1231, AE=E)", "currency=USD")/1000000000} -> #NAME? | BD11: {=_xll.BQL($C11, "CF_CASH_FROM_OPER(FPT=BA, FPR=2026, FYE=C1231, AE=E)", "currency=USD")/1000000000} -> #NAME? | BE11: {=_xll.BQL($C11, "CF_CASH_FROM_OPER(FPT=BA, FPR=2027, FYE=C1231, AE=E)", "currency=USD")/1000000000} -> #NAME? | BF11: {=_xll.BQL($C11, "CF_FREE_CASH_FLOW(FPT=BA, FPR=2022, FYE=C1231, AE=A)", "currency=USD")/1000000000} -> #NAME? | BG11: {=_xll.BQL($C11, "CF_FREE_CASH_FLOW(FPT=BA, FPR=2023, FYE=C1231, AE=A)", "currency=USD")/1000000000} -> #NAME? | BH11: {=_xll.BQL($C11, "CF_FREE_CASH_FLOW(FPT=BA, FPR=2024, FYE=C1231, AE=A)", "currency=USD")/1000000000} -> #NAME? | BI11: {=_xll.BQL($C11, "CF_FREE_CASH_FLOW(FPT=BA, FPR=2025, FYE=C1231, AE=E)", "currency=USD")/1000000000} -> #NAME? | BJ11: {=_xll.BQL($C11, "CF_FREE_CASH_FLOW(FPT=BA, FPR=2026, FYE=C1231, AE=E)", "currency=USD")/1000000000} -> #NAME? | BK11: {=_xll.BQL($C11, "CF_FREE_CASH_FLOW(FPT=BA, FPR=2027, FYE=C1231, AE=E)", "currency=USD")/1000000000} -> #NAME? | BL11: {=_xll.BQL($C11, "SALES_REV_TURN(FPT=BA, FPR=2022, FYE=C1231, AE=A)", "currency=USD")/1000000000} -> #NAME? | BM11: {=_xll.BQL($C11, "SALES_REV_TURN(FPT=BA, FPR=2023, FYE=C1231, AE=A)", "currency=USD")/1000000000} -> #NAME? | BN11: {=_xll.BQL($C11, "SALES_REV_TURN(FPT=BA, FPR=2024, FYE=C1231, AE=A)", "currency=USD")/1000000000} -> #NAME? | BO11: {=_xll.BQL($C11, "SALES_REV_TURN(FPT=BA, FPR=2025, FYE=C1231, AE=E)", "currency=USD")/1000000000} -> #NAME? | BP11: {=_xll.BQL($C11, "SALES_REV_TURN(FPT=BA, FPR=2026, FYE=C1231, AE=E)", "currency=USD")/1000000000} -> #NAME? | BQ11: {=_xll.BQL($C11, "SALES_REV_TURN(FPT=BA, FPR=2027, FYE=C1231, AE=E)", "currency=USD")/1000000000} -> #NAME? | BR11: {=_xll.BQL($C11, "EBITDA(FPT=BA, FPR=2022, FYE=C1231, AE=A)", "currency=USD")/1000000000} -> #NAME? | BS11: {=_xll.BQL($C11, "EBITDA(FPT=BA, FPR=2023, FYE=C1231, AE=A)", "currency=USD")/1000000000} -> #NAME? | BT11: {=_xll.BQL($C11, "EBITDA(FPT=BA, FPR=2024, FYE=C1231, AE=A)", "currency=USD")/1000000000} -> #NAME? | BU11: {=_xll.BQL($C11, "EBITDA(FPT=BA, FPR=2025, FYE=C1231, AE=E)", "currency=USD")/1000000000} -> #NAME? | BV11: {=_xll.BQL($C11, "EBITDA(FPT=BA, FPR=2026, FYE=C1231, AE=E)", "currency=USD")/1000000000} -> #NAME? | BW11: {=_xll.BQL($C11, "EBITDA(FPT=BA, FPR=2027, FYE=C1231, AE=E)", "currency=USD")/1000000000} -> #NAME? | BX11: {=_xll.BQL($C11, "NET_INCOME(FPT=BA, FPR=2022, FYE=C1231, AE=A)", "currency=USD")/1000000000} -> #NAME? | BY11: {=_xll.BQL($C11, "NET_INCOME(FPT=BA, FPR=2023, FYE=C1231, AE=A)", "currency=USD")/1000000000} -> #NAME? | BZ11: {=_xll.BQL($C11, "NET_INCOME(FPT=BA, FPR=2024, FYE=C1231, AE=A)", "currency=USD")/1000000000} -> #NAME? | CA11: {=_xll.BQL($C11, "NET_INCOME(FPT=BA, FPR=2025, FYE=C1231, AE=E)", "currency=USD")/1000000000} -> #NAME? | CB11: {=_xll.BQL($C11, "NET_INCOME(FPT=BA, FPR=2026, FYE=C1231, AE=E)", "currency=USD")/1000000000} -> #NAME? | CC11: {=_xll.BQL($C11, "NET_INCOME(FPT=BA, FPR=2027, FYE=C1231, AE=E)", "currency=USD")/1000000000} -> #NAME? | CD11: {=-_xll.BQL($C11, "CF_DVD_PAID(FPT=BA, FPR=2024, FYE=C1231, AE=A)", "currency=USD")/1000000000} -> #NAME? | CE11: {=-_xll.BQL($C11, "CF_DVD_PAID(FPT=BA, FPR=2025, FYE=C1231, AE=E)", "currency=USD")/1000000000} -> #NAME? | CF11: {=-_xll.BQL($C11, "CF_DVD_PAID(FPT=BA, FPR=2026, FYE=C1231, AE=E)", "currency=USD")/1000000000} -> #NAME? | CG11: {=-_xll.BQL($C11, "CF_DVD_PAID(FPT=BA, FPR=2027, FYE=C1231, AE=E)", "currency=USD")/1000000000} -> #NAME? | CH11: =CD11/$F11 -> #NAME? | CI11: =CE11/$F11 -> #NAME? | CJ11: =CF11/$F11 -> #NAME? | CK11: =CG11/$F11 -> #NAME? | CL11: {=_xll.BDP($C11,"INTERVAL_AVG", "MARKET_DATA_OVERRIDE=turnover", "CALC_INTERVAL=5D","CRNCY=HKD")/1000000} -> #NAME? | CM11: {=_xll.BDP($C11,"INTERVAL_AVG", "MARKET_DATA_OVERRIDE=turnover", "CALC_INTERVAL=10D","CRNCY=HKD")/1000000} -> #NAME? | CN11: {=_xll.BDP($C11,"INTERVAL_AVG", "MARKET_DATA_OVERRIDE=turnover", "CALC_INTERVAL=20D","CRNCY=HKD")/1000000} -> #NAME? | CO11: {=_xll.BDP($C11,"INTERVAL_AVG", "MARKET_DATA_OVERRIDE=turnover", "CALC_INTERVAL=1m","CRNCY=HKD")/1000000} -> #NAME? | CP11: {=_xll.BDP($C11,"INTERVAL_AVG", "MARKET_DATA_OVERRIDE=turnover", "CALC_INTERVAL=3M","CRNCY=HKD")/1000000} -> #NAME? | CQ11: {=_xll.BDP($C11,"INTERVAL_AVG", "MARKET_DATA_OVERRIDE=turnover", "CALC_INTERVAL=6M","CRNCY=HKD")/1000000} -> #NAME? | CR11: =_xll.BDP($C11,"chg pct 1m")/100 -> #NAME? | CS11: =_xll.BDP($C11,"chg pct 3m")/100 -> #NAME? | CT11: =_xll.BDP($C11,"chg pct 6m")/100 -> #NAME? | CU11: =_xll.BDP($C11,"chg pct 1yr")/100 -> #NAME? | CV11: =_xll.BDP($C11,"chg pct ytd")/100 -> #NAME? | CW11: {=_xll.BQL($C11, "volatility(calc_interval=range(-1M, 0D))")} -> #NAME? | CX11: {=_xll.BQL($C11, "volatility(calc_interval=range(-3M, 0D))")} -> #NAME? | CY11: {=_xll.BQL($C11, "volatility(calc_interval=range(-6M, 0D))")} -> #NAME? | CZ11: =_xll.BDP($C11,CZ$1) -> #NAME?
A12: =_xll.BDP($C12,"security name") -> #NAME? | B12: =_xll.BDP($C12,"NAME_CHINESE_SIMPLIFIED") -> #NAME? | C12: MANH US EQUITY | D12: =_xll.BDP($C12,"LISTING_DATE") -> #NAME? | E12: =_xll.BDP($C12,E$1,"EQY_FUND_CRNCY="&$B$1) -> #NAME? | F12: =_xll.BDP($C12,F$1,"EQY_FUND_CRNCY="&$C$1) -> #NAME? | G12: =_xll.BDP($C12,G$1) -> #NAME? | H12: =_xll.BDP($C12,H$1,"EQY_FUND_CRNCY="&$B$1) -> #NAME? | I12: =_xll.BDP($C12,I$1,"EQY_FUND_CRNCY="&$C$1) -> #NAME? | J12: =_xll.BDP($C12,J$1,"EQY_FUND_CRNCY="&$B$1) -> #NAME? | K12: =_xll.BDP($C12,K$1,"EQY_FUND_CRNCY="&$C$1) -> #NAME? | L12: =_xll.BDP($C12,L$1,"EQY_FUND_CRNCY="&$B$1) -> #NAME? | M12: =_xll.BDP($C12,M$1,"EQY_FUND_CRNCY="&$C$1) -> #NAME? | N12: =_xll.BDP($C12,N$1)/100 -> #NAME? | O12: =_xll.BDP($C12,O$1)/100 -> #NAME? | P12: =_xll.BDP($C12,P$1)/100 -> #NAME? | Q12: =_xll.BDP($C12,Q$1)/100 -> #NAME? | R12: =_xll.BDP($C12,R$1)/100 -> #NAME? | S12: =_xll.BDP($C12,S$1)/100 -> #NAME? | T12: =_xll.BDP($C12,T$1)/100 -> #NAME? | U12: =_xll.BDP($C12,U$1)/100 -> #NAME? | ... W12: =_xll.BDP($C12,W$1)/100 -> #NAME? | X12: {=_xll.BDP($C12,"CRNCY_ADJ_CURR_EV", "EQY_FUND_CRNCY=HKD")} -> #NAME? | Y12: {=_xll.BDP($C12,"CRNCY_ADJ_CURR_EV", "EQY_FUND_CRNCY=USD")} -> #NAME? | Z12: =_xll.BDP($C12,Z$1)/100 -> #NAME? | AA12: =_xll.BDP($C12,"TRAIL_12M_NET_SALES","EQY_FUND_CRNCY=HKD") -> #NAME? | AB12: =_xll.BDP($C12,"TRAIL_12M_NET_INC","EQY_FUND_CRNCY=HKD") -> #NAME? | AC12: =_xll.BDP($C12,"TRAIL_12M_EBITDA","EQY_FUND_CRNCY=HKD") -> #NAME? | AD12: {=_xll.BQL($C12, "PE_RATIO(FPT=BA, FPR=2025, FYE=C1231, AE=E)")} -> #NAME? | AE12: {=_xll.BQL($C12, "PE_RATIO(FPT=BA, FPR=2026, FYE=C1231, AE=E)")} -> #NAME? | AF12: {=_xll.BQL($C12, "PE_RATIO(FPT=BA, FPR=2027, FYE=C1231, AE=E)")} -> #NAME? | AG12: {=_xll.BQL($C12, "PX_TO_SALES_RATIO(FPT=BA, FPR=2025, FYE=C1231, AE=E)")} -> #NAME? | AH12: {=_xll.BQL($C12, "PX_TO_SALES_RATIO(FPT=BA, FPR=2026, FYE=C1231, AE=E)")} -> #NAME? | AI12: {=_xll.BQL($C12, "PX_TO_SALES_RATIO(FPT=BA, FPR=2027, FYE=C1231, AE=E)")} -> #NAME? | AJ12: =IF(AC12<0,"N/A",$X12/AC12) -> #NAME? | AK12: {=IF(_xll.BQL($C12, "CURR_ENTP_VAL(FPT=A,FPO=0)/EBITDA(FPT=BA, FPR=2026, FYE=C1231, AE=E)")<0,"N/A",_xll.BQL($C12, "CURR_ENTP_VAL(FPT=A,FPO=0)/EBITDA(FPT=BA, FPR=2026, FYE=C1231, AE=E)"))} -> #NAME? | AL12: {=IF(_xll.BQL($C12, "CURR_ENTP_VAL(FPT=A,FPO=0)/EBITDA(FPT=BA, FPR=2027, FYE=C1231, AE=E)")<0,"N/A",_xll.BQL($C12, "CURR_ENTP_VAL(FPT=A,FPO=0)/EBITDA(FPT=BA, FPR=2027, FYE=C1231, AE=E)"))} -> #NAME? | AM12: =_xll.BDP($C12,AM$1) -> #NAME? | AN12: {=_xll.BQL($C12, "PX_TO_BOOK_RATIO(FPT=BA, FPR=2026, FYE=C1231, AE=E)")} -> #NAME? | AO12: {=_xll.BQL($C12, "PX_TO_BOOK_RATIO(FPT=BA, FPR=2027, FYE=C1231, AE=E)")} -> #NAME? | AP12: =_xll.BDP($C12,"BEST Px bps ratio","BEST fperiod override","27Y") -> #NAME? | AQ12: =Z12 -> #NAME? | AR12: =_xll.BDP($C12,"BEST_ROE","BEST fperiod override","26Y")/100 -> #NAME? | AS12: =_xll.BDP($C12,"BEST_ROE","BEST fperiod override","27Y")/100 -> #NAME? | AT12: =_xll.BDP($C12,AT$1) -> #NAME? | AU12: =_xll.BDP($C12,$AU$1,"BEST fperiod override","26Y") -> #NAME? | AV12: =_xll.BDP($C12,$AU$1,"BEST fperiod override","27Y") -> #NAME? | AW12: =(BP12/BN12)^(1/2)-1 -> #NAME? | AX12: =(BV12/BT12)^(1/2)-1 -> #NAME? | AY12: =(CB12/BZ12)^(1/2)-1 -> #NAME? | AZ12: {=_xll.BQL($C12, "CF_CASH_FROM_OPER(FPT=BA, FPR=2022, FYE=C1231, AE=A)", "currency=USD")/1000000000} -> #NAME? | BA12: {=_xll.BQL($C12, "CF_CASH_FROM_OPER(FPT=BA, FPR=2023, FYE=C1231, AE=A)", "currency=USD")/1000000000} -> #NAME? | BB12: {=_xll.BQL($C12, "CF_CASH_FROM_OPER(FPT=BA, FPR=2024, FYE=C1231, AE=A)", "currency=USD")/1000000000} -> #NAME? | BC12: {=_xll.BQL($C12, "CF_CASH_FROM_OPER(FPT=BA, FPR=2025, FYE=C1231, AE=E)", "currency=USD")/1000000000} -> #NAME? | BD12: {=_xll.BQL($C12, "CF_CASH_FROM_OPER(FPT=BA, FPR=2026, FYE=C1231, AE=E)", "currency=USD")/1000000000} -> #NAME? | BE12: {=_xll.BQL($C12, "CF_CASH_FROM_OPER(FPT=BA, FPR=2027, FYE=C1231, AE=E)", "currency=USD")/1000000000} -> #NAME? | BF12: {=_xll.BQL($C12, "CF_FREE_CASH_FLOW(FPT=BA, FPR=2022, FYE=C1231, AE=A)", "currency=USD")/1000000000} -> #NAME? | BG12: {=_xll.BQL($C12, "CF_FREE_CASH_FLOW(FPT=BA, FPR=2023, FYE=C1231, AE=A)", "currency=USD")/1000000000} -> #NAME? | BH12: {=_xll.BQL($C12, "CF_FREE_CASH_FLOW(FPT=BA, FPR=2024, FYE=C1231, AE=A)", "currency=USD")/1000000000} -> #NAME? | BI12: {=_xll.BQL($C12, "CF_FREE_CASH_FLOW(FPT=BA, FPR=2025, FYE=C1231, AE=E)", "currency=USD")/1000000000} -> #NAME? | BJ12: {=_xll.BQL($C12, "CF_FREE_CASH_FLOW(FPT=BA, FPR=2026, FYE=C1231, AE=E)", "currency=USD")/1000000000} -> #NAME? | BK12: {=_xll.BQL($C12, "CF_FREE_CASH_FLOW(FPT=BA, FPR=2027, FYE=C1231, AE=E)", "currency=USD")/1000000000} -> #NAME? | BL12: {=_xll.BQL($C12, "SALES_REV_TURN(FPT=BA, FPR=2022, FYE=C1231, AE=A)", "currency=USD")/1000000000} -> #NAME? | BM12: {=_xll.BQL($C12, "SALES_REV_TURN(FPT=BA, FPR=2023, FYE=C1231, AE=A)", "currency=USD")/1000000000} -> #NAME? | BN12: {=_xll.BQL($C12, "SALES_REV_TURN(FPT=BA, FPR=2024, FYE=C1231, AE=A)", "currency=USD")/1000000000} -> #NAME? | BO12: {=_xll.BQL($C12, "SALES_REV_TURN(FPT=BA, FPR=2025, FYE=C1231, AE=E)", "currency=USD")/1000000000} -> #NAME? | BP12: {=_xll.BQL($C12, "SALES_REV_TURN(FPT=BA, FPR=2026, FYE=C1231, AE=E)", "currency=USD")/1000000000} -> #NAME? | BQ12: {=_xll.BQL($C12, "SALES_REV_TURN(FPT=BA, FPR=2027, FYE=C1231, AE=E)", "currency=USD")/1000000000} -> #NAME? | BR12: {=_xll.BQL($C12, "EBITDA(FPT=BA, FPR=2022, FYE=C1231, AE=A)", "currency=USD")/1000000000} -> #NAME? | BS12: {=_xll.BQL($C12, "EBITDA(FPT=BA, FPR=2023, FYE=C1231, AE=A)", "currency=USD")/1000000000} -> #NAME? | BT12: {=_xll.BQL($C12, "EBITDA(FPT=BA, FPR=2024, FYE=C1231, AE=A)", "currency=USD")/1000000000} -> #NAME? | BU12: {=_xll.BQL($C12, "EBITDA(FPT=BA, FPR=2025, FYE=C1231, AE=E)", "currency=USD")/1000000000} -> #NAME? | BV12: {=_xll.BQL($C12, "EBITDA(FPT=BA, FPR=2026, FYE=C1231, AE=E)", "currency=USD")/1000000000} -> #NAME? | BW12: {=_xll.BQL($C12, "EBITDA(FPT=BA, FPR=2027, FYE=C1231, AE=E)", "currency=USD")/1000000000} -> #NAME? | BX12: {=_xll.BQL($C12, "NET_INCOME(FPT=BA, FPR=2022, FYE=C1231, AE=A)", "currency=USD")/1000000000} -> #NAME? | BY12: {=_xll.BQL($C12, "NET_INCOME(FPT=BA, FPR=2023, FYE=C1231, AE=A)", "currency=USD")/1000000000} -> #NAME? | BZ12: {=_xll.BQL($C12, "NET_INCOME(FPT=BA, FPR=2024, FYE=C1231, AE=A)", "currency=USD")/1000000000} -> #NAME? | CA12: {=_xll.BQL($C12, "NET_INCOME(FPT=BA, FPR=2025, FYE=C1231, AE=E)", "currency=USD")/1000000000} -> #NAME? | CB12: {=_xll.BQL($C12, "NET_INCOME(FPT=BA, FPR=2026, FYE=C1231, AE=E)", "currency=USD")/1000000000} -> #NAME? | CC12: {=_xll.BQL($C12, "NET_INCOME(FPT=BA, FPR=2027, FYE=C1231, AE=E)", "currency=USD")/1000000000} -> #NAME? | CD12: {=-_xll.BQL($C12, "CF_DVD_PAID(FPT=BA, FPR=2024, FYE=C1231, AE=A)", "currency=USD")/1000000000} -> #NAME? | CE12: {=-_xll.BQL($C12, "CF_DVD_PAID(FPT=BA, FPR=2025, FYE=C1231, AE=E)", "currency=USD")/1000000000} -> #NAME? | CF12: {=-_xll.BQL($C12, "CF_DVD_PAID(FPT=BA, FPR=2026, FYE=C1231, AE=E)", "currency=USD")/1000000000} -> #NAME? | CG12: {=-_xll.BQL($C12, "CF_DVD_PAID(FPT=BA, FPR=2027, FYE=C1231, AE=E)", "currency=USD")/1000000000} -> #NAME? | CH12: =CD12/$F12 -> #NAME? | CI12: =CE12/$F12 -> #NAME? | CJ12: =CF12/$F12 -> #NAME? | CK12: =CG12/$F12 -> #NAME? | CL12: {=_xll.BDP($C12,"INTERVAL_AVG", "MARKET_DATA_OVERRIDE=turnover", "CALC_INTERVAL=5D","CRNCY=HKD")/1000000} -> #NAME? | CM12: {=_xll.BDP($C12,"INTERVAL_AVG", "MARKET_DATA_OVERRIDE=turnover", "CALC_INTERVAL=10D","CRNCY=HKD")/1000000} -> #NAME? | CN12: {=_xll.BDP($C12,"INTERVAL_AVG", "MARKET_DATA_OVERRIDE=turnover", "CALC_INTERVAL=20D","CRNCY=HKD")/1000000} -> #NAME? | CO12: {=_xll.BDP($C12,"INTERVAL_AVG", "MARKET_DATA_OVERRIDE=turnover", "CALC_INTERVAL=1m","CRNCY=HKD")/1000000} -> #NAME? | CP12: {=_xll.BDP($C12,"INTERVAL_AVG", "MARKET_DATA_OVERRIDE=turnover", "CALC_INTERVAL=3M","CRNCY=HKD")/1000000} -> #NAME? | CQ12: {=_xll.BDP($C12,"INTERVAL_AVG", "MARKET_DATA_OVERRIDE=turnover", "CALC_INTERVAL=6M","CRNCY=HKD")/1000000} -> #NAME? | CR12: =_xll.BDP($C12,"chg pct 1m")/100 -> #NAME? | CS12: =_xll.BDP($C12,"chg pct 3m")/100 -> #NAME? | CT12: =_xll.BDP($C12,"chg pct 6m")/100 -> #NAME? | CU12: =_xll.BDP($C12,"chg pct 1yr")/100 -> #NAME? | CV12: =_xll.BDP($C12,"chg pct ytd")/100 -> #NAME? | CW12: {=_xll.BQL($C12, "volatility(calc_interval=range(-1M, 0D))")} -> #NAME? | CX12: {=_xll.BQL($C12, "volatility(calc_interval=range(-3M, 0D))")} -> #NAME? | CY12: {=_xll.BQL($C12, "volatility(calc_interval=range(-6M, 0D))")} -> #NAME? | CZ12: =_xll.BDP($C12,CZ$1) -> #NAME?
A13: =_xll.BDP($C13,"security name") -> #NAME? | B13: =_xll.BDP($C13,"NAME_CHINESE_SIMPLIFIED") -> #NAME? | C13: CHRW US EQUITY | D13: =_xll.BDP($C13,"LISTING_DATE") -> #NAME? | E13: =_xll.BDP($C13,E$1,"EQY_FUND_CRNCY="&$B$1) -> #NAME? | F13: =_xll.BDP($C13,F$1,"EQY_FUND_CRNCY="&$C$1) -> #NAME? | G13: =_xll.BDP($C13,G$1) -> #NAME? | H13: =_xll.BDP($C13,H$1,"EQY_FUND_CRNCY="&$B$1) -> #NAME? | I13: =_xll.BDP($C13,I$1,"EQY_FUND_CRNCY="&$C$1) -> #NAME? | J13: =_xll.BDP($C13,J$1,"EQY_FUND_CRNCY="&$B$1) -> #NAME? | K13: =_xll.BDP($C13,K$1,"EQY_FUND_CRNCY="&$C$1) -> #NAME? | L13: =_xll.BDP($C13,L$1,"EQY_FUND_CRNCY="&$B$1) -> #NAME? | M13: =_xll.BDP($C13,M$1,"EQY_FUND_CRNCY="&$C$1) -> #NAME? | N13: =_xll.BDP($C13,N$1)/100 -> #NAME? | O13: =_xll.BDP($C13,O$1)/100 -> #NAME? | P13: =_xll.BDP($C13,P$1)/100 -> #NAME? | Q13: =_xll.BDP($C13,Q$1)/100 -> #NAME? | R13: =_xll.BDP($C13,R$1)/100 -> #NAME? | S13: =_xll.BDP($C13,S$1)/100 -> #NAME? | T13: =_xll.BDP($C13,T$1)/100 -> #NAME? | U13: =_xll.BDP($C13,U$1)/100 -> #NAME? | ... W13: =_xll.BDP($C13,W$1)/100 -> #NAME? | X13: {=_xll.BDP($C13,"CRNCY_ADJ_CURR_EV", "EQY_FUND_CRNCY=HKD")} -> #NAME? | Y13: {=_xll.BDP($C13,"CRNCY_ADJ_CURR_EV", "EQY_FUND_CRNCY=USD")} -> #NAME? | Z13: =_xll.BDP($C13,Z$1)/100 -> #NAME? | AA13: =_xll.BDP($C13,"TRAIL_12M_NET_SALES","EQY_FUND_CRNCY=HKD") -> #NAME? | AB13: =_xll.BDP($C13,"TRAIL_12M_NET_INC","EQY_FUND_CRNCY=HKD") -> #NAME? | AC13: =_xll.BDP($C13,"TRAIL_12M_EBITDA","EQY_FUND_CRNCY=HKD") -> #NAME? | AD13: {=_xll.BQL($C13, "PE_RATIO(FPT=BA, FPR=2025, FYE=C1231, AE=E)")} -> #NAME? | AE13: {=_xll.BQL($C13, "PE_RATIO(FPT=BA, FPR=2026, FYE=C1231, AE=E)")} -> #NAME? | AF13: {=_xll.BQL($C13, "PE_RATIO(FPT=BA, FPR=2027, FYE=C1231, AE=E)")} -> #NAME? | AG13: {=_xll.BQL($C13, "PX_TO_SALES_RATIO(FPT=BA, FPR=2025, FYE=C1231, AE=E)")} -> #NAME? | AH13: {=_xll.BQL($C13, "PX_TO_SALES_RATIO(FPT=BA, FPR=2026, FYE=C1231, AE=E)")} -> #NAME? | AI13: {=_xll.BQL($C13, "PX_TO_SALES_RATIO(FPT=BA, FPR=2027, FYE=C1231, AE=E)")} -> #NAME? | AJ13: =IF(AC13<0,"N/A",$X13/AC13) -> #NAME? | AK13: {=IF(_xll.BQL($C13, "CURR_ENTP_VAL(FPT=A,FPO=0)/EBITDA(FPT=BA, FPR=2026, FYE=C1231, AE=E)")<0,"N/A",_xll.BQL($C13, "CURR_ENTP_VAL(FPT=A,FPO=0)/EBITDA(FPT=BA, FPR=2026, FYE=C1231, AE=E)"))} -> #NAME? | AL13: {=IF(_xll.BQL($C13, "CURR_ENTP_VAL(FPT=A,FPO=0)/EBITDA(FPT=BA, FPR=2027, FYE=C1231, AE=E)")<0,"N/A",_xll.BQL($C13, "CURR_ENTP_VAL(FPT=A,FPO=0)/EBITDA(FPT=BA, FPR=2027, FYE=C1231, AE=E)"))} -> #NAME? | AM13: =_xll.BDP($C13,AM$1) -> #NAME? | AN13: {=_xll.BQL($C13, "PX_TO_BOOK_RATIO(FPT=BA, FPR=2026, FYE=C1231, AE=E)")} -> #NAME? | AO13: {=_xll.BQL($C13, "PX_TO_BOOK_RATIO(FPT=BA, FPR=2027, FYE=C1231, AE=E)")} -> #NAME? | AP13: =_xll.BDP($C13,"BEST Px bps ratio","BEST fperiod override","27Y") -> #NAME? | AQ13: =Z13 -> #NAME? | AR13: =_xll.BDP($C13,"BEST_ROE","BEST fperiod override","26Y")/100 -> #NAME? | AS13: =_xll.BDP($C13,"BEST_ROE","BEST fperiod override","27Y")/100 -> #NAME? | AT13: =_xll.BDP($C13,AT$1) -> #NAME? | AU13: =_xll.BDP($C13,$AU$1,"BEST fperiod override","26Y") -> #NAME? | AV13: =_xll.BDP($C13,$AU$1,"BEST fperiod override","27Y") -> #NAME? | AW13: =(BP13/BN13)^(1/2)-1 -> #NAME? | AX13: =(BV13/BT13)^(1/2)-1 -> #NAME? | AY13: =(CB13/BZ13)^(1/2)-1 -> #NAME? | AZ13: {=_xll.BQL($C13, "CF_CASH_FROM_OPER(FPT=BA, FPR=2022, FYE=C1231, AE=A)", "currency=USD")/1000000000} -> #NAME? | BA13: {=_xll.BQL($C13, "CF_CASH_FROM_OPER(FPT=BA, FPR=2023, FYE=C1231, AE=A)", "currency=USD")/1000000000} -> #NAME? | BB13: {=_xll.BQL($C13, "CF_CASH_FROM_OPER(FPT=BA, FPR=2024, FYE=C1231, AE=A)", "currency=USD")/1000000000} -> #NAME? | BC13: {=_xll.BQL($C13, "CF_CASH_FROM_OPER(FPT=BA, FPR=2025, FYE=C1231, AE=E)", "currency=USD")/1000000000} -> #NAME? | BD13: {=_xll.BQL($C13, "CF_CASH_FROM_OPER(FPT=BA, FPR=2026, FYE=C1231, AE=E)", "currency=USD")/1000000000} -> #NAME? | BE13: {=_xll.BQL($C13, "CF_CASH_FROM_OPER(FPT=BA, FPR=2027, FYE=C1231, AE=E)", "currency=USD")/1000000000} -> #NAME? | BF13: {=_xll.BQL($C13, "CF_FREE_CASH_FLOW(FPT=BA, FPR=2022, FYE=C1231, AE=A)", "currency=USD")/1000000000} -> #NAME? | BG13: {=_xll.BQL($C13, "CF_FREE_CASH_FLOW(FPT=BA, FPR=2023, FYE=C1231, AE=A)", "currency=USD")/1000000000} -> #NAME? | BH13: {=_xll.BQL($C13, "CF_FREE_CASH_FLOW(FPT=BA, FPR=2024, FYE=C1231, AE=A)", "currency=USD")/1000000000} -> #NAME? | BI13: {=_xll.BQL($C13, "CF_FREE_CASH_FLOW(FPT=BA, FPR=2025, FYE=C1231, AE=E)", "currency=USD")/1000000000} -> #NAME? | BJ13: {=_xll.BQL($C13, "CF_FREE_CASH_FLOW(FPT=BA, FPR=2026, FYE=C1231, AE=E)", "currency=USD")/1000000000} -> #NAME? | BK13: {=_xll.BQL($C13, "CF_FREE_CASH_FLOW(FPT=BA, FPR=2027, FYE=C1231, AE=E)", "currency=USD")/1000000000} -> #NAME? | BL13: {=_xll.BQL($C13, "SALES_REV_TURN(FPT=BA, FPR=2022, FYE=C1231, AE=A)", "currency=USD")/1000000000} -> #NAME? | BM13: {=_xll.BQL($C13, "SALES_REV_TURN(FPT=BA, FPR=2023, FYE=C1231, AE=A)", "currency=USD")/1000000000} -> #NAME? | BN13: {=_xll.BQL($C13, "SALES_REV_TURN(FPT=BA, FPR=2024, FYE=C1231, AE=A)", "currency=USD")/1000000000} -> #NAME? | BO13: {=_xll.BQL($C13, "SALES_REV_TURN(FPT=BA, FPR=2025, FYE=C1231, AE=E)", "currency=USD")/1000000000} -> #NAME? | BP13: {=_xll.BQL($C13, "SALES_REV_TURN(FPT=BA, FPR=2026, FYE=C1231, AE=E)", "currency=USD")/1000000000} -> #NAME? | BQ13: {=_xll.BQL($C13, "SALES_REV_TURN(FPT=BA, FPR=2027, FYE=C1231, AE=E)", "currency=USD")/1000000000} -> #NAME? | BR13: {=_xll.BQL($C13, "EBITDA(FPT=BA, FPR=2022, FYE=C1231, AE=A)", "currency=USD")/1000000000} -> #NAME? | BS13: {=_xll.BQL($C13, "EBITDA(FPT=BA, FPR=2023, FYE=C1231, AE=A)", "currency=USD")/1000000000} -> #NAME? | BT13: {=_xll.BQL($C13, "EBITDA(FPT=BA, FPR=2024, FYE=C1231, AE=A)", "currency=USD")/1000000000} -> #NAME? | BU13: {=_xll.BQL($C13, "EBITDA(FPT=BA, FPR=2025, FYE=C1231, AE=E)", "currency=USD")/1000000000} -> #NAME? | BV13: {=_xll.BQL($C13, "EBITDA(FPT=BA, FPR=2026, FYE=C1231, AE=E)", "currency=USD")/1000000000} -> #NAME? | BW13: {=_xll.BQL($C13, "EBITDA(FPT=BA, FPR=2027, FYE=C1231, AE=E)", "currency=USD")/1000000000} -> #NAME? | BX13: {=_xll.BQL($C13, "NET_INCOME(FPT=BA, FPR=2022, FYE=C1231, AE=A)", "currency=USD")/1000000000} -> #NAME? | BY13: {=_xll.BQL($C13, "NET_INCOME(FPT=BA, FPR=2023, FYE=C1231, AE=A)", "currency=USD")/1000000000} -> #NAME? | BZ13: {=_xll.BQL($C13, "NET_INCOME(FPT=BA, FPR=2024, FYE=C1231, AE=A)", "currency=USD")/1000000000} -> #NAME? | CA13: {=_xll.BQL($C13, "NET_INCOME(FPT=BA, FPR=2025, FYE=C1231, AE=E)", "currency=USD")/1000000000} -> #NAME? | CB13: {=_xll.BQL($C13, "NET_INCOME(FPT=BA, FPR=2026, FYE=C1231, AE=E)", "currency=USD")/1000000000} -> #NAME? | CC13: {=_xll.BQL($C13, "NET_INCOME(FPT=BA, FPR=2027, FYE=C1231, AE=E)", "currency=USD")/1000000000} -> #NAME? | CD13: {=-_xll.BQL($C13, "CF_DVD_PAID(FPT=BA, FPR=2024, FYE=C1231, AE=A)", "currency=USD")/1000000000} -> #NAME? | CE13: {=-_xll.BQL($C13, "CF_DVD_PAID(FPT=BA, FPR=2025, FYE=C1231, AE=E)", "currency=USD")/1000000000} -> #NAME? | CF13: {=-_xll.BQL($C13, "CF_DVD_PAID(FPT=BA, FPR=2026, FYE=C1231, AE=E)", "currency=USD")/1000000000} -> #NAME? | CG13: {=-_xll.BQL($C13, "CF_DVD_PAID(FPT=BA, FPR=2027, FYE=C1231, AE=E)", "currency=USD")/1000000000} -> #NAME? | CH13: =CD13/$F13 -> #NAME? | CI13: =CE13/$F13 -> #NAME? | CJ13: =CF13/$F13 -> #NAME? | CK13: =CG13/$F13 -> #NAME? | CL13: {=_xll.BDP($C13,"INTERVAL_AVG", "MARKET_DATA_OVERRIDE=turnover", "CALC_INTERVAL=5D","CRNCY=HKD")/1000000} -> #NAME? | CM13: {=_xll.BDP($C13,"INTERVAL_AVG", "MARKET_DATA_OVERRIDE=turnover", "CALC_INTERVAL=10D","CRNCY=HKD")/1000000} -> #NAME? | CN13: {=_xll.BDP($C13,"INTERVAL_AVG", "MARKET_DATA_OVERRIDE=turnover", "CALC_INTERVAL=20D","CRNCY=HKD")/1000000} -> #NAME? | CO13: {=_xll.BDP($C13,"INTERVAL_AVG", "MARKET_DATA_OVERRIDE=turnover", "CALC_INTERVAL=1m","CRNCY=HKD")/1000000} -> #NAME? | CP13: {=_xll.BDP($C13,"INTERVAL_AVG", "MARKET_DATA_OVERRIDE=turnover", "CALC_INTERVAL=3M","CRNCY=HKD")/1000000} -> #NAME? | CQ13: {=_xll.BDP($C13,"INTERVAL_AVG", "MARKET_DATA_OVERRIDE=turnover", "CALC_INTERVAL=6M","CRNCY=HKD")/1000000} -> #NAME? | CR13: =_xll.BDP($C13,"chg pct 1m")/100 -> #NAME? | CS13: =_xll.BDP($C13,"chg pct 3m")/100 -> #NAME? | CT13: =_xll.BDP($C13,"chg pct 6m")/100 -> #NAME? | CU13: =_xll.BDP($C13,"chg pct 1yr")/100 -> #NAME? | CV13: =_xll.BDP($C13,"chg pct ytd")/100 -> #NAME? | CW13: {=_xll.BQL($C13, "volatility(calc_interval=range(-1M, 0D))")} -> #NAME? | CX13: {=_xll.BQL($C13, "volatility(calc_interval=range(-3M, 0D))")} -> #NAME? | CY13: {=_xll.BQL($C13, "volatility(calc_interval=range(-6M, 0D))")} -> #NAME? | CZ13: =_xll.BDP($C13,CZ$1) -> #NAME?
A14: =_xll.BDP($C14,"security name") -> #NAME? | B14: =_xll.BDP($C14,"NAME_CHINESE_SIMPLIFIED") -> #NAME? | C14: cvs us EQUITY | D14: =_xll.BDP($C14,"LISTING_DATE") -> #NAME? | E14: =_xll.BDP($C14,E$1,"EQY_FUND_CRNCY="&$B$1) -> #NAME? | F14: =_xll.BDP($C14,F$1,"EQY_FUND_CRNCY="&$C$1) -> #NAME? | G14: =_xll.BDP($C14,G$1) -> #NAME? | H14: =_xll.BDP($C14,H$1,"EQY_FUND_CRNCY="&$B$1) -> #NAME? | I14: =_xll.BDP($C14,I$1,"EQY_FUND_CRNCY="&$C$1) -> #NAME? | J14: =_xll.BDP($C14,J$1,"EQY_FUND_CRNCY="&$B$1) -> #NAME? | K14: =_xll.BDP($C14,K$1,"EQY_FUND_CRNCY="&$C$1) -> #NAME? | L14: =_xll.BDP($C14,L$1,"EQY_FUND_CRNCY="&$B$1) -> #NAME? | M14: =_xll.BDP($C14,M$1,"EQY_FUND_CRNCY="&$C$1) -> #NAME? | N14: =_xll.BDP($C14,N$1)/100 -> #NAME? | O14: =_xll.BDP($C14,O$1)/100 -> #NAME? | P14: =_xll.BDP($C14,P$1)/100 -> #NAME? | Q14: =_xll.BDP($C14,Q$1)/100 -> #NAME? | R14: =_xll.BDP($C14,R$1)/100 -> #NAME? | S14: =_xll.BDP($C14,S$1)/100 -> #NAME? | T14: =_xll.BDP($C14,T$1)/100 -> #NAME? | U14: =_xll.BDP($C14,U$1)/100 -> #NAME? | ... W14: =_xll.BDP($C14,W$1)/100 -> #NAME? | X14: {=_xll.BDP($C14,"CRNCY_ADJ_CURR_EV", "EQY_FUND_CRNCY=HKD")} -> #NAME? | Y14: {=_xll.BDP($C14,"CRNCY_ADJ_CURR_EV", "EQY_FUND_CRNCY=USD")} -> #NAME? | Z14: =_xll.BDP($C14,Z$1)/100 -> #NAME? | AA14: =_xll.BDP($C14,"TRAIL_12M_NET_SALES","EQY_FUND_CRNCY=HKD") -> #NAME? | AB14: =_xll.BDP($C14,"TRAIL_12M_NET_INC","EQY_FUND_CRNCY=HKD") -> #NAME? | AC14: =_xll.BDP($C14,"TRAIL_12M_EBITDA","EQY_FUND_CRNCY=HKD") -> #NAME? | AD14: {=_xll.BQL($C14, "PE_RATIO(FPT=BA, FPR=2025, FYE=C1231, AE=E)")} -> #NAME? | AE14: {=_xll.BQL($C14, "PE_RATIO(FPT=BA, FPR=2026, FYE=C1231, AE=E)")} -> #NAME? | AF14: {=_xll.BQL($C14, "PE_RATIO(FPT=BA, FPR=2027, FYE=C1231, AE=E)")} -> #NAME? | AG14: {=_xll.BQL($C14, "PX_TO_SALES_RATIO(FPT=BA, FPR=2025, FYE=C1231, AE=E)")} -> #NAME? | AH14: {=_xll.BQL($C14, "PX_TO_SALES_RATIO(FPT=BA, FPR=2026, FYE=C1231, AE=E)")} -> #NAME? | AI14: {=_xll.BQL($C14, "PX_TO_SALES_RATIO(FPT=BA, FPR=2027, FYE=C1231, AE=E)")} -> #NAME? | AJ14: =IF(AC14<0,"N/A",$X14/AC14) -> #NAME? | AK14: {=IF(_xll.BQL($C14, "CURR_ENTP_VAL(FPT=A,FPO=0)/EBITDA(FPT=BA, FPR=2026, FYE=C1231, AE=E)")<0,"N/A",_xll.BQL($C14, "CURR_ENTP_VAL(FPT=A,FPO=0)/EBITDA(FPT=BA, FPR=2026, FYE=C1231, AE=E)"))} -> #NAME? | AL14: {=IF(_xll.BQL($C14, "CURR_ENTP_VAL(FPT=A,FPO=0)/EBITDA(FPT=BA, FPR=2027, FYE=C1231, AE=E)")<0,"N/A",_xll.BQL($C14, "CURR_ENTP_VAL(FPT=A,FPO=0)/EBITDA(FPT=BA, FPR=2027, FYE=C1231, AE=E)"))} -> #NAME? | AM14: =_xll.BDP($C14,AM$1) -> #NAME? | AN14: {=_xll.BQL($C14, "PX_TO_BOOK_RATIO(FPT=BA, FPR=2026, FYE=C1231, AE=E)")} -> #NAME? | AO14: {=_xll.BQL($C14, "PX_TO_BOOK_RATIO(FPT=BA, FPR=2027, FYE=C1231, AE=E)")} -> #NAME? | AP14: =_xll.BDP($C14,"BEST Px bps ratio","BEST fperiod override","27Y") -> #NAME? | AQ14: =Z14 -> #NAME? | AR14: =_xll.BDP($C14,"BEST_ROE","BEST fperiod override","26Y")/100 -> #NAME? | AS14: =_xll.BDP($C14,"BEST_ROE","BEST fperiod override","27Y")/100 -> #NAME? | AT14: =_xll.BDP($C14,AT$1) -> #NAME? | AU14: =_xll.BDP($C14,$AU$1,"BEST fperiod override","26Y") -> #NAME? | AV14: =_xll.BDP($C14,$AU$1,"BEST fperiod override","27Y") -> #NAME? | AW14: =(BP14/BN14)^(1/2)-1 -> #NAME? | AX14: =(BV14/BT14)^(1/2)-1 -> #NAME? | AY14: =(CB14/BZ14)^(1/2)-1 -> #NAME? | AZ14: {=_xll.BQL($C14, "CF_CASH_FROM_OPER(FPT=BA, FPR=2022, FYE=C1231, AE=A)", "currency=USD")/1000000000} -> #NAME? | BA14: {=_xll.BQL($C14, "CF_CASH_FROM_OPER(FPT=BA, FPR=2023, FYE=C1231, AE=A)", "currency=USD")/1000000000} -> #NAME? | BB14: {=_xll.BQL($C14, "CF_CASH_FROM_OPER(FPT=BA, FPR=2024, FYE=C1231, AE=A)", "currency=USD")/1000000000} -> #NAME? | BC14: {=_xll.BQL($C14, "CF_CASH_FROM_OPER(FPT=BA, FPR=2025, FYE=C1231, AE=E)", "currency=USD")/1000000000} -> #NAME? | BD14: {=_xll.BQL($C14, "CF_CASH_FROM_OPER(FPT=BA, FPR=2026, FYE=C1231, AE=E)", "currency=USD")/1000000000} -> #NAME? | BE14: {=_xll.BQL($C14, "CF_CASH_FROM_OPER(FPT=BA, FPR=2027, FYE=C1231, AE=E)", "currency=USD")/1000000000} -> #NAME? | BF14: {=_xll.BQL($C14, "CF_FREE_CASH_FLOW(FPT=BA, FPR=2022, FYE=C1231, AE=A)", "currency=USD")/1000000000} -> #NAME? | BG14: {=_xll.BQL($C14, "CF_FREE_CASH_FLOW(FPT=BA, FPR=2023, FYE=C1231, AE=A)", "currency=USD")/1000000000} -> #NAME? | BH14: {=_xll.BQL($C14, "CF_FREE_CASH_FLOW(FPT=BA, FPR=2024, FYE=C1231, AE=A)", "currency=USD")/1000000000} -> #NAME? | BI14: {=_xll.BQL($C14, "CF_FREE_CASH_FLOW(FPT=BA, FPR=2025, FYE=C1231, AE=E)", "currency=USD")/1000000000} -> #NAME? | BJ14: {=_xll.BQL($C14, "CF_FREE_CASH_FLOW(FPT=BA, FPR=2026, FYE=C1231, AE=E)", "currency=USD")/1000000000} -> #NAME? | BK14: {=_xll.BQL($C14, "CF_FREE_CASH_FLOW(FPT=BA, FPR=2027, FYE=C1231, AE=E)", "currency=USD")/1000000000} -> #NAME? | BL14: {=_xll.BQL($C14, "SALES_REV_TURN(FPT=BA, FPR=2022, FYE=C1231, AE=A)", "currency=USD")/1000000000} -> #NAME? | BM14: {=_xll.BQL($C14, "SALES_REV_TURN(FPT=BA, FPR=2023, FYE=C1231, AE=A)", "currency=USD")/1000000000} -> #NAME? | BN14: {=_xll.BQL($C14, "SALES_REV_TURN(FPT=BA, FPR=2024, FYE=C1231, AE=A)", "currency=USD")/1000000000} -> #NAME? | BO14: {=_xll.BQL($C14, "SALES_REV_TURN(FPT=BA, FPR=2025, FYE=C1231, AE=E)", "currency=USD")/1000000000} -> #NAME? | BP14: {=_xll.BQL($C14, "SALES_REV_TURN(FPT=BA, FPR=2026, FYE=C1231, AE=E)", "currency=USD")/1000000000} -> #NAME? | BQ14: {=_xll.BQL($C14, "SALES_REV_TURN(FPT=BA, FPR=2027, FYE=C1231, AE=E)", "currency=USD")/1000000000} -> #NAME? | BR14: {=_xll.BQL($C14, "EBITDA(FPT=BA, FPR=2022, FYE=C1231, AE=A)", "currency=USD")/1000000000} -> #NAME? | BS14: {=_xll.BQL($C14, "EBITDA(FPT=BA, FPR=2023, FYE=C1231, AE=A)", "currency=USD")/1000000000} -> #NAME? | BT14: {=_xll.BQL($C14, "EBITDA(FPT=BA, FPR=2024, FYE=C1231, AE=A)", "currency=USD")/1000000000} -> #NAME? | BU14: {=_xll.BQL($C14, "EBITDA(FPT=BA, FPR=2025, FYE=C1231, AE=E)", "currency=USD")/1000000000} -> #NAME? | BV14: {=_xll.BQL($C14, "EBITDA(FPT=BA, FPR=2026, FYE=C1231, AE=E)", "currency=USD")/1000000000} -> #NAME? | BW14: {=_xll.BQL($C14, "EBITDA(FPT=BA, FPR=2027, FYE=C1231, AE=E)", "currency=USD")/1000000000} -> #NAME? | BX14: {=_xll.BQL($C14, "NET_INCOME(FPT=BA, FPR=2022, FYE=C1231, AE=A)", "currency=USD")/1000000000} -> #NAME? | BY14: {=_xll.BQL($C14, "NET_INCOME(FPT=BA, FPR=2023, FYE=C1231, AE=A)", "currency=USD")/1000000000} -> #NAME? | BZ14: {=_xll.BQL($C14, "NET_INCOME(FPT=BA, FPR=2024, FYE=C1231, AE=A)", "currency=USD")/1000000000} -> #NAME? | CA14: {=_xll.BQL($C14, "NET_INCOME(FPT=BA, FPR=2025, FYE=C1231, AE=E)", "currency=USD")/1000000000} -> #NAME? | CB14: {=_xll.BQL($C14, "NET_INCOME(FPT=BA, FPR=2026, FYE=C1231, AE=E)", "currency=USD")/1000000000} -> #NAME? | CC14: {=_xll.BQL($C14, "NET_INCOME(FPT=BA, FPR=2027, FYE=C1231, AE=E)", "currency=USD")/1000000000} -> #NAME? | CD14: {=-_xll.BQL($C14, "CF_DVD_PAID(FPT=BA, FPR=2024, FYE=C1231, AE=A)", "currency=USD")/1000000000} -> #NAME? | CE14: {=-_xll.BQL($C14, "CF_DVD_PAID(FPT=BA, FPR=2025, FYE=C1231, AE=E)", "currency=USD")/1000000000} -> #NAME? | CF14: {=-_xll.BQL($C14, "CF_DVD_PAID(FPT=BA, FPR=2026, FYE=C1231, AE=E)", "currency=USD")/1000000000} -> #NAME? | CG14: {=-_xll.BQL($C14, "CF_DVD_PAID(FPT=BA, FPR=2027, FYE=C1231, AE=E)", "currency=USD")/1000000000} -> #NAME? | CH14: =CD14/$F14 -> #NAME? | CI14: =CE14/$F14 -> #NAME? | CJ14: =CF14/$F14 -> #NAME? | CK14: =CG14/$F14 -> #NAME? | CL14: {=_xll.BDP($C14,"INTERVAL_AVG", "MARKET_DATA_OVERRIDE=turnover", "CALC_INTERVAL=5D","CRNCY=HKD")/1000000} -> #NAME? | CM14: {=_xll.BDP($C14,"INTERVAL_AVG", "MARKET_DATA_OVERRIDE=turnover", "CALC_INTERVAL=10D","CRNCY=HKD")/1000000} -> #NAME? | CN14: {=_xll.BDP($C14,"INTERVAL_AVG", "MARKET_DATA_OVERRIDE=turnover", "CALC_INTERVAL=20D","CRNCY=HKD")/1000000} -> #NAME? | CO14: {=_xll.BDP($C14,"INTERVAL_AVG", "MARKET_DATA_OVERRIDE=turnover", "CALC_INTERVAL=1m","CRNCY=HKD")/1000000} -> #NAME? | CP14: {=_xll.BDP($C14,"INTERVAL_AVG", "MARKET_DATA_OVERRIDE=turnover", "CALC_INTERVAL=3M","CRNCY=HKD")/1000000} -> #NAME? | CQ14: {=_xll.BDP($C14,"INTERVAL_AVG", "MARKET_DATA_OVERRIDE=turnover", "CALC_INTERVAL=6M","CRNCY=HKD")/1000000} -> #NAME? | CR14: =_xll.BDP($C14,"chg pct 1m")/100 -> #NAME? | CS14: =_xll.BDP($C14,"chg pct 3m")/100 -> #NAME? | CT14: =_xll.BDP($C14,"chg pct 6m")/100 -> #NAME? | CU14: =_xll.BDP($C14,"chg pct 1yr")/100 -> #NAME? | CV14: =_xll.BDP($C14,"chg pct ytd")/100 -> #NAME? | CW14: {=_xll.BQL($C14, "volatility(calc_interval=range(-1M, 0D))")} -> #NAME? | CX14: {=_xll.BQL($C14, "volatility(calc_interval=range(-3M, 0D))")} -> #NAME? | CY14: {=_xll.BQL($C14, "volatility(calc_interval=range(-6M, 0D))")} -> #NAME? | CZ14: =_xll.BDP($C14,CZ$1) -> #NAME?
A15: =_xll.BDP($C15,"security name") -> #NAME? | B15: =_xll.BDP($C15,"NAME_CHINESE_SIMPLIFIED") -> #NAME? | C15: hmb ss EQUITY | D15: =_xll.BDP($C15,"LISTING_DATE") -> #NAME? | E15: =_xll.BDP($C15,E$1,"EQY_FUND_CRNCY="&$B$1) -> #NAME? | F15: =_xll.BDP($C15,F$1,"EQY_FUND_CRNCY="&$C$1) -> #NAME? | G15: =_xll.BDP($C15,G$1) -> #NAME? | H15: =_xll.BDP($C15,H$1,"EQY_FUND_CRNCY="&$B$1) -> #NAME? | I15: =_xll.BDP($C15,I$1,"EQY_FUND_CRNCY="&$C$1) -> #NAME? | J15: =_xll.BDP($C15,J$1,"EQY_FUND_CRNCY="&$B$1) -> #NAME? | K15: =_xll.BDP($C15,K$1,"EQY_FUND_CRNCY="&$C$1) -> #NAME? | L15: =_xll.BDP($C15,L$1,"EQY_FUND_CRNCY="&$B$1) -> #NAME? | M15: =_xll.BDP($C15,M$1,"EQY_FUND_CRNCY="&$C$1) -> #NAME? | N15: =_xll.BDP($C15,N$1)/100 -> #NAME? | O15: =_xll.BDP($C15,O$1)/100 -> #NAME? | P15: =_xll.BDP($C15,P$1)/100 -> #NAME? | Q15: =_xll.BDP($C15,Q$1)/100 -> #NAME? | R15: =_xll.BDP($C15,R$1)/100 -> #NAME? | S15: =_xll.BDP($C15,S$1)/100 -> #NAME? | T15: =_xll.BDP($C15,T$1)/100 -> #NAME? | U15: =_xll.BDP($C15,U$1)/100 -> #NAME? | ... W15: =_xll.BDP($C15,W$1)/100 -> #NAME? | X15: {=_xll.BDP($C15,"CRNCY_ADJ_CURR_EV", "EQY_FUND_CRNCY=HKD")} -> #NAME? | Y15: {=_xll.BDP($C15,"CRNCY_ADJ_CURR_EV", "EQY_FUND_CRNCY=USD")} -> #NAME? | Z15: =_xll.BDP($C15,Z$1)/100 -> #NAME? | AA15: =_xll.BDP($C15,"TRAIL_12M_NET_SALES","EQY_FUND_CRNCY=HKD") -> #NAME? | AB15: =_xll.BDP($C15,"TRAIL_12M_NET_INC","EQY_FUND_CRNCY=HKD") -> #NAME? | AC15: =_xll.BDP($C15,"TRAIL_12M_EBITDA","EQY_FUND_CRNCY=HKD") -> #NAME? | AD15: {=_xll.BQL($C15, "PE_RATIO(FPT=BA, FPR=2025, FYE=C1231, AE=E)")} -> #NAME? | AE15: {=_xll.BQL($C15, "PE_RATIO(FPT=BA, FPR=2026, FYE=C1231, AE=E)")} -> #NAME? | AF15: {=_xll.BQL($C15, "PE_RATIO(FPT=BA, FPR=2027, FYE=C1231, AE=E)")} -> #NAME? | AG15: {=_xll.BQL($C15, "PX_TO_SALES_RATIO(FPT=BA, FPR=2025, FYE=C1231, AE=E)")} -> #NAME? | AH15: {=_xll.BQL($C15, "PX_TO_SALES_RATIO(FPT=BA, FPR=2026, FYE=C1231, AE=E)")} -> #NAME? | AI15: {=_xll.BQL($C15, "PX_TO_SALES_RATIO(FPT=BA, FPR=2027, FYE=C1231, AE=E)")} -> #NAME? | AJ15: =IF(AC15<0,"N/A",$X15/AC15) -> #NAME? | AK15: {=IF(_xll.BQL($C15, "CURR_ENTP_VAL(FPT=A,FPO=0)/EBITDA(FPT=BA, FPR=2026, FYE=C1231, AE=E)")<0,"N/A",_xll.BQL($C15, "CURR_ENTP_VAL(FPT=A,FPO=0)/EBITDA(FPT=BA, FPR=2026, FYE=C1231, AE=E)"))} -> #NAME? | AL15: {=IF(_xll.BQL($C15, "CURR_ENTP_VAL(FPT=A,FPO=0)/EBITDA(FPT=BA, FPR=2027, FYE=C1231, AE=E)")<0,"N/A",_xll.BQL($C15, "CURR_ENTP_VAL(FPT=A,FPO=0)/EBITDA(FPT=BA, FPR=2027, FYE=C1231, AE=E)"))} -> #NAME? | AM15: =_xll.BDP($C15,AM$1) -> #NAME? | AN15: {=_xll.BQL($C15, "PX_TO_BOOK_RATIO(FPT=BA, FPR=2026, FYE=C1231, AE=E)")} -> #NAME? | AO15: {=_xll.BQL($C15, "PX_TO_BOOK_RATIO(FPT=BA, FPR=2027, FYE=C1231, AE=E)")} -> #NAME? | AP15: =_xll.BDP($C15,"BEST Px bps ratio","BEST fperiod override","27Y") -> #NAME? | AQ15: =Z15 -> #NAME? | AR15: =_xll.BDP($C15,"BEST_ROE","BEST fperiod override","26Y")/100 -> #NAME? | AS15: =_xll.BDP($C15,"BEST_ROE","BEST fperiod override","27Y")/100 -> #NAME? | AT15: =_xll.BDP($C15,AT$1) -> #NAME? | AU15: =_xll.BDP($C15,$AU$1,"BEST fperiod override","26Y") -> #NAME? | AV15: =_xll.BDP($C15,$AU$1,"BEST fperiod override","27Y") -> #NAME? | AW15: =(BP15/BN15)^(1/2)-1 -> #NAME? | AX15: =(BV15/BT15)^(1/2)-1 -> #NAME? | AY15: =(CB15/BZ15)^(1/2)-1 -> #NAME? | AZ15: {=_xll.BQL($C15, "CF_CASH_FROM_OPER(FPT=BA, FPR=2022, FYE=C1231, AE=A)", "currency=USD")/1000000000} -> #NAME? | BA15: {=_xll.BQL($C15, "CF_CASH_FROM_OPER(FPT=BA, FPR=2023, FYE=C1231, AE=A)", "currency=USD")/1000000000} -> #NAME? | BB15: {=_xll.BQL($C15, "CF_CASH_FROM_OPER(FPT=BA, FPR=2024, FYE=C1231, AE=A)", "currency=USD")/1000000000} -> #NAME? | BC15: {=_xll.BQL($C15, "CF_CASH_FROM_OPER(FPT=BA, FPR=2025, FYE=C1231, AE=E)", "currency=USD")/1000000000} -> #NAME? | BD15: {=_xll.BQL($C15, "CF_CASH_FROM_OPER(FPT=BA, FPR=2026, FYE=C1231, AE=E)", "currency=USD")/1000000000} -> #NAME? | BE15: {=_xll.BQL($C15, "CF_CASH_FROM_OPER(FPT=BA, FPR=2027, FYE=C1231, AE=E)", "currency=USD")/1000000000} -> #NAME? | BF15: {=_xll.BQL($C15, "CF_FREE_CASH_FLOW(FPT=BA, FPR=2022, FYE=C1231, AE=A)", "currency=USD")/1000000000} -> #NAME? | BG15: {=_xll.BQL($C15, "CF_FREE_CASH_FLOW(FPT=BA, FPR=2023, FYE=C1231, AE=A)", "currency=USD")/1000000000} -> #NAME? | BH15: {=_xll.BQL($C15, "CF_FREE_CASH_FLOW(FPT=BA, FPR=2024, FYE=C1231, AE=A)", "currency=USD")/1000000000} -> #NAME? | BI15: {=_xll.BQL($C15, "CF_FREE_CASH_FLOW(FPT=BA, FPR=2025, FYE=C1231, AE=E)", "currency=USD")/1000000000} -> #NAME? | BJ15: {=_xll.BQL($C15, "CF_FREE_CASH_FLOW(FPT=BA, FPR=2026, FYE=C1231, AE=E)", "currency=USD")/1000000000} -> #NAME? | BK15: {=_xll.BQL($C15, "CF_FREE_CASH_FLOW(FPT=BA, FPR=2027, FYE=C1231, AE=E)", "currency=USD")/1000000000} -> #NAME? | BL15: {=_xll.BQL($C15, "SALES_REV_TURN(FPT=BA, FPR=2022, FYE=C1231, AE=A)", "currency=USD")/1000000000} -> #NAME? | BM15: {=_xll.BQL($C15, "SALES_REV_TURN(FPT=BA, FPR=2023, FYE=C1231, AE=A)", "currency=USD")/1000000000} -> #NAME? | BN15: {=_xll.BQL($C15, "SALES_REV_TURN(FPT=BA, FPR=2024, FYE=C1231, AE=A)", "currency=USD")/1000000000} -> #NAME? | BO15: {=_xll.BQL($C15, "SALES_REV_TURN(FPT=BA, FPR=2025, FYE=C1231, AE=E)", "currency=USD")/1000000000} -> #NAME? | BP15: {=_xll.BQL($C15, "SALES_REV_TURN(FPT=BA, FPR=2026, FYE=C1231, AE=E)", "currency=USD")/1000000000} -> #NAME? | BQ15: {=_xll.BQL($C15, "SALES_REV_TURN(FPT=BA, FPR=2027, FYE=C1231, AE=E)", "currency=USD")/1000000000} -> #NAME? | BR15: {=_xll.BQL($C15, "EBITDA(FPT=BA, FPR=2022, FYE=C1231, AE=A)", "currency=USD")/1000000000} -> #NAME? | BS15: {=_xll.BQL($C15, "EBITDA(FPT=BA, FPR=2023, FYE=C1231, AE=A)", "currency=USD")/1000000000} -> #NAME? | BT15: {=_xll.BQL($C15, "EBITDA(FPT=BA, FPR=2024, FYE=C1231, AE=A)", "currency=USD")/1000000000} -> #NAME? | BU15: {=_xll.BQL($C15, "EBITDA(FPT=BA, FPR=2025, FYE=C1231, AE=E)", "currency=USD")/1000000000} -> #NAME? | BV15: {=_xll.BQL($C15, "EBITDA(FPT=BA, FPR=2026, FYE=C1231, AE=E)", "currency=USD")/1000000000} -> #NAME? | BW15: {=_xll.BQL($C15, "EBITDA(FPT=BA, FPR=2027, FYE=C1231, AE=E)", "currency=USD")/1000000000} -> #NAME? | BX15: {=_xll.BQL($C15, "NET_INCOME(FPT=BA, FPR=2022, FYE=C1231, AE=A)", "currency=USD")/1000000000} -> #NAME? | BY15: {=_xll.BQL($C15, "NET_INCOME(FPT=BA, FPR=2023, FYE=C1231, AE=A)", "currency=USD")/1000000000} -> #NAME? | BZ15: {=_xll.BQL($C15, "NET_INCOME(FPT=BA, FPR=2024, FYE=C1231, AE=A)", "currency=USD")/1000000000} -> #NAME? | CA15: {=_xll.BQL($C15, "NET_INCOME(FPT=BA, FPR=2025, FYE=C1231, AE=E)", "currency=USD")/1000000000} -> #NAME? | CB15: {=_xll.BQL($C15, "NET_INCOME(FPT=BA, FPR=2026, FYE=C1231, AE=E)", "currency=USD")/1000000000} -> #NAME? | CC15: {=_xll.BQL($C15, "NET_INCOME(FPT=BA, FPR=2027, FYE=C1231, AE=E)", "currency=USD")/1000000000} -> #NAME? | CD15: {=-_xll.BQL($C15, "CF_DVD_PAID(FPT=BA, FPR=2024, FYE=C1231, AE=A)", "currency=USD")/1000000000} -> #NAME? | CE15: {=-_xll.BQL($C15, "CF_DVD_PAID(FPT=BA, FPR=2025, FYE=C1231, AE=E)", "currency=USD")/1000000000} -> #NAME? | CF15: {=-_xll.BQL($C15, "CF_DVD_PAID(FPT=BA, FPR=2026, FYE=C1231, AE=E)", "currency=USD")/1000000000} -> #NAME? | CG15: {=-_xll.BQL($C15, "CF_DVD_PAID(FPT=BA, FPR=2027, FYE=C1231, AE=E)", "currency=USD")/1000000000} -> #NAME? | CH15: =CD15/$F15 -> #NAME? | CI15: =CE15/$F15 -> #NAME? | CJ15: =CF15/$F15 -> #NAME? | CK15: =CG15/$F15 -> #NAME? | CL15: {=_xll.BDP($C15,"INTERVAL_AVG", "MARKET_DATA_OVERRIDE=turnover", "CALC_INTERVAL=5D","CRNCY=HKD")/1000000} -> #NAME? | CM15: {=_xll.BDP($C15,"INTERVAL_AVG", "MARKET_DATA_OVERRIDE=turnover", "CALC_INTERVAL=10D","CRNCY=HKD")/1000000} -> #NAME? | CN15: {=_xll.BDP($C15,"INTERVAL_AVG", "MARKET_DATA_OVERRIDE=turnover", "CALC_INTERVAL=20D","CRNCY=HKD")/1000000} -> #NAME? | CO15: {=_xll.BDP($C15,"INTERVAL_AVG", "MARKET_DATA_OVERRIDE=turnover", "CALC_INTERVAL=1m","CRNCY=HKD")/1000000} -> #NAME? | CP15: {=_xll.BDP($C15,"INTERVAL_AVG", "MARKET_DATA_OVERRIDE=turnover", "CALC_INTERVAL=3M","CRNCY=HKD")/1000000} -> #NAME? | CQ15: {=_xll.BDP($C15,"INTERVAL_AVG", "MARKET_DATA_OVERRIDE=turnover", "CALC_INTERVAL=6M","CRNCY=HKD")/1000000} -> #NAME? | CR15: =_xll.BDP($C15,"chg pct 1m")/100 -> #NAME? | CS15: =_xll.BDP($C15,"chg pct 3m")/100 -> #NAME? | CT15: =_xll.BDP($C15,"chg pct 6m")/100 -> #NAME? | CU15: =_xll.BDP($C15,"chg pct 1yr")/100 -> #NAME? | CV15: =_xll.BDP($C15,"chg pct ytd")/100 -> #NAME? | CW15: {=_xll.BQL($C15, "volatility(calc_interval=range(-1M, 0D))")} -> #NAME? | CX15: {=_xll.BQL($C15, "volatility(calc_interval=range(-3M, 0D))")} -> #NAME? | CY15: {=_xll.BQL($C15, "volatility(calc_interval=range(-6M, 0D))")} -> #NAME? | CZ15: =_xll.BDP($C15,CZ$1) -> #NAME?
E16: pe
B17: HK | C17: 13.732419 | E17: {=_xll.BDP("HSI Index", "PE_RATIO")} -> #NAME? | L17: Max | M17: Max | N17: =MAX(N7:N11) -> #NAME? | O17: =MAX(O7:O11) -> #NAME? | P17: =MAX(P7:P11) -> #NAME? | Q17: =MAX(Q7:Q11) -> #NAME? | R17: =MAX(#REF!) -> #REF! | S17: =MAX(#REF!) -> #REF! | T17: =MAX(#REF!) -> #REF! | U17: =MAX(#REF!) -> #REF! | V17: =MAX(#REF!) -> #REF! | W17: =MAX(#REF!) -> #REF! | X17: =MAX(#REF!) -> #REF! | Y17: =MAX(#REF!) -> #REF! | Z17: =MAX(#REF!) -> #REF! | AD17: =MAX(AD7:AD11) -> #NAME? | AE17: =MAX(AE7:AE9) -> #NAME? | AF17: =MAX(AF7:AF9) -> #NAME? | AG17: =MAX(AG7:AG9) -> #NAME? | AH17: =MAX(AH7:AH9) -> #NAME? | AI17: =MAX(AI7:AI9) -> #NAME? | AJ17: =MAX(AJ7:AJ9) -> #NAME? | AK17: =MAX(AK7:AK9) -> #NAME? | AL17: =MAX(AL7:AL9) -> #NAME? | ... AV17: =MAX(AV7:AV9) -> #NAME? | CL17: =MAX(CL7:CL9) -> #NAME? | CM17: =MAX(CM7:CM9) -> #NAME? | CN17: =MAX(CN7:CN9) -> #NAME? | CO17: =MAX(CO7:CO9) -> #NAME? | CP17: =MAX(CP7:CP9) -> #NAME? | CQ17: =MAX(CQ7:CQ9) -> #NAME? | CR17: =MAX(CR7:CR9) -> #NAME? | CS17: =MAX(CS7:CS9) -> #NAME? | ... CY17: =MAX(CY7:CY9) -> #NAME?
B18: NY | C18: 20.580119 | E18: {=_xll.BDP("NYA Index", "PE_RATIO")} -> #NAME? | L18: Median | M18: Median | N18: =MEDIAN(N7:N11) -> #NAME? | O18: =MEDIAN(O7:O11) -> #NAME? | P18: =MEDIAN(P7:P11) -> #NAME? | Q18: =MEDIAN(Q7:Q11) -> #NAME? | R18: =MEDIAN(#REF!) -> #REF! | S18: =MEDIAN(#REF!) -> #REF! | T18: =MEDIAN(#REF!) -> #REF! | U18: =MEDIAN(#REF!) -> #REF! | V18: =MEDIAN(#REF!) -> #REF! | W18: =MEDIAN(#REF!) -> #REF! | X18: =MEDIAN(#REF!) -> #REF! | Y18: =MEDIAN(#REF!) -> #REF! | Z18: =MEDIAN(#REF!) -> #REF! | AD18: =MEDIAN(AD7:AD9) -> #NAME? | AE18: =MEDIAN(AE7:AE9) -> #NAME? | AF18: =MEDIAN(AF7:AF9) -> #NAME? | AG18: =MEDIAN(AG7:AG9) -> #NAME? | AH18: =MEDIAN(AH7:AH9) -> #NAME? | AI18: =MEDIAN(AI7:AI9) -> #NAME? | AJ18: =MEDIAN(AJ7:AJ9) -> #NAME? | AK18: =MEDIAN(AK7:AK9) -> #NAME? | ... AV18: =MEDIAN(AV7:AV9) -> #NAME? | CL18: =MEDIAN(CL7:CL9) -> #NAME? | CM18: =MEDIAN(CM7:CM9) -> #NAME? | CN18: =MEDIAN(CN7:CN9) -> #NAME? | CO18: =MEDIAN(CO7:CO9) -> #NAME? | CP18: =MEDIAN(CP7:CP9) -> #NAME? | CQ18: =MEDIAN(CQ7:CQ9) -> #NAME? | CR18: =MEDIAN(CR7:CR9) -> #NAME? | CS18: =MEDIAN(CS7:CS9) -> #NAME? | ... CY18: =MEDIAN(CY7:CY9) -> #NAME?
B19: LN | C19: 16.720078 | E19: {=_xll.BDP("UKX Index", "PE_RATIO")} -> #NAME? | L19: Mean | M19: Mean | N19: =AVERAGE(N7:N11) -> #NAME? | O19: =AVERAGE(O7:O11) -> #NAME? | P19: =AVERAGE(P7:P11) -> #NAME? | Q19: =AVERAGE(Q7:Q11) -> #NAME? | R19: =AVERAGE(#REF!) -> #REF! | S19: =AVERAGE(#REF!) -> #REF! | T19: =AVERAGE(#REF!) -> #REF! | U19: =AVERAGE(#REF!) -> #REF! | V19: =AVERAGE(#REF!) -> #REF! | W19: =AVERAGE(#REF!) -> #REF! | X19: =AVERAGE(#REF!) -> #REF! | Y19: =AVERAGE(#REF!) -> #REF! | Z19: =AVERAGE(#REF!) -> #REF! | AD19: =AVERAGE(AD7:AD9) -> #NAME? | AE19: =AVERAGE(AE7:AE9) -> #NAME? | AF19: =AVERAGE(AF7:AF9) -> #NAME? | AG19: =AVERAGE(AG7:AG9) -> #NAME? | AH19: =AVERAGE(AH7:AH9) -> #NAME? | AI19: =AVERAGE(AI7:AI9) -> #NAME? | AJ19: =AVERAGE(AJ7:AJ9) -> #NAME? | AK19: =AVERAGE(AK7:AK9) -> #NAME? | ... AV19: =AVERAGE(AV7:AV9) -> #NAME? | CL19: =AVERAGE(CL7:CL9) -> #NAME? | CM19: =AVERAGE(CM7:CM9) -> #NAME? | CN19: =AVERAGE(CN7:CN9) -> #NAME? | CO19: =AVERAGE(CO7:CO9) -> #NAME? | CP19: =AVERAGE(CP7:CP9) -> #NAME? | CQ19: =AVERAGE(CQ7:CQ9) -> #NAME? | CR19: =AVERAGE(CR7:CR9) -> #NAME? | CS19: =AVERAGE(CS7:CS9) -> #NAME? | ... CY19: =AVERAGE(CY7:CY9) -> #NAME?
B20: INDIA | C20: 21.956182 | E20: {=_xll.BDP("NIFTY Index", "PE_RATIO")} -> #NAME? | L20: Min | M20: Min | N20: =MIN(N7:N11) -> #NAME? | O20: =MIN(O7:O11) -> #NAME? | P20: =MIN(P7:P11) -> #NAME? | Q20: =MIN(Q7:Q11) -> #NAME? | R20: =MIN(#REF!) -> #REF! | S20: =MIN(#REF!) -> #REF! | T20: =MIN(#REF!) -> #REF! | U20: =MIN(#REF!) -> #REF! | V20: =MIN(#REF!) -> #REF! | W20: =MIN(#REF!) -> #REF! | X20: =MIN(#REF!) -> #REF! | Y20: =MIN(#REF!) -> #REF! | Z20: =MIN(#REF!) -> #REF! | AD20: =MIN(AD7:AD9) -> #NAME? | AE20: =MIN(AE7:AE9) -> #NAME? | AF20: =MIN(AF7:AF9) -> #NAME? | AG20: =MIN(AG7:AG9) -> #NAME? | AH20: =MIN(AH7:AH9) -> #NAME? | AI20: =MIN(AI7:AI9) -> #NAME? | AJ20: =MIN(AJ7:AJ9) -> #NAME? | AK20: =MIN(AK7:AK9) -> #NAME? | ... AV20: =MIN(AV7:AV9) -> #NAME? | CL20: =MIN(CL7:CL9) -> #NAME? | CM20: =MIN(CM7:CM9) -> #NAME? | CN20: =MIN(CN7:CN9) -> #NAME? | CO20: =MIN(CO7:CO9) -> #NAME? | CP20: =MIN(CP7:CP9) -> #NAME? | CQ20: =MIN(CQ7:CQ9) -> #NAME? | CR20: =MIN(CR7:CR9) -> #NAME? | CS20: =MIN(CS7:CS9) -> #NAME? | ... CY20: =MIN(CY7:CY9) -> #NAME?
B21: STOCKHOLM | C21: 14.84786 | E21: {=_xll.BDP("OMX Index", "PE_RATIO")} -> #NAME?
B22: NASDAQ | C22: 40.245419 | E22: {=_xll.BDP("ndx Index", "PE_RATIO")} -> #NAME?
E23: ps
B24: HK | C24: 4.5696845 | E24: {=_xll.BQL("members('HSI Index')", "avg(group(px_to_sales_ratio().value))")} -> #NAME?
B25: NY | E25: {=_xll.BQL("members('NYA Index')", "avg(group(px_to_sales_ratio().value))")} -> #NAME? | J25: =E24/E25 -> #NAME?
B26: LN | C26: 2.786486 | E26: {=_xll.BQL("members('UKX Index')", "avg(group(px_to_sales_ratio().value))")} -> #NAME?
B27: INDIA | C27: 4.8486973 | E27: {=_xll.BQL("members('NIFTY Index')", "avg(group(px_to_sales_ratio().value))")} -> #NAME?
B28: STOCKHOLM | C28: 3.5492543 | E28: {=_xll.BQL("members('OMX Index')", "avg(group(px_to_sales_ratio().value))")} -> #NAME?
B29: NASDAQ | C29: 11.666455 | E29: {=_xll.BQL("members('NDX Index')", "avg(group(px_to_sales_ratio().value))")} -> #NAME?
E31: {=_xll.BQL("members('HSI Index')", "avg(group(EV_TO_EBITDAR().value))")} -> #NAME?
E32: \
E33: {=_xll.BQL("members('UKX Index')", "avg(group(EV_TO_EBITDAR().value))")} -> #NAME?
E34: {=_xll.BQL("members('HSI Index')", "avg(group(EV_TO_EBITDAR().value))")} -> #NAME?
E35: \
E36: {=_xll.BQL("members('NDX Index')", "avg(group(EV_TO_EBITDAR().value))")} -> #NAME?

Sheet Sheet 2
C2: PE (2025) Original | D2: PE (2025) (Normalised to HK) | E2: PE (TTM) Original | F2: PE (TTM) (Normalised to HK) | G2: PE (2026F) Original | H2: PE (2026F) (Normalised to HK) | I2: PE (2027F) Original | J2: PE (2027F) (Normalised to HK) | K2: PS 2025 | L2: HK local PS 2025 | M2: PS TTM | N2: PS 2026 | O2: HK local PS 2026 | P2: PS T2027 | Q2: HK local PS 2027 | R2: EV/EBITDA 2026 | S2: HK Local EV/EBITDA 2026 | T2: EV/EBITDA 2026 | U2: HK Local EV/EBITDA 2027
B3: PDS Ltd | C3: 37.379277 | D3: =IF(C3="","",C3*Sheet2!$C$17/Sheet2!C20) -> 23.378742 | E3: =IFERROR(VLOOKUP(B3,Sheet2!$B$7:$AF$15,29,0),"") -> 34.063097 | F3: =IF(E3="","",E3*Sheet2!$C$17/Sheet2!C20) -> 21.304648 | G3: =IFERROR(VLOOKUP(B3,Sheet2!$B$7:$AF$15,30,0),"") -> 34.159526 | H3: =IF(G3="","",G3*Sheet2!$C$17/Sheet2!C20) -> 21.364959 | I3: =IFERROR(VLOOKUP(B3,Sheet2!$B$7:$AF$15,31,0),"") -> 27.694363 | J3: =IF(I3="","",I3*Sheet2!$C$17/Sheet2!C20) -> 17.321345 | K3: 0.3287479 | L3: =IF(K3="","",K3*Sheet2!$C$24/Sheet2!$C27) -> 0.30983048 | M3: =IFERROR(VLOOKUP(B3,Sheet2!$B$7:$AJ$15,32,0),"") -> 37.379277 | N3: =IFERROR(VLOOKUP(B3,Sheet2!$B$7:$AJ$15,33,0),"") -> 0.29020149 | O3: =IF(N3="","",N3*Sheet2!$C$24/Sheet2!$C27) -> 0.27350217 | P3: =IFERROR(VLOOKUP(B3,Sheet2!$B$7:$AJ$15,34,0),"") -> 0.29706215 | Q3: =IF(P3="","",P3*Sheet2!$C$24/Sheet2!$C27) -> 0.27996805 | R3: #N/A | S3: =IF(R3="","",R3*Sheet2!$C$31/Sheet2!$C34) -> #VALUE! | T3: #N/A | U3: =IF(T3="","",T3*Sheet2!$C$31/Sheet2!$C34) -> #VALUE!
B4: 沃尔玛股份有限公司 | C4: 45.288336 | D4: =IF(C4="","",C4*Sheet2!$C$17/Sheet2!C22) -> 15.453148 | E4: =IFERROR(VLOOKUP(B4,Sheet2!$B$7:$AF$15,29,0),"") -> 49.093332 | F4: =IF(E4="","",E4*Sheet2!$C$17/Sheet2!C22) -> 16.751477 | G4: =IFERROR(VLOOKUP(B4,Sheet2!$B$7:$AF$15,30,0),"") -> 46.576104 | H4: =IF(G4="","",G4*Sheet2!$C$17/Sheet2!C22) -> 15.892556 | I4: =IFERROR(VLOOKUP(B4,Sheet2!$B$7:$AF$15,31,0),"") -> 40.85241 | J4: =IF(I4="","",I4*Sheet2!$C$17/Sheet2!C22) -> 13.939535 | K4: 1.337026 | L4: =IF(K4="","",K4*Sheet2!$C$24/Sheet2!$C29) -> 0.52370554 | M4: =IFERROR(VLOOKUP(B4,Sheet2!$B$7:$AJ$15,32,0),"") -> 45.288336 | N4: =IFERROR(VLOOKUP(B4,Sheet2!$B$7:$AJ$15,33,0),"") -> 1.5070893 | O4: =IF(N4="","",N4*Sheet2!$C$24/Sheet2!$C29) -> 0.59031835 | P4: =IFERROR(VLOOKUP(B4,Sheet2!$B$7:$AJ$15,34,0),"") -> 1.433405 | Q4: =IF(P4="","",P4*Sheet2!$C$24/Sheet2!$C29) -> 0.56145662 | R4: 21.698405 | S4: =IF(R4="","",R4*Sheet2!$C$31/Sheet2!$C36) -> 4.1101402 | T4: 19.712839 | U4: =IF(T4="","",T4*Sheet2!$C$31/Sheet2!$C36) -> 3.7340319
B5: 美鹰傲飞AEO有限公司 | C5: 15.937874 | D5: =IF(C5="","",C5*Sheet2!$C$17/Sheet2!C18) -> 10.634806 | E5: =IFERROR(VLOOKUP(B5,Sheet2!$B$7:$AF$15,29,0),"") -> 13.466502 | F5: =IF(E5="","",E5*Sheet2!$C$17/Sheet2!C18) -> 8.9857426 | G5: =IFERROR(VLOOKUP(B5,Sheet2!$B$7:$AF$15,30,0),"") -> 8.8269914 | H5: =IF(G5="","",G5*Sheet2!$C$17/Sheet2!C18) -> 5.8899537 | I5: =IFERROR(VLOOKUP(B5,Sheet2!$B$7:$AF$15,31,0),"") -> 7.7833708 | J5: =IF(I5="","",I5*Sheet2!$C$17/Sheet2!C18) -> 5.1935809 | K5: 0.54861584 | L5: \ | M5: =IFERROR(VLOOKUP(B5,Sheet2!$B$7:$AJ$15,32,0),"") -> 15.937874 | N5: =IFERROR(VLOOKUP(B5,Sheet2!$B$7:$AJ$15,33,0),"") -> 0.46605903 | O5: \ | P5: =IFERROR(VLOOKUP(B5,Sheet2!$B$7:$AJ$15,34,0),"") -> 0.44585488 | Q5: \ | R5: 8.3320805 | S5: \ | T5: 7.6098393 | U5: \
B6: 开市客公司 | C6: 53.670448 | D6: =IF(C6="","",C6*Sheet2!$C$17/Sheet2!C22) -> 18.313267 | E6: =IFERROR(VLOOKUP(B6,Sheet2!$B$7:$AF$15,29,0),"") -> 57.053171 | F6: =IF(E6="","",E6*Sheet2!$C$17/Sheet2!C22) -> 19.467509 | G6: =IFERROR(VLOOKUP(B6,Sheet2!$B$7:$AF$15,30,0),"") -> 51.687613 | H6: =IF(G6="","",G6*Sheet2!$C$17/Sheet2!C22) -> 17.63669 | I6: =IFERROR(VLOOKUP(B6,Sheet2!$B$7:$AF$15,31,0),"") -> 46.888178 | J6: =IF(I6="","",I6*Sheet2!$C$17/Sheet2!C22) -> 15.999041 | K6: 1.5737516 | L6: =IF(K6="","",K6*Sheet2!$C$24/Sheet2!$C29) -> 0.6164296 | M6: =IFERROR(VLOOKUP(B6,Sheet2!$B$7:$AJ$15,32,0),"") -> 53.670448 | N6: =IFERROR(VLOOKUP(B6,Sheet2!$B$7:$AJ$15,33,0),"") -> 1.7038323 | O6: =IF(N6="","",N6*Sheet2!$C$24/Sheet2!$C29) -> 0.66738148 | P6: =IFERROR(VLOOKUP(B6,Sheet2!$B$7:$AJ$15,34,0),"") -> 1.5700454 | Q6: =IF(P6="","",P6*Sheet2!$C$24/Sheet2!$C29) -> 0.61497792 | R6: 27.964893 | S6: =IF(R6="","",R6*Sheet2!$C$31/Sheet2!$C36) -> 5.2971468 | T6: 25.553506 | U6: =IF(T6="","",T6*Sheet2!$C$31/Sheet2!$C36) -> 4.8403787
B7: 英国联合食品公共有限公司 | C7: 10.9633 | D7: =IF(C7="","",C7*Sheet2!$C$17/Sheet2!C19) -> 9.004302 | E7: =IFERROR(VLOOKUP(B7,Sheet2!$B$7:$AF$15,29,0),"") -> 13.657785 | F7: =IF(E7="","",E7*Sheet2!$C$17/Sheet2!C19) -> 11.217318 | G7: =IFERROR(VLOOKUP(B7,Sheet2!$B$7:$AF$15,30,0),"") -> 11.27466 | H7: =IF(G7="","",G7*Sheet2!$C$17/Sheet2!C19) -> 9.2600259 | I7: =IFERROR(VLOOKUP(B7,Sheet2!$B$7:$AF$15,31,0),"") -> 10.646149 | J7: =IF(I7="","",I7*Sheet2!$C$17/Sheet2!C19) -> 8.7438221 | K7: 0.67762957 | L7: =IF(K7="","",K7*Sheet2!$C$24/Sheet2!$C26) -> 1.1112754 | M7: =IFERROR(VLOOKUP(B7,Sheet2!$B$7:$AJ$15,32,0),"") -> 10.9633 | N7: =IFERROR(VLOOKUP(B7,Sheet2!$B$7:$AJ$15,33,0),"") -> 0.66812028 | O7: =IF(N7="","",N7*Sheet2!$C$24/Sheet2!$C26) -> 1.0956807 | P7: =IFERROR(VLOOKUP(B7,Sheet2!$B$7:$AJ$15,34,0),"") -> 0.68200855 | Q7: =IF(P7="","",P7*Sheet2!$C$24/Sheet2!$C26) -> 1.1184567 | R7: 7.290167 | S7: =IF(R7="","",R7*Sheet2!$C$31/Sheet2!$C33) -> 26.031739 | T7: 6.9691059 | U7: =IF(T7="","",T7*Sheet2!$C$31/Sheet2!$C33) -> 24.885294
B8: CVS健康公司 | C8: 27.83992 | D8: =IF(C8="","",C8*Sheet2!$C$17/Sheet2!C18) -> 18.57664 | E8: =IFERROR(VLOOKUP(B8,Sheet2!$B$7:$AF$15,29,0),"") -> 41.142407 | F8: =IF(E8="","",E8*Sheet2!$C$17/Sheet2!C18) -> 27.452941 | G8: =IFERROR(VLOOKUP(B8,Sheet2!$B$7:$AF$15,30,0),"") -> 12.755116 | H8: =IF(G8="","",G8*Sheet2!$C$17/Sheet2!C18) -> 8.5110591 | I8: =IFERROR(VLOOKUP(B8,Sheet2!$B$7:$AF$15,31,0),"") -> 11.256229 | J8: =IF(I8="","",I8*Sheet2!$C$17/Sheet2!C18) -> 7.5109019 | K8: 7.6194477 | L8: \ | M8: =IFERROR(VLOOKUP(B8,Sheet2!$B$7:$AJ$15,32,0),"") -> 13.818396 | N8: =IFERROR(VLOOKUP(B8,Sheet2!$B$7:$AJ$15,33,0),"") -> 0.29572949 | O8: \ | P8: =IFERROR(VLOOKUP(B8,Sheet2!$B$7:$AJ$15,34,0),"") -> 0.2950372 | Q8: \ | R8: 22.767815 | S8: \ | T8: 20.555926 | U8: \
B9: 海恩斯莫里斯公司 | C9: 35.431551 | D9: =IF(C9="","",C9*Sheet2!$C$17/Sheet2!C21) -> 32.769768 | E9: =IFERROR(VLOOKUP(B9,Sheet2!$B$7:$AF$15,29,0),"") -> 21.549061 | F9: =IF(E9="","",E9*Sheet2!$C$17/Sheet2!C21) -> 19.930195 | G9: =IFERROR(VLOOKUP(B9,Sheet2!$B$7:$AF$15,30,0),"") -> 19.094264 | H9: =IF(G9="","",G9*Sheet2!$C$17/Sheet2!C21) -> 17.659814 | I9: =IFERROR(VLOOKUP(B9,Sheet2!$B$7:$AF$15,31,0),"") -> 18.103523 | J9: =IF(I9="","",I9*Sheet2!$C$17/Sheet2!C21) -> 16.743502 | K9: 1.2761392 | L9: =IF(K9="","",K9*Sheet2!$C$24/Sheet2!$C28) -> 1.6430362 | M9: =IFERROR(VLOOKUP(B9,Sheet2!$B$7:$AJ$15,32,0),"") -> 23.236558 | N9: =IFERROR(VLOOKUP(B9,Sheet2!$B$7:$AJ$15,33,0),"") -> 1.1901611 | O9: =IF(N9="","",N9*Sheet2!$C$24/Sheet2!$C28) -> 1.5323389 | P9: =IFERROR(VLOOKUP(B9,Sheet2!$B$7:$AJ$15,34,0),"") -> 1.1749797 | Q9: =IF(P9="","",P9*Sheet2!$C$24/Sheet2!$C28) -> 1.5127929 | R9: 21.826218 | S9: =IF(R9="","",R9*Sheet2!$C$24/Sheet2!$C35) -> #VALUE! | T9: 18.813097 | U9: =IF(T9="","",T9*Sheet2!$C$24/Sheet2!$C35) -> #VALUE!
B10: 曼哈顿联合软件公司 | C10: 13.818396 | D10: =IF(C10="","",C10*Sheet2!$C$17/Sheet2!C22) -> 4.715071 | E10: =IFERROR(VLOOKUP(B10,Sheet2!$B$7:$AF$15,29,0),"") -> 37.120723 | F10: =IF(E10="","",E10*Sheet2!$C$17/Sheet2!C22) -> 12.66622 | G10: =IFERROR(VLOOKUP(B10,Sheet2!$B$7:$AF$15,30,0),"") -> 25.272783 | H10: =IF(G10="","",G10*Sheet2!$C$17/Sheet2!C22) -> 8.6235021 | I10: =IFERROR(VLOOKUP(B10,Sheet2!$B$7:$AF$15,31,0),"") -> 22.705603 | J10: =IF(I10="","",I10*Sheet2!$C$17/Sheet2!C22) -> 7.7475365 | K10: 0.2935952 | L10: =IF(K10="","",K10*Sheet2!$C$24/Sheet2!$C29) -> 0.11499958 | M10: =IFERROR(VLOOKUP(B10,Sheet2!$B$7:$AJ$15,32,0),"") -> 27.83992 | N10: =IFERROR(VLOOKUP(B10,Sheet2!$B$7:$AJ$15,33,0),"") -> 7.30602 | O10: =IF(N10="","",N10*Sheet2!$C$24/Sheet2!$C29) -> 2.8617267 | P10: =IFERROR(VLOOKUP(B10,Sheet2!$B$7:$AJ$15,34,0),"") -> 6.9463799 | Q10: =IF(P10="","",P10*Sheet2!$C$24/Sheet2!$C29) -> 2.7208577 | R10: 9.0639446 | S10: =IF(R10="","",R10*Sheet2!$C$31/Sheet2!$C36) -> 1.7169043 | T10: 8.7266069 | U10: =IF(T10="","",T10*Sheet2!$C$31/Sheet2!$C36) -> 1.6530053
B11: 罗宾逊全球物流有限公司 | C11: 23.236558 | D11: =IF(C11="","",C11*Sheet2!$C$17/Sheet2!C22) -> 7.9287076 | E11: =IFERROR(VLOOKUP(B11,Sheet2!$B$7:$AF$15,29,0),"") -> 34.169947 | F11: =IF(E11="","",E11*Sheet2!$C$17/Sheet2!C22) -> 11.659365 | G11: =IFERROR(VLOOKUP(B11,Sheet2!$B$7:$AF$15,30,0),"") -> 28.120531 | H11: =IF(G11="","",G11*Sheet2!$C$17/Sheet2!C22) -> 9.5952019 | I11: =IFERROR(VLOOKUP(B11,Sheet2!$B$7:$AF$15,31,0),"") -> 23.718266 | J11: =IF(I11="","",I11*Sheet2!$C$17/Sheet2!C22) -> 8.0930743 | K11: 1.1661493 | L11: =IF(K11="","",K11*Sheet2!$C$24/Sheet2!$C29) -> 0.45677407 | M11: =IFERROR(VLOOKUP(B11,Sheet2!$B$7:$AJ$15,32,0),"") -> 35.431551 | N11: =IFERROR(VLOOKUP(B11,Sheet2!$B$7:$AJ$15,33,0),"") -> 1.263551 | O11: =IF(N11="","",N11*Sheet2!$C$24/Sheet2!$C29) -> 0.49492578 | P11: =IFERROR(VLOOKUP(B11,Sheet2!$B$7:$AJ$15,34,0),"") -> 1.2081685 | Q11: =IF(P11="","",P11*Sheet2!$C$24/Sheet2!$C29) -> 0.47323275 | R11: 8.3000656 | S11: =IF(R11="","",R11*Sheet2!$C$31/Sheet2!$C36) -> 1.5722093 | T11: 8.0155369 | U11: =IF(T11="","",T11*Sheet2!$C$31/Sheet2!$C36) -> 1.5183135
B13: median | C13: =MEDIAN(C3:C11) -> 27.83992 | D13: =MEDIAN(D3:D11) -> 15.453148 | E13: =MEDIAN(E3:E11) -> 34.169947 | F13: =MEDIAN(F3:F11) -> 16.751477 | G13: =MEDIAN(G3:G11) -> 25.272783 | H13: =MEDIAN(H3:H11) -> 9.5952019 | I13: =MEDIAN(I3:I11) -> 22.705603 | J13: =MEDIAN(J3:J11) -> 8.7438221 | K13: =MEDIAN(K3:K11) -> 1.1661493 | L13: =MEDIAN(L3:L4,L6:L7,L9:L11) -> 0.52370554 | M13: =MEDIAN(M3:M11) -> 27.83992 | N13: =MEDIAN(N3:N11) -> 1.1901611 | O13: =MEDIAN(O3:O4,O6:O7,O9:O11) -> 0.66738148 | P13: =MEDIAN(P3:P11) -> 1.1749797 | Q13: =MEDIAN(Q3:Q4,Q6:Q7,Q9:Q11) -> 0.61497792 | S13: =MEDIAN(S4,S6,S7,S11,S10) -> 4.1101402 | U13: =MEDIAN(U4,U6,U7,U11,U10) -> 3.7340319
B14: average | C14: =AVERAGE(C3:C11) -> 29.285073 | D14: =AVERAGE(D3:D11) -> 15.641606 | E14: =AVERAGE(E3:E11) -> 33.479558 | F14: =AVERAGE(F3:F11) -> 16.603935 | G14: =AVERAGE(G3:G11) -> 26.418621 | H14: =AVERAGE(H3:H11) -> 12.714863 | I14: =AVERAGE(I3:I11) -> 23.294232 | J14: =AVERAGE(J3:J11) -> 11.254704 | K14: =AVERAGE(K3:K11) -> 1.6467891 | L14: =AVERAGE(L3:L4,L6:L7,L9:L11) -> 0.68229298 | M14: =AVERAGE(M3:M11) -> 29.285073 | N14: =AVERAGE(N3:N11) -> 1.6323071 | O14: =AVERAGE(O3:O4,O6:O7,O9:O11) -> 1.0736963 | P14: =AVERAGE(P3:P11) -> 1.5614379 | Q14: =AVERAGE(Q3:Q4,Q6:Q7,Q9:Q11) -> 1.0402489 | S14: =AVERAGE(S11,S10,S7,S6,S4) -> 7.745628 | U14: =AVERAGE(U11,U10,U7,U6,U4) -> 7.3262046
O16: 0.27350217
O17: 0.59031835
O18: 0.47
O19: 0.66738148
O20: 1.0956807
O21: 0.3
O22: 1.5323389
O23: 2.8617267
O24: 0.49492578
O26: =MEDIAN(O16:O24) -> 0.59031835
O27: =AVERAGE(O16:O24) -> 0.92065268

Sheet Sheet3
A1: (2)
A3: If after expanding search scope of Comp using "AI-enabled B2B supply chain service providers" on 15 May 2026,
A7: (a) software centric e.g. Oracle/SAP --> suggest we add Manhattan Associates, P/E TTM close to 40) :
A25: (b) logistic centric e.g. UPS / Fedex --> suggest you add CWRW.nasdaq, P/E TTM close to 35 :

Sheet Sheet2
A1: Currency | B1: HKD | C1: USD | E1: CRNCY_ADJ_MKT_CAP | F1: Crncy Adj Mkt Cap | G1: Px Last | H1: Net Assets | I1: Net Assets | J1: Sales Rev Turn | K1: Sales Rev Turn | L1: Net Income | M1: Net Income | N1: Gross_Margin_Adjusted | O1: EBITDA_MARGIN_ADJUSTED | P1: Prof Margin | Q1: Sales_Growth | R1: Net Inc Growth | S1: TOT_DEBT_TO_TOT_EQY | T1: TOT_DEBT_TO_COM_EQY | U1: NET_DEBT_TO_SHRHLDR_EQTY | V1: TOT_DEBT_TO_TOT_ASSET | W1: RETURN_ON_ASSET | Z1: RETURN_COM_EQY | AD1: Pe Ratio | AL1: BEST_EV_TO_BEST_EBITDA | AO1: Px To Book Ratio | AV1: EQY_DVD_YLD_IND | AW1: BEST_DIV_YLD | DB1: CIE_DES
A3: Company Name | B3: 公司名 | C3: Stock Code | E3: Operating Data | AD3: Valuation | AY3: Forecast CAGR | BB3: Key financials (USD'b) | CY3: Volatility
D4: Listing date | E4: Market Capitalization (HKD 'm) | F4: Market Capitalization (USD 'm) | G4: Price (Traded Currency) | H4: Net Assets (HKD 'm) | I4: Net Assets (USD 'm) | J4: Revenue (HKD 'm) | K4: Revenue (USD 'm) | L4: Net Profit (HKD 'm) | M4: Net Profit (USD 'm) | N4: GP Margin (%) | O4: EBITDA Margin (%) | P4: NP Margin (%) | Q4: Revenue Growth (%) | R4: NP Growth (%) | S4: Debt to equity | T4: Debt to common equity | U4: Net debt To Shareholders Equity | V4: Total Debt to Total Assets | W4: ROA | X4: EV (HKD'm) | Y4: EV (USD'm) | Z4: ROE | AA4: TTM Sales Profit (HKD 'm) | AB4: TTM Net Profit (HKD 'm) | AC4: TTM EBITDA (HKD 'm) | AD4: PE Ratio (x) | AH4: PS Ratio (x) | AL4: EV/EBITDA (x) | AO4: PB Ratio (x) | AS4: ROE (%) | AV4: Dividend Yield (x) | AY4: Revenue | AZ4: EBITDA | BA4: Net profit | BB4: cash flow from operations (USD'b) | BH4: Free cash flow (USD'b) | BN4: Revenue | BT4: EBITDA | BZ4: Net profit | CF4: Dividend | CJ4: Dividend yield | CN4: 5D Avg ADTV (HKD'm) | CO4: 10D Avg ADTV (HKD'm) | CP4: 20D Avg ADTV (HKD'm) | CQ4: 1M Avg ADTV (HKD'm) | CR4: 3M Avg ADTV (HKD'm) | CS4: 6M Avg ADTV (HKD'm) | CT4: 1M Return | CU4: 3M Return | CV4: 6M Return | CW4: 1Y Return | CX4: YTD Return | CY4: 30-day volatility (%) | CZ4: 90-day volatility (%) | DA4: 180-day volatility (%)
AD5: TTM | AE5: 2026F | AF5: 2027F | AG5: 2025A | AH5: TTM | AI5: 2026F | AJ5: 2027F | AL5: TTM | AM5: 2026F | AN5: 2027F | AO5: TTM | AP5: 2026F | AQ5: 2027F | AR5: 2027F | AS5: TTM | AT5: 2026F | AU5: 2027F | AV5: TTM | AW5: 2026F | AX5: 2027F | AY5: 2026 vs 2024 | BB5: CY2022A | BC5: CY2023A | BD5: CY2024A | BE5: CY2025F | BF5: CY2026F | BG5: CY2027F | BH5: CY2022A | BI5: CY2023A | BJ5: CY2024A | BK5: CY2025F | BL5: CY2026F | BM5: CY2027F | BN5: CY2022A | BO5: CY2023A | BP5: CY2024A | BQ5: CY2025F | BR5: CY2026F | BS5: CY2027F | BT5: CY2022A | BU5: CY2023A | BV5: CY2024A | BW5: CY2025F | BX5: CY2026F | BY5: CY2027F | BZ5: CY2022A | CA5: CY2023A | CB5: CY2024A | CC5: CY2025F | CD5: CY2026F | CE5: CY2027F | CF5: CY2024A | CG5: CY2025F | CH5: CY2026F | CI5: CY2027F | CJ5: CY2024A | CK5: CY2025F | CL5: CY2026F | CM5: CY2027F
A7: PDS Ltd | B7: PDS Ltd | C7: pdsl in Equity | D7: 10/21/2014 | E7: 3363.6485 | F7: 429.36539 | G7: 293.8 | H7: 1544.2295 | I7: 196.94544 | J7: 11590.735 | K7: 1484.796 | L7: 98.747584 | M7: 12.64976 | N7: =#VALUE! -> #VALUE! | O7: 0.029377399 | P7: 0.0085195274 | Q7: 0.083469248 | R7: -0.28810317 | S7: 0.6799445 | T7: 0.7167187 | U7: 0.12262357 | V7: 0.24004735 | W7: 0.022891973 | X7: 3632.2403 | Y7: 463.62063 | Z7: 0.065611822 | AA7: 11590.735 | AB7: 98.747584 | AC7: 340.37462 | AD7: 34.063097 | AE7: 34.159526 | AF7: 27.694363 | AG7: 37.379277 | AH7: 0.29020149 | AI7: 0.29706215 | AJ7: 0.27930084 | AL7: 10.671302 | AM7: #N/A | AN7: #N/A | AO7: 2.3563056 | AP7: 2.2737624 | AQ7: 2.1338398 | AR7: 2.2325228 | AS7: 0.065611822 | AT7: 0.0555 | AU7: 0.0699 | AV7: 1.1232131 | AW7: #N/A N/A | AX7: #N/A N/A | AY7: -0.004529693 | AZ7: =#VALUE! -> #VALUE! | BA7: -0.1925306 | BB7: 0.054043298 | BC7: 0.021999611 | BD7: -0.0098155305 | BE7: =#VALUE! -> #VALUE! | BF7: =#VALUE! -> #VALUE! | BG7: =#VALUE! -> #VALUE! | BH7: 0.049792862 | BI7: 0.0062953556 | BJ7: -0.022833284 | BK7: =#VALUE! -> #VALUE! | BL7: =#VALUE! -> #VALUE! | BM7: =#VALUE! -> #VALUE! | BN7: 1.3512945 | BO7: 1.1990861 | BP7: 1.4662796 | BQ7: 1.3931129 | BR7: 1.453026 | BS7: 1.5454269 | BT7: 0.054375123 | BU7: 0.049776924 | BV7: 0.052570466 | BW7: =#VALUE! -> #VALUE! | BX7: =#VALUE! -> #VALUE! | BY7: =#VALUE! -> #VALUE! | BZ7: 0.036362788 | CA7: 0.018778827 | CB7: 0.019408024 | CC7: 0.011725291 | CD7: 0.012654164 | CE7: 0.015608947 | CF7: 0.0074249516 | CG7: =#VALUE! -> #VALUE! | CH7: =#VALUE! -> #VALUE! | CI7: =#VALUE! -> #VALUE! | CJ7: 1.7292851e-05 | CK7: =#VALUE! -> #VALUE! | CL7: =#VALUE! -> #VALUE! | CM7: =#VALUE! -> #VALUE! | CN7: 7.2448675 | CO7: 4.2623237 | CP7: 3.4449756 | CQ7: 3.3175718 | CR7: 10.078578 | CS7: 7.5417473 | CT7: -0.000340231 | CU7: -0.03876982 | CV7: -0.2788414 | CW7: -0.2847231 | CX7: -0.2132816 | CY7: 0.36384718 | CZ7: 0.43541756 | DA7: 0.43323304 | DB7: PDS Limited is a consumer-driven manufacturing and sourcing company. The Company designs, produces, and markets blazers, school wear, shirts, softs, and footwear products, as well as invests in sustainability, technology, and direct to consumer digital brands. PDS serves brand agencies and retailers worldwide.
A8: Walmart Inc | B8: 沃尔玛股份有限公司 | C8: wmt us Equity | D8: #N/A Field Not Applicable | E8: 8380084.2 | F8: 1069706.9 | G8: 134.2 | H8: 829276.42 | I8: 106180 | J8: 5560443 | K8: 713163 | L8: 170696.99 | M8: 21893 | N8: 0.249267 | O8: 0.06575916 | P8: 0.030698452 | Q8: 0.047252142 | R8: 0.1264149 | S8: 0.63189866 | T8: 0.67352962 | U8: 0.5308721 | V8: 0.23569562 | W8: 0.080268969 | X8: 8871581.5 | Y8: 1132637.9 | Z8: 0.22969102 | AA8: 5560443 | AB8: 170696.99 | AC8: 362258.42 | AD8: 49.093332 | AE8: 46.576104 | AF8: 40.85241 | AG8: 45.288336 | AH8: 1.5070893 | AI8: 1.433405 | AJ8: 1.3671795 | AL8: 24.489648 | AM8: 21.698405 | AN8: 19.712839 | AO8: 10.735515 | AP8: 9.7242299 | AQ8: 8.8181213 | AR8: 9.7232285 | AS8: 0.22969102 | AT8: 0.21592 | AU8: 0.21427 | AV8: 0.73770493 | AW8: 0.695231 | AX8: 0.73099851 | AY8: 0.048698146 | AZ8: 0.077160566 | BA8: 0.079747432 | BB8: 27.070967 | BC8: 34.523402 | BD8: 37.51688 | BE8: 39.156214 | BF8: 40.128463 | BG8: 43.735809 | BH8: 10.307641 | BI8: 14.300185 | BJ8: 14.123065 | BK8: 16.499711 | BL8: 14.119226 | BM8: 18.194063 | BN8: 607.52284 | BO8: 644.97783 | BP8: 678.57037 | BQ8: 706.70368 | BR8: 746.26984 | BS8: 782.41879 | BT8: 31.447467 | BU8: 38.191424 | BV8: 42.030543 | BW8: 44.809955 | BX8: 48.766984 | BY8: 53.679012 | BZ8: 10.765837 | CA8: 15.774163 | CB8: 19.51687 | CC8: 20.761634 | CD8: 22.753831 | CE8: 25.800935 | CF8: 6.6374565 | CG8: 7.398584 | CH8: 7.6709596 | CI8: 8.139111 | CJ8: 6.2049299e-06 | CK8: 6.9164589e-06 | CL8: 7.1710853e-06 | CM8: 7.6087299e-06 | CN8: 19123.993 | CO8: 17589.413 | CP8: 16368.912 | CQ8: 16610.733 | CR8: 18447.682 | CS8: 23745.789 | CT8: 0.0490932 | CU8: 0.09114564 | CV8: 0.2529176 | CW8: 0.3721881 | CX8: 0.2045597 | CY8: 0.2058647 | CZ8: 0.22858561 | DA8: 0.2382971 | DB8: Walmart Inc. operates discount stores, supercenters, and neighborhood markets. The Company offers merchandise such as apparel, house wares, small appliances, electronics, musical instruments, books, home improvement, shoes, jewelry, toddler, games, household essentials, pets, pharmaceutical products, party supplies, and automotive tools. Walmart serves customers worldwide.
A9: American Eagle Outfitters Inc | B9: 美鹰傲飞AEO有限公司 | C9: aeo us Equity | D9: #N/A Field Not Applicable | E9: 20157.569 | F9: 2573.0877 | G9: 15.36 | H9: 13210.269 | I9: 1691.434 | J9: 43251.108 | K9: 5547.236 | L9: 1496.8675 | M9: 191.983 | N9: 0.36510453 | O9: 0.17345972 | P9: 0.034608767 | Q9: 0.041020506 | R9: -0.41713826 | S9: 1.0052553 | T9: 1.0042347 | U9: 0.86400061 | V9: 0.42405454 | W9: 0.048972413 | X9: 31557.824 | Y9: 4032.7687 | Z9: 0.11097242 | AA9: 43251.108 | AB9: 1496.8675 | AC9: 6710.1391 | AD9: 13.466502 | AE9: 8.8269914 | AF9: 7.7833708 | AG9: 15.937874 | AH9: 0.46605903 | AI9: 0.44585488 | AJ9: 0.43027257 | AL9: 4.7030059 | AM9: 8.3320805 | AN9: 7.6098393 | AO9: 1.5327586 | AP9: 1.2597358 | AQ9: 1.1445369 | AR9: 1.2687923 | AS9: 0.11097242 | AT9: 0.13893 | AU9: 0.17072 | AV9: 3.2552083 | AW9: 3.2747396 | AX9: 3.2356771 | AY9: 0.038917207 | AZ9: 0.02443777 | BA9: 0.015840872 | BB9: 0.30877057 | BC9: 0.62958049 | BD9: 0.44467309 | BE9: 0.88413334 | BF9: 0.60041393 | BG9: 0.60689928 | BH9: 0.038662615 | BI9: 0.45008166 | BJ9: 0.23123481 | BK9: 0.49798702 | BL9: 0.35781943 | BM9: 0.32122047 | BN9: 5.0100486 | BO9: 5.1396258 | BP9: 5.3468644 | BQ9: 5.3619101 | BR9: 5.7711326 | BS9: 5.980134 | BT9: 0.4586707 | BU9: 0.47541237 | BV9: 0.6021329 | BW9: 0.458687 | BX9: 0.63192207 | BY9: 0.69189707 | BZ9: 0.12441023 | CA9: 0.18464497 | CB9: 0.29487917 | CC9: 0.20500813 | CD9: 0.30429545 | CE9: 0.35161115 | CF9: 0.09664705 | CG9: 0.090614801 | CH9: 0.088729529 | CI9: 0.093559922 | CJ9: 3.7560729e-05 | CK9: 3.5216367e-05 | CL9: 3.4483679e-05 | CM9: 3.6360953e-05 | CN9: 554.67983 | CO9: 543.59402 | CP9: 540.68725 | CQ9: 563.99768 | CR9: 780.81676 | CS9: 1081.9367 | CT9: -0.2273642 | CU9: -0.391924 | CV9: -0.1242874 | CW9: 0.3391456 | CX9: -0.4175199 | CY9: 0.37298253 | CZ9: 0.53793434 | DA9: 0.5440254 | DB9: American Eagle Outfitters, Inc. retails men's and women's casual apparel, footwear, outerwear, and accessories. The Company provides products include jeans, khakis, t-shirts, and other similar apparel. American Eagle serves customers in the United States.
A10: Costco Wholesale Corp | B10: 开市客公司 | C10: cost us Equity | D10: 12/5/1985 | E10: 3803390.2 | F10: 485497.85 | G10: 1094.32 | H10: 227315.88 | I10: 29164 | J10: 2145593.8 | K10: 275235 | L10: 63135.736 | M10: 8099 | N10: 0.12843207 | O10: 0.047097934 | P10: 0.029425763 | Q10: 0.081673236 | R10: 0.09936202 | S10: 0.29262104 | T10: 0.29262104 | U10: -0.23144973 | V10: 0.11068885 | W10: 0.10899957 | X10: 3724627.8 | Y10: 475422.85 | Z10: 0.29651082 | AA10: 2232256.2 | AB10: 66663.958 | AC10: 104959.28 | AD10: 57.053171 | AE10: 51.687613 | AF10: 46.888178 | AG10: 53.670448 | AH10: 1.7038323 | AI10: 1.5700454 | AJ10: 1.4522641 | AL10: 35.486408 | AM10: 27.964893 | AN10: 25.553506 | AO10: 15.132016 | AP10: 12.562627 | AQ10: 10.905653 | AR10: 11.56212 | AS10: 0.29651082 | AT10: 0.28724 | AU10: 0.26459 | AV10: 0.53711385 | AW10: 0.49382265 | AX10: 0.5353096 | AY10: 0.085310885 | AZ10: 0.10881618 | BA10: 0.11049497 | BB10: 8.1110476 | BC10: 11.855583 | BD10: 10.853845 | BE10: 12.776401 | BF10: 14.729238 | BG10: 15.302553 | BH10: 4.1279286 | BI10: 7.5544048 | BJ10: 5.8486071 | BK10: 6.8187958 | BL10: 7.5226847 | BM10: 8.8964661 | BN10: 233.28688 | BO10: 243.02776 | BP10: 262.52263 | BQ10: 282.94784 | BR10: 309.22533 | BS10: 334.30408 | BT10: 9.8537738 | BU10: 10.393083 | BV10: 11.970952 | BW10: 13.17599 | BX10: 14.717967 | BY10: 16.106845 | BZ10: 5.9809762 | CA10: 6.5277024 | CB10: 7.6373214 | CC10: 8.3099475 | CD10: 9.4183377 | CE10: 10.381945 | CF10: 5.68975 | CG10: 2.3518354 | CH10: 4.3629676 | CI10: 3.0642975 | CJ10: 1.1719413e-05 | CK10: 4.8441727e-06 | CL10: 8.9865848e-06 | CM10: 6.3116603e-06 | CN10: 18203.075 | CO10: 16602.223 | CP10: 15043.904 | CQ10: 14440.37 | CR10: 14496.744 | CS10: 16842.298 | CT10: 0.09668882 | CU10: 0.1106803 | CV10: 0.2250445 | CW10: 0.05545809 | CX10: 0.2690122 | CY10: 0.18496035 | CZ10: 0.18377653 | DA10: 0.1952656 | DB10: Costco Wholesale Corporation is a membership warehouse club The Company sells all kinds of food, automotive supplies, toys, hardware, sporting goods, jewelry, electronics, apparel, health, and beauty aids, as well as other goods. Costco Wholesale serves customers worldwide.
A11: Associated British Foods PLC | B11: 英国联合食品公共有限公司 | C11: abf ln EQUITY | D11: #N/A Field Not Applicable | E11: 135311.2 | F11: 17272.3 | G11: 1833 | H11: 118036.02 | I11: 15168.216 | J11: 198050.84 | K11: 25404.338 | L11: 10432.299 | M11: 1338.1698 | N11: 0.23922093 | O11: 0.13253507 | P11: 0.052674855 | Q11: -0.027195921 | R11: -0.29553265 | S11: 0.32951904 | T11: 0.33330319 | U11: 0.23502593 | V11: 0.19107356 | W11: 0.049596701 | X11: 168838.28 | Y11: 21558.665 | Z11: 0.084613672 | AA11: 202525.2 | AB11: 9907.2577 | AC11: 24622.143 | AD11: 13.657785 | AE11: 11.27466 | AF11: 10.646149 | AG11: 10.9633 | AH11: 0.66812028 | AI11: 0.68200855 | AJ11: 0.644861 | AL11: 6.8571725 | AM11: 7.290167 | AN11: 6.9691059 | AO11: 1.1298633 | AP11: 1.1192199 | AQ11: 1.0494899 | AR11: 1.0751994 | AS11: 0.084613672 | AT11: 0.09814 | AU11: 0.10043 | AV11: 3.4369885 | AW11: 3.2460447 | AX11: 3.3715221 | AY11: 0.0023239674 | AZ11: 0.0087649321 | BA11: -0.10748368 | BB11: 1.1691067 | BC11: 2.9357923 | BD11: 3.3824466 | BE11: 2.3953424 | BF11: 1.9686017 | BG11: 2.0516051 | BH11: 0.21227288 | BI11: 1.621035 | BJ11: 1.9691316 | BK11: 0.91571912 | BL11: 0.94270928 | BM11: 0.92799304 | BN11: 21.937978 | BO11: 24.950845 | BP11: 25.454993 | BQ11: 26.137291 | BR11: 25.573444 | BS11: 27.046615 | BT11: 2.3553044 | BU11: 2.9400949 | BV11: 3.3878779 | BW11: 3.5387547 | BX11: 3.4475273 | BY11: 3.6063521 | BZ11: 0.890859 | CA11: 1.4193107 | CB11: 1.7471448 | CC11: 1.5377899 | CD11: 1.39175 | CE11: 1.4961078 | CF11: 0.77610423 | CG11: 0.49583445 | CH11: 0.55177703 | CI11: 0.47900223 | CJ11: 4.4933463e-05 | CK11: 2.8706916e-05 | CL11: 3.1945777e-05 | CM11: 2.7732395e-05 | CN11: 129.2982 | CO11: 135.86173 | CP11: 149.59612 | CQ11: 163.17554 | CR11: 160.5872 | CS11: 154.51915 | CT11: -0.02758621 | CU11: -0.06168416 | CV11: -0.126727 | CW11: -0.1390324 | CX11: -0.1382228 | CY11: 0.21825153 | CZ11: 0.21275675 | DA11: 0.2706094 | DB11: Associated British Foods PLC operates as a group company. The Company, through its subsidiaries, offers groceries, clothing, and household products, as well as produces sugar and baker's yeast ingredients including emulsifiers, enzymes, and lactose. Associated British Foods serves customers worldwide.
A12: Manhattan Associates Inc | B12: 曼哈顿联合软件公司 | C12: MANH US EQUITY | D12: 4/23/1998 | E12: 62764.157 | F12: 8012.0704 | G12: 135.42 | H12: 2450.0993 | I12: 314.765 | J12: 8430.351 | K12: 1081.392 | L12: 1714.6778 | M12: 219.948 | N12: 0.56321205 | O12: 0.26997703 | P12: 0.2033934 | Q12: 0.037453758 | R12: 0.007253943 | S12: 0.19399552 | T12: 0.19399552 | U12: -0.85042492 | V12: 0.072747049 | W12: 0.29909875 | X12: 61427.69 | Y12: 7841.6224 | Z12: 0.96236036 | AA12: 8590.7453 | AB12: 1690.8118 | AC12: 2248.8958 | AD12: 37.120723 | AE12: 25.272783 | AF12: 22.705603 | AG12: 27.83992 | AH12: 7.30602 | AI12: 6.9463799 | AJ12: 6.3989913 | AL12: 27.314601 | AM12: 22.767815 | AN12: 20.555926 | AO12: 39.049862 | AP12: 28.509473 | AQ12: 12.603071 | AR12: 26.244186 | AS12: 0.96236036 | AT12: 1.05773 | AU12: 1.47583 | AV12: #N/A N/A | AW12: 0 | AX12: 0 | AY12: 0.051927743 | AZ12: 0.21950629 | BA12: 0.0073823964 | BB12: 0.17963 | BC12: 0.246218 | BD12: 0.295003 | BE12: 0.33073013 | BF12: 0.38220333 | BG12: 0.41356057 | BH12: 0.173043 | BI12: 0.241488 | BJ12: 0.286328 | BK12: 0.3199796 | BL12: 0.37471904 | BM12: 0.41477038 | BN12: 0.767084 | BO12: 0.928725 | BP12: 1.042352 | BQ12: 1.0758333 | BR12: 1.1534167 | BS12: 1.2520833 | BT12: 0.166663 | BU12: 0.223433 | BV12: 0.276897 | BW12: 0.391 | BX12: 0.4118 | BY12: 0.45611111 | BZ12: 0.128959 | CA12: 0.176568 | CB12: 0.218364 | CC12: 0.2144 | CD12: 0.2216 | CE12: 0.2537 | CF12: 0 | CG12: =#VALUE! -> #VALUE! | CH12: =#VALUE! -> #VALUE! | CI12: =#VALUE! -> #VALUE! | CJ12: 0 | CK12: =#VALUE! -> #VALUE! | CL12: =#VALUE! -> #VALUE! | CM12: =#VALUE! -> #VALUE! | CN12: 570.01422 | CO12: 599.99188 | CP12: 758.0417 | CQ12: 801.78106 | CR12: 751.70417 | CS12: 834.43368 | CT12: 0.01188073 | CU12: -0.06134334 | CV12: -0.1971305 | CW12: -0.2941361 | CX12: -0.2186256 | CY12: 0.51654275 | CZ12: 0.49307174 | DA12: 0.43677486 | DB12: Manhattan Associates, Inc. provides information technology solutions for distribution centers. The solutions are designed to enable the efficient movement of goods through the supply chain. The Company offers solutions optimize the receipt, storage, and distribution of inventory, as well as manage equipment and personnel within a distribution center.
A13: CH Robinson Worldwide Inc | B13: 罗宾逊全球物流有限公司 | C13: CHRW US EQUITY | D13: 10/15/1997 | E13: 159732.89 | F13: 20390.478 | G13: 173.02 | H13: 14366.332 | I13: 1845.647 | J13: 126547.9 | K13: 16232.763 | L13: 4576.7852 | M13: 587.081 | N13: 0.083735098 | O13: 0.063262366 | P13: 0.036166425 | Q13: -0.084185992 | R13: 0.26066911 | S13: 0.75604165 | T13: 0.75604165 | U13: 0.66887926 | V13: 0.27585625 | W13: 0.11451706 | X13: 171375.22 | Y13: 21875.299 | Z13: 0.34837966 | AA13: 126415.87 | AB13: 4674.6603 | AC13: 7712.5745 | AD13: 34.169947 | AE13: 28.120531 | AF13: 23.718266 | AG13: 35.431551 | AH13: 1.263551 | AI13: 1.2081685 | AJ13: 1.1362245 | AL13: 22.220236 | AM13: 21.826218 | AN13: 18.813097 | AO13: 11.996522 | AP13: 11.525447 | AQ13: 10.786783 | AR13: 11.037959 | AS13: 0.34837966 | AT13: 0.39701 | AU13: 0.4616 | AV13: 1.4563948 | AW13: 1.4524332 | AX13: 1.4784418 | AY13: -0.024207711 | AZ13: 0.097445037 | BA13: 0.253025 | BB13: 1.650171 | BC13: 0.731946 | BD13: 0.509084 | BE13: 0.83654123 | BF13: 0.81848958 | BG13: 0.97863258 | BH13: 1.588256 | BI13: 0.701957 | BJ13: 0.486431 | BK13: 0.74980139 | BL13: 0.74545011 | BM13: 0.88281303 | BN13: 24.696625 | BO13: 17.596443 | BP13: 17.724956 | BQ13: 16.298708 | BR13: 16.877182 | BS13: 17.945818 | BT13: 1.45159 | BU13: 0.714227 | BV13: 0.875135 | BW13: 0.91273913 | BX13: 1.054 | BY13: 1.2228095 | BZ13: 0.940524 | CA13: 0.325129 | CB13: 0.46569 | CC13: 0.5959 | CD13: 0.73116667 | CE13: 0.88388889 | CF13: 0.294772 | CG13: 0.30527602 | CH13: 0.30768054 | CI13: 0.32098167 | CJ13: 1.4456355e-05 | CK13: 1.4971498e-05 | CL13: 1.5089422e-05 | CM13: 1.5741743e-05 | CN13: 3712.5822 | CO13: 2629.6555 | CP13: 2914.868 | CQ13: 2854.8895 | CR13: 2562.9612 | CS13: 2752.925 | CT13: -0.0594183 | CU13: -0.08965589 | CV13: 0.1645688 | CW13: 0.7289897 | CX13: 0.07626279 | CY13: 0.44536685 | CZ13: 0.42336611 | DA13: 0.41262464 | DB13: C.H. Robinson Worldwide, Inc. operates as a logistics company. The Company freight, supply chain, and logistics services. C.H. Robinson Worldwide serves clients worldwide.
A14: CVS Health Corp | B14: CVS健康公司 | C14: cvs us EQUITY | D14: 10/1/1952 | E14: 941386.99 | F14: 120166.83 | G14: 94.18 | H14: 586765.95 | I14: 75382 | J14: 3134447 | K14: 402067 | L14: 13783.032 | M14: 1768 | N14: 0.13769347 | O14: 0.048268075 | P14: 0.0043972771 | Q14: 0.078479865 | R14: -0.61681838 | S14: 1.060598 | T14: 1.062967 | U14: 0.92000743 | V14: 0.31533735 | W14: 0.011530619 | X14: 1464563.2 | Y14: 186890.83 | Z14: 0.037982965 | AA14: 3183270.6 | AB14: 22881.184 | AC14: 82199.015 | AD14: 41.142407 | AE14: 12.755116 | AF14: 11.256229 | AG14: 13.818396 | AH14: 0.29572949 | AI14: 0.2950372 | AJ14: 0.28275297 | AL14: 17.817284 | AM14: 9.0639446 | AN14: 8.7266069 | AO14: 1.5478612 | AP14: 1.5070609 | AQ14: 1.4279433 | AR14: 1.3983875 | AS14: 0.037982965 | AT14: 0.1066 | AU14: 0.11405 | AV14: 2.8243789 | AW14: 2.8073901 | AX14: 2.9868337 | AY14: 0.045227266 | AZ14: 0.087519531 | BA14: 0.30704781 | BB14: 16.177 | BC14: 13.426 | BD14: 9.107 | BE14: 6.8931973 | BF14: 9.5035319 | BG14: 12.567884 | BH14: 13.45 | BI14: 10.395 | BJ14: 6.326 | BK14: 5.5684131 | BL14: 7.2600573 | BM14: 10.751112 | BN14: 322.467 | BO14: 357.776 | BP14: 372.809 | BQ14: 400.12448 | BR14: 407.29385 | BS14: 424.98876 | BT14: 14.696 | BU14: 20.578 | BV14: 15.469 | BW14: 17.375389 | BX14: 18.295167 | BY14: 19.002389 | BZ14: 4.311 | CA14: 8.344 | CB14: 4.614 | CC14: -0.34181818 | CD14: 7.8824375 | CE14: 9.1240625 | CF14: 3.373 | CG14: 3.348705 | CH14: 3.4198385 | CI14: 3.5900269 | CJ14: 2.8069309e-05 | CK14: 2.7867132e-05 | CL14: 2.8459088e-05 | CM14: 2.9875356e-05 | CN14: 7181.2996 | CO14: 7847.3575 | CP14: 6391.7576 | CQ14: 6069.4642 | CR14: 5187.3017 | CS14: 5116.5103 | CT14: 0.229825 | CU14: 0.228061 | CV14: 0.2385586 | CW14: 0.4775651 | CX14: 0.1867439 | CY14: 0.40133415 | CZ14: 0.35036859 | DA14: 0.36396735 | DB14: CVS Health Corporation provides health care and retail pharmacy services. The Company offers prescription medications, beauty, personal care, cosmetics, and health care products, as well as pharmacy benefit management (PBM), disease management, and administrative services. CVS Health operates in the United States and Puerto Rico.
A15: H & M Hennes & Mauritz AB | B15: 海恩斯莫里斯公司 | C15: hmb ss EQUITY | D15: #N/A Field Not Applicable | E15: 217702.58 | F15: 27789.454 | G15: 163 | H15: 35412.183 | I15: 4548.3622 | J15: 179395.13 | K15: 23011.543 | L15: 9554.224 | M15: 1225.5485 | N15: 0.53395098 | O15: 0.17376963 | P15: 0.053257989 | Q15: -0.02641186 | R15: 0.046209448 | S15: 1.8056442 | T15: 1.806738 | U15: 1.3188116 | V15: 0.45542746 | W15: =#VALUE! -> #VALUE! | X15: 268039.39 | Y15: 34224.905 | Z15: =#VALUE! -> #VALUE! | AA15: 182918.59 | AB15: 10102.648 | AC15: 31672.279 | AD15: 21.549061 | AE15: 19.094264 | AF15: 18.103523 | AG15: 23.236558 | AH15: 1.1901611 | AI15: 1.1749797 | AJ15: 1.1540057 | AL15: 8.4629021 | AM15: 8.3000656 | AN15: 8.0155369 | AO15: 6.2869523 | AP15: 5.932914 | AQ15: 5.6001816 | AR15: 5.5768441 | AS15: =#VALUE! -> #VALUE! | AT15: 0.30293 | AU15: 0.32374 | AV15: 4.3585021 | AW15: 4.502454 | AX15: 4.7865031 | AY15: 0.036145043 | AZ15: 0.093730152 | BA15: 0.15880726 | BB15: 2.4241186 | BC15: 3.1688053 | BD15: 2.9881701 | BE15: 4.686497 | BF15: 3.9173809 | BG15: 3.9331037 | BH15: 1.9597794 | BI15: 2.4125135 | BJ15: 2.0299634 | BK15: 3.9477056 | BL15: 2.8950644 | BM15: 2.8533001 | BN15: 21.915431 | BO15: 22.21339 | BP15: 22.070462 | BQ15: 24.319544 | BR15: 23.694772 | BS15: 24.125423 | BT15: 2.8700988 | BU15: 3.5157686 | BV15: 3.633467 | BW15: 4.173431 | BX15: 4.346519 | BY15: 4.500808 | BZ15: 0.35738188 | CA15: 0.84739888 | CB15: 1.0725106 | CC15: 1.19362 | CD15: 1.440204 | CE15: 1.5787607 | CF15: 0.98093319 | CG15: 1.5864488 | CH15: 1.3871056 | CI15: 1.3481862 | CJ15: 3.5298758e-05 | CK15: 5.7088161e-05 | CL15: 4.9914822e-05 | CM15: 4.8514311e-05 | CN15: 309.90782 | CO15: 351.31867 | CP15: 295.32087 | CQ15: 291.76019 | CR15: 304.36469 | CS15: 315.80159 | CT15: -0.08323961 | CU15: -0.1090462 | CV15: -0.04900813 | CW15: 0.1470795 | CX15: -0.1231845 | CY15: 0.30626581 | CZ15: 0.28051779 | DA15: 0.24983431 | DB15: H & M Hennes & Mauritz AB designs and retails fashions for women, men, teens, and children. The Company sells a variety trendy, sporty, and classic garments in addition to accessories such as jewelery, bags, scarves, and cosmetics. H & M Hennes & Mauritz serves customers worldwide.
B17: HK | C17: 13.732419 | E17: 13.424774 | L17: Max | M17: Max | N17: =#VALUE! -> #VALUE! | O17: 0.17345972 | P17: 0.052674855 | Q17: 0.083469248 | R17: =#REF! -> #REF! | S17: =#REF! -> #REF! | T17: =#REF! -> #REF! | U17: =#REF! -> #REF! | V17: =#REF! -> #REF! | W17: =#REF! -> #REF! | X17: =#REF! -> #REF! | Y17: =#REF! -> #REF! | Z17: =#REF! -> #REF! | AD17: 57.053171 | AE17: 46.576104 | AF17: 40.85241 | AH17: 1.5070893 | AI17: 1.433405 | AJ17: 1.3671795 | AL17: 24.489648 | AM17: 21.698405 | AN17: 19.712839 | AO17: 10.735515 | AP17: 9.7242299 | AQ17: 8.8181213 | AR17: 9.7232285 | AS17: 0.22969102 | AT17: 0.21592 | AU17: 0.21427 | AV17: 3.2552083 | AW17: 3.2747396 | AX17: 3.2356771 | CN17: 19123.993 | CO17: 17589.413 | CP17: 16368.912 | CQ17: 16610.733 | CR17: 18447.682 | CS17: 23745.789 | CT17: 0.0490932 | CU17: 0.09114564 | CV17: 0.2529176 | CW17: 0.3721881 | CX17: 0.2045597 | CY17: 0.37298253 | CZ17: 0.53793434 | DA17: 0.5440254
B18: NY | C18: 20.580119 | E18: 20.316364 | L18: Median | M18: Median | N18: =#VALUE! -> #VALUE! | O18: 0.06575916 | P18: 0.030698452 | Q18: 0.047252142 | R18: =#REF! -> #REF! | S18: =#REF! -> #REF! | T18: =#REF! -> #REF! | U18: =#REF! -> #REF! | V18: =#REF! -> #REF! | W18: =#REF! -> #REF! | X18: =#REF! -> #REF! | Y18: =#REF! -> #REF! | Z18: =#REF! -> #REF! | AD18: 34.063097 | AE18: 34.159526 | AF18: 27.694363 | AH18: 0.46605903 | AI18: 0.44585488 | AJ18: 0.43027257 | AL18: 10.671302 | AM18: 15.015243 | AN18: 13.661339 | AO18: 2.3563056 | AP18: 2.2737624 | AQ18: 2.1338398 | AR18: 2.2325228 | AS18: 0.11097242 | AT18: 0.13893 | AU18: 0.17072 | AV18: 1.1232131 | AW18: 1.9849853 | AX18: 1.9833378 | CN18: 554.67983 | CO18: 543.59402 | CP18: 540.68725 | CQ18: 563.99768 | CR18: 780.81676 | CS18: 1081.9367 | CT18: -0.000340231 | CU18: -0.03876982 | CV18: -0.1242874 | CW18: 0.3391456 | CX18: -0.2132816 | CY18: 0.36384718 | CZ18: 0.43541756 | DA18: 0.43323304
B19: LN | C19: 16.720078 | E19: 16.688296 | L19: Mean | M19: Mean | N19: =#VALUE! -> #VALUE! | O19: 0.089645857 | P19: 0.031185473 | Q19: 0.045243842 | R19: =#REF! -> #REF! | S19: =#REF! -> #REF! | T19: =#REF! -> #REF! | U19: =#REF! -> #REF! | V19: =#REF! -> #REF! | W19: =#REF! -> #REF! | X19: =#REF! -> #REF! | Y19: =#REF! -> #REF! | Z19: =#REF! -> #REF! | AD19: 32.207644 | AE19: 29.854207 | AF19: 25.443381 | AH19: 0.75444994 | AI19: 0.72544067 | AJ19: 0.69225096 | AL19: 13.287985 | AM19: 15.015243 | AN19: 13.661339 | AO19: 4.8748597 | AP19: 4.4192427 | AQ19: 4.032166 | AR19: 4.4081812 | AS19: 0.13542509 | AT19: 0.13678333 | AU19: 0.15163 | AV19: 1.7053754 | AW19: 1.9849853 | AX19: 1.9833378 | CN19: 6561.9725 | CO19: 6045.7565 | CP19: 5637.6814 | CQ19: 5726.0162 | CR19: 6412.859 | CS19: 8278.4224 | CT19: -0.059537077 | CU19: -0.11318273 | CV19: -0.0500704 | CW19: 0.14220353 | CX19: -0.1420806 | CY19: 0.31423147 | CZ19: 0.40064584 | DA19: 0.40518518
B20: INDIA | C20: 21.956182 | E20: 21.825203 | L20: Min | M20: Min | N20: =#VALUE! -> #VALUE! | O20: 0.029377399 | P20: 0.0085195274 | Q20: -0.027195921 | R20: =#REF! -> #REF! | S20: =#REF! -> #REF! | T20: =#REF! -> #REF! | U20: =#REF! -> #REF! | V20: =#REF! -> #REF! | W20: =#REF! -> #REF! | X20: =#REF! -> #REF! | Y20: =#REF! -> #REF! | Z20: =#REF! -> #REF! | AD20: 13.466502 | AE20: 8.8269914 | AF20: 7.7833708 | AH20: 0.29020149 | AI20: 0.29706215 | AJ20: 0.27930084 | AL20: 4.7030059 | AM20: 8.3320805 | AN20: 7.6098393 | AO20: 1.5327586 | AP20: 1.2597358 | AQ20: 1.1445369 | AR20: 1.2687923 | AS20: 0.065611822 | AT20: 0.0555 | AU20: 0.0699 | AV20: 0.73770493 | AW20: 0.695231 | AX20: 0.73099851 | CN20: 7.2448675 | CO20: 4.2623237 | CP20: 3.4449756 | CQ20: 3.3175718 | CR20: 10.078578 | CS20: 7.5417473 | CT20: -0.2273642 | CU20: -0.391924 | CV20: -0.2788414 | CW20: -0.2847231 | CX20: -0.4175199 | CY20: 0.2058647 | CZ20: 0.22858561 | DA20: 0.2382971
B21: STOCKHOLM | C21: 14.84786 | E21: 14.913889
B22: NASDAQ | C22: 40.245419 | E22: 39.209416
B24: HK | C24: 4.5696845 | E24: {=_xll.BQL("members('HSI Index')", "avg(group(px_to_sales_ratio().value))")} -> #NAME?
B25: NY | E25: {=_xll.BQL("members('NYA Index')", "avg(group(px_to_sales_ratio().value))")} -> #NAME?
B26: LN | C26: 2.786486 | E26: {=_xll.BQL("members('UKX Index')", "avg(group(px_to_sales_ratio().value))")} -> #NAME?
B27: INDIA | C27: 4.8486973 | E27: {=_xll.BQL("members('NIFTY Index')", "avg(group(px_to_sales_ratio().value))")} -> #NAME?
B28: STOCKHOLM | C28: 3.5492543 | E28: {=_xll.BQL("members('OMX Index')", "avg(group(px_to_sales_ratio().value))")} -> #NAME?
B29: NASDAQ | C29: 11.666455 | E29: {=_xll.BQL("members('NDX Index')", "avg(group(px_to_sales_ratio().value))")} -> #NAME?
B31: HK | C31: 12.620141 | E31: {=_xll.BQL("members('HSI Index')", "avg(group(EV_TO_EBITDAR().value))")} -> #NAME?
B32: NY | C32: \ | E32: \
B33: LN | C33: 3.53426 | E33: {=_xll.BQL("members('UKX Index')", "avg(group(EV_TO_EBITDAR().value))")} -> #NAME?
B34: INDIA | C34: 12.620141 | E34: {=_xll.BQL("members('HSI Index')", "avg(group(EV_TO_EBITDAR().value))")} -> #NAME?
B35: STOCKHOLM | C35: \ | E35: \
B36: NASDAQ | C36: 66.624715 | E36: {=_xll.BQL("members('NDX Index')", "avg(group(EV_TO_EBITDAR().value))")} -> #NAME?
