Workbook

Sheet Sheet1
A1: Currency | B1: HKD | C1: USD | E1: CRNCY_ADJ_MKT_CAP | F1: Crncy Adj Mkt Cap | G1: Px Last | H1: Net Assets | I1: Net Assets | J1: Sales Rev Turn | K1: Sales Rev Turn | L1: Net Income | M1: Net Income | N1: Gross_Margin_Adjusted | O1: EBITDA_MARGIN_ADJUSTED | P1: Prof Margin | Q1: Sales_Growth | R1: Net Inc Growth | S1: TOT_DEBT_TO_TOT_EQY | T1: TOT_DEBT_TO_COM_EQY | U1: NET_DEBT_TO_SHRHLDR_EQTY | V1: TOT_DEBT_TO_TOT_ASSET | W1: RETURN_ON_ASSET | Z1: RETURN_COM_EQY | AD1: Pe Ratio | AJ1: BEST_EV_TO_BEST_EBITDA | AM1: Px To Book Ratio | AT1: EQY_DVD_YLD_IND | AU1: BEST_DIV_YLD | CZ1: CIE_DES
A3: Company Name | B3: 公司名 | C3: Stock Code | E3: Operating Data | AD3: Valuation | AW3: Forecast CAGR | AZ3: Key financials (USD'b) | CW3: Volatility
D4: Listing date | E4: Market Capitalization (HKD 'm) | F4: Market Capitalization (USD 'm) | G4: Price (Traded Currency) | H4: Net Assets (HKD 'm) | I4: Net Assets (USD 'm) | J4: Revenue (HKD 'm) | K4: Revenue (USD 'm) | L4: Net Profit (HKD 'm) | M4: Net Profit (USD 'm) | N4: GP Margin (%) | O4: EBITDA Margin (%) | P4: NP Margin (%) | Q4: Revenue Growth (%) | R4: NP Growth (%) | S4: Debt to equity | T4: Debt to common equity | U4: Net debt To Shareholders Equity | V4: Total Debt to Total Assets | W4: ROA | X4: EV (HKD'm) | Y4: EV (USD'm) | Z4: ROE | AA4: TTM Sales Profit (HKD 'm) | AB4: TTM Net Profit (HKD 'm) | AC4: TTM EBITDA (HKD 'm) | AD4: PE Ratio (x) | AG4: PS Ratio (x) | AJ4: EV/EBITDA (x) | AM4: PB Ratio (x) | AQ4: ROE (%) | AT4: Dividend Yield (x) | AW4: Revenue | AX4: EBITDA | AY4: Net profit | AZ4: cash flow from operations (USD'b) | BF4: Free cash flow (USD'b) | BL4: Revenue | BR4: EBITDA | BX4: Net profit | CD4: Dividend | CH4: Dividend yield | CL4: 5D Avg ADTV (HKD'm) | CM4: 10D Avg ADTV (HKD'm) | CN4: 20D Avg ADTV (HKD'm) | CO4: 1M Avg ADTV (HKD'm) | CP4: 3M Avg ADTV (HKD'm) | CQ4: 6M Avg ADTV (HKD'm) | CR4: 1M Return | CS4: 3M Return | CT4: 6M Return | CU4: 1Y Return | CV4: YTD Return | CW4: 30-day volatility (%) | CX4: 90-day volatility (%) | CY4: 180-day volatility (%)
AD5: TTM | AE5: 2026F | AF5: 2027F | AG5: TTM | AH5: 2026F | AI5: 2027F | AJ5: TTM | AK5: 2026F | AL5: 2027F | AM5: TTM | AN5: 2026F | AO5: 2027F | AP5: 2027F | AQ5: TTM | AR5: 2026F | AS5: 2027F | AT5: TTM | AU5: 2026F | AV5: 2027F | AW5: 2026 vs 2024 | AZ5: CY2022A | BA5: CY2023A | BB5: CY2024A | BC5: CY2025F | BD5: CY2026F | BE5: CY2027F | BF5: CY2022A | BG5: CY2023A | BH5: CY2024A | BI5: CY2025F | BJ5: CY2026F | BK5: CY2027F | BL5: CY2022A | BM5: CY2023A | BN5: CY2024A | BO5: CY2025F | BP5: CY2026F | BQ5: CY2027F | BR5: CY2022A | BS5: CY2023A | BT5: CY2024A | BU5: CY2025F | BV5: CY2026F | BW5: CY2027F | BX5: CY2022A | BY5: CY2023A | BZ5: CY2024A | CA5: CY2025F | CB5: CY2026F | CC5: CY2027F | CD5: CY2024A | CE5: CY2025F | CF5: CY2026F | CG5: CY2027F | CH5: CY2024A | CI5: CY2025F | CJ5: CY2026F | CK5: CY2027F
A7: =_xll.BDP($C7,"security name") -> PDS Ltd | B7: =_xll.BDP($C7,"NAME_CHINESE_SIMPLIFIED") -> PDS Ltd | C7: pdsl in Equity | D7: =_xll.BDP($C7,"LISTING_DATE") -> 10/21/2014 | E7: =_xll.BDP($C7,E$1,"EQY_FUND_CRNCY="&$B$1) -> 3363.6485 | F7: =_xll.BDP($C7,F$1,"EQY_FUND_CRNCY="&$C$1) -> 429.36539 | G7: =_xll.BDP($C7,G$1) -> 293.8 | H7: =_xll.BDP($C7,H$1,"EQY_FUND_CRNCY="&$B$1) -> 1544.2295 | I7: =_xll.BDP($C7,I$1,"EQY_FUND_CRNCY="&$C$1) -> 196.94544 | J7: =_xll.BDP($C7,J$1,"EQY_FUND_CRNCY="&$B$1) -> 11590.735 | K7: =_xll.BDP($C7,K$1,"EQY_FUND_CRNCY="&$C$1) -> 1484.796 | L7: =_xll.BDP($C7,L$1,"EQY_FUND_CRNCY="&$B$1) -> 98.747584 | M7: =_xll.BDP($C7,M$1,"EQY_FUND_CRNCY="&$C$1) -> 12.64976 | N7: =_xll.BDP($C7,N$1)/100 -> #VALUE! | O7: =_xll.BDP($C7,O$1)/100 -> 0.029377399 | P7: =_xll.BDP($C7,P$1)/100 -> 0.0085195274 | Q7: =_xll.BDP($C7,Q$1)/100 -> 0.083469248 | R7: =_xll.BDP($C7,R$1)/100 -> -0.28810317 | S7: =_xll.BDP($C7,S$1)/100 -> 0.6799445 | T7: =_xll.BDP($C7,T$1)/100 -> 0.7167187 | U7: =_xll.BDP($C7,U$1)/100 -> 0.12262357 | ... W7: =_xll.BDP($C7,W$1)/100 -> 0.022891973 | X7: {=_xll.BDP($C7,"CRNCY_ADJ_CURR_EV", "EQY_FUND_CRNCY=HKD")} -> 3632.2403 | Y7: {=_xll.BDP($C7,"CRNCY_ADJ_CURR_EV", "EQY_FUND_CRNCY=USD")} -> 463.62063 | Z7: =_xll.BDP($C7,Z$1)/100 -> 0.065611822 | AA7: =_xll.BDP($C7,"TRAIL_12M_NET_SALES","EQY_FUND_CRNCY=HKD") -> 11590.735 | AB7: =_xll.BDP($C7,"TRAIL_12M_NET_INC","EQY_FUND_CRNCY=HKD") -> 98.747584 | AC7: =_xll.BDP($C7,"TRAIL_12M_EBITDA","EQY_FUND_CRNCY=HKD") -> 340.37462 | AD7: =IF(AB7<0,"N/A",$E7/AB7) -> 34.063097 | AE7: {=_xll.BQL($C7, "PE_RATIO(FPT=BA, FPR=2026, FYE=C1231, AE=E)")} -> 34.159526 | AF7: {=_xll.BQL($C7, "PE_RATIO(FPT=BA, FPR=2027, FYE=C1231, AE=E)")} -> 27.694363 | AG7: =$E7/AA7 -> 0.29020149 | AH7: {=_xll.BQL($C7, "PX_TO_SALES_RATIO(FPT=BA, FPR=2026, FYE=C1231, AE=E)")} -> 0.29706215 | AI7: {=_xll.BQL($C7, "PX_TO_SALES_RATIO(FPT=BA, FPR=2027, FYE=C1231, AE=E)")} -> 0.27930084 | AJ7: =IF(AC7<0,"N/A",$X7/AC7) -> 10.671302 | AK7: {=IF(_xll.BQL($C7, "CURR_ENTP_VAL(FPT=A,FPO=0)/EBITDA(FPT=BA, FPR=2026, FYE=C1231, AE=E)")<0,"N/A",_xll.BQL($C7, "CURR_ENTP_VAL(FPT=A,FPO=0)/EBITDA(FPT=BA, FPR=2026, FYE=C1231, AE=E)"))} -> #N/A | AL7: {=IF(_xll.BQL($C7, "CURR_ENTP_VAL(FPT=A,FPO=0)/EBITDA(FPT=BA, FPR=2027, FYE=C1231, AE=E)")<0,"N/A",_xll.BQL($C7, "CURR_ENTP_VAL(FPT=A,FPO=0)/EBITDA(FPT=BA, FPR=2027, FYE=C1231, AE=E)"))} -> #N/A | AM7: =_xll.BDP($C7,AM$1) -> 2.3563056 | AN7: {=_xll.BQL($C7, "PX_TO_BOOK_RATIO(FPT=BA, FPR=2026, FYE=C1231, AE=E)")} -> 2.2737624 | AO7: {=_xll.BQL($C7, "PX_TO_BOOK_RATIO(FPT=BA, FPR=2027, FYE=C1231, AE=E)")} -> 2.1338398 | AP7: =_xll.BDP($C7,"BEST Px bps ratio","BEST fperiod override","27Y") -> 2.2325228 | AQ7: =Z7 -> 0.065611822 | AR7: =_xll.BDP($C7,"BEST_ROE","BEST fperiod override","26Y")/100 -> 0.0555 | AS7: =_xll.BDP($C7,"BEST_ROE","BEST fperiod override","27Y")/100 -> 0.0699 | AT7: =_xll.BDP($C7,AT$1) -> 1.1232131 | AU7: =_xll.BDP($C7,$AU$1,"BEST fperiod override","26Y") -> #N/A N/A | AV7: =_xll.BDP($C7,$AU$1,"BEST fperiod override","27Y") -> #N/A N/A | AW7: =(BP7/BN7)^(1/2)-1 -> -0.004529693 | AX7: =(BV7/BT7)^(1/2)-1 -> #VALUE! | AY7: =(CB7/BZ7)^(1/2)-1 -> -0.1925306 | AZ7: {=_xll.BQL($C7, "CF_CASH_FROM_OPER(FPT=BA, FPR=2022, FYE=C1231, AE=A)", "currency=USD")/1000000000} -> 0.054043298 | BA7: {=_xll.BQL($C7, "CF_CASH_FROM_OPER(FPT=BA, FPR=2023, FYE=C1231, AE=A)", "currency=USD")/1000000000} -> 0.021999611 | BB7: {=_xll.BQL($C7, "CF_CASH_FROM_OPER(FPT=BA, FPR=2024, FYE=C1231, AE=A)", "currency=USD")/1000000000} -> -0.0098155305 | BC7: {=_xll.BQL($C7, "CF_CASH_FROM_OPER(FPT=BA, FPR=2025, FYE=C1231, AE=E)", "currency=USD")/1000000000} -> #VALUE! | BD7: {=_xll.BQL($C7, "CF_CASH_FROM_OPER(FPT=BA, FPR=2026, FYE=C1231, AE=E)", "currency=USD")/1000000000} -> #VALUE! | BE7: {=_xll.BQL($C7, "CF_CASH_FROM_OPER(FPT=BA, FPR=2027, FYE=C1231, AE=E)", "currency=USD")/1000000000} -> #VALUE! | BF7: {=_xll.BQL($C7, "CF_FREE_CASH_FLOW(FPT=BA, FPR=2022, FYE=C1231, AE=A)", "currency=USD")/1000000000} -> 0.049792862 | BG7: {=_xll.BQL($C7, "CF_FREE_CASH_FLOW(FPT=BA, FPR=2023, FYE=C1231, AE=A)", "currency=USD")/1000000000} -> 0.0062953556 | BH7: {=_xll.BQL($C7, "CF_FREE_CASH_FLOW(FPT=BA, FPR=2024, FYE=C1231, AE=A)", "currency=USD")/1000000000} -> -0.022833284 | BI7: {=_xll.BQL($C7, "CF_FREE_CASH_FLOW(FPT=BA, FPR=2025, FYE=C1231, AE=E)", "currency=USD")/1000000000} -> #VALUE! | BJ7: {=_xll.BQL($C7, "CF_FREE_CASH_FLOW(FPT=BA, FPR=2026, FYE=C1231, AE=E)", "currency=USD")/1000000000} -> #VALUE! | BK7: {=_xll.BQL($C7, "CF_FREE_CASH_FLOW(FPT=BA, FPR=2027, FYE=C1231, AE=E)", "currency=USD")/1000000000} -> #VALUE! | BL7: {=_xll.BQL($C7, "SALES_REV_TURN(FPT=BA, FPR=2022, FYE=C1231, AE=A)", "currency=USD")/1000000000} -> 1.3512945 | BM7: {=_xll.BQL($C7, "SALES_REV_TURN(FPT=BA, FPR=2023, FYE=C1231, AE=A)", "currency=USD")/1000000000} -> 1.1990861 | BN7: {=_xll.BQL($C7, "SALES_REV_TURN(FPT=BA, FPR=2024, FYE=C1231, AE=A)", "currency=USD")/1000000000} -> 1.4662796 | BO7: {=_xll.BQL($C7, "SALES_REV_TURN(FPT=BA, FPR=2025, FYE=C1231, AE=E)", "currency=USD")/1000000000} -> 1.3931129 | BP7: {=_xll.BQL($C7, "SALES_REV_TURN(FPT=BA, FPR=2026, FYE=C1231, AE=E)", "currency=USD")/1000000000} -> 1.453026 | BQ7: {=_xll.BQL($C7, "SALES_REV_TURN(FPT=BA, FPR=2027, FYE=C1231, AE=E)", "currency=USD")/1000000000} -> 1.5454269 | BR7: {=_xll.BQL($C7, "EBITDA(FPT=BA, FPR=2022, FYE=C1231, AE=A)", "currency=USD")/1000000000} -> 0.054375123 | BS7: {=_xll.BQL($C7, "EBITDA(FPT=BA, FPR=2023, FYE=C1231, AE=A)", "currency=USD")/1000000000} -> 0.049776924 | BT7: {=_xll.BQL($C7, "EBITDA(FPT=BA, FPR=2024, FYE=C1231, AE=A)", "currency=USD")/1000000000} -> 0.052570466 | BU7: {=_xll.BQL($C7, "EBITDA(FPT=BA, FPR=2025, FYE=C1231, AE=E)", "currency=USD")/1000000000} -> #VALUE! | BV7: {=_xll.BQL($C7, "EBITDA(FPT=BA, FPR=2026, FYE=C1231, AE=E)", "currency=USD")/1000000000} -> #VALUE! | BW7: {=_xll.BQL($C7, "EBITDA(FPT=BA, FPR=2027, FYE=C1231, AE=E)", "currency=USD")/1000000000} -> #VALUE! | BX7: {=_xll.BQL($C7, "NET_INCOME(FPT=BA, FPR=2022, FYE=C1231, AE=A)", "currency=USD")/1000000000} -> 0.036362788 | BY7: {=_xll.BQL($C7, "NET_INCOME(FPT=BA, FPR=2023, FYE=C1231, AE=A)", "currency=USD")/1000000000} -> 0.018778827 | BZ7: {=_xll.BQL($C7, "NET_INCOME(FPT=BA, FPR=2024, FYE=C1231, AE=A)", "currency=USD")/1000000000} -> 0.019408024 | CA7: {=_xll.BQL($C7, "NET_INCOME(FPT=BA, FPR=2025, FYE=C1231, AE=E)", "currency=USD")/1000000000} -> 0.011725291 | CB7: {=_xll.BQL($C7, "NET_INCOME(FPT=BA, FPR=2026, FYE=C1231, AE=E)", "currency=USD")/1000000000} -> 0.012654164 | CC7: {=_xll.BQL($C7, "NET_INCOME(FPT=BA, FPR=2027, FYE=C1231, AE=E)", "currency=USD")/1000000000} -> 0.015608947 | CD7: {=-_xll.BQL($C7, "CF_DVD_PAID(FPT=BA, FPR=2024, FYE=C1231, AE=A)", "currency=USD")/1000000000} -> 0.0074249516 | CE7: {=-_xll.BQL($C7, "CF_DVD_PAID(FPT=BA, FPR=2025, FYE=C1231, AE=E)", "currency=USD")/1000000000} -> #VALUE! | CF7: {=-_xll.BQL($C7, "CF_DVD_PAID(FPT=BA, FPR=2026, FYE=C1231, AE=E)", "currency=USD")/1000000000} -> #VALUE! | CG7: {=-_xll.BQL($C7, "CF_DVD_PAID(FPT=BA, FPR=2027, FYE=C1231, AE=E)", "currency=USD")/1000000000} -> #VALUE! | CH7: =CD7/$F7 -> 1.7292851e-05 | CI7: =CE7/$F7 -> #VALUE! | CJ7: =CF7/$F7 -> #VALUE! | CK7: =CG7/$F7 -> #VALUE! | CL7: {=_xll.BDP($C7,"INTERVAL_AVG", "MARKET_DATA_OVERRIDE=turnover", "CALC_INTERVAL=5D","CRNCY=HKD")/1000000} -> 7.2448675 | CM7: {=_xll.BDP($C7,"INTERVAL_AVG", "MARKET_DATA_OVERRIDE=turnover", "CALC_INTERVAL=10D","CRNCY=HKD")/1000000} -> 4.2623237 | CN7: {=_xll.BDP($C7,"INTERVAL_AVG", "MARKET_DATA_OVERRIDE=turnover", "CALC_INTERVAL=20D","CRNCY=HKD")/1000000} -> 3.4449756 | CO7: {=_xll.BDP($C7,"INTERVAL_AVG", "MARKET_DATA_OVERRIDE=turnover", "CALC_INTERVAL=1m","CRNCY=HKD")/1000000} -> 3.3175718 | CP7: {=_xll.BDP($C7,"INTERVAL_AVG", "MARKET_DATA_OVERRIDE=turnover", "CALC_INTERVAL=3M","CRNCY=HKD")/1000000} -> 10.078578 | CQ7: {=_xll.BDP($C7,"INTERVAL_AVG", "MARKET_DATA_OVERRIDE=turnover", "CALC_INTERVAL=6M","CRNCY=HKD")/1000000} -> 7.5417473 | CR7: =_xll.BDP($C7,"chg pct 1m")/100 -> -0.000340231 | CS7: =_xll.BDP($C7,"chg pct 3m")/100 -> -0.03876982 | CT7: =_xll.BDP($C7,"chg pct 6m")/100 -> -0.2788414 | CU7: =_xll.BDP($C7,"chg pct 1yr")/100 -> -0.2847231 | CV7: =_xll.BDP($C7,"chg pct ytd")/100 -> -0.2132816 | CW7: {=_xll.BQL($C7, "volatility(calc_interval=range(-1M, 0D))")} -> 0.36384718 | CX7: {=_xll.BQL($C7, "volatility(calc_interval=range(-3M, 0D))")} -> 0.43541756 | CY7: {=_xll.BQL($C7, "volatility(calc_interval=range(-6M, 0D))")} -> 0.43323304 | CZ7: =_xll.BDP($C7,CZ$1) -> PDS Limited is a consumer-driven manufacturing and sourcing company. The Company designs, produces, and markets blazers, school wear, shirts, softs, and footwear products, as well as invests in sustainability, technology, and direct to consumer digital brands. PDS serves brand agencies and retailers worldwide.
A8: =_xll.BDP($C8,"security name") -> Walmart Inc | B8: =_xll.BDP($C8,"NAME_CHINESE_SIMPLIFIED") -> 沃尔玛股份有限公司 | C8: wmt us Equity | D8: =_xll.BDP($C8,"LISTING_DATE") -> #N/A Field Not Applicable | E8: =_xll.BDP($C8,E$1,"EQY_FUND_CRNCY="&$B$1) -> 8380084.2 | F8: =_xll.BDP($C8,F$1,"EQY_FUND_CRNCY="&$C$1) -> 1069706.9 | G8: =_xll.BDP($C8,G$1) -> 134.2 | H8: =_xll.BDP($C8,H$1,"EQY_FUND_CRNCY="&$B$1) -> 829276.42 | I8: =_xll.BDP($C8,I$1,"EQY_FUND_CRNCY="&$C$1) -> 106180 | J8: =_xll.BDP($C8,J$1,"EQY_FUND_CRNCY="&$B$1) -> 5560443 | K8: =_xll.BDP($C8,K$1,"EQY_FUND_CRNCY="&$C$1) -> 713163 | L8: =_xll.BDP($C8,L$1,"EQY_FUND_CRNCY="&$B$1) -> 170696.99 | M8: =_xll.BDP($C8,M$1,"EQY_FUND_CRNCY="&$C$1) -> 21893 | N8: =_xll.BDP($C8,N$1)/100 -> 0.249267 | O8: =_xll.BDP($C8,O$1)/100 -> 0.06575916 | P8: =_xll.BDP($C8,P$1)/100 -> 0.030698452 | Q8: =_xll.BDP($C8,Q$1)/100 -> 0.047252142 | R8: =_xll.BDP($C8,R$1)/100 -> 0.1264149 | S8: =_xll.BDP($C8,S$1)/100 -> 0.63189866 | T8: =_xll.BDP($C8,T$1)/100 -> 0.67352962 | U8: =_xll.BDP($C8,U$1)/100 -> 0.5308721 | ... W8: =_xll.BDP($C8,W$1)/100 -> 0.080268969 | X8: {=_xll.BDP($C8,"CRNCY_ADJ_CURR_EV", "EQY_FUND_CRNCY=HKD")} -> 8871581.5 | Y8: {=_xll.BDP($C8,"CRNCY_ADJ_CURR_EV", "EQY_FUND_CRNCY=USD")} -> 1132637.9 | Z8: =_xll.BDP($C8,Z$1)/100 -> 0.22969102 | AA8: =_xll.BDP($C8,"TRAIL_12M_NET_SALES","EQY_FUND_CRNCY=HKD") -> 5560443 | AB8: =_xll.BDP($C8,"TRAIL_12M_NET_INC","EQY_FUND_CRNCY=HKD") -> 170696.99 | AC8: =_xll.BDP($C8,"TRAIL_12M_EBITDA","EQY_FUND_CRNCY=HKD") -> 362258.42 | AD8: =IF(AB8<0,"N/A",$E8/AB8) -> 49.093332 | AE8: {=_xll.BQL($C8, "PE_RATIO(FPT=BA, FPR=2026, FYE=C1231, AE=E)")} -> 46.576104 | AF8: {=_xll.BQL($C8, "PE_RATIO(FPT=BA, FPR=2027, FYE=C1231, AE=E)")} -> 40.85241 | AG8: =$E8/AA8 -> 1.5070893 | AH8: {=_xll.BQL($C8, "PX_TO_SALES_RATIO(FPT=BA, FPR=2026, FYE=C1231, AE=E)")} -> 1.433405 | AI8: {=_xll.BQL($C8, "PX_TO_SALES_RATIO(FPT=BA, FPR=2027, FYE=C1231, AE=E)")} -> 1.3671795 | AJ8: =IF(AC8<0,"N/A",$X8/AC8) -> 24.489648 | AK8: {=IF(_xll.BQL($C8, "CURR_ENTP_VAL(FPT=A,FPO=0)/EBITDA(FPT=BA, FPR=2026, FYE=C1231, AE=E)")<0,"N/A",_xll.BQL($C8, "CURR_ENTP_VAL(FPT=A,FPO=0)/EBITDA(FPT=BA, FPR=2026, FYE=C1231, AE=E)"))} -> 21.698405 | AL8: {=IF(_xll.BQL($C8, "CURR_ENTP_VAL(FPT=A,FPO=0)/EBITDA(FPT=BA, FPR=2027, FYE=C1231, AE=E)")<0,"N/A",_xll.BQL($C8, "CURR_ENTP_VAL(FPT=A,FPO=0)/EBITDA(FPT=BA, FPR=2027, FYE=C1231, AE=E)"))} -> 19.712839 | AM8: =_xll.BDP($C8,AM$1) -> 10.735515 | AN8: {=_xll.BQL($C8, "PX_TO_BOOK_RATIO(FPT=BA, FPR=2026, FYE=C1231, AE=E)")} -> 9.7242299 | AO8: {=_xll.BQL($C8, "PX_TO_BOOK_RATIO(FPT=BA, FPR=2027, FYE=C1231, AE=E)")} -> 8.8181213 | AP8: =_xll.BDP($C8,"BEST Px bps ratio","BEST fperiod override","27Y") -> 9.7232285 | AQ8: =Z8 -> 0.22969102 | AR8: =_xll.BDP($C8,"BEST_ROE","BEST fperiod override","26Y")/100 -> 0.21592 | AS8: =_xll.BDP($C8,"BEST_ROE","BEST fperiod override","27Y")/100 -> 0.21427 | AT8: =_xll.BDP($C8,AT$1) -> 0.73770493 | AU8: =_xll.BDP($C8,$AU$1,"BEST fperiod override","26Y") -> 0.695231 | AV8: =_xll.BDP($C8,$AU$1,"BEST fperiod override","27Y") -> 0.73099851 | AW8: =(BP8/BN8)^(1/2)-1 -> 0.048698146 | AX8: =(BV8/BT8)^(1/2)-1 -> 0.077160566 | AY8: =(CB8/BZ8)^(1/2)-1 -> 0.079747432 | AZ8: {=_xll.BQL($C8, "CF_CASH_FROM_OPER(FPT=BA, FPR=2022, FYE=C1231, AE=A)", "currency=USD")/1000000000} -> 27.070967 | BA8: {=_xll.BQL($C8, "CF_CASH_FROM_OPER(FPT=BA, FPR=2023, FYE=C1231, AE=A)", "currency=USD")/1000000000} -> 34.523402 | BB8: {=_xll.BQL($C8, "CF_CASH_FROM_OPER(FPT=BA, FPR=2024, FYE=C1231, AE=A)", "currency=USD")/1000000000} -> 37.51688 | BC8: {=_xll.BQL($C8, "CF_CASH_FROM_OPER(FPT=BA, FPR=2025, FYE=C1231, AE=E)", "currency=USD")/1000000000} -> 39.156214 | BD8: {=_xll.BQL($C8, "CF_CASH_FROM_OPER(FPT=BA, FPR=2026, FYE=C1231, AE=E)", "currency=USD")/1000000000} -> 40.128463 | BE8: {=_xll.BQL($C8, "CF_CASH_FROM_OPER(FPT=BA, FPR=2027, FYE=C1231, AE=E)", "currency=USD")/1000000000} -> 43.735809 | BF8: {=_xll.BQL($C8, "CF_FREE_CASH_FLOW(FPT=BA, FPR=2022, FYE=C1231, AE=A)", "currency=USD")/1000000000} -> 10.307641 | BG8: {=_xll.BQL($C8, "CF_FREE_CASH_FLOW(FPT=BA, FPR=2023, FYE=C1231, AE=A)", "currency=USD")/1000000000} -> 14.300185 | BH8: {=_xll.BQL($C8, "CF_FREE_CASH_FLOW(FPT=BA, FPR=2024, FYE=C1231, AE=A)", "currency=USD")/1000000000} -> 14.123065 | BI8: {=_xll.BQL($C8, "CF_FREE_CASH_FLOW(FPT=BA, FPR=2025, FYE=C1231, AE=E)", "currency=USD")/1000000000} -> 16.499711 | BJ8: {=_xll.BQL($C8, "CF_FREE_CASH_FLOW(FPT=BA, FPR=2026, FYE=C1231, AE=E)", "currency=USD")/1000000000} -> 14.119226 | BK8: {=_xll.BQL($C8, "CF_FREE_CASH_FLOW(FPT=BA, FPR=2027, FYE=C1231, AE=E)", "currency=USD")/1000000000} -> 18.194063 | BL8: {=_xll.BQL($C8, "SALES_REV_TURN(FPT=BA, FPR=2022, FYE=C1231, AE=A)", "currency=USD")/1000000000} -> 607.52284 | BM8: {=_xll.BQL($C8, "SALES_REV_TURN(FPT=BA, FPR=2023, FYE=C1231, AE=A)", "currency=USD")/1000000000} -> 644.97783 | BN8: {=_xll.BQL($C8, "SALES_REV_TURN(FPT=BA, FPR=2024, FYE=C1231, AE=A)", "currency=USD")/1000000000} -> 678.57037 | BO8: {=_xll.BQL($C8, "SALES_REV_TURN(FPT=BA, FPR=2025, FYE=C1231, AE=E)", "currency=USD")/1000000000} -> 706.70368 | BP8: {=_xll.BQL($C8, "SALES_REV_TURN(FPT=BA, FPR=2026, FYE=C1231, AE=E)", "currency=USD")/1000000000} -> 746.26984 | BQ8: {=_xll.BQL($C8, "SALES_REV_TURN(FPT=BA, FPR=2027, FYE=C1231, AE=E)", "currency=USD")/1000000000} -> 782.41879 | BR8: {=_xll.BQL($C8, "EBITDA(FPT=BA, FPR=2022, FYE=C1231, AE=A)", "currency=USD")/1000000000} -> 31.447467 | BS8: {=_xll.BQL($C8, "EBITDA(FPT=BA, FPR=2023, FYE=C1231, AE=A)", "currency=USD")/1000000000} -> 38.191424 | BT8: {=_xll.BQL($C8, "EBITDA(FPT=BA, FPR=2024, FYE=C1231, AE=A)", "currency=USD")/1000000000} -> 42.030543 | BU8: {=_xll.BQL($C8, "EBITDA(FPT=BA, FPR=2025, FYE=C1231, AE=E)", "currency=USD")/1000000000} -> 44.809955 | BV8: {=_xll.BQL($C8, "EBITDA(FPT=BA, FPR=2026, FYE=C1231, AE=E)", "currency=USD")/1000000000} -> 48.766984 | BW8: {=_xll.BQL($C8, "EBITDA(FPT=BA, FPR=2027, FYE=C1231, AE=E)", "currency=USD")/1000000000} -> 53.679012 | BX8: {=_xll.BQL($C8, "NET_INCOME(FPT=BA, FPR=2022, FYE=C1231, AE=A)", "currency=USD")/1000000000} -> 10.765837 | BY8: {=_xll.BQL($C8, "NET_INCOME(FPT=BA, FPR=2023, FYE=C1231, AE=A)", "currency=USD")/1000000000} -> 15.774163 | BZ8: {=_xll.BQL($C8, "NET_INCOME(FPT=BA, FPR=2024, FYE=C1231, AE=A)", "currency=USD")/1000000000} -> 19.51687 | CA8: {=_xll.BQL($C8, "NET_INCOME(FPT=BA, FPR=2025, FYE=C1231, AE=E)", "currency=USD")/1000000000} -> 20.761634 | CB8: {=_xll.BQL($C8, "NET_INCOME(FPT=BA, FPR=2026, FYE=C1231, AE=E)", "currency=USD")/1000000000} -> 22.753831 | CC8: {=_xll.BQL($C8, "NET_INCOME(FPT=BA, FPR=2027, FYE=C1231, AE=E)", "currency=USD")/1000000000} -> 25.800935 | CD8: {=-_xll.BQL($C8, "CF_DVD_PAID(FPT=BA, FPR=2024, FYE=C1231, AE=A)", "currency=USD")/1000000000} -> 6.6374565 | CE8: {=-_xll.BQL($C8, "CF_DVD_PAID(FPT=BA, FPR=2025, FYE=C1231, AE=E)", "currency=USD")/1000000000} -> 7.398584 | CF8: {=-_xll.BQL($C8, "CF_DVD_PAID(FPT=BA, FPR=2026, FYE=C1231, AE=E)", "currency=USD")/1000000000} -> 7.6709596 | CG8: {=-_xll.BQL($C8, "CF_DVD_PAID(FPT=BA, FPR=2027, FYE=C1231, AE=E)", "currency=USD")/1000000000} -> 8.139111 | CH8: =CD8/$F8 -> 6.2049299e-06 | CI8: =CE8/$F8 -> 6.9164589e-06 | CJ8: =CF8/$F8 -> 7.1710853e-06 | CK8: =CG8/$F8 -> 7.6087299e-06 | CL8: {=_xll.BDP($C8,"INTERVAL_AVG", "MARKET_DATA_OVERRIDE=turnover", "CALC_INTERVAL=5D","CRNCY=HKD")/1000000} -> 19123.993 | CM8: {=_xll.BDP($C8,"INTERVAL_AVG", "MARKET_DATA_OVERRIDE=turnover", "CALC_INTERVAL=10D","CRNCY=HKD")/1000000} -> 17589.413 | CN8: {=_xll.BDP($C8,"INTERVAL_AVG", "MARKET_DATA_OVERRIDE=turnover", "CALC_INTERVAL=20D","CRNCY=HKD")/1000000} -> 16368.912 | CO8: {=_xll.BDP($C8,"INTERVAL_AVG", "MARKET_DATA_OVERRIDE=turnover", "CALC_INTERVAL=1m","CRNCY=HKD")/1000000} -> 16610.733 | CP8: {=_xll.BDP($C8,"INTERVAL_AVG", "MARKET_DATA_OVERRIDE=turnover", "CALC_INTERVAL=3M","CRNCY=HKD")/1000000} -> 18447.682 | CQ8: {=_xll.BDP($C8,"INTERVAL_AVG", "MARKET_DATA_OVERRIDE=turnover", "CALC_INTERVAL=6M","CRNCY=HKD")/1000000} -> 23745.789 | CR8: =_xll.BDP($C8,"chg pct 1m")/100 -> 0.0490932 | CS8: =_xll.BDP($C8,"chg pct 3m")/100 -> 0.09114564 | CT8: =_xll.BDP($C8,"chg pct 6m")/100 -> 0.2529176 | CU8: =_xll.BDP($C8,"chg pct 1yr")/100 -> 0.3721881 | CV8: =_xll.BDP($C8,"chg pct ytd")/100 -> 0.2045597 | CW8: {=_xll.BQL($C8, "volatility(calc_interval=range(-1M, 0D))")} -> 0.2058647 | CX8: {=_xll.BQL($C8, "volatility(calc_interval=range(-3M, 0D))")} -> 0.22858561 | CY8: {=_xll.BQL($C8, "volatility(calc_interval=range(-6M, 0D))")} -> 0.2382971 | CZ8: =_xll.BDP($C8,CZ$1) -> Walmart Inc. operates discount stores, supercenters, and neighborhood markets. The Company offers merchandise such as apparel, house wares, small appliances, electronics, musical instruments, books, home improvement, shoes, jewelry, toddler, games, household essentials, pets, pharmaceutical products, party supplies, and automotive tools. Walmart serves customers worldwide.
A9: =_xll.BDP($C9,"security name") -> American Eagle Outfitters Inc | B9: =_xll.BDP($C9,"NAME_CHINESE_SIMPLIFIED") -> 美鹰傲飞AEO有限公司 | C9: aeo us Equity | D9: =_xll.BDP($C9,"LISTING_DATE") -> #N/A Field Not Applicable | E9: =_xll.BDP($C9,E$1,"EQY_FUND_CRNCY="&$B$1) -> 20157.569 | F9: =_xll.BDP($C9,F$1,"EQY_FUND_CRNCY="&$C$1) -> 2573.0877 | G9: =_xll.BDP($C9,G$1) -> 15.36 | H9: =_xll.BDP($C9,H$1,"EQY_FUND_CRNCY="&$B$1) -> 13210.269 | I9: =_xll.BDP($C9,I$1,"EQY_FUND_CRNCY="&$C$1) -> 1691.434 | J9: =_xll.BDP($C9,J$1,"EQY_FUND_CRNCY="&$B$1) -> 43251.108 | K9: =_xll.BDP($C9,K$1,"EQY_FUND_CRNCY="&$C$1) -> 5547.236 | L9: =_xll.BDP($C9,L$1,"EQY_FUND_CRNCY="&$B$1) -> 1496.8675 | M9: =_xll.BDP($C9,M$1,"EQY_FUND_CRNCY="&$C$1) -> 191.983 | N9: =_xll.BDP($C9,N$1)/100 -> 0.36510453 | O9: =_xll.BDP($C9,O$1)/100 -> 0.17345972 | P9: =_xll.BDP($C9,P$1)/100 -> 0.034608767 | Q9: =_xll.BDP($C9,Q$1)/100 -> 0.041020506 | R9: =_xll.BDP($C9,R$1)/100 -> -0.41713826 | S9: =_xll.BDP($C9,S$1)/100 -> 1.0052553 | T9: =_xll.BDP($C9,T$1)/100 -> 1.0042347 | U9: =_xll.BDP($C9,U$1)/100 -> 0.86400061 | ... W9: =_xll.BDP($C9,W$1)/100 -> 0.048972413 | X9: {=_xll.BDP($C9,"CRNCY_ADJ_CURR_EV", "EQY_FUND_CRNCY=HKD")} -> 31557.824 | Y9: {=_xll.BDP($C9,"CRNCY_ADJ_CURR_EV", "EQY_FUND_CRNCY=USD")} -> 4032.7687 | Z9: =_xll.BDP($C9,Z$1)/100 -> 0.11097242 | AA9: =_xll.BDP($C9,"TRAIL_12M_NET_SALES","EQY_FUND_CRNCY=HKD") -> 43251.108 | AB9: =_xll.BDP($C9,"TRAIL_12M_NET_INC","EQY_FUND_CRNCY=HKD") -> 1496.8675 | AC9: =_xll.BDP($C9,"TRAIL_12M_EBITDA","EQY_FUND_CRNCY=HKD") -> 6710.1391 | AD9: =IF(AB9<0,"N/A",$E9/AB9) -> 13.466502 | AE9: {=_xll.BQL($C9, "PE_RATIO(FPT=BA, FPR=2026, FYE=C1231, AE=E)")} -> 8.8269914 | AF9: {=_xll.BQL($C9, "PE_RATIO(FPT=BA, FPR=2027, FYE=C1231, AE=E)")} -> 7.7833708 | AG9: =$E9/AA9 -> 0.46605903 | AH9: {=_xll.BQL($C9, "PX_TO_SALES_RATIO(FPT=BA, FPR=2026, FYE=C1231, AE=E)")} -> 0.44585488 | AI9: {=_xll.BQL($C9, "PX_TO_SALES_RATIO(FPT=BA, FPR=2027, FYE=C1231, AE=E)")} -> 0.43027257 | AJ9: =IF(AC9<0,"N/A",$X9/AC9) -> 4.7030059 | AK9: {=IF(_xll.BQL($C9, "CURR_ENTP_VAL(FPT=A,FPO=0)/EBITDA(FPT=BA, FPR=2026, FYE=C1231, AE=E)")<0,"N/A",_xll.BQL($C9, "CURR_ENTP_VAL(FPT=A,FPO=0)/EBITDA(FPT=BA, FPR=2026, FYE=C1231, AE=E)"))} -> 8.3320805 | AL9: {=IF(_xll.BQL($C9, "CURR_ENTP_VAL(FPT=A,FPO=0)/EBITDA(FPT=BA, FPR=2027, FYE=C1231, AE=E)")<0,"N/A",_xll.BQL($C9, "CURR_ENTP_VAL(FPT=A,FPO=0)/EBITDA(FPT=BA, FPR=2027, FYE=C1231, AE=E)"))} -> 7.6098393 | AM9: =_xll.BDP($C9,AM$1) -> 1.5327586 | AN9: {=_xll.BQL($C9, "PX_TO_BOOK_RATIO(FPT=BA, FPR=2026, FYE=C1231, AE=E)")} -> 1.2597358 | AO9: {=_xll.BQL($C9, "PX_TO_BOOK_RATIO(FPT=BA, FPR=2027, FYE=C1231, AE=E)")} -> 1.1445369 | AP9: =_xll.BDP($C9,"BEST Px bps ratio","BEST fperiod override","27Y") -> 1.2687923 | AQ9: =Z9 -> 0.11097242 | AR9: =_xll.BDP($C9,"BEST_ROE","BEST fperiod override","26Y")/100 -> 0.13893 | AS9: =_xll.BDP($C9,"BEST_ROE","BEST fperiod override","27Y")/100 -> 0.17072 | AT9: =_xll.BDP($C9,AT$1) -> 3.2552083 | AU9: =_xll.BDP($C9,$AU$1,"BEST fperiod override","26Y") -> 3.2747396 | AV9: =_xll.BDP($C9,$AU$1,"BEST fperiod override","27Y") -> 3.2356771 | AW9: =(BP9/BN9)^(1/2)-1 -> 0.038917207 | AX9: =(BV9/BT9)^(1/2)-1 -> 0.02443777 | AY9: =(CB9/BZ9)^(1/2)-1 -> 0.015840872 | AZ9: {=_xll.BQL($C9, "CF_CASH_FROM_OPER(FPT=BA, FPR=2022, FYE=C1231, AE=A)", "currency=USD")/1000000000} -> 0.30877057 | BA9: {=_xll.BQL($C9, "CF_CASH_FROM_OPER(FPT=BA, FPR=2023, FYE=C1231, AE=A)", "currency=USD")/1000000000} -> 0.62958049 | BB9: {=_xll.BQL($C9, "CF_CASH_FROM_OPER(FPT=BA, FPR=2024, FYE=C1231, AE=A)", "currency=USD")/1000000000} -> 0.44467309 | BC9: {=_xll.BQL($C9, "CF_CASH_FROM_OPER(FPT=BA, FPR=2025, FYE=C1231, AE=E)", "currency=USD")/1000000000} -> 0.88413334 | BD9: {=_xll.BQL($C9, "CF_CASH_FROM_OPER(FPT=BA, FPR=2026, FYE=C1231, AE=E)", "currency=USD")/1000000000} -> 0.60041393 | BE9: {=_xll.BQL($C9, "CF_CASH_FROM_OPER(FPT=BA, FPR=2027, FYE=C1231, AE=E)", "currency=USD")/1000000000} -> 0.60689928 | BF9: {=_xll.BQL($C9, "CF_FREE_CASH_FLOW(FPT=BA, FPR=2022, FYE=C1231, AE=A)", "currency=USD")/1000000000} -> 0.038662615 | BG9: {=_xll.BQL($C9, "CF_FREE_CASH_FLOW(FPT=BA, FPR=2023, FYE=C1231, AE=A)", "currency=USD")/1000000000} -> 0.45008166 | BH9: {=_xll.BQL($C9, "CF_FREE_CASH_FLOW(FPT=BA, FPR=2024, FYE=C1231, AE=A)", "currency=USD")/1000000000} -> 0.23123481 | BI9: {=_xll.BQL($C9, "CF_FREE_CASH_FLOW(FPT=BA, FPR=2025, FYE=C1231, AE=E)", "currency=USD")/1000000000} -> 0.49798702 | BJ9: {=_xll.BQL($C9, "CF_FREE_CASH_FLOW(FPT=BA, FPR=2026, FYE=C1231, AE=E)", "currency=USD")/1000000000} -> 0.35781943 | BK9: {=_xll.BQL($C9, "CF_FREE_CASH_FLOW(FPT=BA, FPR=2027, FYE=C1231, AE=E)", "currency=USD")/1000000000} -> 0.32122047 | BL9: {=_xll.BQL($C9, "SALES_REV_TURN(FPT=BA, FPR=2022, FYE=C1231, AE=A)", "currency=USD")/1000000000} -> 5.0100486 | BM9: {=_xll.BQL($C9, "SALES_REV_TURN(FPT=BA, FPR=2023, FYE=C1231, AE=A)", "currency=USD")/1000000000} -> 5.1396258 | BN9: {=_xll.BQL($C9, "SALES_REV_TURN(FPT=BA, FPR=2024, FYE=C1231, AE=A)", "currency=USD")/1000000000} -> 5.3468644 | BO9: {=_xll.BQL($C9, "SALES_REV_TURN(FPT=BA, FPR=2025, FYE=C1231, AE=E)", "currency=USD")/1000000000} -> 5.3619101 | BP9: {=_xll.BQL($C9, "SALES_REV_TURN(FPT=BA, FPR=2026, FYE=C1231, AE=E)", "currency=USD")/1000000000} -> 5.7711326 | BQ9: {=_xll.BQL($C9, "SALES_REV_TURN(FPT=BA, FPR=2027, FYE=C1231, AE=E)", "currency=USD")/1000000000} -> 5.980134 | BR9: {=_xll.BQL($C9, "EBITDA(FPT=BA, FPR=2022, FYE=C1231, AE=A)", "currency=USD")/1000000000} -> 0.4586707 | BS9: {=_xll.BQL($C9, "EBITDA(FPT=BA, FPR=2023, FYE=C1231, AE=A)", "currency=USD")/1000000000} -> 0.47541237 | BT9: {=_xll.BQL($C9, "EBITDA(FPT=BA, FPR=2024, FYE=C1231, AE=A)", "currency=USD")/1000000000} -> 0.6021329 | BU9: {=_xll.BQL($C9, "EBITDA(FPT=BA, FPR=2025, FYE=C1231, AE=E)", "currency=USD")/1000000000} -> 0.458687 | BV9: {=_xll.BQL($C9, "EBITDA(FPT=BA, FPR=2026, FYE=C1231, AE=E)", "currency=USD")/1000000000} -> 0.63192207 | BW9: {=_xll.BQL($C9, "EBITDA(FPT=BA, FPR=2027, FYE=C1231, AE=E)", "currency=USD")/1000000000} -> 0.69189707 | BX9: {=_xll.BQL($C9, "NET_INCOME(FPT=BA, FPR=2022, FYE=C1231, AE=A)", "currency=USD")/1000000000} -> 0.12441023 | BY9: {=_xll.BQL($C9, "NET_INCOME(FPT=BA, FPR=2023, FYE=C1231, AE=A)", "currency=USD")/1000000000} -> 0.18464497 | BZ9: {=_xll.BQL($C9, "NET_INCOME(FPT=BA, FPR=2024, FYE=C1231, AE=A)", "currency=USD")/1000000000} -> 0.29487917 | CA9: {=_xll.BQL($C9, "NET_INCOME(FPT=BA, FPR=2025, FYE=C1231, AE=E)", "currency=USD")/1000000000} -> 0.20500813 | CB9: {=_xll.BQL($C9, "NET_INCOME(FPT=BA, FPR=2026, FYE=C1231, AE=E)", "currency=USD")/1000000000} -> 0.30429545 | CC9: {=_xll.BQL($C9, "NET_INCOME(FPT=BA, FPR=2027, FYE=C1231, AE=E)", "currency=USD")/1000000000} -> 0.35161115 | CD9: {=-_xll.BQL($C9, "CF_DVD_PAID(FPT=BA, FPR=2024, FYE=C1231, AE=A)", "currency=USD")/1000000000} -> 0.09664705 | CE9: {=-_xll.BQL($C9, "CF_DVD_PAID(FPT=BA, FPR=2025, FYE=C1231, AE=E)", "currency=USD")/1000000000} -> 0.090614801 | CF9: {=-_xll.BQL($C9, "CF_DVD_PAID(FPT=BA, FPR=2026, FYE=C1231, AE=E)", "currency=USD")/1000000000} -> 0.088729529 | CG9: {=-_xll.BQL($C9, "CF_DVD_PAID(FPT=BA, FPR=2027, FYE=C1231, AE=E)", "currency=USD")/1000000000} -> 0.093559922 | CH9: =CD9/$F9 -> 3.7560729e-05 | CI9: =CE9/$F9 -> 3.5216367e-05 | CJ9: =CF9/$F9 -> 3.4483679e-05 | CK9: =CG9/$F9 -> 3.6360953e-05 | CL9: {=_xll.BDP($C9,"INTERVAL_AVG", "MARKET_DATA_OVERRIDE=turnover", "CALC_INTERVAL=5D","CRNCY=HKD")/1000000} -> 554.67983 | CM9: {=_xll.BDP($C9,"INTERVAL_AVG", "MARKET_DATA_OVERRIDE=turnover", "CALC_INTERVAL=10D","CRNCY=HKD")/1000000} -> 543.59402 | CN9: {=_xll.BDP($C9,"INTERVAL_AVG", "MARKET_DATA_OVERRIDE=turnover", "CALC_INTERVAL=20D","CRNCY=HKD")/1000000} -> 540.68725 | CO9: {=_xll.BDP($C9,"INTERVAL_AVG", "MARKET_DATA_OVERRIDE=turnover", "CALC_INTERVAL=1m","CRNCY=HKD")/1000000} -> 563.99768 | CP9: {=_xll.BDP($C9,"INTERVAL_AVG", "MARKET_DATA_OVERRIDE=turnover", "CALC_INTERVAL=3M","CRNCY=HKD")/1000000} -> 780.81676 | CQ9: {=_xll.BDP($C9,"INTERVAL_AVG", "MARKET_DATA_OVERRIDE=turnover", "CALC_INTERVAL=6M","CRNCY=HKD")/1000000} -> 1081.9367 | CR9: =_xll.BDP($C9,"chg pct 1m")/100 -> -0.2273642 | CS9: =_xll.BDP($C9,"chg pct 3m")/100 -> -0.391924 | CT9: =_xll.BDP($C9,"chg pct 6m")/100 -> -0.1242874 | CU9: =_xll.BDP($C9,"chg pct 1yr")/100 -> 0.3391456 | CV9: =_xll.BDP($C9,"chg pct ytd")/100 -> -0.4175199 | CW9: {=_xll.BQL($C9, "volatility(calc_interval=range(-1M, 0D))")} -> 0.37298253 | CX9: {=_xll.BQL($C9, "volatility(calc_interval=range(-3M, 0D))")} -> 0.53793434 | CY9: {=_xll.BQL($C9, "volatility(calc_interval=range(-6M, 0D))")} -> 0.5440254 | CZ9: =_xll.BDP($C9,CZ$1) -> American Eagle Outfitters, Inc. retails men's and women's casual apparel, footwear, outerwear, and accessories. The Company provides products include jeans, khakis, t-shirts, and other similar apparel. American Eagle serves customers in the United States.
A10: =_xll.BDP($C10,"security name") -> Costco Wholesale Corp | B10: =_xll.BDP($C10,"NAME_CHINESE_SIMPLIFIED") -> 开市客公司 | C10: cost us Equity | D10: =_xll.BDP($C10,"LISTING_DATE") -> 12/5/1985 | E10: =_xll.BDP($C10,E$1,"EQY_FUND_CRNCY="&$B$1) -> 3803390.2 | F10: =_xll.BDP($C10,F$1,"EQY_FUND_CRNCY="&$C$1) -> 485497.85 | G10: =_xll.BDP($C10,G$1) -> 1094.32 | H10: =_xll.BDP($C10,H$1,"EQY_FUND_CRNCY="&$B$1) -> 227315.88 | I10: =_xll.BDP($C10,I$1,"EQY_FUND_CRNCY="&$C$1) -> 29164 | J10: =_xll.BDP($C10,J$1,"EQY_FUND_CRNCY="&$B$1) -> 2145593.8 | K10: =_xll.BDP($C10,K$1,"EQY_FUND_CRNCY="&$C$1) -> 275235 | L10: =_xll.BDP($C10,L$1,"EQY_FUND_CRNCY="&$B$1) -> 63135.736 | M10: =_xll.BDP($C10,M$1,"EQY_FUND_CRNCY="&$C$1) -> 8099 | N10: =_xll.BDP($C10,N$1)/100 -> 0.12843207 | O10: =_xll.BDP($C10,O$1)/100 -> 0.047097934 | P10: =_xll.BDP($C10,P$1)/100 -> 0.029425763 | Q10: =_xll.BDP($C10,Q$1)/100 -> 0.081673236 | R10: =_xll.BDP($C10,R$1)/100 -> 0.09936202 | S10: =_xll.BDP($C10,S$1)/100 -> 0.29262104 | T10: =_xll.BDP($C10,T$1)/100 -> 0.29262104 | U10: =_xll.BDP($C10,U$1)/100 -> -0.23144973 | ... W10: =_xll.BDP($C10,W$1)/100 -> 0.10899957 | X10: {=_xll.BDP($C10,"CRNCY_ADJ_CURR_EV", "EQY_FUND_CRNCY=HKD")} -> 3724627.8 | Y10: {=_xll.BDP($C10,"CRNCY_ADJ_CURR_EV", "EQY_FUND_CRNCY=USD")} -> 475422.85 | Z10: =_xll.BDP($C10,Z$1)/100 -> 0.29651082 | AA10: =_xll.BDP($C10,"TRAIL_12M_NET_SALES","EQY_FUND_CRNCY=HKD") -> 2232256.2 | AB10: =_xll.BDP($C10,"TRAIL_12M_NET_INC","EQY_FUND_CRNCY=HKD") -> 66663.958 | AC10: =_xll.BDP($C10,"TRAIL_12M_EBITDA","EQY_FUND_CRNCY=HKD") -> 104959.28 | AD10: =IF(AB10<0,"N/A",$E10/AB10) -> 57.053171 | AE10: {=_xll.BQL($C10, "PE_RATIO(FPT=BA, FPR=2026, FYE=C1231, AE=E)")} -> 51.687613 | AF10: {=_xll.BQL($C10, "PE_RATIO(FPT=BA, FPR=2027, FYE=C1231, AE=E)")} -> 46.888178 | AG10: =$E10/AA10 -> 1.7038323 | AH10: {=_xll.BQL($C10, "PX_TO_SALES_RATIO(FPT=BA, FPR=2026, FYE=C1231, AE=E)")} -> 1.5700454 | AI10: {=_xll.BQL($C10, "PX_TO_SALES_RATIO(FPT=BA, FPR=2027, FYE=C1231, AE=E)")} -> 1.4522641 | AJ10: =IF(AC10<0,"N/A",$X10/AC10) -> 35.486408 | AK10: {=IF(_xll.BQL($C10, "CURR_ENTP_VAL(FPT=A,FPO=0)/EBITDA(FPT=BA, FPR=2026, FYE=C1231, AE=E)")<0,"N/A",_xll.BQL($C10, "CURR_ENTP_VAL(FPT=A,FPO=0)/EBITDA(FPT=BA, FPR=2026, FYE=C1231, AE=E)"))} -> 27.964893 | AL10: {=IF(_xll.BQL($C10, "CURR_ENTP_VAL(FPT=A,FPO=0)/EBITDA(FPT=BA, FPR=2027, FYE=C1231, AE=E)")<0,"N/A",_xll.BQL($C10, "CURR_ENTP_VAL(FPT=A,FPO=0)/EBITDA(FPT=BA, FPR=2027, FYE=C1231, AE=E)"))} -> 25.553506 | AM10: =_xll.BDP($C10,AM$1) -> 15.132016 | AN10: {=_xll.BQL($C10, "PX_TO_BOOK_RATIO(FPT=BA, FPR=2026, FYE=C1231, AE=E)")} -> 12.562627 | AO10: {=_xll.BQL($C10, "PX_TO_BOOK_RATIO(FPT=BA, FPR=2027, FYE=C1231, AE=E)")} -> 10.905653 | AP10: =_xll.BDP($C10,"BEST Px bps ratio","BEST fperiod override","27Y") -> 11.56212 | AQ10: =Z10 -> 0.29651082 | AR10: =_xll.BDP($C10,"BEST_ROE","BEST fperiod override","26Y")/100 -> 0.28724 | AS10: =_xll.BDP($C10,"BEST_ROE","BEST fperiod override","27Y")/100 -> 0.26459 | AT10: =_xll.BDP($C10,AT$1) -> 0.53711385 | AU10: =_xll.BDP($C10,$AU$1,"BEST fperiod override","26Y") -> 0.49382265 | AV10: =_xll.BDP($C10,$AU$1,"BEST fperiod override","27Y") -> 0.5353096 | AW10: =(BP10/BN10)^(1/2)-1 -> 0.085310885 | AX10: =(BV10/BT10)^(1/2)-1 -> 0.10881618 | AY10: =(CB10/BZ10)^(1/2)-1 -> 0.11049497 | AZ10: {=_xll.BQL($C10, "CF_CASH_FROM_OPER(FPT=BA, FPR=2022, FYE=C1231, AE=A)", "currency=USD")/1000000000} -> 8.1110476 | BA10: {=_xll.BQL($C10, "CF_CASH_FROM_OPER(FPT=BA, FPR=2023, FYE=C1231, AE=A)", "currency=USD")/1000000000} -> 11.855583 | BB10: {=_xll.BQL($C10, "CF_CASH_FROM_OPER(FPT=BA, FPR=2024, FYE=C1231, AE=A)", "currency=USD")/1000000000} -> 10.853845 | BC10: {=_xll.BQL($C10, "CF_CASH_FROM_OPER(FPT=BA, FPR=2025, FYE=C1231, AE=E)", "currency=USD")/1000000000} -> 12.776401 | BD10: {=_xll.BQL($C10, "CF_CASH_FROM_OPER(FPT=BA, FPR=2026, FYE=C1231, AE=E)", "currency=USD")/1000000000} -> 14.729238 | BE10: {=_xll.BQL($C10, "CF_CASH_FROM_OPER(FPT=BA, FPR=2027, FYE=C1231, AE=E)", "currency=USD")/1000000000} -> 15.302553 | BF10: {=_xll.BQL($C10, "CF_FREE_CASH_FLOW(FPT=BA, FPR=2022, FYE=C1231, AE=A)", "currency=USD")/1000000000} -> 4.1279286 | BG10: {=_xll.BQL($C10, "CF_FREE_CASH_FLOW(FPT=BA, FPR=2023, FYE=C1231, AE=A)", "currency=USD")/1000000000} -> 7.5544048 | BH10: {=_xll.BQL($C10, "CF_FREE_CASH_FLOW(FPT=BA, FPR=2024, FYE=C1231, AE=A)", "currency=USD")/1000000000} -> 5.8486071 | BI10: {=_xll.BQL($C10, "CF_FREE_CASH_FLOW(FPT=BA, FPR=2025, FYE=C1231, AE=E)", "currency=USD")/1000000000} -> 6.8187958 | BJ10: {=_xll.BQL($C10, "CF_FREE_CASH_FLOW(FPT=BA, FPR=2026, FYE=C1231, AE=E)", "currency=USD")/1000000000} -> 7.5226847 | BK10: {=_xll.BQL($C10, "CF_FREE_CASH_FLOW(FPT=BA, FPR=2027, FYE=C1231, AE=E)", "currency=USD")/1000000000} -> 8.8964661 | BL10: {=_xll.BQL($C10, "SALES_REV_TURN(FPT=BA, FPR=2022, FYE=C1231, AE=A)", "currency=USD")/1000000000} -> 233.28688 | BM10: {=_xll.BQL($C10, "SALES_REV_TURN(FPT=BA, FPR=2023, FYE=C1231, AE=A)", "currency=USD")/1000000000} -> 243.02776 | BN10: {=_xll.BQL($C10, "SALES_REV_TURN(FPT=BA, FPR=2024, FYE=C1231, AE=A)", "currency=USD")/1000000000} -> 262.52263 | BO10: {=_xll.BQL($C10, "SALES_REV_TURN(FPT=BA, FPR=2025, FYE=C1231, AE=E)", "currency=USD")/1000000000} -> 282.94784 | BP10: {=_xll.BQL($C10, "SALES_REV_TURN(FPT=BA, FPR=2026, FYE=C1231, AE=E)", "currency=USD")/1000000000} -> 309.22533 | BQ10: {=_xll.BQL($C10, "SALES_REV_TURN(FPT=BA, FPR=2027, FYE=C1231, AE=E)", "currency=USD")/1000000000} -> 334.30408 | BR10: {=_xll.BQL($C10, "EBITDA(FPT=BA, FPR=2022, FYE=C1231, AE=A)", "currency=USD")/1000000000} -> 9.8537738 | BS10: {=_xll.BQL($C10, "EBITDA(FPT=BA, FPR=2023, FYE=C1231, AE=A)", "currency=USD")/1000000000} -> 10.393083 | BT10: {=_xll.BQL($C10, "EBITDA(FPT=BA, FPR=2024, FYE=C1231, AE=A)", "currency=USD")/1000000000} -> 11.970952 | BU10: {=_xll.BQL($C10, "EBITDA(FPT=BA, FPR=2025, FYE=C1231, AE=E)", "currency=USD")/1000000000} -> 13.17599 | BV10: {=_xll.BQL($C10, "EBITDA(FPT=BA, FPR=2026, FYE=C1231, AE=E)", "currency=USD")/1000000000} -> 14.717967 | BW10: {=_xll.BQL($C10, "EBITDA(FPT=BA, FPR=2027, FYE=C1231, AE=E)", "currency=USD")/1000000000} -> 16.106845 | BX10: {=_xll.BQL($C10, "NET_INCOME(FPT=BA, FPR=2022, FYE=C1231, AE=A)", "currency=USD")/1000000000} -> 5.9809762 | BY10: {=_xll.BQL($C10, "NET_INCOME(FPT=BA, FPR=2023, FYE=C1231, AE=A)", "currency=USD")/1000000000} -> 6.5277024 | BZ10: {=_xll.BQL($C10, "NET_INCOME(FPT=BA, FPR=2024, FYE=C1231, AE=A)", "currency=USD")/1000000000} -> 7.6373214 | CA10: {=_xll.BQL($C10, "NET_INCOME(FPT=BA, FPR=2025, FYE=C1231, AE=E)", "currency=USD")/1000000000} -> 8.3099475 | CB10: {=_xll.BQL($C10, "NET_INCOME(FPT=BA, FPR=2026, FYE=C1231, AE=E)", "currency=USD")/1000000000} -> 9.4183377 | CC10: {=_xll.BQL($C10, "NET_INCOME(FPT=BA, FPR=2027, FYE=C1231, AE=E)", "currency=USD")/1000000000} -> 10.381945 | CD10: {=-_xll.BQL($C10, "CF_DVD_PAID(FPT=BA, FPR=2024, FYE=C1231, AE=A)", "currency=USD")/1000000000} -> 5.68975 | CE10: {=-_xll.BQL($C10, "CF_DVD_PAID(FPT=BA, FPR=2025, FYE=C1231, AE=E)", "currency=USD")/1000000000} -> 2.3518354 | CF10: {=-_xll.BQL($C10, "CF_DVD_PAID(FPT=BA, FPR=2026, FYE=C1231, AE=E)", "currency=USD")/1000000000} -> 4.3629676 | CG10: {=-_xll.BQL($C10, "CF_DVD_PAID(FPT=BA, FPR=2027, FYE=C1231, AE=E)", "currency=USD")/1000000000} -> 3.0642975 | CH10: =CD10/$F10 -> 1.1719413e-05 | CI10: =CE10/$F10 -> 4.8441727e-06 | CJ10: =CF10/$F10 -> 8.9865848e-06 | CK10: =CG10/$F10 -> 6.3116603e-06 | CL10: {=_xll.BDP($C10,"INTERVAL_AVG", "MARKET_DATA_OVERRIDE=turnover", "CALC_INTERVAL=5D","CRNCY=HKD")/1000000} -> 18203.075 | CM10: {=_xll.BDP($C10,"INTERVAL_AVG", "MARKET_DATA_OVERRIDE=turnover", "CALC_INTERVAL=10D","CRNCY=HKD")/1000000} -> 16602.223 | CN10: {=_xll.BDP($C10,"INTERVAL_AVG", "MARKET_DATA_OVERRIDE=turnover", "CALC_INTERVAL=20D","CRNCY=HKD")/1000000} -> 15043.904 | CO10: {=_xll.BDP($C10,"INTERVAL_AVG", "MARKET_DATA_OVERRIDE=turnover", "CALC_INTERVAL=1m","CRNCY=HKD")/1000000} -> 14440.37 | CP10: {=_xll.BDP($C10,"INTERVAL_AVG", "MARKET_DATA_OVERRIDE=turnover", "CALC_INTERVAL=3M","CRNCY=HKD")/1000000} -> 14496.744 | CQ10: {=_xll.BDP($C10,"INTERVAL_AVG", "MARKET_DATA_OVERRIDE=turnover", "CALC_INTERVAL=6M","CRNCY=HKD")/1000000} -> 16842.298 | CR10: =_xll.BDP($C10,"chg pct 1m")/100 -> 0.09668882 | CS10: =_xll.BDP($C10,"chg pct 3m")/100 -> 0.1106803 | CT10: =_xll.BDP($C10,"chg pct 6m")/100 -> 0.2250445 | CU10: =_xll.BDP($C10,"chg pct 1yr")/100 -> 0.05545809 | CV10: =_xll.BDP($C10,"chg pct ytd")/100 -> 0.2690122 | CW10: {=_xll.BQL($C10, "volatility(calc_interval=range(-1M, 0D))")} -> 0.18496035 | CX10: {=_xll.BQL($C10, "volatility(calc_interval=range(-3M, 0D))")} -> 0.18377653 | CY10: {=_xll.BQL($C10, "volatility(calc_interval=range(-6M, 0D))")} -> 0.1952656 | CZ10: =_xll.BDP($C10,CZ$1) -> Costco Wholesale Corporation is a membership warehouse club The Company sells all kinds of food, automotive supplies, toys, hardware, sporting goods, jewelry, electronics, apparel, health, and beauty aids, as well as other goods. Costco Wholesale serves customers worldwide.
A11: =_xll.BDP($C11,"security name") -> Associated British Foods PLC | B11: =_xll.BDP($C11,"NAME_CHINESE_SIMPLIFIED") -> 英国联合食品公共有限公司 | C11: abf ln EQUITY | D11: =_xll.BDP($C11,"LISTING_DATE") -> #N/A Field Not Applicable | E11: =_xll.BDP($C11,E$1,"EQY_FUND_CRNCY="&$B$1) -> 135311.2 | F11: =_xll.BDP($C11,F$1,"EQY_FUND_CRNCY="&$C$1) -> 17272.3 | G11: =_xll.BDP($C11,G$1) -> 1833 | H11: =_xll.BDP($C11,H$1,"EQY_FUND_CRNCY="&$B$1) -> 118036.02 | I11: =_xll.BDP($C11,I$1,"EQY_FUND_CRNCY="&$C$1) -> 15168.216 | J11: =_xll.BDP($C11,J$1,"EQY_FUND_CRNCY="&$B$1) -> 198050.84 | K11: =_xll.BDP($C11,K$1,"EQY_FUND_CRNCY="&$C$1) -> 25404.338 | L11: =_xll.BDP($C11,L$1,"EQY_FUND_CRNCY="&$B$1) -> 10432.299 | M11: =_xll.BDP($C11,M$1,"EQY_FUND_CRNCY="&$C$1) -> 1338.1698 | N11: =_xll.BDP($C11,N$1)/100 -> 0.23922093 | O11: =_xll.BDP($C11,O$1)/100 -> 0.13253507 | P11: =_xll.BDP($C11,P$1)/100 -> 0.052674855 | Q11: =_xll.BDP($C11,Q$1)/100 -> -0.027195921 | R11: =_xll.BDP($C11,R$1)/100 -> -0.29553265 | S11: =_xll.BDP($C11,S$1)/100 -> 0.32951904 | T11: =_xll.BDP($C11,T$1)/100 -> 0.33330319 | U11: =_xll.BDP($C11,U$1)/100 -> 0.23502593 | ... W11: =_xll.BDP($C11,W$1)/100 -> 0.049596701 | X11: {=_xll.BDP($C11,"CRNCY_ADJ_CURR_EV", "EQY_FUND_CRNCY=HKD")} -> 168838.28 | Y11: {=_xll.BDP($C11,"CRNCY_ADJ_CURR_EV", "EQY_FUND_CRNCY=USD")} -> 21558.665 | Z11: =_xll.BDP($C11,Z$1)/100 -> 0.084613672 | AA11: =_xll.BDP($C11,"TRAIL_12M_NET_SALES","EQY_FUND_CRNCY=HKD") -> 202525.2 | AB11: =_xll.BDP($C11,"TRAIL_12M_NET_INC","EQY_FUND_CRNCY=HKD") -> 9907.2577 | AC11: =_xll.BDP($C11,"TRAIL_12M_EBITDA","EQY_FUND_CRNCY=HKD") -> 24622.143 | AD11: =IF(AB11<0,"N/A",$E11/AB11) -> 13.657785 | AE11: {=_xll.BQL($C11, "PE_RATIO(FPT=BA, FPR=2026, FYE=C1231, AE=E)")} -> 11.27466 | AF11: {=_xll.BQL($C11, "PE_RATIO(FPT=BA, FPR=2027, FYE=C1231, AE=E)")} -> 10.646149 | AG11: =$E11/AA11 -> 0.66812028 | AH11: {=_xll.BQL($C11, "PX_TO_SALES_RATIO(FPT=BA, FPR=2026, FYE=C1231, AE=E)")} -> 0.68200855 | AI11: {=_xll.BQL($C11, "PX_TO_SALES_RATIO(FPT=BA, FPR=2027, FYE=C1231, AE=E)")} -> 0.644861 | AJ11: =IF(AC11<0,"N/A",$X11/AC11) -> 6.8571725 | AK11: {=IF(_xll.BQL($C11, "CURR_ENTP_VAL(FPT=A,FPO=0)/EBITDA(FPT=BA, FPR=2026, FYE=C1231, AE=E)")<0,"N/A",_xll.BQL($C11, "CURR_ENTP_VAL(FPT=A,FPO=0)/EBITDA(FPT=BA, FPR=2026, FYE=C1231, AE=E)"))} -> 7.290167 | AL11: {=IF(_xll.BQL($C11, "CURR_ENTP_VAL(FPT=A,FPO=0)/EBITDA(FPT=BA, FPR=2027, FYE=C1231, AE=E)")<0,"N/A",_xll.BQL($C11, "CURR_ENTP_VAL(FPT=A,FPO=0)/EBITDA(FPT=BA, FPR=2027, FYE=C1231, AE=E)"))} -> 6.9691059 | AM11: =_xll.BDP($C11,AM$1) -> 1.1298633 | AN11: {=_xll.BQL($C11, "PX_TO_BOOK_RATIO(FPT=BA, FPR=2026, FYE=C1231, AE=E)")} -> 1.1192199 | AO11: {=_xll.BQL($C11, "PX_TO_BOOK_RATIO(FPT=BA, FPR=2027, FYE=C1231, AE=E)")} -> 1.0494899 | AP11: =_xll.BDP($C11,"BEST Px bps ratio","BEST fperiod override","27Y") -> 1.0751994 | AQ11: =Z11 -> 0.084613672 | AR11: =_xll.BDP($C11,"BEST_ROE","BEST fperiod override","26Y")/100 -> 0.09814 | AS11: =_xll.BDP($C11,"BEST_ROE","BEST fperiod override","27Y")/100 -> 0.10043 | AT11: =_xll.BDP($C11,AT$1) -> 3.4369885 | AU11: =_xll.BDP($C11,$AU$1,"BEST fperiod override","26Y") -> 3.2460447 | AV11: =_xll.BDP($C11,$AU$1,"BEST fperiod override","27Y") -> 3.3715221 | AW11: =(BP11/BN11)^(1/2)-1 -> 0.0023239674 | AX11: =(BV11/BT11)^(1/2)-1 -> 0.0087649321 | AY11: =(CB11/BZ11)^(1/2)-1 -> -0.10748368 | AZ11: {=_xll.BQL($C11, "CF_CASH_FROM_OPER(FPT=BA, FPR=2022, FYE=C1231, AE=A)", "currency=USD")/1000000000} -> 1.1691067 | BA11: {=_xll.BQL($C11, "CF_CASH_FROM_OPER(FPT=BA, FPR=2023, FYE=C1231, AE=A)", "currency=USD")/1000000000} -> 2.9357923 | BB11: {=_xll.BQL($C11, "CF_CASH_FROM_OPER(FPT=BA, FPR=2024, FYE=C1231, AE=A)", "currency=USD")/1000000000} -> 3.3824466 | BC11: {=_xll.BQL($C11, "CF_CASH_FROM_OPER(FPT=BA, FPR=2025, FYE=C1231, AE=E)", "currency=USD")/1000000000} -> 2.3953424 | BD11: {=_xll.BQL($C11, "CF_CASH_FROM_OPER(FPT=BA, FPR=2026, FYE=C1231, AE=E)", "currency=USD")/1000000000} -> 1.9686017 | BE11: {=_xll.BQL($C11, "CF_CASH_FROM_OPER(FPT=BA, FPR=2027, FYE=C1231, AE=E)", "currency=USD")/1000000000} -> 2.0516051 | BF11: {=_xll.BQL($C11, "CF_FREE_CASH_FLOW(FPT=BA, FPR=2022, FYE=C1231, AE=A)", "currency=USD")/1000000000} -> 0.21227288 | BG11: {=_xll.BQL($C11, "CF_FREE_CASH_FLOW(FPT=BA, FPR=2023, FYE=C1231, AE=A)", "currency=USD")/1000000000} -> 1.621035 | BH11: {=_xll.BQL($C11, "CF_FREE_CASH_FLOW(FPT=BA, FPR=2024, FYE=C1231, AE=A)", "currency=USD")/1000000000} -> 1.9691316 | BI11: {=_xll.BQL($C11, "CF_FREE_CASH_FLOW(FPT=BA, FPR=2025, FYE=C1231, AE=E)", "currency=USD")/1000000000} -> 0.91571912 | BJ11: {=_xll.BQL($C11, "CF_FREE_CASH_FLOW(FPT=BA, FPR=2026, FYE=C1231, AE=E)", "currency=USD")/1000000000} -> 0.94270928 | BK11: {=_xll.BQL($C11, "CF_FREE_CASH_FLOW(FPT=BA, FPR=2027, FYE=C1231, AE=E)", "currency=USD")/1000000000} -> 0.92799304 | BL11: {=_xll.BQL($C11, "SALES_REV_TURN(FPT=BA, FPR=2022, FYE=C1231, AE=A)", "currency=USD")/1000000000} -> 21.937978 | BM11: {=_xll.BQL($C11, "SALES_REV_TURN(FPT=BA, FPR=2023, FYE=C1231, AE=A)", "currency=USD")/1000000000} -> 24.950845 | BN11: {=_xll.BQL($C11, "SALES_REV_TURN(FPT=BA, FPR=2024, FYE=C1231, AE=A)", "currency=USD")/1000000000} -> 25.454993 | BO11: {=_xll.BQL($C11, "SALES_REV_TURN(FPT=BA, FPR=2025, FYE=C1231, AE=E)", "currency=USD")/1000000000} -> 26.137291 | BP11: {=_xll.BQL($C11, "SALES_REV_TURN(FPT=BA, FPR=2026, FYE=C1231, AE=E)", "currency=USD")/1000000000} -> 25.573444 | BQ11: {=_xll.BQL($C11, "SALES_REV_TURN(FPT=BA, FPR=2027, FYE=C1231, AE=E)", "currency=USD")/1000000000} -> 27.046615 | BR11: {=_xll.BQL($C11, "EBITDA(FPT=BA, FPR=2022, FYE=C1231, AE=A)", "currency=USD")/1000000000} -> 2.3553044 | BS11: {=_xll.BQL($C11, "EBITDA(FPT=BA, FPR=2023, FYE=C1231, AE=A)", "currency=USD")/1000000000} -> 2.9400949 | BT11: {=_xll.BQL($C11, "EBITDA(FPT=BA, FPR=2024, FYE=C1231, AE=A)", "currency=USD")/1000000000} -> 3.3878779 | BU11: {=_xll.BQL($C11, "EBITDA(FPT=BA, FPR=2025, FYE=C1231, AE=E)", "currency=USD")/1000000000} -> 3.5387547 | BV11: {=_xll.BQL($C11, "EBITDA(FPT=BA, FPR=2026, FYE=C1231, AE=E)", "currency=USD")/1000000000} -> 3.4475273 | BW11: {=_xll.BQL($C11, "EBITDA(FPT=BA, FPR=2027, FYE=C1231, AE=E)", "currency=USD")/1000000000} -> 3.6063521 | BX11: {=_xll.BQL($C11, "NET_INCOME(FPT=BA, FPR=2022, FYE=C1231, AE=A)", "currency=USD")/1000000000} -> 0.890859 | BY11: {=_xll.BQL($C11, "NET_INCOME(FPT=BA, FPR=2023, FYE=C1231, AE=A)", "currency=USD")/1000000000} -> 1.4193107 | BZ11: {=_xll.BQL($C11, "NET_INCOME(FPT=BA, FPR=2024, FYE=C1231, AE=A)", "currency=USD")/1000000000} -> 1.7471448 | CA11: {=_xll.BQL($C11, "NET_INCOME(FPT=BA, FPR=2025, FYE=C1231, AE=E)", "currency=USD")/1000000000} -> 1.5377899 | CB11: {=_xll.BQL($C11, "NET_INCOME(FPT=BA, FPR=2026, FYE=C1231, AE=E)", "currency=USD")/1000000000} -> 1.39175 | CC11: {=_xll.BQL($C11, "NET_INCOME(FPT=BA, FPR=2027, FYE=C1231, AE=E)", "currency=USD")/1000000000} -> 1.4961078 | CD11: {=-_xll.BQL($C11, "CF_DVD_PAID(FPT=BA, FPR=2024, FYE=C1231, AE=A)", "currency=USD")/1000000000} -> 0.77610423 | CE11: {=-_xll.BQL($C11, "CF_DVD_PAID(FPT=BA, FPR=2025, FYE=C1231, AE=E)", "currency=USD")/1000000000} -> 0.49583445 | CF11: {=-_xll.BQL($C11, "CF_DVD_PAID(FPT=BA, FPR=2026, FYE=C1231, AE=E)", "currency=USD")/1000000000} -> 0.55177703 | CG11: {=-_xll.BQL($C11, "CF_DVD_PAID(FPT=BA, FPR=2027, FYE=C1231, AE=E)", "currency=USD")/1000000000} -> 0.47900223 | CH11: =CD11/$F11 -> 4.4933463e-05 | CI11: =CE11/$F11 -> 2.8706916e-05 | CJ11: =CF11/$F11 -> 3.1945777e-05 | CK11: =CG11/$F11 -> 2.7732395e-05 | CL11: {=_xll.BDP($C11,"INTERVAL_AVG", "MARKET_DATA_OVERRIDE=turnover", "CALC_INTERVAL=5D","CRNCY=HKD")/1000000} -> 129.2982 | CM11: {=_xll.BDP($C11,"INTERVAL_AVG", "MARKET_DATA_OVERRIDE=turnover", "CALC_INTERVAL=10D","CRNCY=HKD")/1000000} -> 135.86173 | CN11: {=_xll.BDP($C11,"INTERVAL_AVG", "MARKET_DATA_OVERRIDE=turnover", "CALC_INTERVAL=20D","CRNCY=HKD")/1000000} -> 149.59612 | CO11: {=_xll.BDP($C11,"INTERVAL_AVG", "MARKET_DATA_OVERRIDE=turnover", "CALC_INTERVAL=1m","CRNCY=HKD")/1000000} -> 163.17554 | CP11: {=_xll.BDP($C11,"INTERVAL_AVG", "MARKET_DATA_OVERRIDE=turnover", "CALC_INTERVAL=3M","CRNCY=HKD")/1000000} -> 160.5872 | CQ11: {=_xll.BDP($C11,"INTERVAL_AVG", "MARKET_DATA_OVERRIDE=turnover", "CALC_INTERVAL=6M","CRNCY=HKD")/1000000} -> 154.51915 | CR11: =_xll.BDP($C11,"chg pct 1m")/100 -> -0.02758621 | CS11: =_xll.BDP($C11,"chg pct 3m")/100 -> -0.06168416 | CT11: =_xll.BDP($C11,"chg pct 6m")/100 -> -0.126727 | CU11: =_xll.BDP($C11,"chg pct 1yr")/100 -> -0.1390324 | CV11: =_xll.BDP($C11,"chg pct ytd")/100 -> -0.1382228 | CW11: {=_xll.BQL($C11, "volatility(calc_interval=range(-1M, 0D))")} -> 0.21825153 | CX11: {=_xll.BQL($C11, "volatility(calc_interval=range(-3M, 0D))")} -> 0.21275675 | CY11: {=_xll.BQL($C11, "volatility(calc_interval=range(-6M, 0D))")} -> 0.2706094 | CZ11: =_xll.BDP($C11,CZ$1) -> Associated British Foods PLC operates as a group company. The Company, through its subsidiaries, offers groceries, clothing, and household products, as well as produces sugar and baker's yeast ingredients including emulsifiers, enzymes, and lactose. Associated British Foods serves customers worldwide.
A12: =_xll.BDP($C12,"security name") -> Manhattan Associates Inc | B12: =_xll.BDP($C12,"NAME_CHINESE_SIMPLIFIED") -> 曼哈顿联合软件公司 | C12: MANH US EQUITY | D12: =_xll.BDP($C12,"LISTING_DATE") -> 4/23/1998 | E12: =_xll.BDP($C12,E$1,"EQY_FUND_CRNCY="&$B$1) -> 62764.157 | F12: =_xll.BDP($C12,F$1,"EQY_FUND_CRNCY="&$C$1) -> 8012.0704 | G12: =_xll.BDP($C12,G$1) -> 135.42 | H12: =_xll.BDP($C12,H$1,"EQY_FUND_CRNCY="&$B$1) -> 2450.0993 | I12: =_xll.BDP($C12,I$1,"EQY_FUND_CRNCY="&$C$1) -> 314.765 | J12: =_xll.BDP($C12,J$1,"EQY_FUND_CRNCY="&$B$1) -> 8430.351 | K12: =_xll.BDP($C12,K$1,"EQY_FUND_CRNCY="&$C$1) -> 1081.392 | L12: =_xll.BDP($C12,L$1,"EQY_FUND_CRNCY="&$B$1) -> 1714.6778 | M12: =_xll.BDP($C12,M$1,"EQY_FUND_CRNCY="&$C$1) -> 219.948 | N12: =_xll.BDP($C12,N$1)/100 -> 0.56321205 | O12: =_xll.BDP($C12,O$1)/100 -> 0.26997703 | P12: =_xll.BDP($C12,P$1)/100 -> 0.2033934 | Q12: =_xll.BDP($C12,Q$1)/100 -> 0.037453758 | R12: =_xll.BDP($C12,R$1)/100 -> 0.007253943 | S12: =_xll.BDP($C12,S$1)/100 -> 0.19399552 | T12: =_xll.BDP($C12,T$1)/100 -> 0.19399552 | U12: =_xll.BDP($C12,U$1)/100 -> -0.85042492 | ... W12: =_xll.BDP($C12,W$1)/100 -> 0.29909875 | X12: {=_xll.BDP($C12,"CRNCY_ADJ_CURR_EV", "EQY_FUND_CRNCY=HKD")} -> 61427.69 | Y12: {=_xll.BDP($C12,"CRNCY_ADJ_CURR_EV", "EQY_FUND_CRNCY=USD")} -> 7841.6224 | Z12: =_xll.BDP($C12,Z$1)/100 -> 0.96236036 | AA12: =_xll.BDP($C12,"TRAIL_12M_NET_SALES","EQY_FUND_CRNCY=HKD") -> 8590.7453 | AB12: =_xll.BDP($C12,"TRAIL_12M_NET_INC","EQY_FUND_CRNCY=HKD") -> 1690.8118 | AC12: =_xll.BDP($C12,"TRAIL_12M_EBITDA","EQY_FUND_CRNCY=HKD") -> 2248.8958 | AD12: =IF(AB12<0,"N/A",$E12/AB12) -> 37.120723 | AE12: {=_xll.BQL($C12, "PE_RATIO(FPT=BA, FPR=2026, FYE=C1231, AE=E)")} -> 25.272783 | AF12: {=_xll.BQL($C12, "PE_RATIO(FPT=BA, FPR=2027, FYE=C1231, AE=E)")} -> 22.705603 | AG12: =$E12/AA12 -> 7.30602 | AH12: {=_xll.BQL($C12, "PX_TO_SALES_RATIO(FPT=BA, FPR=2026, FYE=C1231, AE=E)")} -> 6.9463799 | AI12: {=_xll.BQL($C12, "PX_TO_SALES_RATIO(FPT=BA, FPR=2027, FYE=C1231, AE=E)")} -> 6.3989913 | AJ12: =IF(AC12<0,"N/A",$X12/AC12) -> 27.314601 | AK12: {=IF(_xll.BQL($C12, "CURR_ENTP_VAL(FPT=A,FPO=0)/EBITDA(FPT=BA, FPR=2026, FYE=C1231, AE=E)")<0,"N/A",_xll.BQL($C12, "CURR_ENTP_VAL(FPT=A,FPO=0)/EBITDA(FPT=BA, FPR=2026, FYE=C1231, AE=E)"))} -> 22.767815 | AL12: {=IF(_xll.BQL($C12, "CURR_ENTP_VAL(FPT=A,FPO=0)/EBITDA(FPT=BA, FPR=2027, FYE=C1231, AE=E)")<0,"N/A",_xll.BQL($C12, "CURR_ENTP_VAL(FPT=A,FPO=0)/EBITDA(FPT=BA, FPR=2027, FYE=C1231, AE=E)"))} -> 20.555926 | AM12: =_xll.BDP($C12,AM$1) -> 39.049862 | AN12: {=_xll.BQL($C12, "PX_TO_BOOK_RATIO(FPT=BA, FPR=2026, FYE=C1231, AE=E)")} -> 28.509473 | AO12: {=_xll.BQL($C12, "PX_TO_BOOK_RATIO(FPT=BA, FPR=2027, FYE=C1231, AE=E)")} -> 12.603071 | AP12: =_xll.BDP($C12,"BEST Px bps ratio","BEST fperiod override","27Y") -> 26.244186 | AQ12: =Z12 -> 0.96236036 | AR12: =_xll.BDP($C12,"BEST_ROE","BEST fperiod override","26Y")/100 -> 1.05773 | AS12: =_xll.BDP($C12,"BEST_ROE","BEST fperiod override","27Y")/100 -> 1.47583 | AT12: =_xll.BDP($C12,AT$1) -> #N/A N/A | AU12: =_xll.BDP($C12,$AU$1,"BEST fperiod override","26Y") -> 0 | AV12: =_xll.BDP($C12,$AU$1,"BEST fperiod override","27Y") -> 0 | AW12: =(BP12/BN12)^(1/2)-1 -> 0.051927743 | AX12: =(BV12/BT12)^(1/2)-1 -> 0.21950629 | AY12: =(CB12/BZ12)^(1/2)-1 -> 0.0073823964 | AZ12: {=_xll.BQL($C12, "CF_CASH_FROM_OPER(FPT=BA, FPR=2022, FYE=C1231, AE=A)", "currency=USD")/1000000000} -> 0.17963 | BA12: {=_xll.BQL($C12, "CF_CASH_FROM_OPER(FPT=BA, FPR=2023, FYE=C1231, AE=A)", "currency=USD")/1000000000} -> 0.246218 | BB12: {=_xll.BQL($C12, "CF_CASH_FROM_OPER(FPT=BA, FPR=2024, FYE=C1231, AE=A)", "currency=USD")/1000000000} -> 0.295003 | BC12: {=_xll.BQL($C12, "CF_CASH_FROM_OPER(FPT=BA, FPR=2025, FYE=C1231, AE=E)", "currency=USD")/1000000000} -> 0.33073013 | BD12: {=_xll.BQL($C12, "CF_CASH_FROM_OPER(FPT=BA, FPR=2026, FYE=C1231, AE=E)", "currency=USD")/1000000000} -> 0.38220333 | BE12: {=_xll.BQL($C12, "CF_CASH_FROM_OPER(FPT=BA, FPR=2027, FYE=C1231, AE=E)", "currency=USD")/1000000000} -> 0.41356057 | BF12: {=_xll.BQL($C12, "CF_FREE_CASH_FLOW(FPT=BA, FPR=2022, FYE=C1231, AE=A)", "currency=USD")/1000000000} -> 0.173043 | BG12: {=_xll.BQL($C12, "CF_FREE_CASH_FLOW(FPT=BA, FPR=2023, FYE=C1231, AE=A)", "currency=USD")/1000000000} -> 0.241488 | BH12: {=_xll.BQL($C12, "CF_FREE_CASH_FLOW(FPT=BA, FPR=2024, FYE=C1231, AE=A)", "currency=USD")/1000000000} -> 0.286328 | BI12: {=_xll.BQL($C12, "CF_FREE_CASH_FLOW(FPT=BA, FPR=2025, FYE=C1231, AE=E)", "currency=USD")/1000000000} -> 0.3199796 | BJ12: {=_xll.BQL($C12, "CF_FREE_CASH_FLOW(FPT=BA, FPR=2026, FYE=C1231, AE=E)", "currency=USD")/1000000000} -> 0.37471904 | BK12: {=_xll.BQL($C12, "CF_FREE_CASH_FLOW(FPT=BA, FPR=2027, FYE=C1231, AE=E)", "currency=USD")/1000000000} -> 0.41477038 | BL12: {=_xll.BQL($C12, "SALES_REV_TURN(FPT=BA, FPR=2022, FYE=C1231, AE=A)", "currency=USD")/1000000000} -> 0.767084 | BM12: {=_xll.BQL($C12, "SALES_REV_TURN(FPT=BA, FPR=2023, FYE=C1231, AE=A)", "currency=USD")/1000000000} -> 0.928725 | BN12: {=_xll.BQL($C12, "SALES_REV_TURN(FPT=BA, FPR=2024, FYE=C1231, AE=A)", "currency=USD")/1000000000} -> 1.042352 | BO12: {=_xll.BQL($C12, "SALES_REV_TURN(FPT=BA, FPR=2025, FYE=C1231, AE=E)", "currency=USD")/1000000000} -> 1.0758333 | BP12: {=_xll.BQL($C12, "SALES_REV_TURN(FPT=BA, FPR=2026, FYE=C1231, AE=E)", "currency=USD")/1000000000} -> 1.1534167 | BQ12: {=_xll.BQL($C12, "SALES_REV_TURN(FPT=BA, FPR=2027, FYE=C1231, AE=E)", "currency=USD")/1000000000} -> 1.2520833 | BR12: {=_xll.BQL($C12, "EBITDA(FPT=BA, FPR=2022, FYE=C1231, AE=A)", "currency=USD")/1000000000} -> 0.166663 | BS12: {=_xll.BQL($C12, "EBITDA(FPT=BA, FPR=2023, FYE=C1231, AE=A)", "currency=USD")/1000000000} -> 0.223433 | BT12: {=_xll.BQL($C12, "EBITDA(FPT=BA, FPR=2024, FYE=C1231, AE=A)", "currency=USD")/1000000000} -> 0.276897 | BU12: {=_xll.BQL($C12, "EBITDA(FPT=BA, FPR=2025, FYE=C1231, AE=E)", "currency=USD")/1000000000} -> 0.391 | BV12: {=_xll.BQL($C12, "EBITDA(FPT=BA, FPR=2026, FYE=C1231, AE=E)", "currency=USD")/1000000000} -> 0.4118 | BW12: {=_xll.BQL($C12, "EBITDA(FPT=BA, FPR=2027, FYE=C1231, AE=E)", "currency=USD")/1000000000} -> 0.45611111 | BX12: {=_xll.BQL($C12, "NET_INCOME(FPT=BA, FPR=2022, FYE=C1231, AE=A)", "currency=USD")/1000000000} -> 0.128959 | BY12: {=_xll.BQL($C12, "NET_INCOME(FPT=BA, FPR=2023, FYE=C1231, AE=A)", "currency=USD")/1000000000} -> 0.176568 | BZ12: {=_xll.BQL($C12, "NET_INCOME(FPT=BA, FPR=2024, FYE=C1231, AE=A)", "currency=USD")/1000000000} -> 0.218364 | CA12: {=_xll.BQL($C12, "NET_INCOME(FPT=BA, FPR=2025, FYE=C1231, AE=E)", "currency=USD")/1000000000} -> 0.2144 | CB12: {=_xll.BQL($C12, "NET_INCOME(FPT=BA, FPR=2026, FYE=C1231, AE=E)", "currency=USD")/1000000000} -> 0.2216 | CC12: {=_xll.BQL($C12, "NET_INCOME(FPT=BA, FPR=2027, FYE=C1231, AE=E)", "currency=USD")/1000000000} -> 0.2537 | CD12: {=-_xll.BQL($C12, "CF_DVD_PAID(FPT=BA, FPR=2024, FYE=C1231, AE=A)", "currency=USD")/1000000000} -> 0 | CE12: {=-_xll.BQL($C12, "CF_DVD_PAID(FPT=BA, FPR=2025, FYE=C1231, AE=E)", "currency=USD")/1000000000} -> #VALUE! | CF12: {=-_xll.BQL($C12, "CF_DVD_PAID(FPT=BA, FPR=2026, FYE=C1231, AE=E)", "currency=USD")/1000000000} -> #VALUE! | CG12: {=-_xll.BQL($C12, "CF_DVD_PAID(FPT=BA, FPR=2027, FYE=C1231, AE=E)", "currency=USD")/1000000000} -> #VALUE! | CH12: =CD12/$F12 -> 0 | CI12: =CE12/$F12 -> #VALUE! | CJ12: =CF12/$F12 -> #VALUE! | CK12: =CG12/$F12 -> #VALUE! | CL12: {=_xll.BDP($C12,"INTERVAL_AVG", "MARKET_DATA_OVERRIDE=turnover", "CALC_INTERVAL=5D","CRNCY=HKD")/1000000} -> 570.01422 | CM12: {=_xll.BDP($C12,"INTERVAL_AVG", "MARKET_DATA_OVERRIDE=turnover", "CALC_INTERVAL=10D","CRNCY=HKD")/1000000} -> 599.99188 | CN12: {=_xll.BDP($C12,"INTERVAL_AVG", "MARKET_DATA_OVERRIDE=turnover", "CALC_INTERVAL=20D","CRNCY=HKD")/1000000} -> 758.0417 | CO12: {=_xll.BDP($C12,"INTERVAL_AVG", "MARKET_DATA_OVERRIDE=turnover", "CALC_INTERVAL=1m","CRNCY=HKD")/1000000} -> 801.78106 | CP12: {=_xll.BDP($C12,"INTERVAL_AVG", "MARKET_DATA_OVERRIDE=turnover", "CALC_INTERVAL=3M","CRNCY=HKD")/1000000} -> 751.70417 | CQ12: {=_xll.BDP($C12,"INTERVAL_AVG", "MARKET_DATA_OVERRIDE=turnover", "CALC_INTERVAL=6M","CRNCY=HKD")/1000000} -> 834.43368 | CR12: =_xll.BDP($C12,"chg pct 1m")/100 -> 0.01188073 | CS12: =_xll.BDP($C12,"chg pct 3m")/100 -> -0.06134334 | CT12: =_xll.BDP($C12,"chg pct 6m")/100 -> -0.1971305 | CU12: =_xll.BDP($C12,"chg pct 1yr")/100 -> -0.2941361 | CV12: =_xll.BDP($C12,"chg pct ytd")/100 -> -0.2186256 | CW12: {=_xll.BQL($C12, "volatility(calc_interval=range(-1M, 0D))")} -> 0.51654275 | CX12: {=_xll.BQL($C12, "volatility(calc_interval=range(-3M, 0D))")} -> 0.49307174 | CY12: {=_xll.BQL($C12, "volatility(calc_interval=range(-6M, 0D))")} -> 0.43677486 | CZ12: =_xll.BDP($C12,CZ$1) -> Manhattan Associates, Inc. provides information technology solutions for distribution centers. The solutions are designed to enable the efficient movement of goods through the supply chain. The Company offers solutions optimize the receipt, storage, and distribution of inventory, as well as manage equipment and personnel within a distribution center.
A13: =_xll.BDP($C13,"security name") -> CH Robinson Worldwide Inc | B13: =_xll.BDP($C13,"NAME_CHINESE_SIMPLIFIED") -> 罗宾逊全球物流有限公司 | C13: CHRW US EQUITY | D13: =_xll.BDP($C13,"LISTING_DATE") -> 10/15/1997 | E13: =_xll.BDP($C13,E$1,"EQY_FUND_CRNCY="&$B$1) -> 159732.89 | F13: =_xll.BDP($C13,F$1,"EQY_FUND_CRNCY="&$C$1) -> 20390.478 | G13: =_xll.BDP($C13,G$1) -> 173.02 | H13: =_xll.BDP($C13,H$1,"EQY_FUND_CRNCY="&$B$1) -> 14366.332 | I13: =_xll.BDP($C13,I$1,"EQY_FUND_CRNCY="&$C$1) -> 1845.647 | J13: =_xll.BDP($C13,J$1,"EQY_FUND_CRNCY="&$B$1) -> 126547.9 | K13: =_xll.BDP($C13,K$1,"EQY_FUND_CRNCY="&$C$1) -> 16232.763 | L13: =_xll.BDP($C13,L$1,"EQY_FUND_CRNCY="&$B$1) -> 4576.7852 | M13: =_xll.BDP($C13,M$1,"EQY_FUND_CRNCY="&$C$1) -> 587.081 | N13: =_xll.BDP($C13,N$1)/100 -> 0.083735098 | O13: =_xll.BDP($C13,O$1)/100 -> 0.063262366 | P13: =_xll.BDP($C13,P$1)/100 -> 0.036166425 | Q13: =_xll.BDP($C13,Q$1)/100 -> -0.084185992 | R13: =_xll.BDP($C13,R$1)/100 -> 0.26066911 | S13: =_xll.BDP($C13,S$1)/100 -> 0.75604165 | T13: =_xll.BDP($C13,T$1)/100 -> 0.75604165 | U13: =_xll.BDP($C13,U$1)/100 -> 0.66887926 | ... W13: =_xll.BDP($C13,W$1)/100 -> 0.11451706 | X13: {=_xll.BDP($C13,"CRNCY_ADJ_CURR_EV", "EQY_FUND_CRNCY=HKD")} -> 171375.22 | Y13: {=_xll.BDP($C13,"CRNCY_ADJ_CURR_EV", "EQY_FUND_CRNCY=USD")} -> 21875.299 | Z13: =_xll.BDP($C13,Z$1)/100 -> 0.34837966 | AA13: =_xll.BDP($C13,"TRAIL_12M_NET_SALES","EQY_FUND_CRNCY=HKD") -> 126415.87 | AB13: =_xll.BDP($C13,"TRAIL_12M_NET_INC","EQY_FUND_CRNCY=HKD") -> 4674.6603 | AC13: =_xll.BDP($C13,"TRAIL_12M_EBITDA","EQY_FUND_CRNCY=HKD") -> 7712.5745 | AD13: =IF(AB13<0,"N/A",$E13/AB13) -> 34.169947 | AE13: {=_xll.BQL($C13, "PE_RATIO(FPT=BA, FPR=2026, FYE=C1231, AE=E)")} -> 28.120531 | AF13: {=_xll.BQL($C13, "PE_RATIO(FPT=BA, FPR=2027, FYE=C1231, AE=E)")} -> 23.718266 | AG13: =$E13/AA13 -> 1.263551 | AH13: {=_xll.BQL($C13, "PX_TO_SALES_RATIO(FPT=BA, FPR=2026, FYE=C1231, AE=E)")} -> 1.2081685 | AI13: {=_xll.BQL($C13, "PX_TO_SALES_RATIO(FPT=BA, FPR=2027, FYE=C1231, AE=E)")} -> 1.1362245 | AJ13: =IF(AC13<0,"N/A",$X13/AC13) -> 22.220236 | AK13: {=IF(_xll.BQL($C13, "CURR_ENTP_VAL(FPT=A,FPO=0)/EBITDA(FPT=BA, FPR=2026, FYE=C1231, AE=E)")<0,"N/A",_xll.BQL($C13, "CURR_ENTP_VAL(FPT=A,FPO=0)/EBITDA(FPT=BA, FPR=2026, FYE=C1231, AE=E)"))} -> 21.826218 | AL13: {=IF(_xll.BQL($C13, "CURR_ENTP_VAL(FPT=A,FPO=0)/EBITDA(FPT=BA, FPR=2027, FYE=C1231, AE=E)")<0,"N/A",_xll.BQL($C13, "CURR_ENTP_VAL(FPT=A,FPO=0)/EBITDA(FPT=BA, FPR=2027, FYE=C1231, AE=E)"))} -> 18.813097 | AM13: =_xll.BDP($C13,AM$1) -> 11.996522 | AN13: {=_xll.BQL($C13, "PX_TO_BOOK_RATIO(FPT=BA, FPR=2026, FYE=C1231, AE=E)")} -> 11.525447 | AO13: {=_xll.BQL($C13, "PX_TO_BOOK_RATIO(FPT=BA, FPR=2027, FYE=C1231, AE=E)")} -> 10.786783 | AP13: =_xll.BDP($C13,"BEST Px bps ratio","BEST fperiod override","27Y") -> 11.037959 | AQ13: =Z13 -> 0.34837966 | AR13: =_xll.BDP($C13,"BEST_ROE","BEST fperiod override","26Y")/100 -> 0.39701 | AS13: =_xll.BDP($C13,"BEST_ROE","BEST fperiod override","27Y")/100 -> 0.4616 | AT13: =_xll.BDP($C13,AT$1) -> 1.4563948 | AU13: =_xll.BDP($C13,$AU$1,"BEST fperiod override","26Y") -> 1.4524332 | AV13: =_xll.BDP($C13,$AU$1,"BEST fperiod override","27Y") -> 1.4784418 | AW13: =(BP13/BN13)^(1/2)-1 -> -0.024207711 | AX13: =(BV13/BT13)^(1/2)-1 -> 0.097445037 | AY13: =(CB13/BZ13)^(1/2)-1 -> 0.253025 | AZ13: {=_xll.BQL($C13, "CF_CASH_FROM_OPER(FPT=BA, FPR=2022, FYE=C1231, AE=A)", "currency=USD")/1000000000} -> 1.650171 | BA13: {=_xll.BQL($C13, "CF_CASH_FROM_OPER(FPT=BA, FPR=2023, FYE=C1231, AE=A)", "currency=USD")/1000000000} -> 0.731946 | BB13: {=_xll.BQL($C13, "CF_CASH_FROM_OPER(FPT=BA, FPR=2024, FYE=C1231, AE=A)", "currency=USD")/1000000000} -> 0.509084 | BC13: {=_xll.BQL($C13, "CF_CASH_FROM_OPER(FPT=BA, FPR=2025, FYE=C1231, AE=E)", "currency=USD")/1000000000} -> 0.83654123 | BD13: {=_xll.BQL($C13, "CF_CASH_FROM_OPER(FPT=BA, FPR=2026, FYE=C1231, AE=E)", "currency=USD")/1000000000} -> 0.81848958 | BE13: {=_xll.BQL($C13, "CF_CASH_FROM_OPER(FPT=BA, FPR=2027, FYE=C1231, AE=E)", "currency=USD")/1000000000} -> 0.97863258 | BF13: {=_xll.BQL($C13, "CF_FREE_CASH_FLOW(FPT=BA, FPR=2022, FYE=C1231, AE=A)", "currency=USD")/1000000000} -> 1.588256 | BG13: {=_xll.BQL($C13, "CF_FREE_CASH_FLOW(FPT=BA, FPR=2023, FYE=C1231, AE=A)", "currency=USD")/1000000000} -> 0.701957 | BH13: {=_xll.BQL($C13, "CF_FREE_CASH_FLOW(FPT=BA, FPR=2024, FYE=C1231, AE=A)", "currency=USD")/1000000000} -> 0.486431 | BI13: {=_xll.BQL($C13, "CF_FREE_CASH_FLOW(FPT=BA, FPR=2025, FYE=C1231, AE=E)", "currency=USD")/1000000000} -> 0.74980139 | BJ13: {=_xll.BQL($C13, "CF_FREE_CASH_FLOW(FPT=BA, FPR=2026, FYE=C1231, AE=E)", "currency=USD")/1000000000} -> 0.74545011 | BK13: {=_xll.BQL($C13, "CF_FREE_CASH_FLOW(FPT=BA, FPR=2027, FYE=C1231, AE=E)", "currency=USD")/1000000000} -> 0.88281303 | BL13: {=_xll.BQL($C13, "SALES_REV_TURN(FPT=BA, FPR=2022, FYE=C1231, AE=A)", "currency=USD")/1000000000} -> 24.696625 | BM13: {=_xll.BQL($C13, "SALES_REV_TURN(FPT=BA, FPR=2023, FYE=C1231, AE=A)", "currency=USD")/1000000000} -> 17.596443 | BN13: {=_xll.BQL($C13, "SALES_REV_TURN(FPT=BA, FPR=2024, FYE=C1231, AE=A)", "currency=USD")/1000000000} -> 17.724956 | BO13: {=_xll.BQL($C13, "SALES_REV_TURN(FPT=BA, FPR=2025, FYE=C1231, AE=E)", "currency=USD")/1000000000} -> 16.298708 | BP13: {=_xll.BQL($C13, "SALES_REV_TURN(FPT=BA, FPR=2026, FYE=C1231, AE=E)", "currency=USD")/1000000000} -> 16.877182 | BQ13: {=_xll.BQL($C13, "SALES_REV_TURN(FPT=BA, FPR=2027, FYE=C1231, AE=E)", "currency=USD")/1000000000} -> 17.945818 | BR13: {=_xll.BQL($C13, "EBITDA(FPT=BA, FPR=2022, FYE=C1231, AE=A)", "currency=USD")/1000000000} -> 1.45159 | BS13: {=_xll.BQL($C13, "EBITDA(FPT=BA, FPR=2023, FYE=C1231, AE=A)", "currency=USD")/1000000000} -> 0.714227 | BT13: {=_xll.BQL($C13, "EBITDA(FPT=BA, FPR=2024, FYE=C1231, AE=A)", "currency=USD")/1000000000} -> 0.875135 | BU13: {=_xll.BQL($C13, "EBITDA(FPT=BA, FPR=2025, FYE=C1231, AE=E)", "currency=USD")/1000000000} -> 0.91273913 | BV13: {=_xll.BQL($C13, "EBITDA(FPT=BA, FPR=2026, FYE=C1231, AE=E)", "currency=USD")/1000000000} -> 1.054 | BW13: {=_xll.BQL($C13, "EBITDA(FPT=BA, FPR=2027, FYE=C1231, AE=E)", "currency=USD")/1000000000} -> 1.2228095 | BX13: {=_xll.BQL($C13, "NET_INCOME(FPT=BA, FPR=2022, FYE=C1231, AE=A)", "currency=USD")/1000000000} -> 0.940524 | BY13: {=_xll.BQL($C13, "NET_INCOME(FPT=BA, FPR=2023, FYE=C1231, AE=A)", "currency=USD")/1000000000} -> 0.325129 | BZ13: {=_xll.BQL($C13, "NET_INCOME(FPT=BA, FPR=2024, FYE=C1231, AE=A)", "currency=USD")/1000000000} -> 0.46569 | CA13: {=_xll.BQL($C13, "NET_INCOME(FPT=BA, FPR=2025, FYE=C1231, AE=E)", "currency=USD")/1000000000} -> 0.5959 | CB13: {=_xll.BQL($C13, "NET_INCOME(FPT=BA, FPR=2026, FYE=C1231, AE=E)", "currency=USD")/1000000000} -> 0.73116667 | CC13: {=_xll.BQL($C13, "NET_INCOME(FPT=BA, FPR=2027, FYE=C1231, AE=E)", "currency=USD")/1000000000} -> 0.88388889 | CD13: {=-_xll.BQL($C13, "CF_DVD_PAID(FPT=BA, FPR=2024, FYE=C1231, AE=A)", "currency=USD")/1000000000} -> 0.294772 | CE13: {=-_xll.BQL($C13, "CF_DVD_PAID(FPT=BA, FPR=2025, FYE=C1231, AE=E)", "currency=USD")/1000000000} -> 0.30527602 | CF13: {=-_xll.BQL($C13, "CF_DVD_PAID(FPT=BA, FPR=2026, FYE=C1231, AE=E)", "currency=USD")/1000000000} -> 0.30768054 | CG13: {=-_xll.BQL($C13, "CF_DVD_PAID(FPT=BA, FPR=2027, FYE=C1231, AE=E)", "currency=USD")/1000000000} -> 0.32098167 | CH13: =CD13/$F13 -> 1.4456355e-05 | CI13: =CE13/$F13 -> 1.4971498e-05 | CJ13: =CF13/$F13 -> 1.5089422e-05 | CK13: =CG13/$F13 -> 1.5741743e-05 | CL13: {=_xll.BDP($C13,"INTERVAL_AVG", "MARKET_DATA_OVERRIDE=turnover", "CALC_INTERVAL=5D","CRNCY=HKD")/1000000} -> 3712.5822 | CM13: {=_xll.BDP($C13,"INTERVAL_AVG", "MARKET_DATA_OVERRIDE=turnover", "CALC_INTERVAL=10D","CRNCY=HKD")/1000000} -> 2629.6555 | CN13: {=_xll.BDP($C13,"INTERVAL_AVG", "MARKET_DATA_OVERRIDE=turnover", "CALC_INTERVAL=20D","CRNCY=HKD")/1000000} -> 2914.868 | CO13: {=_xll.BDP($C13,"INTERVAL_AVG", "MARKET_DATA_OVERRIDE=turnover", "CALC_INTERVAL=1m","CRNCY=HKD")/1000000} -> 2854.8895 | CP13: {=_xll.BDP($C13,"INTERVAL_AVG", "MARKET_DATA_OVERRIDE=turnover", "CALC_INTERVAL=3M","CRNCY=HKD")/1000000} -> 2562.9612 | CQ13: {=_xll.BDP($C13,"INTERVAL_AVG", "MARKET_DATA_OVERRIDE=turnover", "CALC_INTERVAL=6M","CRNCY=HKD")/1000000} -> 2752.925 | CR13: =_xll.BDP($C13,"chg pct 1m")/100 -> -0.0594183 | CS13: =_xll.BDP($C13,"chg pct 3m")/100 -> -0.08965589 | CT13: =_xll.BDP($C13,"chg pct 6m")/100 -> 0.1645688 | CU13: =_xll.BDP($C13,"chg pct 1yr")/100 -> 0.7289897 | CV13: =_xll.BDP($C13,"chg pct ytd")/100 -> 0.07626279 | CW13: {=_xll.BQL($C13, "volatility(calc_interval=range(-1M, 0D))")} -> 0.44536685 | CX13: {=_xll.BQL($C13, "volatility(calc_interval=range(-3M, 0D))")} -> 0.42336611 | CY13: {=_xll.BQL($C13, "volatility(calc_interval=range(-6M, 0D))")} -> 0.41262464 | CZ13: =_xll.BDP($C13,CZ$1) -> C.H. Robinson Worldwide, Inc. operates as a logistics company. The Company freight, supply chain, and logistics services. C.H. Robinson Worldwide serves clients worldwide.
A14: =_xll.BDP($C14,"security name") -> CVS Health Corp | B14: =_xll.BDP($C14,"NAME_CHINESE_SIMPLIFIED") -> CVS健康公司 | C14: cvs us EQUITY | D14: =_xll.BDP($C14,"LISTING_DATE") -> 10/1/1952 | E14: =_xll.BDP($C14,E$1,"EQY_FUND_CRNCY="&$B$1) -> 941386.99 | F14: =_xll.BDP($C14,F$1,"EQY_FUND_CRNCY="&$C$1) -> 120166.83 | G14: =_xll.BDP($C14,G$1) -> 94.18 | H14: =_xll.BDP($C14,H$1,"EQY_FUND_CRNCY="&$B$1) -> 586765.95 | I14: =_xll.BDP($C14,I$1,"EQY_FUND_CRNCY="&$C$1) -> 75382 | J14: =_xll.BDP($C14,J$1,"EQY_FUND_CRNCY="&$B$1) -> 3134447 | K14: =_xll.BDP($C14,K$1,"EQY_FUND_CRNCY="&$C$1) -> 402067 | L14: =_xll.BDP($C14,L$1,"EQY_FUND_CRNCY="&$B$1) -> 13783.032 | M14: =_xll.BDP($C14,M$1,"EQY_FUND_CRNCY="&$C$1) -> 1768 | N14: =_xll.BDP($C14,N$1)/100 -> 0.13769347 | O14: =_xll.BDP($C14,O$1)/100 -> 0.048268075 | P14: =_xll.BDP($C14,P$1)/100 -> 0.0043972771 | Q14: =_xll.BDP($C14,Q$1)/100 -> 0.078479865 | R14: =_xll.BDP($C14,R$1)/100 -> -0.61681838 | S14: =_xll.BDP($C14,S$1)/100 -> 1.060598 | T14: =_xll.BDP($C14,T$1)/100 -> 1.062967 | U14: =_xll.BDP($C14,U$1)/100 -> 0.92000743 | ... W14: =_xll.BDP($C14,W$1)/100 -> 0.011530619 | X14: {=_xll.BDP($C14,"CRNCY_ADJ_CURR_EV", "EQY_FUND_CRNCY=HKD")} -> 1464563.2 | Y14: {=_xll.BDP($C14,"CRNCY_ADJ_CURR_EV", "EQY_FUND_CRNCY=USD")} -> 186890.83 | Z14: =_xll.BDP($C14,Z$1)/100 -> 0.037982965 | AA14: =_xll.BDP($C14,"TRAIL_12M_NET_SALES","EQY_FUND_CRNCY=HKD") -> 3183270.6 | AB14: =_xll.BDP($C14,"TRAIL_12M_NET_INC","EQY_FUND_CRNCY=HKD") -> 22881.184 | AC14: =_xll.BDP($C14,"TRAIL_12M_EBITDA","EQY_FUND_CRNCY=HKD") -> 82199.015 | AD14: =IF(AB14<0,"N/A",$E14/AB14) -> 41.142407 | AE14: {=_xll.BQL($C14, "PE_RATIO(FPT=BA, FPR=2026, FYE=C1231, AE=E)")} -> 12.755116 | AF14: {=_xll.BQL($C14, "PE_RATIO(FPT=BA, FPR=2027, FYE=C1231, AE=E)")} -> 11.256229 | AG14: =$E14/AA14 -> 0.29572949 | AH14: {=_xll.BQL($C14, "PX_TO_SALES_RATIO(FPT=BA, FPR=2026, FYE=C1231, AE=E)")} -> 0.2950372 | AI14: {=_xll.BQL($C14, "PX_TO_SALES_RATIO(FPT=BA, FPR=2027, FYE=C1231, AE=E)")} -> 0.28275297 | AJ14: =IF(AC14<0,"N/A",$X14/AC14) -> 17.817284 | AK14: {=IF(_xll.BQL($C14, "CURR_ENTP_VAL(FPT=A,FPO=0)/EBITDA(FPT=BA, FPR=2026, FYE=C1231, AE=E)")<0,"N/A",_xll.BQL($C14, "CURR_ENTP_VAL(FPT=A,FPO=0)/EBITDA(FPT=BA, FPR=2026, FYE=C1231, AE=E)"))} -> 9.0639446 | AL14: {=IF(_xll.BQL($C14, "CURR_ENTP_VAL(FPT=A,FPO=0)/EBITDA(FPT=BA, FPR=2027, FYE=C1231, AE=E)")<0,"N/A",_xll.BQL($C14, "CURR_ENTP_VAL(FPT=A,FPO=0)/EBITDA(FPT=BA, FPR=2027, FYE=C1231, AE=E)"))} -> 8.7266069 | AM14: =_xll.BDP($C14,AM$1) -> 1.5478612 | AN14: {=_xll.BQL($C14, "PX_TO_BOOK_RATIO(FPT=BA, FPR=2026, FYE=C1231, AE=E)")} -> 1.5070609 | AO14: {=_xll.BQL($C14, "PX_TO_BOOK_RATIO(FPT=BA, FPR=2027, FYE=C1231, AE=E)")} -> 1.4279433 | AP14: =_xll.BDP($C14,"BEST Px bps ratio","BEST fperiod override","27Y") -> 1.3983875 | AQ14: =Z14 -> 0.037982965 | AR14: =_xll.BDP($C14,"BEST_ROE","BEST fperiod override","26Y")/100 -> 0.1066 | AS14: =_xll.BDP($C14,"BEST_ROE","BEST fperiod override","27Y")/100 -> 0.11405 | AT14: =_xll.BDP($C14,AT$1) -> 2.8243789 | AU14: =_xll.BDP($C14,$AU$1,"BEST fperiod override","26Y") -> 2.8073901 | AV14: =_xll.BDP($C14,$AU$1,"BEST fperiod override","27Y") -> 2.9868337 | AW14: =(BP14/BN14)^(1/2)-1 -> 0.045227266 | AX14: =(BV14/BT14)^(1/2)-1 -> 0.087519531 | AY14: =(CB14/BZ14)^(1/2)-1 -> 0.30704781 | AZ14: {=_xll.BQL($C14, "CF_CASH_FROM_OPER(FPT=BA, FPR=2022, FYE=C1231, AE=A)", "currency=USD")/1000000000} -> 16.177 | BA14: {=_xll.BQL($C14, "CF_CASH_FROM_OPER(FPT=BA, FPR=2023, FYE=C1231, AE=A)", "currency=USD")/1000000000} -> 13.426 | BB14: {=_xll.BQL($C14, "CF_CASH_FROM_OPER(FPT=BA, FPR=2024, FYE=C1231, AE=A)", "currency=USD")/1000000000} -> 9.107 | BC14: {=_xll.BQL($C14, "CF_CASH_FROM_OPER(FPT=BA, FPR=2025, FYE=C1231, AE=E)", "currency=USD")/1000000000} -> 6.8931973 | BD14: {=_xll.BQL($C14, "CF_CASH_FROM_OPER(FPT=BA, FPR=2026, FYE=C1231, AE=E)", "currency=USD")/1000000000} -> 9.5035319 | BE14: {=_xll.BQL($C14, "CF_CASH_FROM_OPER(FPT=BA, FPR=2027, FYE=C1231, AE=E)", "currency=USD")/1000000000} -> 12.567884 | BF14: {=_xll.BQL($C14, "CF_FREE_CASH_FLOW(FPT=BA, FPR=2022, FYE=C1231, AE=A)", "currency=USD")/1000000000} -> 13.45 | BG14: {=_xll.BQL($C14, "CF_FREE_CASH_FLOW(FPT=BA, FPR=2023, FYE=C1231, AE=A)", "currency=USD")/1000000000} -> 10.395 | BH14: {=_xll.BQL($C14, "CF_FREE_CASH_FLOW(FPT=BA, FPR=2024, FYE=C1231, AE=A)", "currency=USD")/1000000000} -> 6.326 | BI14: {=_xll.BQL($C14, "CF_FREE_CASH_FLOW(FPT=BA, FPR=2025, FYE=C1231, AE=E)", "currency=USD")/1000000000} -> 5.5684131 | BJ14: {=_xll.BQL($C14, "CF_FREE_CASH_FLOW(FPT=BA, FPR=2026, FYE=C1231, AE=E)", "currency=USD")/1000000000} -> 7.2600573 | BK14: {=_xll.BQL($C14, "CF_FREE_CASH_FLOW(FPT=BA, FPR=2027, FYE=C1231, AE=E)", "currency=USD")/1000000000} -> 10.751112 | BL14: {=_xll.BQL($C14, "SALES_REV_TURN(FPT=BA, FPR=2022, FYE=C1231, AE=A)", "currency=USD")/1000000000} -> 322.467 | BM14: {=_xll.BQL($C14, "SALES_REV_TURN(FPT=BA, FPR=2023, FYE=C1231, AE=A)", "currency=USD")/1000000000} -> 357.776 | BN14: {=_xll.BQL($C14, "SALES_REV_TURN(FPT=BA, FPR=2024, FYE=C1231, AE=A)", "currency=USD")/1000000000} -> 372.809 | BO14: {=_xll.BQL($C14, "SALES_REV_TURN(FPT=BA, FPR=2025, FYE=C1231, AE=E)", "currency=USD")/1000000000} -> 400.12448 | BP14: {=_xll.BQL($C14, "SALES_REV_TURN(FPT=BA, FPR=2026, FYE=C1231, AE=E)", "currency=USD")/1000000000} -> 407.29385 | BQ14: {=_xll.BQL($C14, "SALES_REV_TURN(FPT=BA, FPR=2027, FYE=C1231, AE=E)", "currency=USD")/1000000000} -> 424.98876 | BR14: {=_xll.BQL($C14, "EBITDA(FPT=BA, FPR=2022, FYE=C1231, AE=A)", "currency=USD")/1000000000} -> 14.696 | BS14: {=_xll.BQL($C14, "EBITDA(FPT=BA, FPR=2023, FYE=C1231, AE=A)", "currency=USD")/1000000000} -> 20.578 | BT14: {=_xll.BQL($C14, "EBITDA(FPT=BA, FPR=2024, FYE=C1231, AE=A)", "currency=USD")/1000000000} -> 15.469 | BU14: {=_xll.BQL($C14, "EBITDA(FPT=BA, FPR=2025, FYE=C1231, AE=E)", "currency=USD")/1000000000} -> 17.375389 | BV14: {=_xll.BQL($C14, "EBITDA(FPT=BA, FPR=2026, FYE=C1231, AE=E)", "currency=USD")/1000000000} -> 18.295167 | BW14: {=_xll.BQL($C14, "EBITDA(FPT=BA, FPR=2027, FYE=C1231, AE=E)", "currency=USD")/1000000000} -> 19.002389 | BX14: {=_xll.BQL($C14, "NET_INCOME(FPT=BA, FPR=2022, FYE=C1231, AE=A)", "currency=USD")/1000000000} -> 4.311 | BY14: {=_xll.BQL($C14, "NET_INCOME(FPT=BA, FPR=2023, FYE=C1231, AE=A)", "currency=USD")/1000000000} -> 8.344 | BZ14: {=_xll.BQL($C14, "NET_INCOME(FPT=BA, FPR=2024, FYE=C1231, AE=A)", "currency=USD")/1000000000} -> 4.614 | CA14: {=_xll.BQL($C14, "NET_INCOME(FPT=BA, FPR=2025, FYE=C1231, AE=E)", "currency=USD")/1000000000} -> -0.34181818 | CB14: {=_xll.BQL($C14, "NET_INCOME(FPT=BA, FPR=2026, FYE=C1231, AE=E)", "currency=USD")/1000000000} -> 7.8824375 | CC14: {=_xll.BQL($C14, "NET_INCOME(FPT=BA, FPR=2027, FYE=C1231, AE=E)", "currency=USD")/1000000000} -> 9.1240625 | CD14: {=-_xll.BQL($C14, "CF_DVD_PAID(FPT=BA, FPR=2024, FYE=C1231, AE=A)", "currency=USD")/1000000000} -> 3.373 | CE14: {=-_xll.BQL($C14, "CF_DVD_PAID(FPT=BA, FPR=2025, FYE=C1231, AE=E)", "currency=USD")/1000000000} -> 3.348705 | CF14: {=-_xll.BQL($C14, "CF_DVD_PAID(FPT=BA, FPR=2026, FYE=C1231, AE=E)", "currency=USD")/1000000000} -> 3.4198385 | CG14: {=-_xll.BQL($C14, "CF_DVD_PAID(FPT=BA, FPR=2027, FYE=C1231, AE=E)", "currency=USD")/1000000000} -> 3.5900269 | CH14: =CD14/$F14 -> 2.8069309e-05 | CI14: =CE14/$F14 -> 2.7867132e-05 | CJ14: =CF14/$F14 -> 2.8459088e-05 | CK14: =CG14/$F14 -> 2.9875356e-05 | CL14: {=_xll.BDP($C14,"INTERVAL_AVG", "MARKET_DATA_OVERRIDE=turnover", "CALC_INTERVAL=5D","CRNCY=HKD")/1000000} -> 7181.2996 | CM14: {=_xll.BDP($C14,"INTERVAL_AVG", "MARKET_DATA_OVERRIDE=turnover", "CALC_INTERVAL=10D","CRNCY=HKD")/1000000} -> 7847.3575 | CN14: {=_xll.BDP($C14,"INTERVAL_AVG", "MARKET_DATA_OVERRIDE=turnover", "CALC_INTERVAL=20D","CRNCY=HKD")/1000000} -> 6391.7576 | CO14: {=_xll.BDP($C14,"INTERVAL_AVG", "MARKET_DATA_OVERRIDE=turnover", "CALC_INTERVAL=1m","CRNCY=HKD")/1000000} -> 6069.4642 | CP14: {=_xll.BDP($C14,"INTERVAL_AVG", "MARKET_DATA_OVERRIDE=turnover", "CALC_INTERVAL=3M","CRNCY=HKD")/1000000} -> 5187.3017 | CQ14: {=_xll.BDP($C14,"INTERVAL_AVG", "MARKET_DATA_OVERRIDE=turnover", "CALC_INTERVAL=6M","CRNCY=HKD")/1000000} -> 5116.5103 | CR14: =_xll.BDP($C14,"chg pct 1m")/100 -> 0.229825 | CS14: =_xll.BDP($C14,"chg pct 3m")/100 -> 0.228061 | CT14: =_xll.BDP($C14,"chg pct 6m")/100 -> 0.2385586 | CU14: =_xll.BDP($C14,"chg pct 1yr")/100 -> 0.4775651 | CV14: =_xll.BDP($C14,"chg pct ytd")/100 -> 0.1867439 | CW14: {=_xll.BQL($C14, "volatility(calc_interval=range(-1M, 0D))")} -> 0.40133415 | CX14: {=_xll.BQL($C14, "volatility(calc_interval=range(-3M, 0D))")} -> 0.35036859 | CY14: {=_xll.BQL($C14, "volatility(calc_interval=range(-6M, 0D))")} -> 0.36396735 | CZ14: =_xll.BDP($C14,CZ$1) -> CVS Health Corporation provides health care and retail pharmacy services. The Company offers prescription medications, beauty, personal care, cosmetics, and health care products, as well as pharmacy benefit management (PBM), disease management, and administrative services. CVS Health operates in the United States and Puerto Rico.
A15: =_xll.BDP($C15,"security name") -> H & M Hennes & Mauritz AB | B15: =_xll.BDP($C15,"NAME_CHINESE_SIMPLIFIED") -> 海恩斯莫里斯公司 | C15: hmb ss EQUITY | D15: =_xll.BDP($C15,"LISTING_DATE") -> #N/A Field Not Applicable | E15: =_xll.BDP($C15,E$1,"EQY_FUND_CRNCY="&$B$1) -> 217702.58 | F15: =_xll.BDP($C15,F$1,"EQY_FUND_CRNCY="&$C$1) -> 27789.454 | G15: =_xll.BDP($C15,G$1) -> 163 | H15: =_xll.BDP($C15,H$1,"EQY_FUND_CRNCY="&$B$1) -> 35412.183 | I15: =_xll.BDP($C15,I$1,"EQY_FUND_CRNCY="&$C$1) -> 4548.3622 | J15: =_xll.BDP($C15,J$1,"EQY_FUND_CRNCY="&$B$1) -> 179395.13 | K15: =_xll.BDP($C15,K$1,"EQY_FUND_CRNCY="&$C$1) -> 23011.543 | L15: =_xll.BDP($C15,L$1,"EQY_FUND_CRNCY="&$B$1) -> 9554.224 | M15: =_xll.BDP($C15,M$1,"EQY_FUND_CRNCY="&$C$1) -> 1225.5485 | N15: =_xll.BDP($C15,N$1)/100 -> 0.53395098 | O15: =_xll.BDP($C15,O$1)/100 -> 0.17376963 | P15: =_xll.BDP($C15,P$1)/100 -> 0.053257989 | Q15: =_xll.BDP($C15,Q$1)/100 -> -0.02641186 | R15: =_xll.BDP($C15,R$1)/100 -> 0.046209448 | S15: =_xll.BDP($C15,S$1)/100 -> 1.8056442 | T15: =_xll.BDP($C15,T$1)/100 -> 1.806738 | U15: =_xll.BDP($C15,U$1)/100 -> 1.3188116 | ... W15: =_xll.BDP($C15,W$1)/100 -> #VALUE! | X15: {=_xll.BDP($C15,"CRNCY_ADJ_CURR_EV", "EQY_FUND_CRNCY=HKD")} -> 268039.39 | Y15: {=_xll.BDP($C15,"CRNCY_ADJ_CURR_EV", "EQY_FUND_CRNCY=USD")} -> 34224.905 | Z15: =_xll.BDP($C15,Z$1)/100 -> #VALUE! | AA15: =_xll.BDP($C15,"TRAIL_12M_NET_SALES","EQY_FUND_CRNCY=HKD") -> 182918.59 | AB15: =_xll.BDP($C15,"TRAIL_12M_NET_INC","EQY_FUND_CRNCY=HKD") -> 10102.648 | AC15: =_xll.BDP($C15,"TRAIL_12M_EBITDA","EQY_FUND_CRNCY=HKD") -> 31672.279 | AD15: =IF(AB15<0,"N/A",$E15/AB15) -> 21.549061 | AE15: {=_xll.BQL($C15, "PE_RATIO(FPT=BA, FPR=2026, FYE=C1231, AE=E)")} -> 19.094264 | AF15: {=_xll.BQL($C15, "PE_RATIO(FPT=BA, FPR=2027, FYE=C1231, AE=E)")} -> 18.103523 | AG15: =$E15/AA15 -> 1.1901611 | AH15: {=_xll.BQL($C15, "PX_TO_SALES_RATIO(FPT=BA, FPR=2026, FYE=C1231, AE=E)")} -> 1.1749797 | AI15: {=_xll.BQL($C15, "PX_TO_SALES_RATIO(FPT=BA, FPR=2027, FYE=C1231, AE=E)")} -> 1.1540057 | AJ15: =IF(AC15<0,"N/A",$X15/AC15) -> 8.4629021 | AK15: {=IF(_xll.BQL($C15, "CURR_ENTP_VAL(FPT=A,FPO=0)/EBITDA(FPT=BA, FPR=2026, FYE=C1231, AE=E)")<0,"N/A",_xll.BQL($C15, "CURR_ENTP_VAL(FPT=A,FPO=0)/EBITDA(FPT=BA, FPR=2026, FYE=C1231, AE=E)"))} -> 8.3000656 | AL15: {=IF(_xll.BQL($C15, "CURR_ENTP_VAL(FPT=A,FPO=0)/EBITDA(FPT=BA, FPR=2027, FYE=C1231, AE=E)")<0,"N/A",_xll.BQL($C15, "CURR_ENTP_VAL(FPT=A,FPO=0)/EBITDA(FPT=BA, FPR=2027, FYE=C1231, AE=E)"))} -> 8.0155369 | AM15: =_xll.BDP($C15,AM$1) -> 6.2869523 | AN15: {=_xll.BQL($C15, "PX_TO_BOOK_RATIO(FPT=BA, FPR=2026, FYE=C1231, AE=E)")} -> 5.932914 | AO15: {=_xll.BQL($C15, "PX_TO_BOOK_RATIO(FPT=BA, FPR=2027, FYE=C1231, AE=E)")} -> 5.6001816 | AP15: =_xll.BDP($C15,"BEST Px bps ratio","BEST fperiod override","27Y") -> 5.5768441 | AQ15: =Z15 -> #VALUE! | AR15: =_xll.BDP($C15,"BEST_ROE","BEST fperiod override","26Y")/100 -> 0.30293 | AS15: =_xll.BDP($C15,"BEST_ROE","BEST fperiod override","27Y")/100 -> 0.32374 | AT15: =_xll.BDP($C15,AT$1) -> 4.3585021 | AU15: =_xll.BDP($C15,$AU$1,"BEST fperiod override","26Y") -> 4.502454 | AV15: =_xll.BDP($C15,$AU$1,"BEST fperiod override","27Y") -> 4.7865031 | AW15: =(BP15/BN15)^(1/2)-1 -> 0.036145043 | AX15: =(BV15/BT15)^(1/2)-1 -> 0.093730152 | AY15: =(CB15/BZ15)^(1/2)-1 -> 0.15880726 | AZ15: {=_xll.BQL($C15, "CF_CASH_FROM_OPER(FPT=BA, FPR=2022, FYE=C1231, AE=A)", "currency=USD")/1000000000} -> 2.4241186 | BA15: {=_xll.BQL($C15, "CF_CASH_FROM_OPER(FPT=BA, FPR=2023, FYE=C1231, AE=A)", "currency=USD")/1000000000} -> 3.1688053 | BB15: {=_xll.BQL($C15, "CF_CASH_FROM_OPER(FPT=BA, FPR=2024, FYE=C1231, AE=A)", "currency=USD")/1000000000} -> 2.9881701 | BC15: {=_xll.BQL($C15, "CF_CASH_FROM_OPER(FPT=BA, FPR=2025, FYE=C1231, AE=E)", "currency=USD")/1000000000} -> 4.686497 | BD15: {=_xll.BQL($C15, "CF_CASH_FROM_OPER(FPT=BA, FPR=2026, FYE=C1231, AE=E)", "currency=USD")/1000000000} -> 3.9173809 | BE15: {=_xll.BQL($C15, "CF_CASH_FROM_OPER(FPT=BA, FPR=2027, FYE=C1231, AE=E)", "currency=USD")/1000000000} -> 3.9331037 | BF15: {=_xll.BQL($C15, "CF_FREE_CASH_FLOW(FPT=BA, FPR=2022, FYE=C1231, AE=A)", "currency=USD")/1000000000} -> 1.9597794 | BG15: {=_xll.BQL($C15, "CF_FREE_CASH_FLOW(FPT=BA, FPR=2023, FYE=C1231, AE=A)", "currency=USD")/1000000000} -> 2.4125135 | BH15: {=_xll.BQL($C15, "CF_FREE_CASH_FLOW(FPT=BA, FPR=2024, FYE=C1231, AE=A)", "currency=USD")/1000000000} -> 2.0299634 | BI15: {=_xll.BQL($C15, "CF_FREE_CASH_FLOW(FPT=BA, FPR=2025, FYE=C1231, AE=E)", "currency=USD")/1000000000} -> 3.9477056 | BJ15: {=_xll.BQL($C15, "CF_FREE_CASH_FLOW(FPT=BA, FPR=2026, FYE=C1231, AE=E)", "currency=USD")/1000000000} -> 2.8950644 | BK15: {=_xll.BQL($C15, "CF_FREE_CASH_FLOW(FPT=BA, FPR=2027, FYE=C1231, AE=E)", "currency=USD")/1000000000} -> 2.8533001 | BL15: {=_xll.BQL($C15, "SALES_REV_TURN(FPT=BA, FPR=2022, FYE=C1231, AE=A)", "currency=USD")/1000000000} -> 21.915431 | BM15: {=_xll.BQL($C15, "SALES_REV_TURN(FPT=BA, FPR=2023, FYE=C1231, AE=A)", "currency=USD")/1000000000} -> 22.21339 | BN15: {=_xll.BQL($C15, "SALES_REV_TURN(FPT=BA, FPR=2024, FYE=C1231, AE=A)", "currency=USD")/1000000000} -> 22.070462 | BO15: {=_xll.BQL($C15, "SALES_REV_TURN(FPT=BA, FPR=2025, FYE=C1231, AE=E)", "currency=USD")/1000000000} -> 24.319544 | BP15: {=_xll.BQL($C15, "SALES_REV_TURN(FPT=BA, FPR=2026, FYE=C1231, AE=E)", "currency=USD")/1000000000} -> 23.694772 | BQ15: {=_xll.BQL($C15, "SALES_REV_TURN(FPT=BA, FPR=2027, FYE=C1231, AE=E)", "currency=USD")/1000000000} -> 24.125423 | BR15: {=_xll.BQL($C15, "EBITDA(FPT=BA, FPR=2022, FYE=C1231, AE=A)", "currency=USD")/1000000000} -> 2.8700988 | BS15: {=_xll.BQL($C15, "EBITDA(FPT=BA, FPR=2023, FYE=C1231, AE=A)", "currency=USD")/1000000000} -> 3.5157686 | BT15: {=_xll.BQL($C15, "EBITDA(FPT=BA, FPR=2024, FYE=C1231, AE=A)", "currency=USD")/1000000000} -> 3.633467 | BU15: {=_xll.BQL($C15, "EBITDA(FPT=BA, FPR=2025, FYE=C1231, AE=E)", "currency=USD")/1000000000} -> 4.173431 | BV15: {=_xll.BQL($C15, "EBITDA(FPT=BA, FPR=2026, FYE=C1231, AE=E)", "currency=USD")/1000000000} -> 4.346519 | BW15: {=_xll.BQL($C15, "EBITDA(FPT=BA, FPR=2027, FYE=C1231, AE=E)", "currency=USD")/1000000000} -> 4.500808 | BX15: {=_xll.BQL($C15, "NET_INCOME(FPT=BA, FPR=2022, FYE=C1231, AE=A)", "currency=USD")/1000000000} -> 0.35738188 | BY15: {=_xll.BQL($C15, "NET_INCOME(FPT=BA, FPR=2023, FYE=C1231, AE=A)", "currency=USD")/1000000000} -> 0.84739888 | BZ15: {=_xll.BQL($C15, "NET_INCOME(FPT=BA, FPR=2024, FYE=C1231, AE=A)", "currency=USD")/1000000000} -> 1.0725106 | CA15: {=_xll.BQL($C15, "NET_INCOME(FPT=BA, FPR=2025, FYE=C1231, AE=E)", "currency=USD")/1000000000} -> 1.19362 | CB15: {=_xll.BQL($C15, "NET_INCOME(FPT=BA, FPR=2026, FYE=C1231, AE=E)", "currency=USD")/1000000000} -> 1.440204 | CC15: {=_xll.BQL($C15, "NET_INCOME(FPT=BA, FPR=2027, FYE=C1231, AE=E)", "currency=USD")/1000000000} -> 1.5787607 | CD15: {=-_xll.BQL($C15, "CF_DVD_PAID(FPT=BA, FPR=2024, FYE=C1231, AE=A)", "currency=USD")/1000000000} -> 0.98093319 | CE15: {=-_xll.BQL($C15, "CF_DVD_PAID(FPT=BA, FPR=2025, FYE=C1231, AE=E)", "currency=USD")/1000000000} -> 1.5864488 | CF15: {=-_xll.BQL($C15, "CF_DVD_PAID(FPT=BA, FPR=2026, FYE=C1231, AE=E)", "currency=USD")/1000000000} -> 1.3871056 | CG15: {=-_xll.BQL($C15, "CF_DVD_PAID(FPT=BA, FPR=2027, FYE=C1231, AE=E)", "currency=USD")/1000000000} -> 1.3481862 | CH15: =CD15/$F15 -> 3.5298758e-05 | CI15: =CE15/$F15 -> 5.7088161e-05 | CJ15: =CF15/$F15 -> 4.9914822e-05 | CK15: =CG15/$F15 -> 4.8514311e-05 | CL15: {=_xll.BDP($C15,"INTERVAL_AVG", "MARKET_DATA_OVERRIDE=turnover", "CALC_INTERVAL=5D","CRNCY=HKD")/1000000} -> 309.90782 | CM15: {=_xll.BDP($C15,"INTERVAL_AVG", "MARKET_DATA_OVERRIDE=turnover", "CALC_INTERVAL=10D","CRNCY=HKD")/1000000} -> 351.31867 | CN15: {=_xll.BDP($C15,"INTERVAL_AVG", "MARKET_DATA_OVERRIDE=turnover", "CALC_INTERVAL=20D","CRNCY=HKD")/1000000} -> 295.32087 | CO15: {=_xll.BDP($C15,"INTERVAL_AVG", "MARKET_DATA_OVERRIDE=turnover", "CALC_INTERVAL=1m","CRNCY=HKD")/1000000} -> 291.76019 | CP15: {=_xll.BDP($C15,"INTERVAL_AVG", "MARKET_DATA_OVERRIDE=turnover", "CALC_INTERVAL=3M","CRNCY=HKD")/1000000} -> 304.36469 | CQ15: {=_xll.BDP($C15,"INTERVAL_AVG", "MARKET_DATA_OVERRIDE=turnover", "CALC_INTERVAL=6M","CRNCY=HKD")/1000000} -> 315.80159 | CR15: =_xll.BDP($C15,"chg pct 1m")/100 -> -0.08323961 | CS15: =_xll.BDP($C15,"chg pct 3m")/100 -> -0.1090462 | CT15: =_xll.BDP($C15,"chg pct 6m")/100 -> -0.04900813 | CU15: =_xll.BDP($C15,"chg pct 1yr")/100 -> 0.1470795 | CV15: =_xll.BDP($C15,"chg pct ytd")/100 -> -0.1231845 | CW15: {=_xll.BQL($C15, "volatility(calc_interval=range(-1M, 0D))")} -> 0.30626581 | CX15: {=_xll.BQL($C15, "volatility(calc_interval=range(-3M, 0D))")} -> 0.28051779 | CY15: {=_xll.BQL($C15, "volatility(calc_interval=range(-6M, 0D))")} -> 0.24983431 | CZ15: =_xll.BDP($C15,CZ$1) -> H & M Hennes & Mauritz AB designs and retails fashions for women, men, teens, and children. The Company sells a variety trendy, sporty, and classic garments in addition to accessories such as jewelery, bags, scarves, and cosmetics. H & M Hennes & Mauritz serves customers worldwide.
B17: HK | C17: 13.732419 | E17: {=_xll.BDP("HSI Index", "PE_RATIO")} -> 13.424774 | L17: Max | M17: Max | N17: =MAX(N7:N11) -> #VALUE! | O17: =MAX(O7:O11) -> 0.17345972 | P17: =MAX(P7:P11) -> 0.052674855 | Q17: =MAX(Q7:Q11) -> 0.083469248 | R17: =MAX(#REF!) -> #REF! | S17: =MAX(#REF!) -> #REF! | T17: =MAX(#REF!) -> #REF! | U17: =MAX(#REF!) -> #REF! | V17: =MAX(#REF!) -> #REF! | W17: =MAX(#REF!) -> #REF! | X17: =MAX(#REF!) -> #REF! | Y17: =MAX(#REF!) -> #REF! | Z17: =MAX(#REF!) -> #REF! | AD17: =MAX(AD7:AD11) -> 57.053171 | AE17: =MAX(AE7:AE9) -> 46.576104 | AF17: =MAX(AF7:AF9) -> 40.85241 | AG17: =MAX(AG7:AG9) -> 1.5070893 | AH17: =MAX(AH7:AH9) -> 1.433405 | AI17: =MAX(AI7:AI9) -> 1.3671795 | AJ17: =MAX(AJ7:AJ9) -> 24.489648 | AK17: =MAX(AK7:AK9) -> 21.698405 | AL17: =MAX(AL7:AL9) -> 19.712839 | ... AV17: =MAX(AV7:AV9) -> 3.2356771 | CL17: =MAX(CL7:CL9) -> 19123.993 | CM17: =MAX(CM7:CM9) -> 17589.413 | CN17: =MAX(CN7:CN9) -> 16368.912 | CO17: =MAX(CO7:CO9) -> 16610.733 | CP17: =MAX(CP7:CP9) -> 18447.682 | CQ17: =MAX(CQ7:CQ9) -> 23745.789 | CR17: =MAX(CR7:CR9) -> 0.0490932 | CS17: =MAX(CS7:CS9) -> 0.09114564 | ... CY17: =MAX(CY7:CY9) -> 0.5440254
B18: NY | C18: 20.580119 | E18: {=_xll.BDP("NYA Index", "PE_RATIO")} -> 20.316364 | L18: Median | M18: Median | N18: =MEDIAN(N7:N11) -> #VALUE! | O18: =MEDIAN(O7:O11) -> 0.06575916 | P18: =MEDIAN(P7:P11) -> 0.030698452 | Q18: =MEDIAN(Q7:Q11) -> 0.047252142 | R18: =MEDIAN(#REF!) -> #REF! | S18: =MEDIAN(#REF!) -> #REF! | T18: =MEDIAN(#REF!) -> #REF! | U18: =MEDIAN(#REF!) -> #REF! | V18: =MEDIAN(#REF!) -> #REF! | W18: =MEDIAN(#REF!) -> #REF! | X18: =MEDIAN(#REF!) -> #REF! | Y18: =MEDIAN(#REF!) -> #REF! | Z18: =MEDIAN(#REF!) -> #REF! | AD18: =MEDIAN(AD7:AD9) -> 34.063097 | AE18: =MEDIAN(AE7:AE9) -> 34.159526 | AF18: =MEDIAN(AF7:AF9) -> 27.694363 | AG18: =MEDIAN(AG7:AG9) -> 0.46605903 | AH18: =MEDIAN(AH7:AH9) -> 0.44585488 | AI18: =MEDIAN(AI7:AI9) -> 0.43027257 | AJ18: =MEDIAN(AJ7:AJ9) -> 10.671302 | AK18: =MEDIAN(AK7:AK9) -> 15.015243 | ... AV18: =MEDIAN(AV7:AV9) -> 1.9833378 | CL18: =MEDIAN(CL7:CL9) -> 554.67983 | CM18: =MEDIAN(CM7:CM9) -> 543.59402 | CN18: =MEDIAN(CN7:CN9) -> 540.68725 | CO18: =MEDIAN(CO7:CO9) -> 563.99768 | CP18: =MEDIAN(CP7:CP9) -> 780.81676 | CQ18: =MEDIAN(CQ7:CQ9) -> 1081.9367 | CR18: =MEDIAN(CR7:CR9) -> -0.000340231 | CS18: =MEDIAN(CS7:CS9) -> -0.03876982 | ... CY18: =MEDIAN(CY7:CY9) -> 0.43323304
B19: LN | C19: 16.720078 | E19: {=_xll.BDP("UKX Index", "PE_RATIO")} -> 16.688296 | L19: Mean | M19: Mean | N19: =AVERAGE(N7:N11) -> #VALUE! | O19: =AVERAGE(O7:O11) -> 0.089645857 | P19: =AVERAGE(P7:P11) -> 0.031185473 | Q19: =AVERAGE(Q7:Q11) -> 0.045243842 | R19: =AVERAGE(#REF!) -> #REF! | S19: =AVERAGE(#REF!) -> #REF! | T19: =AVERAGE(#REF!) -> #REF! | U19: =AVERAGE(#REF!) -> #REF! | V19: =AVERAGE(#REF!) -> #REF! | W19: =AVERAGE(#REF!) -> #REF! | X19: =AVERAGE(#REF!) -> #REF! | Y19: =AVERAGE(#REF!) -> #REF! | Z19: =AVERAGE(#REF!) -> #REF! | AD19: =AVERAGE(AD7:AD9) -> 32.207644 | AE19: =AVERAGE(AE7:AE9) -> 29.854207 | AF19: =AVERAGE(AF7:AF9) -> 25.443381 | AG19: =AVERAGE(AG7:AG9) -> 0.75444994 | AH19: =AVERAGE(AH7:AH9) -> 0.72544067 | AI19: =AVERAGE(AI7:AI9) -> 0.69225096 | AJ19: =AVERAGE(AJ7:AJ9) -> 13.287985 | AK19: =AVERAGE(AK7:AK9) -> 15.015243 | ... AV19: =AVERAGE(AV7:AV9) -> 1.9833378 | CL19: =AVERAGE(CL7:CL9) -> 6561.9725 | CM19: =AVERAGE(CM7:CM9) -> 6045.7565 | CN19: =AVERAGE(CN7:CN9) -> 5637.6814 | CO19: =AVERAGE(CO7:CO9) -> 5726.0162 | CP19: =AVERAGE(CP7:CP9) -> 6412.859 | CQ19: =AVERAGE(CQ7:CQ9) -> 8278.4224 | CR19: =AVERAGE(CR7:CR9) -> -0.059537077 | CS19: =AVERAGE(CS7:CS9) -> -0.11318273 | ... CY19: =AVERAGE(CY7:CY9) -> 0.40518518
B20: INDIA | C20: 21.956182 | E20: {=_xll.BDP("NIFTY Index", "PE_RATIO")} -> 21.825203 | L20: Min | M20: Min | N20: =MIN(N7:N11) -> #VALUE! | O20: =MIN(O7:O11) -> 0.029377399 | P20: =MIN(P7:P11) -> 0.0085195274 | Q20: =MIN(Q7:Q11) -> -0.027195921 | R20: =MIN(#REF!) -> #REF! | S20: =MIN(#REF!) -> #REF! | T20: =MIN(#REF!) -> #REF! | U20: =MIN(#REF!) -> #REF! | V20: =MIN(#REF!) -> #REF! | W20: =MIN(#REF!) -> #REF! | X20: =MIN(#REF!) -> #REF! | Y20: =MIN(#REF!) -> #REF! | Z20: =MIN(#REF!) -> #REF! | AD20: =MIN(AD7:AD9) -> 13.466502 | AE20: =MIN(AE7:AE9) -> 8.8269914 | AF20: =MIN(AF7:AF9) -> 7.7833708 | AG20: =MIN(AG7:AG9) -> 0.29020149 | AH20: =MIN(AH7:AH9) -> 0.29706215 | AI20: =MIN(AI7:AI9) -> 0.27930084 | AJ20: =MIN(AJ7:AJ9) -> 4.7030059 | AK20: =MIN(AK7:AK9) -> 8.3320805 | ... AV20: =MIN(AV7:AV9) -> 0.73099851 | CL20: =MIN(CL7:CL9) -> 7.2448675 | CM20: =MIN(CM7:CM9) -> 4.2623237 | CN20: =MIN(CN7:CN9) -> 3.4449756 | CO20: =MIN(CO7:CO9) -> 3.3175718 | CP20: =MIN(CP7:CP9) -> 10.078578 | CQ20: =MIN(CQ7:CQ9) -> 7.5417473 | CR20: =MIN(CR7:CR9) -> -0.2273642 | CS20: =MIN(CS7:CS9) -> -0.391924 | ... CY20: =MIN(CY7:CY9) -> 0.2382971
B21: STOCKHOLM | C21: 14.84786 | E21: {=_xll.BDP("OMX Index", "PE_RATIO")} -> 14.913889
B22: NASDAQ | C22: 40.245419 | E22: {=_xll.BDP("ndx Index", "PE_RATIO")} -> 39.209416

Sheet Sheet 2
C2: PE (TTM) Original | D2: PE (TTM) (Normalised to HK) | E2: PE (2025A) Original | F2: PE (2025A) (Normalised to HK) | G2: PE (2026F) Original | H2: PE (2026F) (Normalised to HK)
B3: PDS Ltd | C3: 32.92029 | D3: =C3*Sheet1!$C$17/Sheet1!C20 -> 20.589884
B4: 沃尔玛股份有限公司 | C4: 48.448142 | D4: =C4*Sheet1!$C$17/Sheet1!C22 -> 16.531327
B5: 美鹰傲飞AEO有限公司 | C5: 13.613112 | D5: =C5*Sheet1!$C$17/Sheet1!C18 -> 9.0835706
B6: 开市客公司 | C6: 54.276627 | D6: =C6*Sheet1!$C$17/Sheet1!C22 -> 18.520105
B7: 英国联合食品公共有限公司 | C7: 13.398425 | D7: =C7*Sheet1!$C$17/Sheet1!C19 -> 11.004302
B8: CVS健康公司 | C8: 42.430638 | D8: =C8*Sheet1!$C$17/Sheet1!C18 -> 28.312534
B9: 海恩斯莫里斯公司 | C9: 20.756869 | D9: =C9*Sheet1!$C$17/Sheet1!C21 -> 19.197516
B10: Manhattan Associates (MANH.nasdaq) | C10: 40
B11: CH Robinson (CHRW.nasdaq) | C11: 34.7
B13: median | C13: =MEDIAN(C3:C11) -> 34.7 | D13: =MEDIAN(D3:D11) -> 18.520105 | E13: =MEDIAN(E3:E11) -> #NUM! | F13: =MEDIAN(F3:F11) -> #NUM! | G13: =MEDIAN(G3:G11) -> #NUM! | H13: =MEDIAN(H3:H11) -> #NUM!
B14: average | C14: =AVERAGE(C3:C11) -> 33.393789 | D14: =MEDIAN(D4:D12) -> 17.525716 | E14: =MEDIAN(E4:E12) -> #NUM! | F14: =MEDIAN(F4:F12) -> #NUM! | G14: =MEDIAN(G4:G12) -> #NUM! | H14: =MEDIAN(H4:H12) -> #NUM!

Sheet Sheet3
A1: (2)
A3: If after expanding search scope of Comp using "AI-enabled B2B supply chain service providers" on 15 May 2026,
A7: (a) software centric e.g. Oracle/SAP --> suggest we add Manhattan Associates, P/E TTM close to 40) :
A25: (b) logistic centric e.g. UPS / Fedex --> suggest you add CWRW.nasdaq, P/E TTM close to 35 :

Sheet Sheet2
A1: Currency | B1: HKD | C1: USD | E1: CRNCY_ADJ_MKT_CAP | F1: Crncy Adj Mkt Cap | G1: Px Last | H1: Net Assets | I1: Net Assets | J1: Sales Rev Turn | K1: Sales Rev Turn | L1: Net Income | M1: Net Income | N1: Gross_Margin_Adjusted | O1: EBITDA_MARGIN_ADJUSTED | P1: Prof Margin | Q1: Sales_Growth | R1: Net Inc Growth | S1: TOT_DEBT_TO_TOT_EQY | T1: TOT_DEBT_TO_COM_EQY | U1: NET_DEBT_TO_SHRHLDR_EQTY | V1: TOT_DEBT_TO_TOT_ASSET | W1: RETURN_ON_ASSET | Z1: RETURN_COM_EQY | AD1: Pe Ratio | AJ1: BEST_EV_TO_BEST_EBITDA | AM1: Px To Book Ratio | AT1: EQY_DVD_YLD_IND | AU1: BEST_DIV_YLD | CZ1: CIE_DES
A3: Company Name | B3: 公司名 | C3: Stock Code | E3: Operating Data | AD3: Valuation | AW3: Forecast CAGR | AZ3: Key financials (USD'b) | CW3: Volatility
D4: Listing date | E4: Market Capitalization (HKD 'm) | F4: Market Capitalization (USD 'm) | G4: Price (Traded Currency) | H4: Net Assets (HKD 'm) | I4: Net Assets (USD 'm) | J4: Revenue (HKD 'm) | K4: Revenue (USD 'm) | L4: Net Profit (HKD 'm) | M4: Net Profit (USD 'm) | N4: GP Margin (%) | O4: EBITDA Margin (%) | P4: NP Margin (%) | Q4: Revenue Growth (%) | R4: NP Growth (%) | S4: Debt to equity | T4: Debt to common equity | U4: Net debt To Shareholders Equity | V4: Total Debt to Total Assets | W4: ROA | X4: EV (HKD'm) | Y4: EV (USD'm) | Z4: ROE | AA4: TTM Sales Profit (HKD 'm) | AB4: TTM Net Profit (HKD 'm) | AC4: TTM EBITDA (HKD 'm) | AD4: PE Ratio (x) | AG4: PS Ratio (x) | AJ4: EV/EBITDA (x) | AM4: PB Ratio (x) | AQ4: ROE (%) | AT4: Dividend Yield (x) | AW4: Revenue | AX4: EBITDA | AY4: Net profit | AZ4: cash flow from operations (USD'b) | BF4: Free cash flow (USD'b) | BL4: Revenue | BR4: EBITDA | BX4: Net profit | CD4: Dividend | CH4: Dividend yield | CL4: 5D Avg ADTV (HKD'm) | CM4: 10D Avg ADTV (HKD'm) | CN4: 20D Avg ADTV (HKD'm) | CO4: 1M Avg ADTV (HKD'm) | CP4: 3M Avg ADTV (HKD'm) | CQ4: 6M Avg ADTV (HKD'm) | CR4: 1M Return | CS4: 3M Return | CT4: 6M Return | CU4: 1Y Return | CV4: YTD Return | CW4: 30-day volatility (%) | CX4: 90-day volatility (%) | CY4: 180-day volatility (%)
AD5: TTM | AE5: 2026F | AF5: 2027F | AG5: TTM | AH5: 2026F | AI5: 2027F | AJ5: TTM | AK5: 2026F | AL5: 2027F | AM5: TTM | AN5: 2026F | AO5: 2027F | AP5: 2027F | AQ5: TTM | AR5: 2026F | AS5: 2027F | AT5: TTM | AU5: 2026F | AV5: 2027F | AW5: 2026 vs 2024 | AZ5: CY2022A | BA5: CY2023A | BB5: CY2024A | BC5: CY2025F | BD5: CY2026F | BE5: CY2027F | BF5: CY2022A | BG5: CY2023A | BH5: CY2024A | BI5: CY2025F | BJ5: CY2026F | BK5: CY2027F | BL5: CY2022A | BM5: CY2023A | BN5: CY2024A | BO5: CY2025F | BP5: CY2026F | BQ5: CY2027F | BR5: CY2022A | BS5: CY2023A | BT5: CY2024A | BU5: CY2025F | BV5: CY2026F | BW5: CY2027F | BX5: CY2022A | BY5: CY2023A | BZ5: CY2024A | CA5: CY2025F | CB5: CY2026F | CC5: CY2027F | CD5: CY2024A | CE5: CY2025F | CF5: CY2026F | CG5: CY2027F | CH5: CY2024A | CI5: CY2025F | CJ5: CY2026F | CK5: CY2027F
A7: PDS Ltd | B7: PDS Ltd | C7: pdsl in Equity | D7: 10/21/2014 | E7: 3363.6485 | F7: 429.36539 | G7: 293.8 | H7: 1544.2295 | I7: 196.94544 | J7: 11590.735 | K7: 1484.796 | L7: 98.747584 | M7: 12.64976 | N7: #VALUE! | O7: 0.029377399 | P7: 0.0085195274 | Q7: 0.083469248 | R7: -0.28810317 | S7: 0.6799445 | T7: 0.7167187 | U7: 0.12262357 | V7: 0.24004735 | W7: 0.022891973 | X7: 3632.2403 | Y7: 463.62063 | Z7: 0.065611822 | AA7: 11590.735 | AB7: 98.747584 | AC7: 340.37462 | AD7: 34.063097 | AE7: 34.159526 | AF7: 27.694363 | AG7: 0.29020149 | AH7: 0.29706215 | AI7: 0.27930084 | AJ7: 10.671302 | AK7: #N/A | AL7: #N/A | AM7: 2.3563056 | AN7: 2.2737624 | AO7: 2.1338398 | AP7: 2.2325228 | AQ7: 0.065611822 | AR7: 0.0555 | AS7: 0.0699 | AT7: 1.1232131 | AU7: #N/A N/A | AV7: #N/A N/A | AW7: -0.004529693 | AX7: #VALUE! | AY7: -0.1925306 | AZ7: 0.054043298 | BA7: 0.021999611 | BB7: -0.0098155305 | BC7: #VALUE! | BD7: #VALUE! | BE7: #VALUE! | BF7: 0.049792862 | BG7: 0.0062953556 | BH7: -0.022833284 | BI7: #VALUE! | BJ7: #VALUE! | BK7: #VALUE! | BL7: 1.3512945 | BM7: 1.1990861 | BN7: 1.4662796 | BO7: 1.3931129 | BP7: 1.453026 | BQ7: 1.5454269 | BR7: 0.054375123 | BS7: 0.049776924 | BT7: 0.052570466 | BU7: #VALUE! | BV7: #VALUE! | BW7: #VALUE! | BX7: 0.036362788 | BY7: 0.018778827 | BZ7: 0.019408024 | CA7: 0.011725291 | CB7: 0.012654164 | CC7: 0.015608947 | CD7: 0.0074249516 | CE7: #VALUE! | CF7: #VALUE! | CG7: #VALUE! | CH7: 1.7292851e-05 | CI7: #VALUE! | CJ7: #VALUE! | CK7: #VALUE! | CL7: 7.2448675 | CM7: 4.2623237 | CN7: 3.4449756 | CO7: 3.3175718 | CP7: 10.078578 | CQ7: 7.5417473 | CR7: -0.000340231 | CS7: -0.03876982 | CT7: -0.2788414 | CU7: -0.2847231 | CV7: -0.2132816 | CW7: 0.36384718 | CX7: 0.43541756 | CY7: 0.43323304 | CZ7: PDS Limited is a consumer-driven manufacturing and sourcing company. The Company designs, produces, and markets blazers, school wear, shirts, softs, and footwear products, as well as invests in sustainability, technology, and direct to consumer digital brands. PDS serves brand agencies and retailers worldwide.
A8: Walmart Inc | B8: 沃尔玛股份有限公司 | C8: wmt us Equity | D8: #N/A Field Not Applicable | E8: 8380084.2 | F8: 1069706.9 | G8: 134.2 | H8: 829276.42 | I8: 106180 | J8: 5560443 | K8: 713163 | L8: 170696.99 | M8: 21893 | N8: 0.249267 | O8: 0.06575916 | P8: 0.030698452 | Q8: 0.047252142 | R8: 0.1264149 | S8: 0.63189866 | T8: 0.67352962 | U8: 0.5308721 | V8: 0.23569562 | W8: 0.080268969 | X8: 8871581.5 | Y8: 1132637.9 | Z8: 0.22969102 | AA8: 5560443 | AB8: 170696.99 | AC8: 362258.42 | AD8: 49.093332 | AE8: 46.576104 | AF8: 40.85241 | AG8: 1.5070893 | AH8: 1.433405 | AI8: 1.3671795 | AJ8: 24.489648 | AK8: 21.698405 | AL8: 19.712839 | AM8: 10.735515 | AN8: 9.7242299 | AO8: 8.8181213 | AP8: 9.7232285 | AQ8: 0.22969102 | AR8: 0.21592 | AS8: 0.21427 | AT8: 0.73770493 | AU8: 0.695231 | AV8: 0.73099851 | AW8: 0.048698146 | AX8: 0.077160566 | AY8: 0.079747432 | AZ8: 27.070967 | BA8: 34.523402 | BB8: 37.51688 | BC8: 39.156214 | BD8: 40.128463 | BE8: 43.735809 | BF8: 10.307641 | BG8: 14.300185 | BH8: 14.123065 | BI8: 16.499711 | BJ8: 14.119226 | BK8: 18.194063 | BL8: 607.52284 | BM8: 644.97783 | BN8: 678.57037 | BO8: 706.70368 | BP8: 746.26984 | BQ8: 782.41879 | BR8: 31.447467 | BS8: 38.191424 | BT8: 42.030543 | BU8: 44.809955 | BV8: 48.766984 | BW8: 53.679012 | BX8: 10.765837 | BY8: 15.774163 | BZ8: 19.51687 | CA8: 20.761634 | CB8: 22.753831 | CC8: 25.800935 | CD8: 6.6374565 | CE8: 7.398584 | CF8: 7.6709596 | CG8: 8.139111 | CH8: 6.2049299e-06 | CI8: 6.9164589e-06 | CJ8: 7.1710853e-06 | CK8: 7.6087299e-06 | CL8: 19123.993 | CM8: 17589.413 | CN8: 16368.912 | CO8: 16610.733 | CP8: 18447.682 | CQ8: 23745.789 | CR8: 0.0490932 | CS8: 0.09114564 | CT8: 0.2529176 | CU8: 0.3721881 | CV8: 0.2045597 | CW8: 0.2058647 | CX8: 0.22858561 | CY8: 0.2382971 | CZ8: Walmart Inc. operates discount stores, supercenters, and neighborhood markets. The Company offers merchandise such as apparel, house wares, small appliances, electronics, musical instruments, books, home improvement, shoes, jewelry, toddler, games, household essentials, pets, pharmaceutical products, party supplies, and automotive tools. Walmart serves customers worldwide.
A9: American Eagle Outfitters Inc | B9: 美鹰傲飞AEO有限公司 | C9: aeo us Equity | D9: #N/A Field Not Applicable | E9: 20157.569 | F9: 2573.0877 | G9: 15.36 | H9: 13210.269 | I9: 1691.434 | J9: 43251.108 | K9: 5547.236 | L9: 1496.8675 | M9: 191.983 | N9: 0.36510453 | O9: 0.17345972 | P9: 0.034608767 | Q9: 0.041020506 | R9: -0.41713826 | S9: 1.0052553 | T9: 1.0042347 | U9: 0.86400061 | V9: 0.42405454 | W9: 0.048972413 | X9: 31557.824 | Y9: 4032.7687 | Z9: 0.11097242 | AA9: 43251.108 | AB9: 1496.8675 | AC9: 6710.1391 | AD9: 13.466502 | AE9: 8.8269914 | AF9: 7.7833708 | AG9: 0.46605903 | AH9: 0.44585488 | AI9: 0.43027257 | AJ9: 4.7030059 | AK9: 8.3320805 | AL9: 7.6098393 | AM9: 1.5327586 | AN9: 1.2597358 | AO9: 1.1445369 | AP9: 1.2687923 | AQ9: 0.11097242 | AR9: 0.13893 | AS9: 0.17072 | AT9: 3.2552083 | AU9: 3.2747396 | AV9: 3.2356771 | AW9: 0.038917207 | AX9: 0.02443777 | AY9: 0.015840872 | AZ9: 0.30877057 | BA9: 0.62958049 | BB9: 0.44467309 | BC9: 0.88413334 | BD9: 0.60041393 | BE9: 0.60689928 | BF9: 0.038662615 | BG9: 0.45008166 | BH9: 0.23123481 | BI9: 0.49798702 | BJ9: 0.35781943 | BK9: 0.32122047 | BL9: 5.0100486 | BM9: 5.1396258 | BN9: 5.3468644 | BO9: 5.3619101 | BP9: 5.7711326 | BQ9: 5.980134 | BR9: 0.4586707 | BS9: 0.47541237 | BT9: 0.6021329 | BU9: 0.458687 | BV9: 0.63192207 | BW9: 0.69189707 | BX9: 0.12441023 | BY9: 0.18464497 | BZ9: 0.29487917 | CA9: 0.20500813 | CB9: 0.30429545 | CC9: 0.35161115 | CD9: 0.09664705 | CE9: 0.090614801 | CF9: 0.088729529 | CG9: 0.093559922 | CH9: 3.7560729e-05 | CI9: 3.5216367e-05 | CJ9: 3.4483679e-05 | CK9: 3.6360953e-05 | CL9: 554.67983 | CM9: 543.59402 | CN9: 540.68725 | CO9: 563.99768 | CP9: 780.81676 | CQ9: 1081.9367 | CR9: -0.2273642 | CS9: -0.391924 | CT9: -0.1242874 | CU9: 0.3391456 | CV9: -0.4175199 | CW9: 0.37298253 | CX9: 0.53793434 | CY9: 0.5440254 | CZ9: American Eagle Outfitters, Inc. retails men's and women's casual apparel, footwear, outerwear, and accessories. The Company provides products include jeans, khakis, t-shirts, and other similar apparel. American Eagle serves customers in the United States.
A10: Costco Wholesale Corp | B10: 开市客公司 | C10: cost us Equity | D10: 12/5/1985 | E10: 3803390.2 | F10: 485497.85 | G10: 1094.32 | H10: 227315.88 | I10: 29164 | J10: 2145593.8 | K10: 275235 | L10: 63135.736 | M10: 8099 | N10: 0.12843207 | O10: 0.047097934 | P10: 0.029425763 | Q10: 0.081673236 | R10: 0.09936202 | S10: 0.29262104 | T10: 0.29262104 | U10: -0.23144973 | V10: 0.11068885 | W10: 0.10899957 | X10: 3724627.8 | Y10: 475422.85 | Z10: 0.29651082 | AA10: 2232256.2 | AB10: 66663.958 | AC10: 104959.28 | AD10: 57.053171 | AE10: 51.687613 | AF10: 46.888178 | AG10: 1.7038323 | AH10: 1.5700454 | AI10: 1.4522641 | AJ10: 35.486408 | AK10: 27.964893 | AL10: 25.553506 | AM10: 15.132016 | AN10: 12.562627 | AO10: 10.905653 | AP10: 11.56212 | AQ10: 0.29651082 | AR10: 0.28724 | AS10: 0.26459 | AT10: 0.53711385 | AU10: 0.49382265 | AV10: 0.5353096 | AW10: 0.085310885 | AX10: 0.10881618 | AY10: 0.11049497 | AZ10: 8.1110476 | BA10: 11.855583 | BB10: 10.853845 | BC10: 12.776401 | BD10: 14.729238 | BE10: 15.302553 | BF10: 4.1279286 | BG10: 7.5544048 | BH10: 5.8486071 | BI10: 6.8187958 | BJ10: 7.5226847 | BK10: 8.8964661 | BL10: 233.28688 | BM10: 243.02776 | BN10: 262.52263 | BO10: 282.94784 | BP10: 309.22533 | BQ10: 334.30408 | BR10: 9.8537738 | BS10: 10.393083 | BT10: 11.970952 | BU10: 13.17599 | BV10: 14.717967 | BW10: 16.106845 | BX10: 5.9809762 | BY10: 6.5277024 | BZ10: 7.6373214 | CA10: 8.3099475 | CB10: 9.4183377 | CC10: 10.381945 | CD10: 5.68975 | CE10: 2.3518354 | CF10: 4.3629676 | CG10: 3.0642975 | CH10: 1.1719413e-05 | CI10: 4.8441727e-06 | CJ10: 8.9865848e-06 | CK10: 6.3116603e-06 | CL10: 18203.075 | CM10: 16602.223 | CN10: 15043.904 | CO10: 14440.37 | CP10: 14496.744 | CQ10: 16842.298 | CR10: 0.09668882 | CS10: 0.1106803 | CT10: 0.2250445 | CU10: 0.05545809 | CV10: 0.2690122 | CW10: 0.18496035 | CX10: 0.18377653 | CY10: 0.1952656 | CZ10: Costco Wholesale Corporation is a membership warehouse club The Company sells all kinds of food, automotive supplies, toys, hardware, sporting goods, jewelry, electronics, apparel, health, and beauty aids, as well as other goods. Costco Wholesale serves customers worldwide.
A11: Associated British Foods PLC | B11: 英国联合食品公共有限公司 | C11: abf ln EQUITY | D11: #N/A Field Not Applicable | E11: 135311.2 | F11: 17272.3 | G11: 1833 | H11: 118036.02 | I11: 15168.216 | J11: 198050.84 | K11: 25404.338 | L11: 10432.299 | M11: 1338.1698 | N11: 0.23922093 | O11: 0.13253507 | P11: 0.052674855 | Q11: -0.027195921 | R11: -0.29553265 | S11: 0.32951904 | T11: 0.33330319 | U11: 0.23502593 | V11: 0.19107356 | W11: 0.049596701 | X11: 168838.28 | Y11: 21558.665 | Z11: 0.084613672 | AA11: 202525.2 | AB11: 9907.2577 | AC11: 24622.143 | AD11: 13.657785 | AE11: 11.27466 | AF11: 10.646149 | AG11: 0.66812028 | AH11: 0.68200855 | AI11: 0.644861 | AJ11: 6.8571725 | AK11: 7.290167 | AL11: 6.9691059 | AM11: 1.1298633 | AN11: 1.1192199 | AO11: 1.0494899 | AP11: 1.0751994 | AQ11: 0.084613672 | AR11: 0.09814 | AS11: 0.10043 | AT11: 3.4369885 | AU11: 3.2460447 | AV11: 3.3715221 | AW11: 0.0023239674 | AX11: 0.0087649321 | AY11: -0.10748368 | AZ11: 1.1691067 | BA11: 2.9357923 | BB11: 3.3824466 | BC11: 2.3953424 | BD11: 1.9686017 | BE11: 2.0516051 | BF11: 0.21227288 | BG11: 1.621035 | BH11: 1.9691316 | BI11: 0.91571912 | BJ11: 0.94270928 | BK11: 0.92799304 | BL11: 21.937978 | BM11: 24.950845 | BN11: 25.454993 | BO11: 26.137291 | BP11: 25.573444 | BQ11: 27.046615 | BR11: 2.3553044 | BS11: 2.9400949 | BT11: 3.3878779 | BU11: 3.5387547 | BV11: 3.4475273 | BW11: 3.6063521 | BX11: 0.890859 | BY11: 1.4193107 | BZ11: 1.7471448 | CA11: 1.5377899 | CB11: 1.39175 | CC11: 1.4961078 | CD11: 0.77610423 | CE11: 0.49583445 | CF11: 0.55177703 | CG11: 0.47900223 | CH11: 4.4933463e-05 | CI11: 2.8706916e-05 | CJ11: 3.1945777e-05 | CK11: 2.7732395e-05 | CL11: 129.2982 | CM11: 135.86173 | CN11: 149.59612 | CO11: 163.17554 | CP11: 160.5872 | CQ11: 154.51915 | CR11: -0.02758621 | CS11: -0.06168416 | CT11: -0.126727 | CU11: -0.1390324 | CV11: -0.1382228 | CW11: 0.21825153 | CX11: 0.21275675 | CY11: 0.2706094 | CZ11: Associated British Foods PLC operates as a group company. The Company, through its subsidiaries, offers groceries, clothing, and household products, as well as produces sugar and baker's yeast ingredients including emulsifiers, enzymes, and lactose. Associated British Foods serves customers worldwide.
A12: Manhattan Associates Inc | B12: 曼哈顿联合软件公司 | C12: MANH US EQUITY | D12: 4/23/1998 | E12: 62764.157 | F12: 8012.0704 | G12: 135.42 | H12: 2450.0993 | I12: 314.765 | J12: 8430.351 | K12: 1081.392 | L12: 1714.6778 | M12: 219.948 | N12: 0.56321205 | O12: 0.26997703 | P12: 0.2033934 | Q12: 0.037453758 | R12: 0.007253943 | S12: 0.19399552 | T12: 0.19399552 | U12: -0.85042492 | V12: 0.072747049 | W12: 0.29909875 | X12: 61427.69 | Y12: 7841.6224 | Z12: 0.96236036 | AA12: 8590.7453 | AB12: 1690.8118 | AC12: 2248.8958 | AD12: 37.120723 | AE12: 25.272783 | AF12: 22.705603 | AG12: 7.30602 | AH12: 6.9463799 | AI12: 6.3989913 | AJ12: 27.314601 | AK12: 22.767815 | AL12: 20.555926 | AM12: 39.049862 | AN12: 28.509473 | AO12: 12.603071 | AP12: 26.244186 | AQ12: 0.96236036 | AR12: 1.05773 | AS12: 1.47583 | AT12: #N/A N/A | AU12: 0 | AV12: 0 | AW12: 0.051927743 | AX12: 0.21950629 | AY12: 0.0073823964 | AZ12: 0.17963 | BA12: 0.246218 | BB12: 0.295003 | BC12: 0.33073013 | BD12: 0.38220333 | BE12: 0.41356057 | BF12: 0.173043 | BG12: 0.241488 | BH12: 0.286328 | BI12: 0.3199796 | BJ12: 0.37471904 | BK12: 0.41477038 | BL12: 0.767084 | BM12: 0.928725 | BN12: 1.042352 | BO12: 1.0758333 | BP12: 1.1534167 | BQ12: 1.2520833 | BR12: 0.166663 | BS12: 0.223433 | BT12: 0.276897 | BU12: 0.391 | BV12: 0.4118 | BW12: 0.45611111 | BX12: 0.128959 | BY12: 0.176568 | BZ12: 0.218364 | CA12: 0.2144 | CB12: 0.2216 | CC12: 0.2537 | CD12: 0 | CE12: #VALUE! | CF12: #VALUE! | CG12: #VALUE! | CH12: 0 | CI12: #VALUE! | CJ12: #VALUE! | CK12: #VALUE! | CL12: 570.01422 | CM12: 599.99188 | CN12: 758.0417 | CO12: 801.78106 | CP12: 751.70417 | CQ12: 834.43368 | CR12: 0.01188073 | CS12: -0.06134334 | CT12: -0.1971305 | CU12: -0.2941361 | CV12: -0.2186256 | CW12: 0.51654275 | CX12: 0.49307174 | CY12: 0.43677486 | CZ12: Manhattan Associates, Inc. provides information technology solutions for distribution centers. The solutions are designed to enable the efficient movement of goods through the supply chain. The Company offers solutions optimize the receipt, storage, and distribution of inventory, as well as manage equipment and personnel within a distribution center.
A13: CH Robinson Worldwide Inc | B13: 罗宾逊全球物流有限公司 | C13: CHRW US EQUITY | D13: 10/15/1997 | E13: 159732.89 | F13: 20390.478 | G13: 173.02 | H13: 14366.332 | I13: 1845.647 | J13: 126547.9 | K13: 16232.763 | L13: 4576.7852 | M13: 587.081 | N13: 0.083735098 | O13: 0.063262366 | P13: 0.036166425 | Q13: -0.084185992 | R13: 0.26066911 | S13: 0.75604165 | T13: 0.75604165 | U13: 0.66887926 | V13: 0.27585625 | W13: 0.11451706 | X13: 171375.22 | Y13: 21875.299 | Z13: 0.34837966 | AA13: 126415.87 | AB13: 4674.6603 | AC13: 7712.5745 | AD13: 34.169947 | AE13: 28.120531 | AF13: 23.718266 | AG13: 1.263551 | AH13: 1.2081685 | AI13: 1.1362245 | AJ13: 22.220236 | AK13: 21.826218 | AL13: 18.813097 | AM13: 11.996522 | AN13: 11.525447 | AO13: 10.786783 | AP13: 11.037959 | AQ13: 0.34837966 | AR13: 0.39701 | AS13: 0.4616 | AT13: 1.4563948 | AU13: 1.4524332 | AV13: 1.4784418 | AW13: -0.024207711 | AX13: 0.097445037 | AY13: 0.253025 | AZ13: 1.650171 | BA13: 0.731946 | BB13: 0.509084 | BC13: 0.83654123 | BD13: 0.81848958 | BE13: 0.97863258 | BF13: 1.588256 | BG13: 0.701957 | BH13: 0.486431 | BI13: 0.74980139 | BJ13: 0.74545011 | BK13: 0.88281303 | BL13: 24.696625 | BM13: 17.596443 | BN13: 17.724956 | BO13: 16.298708 | BP13: 16.877182 | BQ13: 17.945818 | BR13: 1.45159 | BS13: 0.714227 | BT13: 0.875135 | BU13: 0.91273913 | BV13: 1.054 | BW13: 1.2228095 | BX13: 0.940524 | BY13: 0.325129 | BZ13: 0.46569 | CA13: 0.5959 | CB13: 0.73116667 | CC13: 0.88388889 | CD13: 0.294772 | CE13: 0.30527602 | CF13: 0.30768054 | CG13: 0.32098167 | CH13: 1.4456355e-05 | CI13: 1.4971498e-05 | CJ13: 1.5089422e-05 | CK13: 1.5741743e-05 | CL13: 3712.5822 | CM13: 2629.6555 | CN13: 2914.868 | CO13: 2854.8895 | CP13: 2562.9612 | CQ13: 2752.925 | CR13: -0.0594183 | CS13: -0.08965589 | CT13: 0.1645688 | CU13: 0.7289897 | CV13: 0.07626279 | CW13: 0.44536685 | CX13: 0.42336611 | CY13: 0.41262464 | CZ13: C.H. Robinson Worldwide, Inc. operates as a logistics company. The Company freight, supply chain, and logistics services. C.H. Robinson Worldwide serves clients worldwide.
A14: CVS Health Corp | B14: CVS健康公司 | C14: cvs us EQUITY | D14: 10/1/1952 | E14: 941386.99 | F14: 120166.83 | G14: 94.18 | H14: 586765.95 | I14: 75382 | J14: 3134447 | K14: 402067 | L14: 13783.032 | M14: 1768 | N14: 0.13769347 | O14: 0.048268075 | P14: 0.0043972771 | Q14: 0.078479865 | R14: -0.61681838 | S14: 1.060598 | T14: 1.062967 | U14: 0.92000743 | V14: 0.31533735 | W14: 0.011530619 | X14: 1464563.2 | Y14: 186890.83 | Z14: 0.037982965 | AA14: 3183270.6 | AB14: 22881.184 | AC14: 82199.015 | AD14: 41.142407 | AE14: 12.755116 | AF14: 11.256229 | AG14: 0.29572949 | AH14: 0.2950372 | AI14: 0.28275297 | AJ14: 17.817284 | AK14: 9.0639446 | AL14: 8.7266069 | AM14: 1.5478612 | AN14: 1.5070609 | AO14: 1.4279433 | AP14: 1.3983875 | AQ14: 0.037982965 | AR14: 0.1066 | AS14: 0.11405 | AT14: 2.8243789 | AU14: 2.8073901 | AV14: 2.9868337 | AW14: 0.045227266 | AX14: 0.087519531 | AY14: 0.30704781 | AZ14: 16.177 | BA14: 13.426 | BB14: 9.107 | BC14: 6.8931973 | BD14: 9.5035319 | BE14: 12.567884 | BF14: 13.45 | BG14: 10.395 | BH14: 6.326 | BI14: 5.5684131 | BJ14: 7.2600573 | BK14: 10.751112 | BL14: 322.467 | BM14: 357.776 | BN14: 372.809 | BO14: 400.12448 | BP14: 407.29385 | BQ14: 424.98876 | BR14: 14.696 | BS14: 20.578 | BT14: 15.469 | BU14: 17.375389 | BV14: 18.295167 | BW14: 19.002389 | BX14: 4.311 | BY14: 8.344 | BZ14: 4.614 | CA14: -0.34181818 | CB14: 7.8824375 | CC14: 9.1240625 | CD14: 3.373 | CE14: 3.348705 | CF14: 3.4198385 | CG14: 3.5900269 | CH14: 2.8069309e-05 | CI14: 2.7867132e-05 | CJ14: 2.8459088e-05 | CK14: 2.9875356e-05 | CL14: 7181.2996 | CM14: 7847.3575 | CN14: 6391.7576 | CO14: 6069.4642 | CP14: 5187.3017 | CQ14: 5116.5103 | CR14: 0.229825 | CS14: 0.228061 | CT14: 0.2385586 | CU14: 0.4775651 | CV14: 0.1867439 | CW14: 0.40133415 | CX14: 0.35036859 | CY14: 0.36396735 | CZ14: CVS Health Corporation provides health care and retail pharmacy services. The Company offers prescription medications, beauty, personal care, cosmetics, and health care products, as well as pharmacy benefit management (PBM), disease management, and administrative services. CVS Health operates in the United States and Puerto Rico.
A15: H & M Hennes & Mauritz AB | B15: 海恩斯莫里斯公司 | C15: hmb ss EQUITY | D15: #N/A Field Not Applicable | E15: 217702.58 | F15: 27789.454 | G15: 163 | H15: 35412.183 | I15: 4548.3622 | J15: 179395.13 | K15: 23011.543 | L15: 9554.224 | M15: 1225.5485 | N15: 0.53395098 | O15: 0.17376963 | P15: 0.053257989 | Q15: -0.02641186 | R15: 0.046209448 | S15: 1.8056442 | T15: 1.806738 | U15: 1.3188116 | V15: 0.45542746 | W15: #VALUE! | X15: 268039.39 | Y15: 34224.905 | Z15: #VALUE! | AA15: 182918.59 | AB15: 10102.648 | AC15: 31672.279 | AD15: 21.549061 | AE15: 19.094264 | AF15: 18.103523 | AG15: 1.1901611 | AH15: 1.1749797 | AI15: 1.1540057 | AJ15: 8.4629021 | AK15: 8.3000656 | AL15: 8.0155369 | AM15: 6.2869523 | AN15: 5.932914 | AO15: 5.6001816 | AP15: 5.5768441 | AQ15: #VALUE! | AR15: 0.30293 | AS15: 0.32374 | AT15: 4.3585021 | AU15: 4.502454 | AV15: 4.7865031 | AW15: 0.036145043 | AX15: 0.093730152 | AY15: 0.15880726 | AZ15: 2.4241186 | BA15: 3.1688053 | BB15: 2.9881701 | BC15: 4.686497 | BD15: 3.9173809 | BE15: 3.9331037 | BF15: 1.9597794 | BG15: 2.4125135 | BH15: 2.0299634 | BI15: 3.9477056 | BJ15: 2.8950644 | BK15: 2.8533001 | BL15: 21.915431 | BM15: 22.21339 | BN15: 22.070462 | BO15: 24.319544 | BP15: 23.694772 | BQ15: 24.125423 | BR15: 2.8700988 | BS15: 3.5157686 | BT15: 3.633467 | BU15: 4.173431 | BV15: 4.346519 | BW15: 4.500808 | BX15: 0.35738188 | BY15: 0.84739888 | BZ15: 1.0725106 | CA15: 1.19362 | CB15: 1.440204 | CC15: 1.5787607 | CD15: 0.98093319 | CE15: 1.5864488 | CF15: 1.3871056 | CG15: 1.3481862 | CH15: 3.5298758e-05 | CI15: 5.7088161e-05 | CJ15: 4.9914822e-05 | CK15: 4.8514311e-05 | CL15: 309.90782 | CM15: 351.31867 | CN15: 295.32087 | CO15: 291.76019 | CP15: 304.36469 | CQ15: 315.80159 | CR15: -0.08323961 | CS15: -0.1090462 | CT15: -0.04900813 | CU15: 0.1470795 | CV15: -0.1231845 | CW15: 0.30626581 | CX15: 0.28051779 | CY15: 0.24983431 | CZ15: H & M Hennes & Mauritz AB designs and retails fashions for women, men, teens, and children. The Company sells a variety trendy, sporty, and classic garments in addition to accessories such as jewelery, bags, scarves, and cosmetics. H & M Hennes & Mauritz serves customers worldwide.
B17: HK | C17: 13.732419 | E17: 13.424774 | L17: Max | M17: Max | N17: #VALUE! | O17: 0.17345972 | P17: 0.052674855 | Q17: 0.083469248 | R17: #REF! | S17: #REF! | T17: #REF! | U17: #REF! | V17: #REF! | W17: #REF! | X17: #REF! | Y17: #REF! | Z17: #REF! | AD17: 57.053171 | AE17: 46.576104 | AF17: 40.85241 | AG17: 1.5070893 | AH17: 1.433405 | AI17: 1.3671795 | AJ17: 24.489648 | AK17: 21.698405 | AL17: 19.712839 | AM17: 10.735515 | AN17: 9.7242299 | AO17: 8.8181213 | AP17: 9.7232285 | AQ17: 0.22969102 | AR17: 0.21592 | AS17: 0.21427 | AT17: 3.2552083 | AU17: 3.2747396 | AV17: 3.2356771 | CL17: 19123.993 | CM17: 17589.413 | CN17: 16368.912 | CO17: 16610.733 | CP17: 18447.682 | CQ17: 23745.789 | CR17: 0.0490932 | CS17: 0.09114564 | CT17: 0.2529176 | CU17: 0.3721881 | CV17: 0.2045597 | CW17: 0.37298253 | CX17: 0.53793434 | CY17: 0.5440254
B18: NY | C18: 20.580119 | E18: 20.316364 | L18: Median | M18: Median | N18: #VALUE! | O18: 0.06575916 | P18: 0.030698452 | Q18: 0.047252142 | R18: #REF! | S18: #REF! | T18: #REF! | U18: #REF! | V18: #REF! | W18: #REF! | X18: #REF! | Y18: #REF! | Z18: #REF! | AD18: 34.063097 | AE18: 34.159526 | AF18: 27.694363 | AG18: 0.46605903 | AH18: 0.44585488 | AI18: 0.43027257 | AJ18: 10.671302 | AK18: 15.015243 | AL18: 13.661339 | AM18: 2.3563056 | AN18: 2.2737624 | AO18: 2.1338398 | AP18: 2.2325228 | AQ18: 0.11097242 | AR18: 0.13893 | AS18: 0.17072 | AT18: 1.1232131 | AU18: 1.9849853 | AV18: 1.9833378 | CL18: 554.67983 | CM18: 543.59402 | CN18: 540.68725 | CO18: 563.99768 | CP18: 780.81676 | CQ18: 1081.9367 | CR18: -0.000340231 | CS18: -0.03876982 | CT18: -0.1242874 | CU18: 0.3391456 | CV18: -0.2132816 | CW18: 0.36384718 | CX18: 0.43541756 | CY18: 0.43323304
B19: LN | C19: 16.720078 | E19: 16.688296 | L19: Mean | M19: Mean | N19: #VALUE! | O19: 0.089645857 | P19: 0.031185473 | Q19: 0.045243842 | R19: #REF! | S19: #REF! | T19: #REF! | U19: #REF! | V19: #REF! | W19: #REF! | X19: #REF! | Y19: #REF! | Z19: #REF! | AD19: 32.207644 | AE19: 29.854207 | AF19: 25.443381 | AG19: 0.75444994 | AH19: 0.72544067 | AI19: 0.69225096 | AJ19: 13.287985 | AK19: 15.015243 | AL19: 13.661339 | AM19: 4.8748597 | AN19: 4.4192427 | AO19: 4.032166 | AP19: 4.4081812 | AQ19: 0.13542509 | AR19: 0.13678333 | AS19: 0.15163 | AT19: 1.7053754 | AU19: 1.9849853 | AV19: 1.9833378 | CL19: 6561.9725 | CM19: 6045.7565 | CN19: 5637.6814 | CO19: 5726.0162 | CP19: 6412.859 | CQ19: 8278.4224 | CR19: -0.059537077 | CS19: -0.11318273 | CT19: -0.0500704 | CU19: 0.14220353 | CV19: -0.1420806 | CW19: 0.31423147 | CX19: 0.40064584 | CY19: 0.40518518
B20: INDIA | C20: 21.956182 | E20: 21.825203 | L20: Min | M20: Min | N20: #VALUE! | O20: 0.029377399 | P20: 0.0085195274 | Q20: -0.027195921 | R20: #REF! | S20: #REF! | T20: #REF! | U20: #REF! | V20: #REF! | W20: #REF! | X20: #REF! | Y20: #REF! | Z20: #REF! | AD20: 13.466502 | AE20: 8.8269914 | AF20: 7.7833708 | AG20: 0.29020149 | AH20: 0.29706215 | AI20: 0.27930084 | AJ20: 4.7030059 | AK20: 8.3320805 | AL20: 7.6098393 | AM20: 1.5327586 | AN20: 1.2597358 | AO20: 1.1445369 | AP20: 1.2687923 | AQ20: 0.065611822 | AR20: 0.0555 | AS20: 0.0699 | AT20: 0.73770493 | AU20: 0.695231 | AV20: 0.73099851 | CL20: 7.2448675 | CM20: 4.2623237 | CN20: 3.4449756 | CO20: 3.3175718 | CP20: 10.078578 | CQ20: 7.5417473 | CR20: -0.2273642 | CS20: -0.391924 | CT20: -0.2788414 | CU20: -0.2847231 | CV20: -0.4175199 | CW20: 0.2058647 | CX20: 0.22858561 | CY20: 0.2382971
B21: STOCKHOLM | C21: 14.84786 | E21: 14.913889
B22: NASDAQ | C22: 40.245419 | E22: 39.209416
