Workbook

Sheet Assumptions
A1: LI & FUNG LIMITED — KEY ASSUMPTIONS
A2: (USD in thousands)
A4: INCOME STATEMENT DRIVERS
B5: FY2023A | C5: FY2024A | D5: FY2025A | E5: FY2026E | F5: FY2027E | G5: FY2028E | H5: FY2029E | I5: FY2030E
A6: Revenue Growth % | B6: N/A | C6: 0.073795705 | D6: -0.081958209 | E6: 0.04 | F6: 0.05 | G6: 0.045 | H6: 0.04 | I6: 0.035
A7: COGS % of Revenue | B7: 0.93215431 | C7: 0.93290562 | D7: 0.92958577 | E7: 0.929 | F7: 0.927 | G7: 0.925 | H7: 0.923 | I7: 0.922
A8: S&M % of Revenue | B8: 0.012918419 | C8: 0.007945104 | D8: 0.011120315 | E8: 0.011 | F8: 0.011 | G8: 0.01 | H8: 0.01 | I8: 0.01
A9: Personnel % of Revenue | B9: 0.033552863 | C9: 0.032586959 | D9: 0.032036845 | E9: 0.032 | F9: 0.031 | G9: 0.03 | H9: 0.03 | I9: 0.029
A10: Other OpEx % of Revenue | B10: 0.006425404 | C10: 0.009038244 | D10: 0.006807078 | E10: 0.007 | F10: 0.007 | G10: 0.006 | H10: 0.006 | I10: 0.006
A11: Depreciation % of Revenue | B11: 0.003608588 | C11: 0.003236788 | D11: 0.003719442 | E11: 0.004 | F11: 0.004 | G11: 0.004 | H11: 0.004 | I11: 0.004
A12: Amortization % of Revenue | B12: 0.002274144 | C12: 0.001675592 | D12: 0.002299985 | E12: 0.002 | F12: 0.002 | G12: 0.002 | H12: 0.002 | I12: 0.002
A13: Interest Expense | B13: 39764 | C13: 33282 | D13: 38587 | E13: 35000 | F13: 33000 | G13: 31000 | H13: 30000 | I13: 29000
A14: Interest Income | B14: 8242 | C14: 15403 | D14: 13836 | E14: 12000 | F14: 11000 | G14: 10000 | H14: 10000 | I14: 10000
A15: Other Income (Expense), net | B15: 60185 | C15: 27271 | D15: 22257 | E15: 15000 | F15: 12000 | G15: 10000 | H15: 10000 | I15: 10000
A16: Effective Tax Rate | B16: 0.344 | C16: 0.242 | D16: 0.173 | E16: 0.2 | F16: 0.2 | G16: 0.2 | H16: 0.2 | I16: 0.2
A17: Minority Interest | B17: -37 | C17: 180 | D17: 32562 | E17: 1000 | F17: 1000 | G17: 1000 | H17: 1000 | I17: 1000
A19: BALANCE SHEET & WORKING CAPITAL DRIVERS
A20: Days Sales Outstanding (DSO) | B20: 39.9 | C20: 39.4 | D20: 32.9 | E20: 35 | F20: 35 | G20: 34 | H20: 34 | I20: 33
A21: Days Inventory Outstanding (DIO) | B21: 6.3 | C21: 5.8 | D21: 7.9 | E21: 7 | F21: 7 | G21: 7 | H21: 7 | I21: 7
A22: Days Payable Outstanding (DPO) | B22: 55.1 | C22: 51.5 | D22: 48.4 | E22: 48 | F22: 48 | G22: 47 | H22: 47 | I22: 47
A24: CapEx (Maintenance) | B24: 5000 | C24: 5000 | D24: 5000 | E24: 5000 | F24: 5000 | G24: 5000 | H24: 5000 | I24: 5000
A25: Dividends | B25: 0 | C25: 0 | D25: 35017 | E25: 20000 | F25: 25000 | G25: 30000 | H25: 30000 | I25: 35000
A26: Net Debt Issuance / (Repayment) | B26: 0 | C26: 145208 | D26: -133178 | E26: 0 | F26: 0 | G26: -50000 | H26: -50000 | I26: -50000
A27: Other Non-Current Assets (net chg) | B27: 0 | C27: 0 | D27: 0 | E27: 0 | F27: 0 | G27: 0 | H27: 0 | I27: 0

Sheet DCF
A1: LI & FUNG LIMITED — DCF VALUATION MODEL
A2: Currency: USD (thousands) | FYE: 31 December | Date: April 2026
A4: Case Selector (1=Bear, 2=Base, 3=Bull) | B4: 2
A5: Selected Case: | B5: =IF(B4=1,"Bear",IF(B4=2,"Base","Bull")) -> Base
A7: MARKET DATA & KEY INPUTS
A8: 2020 Privatization Equity Value (US$ '000) | B8: 1370000
A9: Total Shares Outstanding ('000) | B9: 8540000
A10: Privatization Price per Share (HK$) | B10: 1.25
A11: FY2025 Net Debt (Cash) (US$ '000) | B11: -135626
A12: FY2025 Total Debt (US$ '000) | B12: 325000
A13: FY2025 Cash & Equivalents (US$ '000) | B13: 460626
A14: S&P Credit Rating | B14: BB
A15: Equity Risk Premium | B15: 0.055
A16: Risk-Free Rate (10Y UST) | B16: 0.0432
A17: Unlevered Beta | B17: 0.9
A18: HKD / USD FX Rate | B18: 7.8
A19: DCF SCENARIO ASSUMPTIONS
A20: BEAR CASE ASSUMPTIONS
A21: Assumption | B21: FY2026E | C21: FY2027E | D21: FY2028E | E21: FY2029E | F21: FY2030E
A22: Revenue Growth (%) | B22: 0.02 | C22: 0.02 | D22: 0.015 | E22: 0.015 | F22: 0.01
A23: EBIT Margin (%) | B23: 0.015 | C23: 0.016 | D23: 0.017 | E23: 0.018 | F23: 0.018
A24: D&A % of Revenue | B24: 0.006 | C24: 0.006 | D24: 0.006 | E24: 0.006 | F24: 0.006
A25: CapEx % of Revenue | B25: =B24 -> 0.006 | C25: =C24 -> 0.006 | D25: =D24 -> 0.006 | E25: =E24 -> 0.006 | F25: =F24 -> 0.006
A26: NWC Change % of ΔRev (+= cash use) | B26: 0.015 | C26: 0.015 | D26: 0.015 | E26: 0.015 | F26: 0.015
A27: Tax Rate (%) | B27: 0.2 | C27: 0.2 | D27: 0.2 | E27: 0.2 | F27: 0.2
A28: Terminal Growth Rate | B28: 0.015
A29: WACC | B29: =WACC!B32 -> 0.097633794
A31: BASE CASE ASSUMPTIONS
A32: Assumption | B32: FY2026E | C32: FY2027E | D32: FY2028E | E32: FY2029E | F32: FY2030E
A33: Revenue Growth (%) | B33: 0.03 | C33: 0.04 | D33: 0.035 | E33: 0.03 | F33: 0.025
A34: EBIT Margin (%) | B34: 0.018 | C34: 0.02 | D34: 0.022 | E34: 0.024 | F34: 0.025
A35: D&A % of Revenue | B35: 0.006 | C35: 0.006 | D35: 0.006 | E35: 0.006 | F35: 0.006
A36: CapEx % of Revenue | B36: =B35*1.2 -> 0.0072 | C36: =C35*1.2 -> 0.0072 | D36: =D35*1.2 -> 0.0072 | E36: =E35*1.2 -> 0.0072 | F36: =F35*1.2 -> 0.0072
A37: NWC Change % of ΔRev (+= cash use) | B37: 0.01 | C37: 0.01 | D37: 0.01 | E37: 0.01 | F37: 0.01
A38: Tax Rate (%) | B38: 0.2 | C38: 0.2 | D38: 0.2 | E38: 0.2 | F38: 0.2
A39: Terminal Growth Rate | B39: 0.02
A40: WACC (from WACC sheet) | B40: =WACC!B32 -> 0.097633794
A42: BULL CASE ASSUMPTIONS
A43: Assumption | B43: FY2026E | C43: FY2027E | D43: FY2028E | E43: FY2029E | F43: FY2030E | G43: FY2031E
A44: Revenue Growth (%) | B44: 0.05 | C44: 0.06 | D44: 0.055 | E44: 0.045 | F44: 0.035
A45: EBIT Margin (%) | B45: 0.02 | C45: 0.023 | D45: 0.026 | E45: 0.028 | F45: 0.03
A46: D&A % of Revenue | B46: 0.006 | C46: 0.006 | D46: 0.006 | E46: 0.006 | F46: 0.006
A47: CapEx % of Revenue | B47: =B46*1.5 -> 0.009 | C47: =C46*1.5 -> 0.009 | D47: =D46*1.5 -> 0.009 | E47: =E46*1.5 -> 0.009 | F47: =F46*1.5 -> 0.009
A48: NWC Change % of ΔRev (+= cash use) | B48: 0.005 | C48: 0.005 | D48: 0.005 | E48: 0.005 | F48: 0.005
A49: Tax Rate (%) | B49: 0.2 | C49: 0.2 | D49: 0.2 | E49: 0.2 | F49: 0.2
A50: Terminal Growth Rate | B50: 0.0225
A51: WACC (from WACC sheet) | B51: =WACC!B32 -> 0.097633794
A53: SELECTED CASE ASSUMPTIONS
A54: Assumption | B54: FY2026E | C54: FY2027E | D54: FY2028E | E54: FY2029E | F54: FY2030E
A55: Revenue Growth (%) | B55: =CHOOSE($B$4,B22,B33,B44) -> 0.03 | C55: =CHOOSE($B$4,C22,C33,C44) -> 0.04 | D55: =CHOOSE($B$4,D22,D33,D44) -> 0.035 | E55: =CHOOSE($B$4,E22,E33,E44) -> 0.03 | F55: =CHOOSE($B$4,F22,F33,F44) -> 0.025
A56: EBIT Margin (%) | B56: =CHOOSE($B$4,B23,B34,B45) -> 0.018 | C56: =CHOOSE($B$4,C23,C34,C45) -> 0.02 | D56: =CHOOSE($B$4,D23,D34,D45) -> 0.022 | E56: =CHOOSE($B$4,E23,E34,E45) -> 0.024 | F56: =CHOOSE($B$4,F23,F34,F45) -> 0.025
A57: D&A % of Revenue | B57: =CHOOSE($B$4,B24,B35,B46) -> 0.006 | C57: =CHOOSE($B$4,C24,C35,C46) -> 0.006 | D57: =CHOOSE($B$4,D24,D35,D46) -> 0.006 | E57: =CHOOSE($B$4,E24,E35,E46) -> 0.006 | F57: =CHOOSE($B$4,F24,F35,F46) -> 0.006
A58: CapEx % of Revenue | B58: =CHOOSE($B$4,B25,B36,B47) -> 0.0072 | C58: =CHOOSE($B$4,C25,C36,C47) -> 0.0072 | D58: =CHOOSE($B$4,D25,D36,D47) -> 0.0072 | E58: =CHOOSE($B$4,E25,E36,E47) -> 0.0072 | F58: =CHOOSE($B$4,F25,F36,F47) -> 0.0072
A59: NWC Change % of ΔRev (+= cash use) | B59: =CHOOSE($B$4,B26,B37,B48) -> 0.01 | C59: =CHOOSE($B$4,C26,C37,C48) -> 0.01 | D59: =CHOOSE($B$4,D26,D37,D48) -> 0.01 | E59: =CHOOSE($B$4,E26,E37,E48) -> 0.01 | F59: =CHOOSE($B$4,F26,F37,F48) -> 0.01
A60: Tax Rate (%) | B60: =CHOOSE($B$4,B27,B38,B49) -> 0.2 | C60: =CHOOSE($B$4,C27,C38,C49) -> 0.2 | D60: =CHOOSE($B$4,D27,D38,D49) -> 0.2 | E60: =CHOOSE($B$4,E27,E38,E49) -> 0.2 | F60: =CHOOSE($B$4,F27,F38,F49) -> 0.2
A61: Terminal Growth Rate | B61: =CHOOSE($B$4,B28,B39,B50) -> 0.02
A62: WACC | B62: =CHOOSE($B$4,B29,B40,B51) -> 0.097633794
A64: HISTORICAL & PROJECTED FINANCIALS (US$ '000)
A65: Income Statement | B65: FY2023A | C65: FY2024A | D65: FY2025A | E65: FY2026E | F65: FY2027E | G65: FY2028E | H65: FY2029E | I65: FY2030E
A66: Revenue | B66: 6138135 | C66: 6591103 | D66: 6050908 | E66: =D66*(1+B55) -> 6232435.2 | F66: =E66*(1+C55) -> 6481732.6 | G66: =F66*(1+D55) -> 6708593.3 | H66: =G66*(1+E55) -> 6909851.1 | I66: =H66*(1+F55) -> 7082597.4
A67: % Growth | C67: =C66/B66-1 -> 0.073795705 | D67: =D66/C66-1 -> -0.081958209 | E67: =E66/D66-1 -> 0.03 | F67: =F66/E66-1 -> 0.04 | G67: =G66/F66-1 -> 0.035 | H67: =H66/G66-1 -> 0.03 | I67: =I66/H66-1 -> 0.025
A68: └ Normalized EBIT (see bridge below ⇓) | B68: =B69+15000 -> 70650 | C68: =C69+5000 -> 88125 | D68: =D69+0 -> 87318 | E68: =AVERAGE(B68,C68,D68) -> 82031
A69: EBIT | B69: 55650 | C69: 83125 | D69: 87318 | E69: =E66*B56 -> 112183.83 | F69: =F66*C56 -> 129634.65 | G69: =G66*D56 -> 147589.05 | H69: =H66*E56 -> 165836.43 | I69: =I66*F56 -> 177064.93
A70: EBIT Margin | B70: =B69/B66 -> 0.0090662718 | C70: =C69/C66 -> 0.012611698 | D70: =D69/D66 -> 0.014430561 | E70: =E69/E66 -> 0.018 | F70: =F69/F66 -> 0.02 | G70: =G69/G66 -> 0.022 | H70: =H69/H66 -> 0.024 | I70: =I69/I66 -> 0.025
A72: (-) Taxes on EBIT | B72: =-B69*B60 -> -11130 | C72: =-C69*C60 -> -16625 | D72: =-D69*D60 -> -17463.6 | E72: =-E69*B60 -> -22436.767 | F72: =-F69*C60 -> -25926.931 | G72: =-G69*D60 -> -29517.81 | H72: =-H69*E60 -> -33167.285 | I72: =-I69*F60 -> -35412.987
A73: NOPAT | B73: =B69+B72 -> 44520 | C73: =C69+C72 -> 66500 | D73: =D69+D72 -> 69854.4 | E73: =E69+E72 -> 89747.067 | F73: =F69+F72 -> 103707.72 | G73: =G69+G72 -> 118071.24 | H73: =H69+H72 -> 132669.14 | I73: =I69+I72 -> 141651.95
A75: (+) D&A | B75: 36109 | C75: 32378 | D75: 36423 | E75: =E66*B57 -> 37394.611 | F75: =F66*C57 -> 38890.396 | G75: =G66*D57 -> 40251.56 | H75: =H66*E57 -> 41459.107 | I75: =I66*F57 -> 42495.584
A76: D&A % of Revenue | B76: =B75/B66 -> 0.0058827315 | C76: =C75/C66 -> 0.0049123796 | D76: =D75/D66 -> 0.0060194272 | E76: =E75/E66 -> 0.006 | F76: =F75/F66 -> 0.006 | G76: =G75/G66 -> 0.006 | H76: =H75/H66 -> 0.006 | I76: =I75/I66 -> 0.006
A78: FREE CASH FLOW BUILD (US$ '000)
A79: Cash Flow Item | B79: FY2023A | C79: FY2024A | D79: FY2025A | E79: FY2026E | F79: FY2027E | G79: FY2028E | H79: FY2029E | I79: FY2030E
A80: NOPAT | E80: =E73 -> 89747.067 | F80: =F73 -> 103707.72 | G80: =G73 -> 118071.24 | H80: =H73 -> 132669.14 | I80: =I73 -> 141651.95
A81: (+) D&A | E81: =E75 -> 37394.611 | F81: =F75 -> 38890.396 | G81: =G75 -> 40251.56 | H81: =H75 -> 41459.107 | I81: =I75 -> 42495.584
A82: (-) CapEx | E82: =-E66*B58 -> -44873.534 | F82: =-F66*C58 -> -46668.475 | G82: =-G66*D58 -> -48301.872 | H82: =-H66*E58 -> -49750.928 | I82: =-I66*F58 -> -50994.701
A83: CapEx % of Revenue | E83: =-E82/E66 -> 0.0072 | F83: =-F82/F66 -> 0.0072 | G83: =-G82/G66 -> 0.0072 | H83: =-H82/H66 -> 0.0072 | I83: =-I82/I66 -> 0.0072
A84: (-) Δ NWC — driver-based (DSO/DIO/DPO) | E84: =-(E66-D66)*B59 -> -1815.2724 | F84: =-(F66-E66)*C59 -> -2492.9741 | G84: =-(G66-F66)*D59 -> -2268.6064 | H84: =-(H66-G66)*E59 -> -2012.578 | I84: =-(I66-H66)*F59 -> -1727.4628
A86: Unlevered Free Cash Flow | E86: =E80+E81+E82+E84 -> 80452.873 | F86: =F80+F81+F82+F84 -> 93436.669 | G86: =G80+G81+G82+G84 -> 107752.32 | H86: =H80+H81+H82+H84 -> 122364.74 | I86: =I80+I81+I82+I84 -> 131425.37
A88: Discount Period (mid-year) | E88: 0.5 | F88: 1.5 | G88: 2.5 | H88: 3.5 | I88: 4.5
A89: Discount Factor | E89: =1/(1+$B$62)^E88 -> 0.95448974 | F89: =1/(1+$B$62)^F88 -> 0.86958852 | G89: =1/(1+$B$62)^G88 -> 0.7922392 | H89: =1/(1+$B$62)^H88 -> 0.72177005 | I89: =1/(1+$B$62)^I88 -> 0.65756908
A90: PV of FCF | E90: =E86*E89 -> 76791.442 | F90: =F86*F89 -> 81251.454 | G90: =G86*G89 -> 85365.614 | H90: =H86*H89 -> 88319.206 | I90: =I86*I89 -> 86421.259
A92: TERMINAL VALUE (US$ '000)
A93: Terminal Year FCF (FY2030E) | B93: =I86 -> 131425.37
A94: Terminal FCF × (1 + g) | B94: =B93*(1+B61) -> 134053.88
A95: Terminal Growth Rate (g) | B95: =B61 -> 0.02
A96: WACC | B96: =B62 -> 0.097633794
A97: Terminal Value (Gordon Growth) | B97: =B94/(B96-B95) -> 1726746.4
A98: PV of Terminal Value | B98: =B97/(1+B96)^I88 -> 1135455.1
A100: VALUATION SUMMARY (US$ '000)
A101: Sum of PV of Projected FCFs (FY2026–FY2030) | B101: =SUM(E90:I90) -> 418148.97
A102: PV of Terminal Value (Gordon Growth) | B102: =B98 -> 1135455.1
A103: Enterprise Value | B103: =B101+B102 -> 1553604
A104: (+) Net Cash / (-) Net Debt | B104: =-B11 -> 135626
A105: Equity Value | B105: =B103+B104 -> 1689230
A106: Equity Value per Share — PGM (HK$) | B106: =B105/B9*$B$18 -> 1.5428565
A107: EXIT EV/EBITDA CROSS-CHECK (US$ '000)
A108: FY2030E EBITDA | B108: =I69+I75 -> 219560.52
A109: Exit EV/EBITDA Multiple | B109: 7
A110: Gross Terminal EV (EBITDA × Multiple) | B110: =B108*B109 -> 1536923.6
A111: PV of Exit Multiple TV | B111: =B110/(1+B62)^I88 -> 1010633.5
A112: Cross-Check EV (FCFs + PV Exit TV + Net Cash) | B112: =SUM(E90:H90)+B111+B104 -> 1477987.2
A113: Equity Value per Share — Exit Multiple (HK$) | B113: =B112/B9*$B$18 -> 1.349918
...

Sheet WACC
A1: WACC CALCULATION
A3: COST OF EQUITY (CAPM)
A4: Risk-Free Rate (10Y UST) | B4: =DCF!B16 -> 0.0432
A5: Unlevered Beta | B5: 0.9
A6: Equity Risk Premium (ERP) | B6: =DCF!B15 -> 0.055
A7: Total Debt (US$ '000) | B7: =DCF!B12 -> 325000
A8: Cash & Equivalents (US$ '000) | B8: =DCF!B13 -> 460626
A9: Estimated Equity Value (US$ '000) | B9: =DCF!B8 -> 1370000
A10: Tax Rate | B10: 0.2
A12: Debt-to-Equity Ratio (D/E) | B12: =B7/B9 -> 0.23722628
A13: Levered Beta | B13: =B5*(1+(1-B10)*B12) -> 1.0708029
A15: Cost of Equity (Ke) | B15: =B4+B13*B6 -> 0.10209416
A17: COST OF DEBT
A18: Interest Expense (FY2025, US$ '000) | B18: 38587
A19: Average Total Debt (FY2024-2025, US$ '000) | B19: =(458178+325000)/2 -> 391589
A20: Pre-Tax Cost of Debt (Kd) | B20: =B18/B19 -> 0.09853954
A21: Tax Rate | B21: =B10 -> 0.2
A22: After-Tax Cost of Debt | B22: =B20*(1-B21) -> 0.078831632
A24: WACC CALCULATION
A25: Equity Value (US$ '000) | B25: =B9 -> 1370000
A26: Net Debt (Cash) (US$ '000) | B26: =DCF!B11 -> -135626
A27: Enterprise Value (ref. only) | B27: =B25+B26 -> 1234374
A29: Equity Weight (Equity / EV) | B29: =B25/B31 -> 0.80825959
A30: Debt Weight (Gross Debt / Total Capital) | B30: =B7/B31 -> 0.19174041
A31: Equity + Gross Debt | B31: =B25+B7 -> 1695000
A32: WACC (Calculated) | B32: =B29*B15+B30*B22 -> 0.097633794
A34: Note: WACC (~10.2%) reflects restated beta (0.90) appropriate for
A35: supply chain/logistics comps. DCF uses this computed WACC directly —
A36: no manual overrides. Bear/Base/Bull scenarios vary via assumptions only.

Sheet P&L
B1: Li&Fung
D3: At Privatisation and before | K3: Harry added :
B4: Continuing Business
B5: USD'000 | D5: 2019 | F5: 2024 | H5: 2025 | I5: yoy growth | K5: 2026 | L5: CAGR growth
B7: Turnover | D7: 11413312 | F7: 6591103 | H7: 6050908 | I7: =H7/F7-1 -> -0.081958209 | K7: =+Multiples!C25*1000 -> 6353445 | L7: =(K7/F7)^(1/2)-1 -> -0.018194212
B8: COS | D8: -10221721 | F8: -6148877 | H8: -5624838 | I8: =H8/F8-1 -> -0.085225156
B10: Gross Profit | D10: =D7+D8 -> 1191591 | F10: =F7+F8 -> 442226 | H10: =H7+H8 -> 426070 | I10: =H10/F10-1 -> -0.036533356
B11: GPM % | D11: =D10/D7 -> 0.10440361 | F11: =F10/F7 -> 0.067094385 | H11: =H10/H7 -> 0.070414225
B13: Other income | D13: 27745 | F13: 31706 | H13: 24906 | I13: =H13/F13-1 -> -0.21447045
B15: Total Margin | D15: =SUM(D10:D13) -> 1219336.1 | F15: =SUM(F10:F13) -> 473932.07 | H15: =SUM(H10:H13) -> 450976.07 | I15: =H15/F15-1 -> -0.048437315
B17: Selling & Distribution Exp. | D17: -384973 | F17: -78243 | H17: -76299 | I17: =H17/F17-1 -> -0.024845673
B18: Merchandising & admin Exp. | D18: -606816 | F18: -275583 | H18: -251637 | I18: =H18/F18-1 -> -0.086892152
B20: Core Operating profit | D20: =SUM(D15:D18) -> 227547.1 | F20: =SUM(F15:F18) -> 120106.07 | H20: =SUM(H15:H18) -> 123040.07 | I20: =H20/F20-1 -> 0.024428436 | K20: =+H20*(1+Multiples!C20) -> 129192.07
B22: Gain on remeasurement of contingent consideration payable | D22: 621 | F22: 0 | H22: 0
B23: Amortisation of other intangible assets | D23: -26534 | F23: -10082 | H23: -12955 | I23: =H23/F23-1 -> 0.2849633
B24: Non-recurring reorganisation costs | D24: -46825 | F24: 0 | H24: 0
B25: Other non-core operating exp. | D25: -6491 | F25: -3763 | H25: -533 | I25: =H25/F25-1 -> -0.85835769
B27: Operating Profit | D27: =SUM(D20:D25) -> 148318.1 | F27: =SUM(F20:F25) -> 106261.07 | H27: =SUM(H20:H25) -> 109552.07 | I27: =H27/F27-1 -> 0.030970923
B29: Interest Income | D29: 11531 | F29: 15403 | H29: 13836 | I29: =H29/F29-1 -> -0.10173343
B31: Finance costs
B32: - early settlement of LT notes | D32: -7640 | F32: 0 | H32: 0
B33: - Non-cash interest exp | D33: -15302 | F33: -2413 | H33: -2016 | I33: =H33/F33-1 -> -0.16452549
B34: - cash int exp. | D34: -66844 | F34: -30869 | H34: -36571 | I34: =H34/F34-1 -> 0.18471606
D35: =SUM(D32:D34) -> -89786 | F35: =SUM(F32:F34) -> -33282 | H35: =SUM(H32:H34) -> -38587 | I35: =H35/F35-1 -> 0.15939547
B36: Shaer of net (losses)/ profits of asso | D36: -36 | F36: 12 | H36: 10 | I36: =H36/F36-1 -> -0.16666667
B38: Profit before tax | D38: =D27+D29+D35+D36 -> 70027.104 | F38: =F27+F29+F35+F36 -> 88394.067 | H38: =H27+H29+H35+H36 -> 84811.07 | I38: =H38/F38-1 -> -0.040534357
B40: Taxation | D40: -15756 | F40: -22355 | H40: -14710 | I40: =H40/F40-1 -> -0.34198166
B42: Profit for the year from Continuing Operations | D42: =D38+D40 -> 54271.104 | F42: =F38+F40 -> 66039.067 | H42: =H38+H40 -> 70101.07 | I42: =H42/F42-1 -> 0.061509096
B44: Discontinued Operations
B45: Loss for the year | D45: 0 | F45: 0 | H45: 0
B47: Net Profit/ (Loss) for the year | D47: =D42+D45 -> 54271.104 | F47: =F42+F45 -> 66039.067 | H47: =H42+H45 -> 70101.07 | K47: =Multiples!C16*1000 -> 73500 | L47: =(K47/F47)^(1/2)-1 -> 0.054977518
B48: NPM (%) | D48: =D47/D7 -> 0.0047550706 | F48: =F47/F7 -> 0.010019426 | H48: =H47/H7 -> 0.011585215 | K48: =K47/K7 -> 0.011568527
B50: Profit/(loss) attributable to:
B51: - Shareholders of the Co | D51: 16748 | F51: 37539 | H51: 37539
B52: - Holders of perpetual capital securities | D52: 34125 | F52: 32375 | H52: 32375
B53: - non-controlling interests | D53: 3398 | F53: 187 | H53: 187
D54: =SUM(D51:D53) -> 54271 | F54: =SUM(F51:F53) -> 70101 | H54: =SUM(H51:H53) -> 70101
B59: EBITDA | D59: =D27-D22-D23-D24 -> 221056.1 | F59: =F27-F23 -> 116343.07 | H59: =H27-H23 -> 122507.07
B60: EBIT | D60: =D27 -> 148318.1 | F60: =F27 -> 106261.07 | H60: =H27 -> 109552.07
B62: Adjusted EBITDA (USD m) | F62: 142 | H62: 147 | K62: =+Multiples!C21 -> 154.35 | L62: =(K62/F62)^(1/2)-1 -> 0.042579412
B63: - Core Operating Profit | F63: =F20 -> 120106.07 | H63: =H20 -> 123040.07 | K63: =+K20 -> 129192.07 | L63: =+K63/H63-1 -> 0.05
B64: - Depreciation of PPE | F64: -3487 | H64: -3882 | K64: =+H64 -> -3882
B65: - Amoritzation of Rights-of-use assets | F65: -17847 | H65: -18624 | K65: =H65 -> -18624
B66: - Amortization of software dev. | F66: -962 | H66: -962 | K66: =H66 -> -962
F67: =F63-F64-F65-F66 -> 142402.07 | H67: =H63-H64-H65-H66 -> 146508.07 | K67: =K63-K64-K65-K66 -> 152660.07
B68: Adjusted EBITDA Margin (%) | F68: =+F67/F7 -> 0.021605195 | H68: =+H67/H7 -> 0.024212576 | K68: =+K67/K7 -> 0.024027921 | L68: =K62*1000/K7 -> 0.024293907
B74: Avg Historical P/E Ratio | D74: 11.3
B75: AV/EBITDA Ratio | D75: 7.6
B77: Privatisation Price:
B78: P/E Ratio | D78: 18.5
B79: AV/ Adjusted EBITDA | D79: 8.4

Sheet Comps
D1: TTM PE | E1: 2026F PE | F1: 2027F PE | G1: TTM EV/Sales | H1: 2026F EV/Sales | I1: 2027F EV/Sales | J1: TTM EV/EBITDA | K1: 2026F EV/EBITDA | L1: 2027F EV/EBITDA
A2: OEM
A3: PDSL IN Equity | B3: PDS Limited | C3: A global fashion infrastructure enterprise offering a consumer-driven platform for design-led sourcing, manufacturing, and supply chain solutions | D3: 36.95 | E3: 37.82 | F3: 19.3 | G3: 0.32 | H3: 0.33 | I3: 0.28 | J3: 10.91 | K3: N/A | L3: N/A
A4: 1346 HK Equity | B4: Lever Style Corporation | C4: A B Corp certified apparel supply chain platform providing technical design and flexible manufacturing for premium and activewear brands globally | D4: 7.76 | G4: 0.44 | J4: 4.47
A5: 2232 HK Equity | B5: Crystal International Group Limited | C5: A global leader in apparel manufacturing with a vertically integrated multi-country platform specializing in denim, knits, sportswear, and intimates | D5: 10.26 | E5: 9.07 | F5: 8.07 | G5: 0.74 | H5: 0.68 | I5: 0.62 | J5: 5.63 | K5: 5.02 | L5: 4.55
A6: 105630 KS Equity | B6: Hansae Co., Ltd. | C6: A South Korean-based global fashion company specializing in the original design and equipment manufacturing (ODM/OEM) of garments for iconic international brands | D6: 7.73 | E6: 6.43 | F6: 5.41 | G6: 0.39 | H6: 0.37 | I6: 0.36 | J6: 5.8 | K6: 5.4 | L6: 4.66
A7: 2313 HK Equity | B7: Shenzhou International Group Holdings Limited | C7: The largest vertically integrated knitwear manufacturer in China, providing premium sportswear, casual wear, and lingerie to major global brands | D7: 10.83 | E7: 10.02 | F7: 9.15 | G7: 1.61 | H7: 1.53 | I7: 1.43 | J7: 6.31 | K7: 5.96 | L7: 5.42
C9: Max | D9: =MAX(D$3:D$7) -> 36.95 | E9: =MAX(E$3:E$7) -> 37.82 | F9: =MAX(F$3:F$7) -> 19.3 | G9: =MAX(G$3:G$7) -> 1.61 | H9: =MAX(H$3:H$7) -> 1.53 | I9: =MAX(I$3:I$7) -> 1.43 | J9: =MAX(J$3:J$7) -> 10.91 | K9: =MAX(K$3:K$7) -> 5.96 | L9: =MAX(L$3:L$7) -> 5.42
C10: Avg | D10: =AVERAGE(D$3:D$7) -> 14.706 | E10: =AVERAGE(E$3:E$7) -> 15.835 | F10: =AVERAGE(F$3:F$7) -> 10.4825 | G10: =AVERAGE(G$3:G$7) -> 0.7 | H10: =AVERAGE(H$3:H$7) -> 0.7275 | I10: =AVERAGE(I$3:I$7) -> 0.6725 | J10: =AVERAGE(J$3:J$7) -> 6.624 | K10: =AVERAGE(K$3:K$7) -> 5.46 | L10: =AVERAGE(L$3:L$7) -> 4.8766667
C11: Median | D11: =MEDIAN(D$3:D$7) -> 10.26 | E11: =MEDIAN(E$3:E$7) -> 9.545 | F11: =MEDIAN(F$3:F$7) -> 8.61 | G11: =MEDIAN(G$3:G$7) -> 0.44 | H11: =MEDIAN(H$3:H$7) -> 0.525 | I11: =MEDIAN(I$3:I$7) -> 0.49 | J11: =MEDIAN(J$3:J$7) -> 5.8 | K11: =MEDIAN(K$3:K$7) -> 5.4 | L11: =MEDIAN(L$3:L$7) -> 4.66
C12: Min | D12: =MIN(D$3:D$7) -> 7.73 | E12: =MIN(E$3:E$7) -> 6.43 | F12: =MIN(F$3:F$7) -> 5.41 | G12: =MIN(G$3:G$7) -> 0.32 | H12: =MIN(H$3:H$7) -> 0.33 | I12: =MIN(I$3:I$7) -> 0.28 | J12: =MIN(J$3:J$7) -> 4.47 | K12: =MIN(K$3:K$7) -> 5.02 | L12: =MIN(L$3:L$7) -> 4.55
D14: TTM PE | E14: 2026F PE | F14: 2027F PE | G14: TTM EV/Sales | H14: 2026F EV/Sales | I14: 2027F EV/Sales | J14: TTM EV/EBITDA | K14: 2026F EV/EBITDA | L14: 2027F EV/EBITDA
A15: Logistics
A16: 636 HK Equity | B16: KLN Logistics Group Limited | C16: An Asia-based global 3PL (formerly Kerry Logistics) providing integrated logistics and international freight forwarding as the international arm of S.F. Holding | D16: 8.48 | E16: 8.57 | F16: 8.17 | G16: 0.34 | H16: 0.33 | I16: 0.31 | J16: 4.46 | K16: 4.39 | L16: 4.24
A17: DSV DC Equity | B17: DSV A/S | C17: A Denmark-headquartered transport leader and one of the world's largest freight forwarders, offering global road, air, sea, and contract logistics services | D17: 45.04 | E17: 25.43 | F17: 19 | G17: 1.92 | H17: 1.65 | I17: 1.6 | J17: 16.85 | K17: 14 | L17: 11.86
A18: KNIN SW Equity | B18: Kuehne+Nagel International AG | C18: A Swiss-based global logistics partner and the world's number one sea and air freight forwarder, specializing in innovative, IT-based integrated supply chain solutions | D18: 23.6 | E18: 22.64 | F18: 20.48 | G18: 1 | H18: 0.97 | I18: 0.94 | J18: 11.43 | K18: 11.05 | L18: 10.28
A19: DHL GY Equity | B19: DHL Group | C19: The world’s leading logistics company, operating the global DHL brand for express and supply chain services alongside Deutsche Post, Europe’s largest postal provider | D19: 15.48 | E19: 14.65 | F19: 13.33 | G19: 0.95 | H19: 0.92 | I19: 0.89 | J19: 7.19 | K19: 6.93 | L19: 6.58
A20: GXO US Equity | B20: GXO Logistics, Inc. | C20: The world’s largest pure-play contract logistics provider, delivering tech-enabled warehousing, e-commerce fulfillment, and reverse logistics for blue-chip corporations | D20: 32.12 | E20: 19.11 | F20: 16.4 | G20: 0.87 | H20: 0.82 | I20: 0.78 | J20: 7.09 | K20: 9.11 | L20: 8.34
C22: Max | D22: =MAX(D$16:D$20) -> 45.04 | E22: =MAX(E$16:E$20) -> 25.43 | F22: =MAX(F$16:F$20) -> 20.48 | G22: =MAX(G$16:G$20) -> 1.92 | H22: =MAX(H$16:H$20) -> 1.65 | I22: =MAX(I$16:I$20) -> 1.6 | J22: =MAX(J$16:J$20) -> 16.85 | K22: =MAX(K$16:K$20) -> 14 | L22: =MAX(L$16:L$20) -> 11.86
C23: Avg | D23: =AVERAGE(D$16:D$20) -> 24.944 | E23: =AVERAGE(E$16:E$20) -> 18.08 | F23: =AVERAGE(F$16:F$20) -> 15.476 | G23: =AVERAGE(G$16:G$20) -> 1.016 | H23: =AVERAGE(H$16:H$20) -> 0.938 | I23: =AVERAGE(I$16:I$20) -> 0.904 | J23: =AVERAGE(J$16:J$20) -> 9.404 | K23: =AVERAGE(K$16:K$20) -> 9.096 | L23: =AVERAGE(L$16:L$20) -> 8.26
C24: Median | D24: =MEDIAN(D$16:D$20) -> 23.6 | E24: =MEDIAN(E$16:E$20) -> 19.11 | F24: =MEDIAN(F$16:F$20) -> 16.4 | G24: =MEDIAN(G$16:G$20) -> 0.95 | H24: =MEDIAN(H$16:H$20) -> 0.92 | I24: =MEDIAN(I$16:I$20) -> 0.89 | J24: =MEDIAN(J$16:J$20) -> 7.19 | K24: =MEDIAN(K$16:K$20) -> 9.11 | L24: =MEDIAN(L$16:L$20) -> 8.34
C25: Min | D25: =MIN(D$16:D$20) -> 8.48 | E25: =MIN(E$16:E$20) -> 8.57 | F25: =MIN(F$16:F$20) -> 8.17 | G25: =MIN(G$16:G$20) -> 0.34 | H25: =MIN(H$16:H$20) -> 0.33 | I25: =MIN(I$16:I$20) -> 0.31 | J25: =MIN(J$16:J$20) -> 4.46 | K25: =MIN(K$16:K$20) -> 4.39 | L25: =MIN(L$16:L$20) -> 4.24

Sheet Multiples
B1: Li & Fung Valuation - mkt multiples
C3: OEM | D3: Logistics | E3: PDS Only
B4: Avg 2026 P/E | C4: =AVERAGE([1]Sheet1!$E$5:$E$7) -> 8.5066667 | D4: =AVERAGE([1]Sheet1!$E$16:$E$20) -> 18.08 | E4: =[1]Sheet1!$E$3 -> 37.82
B5: Avg 2027 P/E | C5: =AVERAGE([1]Sheet1!$F$5:$F$7) -> 7.5433333 | D5: =AVERAGE([1]Sheet1!$F$16:$F$20) -> 15.476 | E5: =[1]Sheet1!$F$3 -> 19.3
B7: Avg 2026 EV/EBITDA | C7: =AVERAGE([1]Sheet1!$K$5:$K$7) -> 5.46 | D7: =AVERAGE([1]Sheet1!$K$16:$K$20) -> 9.096
B8: Avg 2027 EV/EBITDA | C8: =AVERAGE([1]Sheet1!$L$5:$L$7) -> 4.8766667 | D8: =AVERAGE([1]Sheet1!$L$16:$L$20) -> 8.26
B10: 2026 EV/ Sales | C10: =AVERAGE(Comps!H3,Comps!H5:H6) -> 0.46 | D10: =AVERAGE(Comps!H16, Comps!H18:H20) -> 0.76 | E10: 0.33
B11: 2027 EV/ Sales | C11: =AVERAGE(Comps!I3,Comps!I5:I6) -> 0.42 | D11: =AVERAGE(Comps!I16,Comps!I18:I20) -> 0.73 | E11: =Comps!I3 -> 0.28
B13: Li & Fung
B14: 2025 Net Profit (USDm) | C14: 70
B15: -assume yoy growth | C15: 0.05
B16: 2026 Net Profit (USDm) | C16: =C14*(1+C15) -> 73.5
B17: 2027 Net Profit (USDm) | C17: =C16*(1+C15) -> 77.175
B19: 2025 Adj. EBITDA (USDm) | C19: 147
B20: -assume yoy growth | C20: =C15 -> 0.05
B21: 2026 Adj. EBITDA (USDm) | C21: =C19*(1+C20) -> 154.35
B22: 2027 Adj. EBITDA (USDm) | C22: =C21*(1+C20) -> 162.0675
B24: 2025 Sales | C24: 6050.9
B25: 2026 Sales | C25: =C24*(1+C15) -> 6353.445
B26: 2027 Sales | C26: =C25*(1+C15) -> 6671.1173
B28: Valuation （USDm)
C29: OEM | D29: Logistics | E29: PDS Only
B30: by 2026 P/E | C30: =C16*C4 -> 625.24 | D30: =C16*D4 -> 1328.88 | E30: =E4*C16 -> 2779.77
B31: by 2027 P/E | C31: =C17*C5 -> 582.15675 | D31: =C17*D5 -> 1194.3603 | E31: =E5*C17 -> 1489.4775
B33: Enterprise Value (USDm)
B34: by 2026 EV/EBITDA | C34: =C21*C7 -> 842.751 | D34: =C21*D7 -> 1403.9676
B35: by 2027 EV/ EBITDA | C35: =C22*C8 -> 790.34918 | D35: =C22*D8 -> 1338.6775
B37: 2025 Net Cash (USDm) | C37: 136
B39: Equity Value (USDm) | C39: =C34+C37 -> 978.751 | D39: =D34+C37 -> 1539.9676
C40: =C35+C37 -> 926.34918 | D40: =D35+C37 -> 1474.6775
B43: by EV/ Sales 2026 | C43: =C25*C10 -> 2922.5847 | D43: =C25*D10 -> 4828.6182 | E43: =C25*E10 -> 2096.6368
B44: by EV/ Sales 2027 | C44: =C11*C26 -> 2801.8692 | D44: =C26*D11 -> 4869.9156 | E44: =C26*E11 -> 1867.9128
B46: Equity Value (USDm) | C46: =C43+$C$37 -> 3058.5847 | D46: =D43+$C$37 -> 4964.6182 | E46: =E43+$C$37 -> 2232.6368
C47: =C44+$C$37 -> 2937.8692 | D47: =D44+$C$37 -> 5005.9156 | E47: =E44+$C$37 -> 2003.9128
